Workbook

Sheet 说明
B2: 参数输入表中：
C3: 标黄项为相对固定模块
C4: 标绿项为对成本类、收入类数据进行分类，成本参数按照：“生产成本/销售费用/管理费用/研发费用”划分；收入参数按照：“营业收入/其他收入/营业外收入”划分
C5: 标橙项为固定的分类原则
C6: 标紫项为在参数表中不需要手动输入、勾选的内容，根据其他输入参数自动计算得出，可不在参数输入界面呈现。
C7: 标红项为引用同样红色sheet中相关数据
C8: 标蓝项为可不展示内容，大部分为中间过程计算表/中间计算过程
C10: 【成本费用表】、【收入税金表】、【利润表】体现的是会计报表相关数据，涉及到的收入及成本数据均为不含增值税金额，不含税金额计算公式为： 【含税金额/（1+增值税税率）】；增值税计算公式为：【不含税金额*增值税税率】或【含税金额/（1+增值税税率）*增值税税率】
C12: 【成本费用表】中各项成本按照：一、营业总成本：（1）生产成本；（2）销售费用；（3）管理费用；（4）研发费用；（5）财务费用；二、营业外支出，进行划分，其中需重点关注长期待摊费用成本项，在成本费用表中以逐年摊销的形式出现。
C14: 【成本费用表】中标蓝的内容为不展示内容，为中间计算表，其中数据均还原成含税金额，用于后续的【现金流量表】引用
C16: 【收入表】中各项收入按照：一、营业收入；二、其他收入；三、营业外收入，营业收入及营业外收入需展示二级目录（具体的收入项）
C18: 【现金流量表】体现的是公司账上实际收到或支付的现金流，因此涉及到的收入及成本数据均为含增值税金额，数据需引用成本费用表中还原后的含税金额或参数输入表中的含税金额。同时，收入数据需关注付款比例及回款期限的应用。原理为当年的部分比例收入的滞后支付，第一年的某项收入现金流为预测现金流*首年支付比例，第二年的某项收入现金流为：当年预测现金流*当年支付比例+上一年预测现金流*（1-上一年支付比例）
C20: 【现金流量表-财务计划】增加IF判定条件，当某年的累计盈余资金<“流动资金（本项目为960万元）”+次年的“生产经营现金支出合计（成本费用表标蓝表第一行）”，给出明显提示（允许用户在参数输入界面填写各年度短期借款当期借款金额及还本金额，再重新生成新的结果）

Sheet 可抵扣进项税
B2: 投资概算 | C2: 序号 | D2: 科目 | E2: 计取基数 | F2: 进项税率 | G2: 进项税
C3: 1 | D3: 设备购置费 | E3: =参数输入表!H69 -> 11947.39 | F3: =参数输入表!H288 -> 0.13 | G3: =E3/(1+F3)*F3 -> 1374.4785
C4: 2 | D4: 建安工程费 | E4: =参数输入表!H70 -> 6235.39 | F4: =参数输入表!H289 -> 0.09 | G4: =E4/(1+F4)*F4 -> 514.84872
C5: 3 | D5: 其他费用 | E5: =参数输入表!H71 -> 3024.1 | F5: =参数输入表!H290 -> 0.06 | G5: =E5/(1+F5)*F5 -> 171.17547
C6: 4 | D6: 预备费 | E6: =参数输入表!H72 -> 442.56 | F6: =参数输入表!H291 -> 0 | G6: =E6/(1+F6)*F6 -> 0
C7: 5 | D7: 储能投资 | E7: =参数输入表!H73 -> 920.92 | F7: =参数输入表!H292 -> 0.13 | G7: =E7/(1+F7)*F7 -> 105.94655
C8: 6 | D8: 送出线路投资 | E8: =参数输入表!H74 -> 1832 | F8: =参数输入表!H293 -> 0.09 | G8: =E8/(1+F8)*F8 -> 151.26606
C9: 7 | D9: 配套支持资金 | E9: =参数输入表!H75 -> 0 | F9: =参数输入表!H294 -> 0 | G9: =E9/(1+F9)*F9 -> 0
C10: 8 | D10: 静态总投资 | E10: =参数输入表!H76 -> 24402.36
C11: 9 | D11: 建设期利息 | E11: =参数输入表!H78 -> 350.1335
C12: 10 | D12: 动态总投资 | E12: =参数输入表!H79 -> 24752.494
C13: 11 | D13: 流动资金 | E13: =参数输入表!H81 -> 150
C14: 12 | D14: 可抵扣进项税 | E14: =SUM(G3:G9) -> 2317.7153
C18: 可抵扣进项税为后台计算，不需要作为成果展示

Sheet 参数输入表
G1: 【风储】财务评价计算模型边界条件输入参数表
B3: 类别 | C3: 序号 | D3: 参数 | E3: 操作类型 | F3: 收入/成本归类 | G3: 参数释义/计算公式 | H3: 数值 | I3: 单位 | J3: 取值说明 | K3: 备注
B4: 基础信息 | C4: 1 | D4: 建设期 | E4: 手动输入 | H4: 12 | I4: 月 | J4: 在初核阶段，不含升压站的集中式光伏项目建设期一般按5个月计算，含升压站的按7个月计算，大型基地项目根据实际情况调整。
C5: 2 | D5: 动工年月 | E5: 手动输入/下拉菜单选择【日历】 | I5: 年/月
C6: 3 | D6: 施工进度安排 | I6: %
D7: 建设期第1年 | E7: 手动输入 | H7: 1
D8: 建设期第2年 | E8: 手动输入
C9: 4 | D9: 运营期 | E9: 手动输入 | H9: 20 | I9: 年 | J9: 原则上按照20年考虑
C10: 5 | D10: 项目所在地 | E10: 下拉菜单选择 | J10: 判定是否属于西部地区
D11: 所在省份 | E11: 下拉菜单选择
D12: 所在市、县 | E12: 下拉菜单选择
B13: 生产相关 | D13: 实际装机容量 | E13: 手动输入 | H13: 50 | I13: MW | J13: 1MW=1000kW
D14: 储能额定功率 | E14: 手动输入 | H14: 10 | I14: MW
D15: 储能容量 | E15: 手动输入 | H15: 20 | I15: MWh
D16: 年均利用小时数 | E16: 手动输入 | H16: 2138.54 | I16: h
D17: 发电量 | E17: 自动计算 | G17: 各年上网电量=年利用小时数*实际装机容量 | H17: =H13*H16 -> 106927 | I17: MWh | J17: 年均
C18: 1 | D18: 上网电量 | G18: 各年上网电量=（（年利用小时数*实际装机容量）-数能融合消纳电量）*（1-限电率） | J18: 1MWh=0.1万度电
D19: 运营期第1年 | E19: 自动计算 | H19: =$H$17*(1-H45)*(1-$H$43) -> 50576.471 | I19: MWh
D20: 运营期第2年 | E20: 自动计算 | H20: =$H$17*(1-H46)*(1-$H$43) -> 50576.471 | I20: MWh
D21: 运营期第3年 | E21: 自动计算 | H21: =$H$17*(1-H47)*(1-$H$43) -> 50576.471 | I21: MWh
D22: 运营期第4年 | E22: 自动计算 | H22: =$H$17*(1-H48)*(1-$H$43) -> 50576.471 | I22: MWh
D23: 运营期第5年 | E23: 自动计算 | H23: =$H$17*(1-H49)*(1-$H$43) -> 50576.471 | I23: MWh
D24: 运营期第6年 | E24: 自动计算 | H24: =$H$17*(1-H50)*(1-$H$43) -> 30345.883 | I24: MWh
D25: 运营期第7年 | E25: 自动计算 | H25: =$H$17*(1-H51)*(1-$H$43) -> 30345.883 | I25: MWh
D26: 运营期第8年 | E26: 自动计算 | H26: =$H$17*(1-H52)*(1-$H$43) -> 30345.883 | I26: MWh
D27: 运营期第9年 | E27: 自动计算 | H27: =$H$17*(1-H53)*(1-$H$43) -> 30345.883 | I27: MWh
D28: 运营期第10年 | E28: 自动计算 | H28: =$H$17*(1-H54)*(1-$H$43) -> 30345.883 | I28: MWh
D29: 运营期第11年 | E29: 自动计算 | H29: =$H$17*(1-H55)*(1-$H$43) -> 30345.883 | I29: MWh
D30: 运营期第12年 | E30: 自动计算 | H30: =$H$17*(1-H56)*(1-$H$43) -> 30345.883 | I30: MWh
... D38: 运营期第20年 | E38: 自动计算 | H38: =$H$17*(1-H64)*(1-$H$43) -> 30345.883 | I38: MWh
D39: 上网电价
D40: 运营期第1年 | E40: 手动输入 | H40: 0.3044 | I40: 元/kWh
D41: …… | E41: 手动输入 | H41: 0.3044 | I41: 元/kWh
D42: 运营期第20年 | E42: 手动输入 | H42: 0.3044 | I42: 元/kWh
D43: 限电率 | E43: 手动输入 | H43: 0.054 | I43: %
C44: 2 | D44: 数能融合消纳风电电量占比
D45: 运营期第1年 | E45: 手动输入 | H45: 0.5 | I45: %
D46: 运营期第2年 | E46: 手动输入 | H46: 0.5 | I46: %
D47: 运营期第3年 | E47: 手动输入 | H47: 0.5 | I47: %
D48: 运营期第4年 | E48: 手动输入 | H48: 0.5 | I48: %
D49: 运营期第5年 | E49: 手动输入 | H49: 0.5 | I49: %
D50: 运营期第6年 | E50: 手动输入 | H50: 0.7 | I50: %
D51: 运营期第7年 | E51: 手动输入 | H51: 0.7 | I51: %
D52: 运营期第8年 | E52: 手动输入 | H52: 0.7 | I52: %
D53: 运营期第9年 | E53: 手动输入 | H53: 0.7 | I53: %
D54: 运营期第10年 | E54: 手动输入 | H54: 0.7 | I54: %
D55: 运营期第11年 | E55: 手动输入 | H55: 0.7 | I55: %
D56: 运营期第12年 | E56: 手动输入 | H56: 0.7 | I56: %
... D64: 运营期第20年 | E64: 手动输入 | H64: 0.7 | I64: %
D65: 数能融合机制电价 | I65: 元/kWh
D66: 运营期第1年 | E66: 手动输入 | H66: 0.3 | I66: 元/kWh
D67: …… | E67: 手动输入 | H67: 0.3 | I67: 元/kWh
D68: 运营期第20年 | E68: 手动输入 | H68: 0.3 | I68: 元/kWh
B69: 投资概算 | C69: 1 | D69: 设备购置费 | E69: 手动输入/下拉菜单选择【增值税税率】 | G69: 增值税税率（自动生成含税和不含税价）：13%/9%/6%/0% | H69: 11947.39 | I69: 万元
C70: 2 | D70: 建安工程费 | E70: 手动输入/下拉菜单选择【增值税税率】 | G70: 增值税税率（自动生成含税和不含税价）：13%/9%/6%/0% | H70: =6238.96-3.57 -> 6235.39 | I70: 万元
C71: 3 | D71: 其他费用 | E71: 手动输入/下拉菜单选择【增值税税率】 | G71: 增值税税率（自动生成含税和不含税价）：13%/9%/6%/0% | H71: 3024.1 | I71: 万元
C72: 4 | D72: 预备费 | E72: 手动输入/下拉菜单选择【增值税税率】 | G72: 增值税税率（自动生成含税和不含税价）：13%/9%/6%/0% | H72: 442.56 | I72: 万元
C73: 5 | D73: 储能投资 | E73: 手动输入/下拉菜单选择【增值税税率】 | G73: 增值税税率（自动生成含税和不含税价）：13%/9%/6%/0% | H73: 920.92 | I73: 万元
C74: 6 | D74: 送出线路投资 | E74: 手动输入/下拉菜单选择【增值税税率】 | G74: 增值税税率（自动生成含税和不含税价）：13%/9%/6%/0% | H74: 1832 | I74: 万元
C75: 7 | D75: 配套支持资金 | E75: 手动输入/下拉菜单选择【增值税税率】 | G75: 增值税税率（自动生成含税和不含税价）：13%/9%/6%/0% | H75: 0 | I75: 万元
C76: 8 | D76: 项目静态总投资 | E76: 自动计算 | G76: 投资概算1-7合计 | H76: =SUM(H69:H75) -> 24402.36 | I76: 万元
C77: 9 | D77: 静态总投资（自主投资） | E77: 自动计算 | G77: 静态总投资（自主投资）=项目静态总投资-建设补贴 | H77: =H76-H84 -> 24402.36 | I77: 万元
C78: 10 | D78: 建设期利息 | E78: 自动计算 | G78: 计入总投资的资本化利息，直接引用资金筹措表数据 | H78: ='表1-资金筹措及还本付息表'!D17 -> 350.1335 | I78: 万元
C79: 11 | D79: 项目动态总投资 (不含流动资金) | E79: 自动计算 | G79: 项目动态总投资（不含流动资金）=项目静态总投资+建设期利息 | H79: =H76+H78 -> 24752.494 | I79: 万元
C80: 12 | D80: 动态总投资（自主投资_不含流动资金） | E80: 自动计算 | G80: 动态总投资（自主投资_不含流动资金）=静态总投资（自主投资）+建设期利息 | H80: =H77+H78 -> 24752.494 | I80: 万元
C81: 13 | D81: 流动资金 | E81: 手动输入后自动计算 | G81: 自定义计算规则 | H81: =H82*H13*1000/10000 -> 150 | I81: 万元 | J81: 建议按照30元/kW考虑
D82: 流动资金取费单价 | E82: 手动输入 | G82: 流动资金=实际装机容量*流动资金取费单价/10000 | H82: 30 | I82: 元/kW
C83: 14 | D83: 可抵扣进项税 | E83: 自动计算 | H83: =可抵扣进项税!E14 -> 2317.7153 | I83: 万元 | J83: 根据项目设计概算梳理出设备类、建安类、服务类投资，再分别按照对应适用税率（现行标准为13%、9%、6%）计算出可抵扣增值税额
C84: 15 | D84: 建设补贴 | E84: 手动输入 | H84: 0 | I84: 万元
B85: 投融资相关 | C85: 1 | D85: 资本金比例 | E85: 手动输入 | H85: 0.2 | I85: % | J85: 资本金比例原则上在20%-30%之间
D86: 资本金 | E86: 自动计算 | G86: 资本金=资金筹措动态总投资*资本金比例 | H86: ='表1-资金筹措及还本付息表'!D11 -> 4995.4987 | I86: 万元
C87: 2 | D87: 宽限期 | E87: 手动输入 | H87: 1 | I87: 年/月 | J87: 建设期仅付息，不还本
C88: 3 | D88: 建设期利息贷款利率 | E88: 手动输入 | H88: 0.036 | I88: % | J88: 用于计算建设期利息的贷款利率
C89: 4 | D89: 长期贷款利率 | E89: 手动输入 | H89: 0.036 | I89: % | J89: 原则上按照开发主体在项目所在地实际融资水平取值，不得高于同期限银行贷款基础利率（LPR）
C90: 5 | D90: 短期贷款利率 | E90: 手动输入 | H90: 0.031 | I90: % | J90: 原则上按照开发主体在项目所在地实际融资水平取值，不得高于同期限银行贷款基础利率（LPR）
C91: 6 | D91: 长期借款本金偿还方式 | E91: 下拉菜单选择 | G91: 等额本息/等额本金/其他
C92: 7 | D92: 长期借款本金还款期限 | E92: 手动输入 | H92: 15 | I92: 年 | J92: 还款期限建议取值15年，最终根据与银行沟通协商情况据实调整
C93: 8 | D93: 流动资金中资本金占比 | E93: 手动输入 | H93: 0.3 | I93: %
C94: 9 | D94: 项目公司注册资本 | E94: 手动输入 | H94: ='表1-资金筹措及还本付息表'!F11 -> 4950.4987 | I94: 万元
C95: 10 | D95: 盈余公积金
D96: 法定盈余公积金提取上限 | E96: 自动计算 | H96: =H94*50% -> 2475.2494 | I96: 万元 | J96: 法定盈余公积金按当年净利润10%提取，累计提取至注册资本的50%不再提取
D97: 法定盈余公积金提取比例 | E97: 默认成固定值 | H97: 0.1 | I97: % | J97: 法定盈余公积金按当年净利润10%提取
D98: 任意盈余公积金提取比例 | E98: 手动输入 | H98: 0 | I98: %
C99: 11 | D99: 短期借款
D100: 短期借款额 | E100: 手动输入（运营期各年），初始默认各年为0 | H100: 0 | I100: 万元
D101: 短期借款还本 | E101: 手动输入（运营期各年），初始默认各年为0 | H101: 0 | I101: 万元
B102: 成本费用 | C102: 1 | D102: 材料费 | F102: 生产成本/销售费用/管理费用/研发费用 | J102: 在运营期前5年（质保期内）将材料费和运行维护费用合并考虑，建议取值不低于1万元/兆瓦/年；自运营期第6年起单独考虑材料费，建议取值不低于0.1万元/兆瓦/年。 （对于外委运维，应结合运维合同约定的工作界面，视情况进行调整）
C103: 1.1 | D103: 前端自定义
D104: 运营期1-5年 | E104: 手动输入 | H104: 1.8 | I104: 万元/兆瓦/年
D105: 运营期6-10年 | E105: 手动输入 | H105: 1.8 | I105: 万元/兆瓦/年
D106: 运营期11-15年 | E106: 手动输入 | H106: 1.8 | I106: 万元/兆瓦/年
D107: 运营期16-20年 | E107: 手动输入 | H107: 1.8 | I107: 万元/兆瓦/年
C108: 1.2 | D108: 增值税税率（自动生成含税和不含税数据） | E108: 下拉菜单选择 | G108: 13%/9%/6%/0% | H108: 0 | I108: %
C109: 2 | D109: 维修费 | F109: 生产成本/管理费用 | J109: 在运营期前5年（质保期内）将材料费和运行维护费用合并考虑，建议取值不低于1万元/兆瓦/年；自运营期第6年开始单独考虑运行维修费，结合固定资产磨损状态，建议第六年按照不低于项目固定资产原值0.3%取值，之后每5年上调不低于0.1%。 （对于外委运维，应结合运维合同约定的工作界面，视情况进行调整）
C110: 2.1 | D110: 取费基数
C111: 2.2 | D111: 费率
D112: 运营期1-5年 | E112: 手动输入 | H112: 0.005 | I112: %
D113: 运营期6-10年 | E113: 手动输入 | H113: 0.01 | I113: %
D114: 运营期11-15年 | E114: 手动输入 | H114: 0.015 | I114: %
D115: 运营期16-20年 | E115: 手动输入 | H115: 0.02 | I115: %
...

Sheet 表1-资金筹措及还本付息表
B2: 资金筹措表
B3: 序号 | C3: 建设期 | D3: 合计 | E3: 单位 | F3: 建设期 | H3: 运营期
F4: 1 | G4: 2 | H4: 1 | I4: 2 | J4: 3 | K4: 4 | L4: 5 | M4: 6 | N4: 7 | O4: 8 | P4: 9 | Q4: 10 | R4: 11 | S4: 12 | T4: 13 | U4: 14 | V4: 15 | W4: 16 | X4: 17 | Y4: 18 | Z4: 19 | AA4: 20
C5: 施工进度安排 | D5: =SUM(F5:M5) -> 1 | F5: =参数输入表!H7 -> 1 | G5: =参数输入表!H8 -> 0
B6: 1 | C6: 动态总投资（自主投资） | D6: =D7+D8+D9 -> 24902.494 | E6: 万元 | F6: =SUM(F7:F9) -> 24752.494 | G6: =SUM(G7:G9) -> 0 | H6: =SUM(H7:H9) -> 150
B7: 1.1 | C7: 静态总投资（自主投资） | D7: =SUM(F7:AA7) -> 24402.36 | E7: 万元 | F7: =参数输入表!$H$77*F5 -> 24402.36 | G7: =参数输入表!$H$77*G5 -> 0 | H7: 0
B8: 1.2 | C8: 建设期利息 | D8: =SUM(F8:AA8) -> 350.1335 | E8: 万元 | F8: =F17 -> 350.1335 | G8: =G17 -> 0 | H8: =H17 -> 0
B9: 1.3 | C9: 流动资金 | D9: =SUM(F9:AA9) -> 150 | E9: 万元 | F9: 0 | G9: 0 | H9: =参数输入表!H81 -> 150
B10: 2 | C10: 资金来源
B11: 2.1 | C11: 资本金 | D11: =SUM(F11:AA11) -> 4995.4987 | E11: 万元 | F11: =F6*参数输入表!$H$85 -> 4950.4987 | G11: =G6*参数输入表!$H$85 -> 0 | H11: =H6*参数输入表!$H$93 -> 45
B12: 2.1.1 | C12: 用于建设投资 | D12: =SUM(F12:AA12) -> 4950.4987 | E12: 万元 | F12: =F11-F13-F14 -> 4950.4987 | G12: =G11-G13-G14 -> 0 | H12: 0
B13: 2.1.2 | C13: 用于建设期利息 | D13: =SUM(F13:AA13) -> 0 | E13: 万元 | F13: 0 | G13: 0 | H13: 0
B14: 2.1.3 | C14: 用于流动资金 | D14: =SUM(F14:AA14) -> 45 | F14: 0 | G14: 0 | H14: =H9*参数输入表!H93 -> 45
B15: 2.2 | C15: 债务资金 | D15: =SUM(F15:M15) -> 19906.995 | E15: 万元 | F15: =SUM(F16:F18) -> 19801.995 | G15: =SUM(G16:G18) -> 0 | H15: =SUM(H16:H18) -> 105
B16: 2.2.1 | C16: 用于建设投资 | D16: =SUM(F16:AA16) -> 19451.861 | E16: 万元 | F16: =F7-F12 -> 19451.861 | G16: =G7-G12 -> 0 | H16: =H7-H12 -> 0
B17: 2.1.2 | C17: 用于建设期利息 | D17: =SUM(F17:AA17) -> 350.1335 | E17: 万元 | F17: =F16/2*参数输入表!$H$88*(参数输入表!H4/12) -> 350.1335 | G17: =IF(G5>0,((G16/2+F15)*参数输入表!$H$88),0) -> 0 | H17: 0
B18: 2.1.3 | C18: 用于流动资金 | D18: =SUM(F18:AA18) -> 105 | E18: 万元 | F18: 0 | G18: 0 | H18: =H9-H14 -> 105
B20: 营运资本变动
B21: 序号 | C21: 项目 | D21: 合计 | E21: 单位 | F21: 建设期 | H21: 运营期
F22: 1 | G22: 2 | H22: 1 | I22: 2 | J22: 3 | K22: 4 | L22: 5 | M22: 6 | N22: 7 | O22: 8 | P22: 9 | Q22: 10 | R22: 11 | S22: 12 | T22: 13 | U22: 14 | V22: 15 | W22: 16 | X22: 17 | Y22: 18 | Z22: 19 | AA22: 20
B23: 1 | C23: 流动资产 | D23: =SUM(F23:AA23) -> 126032.64 | E23: 万元 | F23: =SUM(F24:F27) -> 2317.7153 | G23: =SUM(G24:G27) -> 2317.7153 | H23: =SUM(H24:H27) -> 2581.26 | I23: =SUM(I24:I27) -> 2873.5605 | J23: =SUM(J24:J27) -> 3192.2166 | K23: =SUM(K24:K27) -> 3498.4989 | L23: =SUM(L24:L27) -> 3824.8812 | M23: =SUM(M24:M27) -> 4099.9845 | ... AA23: =SUM(AA24:AA27) -> 11912.077
C24: 货币资金 | D24: =SUM(F24:AA24) -> 115088.24 | E24: 万元 | F24: ='表9-现金流量表-财务计划'!F34 -> 0 | G24: ='表9-现金流量表-财务计划'!G34 -> 0 | H24: ='表9-现金流量表-财务计划'!H34 -> 625.18088 | I24: ='表9-现金流量表-财务计划'!I34 -> 1279.1176 | J24: ='表9-现金流量表-财务计划'!J34 -> 1959.4098 | K24: ='表9-现金流量表-财务计划'!K34 -> 2627.3282 | L24: ='表9-现金流量表-财务计划'!L34 -> 3315.3467 | M24: ='表9-现金流量表-财务计划'!M34 -> 3955.0477 | ... AA24: ='表9-现金流量表-财务计划'!AA34 -> 11912.077
C25: 应收账款 | D25: =SUM(F25:AA25) -> 0 | E25: 万元 | H25: ='表4-收入税金表'!H60 -> 0 | I25: ='表4-收入税金表'!I60 -> 0 | J25: ='表4-收入税金表'!J60 -> 0 | K25: ='表4-收入税金表'!K60 -> 0 | L25: ='表4-收入税金表'!L60 -> 0 | M25: ='表4-收入税金表'!M60 -> 0 | N25: ='表4-收入税金表'!N60 -> 0 | O25: ='表4-收入税金表'!O60 -> 0 | ... AA25: ='表4-收入税金表'!AA60 -> 0
C26: 存货 | D26: =SUM(F26:AA26) -> 0 | E26: 万元
C27: 其他流动资产（留抵税额） | D27: =SUM(F27:AA27) -> 10944.401 | E27: 万元 | F27: ='表4-收入税金表'!F45 -> 2317.7153 | G27: ='表4-收入税金表'!G45 -> 2317.7153 | H27: ='表4-收入税金表'!H45 -> 1956.0791 | I27: ='表4-收入税金表'!I45 -> 1594.443 | J27: ='表4-收入税金表'!J45 -> 1232.8068 | K27: ='表4-收入税金表'!K45 -> 871.17065 | L27: ='表4-收入税金表'!L45 -> 509.53449 | M27: ='表4-收入税金表'!M45 -> 144.93675 | ... AA27: ='表4-收入税金表'!AA45 -> 0
B28: 2 | C28: 流动负债 | D28: =SUM(F28:AA28) -> 17802.258 | E28: 万元 | F28: =SUM(F29:F34) -> 0 | G28: =SUM(G29:G34) -> 0 | H28: =SUM(H29:H34) -> 255.50193 | I28: =SUM(I29:I34) -> 169.2709 | J28: =SUM(J29:J34) -> 190.4402 | K28: =SUM(K29:K34) -> 250.33869 | L28: =SUM(L29:L34) -> 277.76348 | M28: =SUM(M29:M34) -> 288.92538 | ... AA28: =SUM(AA29:AA34) -> 1829.4912
C29: 短期借款 | D29: =SUM(F29:AA29) -> 105 | E29: 万元 | F29: =F64+F74 -> 0 | G29: =G60+G70 -> 0 | H29: =H60+H70 -> 105 | I29: =I60+I70 -> 0 | J29: =J60+J70 -> 0 | K29: =K60+K70 -> 0 | L29: =L60+L70 -> 0 | M29: =M60+M70 -> 0 | N29: =N60+N70 -> 0 | ... AA29: =AA60+AA70 -> 0
C30: 预收款项 | D30: =SUM(F30:AA30) -> 0 | E30: 万元
C31: 应付职工薪酬 | D31: =SUM(F31:AA31) -> 2688 | E31: 万元 | H31: ='表3-成本费用表'!H52 -> 134.4 | I31: ='表3-成本费用表'!I52 -> 134.4 | J31: ='表3-成本费用表'!J52 -> 134.4 | K31: ='表3-成本费用表'!K52 -> 134.4 | L31: ='表3-成本费用表'!L52 -> 134.4 | M31: ='表3-成本费用表'!M52 -> 134.4 | N31: ='表3-成本费用表'!N52 -> 134.4 | O31: ='表3-成本费用表'!O52 -> 134.4 | ... AA31: ='表3-成本费用表'!AA52 -> 134.4
C32: 应交税费 | D32: =SUM(F32:AA32) -> 9626.9904 | E32: 万元 | H32: ='表6-现金流量表-资本金'!H24+'表6-现金流量表-资本金'!H25+'表6-现金流量表-资本金'!H29 -> 0 | I32: ='表6-现金流量表-资本金'!I24+'表6-现金流量表-资本金'!I25+'表6-现金流量表-资本金'!I29 -> 0 | J32: ='表6-现金流量表-资本金'!J24+'表6-现金流量表-资本金'!J25+'表6-现金流量表-资本金'!J29 -> 0 | K32: ='表6-现金流量表-资本金'!K24+'表6-现金流量表-资本金'!K25+'表6-现金流量表-资本金'!K29 -> 40.185589 | L32: ='表6-现金流量表-资本金'!L24+'表6-现金流量表-资本金'!L25+'表6-现金流量表-资本金'!L29 -> 46.126187 | M32: ='表6-现金流量表-资本金'!M24+'表6-现金流量表-资本金'!M25+'表6-现金流量表-资本金'!M29 -> 41.111547 | N32: ='表6-现金流量表-资本金'!N24+'表6-现金流量表-资本金'!N25+'表6-现金流量表-资本金'!N29 -> 360.99238 | O32: ='表6-现金流量表-资本金'!O24+'表6-现金流量表-资本金'!O25+'表6-现金流量表-资本金'!O29 -> 548.97173 | ... AA32: ='表6-现金流量表-资本金'!AA24+'表6-现金流量表-资本金'!AA25+'表6-现金流量表-资本金'!AA29 -> 933.93852
C33: 应付股利 | D33: =SUM(F33:AA33) -> 5382.2673 | E33: 万元 | H33: ='表5-利润表-资本金'!H31 -> 16.101931 | I33: ='表5-利润表-资本金'!I31 -> 34.8709 | J33: ='表5-利润表-资本金'!J31 -> 56.040203 | K33: ='表5-利润表-资本金'!K31 -> 75.753104 | L33: ='表5-利润表-资本金'!L31 -> 97.237292 | M33: ='表5-利润表-资本金'!M31 -> 113.41384 | N33: ='表5-利润表-资本金'!N31 -> 133.11492 | O33: ='表5-利润表-资本金'!O31 -> 157.77144 | ... AA33: ='表5-利润表-资本金'!AA31 -> 761.15263
C34: 其他流动负债 | D34: =SUM(F34:AA34) -> 0 | E34: 万元
B36: 借款还本付息表（长期借款）
B37: 序号 | C37: 项目 | D37: 合计 | E37: 单位 | F37: 建设期 | H37: 运营期
F38: 1 | G38: 2 | H38: 1 | I38: 2 | J38: 3 | K38: 4 | L38: 5 | M38: 6 | N38: 7 | O38: 8 | P38: 9 | Q38: 10 | R38: 11 | S38: 12 | T38: 13 | U38: 14 | V38: 15 | W38: 16 | X38: 17 | Y38: 18 | Z38: 19 | AA38: 20
B39: 1 | C39: 期初借款累计 | E39: 万元 | F39: 0 | G39: =F44 -> 19801.995 | H39: =G44 -> 19801.995 | I39: =H44 -> 18783.307 | J39: =I44 -> 17727.946 | K39: =J44 -> 16634.593 | L39: =K44 -> 15501.878 | M39: =L44 -> 14328.386 | N39: =M44 -> 13112.649 | ... AA39: =Z44 -> 0
B40: 2 | C40: 当期借款 | D40: =SUM(F40:AA40) -> 19801.995 | E40: 万元 | F40: =F15 -> 19801.995 | G40: =G15 -> 0
B41: 3 | C41: 当期还本付息 | D41: =SUM(F41:AA41) -> 25973.395 | E41: 万元 | H41: =-PMT(参数输入表!$H$89,参数输入表!$H$92,'表1-资金筹措及还本付息表'!$D$40) -> 1731.5597 | I41: =-PMT(参数输入表!$H$89,参数输入表!$H$92,'表1-资金筹措及还本付息表'!$D$40) -> 1731.5597 | J41: =-PMT(参数输入表!$H$89,参数输入表!$H$92,'表1-资金筹措及还本付息表'!$D$40) -> 1731.5597 | K41: =-PMT(参数输入表!$H$89,参数输入表!$H$92,'表1-资金筹措及还本付息表'!$D$40) -> 1731.5597 | L41: =-PMT(参数输入表!$H$89,参数输入表!$H$92,'表1-资金筹措及还本付息表'!$D$40) -> 1731.5597 | M41: =-PMT(参数输入表!$H$89,参数输入表!$H$92,'表1-资金筹措及还本付息表'!$D$40) -> 1731.5597 | N41: =-PMT(参数输入表!$H$89,参数输入表!$H$92,'表1-资金筹措及还本付息表'!$D$40) -> 1731.5597 | O41: =-PMT(参数输入表!$H$89,参数输入表!$H$92,'表1-资金筹措及还本付息表'!$D$40) -> 1731.5597 | ... V41: =-PMT(参数输入表!$H$89,参数输入表!$H$92,'表1-资金筹措及还本付息表'!$D$40) -> 1731.5597
C42: 其中：还本（等额本息） | D42: =SUM(F42:AA42) -> 19801.995 | E42: 万元 | H42: =H41-H43 -> 1018.6879 | I42: =I41-I43 -> 1055.3606 | J42: =J41-J43 -> 1093.3536 | K42: =K41-K43 -> 1132.7143 | L42: =L41-L43 -> 1173.4921 | M42: =M41-M43 -> 1215.7378 | N42: =N41-N43 -> 1259.5043 | O42: =O41-O43 -> 1304.8465 | ... V42: =V41-V43 -> 1671.3897
C43: 付息 | D43: =SUM(F43:AA43) -> 6171.4004 | E43: 万元 | H43: =(H39+H40/2)*参数输入表!$H$89 -> 712.87181 | I43: =(I39+I40/2)*参数输入表!$H$89 -> 676.19905 | J43: =(J39+J40/2)*参数输入表!$H$89 -> 638.20607 | K43: =(K39+K40/2)*参数输入表!$H$89 -> 598.84534 | L43: =(L39+L40/2)*参数输入表!$H$89 -> 558.06762 | M43: =(M39+M40/2)*参数输入表!$H$89 -> 515.82191 | N43: =(N39+N40/2)*参数输入表!$H$89 -> 472.05535 | O43: =(O39+O40/2)*参数输入表!$H$89 -> 426.71319 | ... V43: =(V39+V40/2)*参数输入表!$H$89 -> 60.170027
B44: 4 | C44: 期末借款余额 | D44: =V44 -> 1.2732926e-11 | E44: 万元 | F44: =F39+F40-F42 -> 19801.995 | G44: =G39+G40-G42 -> 19801.995 | H44: =H39+H40-H42 -> 18783.307 | I44: =I39+I40-I42 -> 17727.946 | J44: =J39+J40-J42 -> 16634.593 | K44: =K39+K40-K42 -> 15501.878 | L44: =L39+L40-L42 -> 14328.386 | M44: =M39+M40-M42 -> 13112.649 | ... V44: =V39+V40-V42 -> 1.2732926e-11
B46: 借款还本付息表（长期借款）
B47: 序号 | C47: 项目 | D47: 合计 | E47: 单位 | F47: 建设期 | H47: 运营期
F48: 1 | G48: 2 | H48: 1 | I48: 2 | J48: 3 | K48: 4 | L48: 5 | M48: 6 | N48: 7 | O48: 8 | P48: 9 | Q48: 10 | R48: 11 | S48: 12 | T48: 13 | U48: 14 | V48: 15 | W48: 16 | X48: 17 | Y48: 18 | Z48: 19 | AA48: 20
B49: 1 | C49: 期初借款累计 | E49: 万元 | F49: 0 | G49: =F54 -> 19801.995 | H49: =G54 -> 19801.995 | I49: =H54 -> 18481.862 | J49: =I54 -> 17161.729 | K49: =J54 -> 15841.596 | L49: =K54 -> 14521.463 | M49: =L54 -> 13201.33 | N49: =M54 -> 11881.197 | ... V49: =U54 -> 1320.133
B50: 2 | C50: 当期借款 | D50: =SUM(F50:AA50) -> 19801.995 | E50: 万元 | F50: =F15 -> 19801.995 | G50: =G15 -> 0
B51: 3 | C51: 当期还本付息 | D51: =SUM(F51:AA51) -> 25504.969 | E51: 万元 | H51: =SUM(H52:H53) -> 2033.0048 | I51: =SUM(I52:I53) -> 1985.48 | J51: =SUM(J52:J53) -> 1937.9552 | K51: =SUM(K52:K53) -> 1890.4304 | L51: =SUM(L52:L53) -> 1842.9056 | M51: =SUM(M52:M53) -> 1795.3809 | N51: =SUM(N52:N53) -> 1747.8561 | O51: =SUM(O52:O53) -> 1700.3313 | ... V51: =SUM(V52:V53) -> 1367.6578
C52: 其中：还本（等额本金） | D52: =SUM(F52:AA52) -> 19801.995 | E52: 万元 | H52: =$D$50/参数输入表!$H$92 -> 1320.133 | I52: =$D$50/参数输入表!$H$92 -> 1320.133 | J52: =$D$50/参数输入表!$H$92 -> 1320.133 | K52: =$D$50/参数输入表!$H$92 -> 1320.133 | L52: =$D$50/参数输入表!$H$92 -> 1320.133 | M52: =$D$50/参数输入表!$H$92 -> 1320.133 | N52: =$D$50/参数输入表!$H$92 -> 1320.133 | O52: =$D$50/参数输入表!$H$92 -> 1320.133 | ... V52: =$D$50/参数输入表!$H$92 -> 1320.133
C53: 付息 | D53: =SUM(F53:AA53) -> 5702.9745 | E53: 万元 | H53: =(H49+H50/2)*参数输入表!$H$89 -> 712.87181 | I53: =(I49+I50/2)*参数输入表!$H$89 -> 665.34703 | J53: =(J49+J50/2)*参数输入表!$H$89 -> 617.82224 | K53: =(K49+K50/2)*参数输入表!$H$89 -> 570.29745 | L53: =(L49+L50/2)*参数输入表!$H$89 -> 522.77266 | M53: =(M49+M50/2)*参数输入表!$H$89 -> 475.24788 | N53: =(N49+N50/2)*参数输入表!$H$89 -> 427.72309 | O53: =(O49+O50/2)*参数输入表!$H$89 -> 380.1983 | ... V53: =(V49+V50/2)*参数输入表!$H$89 -> 47.524788
B54: 4 | C54: 期末借款余额 | D54: =V54 -> 2.2737368e-12 | E54: 万元 | F54: =F49+F50-F52 -> 19801.995 | G54: =G49+G50-G52 -> 19801.995 | H54: =H49+H50-H52 -> 18481.862 | I54: =I49+I50-I52 -> 17161.729 | J54: =J49+J50-J52 -> 15841.596 | K54: =K49+K50-K52 -> 14521.463 | L54: =L49+L50-L52 -> 13201.33 | M54: =M49+M50-M52 -> 11881.197 | ... V54: =V49+V50-V52 -> 2.2737368e-12
B56: 借款还本付息表（流动资金借款）
B57: 序号 | C57: 项目 | D57: 合计 | E57: 单位 | F57: 建设期 | H57: 运营期
F58: 1 | G58: 2 | H58: 1 | I58: 2 | J58: 3 | K58: 4 | L58: 5 | M58: 6 | N58: 7 | O58: 8 | P58: 9 | Q58: 10 | R58: 11 | S58: 12 | T58: 13 | U58: 14 | V58: 15 | W58: 16 | X58: 17 | Y58: 18 | Z58: 19 | AA58: 20
B59: 一 | C59: 期初借款累计 | E59: 万元 | F59: 0 | G59: =F64 -> 0 | H59: =G64 -> 0 | I59: =H64 -> 105 | J59: =I64 -> 105 | K59: =J64 -> 105 | L59: =K64 -> 105 | M59: =L64 -> 105 | N59: =M64 -> 105 | ... AA59: =Z64 -> 105
B60: 二 | C60: 当期借款 | D60: =SUM(F60:AA60) -> 105 | E60: 万元 | F60: 0 | G60: 0 | H60: =$H$15 -> 105
B61: 三 | C61: 当期还本付息 | D61: =SUM(F61:AA61) -> 166.845 | E61: 万元 | H61: 0 | I61: =SUM(I62:I63) -> 3.255 | J61: =SUM(J62:J63) -> 3.255 | K61: =SUM(K62:K63) -> 3.255 | L61: =SUM(L62:L63) -> 3.255 | M61: =SUM(M62:M63) -> 3.255 | N61: =SUM(N62:N63) -> 3.255 | O61: =SUM(O62:O63) -> 3.255 | P61: =SUM(P62:P63) -> 3.255 | ... AA61: =SUM(AA62:AA63) -> 108.255
C62: 其中：还本 | D62: =SUM(F62:AA62) -> 105 | E62: 万元 | H62: 0 | AA62: =H64 -> 105
C63: 付息 | D63: =SUM(F63:AA63) -> 65.1 | E63: 万元 | H63: =(H59+H60)*参数输入表!$H$90 -> 3.255 | I63: =(I59+I60)*参数输入表!$H$90 -> 3.255 | J63: =(J59+J60)*参数输入表!$H$90 -> 3.255 | K63: =(K59+K60)*参数输入表!$H$90 -> 3.255 | L63: =(L59+L60)*参数输入表!$H$90 -> 3.255 | M63: =(M59+M60)*参数输入表!$H$90 -> 3.255 | N63: =(N59+N60)*参数输入表!$H$90 -> 3.255 | O63: =(O59+O60)*参数输入表!$H$90 -> 3.255 | ... AA63: =(AA59+AA60)*参数输入表!$H$90 -> 3.255
B64: 四 | C64: 期末借款余额 | D64: =AA64 -> 0 | E64: 万元 | F64: =F59+F60-F62 -> 0 | G64: =G59+G60-G62 -> 0 | H64: =H59+H60-H62 -> 105 | I64: =I59+I60-I62 -> 105 | J64: =J59+J60-J62 -> 105 | K64: =K59+K60-K62 -> 105 | L64: =L59+L60-L62 -> 105 | M64: =M59+M60-M62 -> 105 | ... AA64: =AA59+AA60-AA62 -> 0
B66: 借款还本付息表（短期借款）
B67: 序号 | C67: 项目 | D67: 合计 | E67: 单位 | F67: 建设期 | H67: 运营期
F68: 1 | G68: 2 | H68: 1 | I68: 2 | J68: 3 | K68: 4 | L68: 5 | M68: 6 | N68: 7 | O68: 8 | P68: 9 | Q68: 10 | R68: 11 | S68: 12 | T68: 13 | U68: 14 | V68: 15 | W68: 16 | X68: 17 | Y68: 18 | Z68: 19 | AA68: 20
B69: 一 | C69: 期初借款累计 | E69: 万元 | F69: 0 | G69: =F74 -> 0 | H69: =G74 -> 0 | I69: =H74 -> 0 | J69: =I74 -> 0 | K69: =J74 -> 0 | L69: =K74 -> 0 | M69: =L74 -> 0 | N69: =M74 -> 0 | ... AA69: =Z74 -> 0
B70: 二 | C70: 当期借款 | D70: =SUM(F70:AA70) -> 0 | E70: 万元 | F70: 0 | G70: 0 | H70: ='表9-现金流量表-财务计划'!H28 -> 0 | I70: ='表9-现金流量表-财务计划'!I28 -> 0 | J70: ='表9-现金流量表-财务计划'!J28 -> 0 | K70: ='表9-现金流量表-财务计划'!K28 -> 0 | L70: ='表9-现金流量表-财务计划'!L28 -> 0 | M70: ='表9-现金流量表-财务计划'!M28 -> 0 | N70: ='表9-现金流量表-财务计划'!N28 -> 0 | O70: ='表9-现金流量表-财务计划'!O28 -> 0 | ... AA70: ='表9-现金流量表-财务计划'!AA28 -> 0
B71: 三 | C71: 当期还本付息 | D71: =SUM(F71:AA71) -> 0 | E71: 万元 | H71: =SUM(H72:H73) -> 0 | I71: =SUM(I72:I73) -> 0 | J71: =SUM(J72:J73) -> 0 | K71: =SUM(K72:K73) -> 0 | L71: =SUM(L72:L73) -> 0 | M71: =SUM(M72:M73) -> 0 | N71: =SUM(N72:N73) -> 0 | O71: =SUM(O72:O73) -> 0 | ... AA71: =SUM(AA72:AA73) -> 0
C72: 其中：还本 | D72: =SUM(F72:AA72) -> 0 | E72: 万元 | H72: 0 | I72: =H69 -> 0 | J72: =I69 -> 0 | K72: =J69 -> 0 | L72: =K69 -> 0 | M72: =L69 -> 0 | N72: =M69 -> 0 | O72: =N69 -> 0 | P72: =O69 -> 0 | ... AA72: =Z69 -> 0
C73: 付息 | D73: =SUM(F73:AA73) -> 0 | E73: 万元 | H73: =(H70)*参数输入表!$H$90 -> 0 | I73: =(I70)*参数输入表!$H$90 -> 0 | J73: =(J70)*参数输入表!$H$90 -> 0 | K73: =(K70)*参数输入表!$H$90 -> 0 | L73: =(L70)*参数输入表!$H$90 -> 0 | M73: =(M70)*参数输入表!$H$90 -> 0 | N73: =(N70)*参数输入表!$H$90 -> 0 | O73: =(O70)*参数输入表!$H$90 -> 0 | ... AA73: =(AA70)*参数输入表!$H$90 -> 0
B74: 四 | C74: 期末借款余额 | D74: =AA74 -> 0 | E74: 万元 | F74: =F69+F70-F72 -> 0 | G74: =G69+G70-G72 -> 0 | H74: =H69+H70-H72 -> 0 | I74: =I69+I70-I72 -> 0 | J74: =J69+J70-J72 -> 0 | K74: =K69+K70-K72 -> 0 | L74: =L69+L70-L72 -> 0 | M74: =M69+M70-M72 -> 0 | ... AA74: =AA69+AA70-AA72 -> 0
B76: 借款还本付息表（汇总—等额本息）
B77: 序号 | C77: 项目 | D77: 合计 | E77: 单位 | F77: 建设期 | H77: 运营期
F78: 1 | G78: 2 | H78: 1 | I78: 2 | J78: 3 | K78: 4 | L78: 5 | M78: 6 | N78: 7 | O78: 8 | P78: 9 | Q78: 10 | R78: 11 | S78: 12 | T78: 13 | U78: 14 | V78: 15 | W78: 16 | X78: 17 | Y78: 18 | Z78: 19 | AA78: 20
B79: 一 | C79: 期初借款累计 | E79: 万元 | F79: =F39+F59+F69 -> 0 | G79: =G39+G59+G69 -> 19801.995 | H79: =H39+H59+H69 -> 19801.995 | I79: =I39+I59+I69 -> 18888.307 | J79: =J39+J59+J69 -> 17832.946 | K79: =K39+K59+K69 -> 16739.593 | L79: =L39+L59+L69 -> 15606.878 | M79: =M39+M59+M69 -> 14433.386 | ... AA79: =AA39+AA59+AA69 -> 105
B80: 二 | C80: 当期借款 | D80: =SUM(F80:AA80) -> 19906.995 | E80: 万元 | F80: =F40+F60+F70 -> 19801.995 | G80: =G40+G60+G70 -> 0 | H80: =H40+H60+H70 -> 105 | I80: =I40+I60+I70 -> 0 | J80: =J40+J60+J70 -> 0 | K80: =K40+K60+K70 -> 0 | L80: =L40+L60+L70 -> 0 | M80: =M40+M60+M70 -> 0 | ... AA80: =AA40+AA60+AA70 -> 0
B81: 三 | C81: 当期还本付息 | D81: =SUM(F81:AA81) -> 26140.24 | E81: 万元 | H81: =H41+H61+H71 -> 1731.5597 | I81: =I41+I61+I71 -> 1734.8147 | J81: =J41+J61+J71 -> 1734.8147 | K81: =K41+K61+K71 -> 1734.8147 | L81: =L41+L61+L71 -> 1734.8147 | M81: =M41+M61+M71 -> 1734.8147 | N81: =N41+N61+N71 -> 1734.8147 | O81: =O41+O61+O71 -> 1734.8147 | ... AA81: =AA41+AA61+AA71 -> 108.255
C82: 其中：还本 | D82: =SUM(F82:AA82) -> 19906.995 | E82: 万元 | H82: =H42+H62+H72 -> 1018.6879 | I82: =I42+I62+I72 -> 1055.3606 | J82: =J42+J62+J72 -> 1093.3536 | K82: =K42+K62+K72 -> 1132.7143 | L82: =L42+L62+L72 -> 1173.4921 | M82: =M42+M62+M72 -> 1215.7378 | N82: =N42+N62+N72 -> 1259.5043 | O82: =O42+O62+O72 -> 1304.8465 | ... AA82: =AA42+AA62+AA72 -> 105
C83: 付息 | D83: =SUM(F83:AA83) -> 6236.5004 | E83: 万元 | H83: =H43+H63+H73 -> 716.12681 | I83: =I43+I63+I73 -> 679.45405 | J83: =J43+J63+J73 -> 641.46107 | K83: =K43+K63+K73 -> 602.10034 | L83: =L43+L63+L73 -> 561.32262 | M83: =M43+M63+M73 -> 519.07691 | N83: =N43+N63+N73 -> 475.31035 | O83: =O43+O63+O73 -> 429.96819 | ... AA83: =AA43+AA63+AA73 -> 3.255
B84: 四 | C84: 期末借款余额 | D84: =AA84 -> 0 | E84: 万元 | F84: =F44+F64+F74 -> 19801.995 | G84: =G44+G64+G74 -> 19801.995 | H84: =H44+H64+H74 -> 18888.307 | I84: =I44+I64+I74 -> 17832.946 | J84: =J44+J64+J74 -> 16739.593 | K84: =K44+K64+K74 -> 15606.878 | L84: =L44+L64+L74 -> 14433.386 | M84: =M44+M64+M74 -> 13217.649 | ... AA84: =AA44+AA64+AA74 -> 0
B86: 借款还本付息表（汇总—等额本金）
B87: 序号 | C87: 项目 | D87: 合计 | E87: 单位 | F87: 建设期 | H87: 运营期
F88: 1 | G88: 2 | H88: 1 | I88: 2 | J88: 3 | K88: 4 | L88: 5 | M88: 6 | N88: 7 | O88: 8 | P88: 9 | Q88: 10 | R88: 11 | S88: 12 | T88: 13 | U88: 14 | V88: 15 | W88: 16 | X88: 17 | Y88: 18 | Z88: 19 | AA88: 20
B89: 一 | C89: 期初借款累计 | E89: 万元 | F89: =F49+F59+F69 -> 0 | G89: =G49+G59+G69 -> 19801.995 | H89: =H49+H59+H69 -> 19801.995 | I89: =I49+I59+I69 -> 18586.862 | J89: =J49+J59+J69 -> 17266.729 | K89: =K49+K59+K69 -> 15946.596 | L89: =L49+L59+L69 -> 14626.463 | M89: =M49+M59+M69 -> 13306.33 | ... AA89: =AA49+AA59+AA69 -> 105
B90: 二 | C90: 当期借款 | D90: =SUM(F90:AA90) -> 19906.995 | E90: 万元 | F90: =F50+F60+F70 -> 19801.995 | G90: =G50+G60+G70 -> 0 | H90: =H50+H60+H70 -> 105 | I90: =I50+I60+I70 -> 0 | J90: =J50+J60+J70 -> 0 | K90: =K50+K60+K70 -> 0 | L90: =L50+L60+L70 -> 0 | M90: =M50+M60+M70 -> 0 | ... AA90: =AA50+AA60+AA70 -> 0
B91: 三 | C91: 当期还本付息 | D91: =SUM(F91:AA91) -> 25671.814 | E91: 万元 | H91: =H51+H61+H71 -> 2033.0048 | I91: =I51+I61+I71 -> 1988.735 | J91: =J51+J61+J71 -> 1941.2102 | K91: =K51+K61+K71 -> 1893.6854 | L91: =L51+L61+L71 -> 1846.1606 | M91: =M51+M61+M71 -> 1798.6359 | N91: =N51+N61+N71 -> 1751.1111 | O91: =O51+O61+O71 -> 1703.5863 | ... AA91: =AA51+AA61+AA71 -> 108.255
C92: 其中：还本 | D92: =SUM(F92:AA92) -> 19906.995 | E92: 万元 | H92: =H52+H62+H72 -> 1320.133 | I92: =I52+I62+I72 -> 1320.133 | J92: =J52+J62+J72 -> 1320.133 | K92: =K52+K62+K72 -> 1320.133 | L92: =L52+L62+L72 -> 1320.133 | M92: =M52+M62+M72 -> 1320.133 | N92: =N52+N62+N72 -> 1320.133 | O92: =O52+O62+O72 -> 1320.133 | ... AA92: =AA52+AA62+AA72 -> 105
C93: 付息 | D93: =SUM(F93:AA93) -> 5768.0745 | E93: 万元 | H93: =H53+H63+H73 -> 716.12681 | I93: =I53+I63+I73 -> 668.60203 | J93: =J53+J63+J73 -> 621.07724 | K93: =K53+K63+K73 -> 573.55245 | L93: =L53+L63+L73 -> 526.02766 | M93: =M53+M63+M73 -> 478.50288 | N93: =N53+N63+N73 -> 430.97809 | O93: =O53+O63+O73 -> 383.4533 | ... AA93: =AA53+AA63+AA73 -> 3.255
B94: 四 | C94: 期末借款余额 | D94: =AA94 -> 0 | E94: 万元 | F94: =F54+F64+F74 -> 19801.995 | G94: =G54+G64+G74 -> 19801.995 | H94: =H54+H64+H74 -> 18586.862 | I94: =I54+I64+I74 -> 17266.729 | J94: =J54+J64+J74 -> 15946.596 | K94: =K54+K64+K74 -> 14626.463 | L94: =L54+L64+L74 -> 13306.33 | M94: =M54+M64+M74 -> 11986.197 | ... AA94: =AA54+AA64+AA74 -> 0
C97: 当期借款引用“资金筹措表”对应年份债务资金数据
C98: 等额本金/等额本息/其他，作为参数输入表—投融资相关板块中的可选择情形，匹配如下不同的计算方法
C99: （1）等额本息情形下，还本付息采用年金公式先得出每年的 本金+利息 之和（固定值），再结合各年度期初及当期借款金额计算出各年度应付利息，进而推算出每年偿还的本金。
C100: （2）等额本金情形下，每年的本金偿还为固定值（建设期借款总额/还款年限），再结合各年度期初及当期借款金额计算出各年度应付利息。
C101: （3）其他情形下，运营期每年的本金偿还设置为手动输入项
C103: 短期借款每年的当期借款及还本直接引用参数表的数据（初始默认为0）

Sheet 表2-折旧摊销表
C1: 中间过程引用（隐藏）
C2: 动态总投资（自主投资_不含流动资金） | D2: =参数输入表!H80 -> 24752.494
C3: 可抵扣进项税 | D3: =参数输入表!H83 -> 2317.7153
C4: 固定资产原值 | D4: =D2-D15-D3 -> 22434.778 | F4: 固定资产原值=项目动态总投资（自主投资_不含流动资金）-可抵扣进项税-无形资产原值=项目静态总投资-建设补贴+建设期利息-可抵扣进项税-无形资产原值
C5: 折旧方式 | D5: 直线法/其他
C6: 折旧年限 | D6: =参数输入表!H151 -> 15
C7: 残值率 | D7: =参数输入表!H152 -> 0.05
C8: 长期待摊费用（第1年） | D8: =参数输入表!H160/(1+参数输入表!H182) -> 0 | F8: 长期待摊费用=计入长期待摊的成本项/（1+增值税税率）
C9: 长期待摊费用（第6年） | D9: =参数输入表!H165/(1+参数输入表!H182) -> 0
C10: 长期待摊费用（第11年） | D10: =参数输入表!H170/(1+参数输入表!H182) -> 0
C11: 长期待摊费用（第16年） | D11: =参数输入表!H175/(1+参数输入表!H182) -> 0
C13: 摊销方式 | D13: 直线法/其他
C14: 摊销年限 | D14: =参数输入表!H181 -> 5
C15: 无形资产原值 | D15: =参数输入表!H154 -> 0
C16: 摊销方式 | D16: 直线法/其他
C17: 摊销年限 | D17: =参数输入表!H156 -> 10 | F17: 建设期 | H17: 运营期
C18: 残值率 | D18: =参数输入表!H157 -> 0 | F18: 1 | G18: 2 | H18: 1 | I18: 2 | J18: 3 | K18: 4 | L18: 5 | M18: 6 | N18: 7 | O18: 8 | P18: 9 | Q18: 10 | R18: 11 | S18: 12 | T18: 13 | U18: 14 | V18: 15 | W18: 16 | X18: 17 | Y18: 18 | Z18: 19 | AA18: 20
C19: 大修及更新重置资产原值
C20: 摊销方式 | D20: 直线法/其他 | H20: =参数输入表!H185 -> 0 | I20: =参数输入表!H186 -> 0 | J20: =参数输入表!H187 -> 0 | K20: =参数输入表!H188 -> 0 | L20: =参数输入表!H189 -> 0 | M20: =参数输入表!H190 -> 0 | N20: =参数输入表!H191 -> 0 | O20: =参数输入表!H192 -> 0 | P20: =参数输入表!H193 -> 0 | Q20: =参数输入表!H194 -> 0 | R20: =参数输入表!H195 -> 480 | S20: =参数输入表!H196 -> 0 | T20: =参数输入表!H197 -> 0 | U20: =参数输入表!H198 -> 0 | V20: =参数输入表!H199 -> 0 | W20: =参数输入表!H200 -> 0 | X20: =参数输入表!H201 -> 0 | Y20: =参数输入表!H202 -> 0 | Z20: =参数输入表!H203 -> 0 | AA20: =参数输入表!H204 -> 0
C21: 摊销年限 | D21: =参数输入表!H206 -> 10
C22: 残值率 | D22: =参数输入表!H207 -> 0.05
B23: 折旧摊销表-资本金
B24: 序号 | C24: 科目 | D24: 合计 | E24: 单位 | F24: 建设期 | H24: 运营期
F25: 1 | G25: 2 | H25: 1 | I25: 2 | J25: 3 | K25: 4 | L25: 5 | M25: 6 | N25: 7 | O25: 8 | P25: 9 | Q25: 10 | R25: 11 | S25: 12 | T25: 13 | U25: 14 | V25: 15 | W25: 16 | X25: 17 | Y25: 18 | Z25: 19 | AA25: 20
B26: 1 | C26: 固定资产净值 | E26: 万元 | F26: =D27 -> 21313.039 | H26: =IF('表1-资金筹措及还本付息表'!G5=0,F26-H27,G26-H27) -> 19892.17 | I26: =H26-I27 -> 18471.301 | J26: =I26-J27 -> 17050.431 | K26: =J26-K27 -> 15629.562 | L26: =K26-L27 -> 14208.693 | M26: =L26-M27 -> 12787.824 | N26: =M26-N27 -> 11366.954 | O26: =N26-O27 -> 9946.085 | P26: =O26-P27 -> 8525.2157 | ... AA26: =Z26-AA27 -> 2.2737368e-12
C27: 当期固定资产折旧 | D27: =SUM(F27:AA27) -> 21313.039 | E27: 万元 | H27: =IF(H25<=$D$6,$D$4*(1-$D$7)/($D$6),0) -> 1420.8693 | I27: =IF(I25<=$D$6,$D$4*(1-$D$7)/($D$6),0) -> 1420.8693 | J27: =IF(J25<=$D$6,$D$4*(1-$D$7)/($D$6),0) -> 1420.8693 | K27: =IF(K25<=$D$6,$D$4*(1-$D$7)/($D$6),0) -> 1420.8693 | L27: =IF(L25<=$D$6,$D$4*(1-$D$7)/($D$6),0) -> 1420.8693 | M27: =IF(M25<=$D$6,$D$4*(1-$D$7)/($D$6),0) -> 1420.8693 | N27: =IF(N25<=$D$6,$D$4*(1-$D$7)/($D$6),0) -> 1420.8693 | O27: =IF(O25<=$D$6,$D$4*(1-$D$7)/($D$6),0) -> 1420.8693 | ... AA27: =IF(AA25<=$D$6,$D$4*(1-$D$7)/($D$6),0) -> 0
B28: 2 | C28: 期初长期待摊费用 | E28: 万元 | H28: 0 | I28: =H31 -> 0 | J28: =I31 -> 0 | K28: =J31 -> 0 | L28: =K31 -> 0 | M28: =L31 -> 0 | N28: =M31 -> 0 | O28: =N31 -> 0 | P28: =O31 -> 0 | ... AA28: =Z31 -> 0
C29: 当期新增长期待摊费用 | H29: =参数输入表!H160/(1+参数输入表!H182) -> 0 | I29: =参数输入表!H161/(1+参数输入表!H182) -> 0 | J29: =参数输入表!H162/(1+参数输入表!H182) -> 0 | K29: =参数输入表!H163/(1+参数输入表!H182) -> 0 | L29: =参数输入表!H164/(1+参数输入表!H182) -> 0 | M29: =参数输入表!H165/(1+参数输入表!H182) -> 0 | N29: =参数输入表!H166/(1+参数输入表!H182) -> 0 | O29: =参数输入表!H167/(1+参数输入表!H182) -> 0 | P29: =参数输入表!H168/(1+参数输入表!H182) -> 0 | Q29: =参数输入表!H169/(1+参数输入表!H182) -> 0 | R29: =参数输入表!H170/(1+参数输入表!H182) -> 0 | S29: =参数输入表!H171/(1+参数输入表!H182) -> 0 | T29: =参数输入表!H172/(1+参数输入表!H182) -> 0 | U29: =参数输入表!H173/(1+参数输入表!H182) -> 0 | V29: =参数输入表!H174/(1+参数输入表!H182) -> 0 | W29: =参数输入表!H175/(1+参数输入表!H182) -> 0 | X29: =参数输入表!H176/(1+参数输入表!H182) -> 0 | Y29: =参数输入表!H177/(1+参数输入表!H182) -> 0 | Z29: =参数输入表!H178/(1+参数输入表!H182) -> 0 | AA29: =参数输入表!H179/(1+参数输入表!H182) -> 0
C30: 当期摊销 | D30: =SUM(F30:AA30) -> 0 | E30: 万元 | H30: =H29/$D$14 -> 0 | I30: =H30 -> 0 | J30: =I30 -> 0 | K30: =J30 -> 0 | L30: =K30 -> 0 | M30: =M29/$D$14 -> 0 | N30: =M30 -> 0 | O30: =N30 -> 0 | P30: =O30 -> 0 | Q30: =P30 -> 0 | R30: =R29/$D$14 -> 0 | S30: =R30 -> 0 | T30: =S30 -> 0 | U30: =T30 -> 0 | V30: =U30 -> 0 | W30: =W29/$D$14 -> 0 | X30: =W30 -> 0 | Y30: =X30 -> 0 | Z30: =Y30 -> 0 | AA30: =Z30 -> 0
C31: 期末期初长期待摊费用 | H31: =H28+H29-H30 -> 0 | I31: =I28+I29-I30 -> 0 | J31: =J28+J29-J30 -> 0 | K31: =K28+K29-K30 -> 0 | L31: =L28+L29-L30 -> 0 | M31: =M28+M29-M30 -> 0 | N31: =N28+N29-N30 -> 0 | O31: =O28+O29-O30 -> 0 | ... AA31: =AA28+AA29-AA30 -> 0
B32: 3 | C32: 无形资产净值 | E32: 万元 | F32: =参数输入表!$H$154*参数输入表!$H$7 -> 0 | G32: =参数输入表!$H$154*参数输入表!$H$7+参数输入表!$H$154*参数输入表!$H$8 -> 0 | H32: =G32-H33 -> 0 | I32: =H32-I33 -> 0 | J32: =I32-J33 -> 0 | K32: =J32-K33 -> 0 | L32: =K32-L33 -> 0 | M32: =L32-M33 -> 0 | N32: =M32-N33 -> 0 | O32: =N32-O33 -> 0 | ... AA32: =Z32-AA33 -> 0
C33: 当期无形资产摊销 | D33: =SUM(F33:AA33) -> 0 | E33: 万元 | H33: =IF(H25<=$D$17,G32*(1-$D$18)/($D$17-H25+1),0) -> 0 | I33: =IF(I25<=$D$17,H32*(1-$D$18)/($D$17-I25+1),0) -> 0 | J33: =IF(J25<=$D$17,I32*(1-$D$18)/($D$17-J25+1),0) -> 0 | K33: =IF(K25<=$D$17,J32*(1-$D$18)/($D$17-K25+1),0) -> 0 | L33: =IF(L25<=$D$17,K32*(1-$D$18)/($D$17-L25+1),0) -> 0 | M33: =IF(M25<=$D$17,L32*(1-$D$18)/($D$17-M25+1),0) -> 0 | N33: =IF(N25<=$D$17,M32*(1-$D$18)/($D$17-N25+1),0) -> 0 | O33: =IF(O25<=$D$17,N32*(1-$D$18)/($D$17-O25+1),0) -> 0 | ... AA33: =IF(AA25<=$D$17,Z32*(1-$D$18)/($D$17-AA25+1),0) -> 0
B34: 4 | C34: 期初大修及更新重置资产净值 | E34: 万元 | H34: 0 | I34: =H37 -> 0 | J34: =I37 -> 0 | K34: =J37 -> 0 | L34: =K37 -> 0 | M34: =L37 -> 0 | N34: =M37 -> 0 | O34: =N37 -> 0 | P34: =O37 -> 0 | ... AA34: =Z37 -> 61.59292
C35: 当期新增大修及更新重置资产 | H35: =参数输入表!H185/(1+参数输入表!$H$208) -> 0 | I35: =参数输入表!H186/(1+参数输入表!$H$208) -> 0 | J35: =参数输入表!H187/(1+参数输入表!$H$208) -> 0 | K35: =参数输入表!H188/(1+参数输入表!$H$208) -> 0 | L35: =参数输入表!H189/(1+参数输入表!$H$208) -> 0 | M35: =参数输入表!H190/(1+参数输入表!$H$208) -> 0 | N35: =参数输入表!H191/(1+参数输入表!$H$208) -> 0 | O35: =参数输入表!H192/(1+参数输入表!$H$208) -> 0 | P35: =参数输入表!H193/(1+参数输入表!$H$208) -> 0 | Q35: =参数输入表!H194/(1+参数输入表!$H$208) -> 0 | R35: =参数输入表!H195/(1+参数输入表!$H$208) -> 424.77876 | S35: =参数输入表!H196/(1+参数输入表!$H$208) -> 0 | T35: =参数输入表!H197/(1+参数输入表!$H$208) -> 0 | U35: =参数输入表!H198/(1+参数输入表!$H$208) -> 0 | V35: =参数输入表!H199/(1+参数输入表!$H$208) -> 0 | W35: =参数输入表!H200/(1+参数输入表!$H$208) -> 0 | X35: =参数输入表!H201/(1+参数输入表!$H$208) -> 0 | Y35: =参数输入表!H202/(1+参数输入表!$H$208) -> 0 | Z35: =参数输入表!H203/(1+参数输入表!$H$208) -> 0 | AA35: =参数输入表!H204/(1+参数输入表!$H$208) -> 0
C36: 当期大修及更新重置资产折旧摊销 | D36: =SUM(F36:AA36) -> 403.53982 | E36: 万元 | H36: 0 | I36: 0 | J36: 0 | K36: 0 | L36: 0 | M36: 0 | N36: 0 | O36: 0 | P36: 0 | Q36: =Q35/D21 -> 0 | R36: =R35*(1-$D$22)/D21 -> 40.353982 | S36: =R36 -> 40.353982 | T36: =S36 -> 40.353982 | U36: =T36 -> 40.353982 | V36: =U36 -> 40.353982 | W36: =V36 -> 40.353982 | X36: =W36 -> 40.353982 | Y36: =X36 -> 40.353982 | Z36: =Y36 -> 40.353982 | AA36: =Z36 -> 40.353982
C37: 期末大修及更新重置资产净值 | H37: =H34+H35-H36 -> 0 | I37: =I34+I35-I36 -> 0 | J37: =J34+J35-J36 -> 0 | K37: =K34+K35-K36 -> 0 | L37: =L34+L35-L36 -> 0 | M37: =M34+M35-M36 -> 0 | N37: =N34+N35-N36 -> 0 | O37: =O34+O35-O36 -> 0 | ... AA37: =AA34+AA35-AA36 -> 21.238938
B38: 5 | C38: 当期折旧摊销 | D38: =SUM(F38:AA38) -> 21716.579 | E38: 万元 | F38: =F27+F30+F33+F36 -> 0 | G38: =G27+G30+G33+G36 -> 0 | H38: =H27+H30+H33+H36 -> 1420.8693 | I38: =I27+I30+I33+I36 -> 1420.8693 | J38: =J27+J30+J33+J36 -> 1420.8693 | K38: =K27+K30+K33+K36 -> 1420.8693 | L38: =L27+L30+L33+L36 -> 1420.8693 | M38: =M27+M30+M33+M36 -> 1420.8693 | ... AA38: =AA27+AA30+AA33+AA36 -> 40.353982
C41: 上述为“直线法”下折旧摊销计算，若在参数输入表中下拉菜单选择为“其他”，设置为手动输入各年份折旧额/摊销额
C43: 中间过程引用（隐藏）
C44: 静态总投资（自主投资） | D44: =D2 -> 24752.494
C45: 可抵扣进项税 | D45: =参数输入表!H83 -> 2317.7153
C46: 固定资产原值 | D46: =D44-D45-参数输入表!H154 -> 22434.778 | F46: 全投资情形下的固定资产原值=静态总投资（自主投资）-可抵扣进项税-无形资产原值；资本金情形下的固定资产原值采用的是“项目动态总投资（自主投资_不含流动资金）”
C47: 折旧方式 | D47: 直线法/其他 | F47: 折旧方式、残值率及折旧年限与资本金情形保持一致
C48: 折旧年限 | D48: =参数输入表!H151 -> 15
C49: 残值率 | D49: =参数输入表!H152 -> 0.05
B51: 折旧摊销表-全投资
B52: 序号 | C52: 科目 | D52: 合计 | E52: 单位 | F52: 建设期 | H52: 运营期
F53: 1 | G53: 2 | H53: 1 | I53: 2 | J53: 3 | K53: 4 | L53: 5 | M53: 6 | N53: 7 | O53: 8 | P53: 9 | Q53: 10 | R53: 11 | S53: 12 | T53: 13 | U53: 14 | V53: 15 | W53: 16 | X53: 17 | Y53: 18 | Z53: 19 | AA53: 20
B54: 1 | C54: 固定资产净值（全投资） | E54: 万元 | F54: =D55 -> 21313.039 | H54: =F54-H55 -> 19892.17 | I54: =H54-I55 -> 18471.301 | J54: =I54-J55 -> 17050.431 | K54: =J54-K55 -> 15629.562 | L54: =K54-L55 -> 14208.693 | M54: =L54-M55 -> 12787.824 | N54: =M54-N55 -> 11366.954 | O54: =N54-O55 -> 9946.085 | P54: =O54-P55 -> 8525.2157 | ... AA54: =Z54-AA55 -> 2.2737368e-12
C55: 当期固定资产折旧 | D55: =SUM(F55:AA55) -> 21313.039 | E55: 万元 | H55: =IF(H53<=$D$48,$D$46*(1-$D$49)/($D$48-$H$53+1),0) -> 1420.8693 | I55: =IF(I53<=$D$48,$D$46*(1-$D$49)/($D$48-$H$53+1),0) -> 1420.8693 | J55: =IF(J53<=$D$48,$D$46*(1-$D$49)/($D$48-$H$53+1),0) -> 1420.8693 | K55: =IF(K53<=$D$48,$D$46*(1-$D$49)/($D$48-$H$53+1),0) -> 1420.8693 | L55: =IF(L53<=$D$48,$D$46*(1-$D$49)/($D$48-$H$53+1),0) -> 1420.8693 | M55: =IF(M53<=$D$48,$D$46*(1-$D$49)/($D$48-$H$53+1),0) -> 1420.8693 | N55: =IF(N53<=$D$48,$D$46*(1-$D$49)/($D$48-$H$53+1),0) -> 1420.8693 | O55: =IF(O53<=$D$48,$D$46*(1-$D$49)/($D$48-$H$53+1),0) -> 1420.8693 | ... AA55: =IF(AA53<=$D$48,$D$46*(1-$D$49)/($D$48-$H$53+1),0) -> 0
B56: 2 | C56: 期初长期待摊费用 | E56: 万元 | H56: 0 | I56: =H59 -> 0 | J56: =I59 -> 0 | K56: =J59 -> 0 | L56: =K59 -> 0 | M56: =L59 -> 0 | N56: =M59 -> 0 | O56: =N59 -> 0 | P56: =O59 -> 0 | ... AA56: =Z59 -> 0
C57: 当期新增长期待摊费用 | H57: =H29 -> 0 | I57: =I29 -> 0 | J57: =J29 -> 0 | K57: =K29 -> 0 | L57: =L29 -> 0 | M57: =M29 -> 0 | N57: =N29 -> 0 | O57: =O29 -> 0 | ... AA57: =AA29 -> 0
C58: 当期摊销 | D58: =SUM(F58:AA58) -> 0 | E58: 万元 | H58: =H57/$D$14 -> 0 | I58: =H58 -> 0 | J58: =I58 -> 0 | K58: =J58 -> 0 | L58: =K58 -> 0 | M58: =M57/$D$14 -> 0 | N58: =M58 -> 0 | O58: =N58 -> 0 | P58: =O58 -> 0 | Q58: =P58 -> 0 | R58: =R57/$D$14 -> 0 | S58: =R58 -> 0 | T58: =S58 -> 0 | U58: =T58 -> 0 | V58: =U58 -> 0 | W58: =W57/$D$14 -> 0 | X58: =W58 -> 0 | Y58: =X58 -> 0 | Z58: =Y58 -> 0 | AA58: =Z58 -> 0
C59: 期末期初长期待摊费用 | H59: =H56+H57-H58 -> 0 | I59: =I56+I57-I58 -> 0 | J59: =J56+J57-J58 -> 0 | K59: =K56+K57-K58 -> 0 | L59: =L56+L57-L58 -> 0 | M59: =M56+M57-M58 -> 0 | N59: =N56+N57-N58 -> 0 | O59: =O56+O57-O58 -> 0 | ... AA59: =AA56+AA57-AA58 -> 0
B60: 3 | C60: 无形资产净值 | E60: 万元 | F60: =参数输入表!$H$154*参数输入表!$H$7 -> 0 | G60: =参数输入表!$H$154*参数输入表!$H$7+参数输入表!$H$154*参数输入表!$H$8 -> 0 | H60: =G60-H61 -> 0 | I60: =H60-I61 -> 0 | J60: =I60-J61 -> 0 | K60: =J60-K61 -> 0 | L60: =K60-L61 -> 0 | M60: =L60-M61 -> 0 | N60: =M60-N61 -> 0 | O60: =N60-O61 -> 0 | ... AA60: =Z60-AA61 -> 0
C61: 当期无形资产摊销 | D61: =SUM(F61:AA61) -> 0 | E61: 万元 | H61: =IF(H53<=$D$17,G60*(1-$D$18)/($D$17-H25+1),0) -> 0 | I61: =IF(I53<=$D$17,H60*(1-$D$18)/($D$17-I25+1),0) -> 0 | J61: =IF(J53<=$D$17,I60*(1-$D$18)/($D$17-J25+1),0) -> 0 | K61: =IF(K53<=$D$17,J60*(1-$D$18)/($D$17-K25+1),0) -> 0 | L61: =IF(L53<=$D$17,K60*(1-$D$18)/($D$17-L25+1),0) -> 0 | M61: =IF(M53<=$D$17,L60*(1-$D$18)/($D$17-M25+1),0) -> 0 | N61: =IF(N53<=$D$17,M60*(1-$D$18)/($D$17-N25+1),0) -> 0 | O61: =IF(O53<=$D$17,N60*(1-$D$18)/($D$17-O25+1),0) -> 0 | ... AA61: =IF(AA53<=$D$17,Z60*(1-$D$18)/($D$17-AA25+1),0) -> 0
B62: 4 | C62: 期初大修及更新重置资产净值 | E62: 万元 | H62: =H34 -> 0 | I62: =I34 -> 0 | J62: =J34 -> 0 | K62: =K34 -> 0 | L62: =L34 -> 0 | M62: =M34 -> 0 | N62: =N34 -> 0 | O62: =O34 -> 0 | ... AA62: =AA34 -> 61.59292
C63: 当期新增大修及更新重置资产 | H63: =H35 -> 0 | I63: =I35 -> 0 | J63: =J35 -> 0 | K63: =K35 -> 0 | L63: =L35 -> 0 | M63: =M35 -> 0 | N63: =N35 -> 0 | O63: =O35 -> 0 | ... AA63: =AA35 -> 0
C64: 当期大修及更新重置资产折旧摊销 | D64: =SUM(F64:AA64) -> 403.53982 | E64: 万元 | H64: =H36 -> 0 | I64: =I36 -> 0 | J64: =J36 -> 0 | K64: =K36 -> 0 | L64: =L36 -> 0 | M64: =M36 -> 0 | N64: =N36 -> 0 | O64: =O36 -> 0 | ... AA64: =AA36 -> 40.353982
C65: 期末大修及更新重置资产净值 | H65: =H37 -> 0 | I65: =I37 -> 0 | J65: =J37 -> 0 | K65: =K37 -> 0 | L65: =L37 -> 0 | M65: =M37 -> 0 | N65: =N37 -> 0 | O65: =O37 -> 0 | ... AA65: =AA37 -> 21.238938
B66: 5 | C66: 当期折旧摊销 | D66: =SUM(F66:AA66) -> 21716.579 | E66: 万元 | F66: =F55+F58+F61+F64 -> 0 | G66: =G55+G58+G61+G64 -> 0 | H66: =H55+H58+H61+H64 -> 1420.8693 | I66: =I55+I58+I61+I64 -> 1420.8693 | J66: =J55+J58+J61+J64 -> 1420.8693 | K66: =K55+K58+K61+K64 -> 1420.8693 | L66: =L55+L58+L61+L64 -> 1420.8693 | M66: =M55+M58+M61+M64 -> 1420.8693 | ... AA66: =AA55+AA58+AA61+AA64 -> 40.353982

Sheet 表3-成本费用表
B2: 成本费用表-资本金
B3: 序号 | C3: 项目 | D3: 合计 | E3: 单位 | F3: 建设期 | H3: 运营期
F4: 1 | G4: 2 | H4: 1 | I4: 2 | J4: 3 | K4: 4 | L4: 5 | M4: 6 | N4: 7 | O4: 8 | P4: 9 | Q4: 10 | R4: 11 | S4: 12 | T4: 13 | U4: 14 | V4: 15 | W4: 16 | X4: 17 | Y4: 18 | Z4: 19 | AA4: 20
B5: 一 | C5: 营业总成本 | D5: =SUM(F5:AA5) -> 40115.554 | E5: 万元 | H5: =H6+H15+H16+H19+H20 -> 2602.9063 | I5: =I6+I15+I16+I19+I20 -> 2555.3815 | J5: =J6+J15+J16+J19+J20 -> 2507.8567 | K5: =K6+K15+K16+K19+K20 -> 2460.3319 | L5: =L6+L15+L16+L19+L20 -> 2412.8071 | M5: =M6+M15+M16+M19+M20 -> 2475.7056 | N5: =N6+N15+N16+N19+N20 -> 2428.1808 | O5: =O6+O15+O16+O19+O20 -> 2380.656 | ... AA5: =AA6+AA15+AA16+AA19+AA20 -> 840.78882
B6: 1 | C6: 生产成本 | D6: =SUM(F6:AA6) -> 33225.74 | H6: =SUM(H7:H14) -> 1830.6925 | I6: =SUM(I7:I14) -> 1830.6925 | J6: =SUM(J7:J14) -> 1830.6925 | K6: =SUM(K7:K14) -> 1830.6925 | L6: =SUM(L7:L14) -> 1830.6925 | M6: =SUM(M7:M14) -> 1941.1157 | N6: =SUM(N7:N14) -> 1941.1157 | O6: =SUM(O7:O14) -> 1941.1157 | ... AA6: =SUM(AA7:AA14) -> 781.44688
B7: 1.1 | C7: 材料费 | D7: =SUM(F7:AA7) -> 1800 | E7: 万元 | H7: =参数输入表!$H$104*参数输入表!$H$13/(1+参数输入表!$H$108) -> 90 | I7: =参数输入表!$H$104*参数输入表!$H$13/(1+参数输入表!$H$108) -> 90 | J7: =参数输入表!$H$104*参数输入表!$H$13/(1+参数输入表!$H$108) -> 90 | K7: =参数输入表!$H$104*参数输入表!$H$13/(1+参数输入表!$H$108) -> 90 | L7: =参数输入表!$H$104*参数输入表!$H$13/(1+参数输入表!$H$108) -> 90 | M7: =参数输入表!$H$105*参数输入表!$H$13/(1+参数输入表!$H$108) -> 90 | N7: =参数输入表!$H$105*参数输入表!$H$13/(1+参数输入表!$H$108) -> 90 | O7: =参数输入表!$H$105*参数输入表!$H$13/(1+参数输入表!$H$108) -> 90 | P7: =参数输入表!$H$105*参数输入表!$H$13/(1+参数输入表!$H$108) -> 90 | Q7: =参数输入表!$H$105*参数输入表!$H$13/(1+参数输入表!$H$108) -> 90 | R7: =参数输入表!$H$106*参数输入表!$H$13/(1+参数输入表!$H$108) -> 90 | S7: =参数输入表!$H$106*参数输入表!$H$13/(1+参数输入表!$H$108) -> 90 | T7: =参数输入表!$H$106*参数输入表!$H$13/(1+参数输入表!$H$108) -> 90 | U7: =参数输入表!$H$106*参数输入表!$H$13/(1+参数输入表!$H$108) -> 90 | V7: =参数输入表!$H$106*参数输入表!$H$13/(1+参数输入表!$H$108) -> 90 | W7: =参数输入表!$H$107*参数输入表!$H$13/(1+参数输入表!$H$108) -> 90 | X7: =参数输入表!$H$107*参数输入表!$H$13/(1+参数输入表!$H$108) -> 90 | Y7: =参数输入表!$H$107*参数输入表!$H$13/(1+参数输入表!$H$108) -> 90 | Z7: =参数输入表!$H$107*参数输入表!$H$13/(1+参数输入表!$H$108) -> 90 | AA7: =参数输入表!$H$107*参数输入表!$H$13/(1+参数输入表!$H$108) -> 90
B8: 1.2 | C8: 维修费 | D8: =SUM(F8:AA8) -> 5521.1612 | E8: 万元 | H8: =(参数输入表!$H$76-参数输入表!$H$83)*参数输入表!$H$112/(1+参数输入表!$H$116) -> 110.42322 | I8: =(参数输入表!$H$76-参数输入表!$H$83)*参数输入表!$H$112/(1+参数输入表!$H$116) -> 110.42322 | J8: =(参数输入表!$H$76-参数输入表!$H$83)*参数输入表!$H$112/(1+参数输入表!$H$116) -> 110.42322 | K8: =(参数输入表!$H$76-参数输入表!$H$83)*参数输入表!$H$112/(1+参数输入表!$H$116) -> 110.42322 | L8: =(参数输入表!$H$76-参数输入表!$H$83)*参数输入表!$H$112/(1+参数输入表!$H$116) -> 110.42322 | M8: =(参数输入表!$H$76-参数输入表!$H$83)*参数输入表!$H$113/(1+参数输入表!$H$116) -> 220.84645 | N8: =(参数输入表!$H$76-参数输入表!$H$83)*参数输入表!$H$113/(1+参数输入表!$H$116) -> 220.84645 | O8: =(参数输入表!$H$76-参数输入表!$H$83)*参数输入表!$H$113/(1+参数输入表!$H$116) -> 220.84645 | P8: =(参数输入表!$H$76-参数输入表!$H$83)*参数输入表!$H$113/(1+参数输入表!$H$116) -> 220.84645 | Q8: =(参数输入表!$H$76-参数输入表!$H$83)*参数输入表!$H$113/(1+参数输入表!$H$116) -> 220.84645 | R8: =(参数输入表!$H$76-参数输入表!$H$83)*参数输入表!$H$114/(1+参数输入表!$H$116) -> 331.26967 | S8: =(参数输入表!$H$76-参数输入表!$H$83)*参数输入表!$H$114/(1+参数输入表!$H$116) -> 331.26967 | T8: =(参数输入表!$H$76-参数输入表!$H$83)*参数输入表!$H$114/(1+参数输入表!$H$116) -> 331.26967 | U8: =(参数输入表!$H$76-参数输入表!$H$83)*参数输入表!$H$114/(1+参数输入表!$H$116) -> 331.26967 | V8: =(参数输入表!$H$76-参数输入表!$H$83)*参数输入表!$H$114/(1+参数输入表!$H$116) -> 331.26967 | W8: =(参数输入表!$H$76-参数输入表!$H$83)*参数输入表!$H$115/(1+参数输入表!$H$116) -> 441.69289 | X8: =(参数输入表!$H$76-参数输入表!$H$83)*参数输入表!$H$115/(1+参数输入表!$H$116) -> 441.69289 | Y8: =(参数输入表!$H$76-参数输入表!$H$83)*参数输入表!$H$115/(1+参数输入表!$H$116) -> 441.69289 | Z8: =(参数输入表!$H$76-参数输入表!$H$83)*参数输入表!$H$115/(1+参数输入表!$H$116) -> 441.69289 | AA8: =(参数输入表!$H$76-参数输入表!$H$83)*参数输入表!$H$115/(1+参数输入表!$H$116) -> 441.69289
B9: 1.3 | C9: 生产人员薪酬及福利 | D9: =SUM(F9:AA9) -> 2688 | E9: 万元 | H9: =(参数输入表!$H$127*参数输入表!$H$130+参数输入表!$H$128*参数输入表!$H$131)*(1+参数输入表!$H$132)*(1+参数输入表!$H$133*(H4-1))/(1+参数输入表!$H$134) -> 134.4 | I9: =(参数输入表!$H$127*参数输入表!$H$130+参数输入表!$H$128*参数输入表!$H$131)*(1+参数输入表!$H$132)*(1+参数输入表!$H$133*(I4-1))/(1+参数输入表!$H$134) -> 134.4 | J9: =(参数输入表!$H$127*参数输入表!$H$130+参数输入表!$H$128*参数输入表!$H$131)*(1+参数输入表!$H$132)*(1+参数输入表!$H$133*(J4-1))/(1+参数输入表!$H$134) -> 134.4 | K9: =(参数输入表!$H$127*参数输入表!$H$130+参数输入表!$H$128*参数输入表!$H$131)*(1+参数输入表!$H$132)*(1+参数输入表!$H$133*(K4-1))/(1+参数输入表!$H$134) -> 134.4 | L9: =(参数输入表!$H$127*参数输入表!$H$130+参数输入表!$H$128*参数输入表!$H$131)*(1+参数输入表!$H$132)*(1+参数输入表!$H$133*(L4-1))/(1+参数输入表!$H$134) -> 134.4 | M9: =(参数输入表!$H$127*参数输入表!$H$130+参数输入表!$H$128*参数输入表!$H$131)*(1+参数输入表!$H$132)*(1+参数输入表!$H$133*(M4-1))/(1+参数输入表!$H$134) -> 134.4 | N9: =(参数输入表!$H$127*参数输入表!$H$130+参数输入表!$H$128*参数输入表!$H$131)*(1+参数输入表!$H$132)*(1+参数输入表!$H$133*(N4-1))/(1+参数输入表!$H$134) -> 134.4 | O9: =(参数输入表!$H$127*参数输入表!$H$130+参数输入表!$H$128*参数输入表!$H$131)*(1+参数输入表!$H$132)*(1+参数输入表!$H$133*(O4-1))/(1+参数输入表!$H$134) -> 134.4 | ... AA9: =(参数输入表!$H$127*参数输入表!$H$130+参数输入表!$H$128*参数输入表!$H$131)*(1+参数输入表!$H$132)*(1+参数输入表!$H$133*(AA4-1))/(1+参数输入表!$H$134) -> 134.4
B10: 1.4 | C10: 长期待摊费用当期摊销 | D10: =SUM(F10:AA10) -> 0 | E10: 万元 | H10: ='表2-折旧摊销表'!H30 -> 0 | I10: ='表2-折旧摊销表'!I30 -> 0 | J10: ='表2-折旧摊销表'!J30 -> 0 | K10: ='表2-折旧摊销表'!K30 -> 0 | L10: ='表2-折旧摊销表'!L30 -> 0 | M10: ='表2-折旧摊销表'!M30 -> 0 | N10: ='表2-折旧摊销表'!N30 -> 0 | O10: ='表2-折旧摊销表'!O30 -> 0 | ... AA10: ='表2-折旧摊销表'!AA30 -> 0
B11: 1.5 | C11: 营业相关资产折旧及摊销 | D11: =SUM(F11:AA11) -> 21716.579 | E11: 万元 | H11: ='表2-折旧摊销表'!H27+'表2-折旧摊销表'!H33+'表2-折旧摊销表'!H36 -> 1420.8693 | I11: ='表2-折旧摊销表'!I27+'表2-折旧摊销表'!I33+'表2-折旧摊销表'!I36 -> 1420.8693 | J11: ='表2-折旧摊销表'!J27+'表2-折旧摊销表'!J33+'表2-折旧摊销表'!J36 -> 1420.8693 | K11: ='表2-折旧摊销表'!K27+'表2-折旧摊销表'!K33+'表2-折旧摊销表'!K36 -> 1420.8693 | L11: ='表2-折旧摊销表'!L27+'表2-折旧摊销表'!L33+'表2-折旧摊销表'!L36 -> 1420.8693 | M11: ='表2-折旧摊销表'!M27+'表2-折旧摊销表'!M33+'表2-折旧摊销表'!M36 -> 1420.8693 | N11: ='表2-折旧摊销表'!N27+'表2-折旧摊销表'!N33+'表2-折旧摊销表'!N36 -> 1420.8693 | O11: ='表2-折旧摊销表'!O27+'表2-折旧摊销表'!O33+'表2-折旧摊销表'!O36 -> 1420.8693 | ... AA11: ='表2-折旧摊销表'!AA27+'表2-折旧摊销表'!AA33+'表2-折旧摊销表'!AA36 -> 40.353982
B12: 1.6 | C12: 其他费用 | D12: =SUM(F12:AA12) -> 1500 | E12: 万元 | H12: =参数输入表!$H$135*参数输入表!$H$13/(1+参数输入表!$H$136) -> 75 | I12: =参数输入表!$H$135*参数输入表!$H$13/(1+参数输入表!$H$136) -> 75 | J12: =参数输入表!$H$135*参数输入表!$H$13/(1+参数输入表!$H$136) -> 75 | K12: =参数输入表!$H$135*参数输入表!$H$13/(1+参数输入表!$H$136) -> 75 | L12: =参数输入表!$H$135*参数输入表!$H$13/(1+参数输入表!$H$136) -> 75 | M12: =参数输入表!$H$135*参数输入表!$H$13/(1+参数输入表!$H$136) -> 75 | N12: =参数输入表!$H$135*参数输入表!$H$13/(1+参数输入表!$H$136) -> 75 | O12: =参数输入表!$H$135*参数输入表!$H$13/(1+参数输入表!$H$136) -> 75 | ... AA12: =参数输入表!$H$135*参数输入表!$H$13/(1+参数输入表!$H$136) -> 75
B13: 1.7 | C13: 储能费用 | D13: =SUM(F13:AA13) -> 0 | E13: 万元 | H13: =参数输入表!$H$145*参数输入表!$H$13*1000/10000/(1+参数输入表!$H$146) -> 0 | I13: =参数输入表!$H$145*参数输入表!$H$13*1000/10000/(1+参数输入表!$H$146) -> 0 | J13: =参数输入表!$H$145*参数输入表!$H$13*1000/10000/(1+参数输入表!$H$146) -> 0 | K13: =参数输入表!$H$145*参数输入表!$H$13*1000/10000/(1+参数输入表!$H$146) -> 0 | L13: =参数输入表!$H$145*参数输入表!$H$13*1000/10000/(1+参数输入表!$H$146) -> 0 | M13: =参数输入表!$H$145*参数输入表!$H$13*1000/10000/(1+参数输入表!$H$146) -> 0 | N13: =参数输入表!$H$145*参数输入表!$H$13*1000/10000/(1+参数输入表!$H$146) -> 0 | O13: =参数输入表!$H$145*参数输入表!$H$13*1000/10000/(1+参数输入表!$H$146) -> 0 | ... AA13: =参数输入表!$H$145*参数输入表!$H$13*1000/10000/(1+参数输入表!$H$146) -> 0
B14: 1.8 | C14: 场地租金费用 | D14: =SUM(F14:AA14) -> 0 | E14: 万元 | H14: =参数输入表!$H$138*参数输入表!$H$139/10000*(1)/(1+参数输入表!$H$140) -> 0 | I14: =参数输入表!$H$138*参数输入表!$H$139/10000*(1)/(1+参数输入表!$H$140) -> 0 | J14: =参数输入表!$H$138*参数输入表!$H$139/10000*(1)/(1+参数输入表!$H$140) -> 0 | K14: =参数输入表!$H$138*参数输入表!$H$139/10000*(1)/(1+参数输入表!$H$140) -> 0 | L14: =参数输入表!$H$138*参数输入表!$H$139/10000*(1)/(1+参数输入表!$H$140) -> 0 | M14: =参数输入表!$H$138*参数输入表!$H$139/10000*(1)/(1+参数输入表!$H$140) -> 0 | N14: =参数输入表!$H$138*参数输入表!$H$139/10000*(1)/(1+参数输入表!$H$140) -> 0 | O14: =参数输入表!$H$138*参数输入表!$H$139/10000*(1)/(1+参数输入表!$H$140) -> 0 | ... AA14: =参数输入表!$H$138*参数输入表!$H$139/10000*(1)/(1+参数输入表!$H$140) -> 0
B15: 2 | C15: 销售费用 | D15: =SUM(F15:AA15) -> 0 | E15: 万元 | H15: 0 | I15: 0 | J15: 0 | K15: 0 | L15: 0 | M15: 0 | N15: 0 | O15: 0 | P15: 0 | Q15: 0 | R15: 0 | S15: 0 | T15: 0 | U15: 0 | V15: 0 | W15: 0 | X15: 0 | Y15: 0 | Z15: 0 | AA15: 0
B16: 3 | C16: 管理费用 | D16: =SUM(F16:AA16) -> 1121.7389 | E16: 万元 | H16: =SUM(H17:H18) -> 56.086946 | I16: =SUM(I17:I18) -> 56.086946 | J16: =SUM(J17:J18) -> 56.086946 | K16: =SUM(K17:K18) -> 56.086946 | L16: =SUM(L17:L18) -> 56.086946 | M16: =SUM(M17:M18) -> 56.086946 | N16: =SUM(N17:N18) -> 56.086946 | O16: =SUM(O17:O18) -> 56.086946 | ... AA16: =SUM(AA17:AA18) -> 56.086946
B17: 3.1 | C17: 保险费 | D17: =SUM(F17:AA17) -> 1121.7389 | E17: 万元 | H17: ='表2-折旧摊销表'!$D$4*参数输入表!$H$120/(1+参数输入表!$H$124) -> 56.086946 | I17: ='表2-折旧摊销表'!$D$4*参数输入表!$H$120/(1+参数输入表!$H$124) -> 56.086946 | J17: ='表2-折旧摊销表'!$D$4*参数输入表!$H$120/(1+参数输入表!$H$124) -> 56.086946 | K17: ='表2-折旧摊销表'!$D$4*参数输入表!$H$120/(1+参数输入表!$H$124) -> 56.086946 | L17: ='表2-折旧摊销表'!$D$4*参数输入表!$H$120/(1+参数输入表!$H$124) -> 56.086946 | M17: ='表2-折旧摊销表'!$D$4*参数输入表!$H$121/(1+参数输入表!$H$124) -> 56.086946 | N17: ='表2-折旧摊销表'!$D$4*参数输入表!$H$121/(1+参数输入表!$H$124) -> 56.086946 | O17: ='表2-折旧摊销表'!$D$4*参数输入表!$H$121/(1+参数输入表!$H$124) -> 56.086946 | P17: ='表2-折旧摊销表'!$D$4*参数输入表!$H$121/(1+参数输入表!$H$124) -> 56.086946 | Q17: ='表2-折旧摊销表'!$D$4*参数输入表!$H$121/(1+参数输入表!$H$124) -> 56.086946 | R17: ='表2-折旧摊销表'!$D$4*参数输入表!$H$122/(1+参数输入表!$H$124) -> 56.086946 | S17: ='表2-折旧摊销表'!$D$4*参数输入表!$H$122/(1+参数输入表!$H$124) -> 56.086946 | T17: ='表2-折旧摊销表'!$D$4*参数输入表!$H$122/(1+参数输入表!$H$124) -> 56.086946 | U17: ='表2-折旧摊销表'!$D$4*参数输入表!$H$122/(1+参数输入表!$H$124) -> 56.086946 | V17: ='表2-折旧摊销表'!$D$4*参数输入表!$H$122/(1+参数输入表!$H$124) -> 56.086946 | W17: ='表2-折旧摊销表'!$D$4*参数输入表!$H$123/(1+参数输入表!$H$124) -> 56.086946 | X17: ='表2-折旧摊销表'!$D$4*参数输入表!$H$123/(1+参数输入表!$H$124) -> 56.086946 | Y17: ='表2-折旧摊销表'!$D$4*参数输入表!$H$123/(1+参数输入表!$H$124) -> 56.086946 | Z17: ='表2-折旧摊销表'!$D$4*参数输入表!$H$123/(1+参数输入表!$H$124) -> 56.086946 | AA17: ='表2-折旧摊销表'!$D$4*参数输入表!$H$123/(1+参数输入表!$H$124) -> 56.086946
B18: 3.2 | C18: 期末拆除费用 | D18: =SUM(F18:AA18) -> 0 | E18: 万元 | H18: 0 | I18: 0 | J18: 0 | K18: 0 | L18: 0 | M18: 0 | N18: 0 | O18: 0 | P18: 0 | Q18: 0 | R18: 0 | S18: 0 | T18: 0 | U18: 0 | V18: 0 | W18: 0 | X18: 0 | Y18: 0 | Z18: 0 | AA18: =参数输入表!H143*参数输入表!H142/(1+参数输入表!$H$144) -> 0
B19: 4 | C19: 研发费用 | D19: =SUM(F19:AA19) -> 0 | E19: 万元 | H19: 0 | I19: 0 | J19: 0 | K19: 0 | L19: 0 | M19: 0 | N19: 0 | O19: 0 | P19: 0 | Q19: 0 | R19: 0 | S19: 0 | T19: 0 | U19: 0 | V19: 0 | W19: 0 | X19: 0 | Y19: 0 | Z19: 0 | AA19: 0
B20: 5 | C20: 财务费用 | D20: =SUM(F20:AA20) -> 5768.0745 | E20: 万元 | H20: =SUM(H21:H23) -> 716.12681 | I20: =SUM(I21:I23) -> 668.60203 | J20: =SUM(J21:J23) -> 621.07724 | K20: =SUM(K21:K23) -> 573.55245 | L20: =SUM(L21:L23) -> 526.02766 | M20: =SUM(M21:M23) -> 478.50288 | N20: =SUM(N21:N23) -> 430.97809 | O20: =SUM(O21:O23) -> 383.4533 | ... AA20: =SUM(AA21:AA23) -> 3.255
B21: 5.1 | C21: 长期借款利息 | D21: =SUM(F21:AA21) -> 5702.9745 | E21: 万元 | H21: ='表1-资金筹措及还本付息表'!H43 -> 712.87181 | I21: ='表1-资金筹措及还本付息表'!I53 -> 665.34703 | J21: ='表1-资金筹措及还本付息表'!J53 -> 617.82224 | K21: ='表1-资金筹措及还本付息表'!K53 -> 570.29745 | L21: ='表1-资金筹措及还本付息表'!L53 -> 522.77266 | M21: ='表1-资金筹措及还本付息表'!M53 -> 475.24788 | N21: ='表1-资金筹措及还本付息表'!N53 -> 427.72309 | O21: ='表1-资金筹措及还本付息表'!O53 -> 380.1983 | P21: ='表1-资金筹措及还本付息表'!P53 -> 332.67351 | ... V21: ='表1-资金筹措及还本付息表'!V53 -> 47.524788 | W21: ='表1-资金筹措及还本付息表'!W43 -> 0 | X21: ='表1-资金筹措及还本付息表'!X43 -> 0 | Y21: ='表1-资金筹措及还本付息表'!Y43 -> 0 | Z21: ='表1-资金筹措及还本付息表'!Z43 -> 0 | AA21: ='表1-资金筹措及还本付息表'!AA43 -> 0
B22: 5.2 | C22: 流动资金利息 | D22: =SUM(F22:AA22) -> 65.1 | E22: 万元 | H22: ='表1-资金筹措及还本付息表'!H63 -> 3.255 | I22: ='表1-资金筹措及还本付息表'!I63 -> 3.255 | J22: ='表1-资金筹措及还本付息表'!J63 -> 3.255 | K22: ='表1-资金筹措及还本付息表'!K63 -> 3.255 | L22: ='表1-资金筹措及还本付息表'!L63 -> 3.255 | M22: ='表1-资金筹措及还本付息表'!M63 -> 3.255 | N22: ='表1-资金筹措及还本付息表'!N63 -> 3.255 | O22: ='表1-资金筹措及还本付息表'!O63 -> 3.255 | ... AA22: ='表1-资金筹措及还本付息表'!AA63 -> 3.255
B23: 5.3 | C23: 短期借款利息 | D23: =SUM(F23:AA23) -> 0 | E23: 万元 | H23: ='表1-资金筹措及还本付息表'!H73 -> 0 | I23: ='表1-资金筹措及还本付息表'!I73 -> 0 | J23: ='表1-资金筹措及还本付息表'!J73 -> 0 | K23: ='表1-资金筹措及还本付息表'!K73 -> 0 | L23: ='表1-资金筹措及还本付息表'!L73 -> 0 | M23: ='表1-资金筹措及还本付息表'!M73 -> 0 | N23: ='表1-资金筹措及还本付息表'!N73 -> 0 | O23: ='表1-资金筹措及还本付息表'!O73 -> 0 | ... AA23: ='表1-资金筹措及还本付息表'!AA73 -> 0
B24: 二 | C24: 营业外支出 | D24: =SUM(F24:AA24) -> 0 | E24: 万元 | H24: =参数输入表!$H$211/(1+参数输入表!$H$215) -> 0 | I24: =参数输入表!$H$211/(1+参数输入表!$H$215) -> 0 | J24: =参数输入表!$H$211/(1+参数输入表!$H$215) -> 0 | K24: =参数输入表!$H$211/(1+参数输入表!$H$215) -> 0 | L24: =参数输入表!$H$211/(1+参数输入表!$H$215) -> 0 | M24: =参数输入表!$H$211/(1+参数输入表!$H$215) -> 0 | N24: =参数输入表!$H$211/(1+参数输入表!$H$215) -> 0 | O24: =参数输入表!$H$211/(1+参数输入表!$H$215) -> 0 | ... AA24: =参数输入表!$H$211/(1+参数输入表!$H$215) -> 0
B26: 成本费用表-全投资
B27: 序号 | C27: 项目 | D27: 合计 | E27: 单位 | F27: 建设期 | H27: 运营期
F28: 1 | G28: 2 | H28: 1 | I28: 2 | J28: 3 | K28: 4 | L28: 5 | M28: 6 | N28: 7 | O28: 8 | P28: 9 | Q28: 10 | R28: 11 | S28: 12 | T28: 13 | U28: 14 | V28: 15 | W28: 16 | X28: 17 | Y28: 18 | Z28: 19 | AA28: 20
B29: 一 | C29: 营业总成本 | D29: =SUM(F29:AA29) -> 34347.479 | E29: 万元 | H29: =H30+H39+H40+H43 -> 1886.7795 | I29: =I30+I39+I40+I43 -> 1886.7795 | J29: =J30+J39+J40+J43 -> 1886.7795 | K29: =K30+K39+K40+K43 -> 1886.7795 | L29: =L30+L39+L40+L43 -> 1886.7795 | M29: =M30+M39+M40+M43 -> 1997.2027 | N29: =N30+N39+N40+N43 -> 1997.2027 | O29: =O30+O39+O40+O43 -> 1997.2027 | ... AA29: =AA30+AA39+AA40+AA43 -> 837.53382
B30: 1 | C30: 生产成本 | D30: =SUM(F30:AA30) -> 33225.74 | H30: =SUM(H31:H38) -> 1830.6925 | I30: =SUM(I31:I38) -> 1830.6925 | J30: =SUM(J31:J38) -> 1830.6925 | K30: =SUM(K31:K38) -> 1830.6925 | L30: =SUM(L31:L38) -> 1830.6925 | M30: =SUM(M31:M38) -> 1941.1157 | N30: =SUM(N31:N38) -> 1941.1157 | O30: =SUM(O31:O38) -> 1941.1157 | ... AA30: =SUM(AA31:AA38) -> 781.44688
B31: 1.1 | C31: 材料费 | D31: =SUM(F31:AA31) -> 1800 | E31: 万元 | H31: =参数输入表!$H$104*参数输入表!$H$13/(1+参数输入表!$H$108) -> 90 | I31: =参数输入表!$H$104*参数输入表!$H$13/(1+参数输入表!$H$108) -> 90 | J31: =参数输入表!$H$104*参数输入表!$H$13/(1+参数输入表!$H$108) -> 90 | K31: =参数输入表!$H$104*参数输入表!$H$13/(1+参数输入表!$H$108) -> 90 | L31: =参数输入表!$H$104*参数输入表!$H$13/(1+参数输入表!$H$108) -> 90 | M31: =参数输入表!$H$105*参数输入表!$H$13/(1+参数输入表!$H$108) -> 90 | N31: =参数输入表!$H$105*参数输入表!$H$13/(1+参数输入表!$H$108) -> 90 | O31: =参数输入表!$H$105*参数输入表!$H$13/(1+参数输入表!$H$108) -> 90 | P31: =参数输入表!$H$105*参数输入表!$H$13/(1+参数输入表!$H$108) -> 90 | Q31: =参数输入表!$H$105*参数输入表!$H$13/(1+参数输入表!$H$108) -> 90 | R31: =参数输入表!$H$106*参数输入表!$H$13/(1+参数输入表!$H$108) -> 90 | S31: =参数输入表!$H$106*参数输入表!$H$13/(1+参数输入表!$H$108) -> 90 | T31: =参数输入表!$H$106*参数输入表!$H$13/(1+参数输入表!$H$108) -> 90 | U31: =参数输入表!$H$106*参数输入表!$H$13/(1+参数输入表!$H$108) -> 90 | V31: =参数输入表!$H$106*参数输入表!$H$13/(1+参数输入表!$H$108) -> 90 | W31: =参数输入表!$H$107*参数输入表!$H$13/(1+参数输入表!$H$108) -> 90 | X31: =参数输入表!$H$107*参数输入表!$H$13/(1+参数输入表!$H$108) -> 90 | Y31: =参数输入表!$H$107*参数输入表!$H$13/(1+参数输入表!$H$108) -> 90 | Z31: =参数输入表!$H$107*参数输入表!$H$13/(1+参数输入表!$H$108) -> 90 | AA31: =参数输入表!$H$107*参数输入表!$H$13/(1+参数输入表!$H$108) -> 90
B32: 1.2 | C32: 维修费 | D32: =SUM(F32:AA32) -> 5521.1612 | E32: 万元 | H32: =(参数输入表!$H$76-参数输入表!$H$83)*参数输入表!$H$112/(1+参数输入表!$H$116) -> 110.42322 | I32: =(参数输入表!$H$76-参数输入表!$H$83)*参数输入表!$H$112/(1+参数输入表!$H$116) -> 110.42322 | J32: =(参数输入表!$H$76-参数输入表!$H$83)*参数输入表!$H$112/(1+参数输入表!$H$116) -> 110.42322 | K32: =(参数输入表!$H$76-参数输入表!$H$83)*参数输入表!$H$112/(1+参数输入表!$H$116) -> 110.42322 | L32: =(参数输入表!$H$76-参数输入表!$H$83)*参数输入表!$H$112/(1+参数输入表!$H$116) -> 110.42322 | M32: =(参数输入表!$H$76-参数输入表!$H$83)*参数输入表!$H$113/(1+参数输入表!$H$116) -> 220.84645 | N32: =(参数输入表!$H$76-参数输入表!$H$83)*参数输入表!$H$113/(1+参数输入表!$H$116) -> 220.84645 | O32: =(参数输入表!$H$76-参数输入表!$H$83)*参数输入表!$H$113/(1+参数输入表!$H$116) -> 220.84645 | P32: =(参数输入表!$H$76-参数输入表!$H$83)*参数输入表!$H$113/(1+参数输入表!$H$116) -> 220.84645 | Q32: =(参数输入表!$H$76-参数输入表!$H$83)*参数输入表!$H$113/(1+参数输入表!$H$116) -> 220.84645 | R32: =(参数输入表!$H$76-参数输入表!$H$83)*参数输入表!$H$114/(1+参数输入表!$H$116) -> 331.26967 | S32: =(参数输入表!$H$76-参数输入表!$H$83)*参数输入表!$H$114/(1+参数输入表!$H$116) -> 331.26967 | T32: =(参数输入表!$H$76-参数输入表!$H$83)*参数输入表!$H$114/(1+参数输入表!$H$116) -> 331.26967 | U32: =(参数输入表!$H$76-参数输入表!$H$83)*参数输入表!$H$114/(1+参数输入表!$H$116) -> 331.26967 | V32: =(参数输入表!$H$76-参数输入表!$H$83)*参数输入表!$H$114/(1+参数输入表!$H$116) -> 331.26967 | W32: =(参数输入表!$H$76-参数输入表!$H$83)*参数输入表!$H$115/(1+参数输入表!$H$116) -> 441.69289 | X32: =(参数输入表!$H$76-参数输入表!$H$83)*参数输入表!$H$115/(1+参数输入表!$H$116) -> 441.69289 | Y32: =(参数输入表!$H$76-参数输入表!$H$83)*参数输入表!$H$115/(1+参数输入表!$H$116) -> 441.69289 | Z32: =(参数输入表!$H$76-参数输入表!$H$83)*参数输入表!$H$115/(1+参数输入表!$H$116) -> 441.69289 | AA32: =(参数输入表!$H$76-参数输入表!$H$83)*参数输入表!$H$115/(1+参数输入表!$H$116) -> 441.69289
B33: 1.3 | C33: 生产人员薪酬及福利 | D33: =SUM(F33:AA33) -> 2688 | E33: 万元 | H33: =(参数输入表!$H$127*参数输入表!$H$130+参数输入表!$H$128*参数输入表!$H$131)*(1+参数输入表!$H$132)*(1+参数输入表!$H$133*(H28-1))/(1+参数输入表!$H$134) -> 134.4 | I33: =(参数输入表!$H$127*参数输入表!$H$130+参数输入表!$H$128*参数输入表!$H$131)*(1+参数输入表!$H$132)*(1+参数输入表!$H$133*(I28-1))/(1+参数输入表!$H$134) -> 134.4 | J33: =(参数输入表!$H$127*参数输入表!$H$130+参数输入表!$H$128*参数输入表!$H$131)*(1+参数输入表!$H$132)*(1+参数输入表!$H$133*(J28-1))/(1+参数输入表!$H$134) -> 134.4 | K33: =(参数输入表!$H$127*参数输入表!$H$130+参数输入表!$H$128*参数输入表!$H$131)*(1+参数输入表!$H$132)*(1+参数输入表!$H$133*(K28-1))/(1+参数输入表!$H$134) -> 134.4 | L33: =(参数输入表!$H$127*参数输入表!$H$130+参数输入表!$H$128*参数输入表!$H$131)*(1+参数输入表!$H$132)*(1+参数输入表!$H$133*(L28-1))/(1+参数输入表!$H$134) -> 134.4 | M33: =(参数输入表!$H$127*参数输入表!$H$130+参数输入表!$H$128*参数输入表!$H$131)*(1+参数输入表!$H$132)*(1+参数输入表!$H$133*(M28-1))/(1+参数输入表!$H$134) -> 134.4 | N33: =(参数输入表!$H$127*参数输入表!$H$130+参数输入表!$H$128*参数输入表!$H$131)*(1+参数输入表!$H$132)*(1+参数输入表!$H$133*(N28-1))/(1+参数输入表!$H$134) -> 134.4 | O33: =(参数输入表!$H$127*参数输入表!$H$130+参数输入表!$H$128*参数输入表!$H$131)*(1+参数输入表!$H$132)*(1+参数输入表!$H$133*(O28-1))/(1+参数输入表!$H$134) -> 134.4 | ... AA33: =(参数输入表!$H$127*参数输入表!$H$130+参数输入表!$H$128*参数输入表!$H$131)*(1+参数输入表!$H$132)*(1+参数输入表!$H$133*(AA28-1))/(1+参数输入表!$H$134) -> 134.4
B34: 1.4 | C34: 长期待摊费用当期摊销 | D34: =SUM(F34:AA34) -> 0 | E34: 万元 | H34: ='表2-折旧摊销表'!H58 -> 0 | I34: ='表2-折旧摊销表'!I58 -> 0 | J34: ='表2-折旧摊销表'!J58 -> 0 | K34: ='表2-折旧摊销表'!K58 -> 0 | L34: ='表2-折旧摊销表'!L58 -> 0 | M34: ='表2-折旧摊销表'!M58 -> 0 | N34: ='表2-折旧摊销表'!N58 -> 0 | O34: ='表2-折旧摊销表'!O58 -> 0 | ... AA34: ='表2-折旧摊销表'!AA58 -> 0
B35: 1.5 | C35: 营业相关资产折旧及摊销 | D35: =SUM(F35:AA35) -> 21716.579 | E35: 万元 | H35: ='表2-折旧摊销表'!H55+'表2-折旧摊销表'!H61+'表2-折旧摊销表'!H64 -> 1420.8693 | I35: ='表2-折旧摊销表'!I55+'表2-折旧摊销表'!I61+'表2-折旧摊销表'!I64 -> 1420.8693 | J35: ='表2-折旧摊销表'!J55+'表2-折旧摊销表'!J61+'表2-折旧摊销表'!J64 -> 1420.8693 | K35: ='表2-折旧摊销表'!K55+'表2-折旧摊销表'!K61+'表2-折旧摊销表'!K64 -> 1420.8693 | L35: ='表2-折旧摊销表'!L55+'表2-折旧摊销表'!L61+'表2-折旧摊销表'!L64 -> 1420.8693 | M35: ='表2-折旧摊销表'!M55+'表2-折旧摊销表'!M61+'表2-折旧摊销表'!M64 -> 1420.8693 | N35: ='表2-折旧摊销表'!N55+'表2-折旧摊销表'!N61+'表2-折旧摊销表'!N64 -> 1420.8693 | O35: ='表2-折旧摊销表'!O55+'表2-折旧摊销表'!O61+'表2-折旧摊销表'!O64 -> 1420.8693 | ... AA35: ='表2-折旧摊销表'!AA55+'表2-折旧摊销表'!AA61+'表2-折旧摊销表'!AA64 -> 40.353982
B36: 1.6 | C36: 其他费用 | D36: =SUM(F36:AA36) -> 1500 | E36: 万元 | H36: =参数输入表!$H$135*参数输入表!$H$13/(1+参数输入表!$H$136) -> 75 | I36: =参数输入表!$H$135*参数输入表!$H$13/(1+参数输入表!$H$136) -> 75 | J36: =参数输入表!$H$135*参数输入表!$H$13/(1+参数输入表!$H$136) -> 75 | K36: =参数输入表!$H$135*参数输入表!$H$13/(1+参数输入表!$H$136) -> 75 | L36: =参数输入表!$H$135*参数输入表!$H$13/(1+参数输入表!$H$136) -> 75 | M36: =参数输入表!$H$135*参数输入表!$H$13/(1+参数输入表!$H$136) -> 75 | N36: =参数输入表!$H$135*参数输入表!$H$13/(1+参数输入表!$H$136) -> 75 | O36: =参数输入表!$H$135*参数输入表!$H$13/(1+参数输入表!$H$136) -> 75 | ... AA36: =参数输入表!$H$135*参数输入表!$H$13/(1+参数输入表!$H$136) -> 75
B37: 1.7 | C37: 储能费用 | D37: =SUM(F37:AA37) -> 0 | E37: 万元 | H37: =参数输入表!$H$145*参数输入表!$H$13*1000/10000/(1+参数输入表!$H$146) -> 0 | I37: =参数输入表!$H$145*参数输入表!$H$13*1000/10000/(1+参数输入表!$H$146) -> 0 | J37: =参数输入表!$H$145*参数输入表!$H$13*1000/10000/(1+参数输入表!$H$146) -> 0 | K37: =参数输入表!$H$145*参数输入表!$H$13*1000/10000/(1+参数输入表!$H$146) -> 0 | L37: =参数输入表!$H$145*参数输入表!$H$13*1000/10000/(1+参数输入表!$H$146) -> 0 | M37: =参数输入表!$H$145*参数输入表!$H$13*1000/10000/(1+参数输入表!$H$146) -> 0 | N37: =参数输入表!$H$145*参数输入表!$H$13*1000/10000/(1+参数输入表!$H$146) -> 0 | O37: =参数输入表!$H$145*参数输入表!$H$13*1000/10000/(1+参数输入表!$H$146) -> 0 | ... AA37: =参数输入表!$H$145*参数输入表!$H$13*1000/10000/(1+参数输入表!$H$146) -> 0
B38: 1.8 | C38: 场地租金费用 | D38: =SUM(F38:AA38) -> 0 | E38: 万元 | H38: =参数输入表!$H$138*参数输入表!$H$139/10000*(1+0)/(1+参数输入表!$H$140) -> 0 | I38: =参数输入表!$H$138*参数输入表!$H$139/10000*(1+0)/(1+参数输入表!$H$140) -> 0 | J38: =参数输入表!$H$138*参数输入表!$H$139/10000*(1+0)/(1+参数输入表!$H$140) -> 0 | K38: =参数输入表!$H$138*参数输入表!$H$139/10000*(1+0)/(1+参数输入表!$H$140) -> 0 | L38: =参数输入表!$H$138*参数输入表!$H$139/10000*(1+0)/(1+参数输入表!$H$140) -> 0 | M38: =参数输入表!$H$138*参数输入表!$H$139/10000*(1+0)/(1+参数输入表!$H$140) -> 0 | N38: =参数输入表!$H$138*参数输入表!$H$139/10000*(1+0)/(1+参数输入表!$H$140) -> 0 | O38: =参数输入表!$H$138*参数输入表!$H$139/10000*(1+0)/(1+参数输入表!$H$140) -> 0 | ... AA38: =参数输入表!$H$138*参数输入表!$H$139/10000*(1+0)/(1+参数输入表!$H$140) -> 0
B39: 2 | C39: 销售费用 | D39: =SUM(F39:AA39) -> 0 | E39: 万元 | H39: 0 | I39: 0 | J39: 0 | K39: 0 | L39: 0 | M39: 0 | N39: 0 | O39: 0 | P39: 0 | Q39: 0 | R39: 0 | S39: 0 | T39: 0 | U39: 0 | V39: 0 | W39: 0 | X39: 0 | Y39: 0 | Z39: 0 | AA39: 0
B40: 3 | C40: 管理费用 | D40: =SUM(F40:AA40) -> 1121.7389 | E40: 万元 | H40: =SUM(H41:H42) -> 56.086946 | I40: =SUM(I41:I42) -> 56.086946 | J40: =SUM(J41:J42) -> 56.086946 | K40: =SUM(K41:K42) -> 56.086946 | L40: =SUM(L41:L42) -> 56.086946 | M40: =SUM(M41:M42) -> 56.086946 | N40: =SUM(N41:N42) -> 56.086946 | O40: =SUM(O41:O42) -> 56.086946 | ... AA40: =SUM(AA41:AA42) -> 56.086946
B41: 3.1 | C41: 保险费 | D41: =SUM(F41:AA41) -> 1121.7389 | E41: 万元 | H41: ='表2-折旧摊销表'!$D$4*参数输入表!$H$120/(1+参数输入表!$H$124) -> 56.086946 | I41: ='表2-折旧摊销表'!$D$4*参数输入表!$H$120/(1+参数输入表!$H$124) -> 56.086946 | J41: ='表2-折旧摊销表'!$D$4*参数输入表!$H$120/(1+参数输入表!$H$124) -> 56.086946 | K41: ='表2-折旧摊销表'!$D$4*参数输入表!$H$120/(1+参数输入表!$H$124) -> 56.086946 | L41: ='表2-折旧摊销表'!$D$4*参数输入表!$H$120/(1+参数输入表!$H$124) -> 56.086946 | M41: ='表2-折旧摊销表'!$D$4*参数输入表!$H$121/(1+参数输入表!$H$124) -> 56.086946 | N41: ='表2-折旧摊销表'!$D$4*参数输入表!$H$121/(1+参数输入表!$H$124) -> 56.086946 | O41: ='表2-折旧摊销表'!$D$4*参数输入表!$H$121/(1+参数输入表!$H$124) -> 56.086946 | P41: ='表2-折旧摊销表'!$D$4*参数输入表!$H$121/(1+参数输入表!$H$124) -> 56.086946 | Q41: ='表2-折旧摊销表'!$D$4*参数输入表!$H$121/(1+参数输入表!$H$124) -> 56.086946 | R41: ='表2-折旧摊销表'!$D$4*参数输入表!$H$122/(1+参数输入表!$H$124) -> 56.086946 | S41: ='表2-折旧摊销表'!$D$4*参数输入表!$H$122/(1+参数输入表!$H$124) -> 56.086946 | T41: ='表2-折旧摊销表'!$D$4*参数输入表!$H$122/(1+参数输入表!$H$124) -> 56.086946 | U41: ='表2-折旧摊销表'!$D$4*参数输入表!$H$122/(1+参数输入表!$H$124) -> 56.086946 | V41: ='表2-折旧摊销表'!$D$4*参数输入表!$H$122/(1+参数输入表!$H$124) -> 56.086946 | W41: ='表2-折旧摊销表'!$D$4*参数输入表!$H$123/(1+参数输入表!$H$124) -> 56.086946 | X41: ='表2-折旧摊销表'!$D$4*参数输入表!$H$123/(1+参数输入表!$H$124) -> 56.086946 | Y41: ='表2-折旧摊销表'!$D$4*参数输入表!$H$123/(1+参数输入表!$H$124) -> 56.086946 | Z41: ='表2-折旧摊销表'!$D$4*参数输入表!$H$123/(1+参数输入表!$H$124) -> 56.086946 | AA41: ='表2-折旧摊销表'!$D$4*参数输入表!$H$123/(1+参数输入表!$H$124) -> 56.086946
B42: 3.2 | C42: 期末拆除费用 | D42: =SUM(F42:AA42) -> 0 | E42: 万元 | H42: 0 | I42: 0 | J42: 0 | K42: 0 | L42: 0 | M42: 0 | N42: 0 | O42: 0 | P42: 0 | Q42: 0 | R42: 0 | S42: 0 | T42: 0 | U42: 0 | V42: 0 | W42: 0 | X42: 0 | Y42: 0 | Z42: 0 | AA42: =参数输入表!H143*参数输入表!H142/(1+参数输入表!$H$144) -> 0
B43: 4 | C43: 研发费用 | D43: =SUM(F43:AA43) -> 0 | E43: 万元 | H43: 0 | I43: 0 | J43: 0 | K43: 0 | L43: 0 | M43: 0 | N43: 0 | O43: 0 | P43: 0 | Q43: 0 | R43: 0 | S43: 0 | T43: 0 | U43: 0 | V43: 0 | W43: 0 | X43: 0 | Y43: 0 | Z43: 0 | AA43: 0
B44: 二 | C44: 营业外支出 | D44: =SUM(F44:AA44) -> 0 | E44: 万元 | H44: =参数输入表!$H$211/(1+参数输入表!$H$215) -> 0 | I44: =参数输入表!$H$211/(1+参数输入表!$H$215) -> 0 | J44: =参数输入表!$H$211/(1+参数输入表!$H$215) -> 0 | K44: =参数输入表!$H$211/(1+参数输入表!$H$215) -> 0 | L44: =参数输入表!$H$211/(1+参数输入表!$H$215) -> 0 | M44: =参数输入表!$H$211/(1+参数输入表!$H$215) -> 0 | N44: =参数输入表!$H$211/(1+参数输入表!$H$215) -> 0 | O44: =参数输入表!$H$211/(1+参数输入表!$H$215) -> 0 | ... AA44: =参数输入表!$H$211/(1+参数输入表!$H$215) -> 0
B47: 成本现金支出表（隐藏）
B48: 一 | C48: 生产经营现金支出合计 | D48: =SUM(F48:AA48) -> 12630.9 | E48: 万元 | H48: =H49+H57+H58+H61 -> 465.91017 | I48: =I49+I57+I58+I61 -> 465.91017 | J48: =J49+J57+J58+J61 -> 465.91017 | K48: =K49+K57+K58+K61 -> 465.91017 | L48: =L49+L57+L58+L61 -> 465.91017 | M48: =M49+M57+M58+M61 -> 576.33339 | N48: =N49+N57+N58+N61 -> 576.33339 | O48: =O49+O57+O58+O61 -> 576.33339 | ... AA48: =AA49+AA57+AA58+AA61 -> 797.17984
B49: 1 | C49: 生产相关现金支出 | D49: =SUM(F49:AA49) -> 11509.161 | E49: 万元 | H49: =SUM(H50:H56) -> 409.82322 | I49: =SUM(I50:I56) -> 409.82322 | J49: =SUM(J50:J56) -> 409.82322 | K49: =SUM(K50:K56) -> 409.82322 | L49: =SUM(L50:L56) -> 409.82322 | M49: =SUM(M50:M56) -> 520.24645 | N49: =SUM(N50:N56) -> 520.24645 | O49: =SUM(O50:O56) -> 520.24645 | ... AA49: =SUM(AA50:AA56) -> 741.09289
B50: 1.1 | C50: 材料费 | D50: =SUM(F50:AA50) -> 1800 | E50: 万元 | H50: =H31 -> 90 | I50: =I31 -> 90 | J50: =J31 -> 90 | K50: =K31 -> 90 | L50: =L31 -> 90 | M50: =M31 -> 90 | N50: =N31 -> 90 | O50: =O31 -> 90 | ... AA50: =AA31 -> 90
B51: 1.2 | C51: 维修费 | D51: =SUM(F51:AA51) -> 5521.1612 | E51: 万元 | H51: =H32 -> 110.42322 | I51: =I32 -> 110.42322 | J51: =J32 -> 110.42322 | K51: =K32 -> 110.42322 | L51: =L32 -> 110.42322 | M51: =M32 -> 220.84645 | N51: =N32 -> 220.84645 | O51: =O32 -> 220.84645 | ... AA51: =AA32 -> 441.69289
B52: 1.3 | C52: 生产人员薪酬及福利 | D52: =SUM(F52:AA52) -> 2688 | E52: 万元 | H52: =H33 -> 134.4 | I52: =I33 -> 134.4 | J52: =J33 -> 134.4 | K52: =K33 -> 134.4 | L52: =L33 -> 134.4 | M52: =M33 -> 134.4 | N52: =N33 -> 134.4 | O52: =O33 -> 134.4 | ... AA52: =AA33 -> 134.4
B53: 1.4 | C53: 长期待摊实际支出 | D53: =SUM(F53:AA53) -> 0 | E53: 万元 | H53: =H34 -> 0 | I53: =I34 -> 0 | J53: =J34 -> 0 | K53: =K34 -> 0 | L53: =L34 -> 0 | M53: =M34 -> 0 | N53: =N34 -> 0 | O53: =O34 -> 0 | ... AA53: =AA34 -> 0
B54: 1.5 | C54: 其他费用 | D54: =SUM(F54:AA54) -> 1500 | E54: 万元 | H54: =H36 -> 75 | I54: =I36 -> 75 | J54: =J36 -> 75 | K54: =K36 -> 75 | L54: =L36 -> 75 | M54: =M36 -> 75 | N54: =N36 -> 75 | O54: =O36 -> 75 | ... AA54: =AA36 -> 75
B55: 1.6 | C55: 储能费用 | D55: =SUM(F55:AA55) -> 0 | E55: 万元 | H55: =H37 -> 0 | I55: =I37 -> 0 | J55: =J37 -> 0 | K55: =K37 -> 0 | L55: =L37 -> 0 | M55: =M37 -> 0 | N55: =N37 -> 0 | O55: =O37 -> 0 | ... AA55: =AA37 -> 0
B56: 1.7 | C56: 场地租金费用 | D56: =SUM(F56:AA56) -> 0 | E56: 万元 | H56: =H38 -> 0 | I56: =I38 -> 0 | J56: =J38 -> 0 | K56: =K38 -> 0 | L56: =L38 -> 0 | M56: =M38 -> 0 | N56: =N38 -> 0 | O56: =O38 -> 0 | ... AA56: =AA38 -> 0
B57: 2 | C57: 销售费用现金支出 | D57: =SUM(F57:AA57) -> 0 | E57: 万元 | H57: 0 | I57: 0 | J57: 0 | K57: 0 | L57: 0 | M57: 0 | N57: 0 | O57: 0 | P57: 0 | Q57: 0 | R57: 0 | S57: 0 | T57: 0 | U57: 0 | V57: 0 | W57: 0 | X57: 0 | Y57: 0 | Z57: 0 | AA57: 0
B58: 3 | C58: 管理费用现金支出 | D58: =SUM(F58:AA58) -> 1121.7389 | E58: 万元 | H58: =SUM(H59:H60) -> 56.086946 | I58: =SUM(I59:I60) -> 56.086946 | J58: =SUM(J59:J60) -> 56.086946 | K58: =SUM(K59:K60) -> 56.086946 | L58: =SUM(L59:L60) -> 56.086946 | M58: =SUM(M59:M60) -> 56.086946 | N58: =SUM(N59:N60) -> 56.086946 | O58: =SUM(O59:O60) -> 56.086946 | ... AA58: =SUM(AA59:AA60) -> 56.086946
B59: 3.1 | C59: 保险费 | D59: =SUM(F59:AA59) -> 1121.7389 | E59: 万元 | H59: =H41 -> 56.086946 | I59: =I41 -> 56.086946 | J59: =J41 -> 56.086946 | K59: =K41 -> 56.086946 | L59: =L41 -> 56.086946 | M59: =M41 -> 56.086946 | N59: =N41 -> 56.086946 | O59: =O41 -> 56.086946 | ... AA59: =AA41 -> 56.086946
B60: 3.2 | C60: 期末拆除费用 | D60: =SUM(F60:AA60) -> 0 | E60: 万元 | H60: 0 | I60: 0 | J60: 0 | K60: 0 | L60: 0 | M60: 0 | N60: 0 | O60: 0 | P60: 0 | Q60: 0 | R60: 0 | S60: 0 | T60: 0 | U60: 0 | V60: 0 | W60: 0 | X60: 0 | Y60: 0 | Z60: 0 | AA60: =参数输入表!H143*参数输入表!H142 -> 0
B61: 4 | C61: 研发费用现金支出 | D61: =SUM(F61:AA61) -> 0 | E61: 万元 | H61: 0 | I61: 0 | J61: 0 | K61: 0 | L61: 0 | M61: 0 | N61: 0 | O61: 0 | P61: 0 | Q61: 0 | R61: 0 | S61: 0 | T61: 0 | U61: 0 | V61: 0 | W61: 0 | X61: 0 | Y61: 0 | Z61: 0 | AA61: 0
B62: 二 | C62: 营业外现金支出 | D62: =SUM(F62:AA62) -> 0 | E62: 万元 | H62: =H44 -> 0 | I62: =I44 -> 0 | J62: =J44 -> 0 | K62: =K44 -> 0 | L62: =L44 -> 0 | M62: =M44 -> 0 | N62: =N44 -> 0 | O62: =O44 -> 0 | ... AA62: =AA44 -> 0

Sheet 表4-收入税金表
B2: 收入表
B3: 序号 | C3: 项目 | D3: 合计 | E3: 单位 | F3: 建设期 | H3: 运营期
F4: 1 | G4: 2 | H4: 1 | I4: 2 | J4: 3 | K4: 4 | L4: 5 | M4: 6 | N4: 7 | O4: 8 | P4: 9 | Q4: 10 | R4: 11 | S4: 12 | T4: 13 | U4: 14 | V4: 15 | W4: 16 | X4: 17 | Y4: 18 | Z4: 19 | AA4: 20
B5: 1 | C5: 营业收入 | D5: =SUM(F5:AA5) -> 55978.052 | E5: 万元 | H5: =H6+H16 -> 2781.8166 | I5: =I6+I16 -> 2781.8166 | J5: =J6+J16 -> 2781.8166 | K5: =K6+K16 -> 2781.8166 | L5: =L6+L16 -> 2781.8166 | M5: =M6+M16 -> 2804.5979 | N5: =N6+N16 -> 2804.5979 | O5: =O6+O16 -> 2804.5979 | ... AA5: =AA6+AA16 -> 2804.5979
B6: 1.1 | C6: 发电销售收入 | D6: =SUM(F6:AA6) -> 55978.052 | E6: 万元 | H6: =(H9*H10-H11-H12)/(1+参数输入表!$H$233)+(H14*H15)/(1+参数输入表!$H$237) -> 2781.8166 | I6: =(I9*I10-I11-I12)/(1+参数输入表!$H$233)+(I14*I15)/(1+参数输入表!$H$237) -> 2781.8166 | J6: =(J9*J10-J11-J12)/(1+参数输入表!$H$233)+(J14*J15)/(1+参数输入表!$H$237) -> 2781.8166 | K6: =(K9*K10-K11-K12)/(1+参数输入表!$H$233)+(K14*K15)/(1+参数输入表!$H$237) -> 2781.8166 | L6: =(L9*L10-L11-L12)/(1+参数输入表!$H$233)+(L14*L15)/(1+参数输入表!$H$237) -> 2781.8166 | M6: =(M9*M10-M11-M12)/(1+参数输入表!$H$233)+(M14*M15)/(1+参数输入表!$H$237) -> 2804.5979 | N6: =(N9*N10-N11-N12)/(1+参数输入表!$H$233)+(N14*N15)/(1+参数输入表!$H$237) -> 2804.5979 | O6: =(O9*O10-O11-O12)/(1+参数输入表!$H$233)+(O14*O15)/(1+参数输入表!$H$237) -> 2804.5979 | ... AA6: =(AA9*AA10-AA11-AA12)/(1+参数输入表!$H$233)+(AA14*AA15)/(1+参数输入表!$H$237) -> 2804.5979
C7: 发电量 | D7: =SUM(F7:AA7) -> 213854 | E7: 万度 | H7: =参数输入表!H17/10 -> 10692.7 | I7: =H7 -> 10692.7 | J7: =I7 -> 10692.7 | K7: =J7 -> 10692.7 | L7: =K7 -> 10692.7 | M7: =L7 -> 10692.7 | N7: =M7 -> 10692.7 | O7: =N7 -> 10692.7 | P7: =O7 -> 10692.7 | ... AA7: =Z7 -> 10692.7
C8: 上网售电收入 | D8: =SUM(F8:AA8) -> 19074.043 | E8: 万元 | H8: =H9*H10/1.13 -> 1362.4317 | I8: =I9*I10/1.13 -> 1362.4317 | J8: =J9*J10/1.13 -> 1362.4317 | K8: =K9*K10/1.13 -> 1362.4317 | L8: =L9*L10/1.13 -> 1362.4317 | M8: =M9*M10/1.13 -> 817.459 | N8: =N9*N10/1.13 -> 817.459 | O8: =O9*O10/1.13 -> 817.459 | ... AA8: =AA9*AA10/1.13 -> 817.459
C9: 上网电量 | D9: =SUM(F9:AA9) -> 70807.059 | E9: 万度 | H9: =参数输入表!H19/10 -> 5057.6471 | I9: =参数输入表!H20/10 -> 5057.6471 | J9: =参数输入表!H21/10 -> 5057.6471 | K9: =参数输入表!H22/10 -> 5057.6471 | L9: =参数输入表!H23/10 -> 5057.6471 | M9: =参数输入表!H24/10 -> 3034.5883 | N9: =参数输入表!H25/10 -> 3034.5883 | O9: =参数输入表!H26/10 -> 3034.5883 | P9: =参数输入表!H27/10 -> 3034.5883 | Q9: =参数输入表!H28/10 -> 3034.5883 | R9: =参数输入表!H29/10 -> 3034.5883 | S9: =参数输入表!H30/10 -> 3034.5883 | T9: =参数输入表!H31/10 -> 3034.5883 | U9: =参数输入表!H32/10 -> 3034.5883 | V9: =参数输入表!H33/10 -> 3034.5883 | W9: =参数输入表!H34/10 -> 3034.5883 | X9: =参数输入表!H35/10 -> 3034.5883 | Y9: =参数输入表!H36/10 -> 3034.5883 | Z9: =参数输入表!H37/10 -> 3034.5883 | AA9: =参数输入表!H38/10 -> 3034.5883
C10: 上网电价（含税） | E10: 元/度 | H10: =参数输入表!$H$40 -> 0.3044 | I10: =参数输入表!$H$40 -> 0.3044 | J10: =参数输入表!$H$40 -> 0.3044 | K10: =参数输入表!$H$40 -> 0.3044 | L10: =参数输入表!$H$40 -> 0.3044 | M10: =参数输入表!$H$40 -> 0.3044 | N10: =参数输入表!$H$40 -> 0.3044 | O10: =参数输入表!$H$40 -> 0.3044 | ... AA10: =参数输入表!$H$40 -> 0.3044
C11: 电网辅助服务分摊 | D11: =SUM(F11:AA11) -> 0 | E11: 万元 | H11: =H9*参数输入表!$H$226 -> 0 | I11: =I9*参数输入表!$H$226 -> 0 | J11: =J9*参数输入表!$H$226 -> 0 | K11: =K9*参数输入表!$H$226 -> 0 | L11: =L9*参数输入表!$H$226 -> 0 | M11: =M9*参数输入表!$H$226 -> 0 | N11: =N9*参数输入表!$H$226 -> 0 | O11: =O9*参数输入表!$H$226 -> 0 | ... AA11: =AA9*参数输入表!$H$226 -> 0
C12: 两个细则考核 | D12: =SUM(F12:AA12) -> 0 | E12: 万元 | H12: =H9*参数输入表!$H$230 -> 0 | I12: =I9*参数输入表!$H$230 -> 0 | J12: =J9*参数输入表!$H$230 -> 0 | K12: =K9*参数输入表!$H$230 -> 0 | L12: =L9*参数输入表!$H$230 -> 0 | M12: =M9*参数输入表!$H$230 -> 0 | N12: =N9*参数输入表!$H$230 -> 0 | O12: =O9*参数输入表!$H$230 -> 0 | ... AA12: =AA9*参数输入表!$H$230 -> 0
C13: 数能融合售电收入 | D13: =SUM(H13:AA13) -> 36904.009 | H13: =H14*H15/1.13 -> 1419.385 | I13: =I14*I15/1.13 -> 1419.385 | J13: =J14*J15/1.13 -> 1419.385 | K13: =K14*K15/1.13 -> 1419.385 | L13: =L14*L15/1.13 -> 1419.385 | M13: =M14*M15/1.13 -> 1987.1389 | N13: =N14*N15/1.13 -> 1987.1389 | O13: =O14*O15/1.13 -> 1987.1389 | ... AA13: =AA14*AA15/1.13 -> 1987.1389
C14: 数能融合消纳电量 | D14: =SUM(F14:AA14) -> 139005.1 | E14: 万度 | H14: =参数输入表!H45*参数输入表!$H$17/10 -> 5346.35 | I14: =参数输入表!H46*参数输入表!$H$17/10 -> 5346.35 | J14: =参数输入表!H47*参数输入表!$H$17/10 -> 5346.35 | K14: =参数输入表!H48*参数输入表!$H$17/10 -> 5346.35 | L14: =参数输入表!H49*参数输入表!$H$17/10 -> 5346.35 | M14: =参数输入表!H50*参数输入表!$H$17/10 -> 7484.89 | N14: =参数输入表!H51*参数输入表!$H$17/10 -> 7484.89 | O14: =参数输入表!H52*参数输入表!$H$17/10 -> 7484.89 | P14: =参数输入表!H53*参数输入表!$H$17/10 -> 7484.89 | Q14: =参数输入表!H54*参数输入表!$H$17/10 -> 7484.89 | R14: =参数输入表!H55*参数输入表!$H$17/10 -> 7484.89 | S14: =参数输入表!H56*参数输入表!$H$17/10 -> 7484.89 | T14: =参数输入表!H57*参数输入表!$H$17/10 -> 7484.89 | U14: =参数输入表!H58*参数输入表!$H$17/10 -> 7484.89 | V14: =参数输入表!H59*参数输入表!$H$17/10 -> 7484.89 | W14: =参数输入表!H60*参数输入表!$H$17/10 -> 7484.89 | X14: =参数输入表!H61*参数输入表!$H$17/10 -> 7484.89 | Y14: =参数输入表!H62*参数输入表!$H$17/10 -> 7484.89 | Z14: =参数输入表!H63*参数输入表!$H$17/10 -> 7484.89 | AA14: =参数输入表!H64*参数输入表!$H$17/10 -> 7484.89
C15: 数能融合机制电价（含税） | E15: 元/度 | H15: =参数输入表!H66 -> 0.3 | I15: =H15 -> 0.3 | J15: =I15 -> 0.3 | K15: =J15 -> 0.3 | L15: =K15 -> 0.3 | M15: =L15 -> 0.3 | N15: =M15 -> 0.3 | O15: =N15 -> 0.3 | P15: =O15 -> 0.3 | ... AA15: =Z15 -> 0.3
B16: 2 | C16: 其他收入 | D16: =SUM(F16:AA16) -> 0 | E16: 万元 | H16: =(参数输入表!$H$239*参数输入表!$H$240)/(1+参数输入表!$H$241) -> 0 | I16: =(参数输入表!$H$239*参数输入表!$H$240)/(1+参数输入表!$H$241) -> 0 | J16: =(参数输入表!$H$239*参数输入表!$H$240)/(1+参数输入表!$H$241) -> 0 | K16: =(参数输入表!$H$239*参数输入表!$H$240)/(1+参数输入表!$H$241) -> 0 | L16: =(参数输入表!$H$239*参数输入表!$H$240)/(1+参数输入表!$H$241) -> 0 | M16: =(参数输入表!$H$239*参数输入表!$H$240)/(1+参数输入表!$H$241) -> 0 | N16: =(参数输入表!$H$239*参数输入表!$H$240)/(1+参数输入表!$H$241) -> 0 | O16: =(参数输入表!$H$239*参数输入表!$H$240)/(1+参数输入表!$H$241) -> 0 | ... AA16: =(参数输入表!$H$239*参数输入表!$H$240)/(1+参数输入表!$H$241) -> 0
B17: 3 | C17: 营业外收入 | D17: =SUM(F17:AA17) -> 2452.1051 | E17: 万元 | H17: =SUM(H18:H19) -> 0 | I17: =SUM(I18:I19) -> 0 | J17: =SUM(J18:J19) -> 0 | K17: =SUM(K18:K19) -> 0 | L17: =SUM(L18:L19) -> 0 | M17: =SUM(M18:M19) -> 0 | N17: =SUM(N18:N19) -> 109.83049 | O17: =SUM(O18:O19) -> 182.29887 | ... AA17: =SUM(AA18:AA19) -> 182.29887
B18: 3.1 | C18: 政府一次性运营补贴收入 | D18: =SUM(F18:AA18) -> 0 | E18: 万元 | H18: =参数输入表!H244 -> 0
B19: 3.2 | C19: 增值税即征即退 | D19: =SUM(F19:AA19) -> 2452.1051 | E19: 万元 | H19: =H22*参数输入表!$H$267 -> 0 | I19: =I22*参数输入表!$H$267 -> 0 | J19: =J22*参数输入表!$H$267 -> 0 | K19: =K22*参数输入表!$H$267 -> 0 | L19: =L22*参数输入表!$H$267 -> 0 | M19: =M22*参数输入表!$H$267 -> 0 | N19: =N22*参数输入表!$H$267 -> 109.83049 | O19: =O22*参数输入表!$H$267 -> 182.29887 | ... AA19: =AA22*参数输入表!$H$267 -> 182.29887
B21: 税金表
B22: 1 | C22: 当期实缴增值税 | D22: =SUM(F22:AA22) -> 4904.2102 | E22: 万元 | F22: 0 | G22: =IF(G45>0,0,G44-F45) -> 0 | H22: =IF(H45>0,0,H44-G45) -> 0 | I22: =IF(I45>0,0,I44-H45) -> 0 | J22: =IF(J45>0,0,J44-I45) -> 0 | K22: =IF(K45>0,0,K44-J45) -> 0 | L22: =IF(L45>0,0,L44-K45) -> 0 | M22: =IF(M45>0,0,M44-L45) -> 0 | N22: =IF(N45>0,0,N44-M45) -> 219.66098 | ... AA22: =IF(AA45>0,0,AA44-Z45) -> 364.59773
B23: 2 | C23: 增值税销项税 | D23: =SUM(F23:AA23) -> 7277.1468 | E23: 万元 | F23: =SUM(F24:F25) -> 0 | G23: =SUM(G24:G25) -> 0 | H23: =SUM(H24:H25) -> 361.63616 | I23: =SUM(I24:I25) -> 361.63616 | J23: =SUM(J24:J25) -> 361.63616 | K23: =SUM(K24:K25) -> 361.63616 | L23: =SUM(L24:L25) -> 361.63616 | M23: =SUM(M24:M25) -> 364.59773 | ... AA23: =SUM(AA24:AA25) -> 364.59773
C24: 发电收入销项税 | D24: =SUM(F24:AA24) -> 7277.1468 | E24: 万元 | H24: =H6*参数输入表!$H$233 -> 361.63616 | I24: =I6*参数输入表!$H$233 -> 361.63616 | J24: =J6*参数输入表!$H$233 -> 361.63616 | K24: =K6*参数输入表!$H$233 -> 361.63616 | L24: =L6*参数输入表!$H$233 -> 361.63616 | M24: =M6*参数输入表!$H$233 -> 364.59773 | N24: =N6*参数输入表!$H$233 -> 364.59773 | O24: =O6*参数输入表!$H$233 -> 364.59773 | ... AA24: =AA6*参数输入表!$H$233 -> 364.59773
C25: 其他收入销项税 | D25: =SUM(F25:AA25) -> 0 | E25: 万元 | H25: =H16*参数输入表!$H$241 -> 0 | I25: =I16*参数输入表!$H$241 -> 0 | J25: =J16*参数输入表!$H$241 -> 0 | K25: =K16*参数输入表!$H$241 -> 0 | L25: =L16*参数输入表!$H$241 -> 0 | M25: =M16*参数输入表!$H$241 -> 0 | N25: =N16*参数输入表!$H$241 -> 0 | O25: =O16*参数输入表!$H$241 -> 0 | ... AA25: =AA16*参数输入表!$H$241 -> 0
B26: 3 | C26: 增值税进项税 | D26: =SUM(F26:AA26) -> 2372.9365 | E26: 万元 | F26: =F27+F28+F42+F43 -> 2317.7153 | G26: =G27+G28+G42+G43 -> 0 | H26: =H27+H28+H42+H43 -> 0 | I26: =I27+I28+I42+I43 -> 0 | J26: =J27+J28+J42+J43 -> 0 | K26: =K27+K28+K42+K43 -> 0 | L26: =L27+L28+L42+L43 -> 0 | M26: =M27+M28+M42+M43 -> 0 | ... AA26: =AA27+AA28+AA42+AA43 -> 0
B27: 3.1 | C27: 建设投资进项税 | D27: =SUM(F27:AA27) -> 2317.7153 | E27: 万元 | F27: =参数输入表!H83*参数输入表!H7 -> 2317.7153 | G27: =参数输入表!H83*参数输入表!H8 -> 0
B28: 3.2 | C28: 营业成本进项税 | D28: =SUM(F28:AA28) -> 0 | E28: 万元 | F28: =F29+F37+F38+F41 -> 0 | G28: =G29+G37+G38+G41 -> 0 | H28: =H29+H37+H38+H41 -> 0 | I28: =I29+I37+I38+I41 -> 0 | J28: =J29+J37+J38+J41 -> 0 | K28: =K29+K37+K38+K41 -> 0 | L28: =L29+L37+L38+L41 -> 0 | M28: =M29+M37+M38+M41 -> 0 | ... AA28: =AA29+AA37+AA38+AA41 -> 0
B29: 3.2.1 | C29: 生产成本进项税 | D29: =SUM(F29:AA29) -> 0 | E29: 万元 | H29: =SUM(H30:H36) -> 0 | I29: =SUM(I30:I36) -> 0 | J29: =SUM(J30:J36) -> 0 | K29: =SUM(K30:K36) -> 0 | L29: =SUM(L30:L36) -> 0 | M29: =SUM(M30:M36) -> 0 | N29: =SUM(N30:N36) -> 0 | O29: =SUM(O30:O36) -> 0 | ... AA29: =SUM(AA30:AA36) -> 0
C30: 材料费 | D30: =SUM(F30:AA30) -> 0 | E30: 万元 | H30: ='表3-成本费用表'!H50/(1+参数输入表!$H$108)*参数输入表!$H$108 -> 0 | I30: ='表3-成本费用表'!I50/(1+参数输入表!$H$108)*参数输入表!$H$108 -> 0 | J30: ='表3-成本费用表'!J50/(1+参数输入表!$H$108)*参数输入表!$H$108 -> 0 | K30: ='表3-成本费用表'!K50/(1+参数输入表!$H$108)*参数输入表!$H$108 -> 0 | L30: ='表3-成本费用表'!L50/(1+参数输入表!$H$108)*参数输入表!$H$108 -> 0 | M30: ='表3-成本费用表'!M50/(1+参数输入表!$H$108)*参数输入表!$H$108 -> 0 | N30: ='表3-成本费用表'!N50/(1+参数输入表!$H$108)*参数输入表!$H$108 -> 0 | O30: ='表3-成本费用表'!O50/(1+参数输入表!$H$108)*参数输入表!$H$108 -> 0 | ... AA30: ='表3-成本费用表'!AA50/(1+参数输入表!$H$108)*参数输入表!$H$108 -> 0
C31: 维修费 | D31: =SUM(F31:AA31) -> 0 | E31: 万元 | H31: ='表3-成本费用表'!H51/(1+参数输入表!$H$116)*参数输入表!$H$116 -> 0 | I31: ='表3-成本费用表'!I51/(1+参数输入表!$H$116)*参数输入表!$H$116 -> 0 | J31: ='表3-成本费用表'!J51/(1+参数输入表!$H$116)*参数输入表!$H$116 -> 0 | K31: ='表3-成本费用表'!K51/(1+参数输入表!$H$116)*参数输入表!$H$116 -> 0 | L31: ='表3-成本费用表'!L51/(1+参数输入表!$H$116)*参数输入表!$H$116 -> 0 | M31: ='表3-成本费用表'!M51/(1+参数输入表!$H$116)*参数输入表!$H$116 -> 0 | N31: ='表3-成本费用表'!N51/(1+参数输入表!$H$116)*参数输入表!$H$116 -> 0 | O31: ='表3-成本费用表'!O51/(1+参数输入表!$H$116)*参数输入表!$H$116 -> 0 | ... AA31: ='表3-成本费用表'!AA51/(1+参数输入表!$H$116)*参数输入表!$H$116 -> 0
C32: 生产人员薪酬及福利 | D32: =SUM(F32:AA32) -> 0 | E32: 万元 | H32: ='表3-成本费用表'!H52/(1+参数输入表!$H$134)*参数输入表!$H$134 -> 0 | I32: ='表3-成本费用表'!I52/(1+参数输入表!$H$134)*参数输入表!$H$134 -> 0 | J32: ='表3-成本费用表'!J52/(1+参数输入表!$H$134)*参数输入表!$H$134 -> 0 | K32: ='表3-成本费用表'!K52/(1+参数输入表!$H$134)*参数输入表!$H$134 -> 0 | L32: ='表3-成本费用表'!L52/(1+参数输入表!$H$134)*参数输入表!$H$134 -> 0 | M32: ='表3-成本费用表'!M52/(1+参数输入表!$H$134)*参数输入表!$H$134 -> 0 | N32: ='表3-成本费用表'!N52/(1+参数输入表!$H$134)*参数输入表!$H$134 -> 0 | O32: ='表3-成本费用表'!O52/(1+参数输入表!$H$134)*参数输入表!$H$134 -> 0 | ... AA32: ='表3-成本费用表'!AA52/(1+参数输入表!$H$134)*参数输入表!$H$134 -> 0
C33: 其他费用 | D33: =SUM(F33:AA33) -> 0 | E33: 万元 | H33: ='表3-成本费用表'!H54/(1+参数输入表!$H$136)*参数输入表!$H$136 -> 0 | I33: ='表3-成本费用表'!I54/(1+参数输入表!$H$136)*参数输入表!$H$136 -> 0 | J33: ='表3-成本费用表'!J54/(1+参数输入表!$H$136)*参数输入表!$H$136 -> 0 | K33: ='表3-成本费用表'!K54/(1+参数输入表!$H$136)*参数输入表!$H$136 -> 0 | L33: ='表3-成本费用表'!L54/(1+参数输入表!$H$136)*参数输入表!$H$136 -> 0 | M33: ='表3-成本费用表'!M54/(1+参数输入表!$H$136)*参数输入表!$H$136 -> 0 | N33: ='表3-成本费用表'!N54/(1+参数输入表!$H$136)*参数输入表!$H$136 -> 0 | O33: ='表3-成本费用表'!O54/(1+参数输入表!$H$136)*参数输入表!$H$136 -> 0 | ... AA33: ='表3-成本费用表'!AA54/(1+参数输入表!$H$136)*参数输入表!$H$136 -> 0
C34: 储能费用 | D34: =SUM(F34:AA34) -> 0 | E34: 万元 | H34: ='表3-成本费用表'!H55/(1+参数输入表!$H$146)*参数输入表!$H$146 -> 0 | I34: ='表3-成本费用表'!I55/(1+参数输入表!$H$146)*参数输入表!$H$146 -> 0 | J34: ='表3-成本费用表'!J55/(1+参数输入表!$H$146)*参数输入表!$H$146 -> 0 | K34: ='表3-成本费用表'!K55/(1+参数输入表!$H$146)*参数输入表!$H$146 -> 0 | L34: ='表3-成本费用表'!L55/(1+参数输入表!$H$146)*参数输入表!$H$146 -> 0 | M34: ='表3-成本费用表'!M55/(1+参数输入表!$H$146)*参数输入表!$H$146 -> 0 | N34: ='表3-成本费用表'!N55/(1+参数输入表!$H$146)*参数输入表!$H$146 -> 0 | O34: ='表3-成本费用表'!O55/(1+参数输入表!$H$146)*参数输入表!$H$146 -> 0 | ... AA34: ='表3-成本费用表'!AA55/(1+参数输入表!$H$146)*参数输入表!$H$146 -> 0
C35: 场地租金费用 | D35: =SUM(F35:AA35) -> 0 | E35: 万元 | H35: ='表3-成本费用表'!H56/(1+参数输入表!$H$140)*参数输入表!$H$140 -> 0 | I35: ='表3-成本费用表'!I56/(1+参数输入表!$H$140)*参数输入表!$H$140 -> 0 | J35: ='表3-成本费用表'!J56/(1+参数输入表!$H$140)*参数输入表!$H$140 -> 0 | K35: ='表3-成本费用表'!K56/(1+参数输入表!$H$140)*参数输入表!$H$140 -> 0 | L35: ='表3-成本费用表'!L56/(1+参数输入表!$H$140)*参数输入表!$H$140 -> 0 | M35: ='表3-成本费用表'!M56/(1+参数输入表!$H$140)*参数输入表!$H$140 -> 0 | N35: ='表3-成本费用表'!N56/(1+参数输入表!$H$140)*参数输入表!$H$140 -> 0 | O35: ='表3-成本费用表'!O56/(1+参数输入表!$H$140)*参数输入表!$H$140 -> 0 | ... AA35: ='表3-成本费用表'!AA56/(1+参数输入表!$H$140)*参数输入表!$H$140 -> 0
C36: 计入长期待摊成本项 | D36: =SUM(F36:AA36) -> 0 | E36: 万元 | H36: ='表3-成本费用表'!H53/(1+参数输入表!$H$182)*参数输入表!$H$182 -> 0 | I36: ='表3-成本费用表'!I53/(1+参数输入表!$H$182)*参数输入表!$H$182 -> 0 | J36: ='表3-成本费用表'!J53/(1+参数输入表!$H$182)*参数输入表!$H$182 -> 0 | K36: ='表3-成本费用表'!K53/(1+参数输入表!$H$182)*参数输入表!$H$182 -> 0 | L36: ='表3-成本费用表'!L53/(1+参数输入表!$H$182)*参数输入表!$H$182 -> 0 | M36: ='表3-成本费用表'!M53/(1+参数输入表!$H$182)*参数输入表!$H$182 -> 0 | N36: ='表3-成本费用表'!N53/(1+参数输入表!$H$182)*参数输入表!$H$182 -> 0 | O36: ='表3-成本费用表'!O53/(1+参数输入表!$H$182)*参数输入表!$H$182 -> 0 | ... AA36: ='表3-成本费用表'!AA53/(1+参数输入表!$H$182)*参数输入表!$H$182 -> 0
B37: 3.2.2 | C37: 销售费用进项税 | D37: =SUM(F37:AA37) -> 0 | E37: 万元 | H37: 0 | I37: 0 | J37: 0 | K37: 0 | L37: 0 | M37: 0 | N37: 0 | O37: 0 | P37: 0 | Q37: 0 | R37: 0 | S37: 0 | T37: 0 | U37: 0 | V37: 0 | W37: 0 | X37: 0 | Y37: 0 | Z37: 0 | AA37: 0
B38: 3.2.3 | C38: 管理费用进项税 | D38: =SUM(F38:AA38) -> 0 | E38: 万元 | H38: =SUM(H39:H40) -> 0 | I38: =SUM(I39:I40) -> 0 | J38: =SUM(J39:J40) -> 0 | K38: =SUM(K39:K40) -> 0 | L38: =SUM(L39:L40) -> 0 | M38: =SUM(M39:M40) -> 0 | N38: =SUM(N39:N40) -> 0 | O38: =SUM(O39:O40) -> 0 | ... AA38: =SUM(AA39:AA40) -> 0
C39: 保险费 | D39: =SUM(F39:AA39) -> 0 | E39: 万元 | H39: ='表3-成本费用表'!H17/(1+参数输入表!$H$124)*参数输入表!$H$124 -> 0 | I39: ='表3-成本费用表'!I17/(1+参数输入表!$H$124)*参数输入表!$H$124 -> 0 | J39: ='表3-成本费用表'!J17/(1+参数输入表!$H$124)*参数输入表!$H$124 -> 0 | K39: ='表3-成本费用表'!K17/(1+参数输入表!$H$124)*参数输入表!$H$124 -> 0 | L39: ='表3-成本费用表'!L17/(1+参数输入表!$H$124)*参数输入表!$H$124 -> 0 | M39: ='表3-成本费用表'!M17/(1+参数输入表!$H$124)*参数输入表!$H$124 -> 0 | N39: ='表3-成本费用表'!N17/(1+参数输入表!$H$124)*参数输入表!$H$124 -> 0 | O39: ='表3-成本费用表'!O17/(1+参数输入表!$H$124)*参数输入表!$H$124 -> 0 | ... AA39: ='表3-成本费用表'!AA17/(1+参数输入表!$H$124)*参数输入表!$H$124 -> 0
C40: 期末拆除费用 | D40: =SUM(F40:AA40) -> 0 | E40: 万元 | H40: ='表3-成本费用表'!H18/(1+参数输入表!$H$144)*参数输入表!$H$144 -> 0 | I40: ='表3-成本费用表'!I18/(1+参数输入表!$H$144)*参数输入表!$H$144 -> 0 | J40: ='表3-成本费用表'!J18/(1+参数输入表!$H$144)*参数输入表!$H$144 -> 0 | K40: ='表3-成本费用表'!K18/(1+参数输入表!$H$144)*参数输入表!$H$144 -> 0 | L40: ='表3-成本费用表'!L18/(1+参数输入表!$H$144)*参数输入表!$H$144 -> 0 | M40: ='表3-成本费用表'!M18/(1+参数输入表!$H$144)*参数输入表!$H$144 -> 0 | N40: ='表3-成本费用表'!N18/(1+参数输入表!$H$144)*参数输入表!$H$144 -> 0 | O40: ='表3-成本费用表'!O18/(1+参数输入表!$H$144)*参数输入表!$H$144 -> 0 | ... AA40: ='表3-成本费用表'!AA18/(1+参数输入表!$H$144)*参数输入表!$H$144 -> 0
B41: 3.2.4 | C41: 研发费用进项税 | D41: =SUM(F41:AA41) -> 0 | E41: 万元 | H41: 0 | I41: 0 | J41: 0 | K41: 0 | L41: 0 | M41: 0 | N41: 0 | O41: 0 | P41: 0 | Q41: 0 | R41: 0 | S41: 0 | T41: 0 | U41: 0 | V41: 0 | W41: 0 | X41: 0 | Y41: 0 | Z41: 0 | AA41: 0
B42: 3.3 | C42: 营业外支出进项税 | D42: =SUM(F42:AA42) -> 0 | E42: 万元 | H42: ='表3-成本费用表'!H62/(1+参数输入表!$H$215)*参数输入表!$H$215 -> 0 | I42: ='表3-成本费用表'!I62/(1+参数输入表!$H$215)*参数输入表!$H$215 -> 0 | J42: ='表3-成本费用表'!J62/(1+参数输入表!$H$215)*参数输入表!$H$215 -> 0 | K42: ='表3-成本费用表'!K62/(1+参数输入表!$H$215)*参数输入表!$H$215 -> 0 | L42: ='表3-成本费用表'!L62/(1+参数输入表!$H$215)*参数输入表!$H$215 -> 0 | M42: ='表3-成本费用表'!M62/(1+参数输入表!$H$215)*参数输入表!$H$215 -> 0 | N42: ='表3-成本费用表'!N62/(1+参数输入表!$H$215)*参数输入表!$H$215 -> 0 | O42: ='表3-成本费用表'!O62/(1+参数输入表!$H$215)*参数输入表!$H$215 -> 0 | ... AA42: ='表3-成本费用表'!AA62/(1+参数输入表!$H$215)*参数输入表!$H$215 -> 0
B43: 3.4 | C43: 大修及更新重置进项税 | D43: =SUM(F43:AA43) -> 55.221239 | E43: 万元 | H43: =参数输入表!H185/(1+参数输入表!$H$208)*参数输入表!$H$208 -> 0 | I43: =参数输入表!H186/(1+参数输入表!$H$208)*参数输入表!$H$208 -> 0 | J43: =参数输入表!H187/(1+参数输入表!$H$208)*参数输入表!$H$208 -> 0 | K43: =参数输入表!H188/(1+参数输入表!$H$208)*参数输入表!$H$208 -> 0 | L43: =参数输入表!H189/(1+参数输入表!$H$208)*参数输入表!$H$208 -> 0 | M43: =参数输入表!H190/(1+参数输入表!$H$208)*参数输入表!$H$208 -> 0 | N43: =参数输入表!H191/(1+参数输入表!$H$208)*参数输入表!$H$208 -> 0 | O43: =参数输入表!H192/(1+参数输入表!$H$208)*参数输入表!$H$208 -> 0 | P43: =参数输入表!H193/(1+参数输入表!$H$208)*参数输入表!$H$208 -> 0 | Q43: =参数输入表!H194/(1+参数输入表!$H$208)*参数输入表!$H$208 -> 0 | R43: =参数输入表!H195/(1+参数输入表!$H$208)*参数输入表!$H$208 -> 55.221239 | S43: =参数输入表!H196/(1+参数输入表!$H$208)*参数输入表!$H$208 -> 0 | T43: =参数输入表!H197/(1+参数输入表!$H$208)*参数输入表!$H$208 -> 0 | U43: =参数输入表!H198/(1+参数输入表!$H$208)*参数输入表!$H$208 -> 0 | V43: =参数输入表!H199/(1+参数输入表!$H$208)*参数输入表!$H$208 -> 0 | W43: =参数输入表!H200/(1+参数输入表!$H$208)*参数输入表!$H$208 -> 0 | X43: =参数输入表!H201/(1+参数输入表!$H$208)*参数输入表!$H$208 -> 0 | Y43: =参数输入表!H202/(1+参数输入表!$H$208)*参数输入表!$H$208 -> 0 | Z43: =参数输入表!H203/(1+参数输入表!$H$208)*参数输入表!$H$208 -> 0 | AA43: =参数输入表!H204/(1+参数输入表!$H$208)*参数输入表!$H$208 -> 0
B44: 4 | C44: 销项税-进项税 | D44: =SUM(F44:AA44) -> 4904.2102 | E44: 万元 | F44: =F23-F26 -> -2317.7153 | G44: =G23-G26 -> 0 | H44: =H23-H26 -> 361.63616 | I44: =I23-I26 -> 361.63616 | J44: =J23-J26 -> 361.63616 | K44: =K23-K26 -> 361.63616 | L44: =L23-L26 -> 361.63616 | M44: =M23-M26 -> 364.59773 | ... AA44: =AA23-AA26 -> 364.59773
B45: 5 | C45: 期末可抵扣进项税余额 | E45: 万元 | F45: =IF(F44<0,-F44,0) -> 2317.7153 | G45: =IF(F45-G44>0,F45-G44,0) -> 2317.7153 | H45: =IF(G45-H44>0,G45-H44,0) -> 1956.0791 | I45: =IF(H45-I44>0,H45-I44,0) -> 1594.443 | J45: =IF(I45-J44>0,I45-J44,0) -> 1232.8068 | K45: =IF(J45-K44>0,J45-K44,0) -> 871.17065 | L45: =IF(K45-L44>0,K45-L44,0) -> 509.53449 | M45: =IF(L45-M44>0,L45-M44,0) -> 144.93675 | N45: =IF(M45-N44>0,M45-N44,0) -> 0 | ... AA45: =IF(Z45-AA44>0,Z45-AA44,0) -> 0
B46: 6 | C46: 增值税附加税 | D46: =SUM(F46:AA46) -> 588.50523 | E46: 万元 | H46: =SUM(H47:H49) -> 0 | I46: =SUM(I47:I49) -> 0 | J46: =SUM(J47:J49) -> 0 | K46: =SUM(K47:K49) -> 0 | L46: =SUM(L47:L49) -> 0 | M46: =SUM(M47:M49) -> 0 | N46: =SUM(N47:N49) -> 26.359317 | O46: =SUM(O47:O49) -> 43.751728 | ... AA46: =SUM(AA47:AA49) -> 43.751728
B47: 6.1 | C47: 城市维护建设税 | D47: =SUM(F47:AA47) -> 343.29472 | E47: 万元 | H47: =H22*参数输入表!$H$273 -> 0 | I47: =I22*参数输入表!$H$273 -> 0 | J47: =J22*参数输入表!$H$273 -> 0 | K47: =K22*参数输入表!$H$273 -> 0 | L47: =L22*参数输入表!$H$273 -> 0 | M47: =M22*参数输入表!$H$273 -> 0 | N47: =N22*参数输入表!$H$273 -> 15.376268 | O47: =O22*参数输入表!$H$273 -> 25.521841 | ... AA47: =AA22*参数输入表!$H$273 -> 25.521841
B48: 6.2 | C48: 教育附加 | D48: =SUM(F48:AA48) -> 147.12631 | E48: 万元 | H48: =H22*参数输入表!$H$277 -> 0 | I48: =I22*参数输入表!$H$277 -> 0 | J48: =J22*参数输入表!$H$277 -> 0 | K48: =K22*参数输入表!$H$277 -> 0 | L48: =L22*参数输入表!$H$277 -> 0 | M48: =M22*参数输入表!$H$277 -> 0 | N48: =N22*参数输入表!$H$277 -> 6.5898293 | O48: =O22*参数输入表!$H$277 -> 10.937932 | ... AA48: =AA22*参数输入表!$H$277 -> 10.937932
B49: 6.3 | C49: 地方教育附加 | D49: =SUM(F49:AA49) -> 98.084205 | E49: 万元 | H49: =H22*参数输入表!$H$278 -> 0 | I49: =I22*参数输入表!$H$278 -> 0 | J49: =J22*参数输入表!$H$278 -> 0 | K49: =K22*参数输入表!$H$278 -> 0 | L49: =L22*参数输入表!$H$278 -> 0 | M49: =M22*参数输入表!$H$278 -> 0 | N49: =N22*参数输入表!$H$278 -> 4.3932196 | O49: =O22*参数输入表!$H$278 -> 7.2919546 | ... AA49: =AA22*参数输入表!$H$278 -> 7.2919546
B50: 7 | C50: 城镇土地使用税 | D50: =SUM(F50:AA50) -> 0 | E50: 万元 | H50: =参数输入表!$H$280*参数输入表!$H$281/10000 -> 0 | I50: =参数输入表!$H$280*参数输入表!$H$281/10000 -> 0 | J50: =参数输入表!$H$280*参数输入表!$H$281/10000 -> 0 | K50: =参数输入表!$H$280*参数输入表!$H$281/10000 -> 0 | L50: =参数输入表!$H$280*参数输入表!$H$281/10000 -> 0 | M50: =参数输入表!$H$280*参数输入表!$H$281/10000 -> 0 | N50: =参数输入表!$H$280*参数输入表!$H$281/10000 -> 0 | O50: =参数输入表!$H$280*参数输入表!$H$281/10000 -> 0 | ... AA50: =参数输入表!$H$280*参数输入表!$H$281/10000 -> 0
C53: 增值税即征即退为参数输入表，税金板块可选条件参数，若选择为常规，即没有增值税即征即退优惠，退税比例为0%；若选择即征即退，同步输入即征即退的比例，第n年增值税即征即退金额=第n年当期实缴增值税*退税比例
C54: 标黄部分为相对固定模块，适用于所有项目
C55: 标蓝部分为计算中间过程，可不展示
B56: 流动资金估算表
B57: 序号 | C57: 项目 | D57: 合计 | E57: 单位 | F57: 建设期 | H57: 运营期
F58: 1 | G58: 2 | H58: 1 | I58: 2 | J58: 3 | K58: 4 | L58: 5 | M58: 6 | N58: 7 | O58: 8 | P58: 9 | Q58: 10 | R58: 11 | S58: 12 | T58: 13 | U58: 14 | V58: 15 | W58: 16 | X58: 17 | Y58: 18 | Z58: 19 | AA58: 20
B59: 一 | C59: 流动资产 | E59: 万元 | F59: =SUM(F60:F63) -> 0 | G59: =SUM(G60:G63) -> 0 | H59: =SUM(H60:H63) -> 0 | I59: =SUM(I60:I63) -> 0 | J59: =SUM(J60:J63) -> 0 | K59: =SUM(K60:K63) -> 0 | L59: =SUM(L60:L63) -> 0 | M59: =SUM(M60:M63) -> 0 | ... AA59: =SUM(AA60:AA63) -> 0
B60: 1.1 | C60: 应收账款 | E60: 万元 | H60: =('表4-收入税金表'!H6+'表4-收入税金表'!H24)*(1-100%)+('表4-收入税金表'!H16+'表4-收入税金表'!H25)*(1-100%) -> 0 | I60: =('表4-收入税金表'!I6+'表4-收入税金表'!I24)*(1-100%)+('表4-收入税金表'!I16+'表4-收入税金表'!I25)*(1-100%) -> 0 | J60: =('表4-收入税金表'!J6+'表4-收入税金表'!J24)*(1-100%)+('表4-收入税金表'!J16+'表4-收入税金表'!J25)*(1-100%) -> 0 | K60: =('表4-收入税金表'!K6+'表4-收入税金表'!K24)*(1-100%)+('表4-收入税金表'!K16+'表4-收入税金表'!K25)*(1-100%) -> 0 | L60: =('表4-收入税金表'!L6+'表4-收入税金表'!L24)*(1-100%)+('表4-收入税金表'!L16+'表4-收入税金表'!L25)*(1-100%) -> 0 | M60: =('表4-收入税金表'!M6+'表4-收入税金表'!M24)*(1-100%)+('表4-收入税金表'!M16+'表4-收入税金表'!M25)*(1-100%) -> 0 | N60: =('表4-收入税金表'!N6+'表4-收入税金表'!N24)*(1-100%)+('表4-收入税金表'!N16+'表4-收入税金表'!N25)*(1-100%) -> 0 | O60: =('表4-收入税金表'!O6+'表4-收入税金表'!O24)*(1-100%)+('表4-收入税金表'!O16+'表4-收入税金表'!O25)*(1-100%) -> 0 | ... AA60: =('表4-收入税金表'!AA6+'表4-收入税金表'!AA24)*(1-100%)+('表4-收入税金表'!AA16+'表4-收入税金表'!AA25)*(1-100%) -> 0
B61: 1.2 | C61: 存货 | E61: 万元
B62: 1.3 | C62: 现金 | E62: 万元
B63: 1.4 | C63: 预付账款 | E63: 万元
B64: 二 | C64: 流动负债 | E64: 万元 | F64: =SUM(F65:F66) -> 0 | G64: =SUM(G65:G66) -> 0 | H64: =SUM(H65:H66) -> 0 | I64: =SUM(I65:I66) -> 0 | J64: =SUM(J65:J66) -> 0 | K64: =SUM(K65:K66) -> 0 | L64: =SUM(L65:L66) -> 0 | M64: =SUM(M65:M66) -> 0 | ... AA64: =SUM(AA65:AA66) -> 0
B65: 2.1 | C65: 应付账款 | E65: 万元
B66: 2.2 | C66: 预收账款 | E66: 万元
B67: 三 | C67: 流动资金 | E67: 万元 | F67: =F59-F64 -> 0 | G67: =G59-G64 -> 0 | H67: =H59-H64 -> 0 | I67: =I59-I64 -> 0 | J67: =J59-J64 -> 0 | K67: =K59-K64 -> 0 | L67: =L59-L64 -> 0 | M67: =M59-M64 -> 0 | ... AA67: =AA59-AA64 -> 0
B68: 四 | C68: 流动资金当期增加额 | E68: 万元 | F68: =F67 -> 0 | G68: =G67-F67 -> 0 | H68: =H67-G67 -> 0 | I68: =I67-H67 -> 0 | J68: =J67-I67 -> 0 | K68: =K67-J67 -> 0 | L68: =L67-K67 -> 0 | M68: =M67-L67 -> 0 | N68: =N67-M67 -> 0 | ... AA68: =AA67-Z67 -> 0
C70: 流动资金估算表用于计算某一项收入当年利润表确认收入与现金流量表中实际到账收入有差额时，差额计入应收账款中。
C71: 关联至参数表中应发收入与实发收入不完全相等的收入项，本模型中为“发电补贴”

Sheet 表5-利润表-资本金
B2: 利润表-资本金
B3: 序号 | C3: 项目 | D3: 合计 | E3: 单位 | F3: 建设期 | H3: 运营期
F4: 1 | G4: 2 | H4: 1 | I4: 2 | J4: 3 | K4: 4 | L4: 5 | M4: 6 | N4: 7 | O4: 8 | P4: 9 | Q4: 10 | R4: 11 | S4: 12 | T4: 13 | U4: 14 | V4: 15 | W4: 16 | X4: 17 | Y4: 18 | Z4: 19 | AA4: 20
B5: 1 | C5: 营业总收入 | D5: =SUM(F5:AA5) -> 55978.052 | E5: 万元 | H5: =H6+H7 -> 2781.8166 | I5: =I6+I7 -> 2781.8166 | J5: =J6+J7 -> 2781.8166 | K5: =K6+K7 -> 2781.8166 | L5: =L6+L7 -> 2781.8166 | M5: =M6+M7 -> 2804.5979 | N5: =N6+N7 -> 2804.5979 | O5: =O6+O7 -> 2804.5979 | ... AA5: =AA6+AA7 -> 2804.5979
B6: 1.1 | C6: 营业收入 | D6: =SUM(F6:AA6) -> 55978.052 | E6: 万元 | H6: ='表4-收入税金表'!H6 -> 2781.8166 | I6: ='表4-收入税金表'!I6 -> 2781.8166 | J6: ='表4-收入税金表'!J6 -> 2781.8166 | K6: ='表4-收入税金表'!K6 -> 2781.8166 | L6: ='表4-收入税金表'!L6 -> 2781.8166 | M6: ='表4-收入税金表'!M6 -> 2804.5979 | N6: ='表4-收入税金表'!N6 -> 2804.5979 | O6: ='表4-收入税金表'!O6 -> 2804.5979 | ... AA6: ='表4-收入税金表'!AA6 -> 2804.5979
B7: 1.2 | C7: 其他收入 | D7: =SUM(F7:AA7) -> 0 | E7: 万元 | H7: ='表4-收入税金表'!H16 -> 0 | I7: ='表4-收入税金表'!I16 -> 0 | J7: ='表4-收入税金表'!J16 -> 0 | K7: ='表4-收入税金表'!K16 -> 0 | L7: ='表4-收入税金表'!L16 -> 0 | M7: ='表4-收入税金表'!M16 -> 0 | N7: ='表4-收入税金表'!N16 -> 0 | O7: ='表4-收入税金表'!O16 -> 0 | ... AA7: ='表4-收入税金表'!AA16 -> 0
B8: 2 | C8: 营业总成本 | D8: =SUM(F8:AA8) -> 40115.554 | E8: 万元 | H8: ='表3-成本费用表'!H5 -> 2602.9063 | I8: ='表3-成本费用表'!I49-'表3-成本费用表'!I53+'表3-成本费用表'!I15+'表3-成本费用表'!I16+'表3-成本费用表'!I19+'表3-成本费用表'!I20+'表2-折旧摊销表'!I38 -> 2555.3815 | J8: ='表3-成本费用表'!J49-'表3-成本费用表'!J53+'表3-成本费用表'!J15+'表3-成本费用表'!J16+'表3-成本费用表'!J19+'表3-成本费用表'!J20+'表2-折旧摊销表'!J38 -> 2507.8567 | K8: ='表3-成本费用表'!K49-'表3-成本费用表'!K53+'表3-成本费用表'!K15+'表3-成本费用表'!K16+'表3-成本费用表'!K19+'表3-成本费用表'!K20+'表2-折旧摊销表'!K38 -> 2460.3319 | L8: ='表3-成本费用表'!L49-'表3-成本费用表'!L53+'表3-成本费用表'!L15+'表3-成本费用表'!L16+'表3-成本费用表'!L19+'表3-成本费用表'!L20+'表2-折旧摊销表'!L38 -> 2412.8071 | M8: ='表3-成本费用表'!M49-'表3-成本费用表'!M53+'表3-成本费用表'!M15+'表3-成本费用表'!M16+'表3-成本费用表'!M19+'表3-成本费用表'!M20+'表2-折旧摊销表'!M38 -> 2475.7056 | N8: ='表3-成本费用表'!N49-'表3-成本费用表'!N53+'表3-成本费用表'!N15+'表3-成本费用表'!N16+'表3-成本费用表'!N19+'表3-成本费用表'!N20+'表2-折旧摊销表'!N38 -> 2428.1808 | O8: ='表3-成本费用表'!O49-'表3-成本费用表'!O53+'表3-成本费用表'!O15+'表3-成本费用表'!O16+'表3-成本费用表'!O19+'表3-成本费用表'!O20+'表2-折旧摊销表'!O38 -> 2380.656 | P8: ='表3-成本费用表'!P49-'表3-成本费用表'!P53+'表3-成本费用表'!P15+'表3-成本费用表'!P16+'表3-成本费用表'!P19+'表3-成本费用表'!P20+'表2-折旧摊销表'!P38 -> 2333.1312 | ... AA8: ='表3-成本费用表'!AA49-'表3-成本费用表'!AA53+'表3-成本费用表'!AA15+'表3-成本费用表'!AA16+'表3-成本费用表'!AA19+'表3-成本费用表'!AA20+'表2-折旧摊销表'!AA38 -> 840.78882
B9: 3 | C9: 营业税金及附加 | D9: =SUM(F9:AA9) -> 588.50523 | E9: 万元 | H9: ='表4-收入税金表'!H46+'表4-收入税金表'!H50 -> 0 | I9: ='表4-收入税金表'!I46+'表4-收入税金表'!I50 -> 0 | J9: ='表4-收入税金表'!J46+'表4-收入税金表'!J50 -> 0 | K9: ='表4-收入税金表'!K46+'表4-收入税金表'!K50 -> 0 | L9: ='表4-收入税金表'!L46+'表4-收入税金表'!L50 -> 0 | M9: ='表4-收入税金表'!M46+'表4-收入税金表'!M50 -> 0 | N9: ='表4-收入税金表'!N46+'表4-收入税金表'!N50 -> 26.359317 | O9: ='表4-收入税金表'!O46+'表4-收入税金表'!O50 -> 43.751728 | ... AA9: ='表4-收入税金表'!AA46+'表4-收入税金表'!AA50 -> 43.751728
B10: 4 | C10: 营业外收入 | D10: =SUM(F10:AA10) -> 2452.1051 | E10: 万元 | H10: =SUM(H11:H12) -> 0 | I10: =SUM(I11:I12) -> 0 | J10: =SUM(J11:J12) -> 0 | K10: =SUM(K11:K12) -> 0 | L10: =SUM(L11:L12) -> 0 | M10: =SUM(M11:M12) -> 0 | N10: =SUM(N11:N12) -> 109.83049 | O10: =SUM(O11:O12) -> 182.29887 | ... AA10: =SUM(AA11:AA12) -> 182.29887
B11: 4.1 | C11: 政府一次性运营补贴收入—递延收益 | D11: =SUM(F11:AA11) -> 0 | E11: 万元 | H11: =参数输入表!H246 -> 0 | I11: =参数输入表!H247 -> 0 | J11: =参数输入表!H248 -> 0 | K11: =参数输入表!H249 -> 0 | L11: =参数输入表!H250 -> 0 | M11: =参数输入表!H251 -> 0 | N11: =参数输入表!H252 -> 0 | O11: =参数输入表!H253 -> 0 | P11: =参数输入表!H254 -> 0 | Q11: =参数输入表!H255 -> 0 | R11: =参数输入表!H256 -> 0 | S11: =参数输入表!H257 -> 0 | T11: =参数输入表!H258 -> 0 | U11: =参数输入表!H259 -> 0 | V11: =参数输入表!H260 -> 0 | W11: =参数输入表!H261 -> 0 | X11: =参数输入表!H262 -> 0 | Y11: =参数输入表!H263 -> 0 | Z11: =参数输入表!H264 -> 0 | AA11: =参数输入表!H265 -> 0
B12: 4.2 | C12: 增值税即征即退收入 | D12: =SUM(F12:AA12) -> 2452.1051 | E12: 万元 | H12: ='表4-收入税金表'!H19 -> 0 | I12: ='表4-收入税金表'!I19 -> 0 | J12: ='表4-收入税金表'!J19 -> 0 | K12: ='表4-收入税金表'!K19 -> 0 | L12: ='表4-收入税金表'!L19 -> 0 | M12: ='表4-收入税金表'!M19 -> 0 | N12: ='表4-收入税金表'!N19 -> 109.83049 | O12: ='表4-收入税金表'!O19 -> 182.29887 | ... AA12: ='表4-收入税金表'!AA19 -> 182.29887
B13: 5 | C13: 营业外支出 | D13: =SUM(F13:AA13) -> 0 | E13: 万元 | H13: ='表3-成本费用表'!H24 -> 0 | I13: ='表3-成本费用表'!I24 -> 0 | J13: ='表3-成本费用表'!J24 -> 0 | K13: ='表3-成本费用表'!K24 -> 0 | L13: ='表3-成本费用表'!L24 -> 0 | M13: ='表3-成本费用表'!M24 -> 0 | N13: ='表3-成本费用表'!N24 -> 0 | O13: ='表3-成本费用表'!O24 -> 0 | ... AA13: ='表3-成本费用表'!AA24 -> 0
B14: 6 | C14: 利润总额（1+4-2-3-5） | D14: =SUM(F14:AA14) -> 17726.098 | E14: 万元 | H14: =H5+H10-H8-H9-H13 -> 178.91035 | I14: =I5+I10-I8-I9-I13 -> 226.43514 | J14: =J5+J10-J8-J9-J13 -> 273.95992 | K14: =K5+K10-K8-K9-K13 -> 321.48471 | L14: =L5+L10-L8-L9-L13 -> 369.0095 | M14: =M5+M10-M8-M9-M13 -> 328.89238 | N14: =N5+N10-N8-N9-N13 -> 459.88834 | O14: =O5+O10-O8-O9-O13 -> 562.48909 | ... AA14: =AA5+AA10-AA8-AA9-AA13 -> 2102.3563
B15: 7 | C15: 弥补以前年度亏损 | D15: =SUM(F15:AA15) -> 0 | E15: 万元 | H15: =SUM(H16:H20) -> 0 | I15: =SUM(I16:I20) -> 0 | J15: =SUM(J16:J20) -> 0 | K15: =SUM(K16:K20) -> 0 | L15: =SUM(L16:L20) -> 0 | M15: =SUM(M16:M20) -> 0 | N15: =SUM(N16:N20) -> 0 | O15: =SUM(O16:O20) -> 0 | ... AA15: =SUM(AA16:AA20) -> 0
C16: 弥补前序第一年亏损 | E16: 万元 | I16: =IF(H14>0,0,IF(I14<0,0,MIN(I14-SUM(I17:I20),-H14))) -> 0 | J16: =IF(I14>0,0,IF(J14<0,0,MIN(J14-SUM(J17:J20),-I14))) -> 0 | K16: =IF(J14>0,0,IF(K14<0,0,MIN(K14-SUM(K17:K20),-J14))) -> 0 | L16: =IF(K14>0,0,IF(L14<0,0,MIN(L14-SUM(L17:L20),-K14))) -> 0 | M16: =IF(L14>0,0,IF(M14<0,0,MIN(M14-SUM(M17:M20),-L14))) -> 0 | N16: =IF(M14>0,0,IF(N14<0,0,MIN(N14-SUM(N17:N20),-M14))) -> 0 | O16: =IF(N14>0,0,IF(O14<0,0,MIN(O14-SUM(O17:O20),-N14))) -> 0 | P16: =IF(O14>0,0,IF(P14<0,0,MIN(P14-SUM(P17:P20),-O14))) -> 0 | ... AA16: =IF(Z14>0,0,IF(AA14<0,0,MIN(AA14-SUM(AA17:AA20),-Z14))) -> 0
C17: 弥补前序第二年亏损 | E17: 万元 | J17: =IF(H14>0,0,IF(J14<0,0,MIN(J14-SUM(J18:J20),-H14-I16))) -> 0 | K17: =IF(I14>0,0,IF(K14<0,0,MIN(K14-SUM(K18:K20),-I14-J16))) -> 0 | L17: =IF(J14>0,0,IF(L14<0,0,MIN(L14-SUM(L18:L20),-J14-K16))) -> 0 | M17: =IF(K14>0,0,IF(M14<0,0,MIN(M14-SUM(M18:M20),-K14-L16))) -> 0 | N17: =IF(L14>0,0,IF(N14<0,0,MIN(N14-SUM(N18:N20),-L14-M16))) -> 0 | O17: =IF(M14>0,0,IF(O14<0,0,MIN(O14-SUM(O18:O20),-M14-N16))) -> 0 | P17: =IF(N14>0,0,IF(P14<0,0,MIN(P14-SUM(P18:P20),-N14-O16))) -> 0 | Q17: =IF(O14>0,0,IF(Q14<0,0,MIN(Q14-SUM(Q18:Q20),-O14-P16))) -> 0 | ... AA17: =IF(Y14>0,0,IF(AA14<0,0,MIN(AA14-SUM(AA18:AA20),-Y14-Z16))) -> 0
C18: 弥补前序第三年亏损 | E18: 万元 | K18: =IF(H14>0,0,IF(K14<0,0,MIN(K14-SUM(K19:K20),-H14-I16-J17))) -> 0 | L18: =IF(I14>0,0,IF(L14<0,0,MIN(L14-SUM(L19:L20),-I14-J16-K17))) -> 0 | M18: =IF(J14>0,0,IF(M14<0,0,MIN(M14-SUM(M19:M20),-J14-K16-L17))) -> 0 | N18: =IF(K14>0,0,IF(N14<0,0,MIN(N14-SUM(N19:N20),-K14-L16-M17))) -> 0 | O18: =IF(L14>0,0,IF(O14<0,0,MIN(O14-SUM(O19:O20),-L14-M16-N17))) -> 0 | P18: =IF(M14>0,0,IF(P14<0,0,MIN(P14-SUM(P19:P20),-M14-N16-O17))) -> 0 | Q18: =IF(N14>0,0,IF(Q14<0,0,MIN(Q14-SUM(Q19:Q20),-N14-O16-P17))) -> 0 | R18: =IF(O14>0,0,IF(R14<0,0,MIN(R14-SUM(R19:R20),-O14-P16-Q17))) -> 0 | ... AA18: =IF(X14>0,0,IF(AA14<0,0,MIN(AA14-SUM(AA19:AA20),-X14-Y16-Z17))) -> 0
C19: 弥补前序第四年亏损 | E19: 万元 | L19: =IF(H14>0,0,IF(L14<0,0,MIN(L14-L20,-H14-I16-J17-K18))) -> 0 | M19: =IF(I14>0,0,IF(M14<0,0,MIN(M14-M20,-I14-J16-K17-L18))) -> 0 | N19: =IF(J14>0,0,IF(N14<0,0,MIN(N14-N20,-J14-K16-L17-M18))) -> 0 | O19: =IF(K14>0,0,IF(O14<0,0,MIN(O14-O20,-K14-L16-M17-N18))) -> 0 | P19: =IF(L14>0,0,IF(P14<0,0,MIN(P14-P20,-L14-M16-N17-O18))) -> 0 | Q19: =IF(M14>0,0,IF(Q14<0,0,MIN(Q14-Q20,-M14-N16-O17-P18))) -> 0 | R19: =IF(N14>0,0,IF(R14<0,0,MIN(R14-R20,-N14-O16-P17-Q18))) -> 0 | S19: =IF(O14>0,0,IF(S14<0,0,MIN(S14-S20,-O14-P16-Q17-R18))) -> 0 | ... AA19: =IF(W14>0,0,IF(AA14<0,0,MIN(AA14-AA20,-W14-X16-Y17-Z18))) -> 0
C20: 弥补前序第五年亏损 | E20: 万元 | M20: =IF(H14>0,0,IF(M14<0,0,MIN(M14,-H14-I16-J17-K18-L19))) -> 0 | N20: =IF(I14>0,0,IF(N14<0,0,MIN(N14,-I14-J16-K17-L18-M19))) -> 0 | O20: =IF(J14>0,0,IF(O14<0,0,MIN(O14,-J14-K16-L17-M18-N19))) -> 0 | P20: =IF(K14>0,0,IF(P14<0,0,MIN(P14,-K14-L16-M17-N18-O19))) -> 0 | Q20: =IF(L14>0,0,IF(Q14<0,0,MIN(Q14,-L14-M16-N17-O18-P19))) -> 0 | R20: =IF(M14>0,0,IF(R14<0,0,MIN(R14,-M14-N16-O17-P18-Q19))) -> 0 | S20: =IF(N14>0,0,IF(S14<0,0,MIN(S14,-N14-O16-P17-Q18-R19))) -> 0 | T20: =IF(O14>0,0,IF(T14<0,0,MIN(T14,-O14-P16-Q17-R18-S19))) -> 0 | ... AA20: =IF(V14>0,0,IF(AA14<0,0,MIN(AA14,-V14-W16-X17-Y18-Z19))) -> 0
B21: 8 | C21: 应税所得额 | D21: =SUM(F21:AA21) -> 17726.098 | E21: 万元 | H21: =IF(H14-H15>0,H14-H15,0) -> 178.91035 | I21: =IF(I14-I15>0,I14-I15,0) -> 226.43514 | J21: =IF(J14-J15>0,J14-J15,0) -> 273.95992 | K21: =IF(K14-K15>0,K14-K15,0) -> 321.48471 | L21: =IF(L14-L15>0,L14-L15,0) -> 369.0095 | M21: =IF(M14-M15>0,M14-M15,0) -> 328.89238 | N21: =IF(N14-N15>0,N14-N15,0) -> 459.88834 | O21: =IF(O14-O15>0,O14-O15,0) -> 562.48909 | ... AA21: =IF(AA14-AA15>0,AA14-AA15,0) -> 2102.3563
B22: 9 | C22: 企业所得税 | D22: =SUM(F22:AA22) -> 4134.2749 | E22: 万元 | H22: =IF(参数输入表!$H$268="三免三减半",0,'表5-利润表-资本金'!H21*参数输入表!$H$269) -> 0 | I22: =IF(参数输入表!$H$268="三免三减半",0,'表5-利润表-资本金'!I21*参数输入表!$H$269) -> 0 | J22: =IF(参数输入表!$H$268="三免三减半",0,'表5-利润表-资本金'!J21*参数输入表!$H$269) -> 0 | K22: =IF(参数输入表!$H$268="三免三减半",'表5-利润表-资本金'!K21*参数输入表!$H$269/2,'表5-利润表-资本金'!K21*参数输入表!$H$269) -> 40.185589 | L22: =IF(参数输入表!$H$268="三免三减半",'表5-利润表-资本金'!L21*参数输入表!$H$269/2,'表5-利润表-资本金'!L21*参数输入表!$H$269) -> 46.126187 | M22: =IF(参数输入表!$H$268="三免三减半",'表5-利润表-资本金'!M21*参数输入表!$H$269/2,'表5-利润表-资本金'!M21*参数输入表!$H$269) -> 41.111547 | N22: =N21*参数输入表!$H$269 -> 114.97208 | O22: =O21*参数输入表!$H$269 -> 140.62227 | P22: =P21*参数输入表!$H$269 -> 152.50347 | Q22: =Q21*参数输入表!$H$269 -> 164.38467 | R22: =R21*参数输入表!$H$269 -> 133.32554 | S22: =S21*参数输入表!$H$269 -> 150.45276 | T22: =T21*参数输入表!$H$269 -> 162.33396 | U22: =U21*参数输入表!$H$269 -> 174.21515 | ... AA22: =AA21*参数输入表!$H$269 -> 525.58906
B23: 10 | C23: 净利润（6-9） | D23: =SUM(F23:AA23) -> 13591.823 | E23: 万元 | H23: =H14-H22 -> 178.91035 | I23: =I14-I22 -> 226.43514 | J23: =J14-J22 -> 273.95992 | K23: =K14-K22 -> 281.29912 | L23: =L14-L22 -> 322.88331 | M23: =M14-M22 -> 287.78083 | N23: =N14-N22 -> 344.91625 | O23: =O14-O22 -> 421.86682 | ... AA23: =AA14-AA22 -> 1576.7672
B24: 11 | C24: 期初未分配的利润 | E24: 万元 | F24: 0 | G24: 0 | H24: =G32 -> 0 | I24: =H32 -> 144.91738 | J24: =I32 -> 313.8381 | K24: =J32 -> 504.36183 | L24: =K32 -> 681.77794 | M24: =L32 -> 875.13562 | N24: =M32 -> 1020.7245 | O24: =N32 -> 1198.0342 | ... AA24: =Z32 -> 6192.4359
B25: 12 | C25: 可供分配的利润（10+11） | D25: =SUM(F25:AA25) -> 55181.856 | E25: 万元 | H25: =H23+H24 -> 178.91035 | I25: =I23+I24 -> 371.35252 | J25: =J23+J24 -> 587.79803 | K25: =K23+K24 -> 785.66095 | L25: =L23+L24 -> 1004.6612 | M25: =M23+M24 -> 1162.9165 | N25: =N23+N24 -> 1365.6408 | O25: =O23+O24 -> 1619.9011 | ... AA25: =AA23+AA24 -> 7769.203
B26: 13 | C26: 提取法定盈余公积金 | D26: =SUM(F26:AA26) -> 1359.1823 | E26: 万元 | H26: =IF(G28>=参数输入表!$H$96,0,IF(H25<0,0,IF(H25*参数输入表!$H$97>=H27,H27,(-H24-H15+H25)*参数输入表!$H$97))) -> 17.891035 | I26: =IF(H28>=参数输入表!$H$96,0,IF(I25<0,0,IF(I25*参数输入表!$H$97>=I27,I27,(-I24-I15+I25)*参数输入表!$H$97))) -> 22.643514 | J26: =IF(I28>=参数输入表!$H$96,0,IF(J25<0,0,IF(J25*参数输入表!$H$97>=J27,J27,(-J24-J15+J25)*参数输入表!$H$97))) -> 27.395992 | K26: =IF(J28>=参数输入表!$H$96,0,IF(K25<0,0,IF(K25*参数输入表!$H$97>=K27,K27,(-K24-K15+K25)*参数输入表!$H$97))) -> 28.129912 | L26: =IF(K28>=参数输入表!$H$96,0,IF(L25<0,0,IF(L25*参数输入表!$H$97>=L27,L27,(-L24-L15+L25)*参数输入表!$H$97))) -> 32.288331 | M26: =IF(L28>=参数输入表!$H$96,0,IF(M25<0,0,IF(M25*参数输入表!$H$97>=M27,M27,(-M24-M15+M25)*参数输入表!$H$97))) -> 28.778083 | N26: =IF(M28>=参数输入表!$H$96,0,IF(N25<0,0,IF(N25*参数输入表!$H$97>=N27,N27,(-N24-N15+N25)*参数输入表!$H$97))) -> 34.491625 | O26: =IF(N28>=参数输入表!$H$96,0,IF(O25<0,0,IF(O25*参数输入表!$H$97>=O27,O27,(-O24-O15+O25)*参数输入表!$H$97))) -> 42.186682 | ... AA26: =IF(Z28>=参数输入表!$H$96,0,IF(AA25<0,0,IF(AA25*参数输入表!$H$97>=AA27,AA27,(-AA24-AA15+AA25)*参数输入表!$H$97))) -> 157.67672
C27: 期初法定盈余公积金上限缺口 | E27: 万元 | H27: =参数输入表!$H$96 -> 2475.2494 | I27: =参数输入表!$H$96-H28 -> 2457.3583 | J27: =参数输入表!$H$96-I28 -> 2434.7148 | K27: =参数输入表!$H$96-J28 -> 2407.3188 | L27: =参数输入表!$H$96-K28 -> 2379.1889 | M27: =参数输入表!$H$96-L28 -> 2346.9006 | N27: =参数输入表!$H$96-M28 -> 2318.1225 | O27: =参数输入表!$H$96-N28 -> 2283.6309 | P27: =参数输入表!$H$96-O28 -> 2241.4442 | ... AA27: =参数输入表!$H$96-Z28 -> 1273.7437
C28: 期末法定盈余公积金累计 | E28: 万元 | H28: =H26 -> 17.891035 | I28: =I26+H28 -> 40.534548 | J28: =J26+I28 -> 67.930541 | K28: =K26+J28 -> 96.060453 | L28: =L26+K28 -> 128.34878 | M28: =M26+L28 -> 157.12687 | N28: =N26+M28 -> 191.61849 | O28: =O26+N28 -> 233.80517 | P28: =P26+O28 -> 279.55622 | ... AA28: =AA26+Z28 -> 1359.1823
B29: 14 | C29: 可供投资者分配的利润（12-13） | D29: =SUM(F29:AA29) -> 53822.673 | E29: 万元 | H29: =H25-H26 -> 161.01931 | I29: =I25-I26 -> 348.709 | J29: =J25-J26 -> 560.40203 | K29: =K25-K26 -> 757.53104 | L29: =L25-L26 -> 972.37292 | M29: =M25-M26 -> 1134.1384 | N29: =N25-N26 -> 1331.1492 | O29: =O25-O26 -> 1577.7144 | ... AA29: =AA25-AA26 -> 7611.5263
B30: 15 | C30: 提取任意盈余公积金 | D30: =SUM(F30:AA30) -> 0 | E30: 万元 | H30: =H29*参数输入表!$H$98 -> 0 | I30: =I29*参数输入表!$H$98 -> 0 | J30: =J29*参数输入表!$H$98 -> 0 | K30: =K29*参数输入表!$H$98 -> 0 | L30: =L29*参数输入表!$H$98 -> 0 | M30: =M29*参数输入表!$H$98 -> 0 | N30: =N29*参数输入表!$H$98 -> 0 | O30: =O29*参数输入表!$H$98 -> 0 | ... AA30: =AA29*参数输入表!$H$98 -> 0
B31: 16 | C31: 各投资方利润分配 | D31: =SUM(F31:AA31) -> 5382.2673 | E31: 万元 | H31: =IF(H29<0,0,(H29)*0.1) -> 16.101931 | I31: =IF(I29<0,0,(I29)*0.1) -> 34.8709 | J31: =IF(J29<0,0,(J29)*0.1) -> 56.040203 | K31: =IF(K29<0,0,(K29)*0.1) -> 75.753104 | L31: =IF(L29<0,0,(L29)*0.1) -> 97.237292 | M31: =IF(M29<0,0,(M29)*0.1) -> 113.41384 | N31: =IF(N29<0,0,(N29)*0.1) -> 133.11492 | O31: =IF(O29<0,0,(O29)*0.1) -> 157.77144 | ... AA31: =IF(AA29<0,0,(AA29)*0.1) -> 761.15263
B32: 17 | C32: 未分配利润（14-15-16） | D32: =SUM(F32:AA32) -> 48440.406 | E32: 万元 | H32: =H29-H30-H31 -> 144.91738 | I32: =I29-I30-I31 -> 313.8381 | J32: =J29-J30-J31 -> 504.36183 | K32: =K29-K30-K31 -> 681.77794 | L32: =L29-L30-L31 -> 875.13562 | M32: =M29-M30-M31 -> 1020.7245 | N32: =N29-N30-N31 -> 1198.0342 | O32: =O29-O30-O31 -> 1419.9429 | ... AA32: =AA29-AA30-AA31 -> 6850.3737
B33: 18 | C33: 息税前利润（利润总额+利息支出） | D33: =SUM(F33:AA33) -> 23494.173 | E33: 万元 | H33: =H14+'表1-资金筹措及还本付息表'!H93 -> 895.03716 | I33: =I14+'表1-资金筹措及还本付息表'!I93 -> 895.03716 | J33: =J14+'表1-资金筹措及还本付息表'!J93 -> 895.03716 | K33: =K14+'表1-资金筹措及还本付息表'!K93 -> 895.03716 | L33: =L14+'表1-资金筹措及还本付息表'!L93 -> 895.03716 | M33: =M14+'表1-资金筹措及还本付息表'!M93 -> 807.39526 | N33: =N14+'表1-资金筹措及还本付息表'!N93 -> 890.86643 | O33: =O14+'表1-资金筹措及还本付息表'!O93 -> 945.94239 | ... AA33: =AA14+'表1-资金筹措及还本付息表'!AA93 -> 2105.6113
B34: 19 | C34: 息税折旧摊销前利润 | D34: =SUM(F34:AA34) -> 45210.752 | E34: 万元 | H34: =H33+'表2-折旧摊销表'!H38 -> 2315.9064 | I34: =I33+'表2-折旧摊销表'!I38 -> 2315.9064 | J34: =J33+'表2-折旧摊销表'!J38 -> 2315.9064 | K34: =K33+'表2-折旧摊销表'!K38 -> 2315.9064 | L34: =L33+'表2-折旧摊销表'!L38 -> 2315.9064 | M34: =M33+'表2-折旧摊销表'!M38 -> 2228.2645 | N34: =N33+'表2-折旧摊销表'!N38 -> 2311.7357 | O34: =O33+'表2-折旧摊销表'!O38 -> 2366.8117 | ... AA34: =AA33+'表2-折旧摊销表'!AA38 -> 2145.9652
C36: 利润表里的收入、成本均为不含税价
C37: 政府一次性运营补贴收入—递延收益，引用自参数输入表“政府一次性补贴收入—递延收益确认”
C38: 弥补以前年度亏损，按照5年为期限，滚动计算。
C40: 标黄部分为相对固定模块，适用于所有项目
C41: 标蓝部分为计算中间过程，可不展示

Sheet 表6-现金流量表-资本金
B2: 现金流量表-资本金
B3: 序号 | C3: 项目 | D3: 合计 | E3: 单位 | F3: 建设期 | H3: 运营期
F4: 1 | G4: 2 | H4: 1 | I4: 2 | J4: 3 | K4: 4 | L4: 5 | M4: 6 | N4: 7 | O4: 8 | P4: 9 | Q4: 10 | R4: 11 | S4: 12 | T4: 13 | U4: 14 | V4: 15 | W4: 16 | X4: 17 | Y4: 18 | Z4: 19 | AA4: 20
B5: 1 | C5: 现金流入 | D5: =SUM(F5:AA5) -> 86802.277 | E5: 万元 | F5: =SUM(F6:F12) -> 19801.995 | G5: =SUM(G6:G12) -> 0 | H5: =H6+H7+H8+H9+H10+H11+H12 -> 3143.4528 | I5: =SUM(I6:I12) -> 3143.4528 | J5: =SUM(J6:J12) -> 3143.4528 | K5: =SUM(K6:K12) -> 3143.4528 | L5: =SUM(L6:L12) -> 3143.4528 | M5: =SUM(M6:M12) -> 3169.1957 | N5: =SUM(N6:N12) -> 3279.0262 | O5: =SUM(O6:O12) -> 3351.4945 | P5: =SUM(P6:P12) -> 3351.4945 | ... AA5: =SUM(AA6:AA12) -> 4644.4724
B6: 1.1 | C6: 债务资金 | D6: =SUM(F6:AA6) -> 19801.995 | E6: 万元 | F6: ='表1-资金筹措及还本付息表'!F80 -> 19801.995 | G6: ='表1-资金筹措及还本付息表'!G80 -> 0 | H6: 0 | I6: ='表1-资金筹措及还本付息表'!I80 -> 0 | J6: ='表1-资金筹措及还本付息表'!J80 -> 0 | K6: ='表1-资金筹措及还本付息表'!K80 -> 0 | L6: ='表1-资金筹措及还本付息表'!L80 -> 0 | M6: ='表1-资金筹措及还本付息表'!M80 -> 0 | N6: ='表1-资金筹措及还本付息表'!N80 -> 0 | O6: ='表1-资金筹措及还本付息表'!O80 -> 0 | P6: ='表1-资金筹措及还本付息表'!P80 -> 0 | ... AA6: ='表1-资金筹措及还本付息表'!AA80 -> 0
B7: 1.2 | C7: 发电销售收入 | D7: =SUM(F7:AA7) -> 63255.199 | E7: 万元 | H7: ='表4-收入税金表'!H6+'表4-收入税金表'!H24 -> 3143.4528 | I7: ='表4-收入税金表'!I6+'表4-收入税金表'!I24 -> 3143.4528 | J7: ='表4-收入税金表'!J6+'表4-收入税金表'!J24 -> 3143.4528 | K7: ='表4-收入税金表'!K6+'表4-收入税金表'!K24 -> 3143.4528 | L7: ='表4-收入税金表'!L6+'表4-收入税金表'!L24 -> 3143.4528 | M7: ='表4-收入税金表'!M6+'表4-收入税金表'!M24 -> 3169.1957 | N7: ='表4-收入税金表'!N6+'表4-收入税金表'!N24 -> 3169.1957 | O7: ='表4-收入税金表'!O6+'表4-收入税金表'!O24 -> 3169.1957 | ... AA7: ='表4-收入税金表'!AA6+'表4-收入税金表'!AA24 -> 3169.1957
B8: 1.3 | C8: 其他收入 | D8: =SUM(F8:AA8) -> 0 | E8: 万元 | H8: =('表4-收入税金表'!H16+'表4-收入税金表'!H25) -> 0 | I8: =('表4-收入税金表'!I16+'表4-收入税金表'!I25) -> 0 | J8: =('表4-收入税金表'!J16+'表4-收入税金表'!J25) -> 0 | K8: =('表4-收入税金表'!K16+'表4-收入税金表'!K25) -> 0 | L8: =('表4-收入税金表'!L16+'表4-收入税金表'!L25) -> 0 | M8: =('表4-收入税金表'!M16+'表4-收入税金表'!M25) -> 0 | N8: =('表4-收入税金表'!N16+'表4-收入税金表'!N25) -> 0 | O8: =('表4-收入税金表'!O16+'表4-收入税金表'!O25) -> 0 | ... AA8: =('表4-收入税金表'!AA16+'表4-收入税金表'!AA25) -> 0
B9: 1.4 | C9: 政府一次性运营补贴收入 | D9: =SUM(F9:AA9) -> 0 | E9: 万元 | H9: =参数输入表!H244 -> 0
B10: 1.5 | C10: 回收固定资产余值 | D10: =SUM(F10:AA10) -> 1142.9778 | E10: 万元 | H10: 0 | I10: 0 | J10: 0 | K10: 0 | L10: 0 | M10: 0 | N10: 0 | O10: 0 | P10: 0 | Q10: 0 | R10: 0 | S10: 0 | T10: 0 | U10: 0 | V10: 0 | W10: 0 | X10: 0 | Y10: 0 | Z10: 0 | AA10: =(参数输入表!H80-参数输入表!H83)*参数输入表!H152+'表2-折旧摊销表'!R35*'表2-折旧摊销表'!D22 -> 1142.9778
B11: 1.6 | C11: 回收流动资金 | D11: =SUM(F11:AA11) -> 150 | E11: 万元 | AA11: ='表1-资金筹措及还本付息表'!H6 -> 150
B12: 1.7 | C12: 增值税即征即退 | D12: =SUM(F12:AA12) -> 2452.1051 | E12: 万元 | H12: ='表4-收入税金表'!H19 -> 0 | I12: ='表4-收入税金表'!I19 -> 0 | J12: ='表4-收入税金表'!J19 -> 0 | K12: ='表4-收入税金表'!K19 -> 0 | L12: ='表4-收入税金表'!L19 -> 0 | M12: ='表4-收入税金表'!M19 -> 0 | N12: ='表4-收入税金表'!N19 -> 109.83049 | O12: ='表4-收入税金表'!O19 -> 182.29887 | ... AA12: ='表4-收入税金表'!AA19 -> 182.29887
B13: 2 | C13: 现金流出 | D13: =SUM(F13:AA13) -> 69076.178 | E13: 万元 | F13: =F14+F17+F18+F22+F23+F24+F25+F26 -> 24752.494 | G13: =G14+G17+G18+G22+G23+G24+G25+G26 -> 0 | H13: =H14+H17+H18+H22+H23+H24+H25+H26 -> 2547.17 | I13: =I14+I17+I18+I22+I23+I24+I25+I26 -> 2454.6452 | J13: =J14+J17+J18+J22+J23+J24+J25+J26 -> 2407.1204 | K13: =K14+K17+K18+K22+K23+K24+K25+K26 -> 2359.5956 | L13: =L14+L17+L18+L22+L23+L24+L25+L26 -> 2312.0708 | M13: =M14+M17+M18+M22+M23+M24+M25+M26 -> 2374.9693 | ... AA13: =AA14+AA17+AA18+AA22+AA23+AA24+AA25+AA26 -> 1313.7843
B14: 2.1 | C14: 工程建设投资 | D14: =SUM(F14:AA14) -> 24752.494 | F14: =SUM(F15:F16) -> 24752.494 | G14: =SUM(G15:G16) -> 0
C15: 项目资本金 | D15: =SUM(F15:AA15) -> 4950.4987 | E15: 万元 | F15: ='表1-资金筹措及还本付息表'!F11 -> 4950.4987 | G15: ='表1-资金筹措及还本付息表'!G11 -> 0
C16: 长期借款 | D16: =SUM(F16:AA16) -> 19801.995 | E16: 万元 | F16: ='表1-资金筹措及还本付息表'!F15 -> 19801.995 | G16: ='表1-资金筹措及还本付息表'!G15 -> 0
B17: 2.2 | C17: 支付流动资金 | D17: =SUM(F17:AA17) -> 45 | E17: 万元 | H17: ='表1-资金筹措及还本付息表'!H11 -> 45
B18: 2.3 | C18: 债务性支出 | D18: =SUM(F18:AA18) -> 25675.069 | E18: 万元 | H18: =SUM(H19:H21) -> 2036.2598 | I18: =SUM(I19:I21) -> 1988.735 | J18: =SUM(J19:J21) -> 1941.2102 | K18: =SUM(K19:K21) -> 1893.6854 | L18: =SUM(L19:L21) -> 1846.1606 | M18: =SUM(M19:M21) -> 1798.6359 | N18: =SUM(N19:N21) -> 1751.1111 | O18: =SUM(O19:O21) -> 1703.5863 | ... AA18: =SUM(AA19:AA21) -> 108.255
C19: 长期借款本金偿还 | D19: =SUM(F19:AA19) -> 19801.995 | E19: 万元 | H19: ='表1-资金筹措及还本付息表'!H52 -> 1320.133 | I19: ='表1-资金筹措及还本付息表'!I52 -> 1320.133 | J19: ='表1-资金筹措及还本付息表'!J52 -> 1320.133 | K19: ='表1-资金筹措及还本付息表'!K52 -> 1320.133 | L19: ='表1-资金筹措及还本付息表'!L52 -> 1320.133 | M19: ='表1-资金筹措及还本付息表'!M52 -> 1320.133 | N19: ='表1-资金筹措及还本付息表'!N52 -> 1320.133 | O19: ='表1-资金筹措及还本付息表'!O52 -> 1320.133 | ... AA19: ='表1-资金筹措及还本付息表'!AA52 -> 0
C20: 流动资金借款本金偿还 | E20: 万元 | H20: ='表1-资金筹措及还本付息表'!H62 -> 0 | I20: ='表1-资金筹措及还本付息表'!I62 -> 0 | J20: ='表1-资金筹措及还本付息表'!J62 -> 0 | K20: ='表1-资金筹措及还本付息表'!K62 -> 0 | L20: ='表1-资金筹措及还本付息表'!L62 -> 0 | M20: ='表1-资金筹措及还本付息表'!M62 -> 0 | N20: ='表1-资金筹措及还本付息表'!N62 -> 0 | O20: ='表1-资金筹措及还本付息表'!O62 -> 0 | ... AA20: ='表1-资金筹措及还本付息表'!AA62 -> 105
C21: 借款利息支付 | D21: =SUM(F21:AA21) -> 5768.0745 | E21: 万元 | H21: ='表1-资金筹措及还本付息表'!H53+'表1-资金筹措及还本付息表'!H63 -> 716.12681 | I21: ='表1-资金筹措及还本付息表'!I53+'表1-资金筹措及还本付息表'!I63 -> 668.60203 | J21: ='表1-资金筹措及还本付息表'!J53+'表1-资金筹措及还本付息表'!J63 -> 621.07724 | K21: ='表1-资金筹措及还本付息表'!K53+'表1-资金筹措及还本付息表'!K63 -> 573.55245 | L21: ='表1-资金筹措及还本付息表'!L53+'表1-资金筹措及还本付息表'!L63 -> 526.02766 | M21: ='表1-资金筹措及还本付息表'!M53+'表1-资金筹措及还本付息表'!M63 -> 478.50288 | N21: ='表1-资金筹措及还本付息表'!N53+'表1-资金筹措及还本付息表'!N63 -> 430.97809 | O21: ='表1-资金筹措及还本付息表'!O53+'表1-资金筹措及还本付息表'!O63 -> 383.4533 | ... AA21: ='表1-资金筹措及还本付息表'!AA53+'表1-资金筹措及还本付息表'!AA63 -> 3.255
B22: 2.4 | C22: 生产经营支出 | D22: =SUM(F22:AA22) -> 12630.9 | E22: 万元 | H22: ='表3-成本费用表'!H48 -> 465.91017 | I22: ='表3-成本费用表'!I48 -> 465.91017 | J22: ='表3-成本费用表'!J48 -> 465.91017 | K22: ='表3-成本费用表'!K48 -> 465.91017 | L22: ='表3-成本费用表'!L48 -> 465.91017 | M22: ='表3-成本费用表'!M48 -> 576.33339 | N22: ='表3-成本费用表'!N48 -> 576.33339 | O22: ='表3-成本费用表'!O48 -> 576.33339 | ... AA22: ='表3-成本费用表'!AA48 -> 797.17984
B23: 2.5 | C23: 营业外支出 | D23: =SUM(F23:AA23) -> 0 | E23: 万元 | H23: ='表3-成本费用表'!H62 -> 0 | I23: ='表3-成本费用表'!I62 -> 0 | J23: ='表3-成本费用表'!J62 -> 0 | K23: ='表3-成本费用表'!K62 -> 0 | L23: ='表3-成本费用表'!L62 -> 0 | M23: ='表3-成本费用表'!M62 -> 0 | N23: ='表3-成本费用表'!N62 -> 0 | O23: ='表3-成本费用表'!O62 -> 0 | ... AA23: ='表3-成本费用表'!AA62 -> 0
B24: 2.6 | C24: 增值税缴纳 | D24: =SUM(F24:AA24) -> 4904.2102 | E24: 万元 | H24: ='表4-收入税金表'!H22 -> 0 | I24: ='表4-收入税金表'!I22 -> 0 | J24: ='表4-收入税金表'!J22 -> 0 | K24: ='表4-收入税金表'!K22 -> 0 | L24: ='表4-收入税金表'!L22 -> 0 | M24: ='表4-收入税金表'!M22 -> 0 | N24: ='表4-收入税金表'!N22 -> 219.66098 | O24: ='表4-收入税金表'!O22 -> 364.59773 | ... AA24: ='表4-收入税金表'!AA22 -> 364.59773
B25: 2.7 | C25: 营业税金及附加 | D25: =SUM(F25:AA25) -> 588.50523 | E25: 万元 | H25: ='表5-利润表-资本金'!H9 -> 0 | I25: ='表5-利润表-资本金'!I9 -> 0 | J25: ='表5-利润表-资本金'!J9 -> 0 | K25: ='表5-利润表-资本金'!K9 -> 0 | L25: ='表5-利润表-资本金'!L9 -> 0 | M25: ='表5-利润表-资本金'!M9 -> 0 | N25: ='表5-利润表-资本金'!N9 -> 26.359317 | O25: ='表5-利润表-资本金'!O9 -> 43.751728 | ... AA25: ='表5-利润表-资本金'!AA9 -> 43.751728
B26: 2.8 | C26: 运营期资本性支出 | D26: =SUM(F26:AA26) -> 480 | E26: 万元 | H26: =参数输入表!H185 -> 0 | I26: =参数输入表!H186 -> 0 | J26: =参数输入表!H187 -> 0 | K26: =参数输入表!H188 -> 0 | L26: =参数输入表!H189 -> 0 | M26: =参数输入表!H190 -> 0 | N26: =参数输入表!H191 -> 0 | O26: =参数输入表!H192 -> 0 | P26: =参数输入表!H193 -> 0 | Q26: =参数输入表!H194 -> 0 | R26: =参数输入表!H195 -> 480 | S26: =参数输入表!H196 -> 0 | T26: =参数输入表!H197 -> 0 | U26: =参数输入表!H198 -> 0 | V26: =参数输入表!H199 -> 0 | W26: =参数输入表!H200 -> 0 | X26: =参数输入表!H201 -> 0 | Y26: =参数输入表!H202 -> 0 | Z26: =参数输入表!H203 -> 0 | AA26: =参数输入表!H204 -> 0
B27: 3 | C27: 税前净现金流量（1-2） | D27: =SUM(F27:AA27) -> 17726.098 | E27: 万元 | F27: =F5-F13 -> -4950.4987 | G27: =G5-G13 -> 0 | H27: =H5-H13 -> 596.28281 | I27: =I5-I13 -> 688.8076 | J27: =J5-J13 -> 736.33238 | K27: =K5-K13 -> 783.85717 | L27: =L5-L13 -> 831.38196 | M27: =M5-M13 -> 794.22641 | ... AA27: =AA5-AA13 -> 3330.6881
B28: 4 | C28: 累计税前净现金流量 | E28: 万元 | F28: =F27 -> -4950.4987 | G28: =IF('表1-资金筹措及还本付息表'!G5>0,F28+G27,0) -> 0 | H28: =G28+H27 -> 596.28281 | I28: =H28+I27 -> 1285.0904 | J28: =I28+J27 -> 2021.4228 | K28: =J28+K27 -> 2805.28 | L28: =K28+L27 -> 3636.6619 | M28: =L28+M27 -> 4430.8883 | N28: =M28+N27 -> 5136.4497 | O28: =N28+O27 -> 5799.6751 | ... AA28: =Z28+AA27 -> 22676.597
B29: 5 | C29: 企业所得税 | D29: =SUM(F29:AA29) -> 4134.2749 | E29: 万元 | H29: ='表5-利润表-资本金'!H22 -> 0 | I29: ='表5-利润表-资本金'!I22 -> 0 | J29: ='表5-利润表-资本金'!J22 -> 0 | K29: ='表5-利润表-资本金'!K22 -> 40.185589 | L29: ='表5-利润表-资本金'!L22 -> 46.126187 | M29: ='表5-利润表-资本金'!M22 -> 41.111547 | N29: ='表5-利润表-资本金'!N22 -> 114.97208 | O29: ='表5-利润表-资本金'!O22 -> 140.62227 | ... AA29: ='表5-利润表-资本金'!AA22 -> 525.58906
B30: 6 | C30: 税后净现金流量（3-5） | D30: =SUM(F30:AA30) -> 13591.823 | E30: 万元 | F30: =F27-F29 -> -4950.4987 | G30: =G27-G29 -> 0 | H30: =H27-H29 -> 596.28281 | I30: =I27-I29 -> 688.8076 | J30: =J27-J29 -> 736.33238 | K30: =K27-K29 -> 743.67158 | L30: =L27-L29 -> 785.25577 | M30: =M27-M29 -> 753.11486 | ... AA30: =AA27-AA29 -> 2805.099
B31: 7 | C31: 累计税后净现金流量 | E31: 万元 | F31: =F30 -> -4950.4987 | G31: =IF('表1-资金筹措及还本付息表'!G5>0,F31+G30,0) -> 0 | H31: =G31+H30 -> 596.28281 | I31: =H31+I30 -> 1285.0904 | J31: =I31+J30 -> 2021.4228 | K31: =J31+K30 -> 2765.0944 | L31: =K31+L30 -> 3550.3501 | M31: =L31+M30 -> 4303.465 | N31: =M31+N30 -> 4894.0543 | O31: =N31+O30 -> 5416.6574 | ... AA31: =Z31+AA30 -> 18542.322
C33: 资本金内部收益率（税前） | D33: =IF('表1-资金筹措及还本付息表'!G5=0,IRR(E52:Y52),IRR(F27:AA27)) -> 0.15445235
C34: 资本金内部收益率（税后） | D34: =IF('表1-资金筹措及还本付息表'!G5=0,IRR(E55:Y55),IRR(F30:AA30)) -> 0.13622615
C35: 投资回收期 | D35: =MAX(F35:AA35) -> 0 | E35: 年 | F35: 0 | G35: 0 | H35: 0 | I35: =IF(I31/H31<0,H4+ABS(H31/I30),0) -> 0 | J35: =IF(J31/I31<0,I4+ABS(I31/J30),0) -> 0 | K35: =IF(K31/J31<0,J4+ABS(J31/K30),0) -> 0 | L35: =IF(L31/K31<0,K4+ABS(K31/L30),0) -> 0 | M35: =IF(M31/L31<0,L4+ABS(L31/M30),0) -> 0 | N35: =IF(N31/M31<0,M4+ABS(M31/N30),0) -> 0 | O35: =IF(O31/N31<0,N4+ABS(N31/O30),0) -> 0 | P35: =IF(P31/O31<0,O4+ABS(O31/P30),0) -> 0 | ... AA35: =IF(AA31/Z31<0,Z4+ABS(Z31/AA30),0) -> 0
C37: 标黄部分为相对固定模块，适用于所有项目
C38: 现金流量表中各年的发电补贴收入数据引用参数表中输入的实发数据（含税且考虑滞后支付情形，即本年度实际支付比例＋上年度剩余支付比例）
C39: 政府一次性运营补贴收入，在运营期第1年引用参数表中政府一次性补贴总额
C40: 标蓝色部分为可隐藏内容
C41: 现金流出中借款本金偿还，关联还本付息表中长期贷款本金偿还
C44: Check | D44: =D30-'表5-利润表-资本金'!D23 -> 0
B46: 建设期为1年时，IRR计算要利用下面的公式计算
B50: 序号 | C50: 项目 | D50: 单位 | E50: 建设期 | F50: 建设 | G50: 运营期
E51: 1 | F51: 1 | G51: 2 | H51: 3 | I51: 4 | J51: 5 | K51: 6 | L51: 7 | M51: 8 | N51: 9 | O51: 10 | P51: 11 | Q51: 12 | R51: 13 | S51: 14 | T51: 15 | U51: 16 | V51: 17 | W51: 18 | X51: 19 | Y51: 20
B52: 3 | C52: 税前净现金流量（1-2） | D52: 万元 | E52: =F27 -> -4950.4987 | F52: =H27 -> 596.28281 | G52: =I27 -> 688.8076 | H52: =J27 -> 736.33238 | I52: =K27 -> 783.85717 | J52: =L27 -> 831.38196 | K52: =M27 -> 794.22641 | L52: =N27 -> 705.56139 | M52: =O27 -> 663.22539 | ... Y52: =AA27 -> 3330.6881
B53: 4 | C53: 累计税前净现金流量 | D53: 万元 | E53: =E52 -> -4950.4987 | F53: =H28 -> 596.28281 | G53: =I28 -> 1285.0904 | H53: =J28 -> 2021.4228 | I53: =K28 -> 2805.28 | J53: =L28 -> 3636.6619 | K53: =M28 -> 4430.8883 | L53: =N28 -> 5136.4497 | M53: =O28 -> 5799.6751 | ... Y53: =AA28 -> 22676.597
B54: 5 | C54: 企业所得税 | D54: 万元 | F54: =H29 -> 0 | G54: =I29 -> 0 | H54: =J29 -> 0 | I54: =K29 -> 40.185589 | J54: =L29 -> 46.126187 | K54: =M29 -> 41.111547 | L54: =N29 -> 114.97208 | M54: =O29 -> 140.62227 | ... Y54: =AA29 -> 525.58906
B55: 6 | C55: 税后净现金流量（3-5） | D55: 万元 | E55: =E52-E54 -> -4950.4987 | F55: =H30 -> 596.28281 | G55: =G52-G54 -> 688.8076 | H55: =H52-H54 -> 736.33238 | I55: =I52-I54 -> 743.67158 | J55: =J52-J54 -> 785.25577 | K55: =K52-K54 -> 753.11486 | L55: =L52-L54 -> 590.58931 | M55: =M52-M54 -> 522.60312 | N55: =N52-N54 -> 558.24671 | ... Y55: =Y52-Y54 -> 2805.099
B56: 7 | C56: 累计税后净现金流量 | D56: 万元 | E56: =E55 -> -4950.4987 | F56: =H31 -> 596.28281 | G56: =F56+G55 -> 1285.0904 | H56: =G56+H55 -> 2021.4228 | I56: =H56+I55 -> 2765.0944 | J56: =I56+J55 -> 3550.3501 | K56: =J56+K55 -> 4303.465 | L56: =K56+L55 -> 4894.0543 | M56: =L56+M55 -> 5416.6574 | N56: =M56+N55 -> 5974.9041 | ... Y56: =X56+Y55 -> 18542.322

Sheet 表7-利润表-全投资
B2: 利润表-全投资
B3: 序号 | C3: 项目 | D3: 合计 | E3: 单位 | F3: 建设期 | H3: 运营期
F4: 1 | G4: 2 | H4: 1 | I4: 2 | J4: 3 | K4: 4 | L4: 5 | M4: 6 | N4: 7 | O4: 8 | P4: 9 | Q4: 10 | R4: 11 | S4: 12 | T4: 13 | U4: 14 | V4: 15 | W4: 16 | X4: 17 | Y4: 18 | Z4: 19 | AA4: 20
B5: 1 | C5: 营业总收入 | D5: =SUM(F5:AA5) -> 55978.052 | E5: 万元 | H5: =SUM(H6:H7) -> 2781.8166 | I5: =SUM(I6:I7) -> 2781.8166 | J5: =SUM(J6:J7) -> 2781.8166 | K5: =SUM(K6:K7) -> 2781.8166 | L5: =SUM(L6:L7) -> 2781.8166 | M5: =SUM(M6:M7) -> 2804.5979 | N5: =SUM(N6:N7) -> 2804.5979 | O5: =SUM(O6:O7) -> 2804.5979 | ... AA5: =SUM(AA6:AA7) -> 2804.5979
B6: 1.1 | C6: 营业收入 | D6: =SUM(F6:AA6) -> 55978.052 | E6: 万元 | H6: ='表4-收入税金表'!H5 -> 2781.8166 | I6: ='表4-收入税金表'!I5 -> 2781.8166 | J6: ='表4-收入税金表'!J5 -> 2781.8166 | K6: ='表4-收入税金表'!K5 -> 2781.8166 | L6: ='表4-收入税金表'!L5 -> 2781.8166 | M6: ='表4-收入税金表'!M5 -> 2804.5979 | N6: ='表4-收入税金表'!N5 -> 2804.5979 | O6: ='表4-收入税金表'!O5 -> 2804.5979 | ... AA6: ='表4-收入税金表'!AA5 -> 2804.5979
B7: 1.2 | C7: 其他收入 | D7: =SUM(F7:AA7) -> 0 | E7: 万元 | H7: ='表4-收入税金表'!H16 -> 0 | I7: ='表4-收入税金表'!I16 -> 0 | J7: ='表4-收入税金表'!J16 -> 0 | K7: ='表4-收入税金表'!K16 -> 0 | L7: ='表4-收入税金表'!L16 -> 0 | M7: ='表4-收入税金表'!M16 -> 0 | N7: ='表4-收入税金表'!N16 -> 0 | O7: ='表4-收入税金表'!O16 -> 0 | ... AA7: ='表4-收入税金表'!AA16 -> 0
B8: 2 | C8: 营业总成本（全投资） | D8: =SUM(F8:AA8) -> 34347.479 | E8: 万元 | H8: ='表3-成本费用表'!H29 -> 1886.7795 | I8: ='表3-成本费用表'!I29 -> 1886.7795 | J8: ='表3-成本费用表'!J29 -> 1886.7795 | K8: ='表3-成本费用表'!K29 -> 1886.7795 | L8: ='表3-成本费用表'!L29 -> 1886.7795 | M8: ='表3-成本费用表'!M29 -> 1997.2027 | N8: ='表3-成本费用表'!N29 -> 1997.2027 | O8: ='表3-成本费用表'!O29 -> 1997.2027 | ... AA8: ='表3-成本费用表'!AA29 -> 837.53382
B9: 3 | C9: 营业税金及附加 | D9: =SUM(F9:AA9) -> 588.50523 | E9: 万元 | H9: ='表4-收入税金表'!H46+'表4-收入税金表'!H50 -> 0 | I9: ='表4-收入税金表'!I46+'表4-收入税金表'!I50 -> 0 | J9: ='表4-收入税金表'!J46+'表4-收入税金表'!J50 -> 0 | K9: ='表4-收入税金表'!K46+'表4-收入税金表'!K50 -> 0 | L9: ='表4-收入税金表'!L46+'表4-收入税金表'!L50 -> 0 | M9: ='表4-收入税金表'!M46+'表4-收入税金表'!M50 -> 0 | N9: ='表4-收入税金表'!N46+'表4-收入税金表'!N50 -> 26.359317 | O9: ='表4-收入税金表'!O46+'表4-收入税金表'!O50 -> 43.751728 | ... AA9: ='表4-收入税金表'!AA46+'表4-收入税金表'!AA50 -> 43.751728
B10: 4 | C10: 营业外收入 | D10: =SUM(F10:AA10) -> 2452.1051 | E10: 万元 | H10: =SUM(H11:H12) -> 0 | I10: =SUM(I11:I12) -> 0 | J10: =SUM(J11:J12) -> 0 | K10: =SUM(K11:K12) -> 0 | L10: =SUM(L11:L12) -> 0 | M10: =SUM(M11:M12) -> 0 | N10: =SUM(N11:N12) -> 109.83049 | O10: =SUM(O11:O12) -> 182.29887 | ... AA10: =SUM(AA11:AA12) -> 182.29887
B11: 4.1 | C11: 政府一次性运营补贴收入—递延收益 | D11: =SUM(F11:AA11) -> 0 | E11: 万元 | H11: =参数输入表!H246 -> 0 | I11: =参数输入表!H247 -> 0 | J11: =参数输入表!H248 -> 0 | K11: =参数输入表!H249 -> 0 | L11: =参数输入表!H250 -> 0 | M11: =参数输入表!H251 -> 0 | N11: =参数输入表!H252 -> 0 | O11: =参数输入表!H253 -> 0 | P11: =参数输入表!H254 -> 0 | Q11: =参数输入表!H255 -> 0 | R11: =参数输入表!H256 -> 0 | S11: =参数输入表!H257 -> 0 | T11: =参数输入表!H258 -> 0 | U11: =参数输入表!H259 -> 0 | V11: =参数输入表!H260 -> 0 | W11: =参数输入表!H261 -> 0 | X11: =参数输入表!H262 -> 0 | Y11: =参数输入表!H263 -> 0 | Z11: =参数输入表!H264 -> 0 | AA11: =参数输入表!H265 -> 0
B12: 4.2 | C12: 增值税即征即退收入 | D12: =SUM(F12:AA12) -> 2452.1051 | E12: 万元 | H12: ='表4-收入税金表'!H19 -> 0 | I12: ='表4-收入税金表'!I19 -> 0 | J12: ='表4-收入税金表'!J19 -> 0 | K12: ='表4-收入税金表'!K19 -> 0 | L12: ='表4-收入税金表'!L19 -> 0 | M12: ='表4-收入税金表'!M19 -> 0 | N12: ='表4-收入税金表'!N19 -> 109.83049 | O12: ='表4-收入税金表'!O19 -> 182.29887 | ... AA12: ='表4-收入税金表'!AA19 -> 182.29887
B13: 5 | C13: 营业外支出 | D13: =SUM(F13:AA13) -> 0 | E13: 万元 | H13: ='表3-成本费用表'!H24 -> 0 | I13: ='表3-成本费用表'!I24 -> 0 | J13: ='表3-成本费用表'!J24 -> 0 | K13: ='表3-成本费用表'!K24 -> 0 | L13: ='表3-成本费用表'!L24 -> 0 | M13: ='表3-成本费用表'!M24 -> 0 | N13: ='表3-成本费用表'!N24 -> 0 | O13: ='表3-成本费用表'!O24 -> 0 | ... AA13: ='表3-成本费用表'!AA24 -> 0
B14: 6 | C14: 利润总额（1+4-2-3-5） | D14: =SUM(F14:AA14) -> 23494.173 | E14: 万元 | H14: =H5+H10-H8-H9-H13 -> 895.03716 | I14: =I5+I10-I8-I9-I13 -> 895.03716 | J14: =J5+J10-J8-J9-J13 -> 895.03716 | K14: =K5+K10-K8-K9-K13 -> 895.03716 | L14: =L5+L10-L8-L9-L13 -> 895.03716 | M14: =M5+M10-M8-M9-M13 -> 807.39526 | N14: =N5+N10-N8-N9-N13 -> 890.86643 | O14: =O5+O10-O8-O9-O13 -> 945.94239 | ... AA14: =AA5+AA10-AA8-AA9-AA13 -> 2105.6113
B15: 7 | C15: 弥补以前年度亏损 | D15: =SUM(F15:AA15) -> 0 | E15: 万元 | H15: =SUM(H16:H20) -> 0 | I15: =SUM(I16:I20) -> 0 | J15: =SUM(J16:J20) -> 0 | K15: =SUM(K16:K20) -> 0 | L15: =SUM(L16:L20) -> 0 | M15: =SUM(M16:M20) -> 0 | N15: =SUM(N16:N20) -> 0 | O15: =SUM(O16:O20) -> 0 | ... AA15: =SUM(AA16:AA20) -> 0
C16: 弥补前序第一年亏损 | E16: 万元 | I16: =IF(H14>0,0,IF(I14<0,0,MIN(I14-SUM(I17:I20),-H14))) -> 0 | J16: =IF(I14>0,0,IF(J14<0,0,MIN(J14-SUM(J17:J20),-I14))) -> 0 | K16: =IF(J14>0,0,IF(K14<0,0,MIN(K14-SUM(K17:K20),-J14))) -> 0 | L16: =IF(K14>0,0,IF(L14<0,0,MIN(L14-SUM(L17:L20),-K14))) -> 0 | M16: =IF(L14>0,0,IF(M14<0,0,MIN(M14-SUM(M17:M20),-L14))) -> 0 | N16: =IF(M14>0,0,IF(N14<0,0,MIN(N14-SUM(N17:N20),-M14))) -> 0 | O16: =IF(N14>0,0,IF(O14<0,0,MIN(O14-SUM(O17:O20),-N14))) -> 0 | P16: =IF(O14>0,0,IF(P14<0,0,MIN(P14-SUM(P17:P20),-O14))) -> 0 | ... AA16: =IF(Z14>0,0,IF(AA14<0,0,MIN(AA14-SUM(AA17:AA20),-Z14))) -> 0
C17: 弥补前序第二年亏损 | E17: 万元 | J17: =IF(H14>0,0,IF(J14<0,0,MIN(J14-SUM(J18:J20),-H14-I16))) -> 0 | K17: =IF(I14>0,0,IF(K14<0,0,MIN(K14-SUM(K18:K20),-I14-J16))) -> 0 | L17: =IF(J14>0,0,IF(L14<0,0,MIN(L14-SUM(L18:L20),-J14-K16))) -> 0 | M17: =IF(K14>0,0,IF(M14<0,0,MIN(M14-SUM(M18:M20),-K14-L16))) -> 0 | N17: =IF(L14>0,0,IF(N14<0,0,MIN(N14-SUM(N18:N20),-L14-M16))) -> 0 | O17: =IF(M14>0,0,IF(O14<0,0,MIN(O14-SUM(O18:O20),-M14-N16))) -> 0 | P17: =IF(N14>0,0,IF(P14<0,0,MIN(P14-SUM(P18:P20),-N14-O16))) -> 0 | Q17: =IF(O14>0,0,IF(Q14<0,0,MIN(Q14-SUM(Q18:Q20),-O14-P16))) -> 0 | ... AA17: =IF(Y14>0,0,IF(AA14<0,0,MIN(AA14-SUM(AA18:AA20),-Y14-Z16))) -> 0
C18: 弥补前序第三年亏损 | E18: 万元 | K18: =IF(H14>0,0,IF(K14<0,0,MIN(K14-SUM(K19:K20),-H14-I16-J17))) -> 0 | L18: =IF(I14>0,0,IF(L14<0,0,MIN(L14-SUM(L19:L20),-I14-J16-K17))) -> 0 | M18: =IF(J14>0,0,IF(M14<0,0,MIN(M14-SUM(M19:M20),-J14-K16-L17))) -> 0 | N18: =IF(K14>0,0,IF(N14<0,0,MIN(N14-SUM(N19:N20),-K14-L16-M17))) -> 0 | O18: =IF(L14>0,0,IF(O14<0,0,MIN(O14-SUM(O19:O20),-L14-M16-N17))) -> 0 | P18: =IF(M14>0,0,IF(P14<0,0,MIN(P14-SUM(P19:P20),-M14-N16-O17))) -> 0 | Q18: =IF(N14>0,0,IF(Q14<0,0,MIN(Q14-SUM(Q19:Q20),-N14-O16-P17))) -> 0 | R18: =IF(O14>0,0,IF(R14<0,0,MIN(R14-SUM(R19:R20),-O14-P16-Q17))) -> 0 | ... AA18: =IF(X14>0,0,IF(AA14<0,0,MIN(AA14-SUM(AA19:AA20),-X14-Y16-Z17))) -> 0
C19: 弥补前序第四年亏损 | E19: 万元 | L19: =IF(H14>0,0,IF(L14<0,0,MIN(L14-L20,-H14-I16-J17-K18))) -> 0 | M19: =IF(I14>0,0,IF(M14<0,0,MIN(M14-M20,-I14-J16-K17-L18))) -> 0 | N19: =IF(J14>0,0,IF(N14<0,0,MIN(N14-N20,-J14-K16-L17-M18))) -> 0 | O19: =IF(K14>0,0,IF(O14<0,0,MIN(O14-O20,-K14-L16-M17-N18))) -> 0 | P19: =IF(L14>0,0,IF(P14<0,0,MIN(P14-P20,-L14-M16-N17-O18))) -> 0 | Q19: =IF(M14>0,0,IF(Q14<0,0,MIN(Q14-Q20,-M14-N16-O17-P18))) -> 0 | R19: =IF(N14>0,0,IF(R14<0,0,MIN(R14-R20,-N14-O16-P17-Q18))) -> 0 | S19: =IF(O14>0,0,IF(S14<0,0,MIN(S14-S20,-O14-P16-Q17-R18))) -> 0 | ... AA19: =IF(W14>0,0,IF(AA14<0,0,MIN(AA14-AA20,-W14-X16-Y17-Z18))) -> 0
C20: 弥补前序第五年亏损 | E20: 万元 | M20: =IF(H14>0,0,IF(M14<0,0,MIN(M14,-H14-I16-J17-K18-L19))) -> 0 | N20: =IF(I14>0,0,IF(N14<0,0,MIN(N14,-I14-J16-K17-L18-M19))) -> 0 | O20: =IF(J14>0,0,IF(O14<0,0,MIN(O14,-J14-K16-L17-M18-N19))) -> 0 | P20: =IF(K14>0,0,IF(P14<0,0,MIN(P14,-K14-L16-M17-N18-O19))) -> 0 | Q20: =IF(L14>0,0,IF(Q14<0,0,MIN(Q14,-L14-M16-N17-O18-P19))) -> 0 | R20: =IF(M14>0,0,IF(R14<0,0,MIN(R14,-M14-N16-O17-P18-Q19))) -> 0 | S20: =IF(N14>0,0,IF(S14<0,0,MIN(S14,-N14-O16-P17-Q18-R19))) -> 0 | T20: =IF(O14>0,0,IF(T14<0,0,MIN(T14,-O14-P16-Q17-R18-S19))) -> 0 | ... AA20: =IF(V14>0,0,IF(AA14<0,0,MIN(AA14,-V14-W16-X17-Y18-Z19))) -> 0
B21: 8 | C21: 应税所得额 | D21: =SUM(F21:AA21) -> 23494.173 | E21: 万元 | H21: =IF(H14-H15>0,H14-H15,0) -> 895.03716 | I21: =IF(I14-I15>0,I14-I15,0) -> 895.03716 | J21: =IF(J14-J15>0,J14-J15,0) -> 895.03716 | K21: =IF(K14-K15>0,K14-K15,0) -> 895.03716 | L21: =IF(L14-L15>0,L14-L15,0) -> 895.03716 | M21: =IF(M14-M15>0,M14-M15,0) -> 807.39526 | N21: =IF(N14-N15>0,N14-N15,0) -> 890.86643 | O21: =IF(O14-O15>0,O14-O15,0) -> 945.94239 | ... AA21: =IF(AA14-AA15>0,AA14-AA15,0) -> 2105.6113
B22: 9 | C22: 调整所得税 | D22: =SUM(F22:AA22) -> 4877.5816 | E22: 万元 | H22: =IF(参数输入表!$H$268="三免三减半",0,H21*参数输入表!$H$269) -> 0 | I22: =IF(参数输入表!$H$268="三免三减半",0,I21*参数输入表!$H$269) -> 0 | J22: =IF(参数输入表!$H$268="三免三减半",0,J21*参数输入表!$H$269) -> 0 | K22: =IF(参数输入表!$H$268="三免三减半",K21*参数输入表!$H$269/2,K21*参数输入表!$H$269) -> 111.87965 | L22: =IF(参数输入表!$H$268="三免三减半",L21*参数输入表!$H$269/2,L21*参数输入表!$H$269) -> 111.87965 | M22: =IF(参数输入表!$H$268="三免三减半",M21*参数输入表!$H$269/2,M21*参数输入表!$H$269) -> 100.92441 | N22: =N21*参数输入表!$H$269 -> 222.71661 | O22: =O21*参数输入表!$H$269 -> 236.4856 | P22: =P21*参数输入表!$H$269 -> 236.4856 | Q22: =Q21*参数输入表!$H$269 -> 236.4856 | R22: =R21*参数输入表!$H$269 -> 193.54528 | S22: =S21*参数输入表!$H$269 -> 198.7913 | T22: =T21*参数输入表!$H$269 -> 198.7913 | U22: =U21*参数输入表!$H$269 -> 198.7913 | ... AA22: =AA21*参数输入表!$H$269 -> 526.40281
B23: 10 | C23: 净利润（6-9） | D23: =SUM(F23:AA23) -> 18616.591 | E23: 万元 | H23: =H14-H22 -> 895.03716 | I23: =I14-I22 -> 895.03716 | J23: =J14-J22 -> 895.03716 | K23: =K14-K22 -> 783.15752 | L23: =L14-L22 -> 783.15752 | M23: =M14-M22 -> 706.47085 | N23: =N14-N22 -> 668.14982 | O23: =O14-O22 -> 709.45679 | ... AA23: =AA14-AA22 -> 1579.2084
B24: 11 | C24: 期初未分配的利润 | D24: =SUM(F24:AA24) -> 0 | E24: 万元 | F24: 0 | G24: 0 | H24: =G32 -> 0 | I24: =H32 -> 0 | J24: =I32 -> 0 | K24: =J32 -> 0 | L24: =K32 -> 0 | M24: =L32 -> 0 | N24: =M32 -> 0 | O24: =N32 -> 0 | ... AA24: =Z32 -> 0
B25: 12 | C25: 可供分配的利润（10+11） | D25: =SUM(F25:AA25) -> 18616.591 | E25: 万元 | H25: =H23+H24 -> 895.03716 | I25: =I23+I24 -> 895.03716 | J25: =J23+J24 -> 895.03716 | K25: =K23+K24 -> 783.15752 | L25: =L23+L24 -> 783.15752 | M25: =M23+M24 -> 706.47085 | N25: =N23+N24 -> 668.14982 | O25: =O23+O24 -> 709.45679 | ... AA25: =AA23+AA24 -> 1579.2084
B26: 13 | C26: 提取法定盈余公积金 | D26: =SUM(F26:AA26) -> 1861.6591 | E26: 万元 | H26: =IF(H25<=0,0,H25*参数输入表!$H$97) -> 89.503716 | I26: =IF(H28>=参数输入表!$H$96,0,IF(I25<0,0,IF(I25*参数输入表!$H$97>=I27,I27,I25*参数输入表!$H$97))) -> 89.503716 | J26: =IF(I28>=参数输入表!$H$96,0,IF(J25<0,0,IF(J25*参数输入表!$H$97>=J27,J27,J25*参数输入表!$H$97))) -> 89.503716 | K26: =IF(J28>=参数输入表!$H$96,0,IF(K25<0,0,IF(K25*参数输入表!$H$97>=K27,K27,K25*参数输入表!$H$97))) -> 78.315752 | L26: =IF(K28>=参数输入表!$H$96,0,IF(L25<0,0,IF(L25*参数输入表!$H$97>=L27,L27,L25*参数输入表!$H$97))) -> 78.315752 | M26: =IF(L28>=参数输入表!$H$96,0,IF(M25<0,0,IF(M25*参数输入表!$H$97>=M27,M27,M25*参数输入表!$H$97))) -> 70.647085 | N26: =IF(M28>=参数输入表!$H$96,0,IF(N25<0,0,IF(N25*参数输入表!$H$97>=N27,N27,N25*参数输入表!$H$97))) -> 66.814982 | O26: =IF(N28>=参数输入表!$H$96,0,IF(O25<0,0,IF(O25*参数输入表!$H$97>=O27,O27,O25*参数输入表!$H$97))) -> 70.945679 | P26: =IF(O28>=参数输入表!$H$96,0,IF(P25<0,0,IF(P25*参数输入表!$H$97>=P27,P27,P25*参数输入表!$H$97))) -> 70.945679 | ... AA26: =IF(Z28>=参数输入表!$H$96,0,IF(AA25<0,0,IF(AA25*参数输入表!$H$97>=AA27,AA27,AA25*参数输入表!$H$97))) -> 157.92084
C27: 期初法定盈余公积金上限缺口 | E27: 万元 | H27: =参数输入表!$H$96 -> 2475.2494 | I27: =参数输入表!$H$96-H28 -> 2385.7456 | J27: =参数输入表!$H$96-I28 -> 2296.2419 | K27: =参数输入表!$H$96-J28 -> 2206.7382 | L27: =参数输入表!$H$96-K28 -> 2128.4225 | M27: =参数输入表!$H$96-L28 -> 2050.1067 | N27: =参数输入表!$H$96-M28 -> 1979.4596 | O27: =参数输入表!$H$96-N28 -> 1912.6446 | P27: =参数输入表!$H$96-O28 -> 1841.699 | ... AA27: =参数输入表!$H$96-Z28 -> 771.51108
C28: 期末法定盈余公积金累计 | E28: 万元 | H28: =H26 -> 89.503716 | I28: =I26+H28 -> 179.00743 | J28: =J26+I28 -> 268.51115 | K28: =K26+J28 -> 346.8269 | L28: =L26+K28 -> 425.14265 | M28: =M26+L28 -> 495.78974 | N28: =N26+M28 -> 562.60472 | O28: =O26+N28 -> 633.5504 | P28: =P26+O28 -> 704.49608 | ... AA28: =AA26+Z28 -> 1861.6591
B29: 14 | C29: 可供投资者分配的利润（12-13） | D29: =SUM(F29:AA29) -> 16754.932 | E29: 万元 | H29: =H25-H26 -> 805.53344 | I29: =I25-I26 -> 805.53344 | J29: =J25-J26 -> 805.53344 | K29: =K25-K26 -> 704.84176 | L29: =L25-L26 -> 704.84176 | M29: =M25-M26 -> 635.82376 | N29: =N25-N26 -> 601.33484 | O29: =O25-O26 -> 638.51112 | ... AA29: =AA25-AA26 -> 1421.2876
B30: 15 | C30: 提取任意盈余公积金 | D30: =SUM(F30:AA30) -> 0 | E30: 万元 | H30: =H29*参数输入表!$H$98 -> 0 | I30: =I29*参数输入表!$H$98 -> 0 | J30: =J29*参数输入表!$H$98 -> 0 | K30: =K29*参数输入表!$H$98 -> 0 | L30: =L29*参数输入表!$H$98 -> 0 | M30: =M29*参数输入表!$H$98 -> 0 | N30: =N29*参数输入表!$H$98 -> 0 | O30: =O29*参数输入表!$H$98 -> 0 | ... AA30: =AA29*参数输入表!$H$98 -> 0
B31: 16 | C31: 各投资方利润分配 | D31: =SUM(F31:AA31) -> 16754.932 | E31: 万元 | H31: =H29-H30 -> 805.53344 | I31: =I29-I30 -> 805.53344 | J31: =J29-J30 -> 805.53344 | K31: =K29-K30 -> 704.84176 | L31: =L29-L30 -> 704.84176 | M31: =M29-M30 -> 635.82376 | N31: =N29-N30 -> 601.33484 | O31: =O29-O30 -> 638.51112 | ... AA31: =AA29-AA30 -> 1421.2876
B32: 17 | C32: 未分配利润（14-15-16） | D32: =SUM(F32:AA32) -> 0 | E32: 万元 | H32: =H29-H30-H31 -> 0 | I32: =I29-I30-I31 -> 0 | J32: =J29-J30-J31 -> 0 | K32: =K29-K30-K31 -> 0 | L32: =L29-L30-L31 -> 0 | M32: =M29-M30-M31 -> 0 | N32: =N29-N30-N31 -> 0 | O32: =O29-O30-O31 -> 0 | ... AA32: =AA29-AA30-AA31 -> 0
B33: 18 | C33: 息税前利润（利润总额+利息支出） | D33: =SUM(F33:AA33) -> 29262.247 | E33: 万元 | H33: =H14+'表1-资金筹措及还本付息表'!H93 -> 1611.164 | I33: =I14+'表1-资金筹措及还本付息表'!I93 -> 1563.6392 | J33: =J14+'表1-资金筹措及还本付息表'!J93 -> 1516.1144 | K33: =K14+'表1-资金筹措及还本付息表'!K93 -> 1468.5896 | L33: =L14+'表1-资金筹措及还本付息表'!L93 -> 1421.0648 | M33: =M14+'表1-资金筹措及还本付息表'!M93 -> 1285.8981 | N33: =N14+'表1-资金筹措及还本付息表'!N93 -> 1321.8445 | O33: =O14+'表1-资金筹措及还本付息表'!O93 -> 1329.3957 | ... AA33: =AA14+'表1-资金筹措及还本付息表'!AA93 -> 2108.8663
B34: 19 | C34: 息税折旧摊销前利润 | D34: =SUM(F34:AA34) -> 50978.826 | E34: 万元 | H34: =H33+'表2-折旧摊销表'!H38 -> 3032.0333 | I34: =I33+'表2-折旧摊销表'!I38 -> 2984.5085 | J34: =J33+'表2-折旧摊销表'!J38 -> 2936.9837 | K34: =K33+'表2-折旧摊销表'!K38 -> 2889.4589 | L34: =L33+'表2-折旧摊销表'!L38 -> 2841.9341 | M34: =M33+'表2-折旧摊销表'!M38 -> 2706.7674 | N34: =N33+'表2-折旧摊销表'!N38 -> 2742.7138 | O34: =O33+'表2-折旧摊销表'!O38 -> 2750.265 | ... AA34: =AA33+'表2-折旧摊销表'!AA38 -> 2149.2202
C38: 标黄部分为相对固定模块，适用于所有项目
C39: 标蓝部分为计算中间过程，可不展示

Sheet 表8-现金流量表-全投资
B2: 现金流量表-全投资
B3: 序号 | C3: 项目 | D3: 合计 | E3: 单位 | F3: 建设期 | H3: 运营期
F4: 1 | G4: 2 | H4: 1 | I4: 2 | J4: 3 | K4: 4 | L4: 5 | M4: 6 | N4: 7 | O4: 8 | P4: 9 | Q4: 10 | R4: 11 | S4: 12 | T4: 13 | U4: 14 | V4: 15 | W4: 16 | X4: 17 | Y4: 18 | Z4: 19 | AA4: 20
B5: 1 | C5: 现金流入 | D5: =SUM(F5:AA5) -> 67000.282 | E5: 万元 | F5: =SUM(F6:F11) -> 0 | G5: =SUM(G6:G11) -> 0 | H5: =SUM(H6:H11) -> 3143.4528 | I5: =SUM(I6:I11) -> 3143.4528 | J5: =SUM(J6:J11) -> 3143.4528 | K5: =SUM(K6:K11) -> 3143.4528 | L5: =SUM(L6:L11) -> 3143.4528 | M5: =SUM(M6:M11) -> 3169.1957 | ... AA5: =SUM(AA6:AA11) -> 4644.4724
B6: 1.1 | C6: 发电销售收入 | D6: =SUM(F6:AA6) -> 63255.199 | E6: 万元 | H6: =('表4-收入税金表'!H6+'表4-收入税金表'!H24) -> 3143.4528 | I6: =('表4-收入税金表'!I6+'表4-收入税金表'!I24) -> 3143.4528 | J6: =('表4-收入税金表'!J6+'表4-收入税金表'!J24) -> 3143.4528 | K6: =('表4-收入税金表'!K6+'表4-收入税金表'!K24) -> 3143.4528 | L6: =('表4-收入税金表'!L6+'表4-收入税金表'!L24) -> 3143.4528 | M6: =('表4-收入税金表'!M6+'表4-收入税金表'!M24) -> 3169.1957 | N6: =('表4-收入税金表'!N6+'表4-收入税金表'!N24) -> 3169.1957 | O6: =('表4-收入税金表'!O6+'表4-收入税金表'!O24) -> 3169.1957 | ... AA6: =('表4-收入税金表'!AA6+'表4-收入税金表'!AA24) -> 3169.1957
B7: 1.2 | C7: 其他收入 | D7: =SUM(F7:AA7) -> 0 | E7: 万元 | H7: =('表4-收入税金表'!H16+'表4-收入税金表'!H25) -> 0 | I7: =('表4-收入税金表'!I16+'表4-收入税金表'!I25) -> 0 | J7: =('表4-收入税金表'!J16+'表4-收入税金表'!J25) -> 0 | K7: =('表4-收入税金表'!K16+'表4-收入税金表'!K25) -> 0 | L7: =('表4-收入税金表'!L16+'表4-收入税金表'!L25) -> 0 | M7: =('表4-收入税金表'!M16+'表4-收入税金表'!M25) -> 0 | N7: =('表4-收入税金表'!N16+'表4-收入税金表'!N25) -> 0 | O7: =('表4-收入税金表'!O16+'表4-收入税金表'!O25) -> 0 | ... AA7: =('表4-收入税金表'!AA16+'表4-收入税金表'!AA25) -> 0
B8: 1.3 | C8: 政府一次性运营补贴收入 | D8: =SUM(F8:AA8) -> 0 | E8: 万元 | H8: =参数输入表!H244 -> 0
B9: 1.4 | C9: 回收固定资产余值 | D9: =SUM(F9:AA9) -> 1142.9778 | E9: 万元 | H9: 0 | I9: 0 | J9: 0 | K9: 0 | L9: 0 | M9: 0 | N9: 0 | O9: 0 | P9: 0 | Q9: 0 | R9: 0 | S9: 0 | T9: 0 | U9: 0 | V9: 0 | W9: 0 | X9: 0 | Y9: 0 | Z9: 0 | AA9: ='表6-现金流量表-资本金'!AA10 -> 1142.9778
B10: 1.5 | C10: 回收流动资金 | D10: =SUM(F10:AA10) -> 150 | E10: 万元 | AA10: =参数输入表!H81 -> 150
B11: 1.6 | C11: 增值税即征即退 | D11: =SUM(F11:AA11) -> 2452.1051 | E11: 万元 | H11: ='表4-收入税金表'!H19 -> 0 | I11: ='表4-收入税金表'!I19 -> 0 | J11: ='表4-收入税金表'!J19 -> 0 | K11: ='表4-收入税金表'!K19 -> 0 | L11: ='表4-收入税金表'!L19 -> 0 | M11: ='表4-收入税金表'!M19 -> 0 | N11: ='表4-收入税金表'!N19 -> 109.83049 | O11: ='表4-收入税金表'!O19 -> 182.29887 | ... AA11: ='表4-收入税金表'!AA19 -> 182.29887
B12: 2 | C12: 现金流出 | D12: =SUM(F12:AA12) -> 43155.976 | E12: 万元 | F12: =SUM(F13:F19) -> 24402.36 | G12: =SUM(G13:G19) -> 0 | H12: =SUM(H13:H19) -> 615.91017 | I12: =SUM(I13:I19) -> 465.91017 | J12: =SUM(J13:J19) -> 465.91017 | K12: =SUM(K13:K19) -> 465.91017 | L12: =SUM(L13:L19) -> 465.91017 | M12: =SUM(M13:M19) -> 576.33339 | ... AA12: =SUM(AA13:AA19) -> 1205.5293
B13: 2.1 | C13: 建设投资 | D13: =SUM(F13:AA13) -> 24402.36 | E13: 万元 | F13: ='表1-资金筹措及还本付息表'!F7 -> 24402.36 | G13: ='表1-资金筹措及还本付息表'!G7 -> 0
B14: 2.2 | C14: 流动资金 | D14: =SUM(F14:AA14) -> 150 | E14: 万元 | H14: =参数输入表!H81 -> 150
B15: 2.3 | C15: 生产经营支出 | D15: =SUM(F15:AA15) -> 12630.9 | E15: 万元 | H15: ='表3-成本费用表'!H48 -> 465.91017 | I15: ='表3-成本费用表'!I48 -> 465.91017 | J15: ='表3-成本费用表'!J48 -> 465.91017 | K15: ='表3-成本费用表'!K48 -> 465.91017 | L15: ='表3-成本费用表'!L48 -> 465.91017 | M15: ='表3-成本费用表'!M48 -> 576.33339 | N15: ='表3-成本费用表'!N48 -> 576.33339 | O15: ='表3-成本费用表'!O48 -> 576.33339 | ... AA15: ='表3-成本费用表'!AA48 -> 797.17984
B16: 2.4 | C16: 营业外支出 | D16: =SUM(F16:AA16) -> 0 | E16: 万元 | H16: ='表3-成本费用表'!H62 -> 0 | I16: ='表3-成本费用表'!I62 -> 0 | J16: ='表3-成本费用表'!J62 -> 0 | K16: ='表3-成本费用表'!K62 -> 0 | L16: ='表3-成本费用表'!L62 -> 0 | M16: ='表3-成本费用表'!M62 -> 0 | N16: ='表3-成本费用表'!N62 -> 0 | O16: ='表3-成本费用表'!O62 -> 0 | ... AA16: ='表3-成本费用表'!AA62 -> 0
B17: 2.5 | C17: 增值税缴纳 | D17: =SUM(F17:AA17) -> 4904.2102 | E17: 万元 | H17: ='表4-收入税金表'!H22 -> 0 | I17: ='表4-收入税金表'!I22 -> 0 | J17: ='表4-收入税金表'!J22 -> 0 | K17: ='表4-收入税金表'!K22 -> 0 | L17: ='表4-收入税金表'!L22 -> 0 | M17: ='表4-收入税金表'!M22 -> 0 | N17: ='表4-收入税金表'!N22 -> 219.66098 | O17: ='表4-收入税金表'!O22 -> 364.59773 | ... AA17: ='表4-收入税金表'!AA22 -> 364.59773
B18: 2.6 | C18: 营业税金及附加 | D18: =SUM(F18:AA18) -> 588.50523 | E18: 万元 | H18: ='表4-收入税金表'!H46+'表4-收入税金表'!H50 -> 0 | I18: ='表4-收入税金表'!I46+'表4-收入税金表'!I50 -> 0 | J18: ='表4-收入税金表'!J46+'表4-收入税金表'!J50 -> 0 | K18: ='表4-收入税金表'!K46+'表4-收入税金表'!K50 -> 0 | L18: ='表4-收入税金表'!L46+'表4-收入税金表'!L50 -> 0 | M18: ='表4-收入税金表'!M46+'表4-收入税金表'!M50 -> 0 | N18: ='表4-收入税金表'!N46+'表4-收入税金表'!N50 -> 26.359317 | O18: ='表4-收入税金表'!O46+'表4-收入税金表'!O50 -> 43.751728 | ... AA18: ='表4-收入税金表'!AA46+'表4-收入税金表'!AA50 -> 43.751728
B19: 2.7 | C19: 运营期资本性支出 | D19: =SUM(F19:AA19) -> 480 | E19: 万元 | H19: =参数输入表!H185 -> 0 | I19: =参数输入表!H186 -> 0 | J19: =参数输入表!H187 -> 0 | K19: =参数输入表!H188 -> 0 | L19: =参数输入表!H189 -> 0 | M19: =参数输入表!H190 -> 0 | N19: =参数输入表!H191 -> 0 | O19: =参数输入表!H192 -> 0 | P19: =参数输入表!H193 -> 0 | Q19: =参数输入表!H194 -> 0 | R19: =参数输入表!H195 -> 480 | S19: =参数输入表!H196 -> 0 | T19: =参数输入表!H197 -> 0 | U19: =参数输入表!H198 -> 0 | V19: =参数输入表!H199 -> 0 | W19: =参数输入表!H200 -> 0 | X19: =参数输入表!H201 -> 0 | Y19: =参数输入表!H202 -> 0 | Z19: =参数输入表!H203 -> 0 | AA19: =参数输入表!H204 -> 0
B20: 3 | C20: 税前净现金流量（1-2） | D20: =SUM(F20:AA20) -> 23844.306 | E20: 万元 | F20: =F5-F12 -> -24402.36 | G20: =G5-G12 -> 0 | H20: =H5-H12 -> 2527.5426 | I20: =I5-I12 -> 2677.5426 | J20: =J5-J12 -> 2677.5426 | K20: =K5-K12 -> 2677.5426 | L20: =L5-L12 -> 2677.5426 | M20: =M5-M12 -> 2592.8623 | ... AA20: =AA5-AA12 -> 3438.9431
B21: 4 | C21: 累计税前净现金流量 | E21: 万元 | F21: =F20 -> -24402.36 | G21: =IF('表1-资金筹措及还本付息表'!G5>0,F21+G20,0) -> 0 | H21: =IF('表1-资金筹措及还本付息表'!G5>0,G21+H20,H20+F21) -> -21874.817 | I21: =H21+I20 -> -19197.275 | J21: =I21+J20 -> -16519.732 | K21: =J21+K20 -> -13842.19 | L21: =K21+L20 -> -11164.647 | M21: =L21+M20 -> -8571.7847 | N21: =M21+N20 -> -6115.1122 | O21: =N21+O20 -> -3748.3005 | P21: =O21+P20 -> -1381.4889 | ... AA21: =Z21+AA20 -> 23844.306
B22: 5 | C22: 调整所得税 | D22: =SUM(F22:AA22) -> 4877.5816 | E22: 万元 | H22: ='表7-利润表-全投资'!H22 -> 0 | I22: ='表7-利润表-全投资'!I22 -> 0 | J22: ='表7-利润表-全投资'!J22 -> 0 | K22: ='表7-利润表-全投资'!K22 -> 111.87965 | L22: ='表7-利润表-全投资'!L22 -> 111.87965 | M22: ='表7-利润表-全投资'!M22 -> 100.92441 | N22: ='表7-利润表-全投资'!N22 -> 222.71661 | O22: ='表7-利润表-全投资'!O22 -> 236.4856 | ... AA22: ='表7-利润表-全投资'!AA22 -> 526.40281
B23: 6 | C23: 税后净现金流量（3-5） | D23: =SUM(F23:AA23) -> 18966.725 | E23: 万元 | F23: =F20-F22 -> -24402.36 | G23: =G20-G22 -> 0 | H23: =H20-H22 -> 2527.5426 | I23: =I20-I22 -> 2677.5426 | J23: =J20-J22 -> 2677.5426 | K23: =K20-K22 -> 2565.663 | L23: =L20-L22 -> 2565.663 | M23: =M20-M22 -> 2491.9379 | ... AA23: =AA20-AA22 -> 2912.5403
B24: 7 | C24: 累计税后净现金流量 | E24: 万元 | F24: =F23 -> -24402.36 | G24: =IF('表1-资金筹措及还本付息表'!G5>0,F24+G23,0) -> 0 | H24: =IF('表1-资金筹措及还本付息表'!G5>0,G24+H23,F24+H23) -> -21874.817 | I24: =H24+I23 -> -19197.275 | J24: =I24+J23 -> -16519.732 | K24: =J24+K23 -> -13954.069 | L24: =K24+L23 -> -11388.406 | M24: =L24+M23 -> -8896.4684 | N24: =M24+N23 -> -6662.5125 | O24: =N24+O23 -> -4532.1864 | P24: =O24+P23 -> -2401.8604 | ... AA24: =Z24+AA23 -> 18966.725
C26: 全投资内部收益率（税前） | D26: =IF('表1-资金筹措及还本付息表'!G5=0,IRR(E44:Y44),IRR(E20:Y20)) -> 0.078490818
C27: 全投资内部收益率（税后） | D27: =IF('表1-资金筹措及还本付息表'!G5=0,IRR(E47:Y47),IRR(F23:AA23)) -> 0.067843501
C28: 投资回收期(税后) | D28: =SUM(F28:AA28)+1 -> 11.167916 | E28: 年 | F28: 0 | G28: 0 | H28: 0 | I28: =IF(I24/H24<0,H4+ABS(H24/I23),0) -> 0 | J28: =IF(J24/I24<0,I4+ABS(I24/J23),0) -> 0 | K28: =IF(K24/J24<0,J4+ABS(J24/K23),0) -> 0 | L28: =IF(L24/K24<0,K4+ABS(K24/L23),0) -> 0 | M28: =IF(M24/L24<0,L4+ABS(L24/M23),0) -> 0 | N28: =IF(N24/M24<0,M4+ABS(M24/N23),0) -> 0 | O28: =IF(O24/N24<0,N4+ABS(N24/O23),0) -> 0 | P28: =IF(P24/O24<0,O4+ABS(O24/P23),0) -> 0 | ... AA28: =IF(AA24/Z24<0,Z4+ABS(Z24/AA23),0) -> 0
C29: 投资回收期(税前) | D29: =SUM(F29:AA29)+1 -> 10.583692 | E29: 年 | F29: 0 | G29: 0 | H29: 0 | I29: =IF(I21/H21<0,H4+ABS(H21/I20),0) -> 0 | J29: =IF(J21/I21<0,I4+ABS(I21/J20),0) -> 0 | K29: =IF(K21/J21<0,J4+ABS(J21/K20),0) -> 0 | L29: =IF(L21/K21<0,K4+ABS(K21/L20),0) -> 0 | M29: =IF(M21/L21<0,L4+ABS(L21/M20),0) -> 0 | N29: =IF(N21/M21<0,M4+ABS(M21/N20),0) -> 0 | O29: =IF(O21/N21<0,N4+ABS(N21/O20),0) -> 0 | P29: =IF(P21/O21<0,O4+ABS(O21/P20),0) -> 0 | ... AA29: =IF(AA21/Z21<0,Z4+ABS(Z21/AA20),0) -> 0
C30: 标黄部分为相对固定模块，适用于所有项目
C31: 现金流量表中各年的发电补贴收入数据引用参数表中输入的实发数据
C32: 政府一次性运营补贴收入，在运营期第1年引用参数表中政府一次性补贴总额
C35: Check | D35: =D23-'表7-利润表-全投资'!D23 -> 350.1335
B38: 建设期为1年时，IRR计算要利用下面的公式计算
B42: 序号 | C42: 项目 | D42: 单位 | E42: 建设期 | F42: 运营期
E43: 1 | F43: 1 | G43: 2 | H43: 3 | I43: 4 | J43: 5 | K43: 6 | L43: 7 | M43: 8 | N43: 9 | O43: 10 | P43: 11 | Q43: 12 | R43: 13 | S43: 14 | T43: 15 | U43: 16 | V43: 17 | W43: 18 | X43: 19 | Y43: 20
B44: 3 | C44: 税前净现金流量（1-2） | D44: 万元 | E44: =F20 -> -24402.36 | F44: =H20 -> 2527.5426 | G44: =I20 -> 2677.5426 | H44: =J20 -> 2677.5426 | I44: =K20 -> 2677.5426 | J44: =L20 -> 2677.5426 | K44: =M20 -> 2592.8623 | L44: =N20 -> 2456.6725 | M44: =O20 -> 2366.8117 | ... Y44: =AA20 -> 3438.9431
B45: 4 | C45: 累计税前净现金流量 | D45: 万元 | E45: =F21 -> -24402.36 | F45: =H21 -> -21874.817 | G45: =F45+G44 -> -19197.275 | H45: =G45+H44 -> -16519.732 | I45: =H45+I44 -> -13842.19 | J45: =I45+J44 -> -11164.647 | K45: =J45+K44 -> -8571.7847 | L45: =K45+L44 -> -6115.1122 | M45: =L45+M44 -> -3748.3005 | N45: =M45+N44 -> -1381.4889 | ... Y45: =X45+Y44 -> 23844.306
B46: 5 | C46: 调整所得税 | D46: 万元 | E46: =F22 -> 0 | F46: =H22 -> 0 | G46: =I22 -> 0 | H46: =J22 -> 0 | I46: =K22 -> 111.87965 | J46: =L22 -> 111.87965 | K46: =M22 -> 100.92441 | L46: =N22 -> 222.71661 | M46: =O22 -> 236.4856 | ... Y46: =AA22 -> 526.40281
B47: 6 | C47: 税后净现金流量（3-5） | D47: 万元 | E47: =F23 -> -24402.36 | F47: =H23 -> 2527.5426 | G47: =I23 -> 2677.5426 | H47: =J23 -> 2677.5426 | I47: =K23 -> 2565.663 | J47: =L23 -> 2565.663 | K47: =M23 -> 2491.9379 | L47: =N23 -> 2233.9559 | M47: =O23 -> 2130.3261 | ... Y47: =AA23 -> 2912.5403
B48: 7 | C48: 累计税后净现金流量 | D48: 万元 | E48: =F24 -> -24402.36 | F48: =H24 -> -21874.817 | G48: =I24 -> -19197.275 | H48: =J24 -> -16519.732 | I48: =K24 -> -13954.069 | J48: =L24 -> -11388.406 | K48: =M24 -> -8896.4684 | L48: =N24 -> -6662.5125 | M48: =O24 -> -4532.1864 | ... Y48: =AA24 -> 18966.725

Sheet 表9-现金流量表-财务计划
B2: 现金流量表-财务计划
B3: 序号 | C3: 项目 | D3: 合计 | E3: 单位 | F3: 建设期 | H3: 运营期
F4: 1 | G4: 2 | H4: 1 | I4: 2 | J4: 3 | K4: 4 | L4: 5 | M4: 6 | N4: 7 | O4: 8 | P4: 9 | Q4: 10 | R4: 11 | S4: 12 | T4: 13 | U4: 14 | V4: 15 | W4: 16 | X4: 17 | Y4: 18 | Z4: 19 | AA4: 20
B5: 1 | C5: 经营活动净现金流量（1.1-1.2） | D5: =SUM(F5:AA5) -> 43449.414 | E5: 万元 | F5: =F6-F12 -> 0 | G5: =G6-G12 -> 0 | H5: =H6-H12 -> 2677.5426 | I5: =I6-I12 -> 2677.5426 | J5: =J6-J12 -> 2677.5426 | K5: =K6-K12 -> 2637.357 | L5: =L6-L12 -> 2631.4164 | M5: =M6-M12 -> 2551.7507 | ... AA5: =AA6-AA12 -> 1620.3762
B6: 1.1 | C6: 现金流入 | D6: =SUM(F6:AA6) -> 65707.304 | E6: 万元 | F6: =SUM(F7:F11) -> 0 | G6: =SUM(G7:G11) -> 0 | H6: =SUM(H7:H11) -> 3143.4528 | I6: =SUM(I7:I11) -> 3143.4528 | J6: =SUM(J7:J11) -> 3143.4528 | K6: =SUM(K7:K11) -> 3143.4528 | L6: =SUM(L7:L11) -> 3143.4528 | M6: =SUM(M7:M11) -> 3169.1957 | ... AA6: =SUM(AA7:AA11) -> 3351.4945
C7: 销售收入 | D7: =SUM(F7:AA7) -> 63255.199 | E7: 万元 | H7: ='表6-现金流量表-资本金'!H7 -> 3143.4528 | I7: ='表6-现金流量表-资本金'!I7 -> 3143.4528 | J7: ='表6-现金流量表-资本金'!J7 -> 3143.4528 | K7: ='表6-现金流量表-资本金'!K7 -> 3143.4528 | L7: ='表6-现金流量表-资本金'!L7 -> 3143.4528 | M7: ='表6-现金流量表-资本金'!M7 -> 3169.1957 | N7: ='表6-现金流量表-资本金'!N7 -> 3169.1957 | O7: ='表6-现金流量表-资本金'!O7 -> 3169.1957 | ... AA7: ='表6-现金流量表-资本金'!AA7 -> 3169.1957
C8: 其他收入 | D8: =SUM(F8:AA8) -> 0 | E8: 万元 | H8: ='表6-现金流量表-资本金'!H8 -> 0 | I8: ='表6-现金流量表-资本金'!I8 -> 0 | J8: ='表6-现金流量表-资本金'!J8 -> 0 | K8: ='表6-现金流量表-资本金'!K8 -> 0 | L8: ='表6-现金流量表-资本金'!L8 -> 0 | M8: ='表6-现金流量表-资本金'!M8 -> 0 | N8: ='表6-现金流量表-资本金'!N8 -> 0 | O8: ='表6-现金流量表-资本金'!O8 -> 0 | ... AA8: ='表6-现金流量表-资本金'!AA8 -> 0
C9: 回收流动资金 | D9: =SUM(F9:AA9) -> 0 | E9: 万元 | AB9: 删除
C10: 政府一次性运营补贴收入 | D10: =SUM(F10:AA10) -> 0 | E10: 万元 | H10: =参数输入表!H244 -> 0
C11: 增值税即征即退 | D11: =SUM(F11:AA11) -> 2452.1051 | E11: 万元 | H11: ='表4-收入税金表'!H19 -> 0 | I11: ='表4-收入税金表'!I19 -> 0 | J11: ='表4-收入税金表'!J19 -> 0 | K11: ='表4-收入税金表'!K19 -> 0 | L11: ='表4-收入税金表'!L19 -> 0 | M11: ='表4-收入税金表'!M19 -> 0 | N11: ='表4-收入税金表'!N19 -> 109.83049 | O11: ='表4-收入税金表'!O19 -> 182.29887 | ... AA11: ='表4-收入税金表'!AA19 -> 182.29887
B12: 1.2 | C12: 现金流出 | D12: =SUM(F12:AA12) -> 22257.89 | E12: 万元 | F12: =SUM(F13:F16) -> 0 | G12: =SUM(G13:G16) -> 0 | H12: =SUM(H13:H16) -> 465.91017 | I12: =SUM(I13:I16) -> 465.91017 | J12: =SUM(J13:J16) -> 465.91017 | K12: =SUM(K13:K16) -> 506.09576 | L12: =SUM(L13:L16) -> 512.03636 | M12: =SUM(M13:M16) -> 617.44494 | ... AA12: =SUM(AA13:AA16) -> 1731.1184
C13: 生产经营支出 | D13: =SUM(F13:AA13) -> 12630.9 | E13: 万元 | H13: ='表3-成本费用表'!H48 -> 465.91017 | I13: ='表3-成本费用表'!I48 -> 465.91017 | J13: ='表3-成本费用表'!J48 -> 465.91017 | K13: ='表3-成本费用表'!K48 -> 465.91017 | L13: ='表3-成本费用表'!L48 -> 465.91017 | M13: ='表3-成本费用表'!M48 -> 576.33339 | N13: ='表3-成本费用表'!N48 -> 576.33339 | O13: ='表3-成本费用表'!O48 -> 576.33339 | ... AA13: ='表3-成本费用表'!AA48 -> 797.17984
C14: 增值税实缴 | D14: =SUM(F14:AA14) -> 4904.2102 | E14: 万元 | H14: ='表4-收入税金表'!H22 -> 0 | I14: ='表4-收入税金表'!I22 -> 0 | J14: ='表4-收入税金表'!J22 -> 0 | K14: ='表4-收入税金表'!K22 -> 0 | L14: ='表4-收入税金表'!L22 -> 0 | M14: ='表4-收入税金表'!M22 -> 0 | N14: ='表4-收入税金表'!N22 -> 219.66098 | O14: ='表4-收入税金表'!O22 -> 364.59773 | ... AA14: ='表4-收入税金表'!AA22 -> 364.59773
C15: 税金及附加税 | D15: =SUM(F15:AA15) -> 588.50523 | E15: 万元 | H15: ='表4-收入税金表'!H46+'表4-收入税金表'!H50 -> 0 | I15: ='表4-收入税金表'!I46+'表4-收入税金表'!I50 -> 0 | J15: ='表4-收入税金表'!J46+'表4-收入税金表'!J50 -> 0 | K15: ='表4-收入税金表'!K46+'表4-收入税金表'!K50 -> 0 | L15: ='表4-收入税金表'!L46+'表4-收入税金表'!L50 -> 0 | M15: ='表4-收入税金表'!M46+'表4-收入税金表'!M50 -> 0 | N15: ='表4-收入税金表'!N46+'表4-收入税金表'!N50 -> 26.359317 | O15: ='表4-收入税金表'!O46+'表4-收入税金表'!O50 -> 43.751728 | ... AA15: ='表4-收入税金表'!AA46+'表4-收入税金表'!AA50 -> 43.751728
C16: 企业所得税 | D16: =SUM(F16:AA16) -> 4134.2749 | E16: 万元 | H16: ='表5-利润表-资本金'!H22 -> 0 | I16: ='表5-利润表-资本金'!I22 -> 0 | J16: ='表5-利润表-资本金'!J22 -> 0 | K16: ='表5-利润表-资本金'!K22 -> 40.185589 | L16: ='表5-利润表-资本金'!L22 -> 46.126187 | M16: ='表5-利润表-资本金'!M22 -> 41.111547 | N16: ='表5-利润表-资本金'!N22 -> 114.97208 | O16: ='表5-利润表-资本金'!O22 -> 140.62227 | ... AA16: ='表5-利润表-资本金'!AA22 -> 525.58906
B17: 2 | C17: 投资活动净现金流量（2.1-2.2） | D17: =SUM(F17:AA17) -> -25032.36 | E17: 万元 | F17: =F18-F19 -> -24402.36 | G17: =G18-G19 -> 0 | H17: =H18-H19 -> -150 | I17: =I18-I19 -> 0 | J17: =J18-J19 -> 0 | K17: =K18-K19 -> 0 | L17: =L18-L19 -> 0 | M17: =M18-M19 -> 0 | ... AA17: =AA18-AA19 -> 0
B18: 2.1 | C18: 现金流入 | D18: =SUM(F18:AA18) -> 0 | E18: 万元 | F18: 0 | G18: 0 | H18: 0 | I18: 0 | J18: 0 | K18: 0 | L18: 0 | M18: 0 | N18: 0 | O18: 0 | P18: 0 | Q18: 0 | R18: 0 | S18: 0 | T18: 0 | U18: 0 | V18: 0 | W18: 0 | X18: 0 | Y18: 0 | Z18: 0 | AA18: 0
B19: 2.2 | C19: 现金流出 | D19: =SUM(F19:AA19) -> 25032.36 | E19: 万元 | F19: =SUM(F20:F22) -> 24402.36 | G19: =SUM(G20:G22) -> 0 | H19: =SUM(H20:H22) -> 150 | I19: =SUM(I20:I22) -> 0 | J19: =SUM(J20:J22) -> 0 | K19: =SUM(K20:K22) -> 0 | L19: =SUM(L20:L22) -> 0 | M19: =SUM(M20:M22) -> 0 | ... AA19: =SUM(AA20:AA22) -> 0
C20: 建设投资 | D20: =SUM(F20:AA20) -> 24402.36 | E20: 万元 | F20: ='表1-资金筹措及还本付息表'!F7 -> 24402.36 | G20: ='表1-资金筹措及还本付息表'!G6 -> 0
C21: 流动资金 | D21: =SUM(F21:AA21) -> 150 | E21: 万元 | H21: =参数输入表!$H$81 -> 150
C22: 运营期资本性支出 | D22: =SUM(F22:AA22) -> 480 | E22: 万元 | H22: =参数输入表!H185 -> 0 | I22: =参数输入表!H186 -> 0 | J22: =参数输入表!H187 -> 0 | K22: =参数输入表!H188 -> 0 | L22: =参数输入表!H189 -> 0 | M22: =参数输入表!H190 -> 0 | N22: =参数输入表!H191 -> 0 | O22: =参数输入表!H192 -> 0 | P22: =参数输入表!H193 -> 0 | Q22: =参数输入表!H194 -> 0 | R22: =参数输入表!H195 -> 480 | S22: =参数输入表!H196 -> 0 | T22: =参数输入表!H197 -> 0 | U22: =参数输入表!H198 -> 0 | V22: =参数输入表!H199 -> 0 | W22: =参数输入表!H200 -> 0 | X22: =参数输入表!H201 -> 0 | Y22: =参数输入表!H202 -> 0 | Z22: =参数输入表!H203 -> 0 | AA22: =参数输入表!H204 -> 0
B23: 3 | C23: 筹资活动净现金流量（3.1-3.2） | D23: =SUM(F23:AA23) -> -6504.9767 | E23: 万元 | F23: =F24-F29 -> 24402.36 | G23: =G24-G29 -> 0 | H23: =H24-H29 -> -1902.3617 | I23: =I24-I29 -> -2023.6059 | J23: =J24-J29 -> -1997.2504 | K23: =K24-K29 -> -1969.4385 | L23: =L24-L29 -> -1943.3979 | M23: =M24-M29 -> -1912.0497 | ... AA23: =AA24-AA29 -> -869.40763
B24: 3.1 | C24: 现金流入 | D24: =SUM(F24:AA24) -> 24902.494 | E24: 万元 | F24: =SUM(F25:F28) -> 24752.494 | G24: =SUM(G25:G28) -> 0 | H24: =SUM(H25:H28) -> 150 | I24: =SUM(I25:I28) -> 0 | J24: =SUM(J25:J28) -> 0 | K24: =SUM(K25:K28) -> 0 | L24: =SUM(L25:L28) -> 0 | M24: =SUM(M25:M28) -> 0 | ... AA24: =SUM(AA25:AA28) -> 0
C25: 项目资本金投入 | D25: =SUM(F25:AA25) -> 4995.4987 | E25: 万元 | F25: ='表1-资金筹措及还本付息表'!F11 -> 4950.4987 | G25: ='表1-资金筹措及还本付息表'!G11 -> 0 | H25: ='表1-资金筹措及还本付息表'!H11 -> 45
C26: 长期借款 | D26: =SUM(F26:AA26) -> 19801.995 | E26: 万元 | F26: ='表1-资金筹措及还本付息表'!F40 -> 19801.995 | G26: ='表1-资金筹措及还本付息表'!G40 -> 0 | H26: ='表1-资金筹措及还本付息表'!H40 -> 0 | I26: ='表1-资金筹措及还本付息表'!I40 -> 0 | J26: ='表1-资金筹措及还本付息表'!J40 -> 0 | K26: ='表1-资金筹措及还本付息表'!K40 -> 0 | L26: ='表1-资金筹措及还本付息表'!L40 -> 0 | M26: ='表1-资金筹措及还本付息表'!M40 -> 0 | ... AA26: ='表1-资金筹措及还本付息表'!AA40 -> 0
C27: 流动资金借款 | D27: =SUM(F27:AA27) -> 105 | E27: 万元 | F27: ='表1-资金筹措及还本付息表'!F60 -> 0 | G27: ='表1-资金筹措及还本付息表'!G60 -> 0 | H27: ='表1-资金筹措及还本付息表'!H60 -> 105 | I27: ='表1-资金筹措及还本付息表'!I60 -> 0 | J27: ='表1-资金筹措及还本付息表'!J60 -> 0 | K27: ='表1-资金筹措及还本付息表'!K60 -> 0 | L27: ='表1-资金筹措及还本付息表'!L60 -> 0 | M27: ='表1-资金筹措及还本付息表'!M60 -> 0 | ... AA27: ='表1-资金筹措及还本付息表'!AA60 -> 0
C28: 短期借款 | D28: =SUM(F28:AA28) -> 0 | E28: 万元 | F28: ='表1-资金筹措及还本付息表'!F70 -> 0 | G28: ='表1-资金筹措及还本付息表'!G70 -> 0 | H28: =H43 -> 0 | I28: =I43 -> 0 | J28: =J43 -> 0 | K28: =K43 -> 0 | L28: =L43 -> 0 | M28: =M43 -> 0 | N28: =N43 -> 0 | O28: =O43 -> 0 | ... AA28: =AA43 -> 0
B29: 3.2 | C29: 现金流出 | D29: =SUM(F29:AA29) -> 31407.47 | E29: 万元 | F29: =SUM(F30:F32) -> 350.1335 | G29: =SUM(G30:G32) -> 0 | H29: =SUM(H30:H32) -> 2052.3617 | I29: =SUM(I30:I32) -> 2023.6059 | J29: =SUM(J30:J32) -> 1997.2504 | K29: =SUM(K30:K32) -> 1969.4385 | L29: =SUM(L30:L32) -> 1943.3979 | M29: =SUM(M30:M32) -> 1912.0497 | ... AA29: =SUM(AA30:AA32) -> 869.40763
C30: 偿还债务本金 | D30: =SUM(F30:AA30) -> 19906.995 | E30: 万元 | H30: ='表1-资金筹措及还本付息表'!H92 -> 1320.133 | I30: ='表1-资金筹措及还本付息表'!I92 -> 1320.133 | J30: ='表1-资金筹措及还本付息表'!J92 -> 1320.133 | K30: ='表1-资金筹措及还本付息表'!K92 -> 1320.133 | L30: ='表1-资金筹措及还本付息表'!L92 -> 1320.133 | M30: ='表1-资金筹措及还本付息表'!M92 -> 1320.133 | N30: ='表1-资金筹措及还本付息表'!N92 -> 1320.133 | O30: ='表1-资金筹措及还本付息表'!O92 -> 1320.133 | ... AA30: ='表1-资金筹措及还本付息表'!AA92 -> 105
C31: 各种利息支出 | D31: =SUM(F31:AA31) -> 6118.208 | E31: 万元 | F31: ='表1-资金筹措及还本付息表'!F8 -> 350.1335 | H31: ='表1-资金筹措及还本付息表'!H93 -> 716.12681 | I31: ='表1-资金筹措及还本付息表'!I93 -> 668.60203 | J31: ='表1-资金筹措及还本付息表'!J93 -> 621.07724 | K31: ='表1-资金筹措及还本付息表'!K93 -> 573.55245 | L31: ='表1-资金筹措及还本付息表'!L93 -> 526.02766 | M31: ='表1-资金筹措及还本付息表'!M93 -> 478.50288 | N31: ='表1-资金筹措及还本付息表'!N93 -> 430.97809 | O31: ='表1-资金筹措及还本付息表'!O93 -> 383.4533 | ... AA31: ='表1-资金筹措及还本付息表'!AA93 -> 3.255
C32: 应付利润（股利分配） | D32: =SUM(F32:AA32) -> 5382.2673 | E32: 万元 | H32: ='表5-利润表-资本金'!H31 -> 16.101931 | I32: ='表5-利润表-资本金'!I31 -> 34.8709 | J32: ='表5-利润表-资本金'!J31 -> 56.040203 | K32: ='表5-利润表-资本金'!K31 -> 75.753104 | L32: ='表5-利润表-资本金'!L31 -> 97.237292 | M32: ='表5-利润表-资本金'!M31 -> 113.41384 | N32: ='表5-利润表-资本金'!N31 -> 133.11492 | O32: ='表5-利润表-资本金'!O31 -> 157.77144 | ... AA32: ='表5-利润表-资本金'!AA31 -> 761.15263
B33: 四 | C33: 项目公司账面净现金流量（1+2+3） | D33: =SUM(F33:AA33) -> 11912.077 | E33: 万元 | F33: =F5+F17+F23 -> 0 | G33: =G5+G17+G23 -> 0 | H33: =H5+H17+H23 -> 625.18088 | I33: =I5+I17+I23 -> 653.9367 | J33: =J5+J17+J23 -> 680.29218 | K33: =K5+K17+K23 -> 667.91848 | L33: =L5+L17+L23 -> 688.01848 | M33: =M5+M17+M23 -> 639.70103 | ... AA33: =AA5+AA17+AA23 -> 750.96854
B34: 五 | C34: 累计盈余资金 | E34: 万元 | F34: =F33 -> 0 | G34: =F34+G33 -> 0 | H34: =G34+H33 -> 625.18088 | I34: =H34+I33 -> 1279.1176 | J34: =I34+J33 -> 1959.4098 | K34: =J34+K33 -> 2627.3282 | L34: =K34+L33 -> 3315.3467 | M34: =L34+M33 -> 3955.0477 | N34: =M34+N33 -> 4412.5221 | ... AA34: =Z34+AA33 -> 11912.077
C37: 增加IF判定条件，当某年的累计盈余资金<“流动资金（本项目为960万元）”+次年的“生产经营现金支出合计（成本费用表标蓝表第一行）”，给出明显提示（允许用户在参数输入界面填写各年度短期借款当期借款金额及还本金额，再重新生成新的结果）
C42: 不含短期借款的累计盈余资金 | H42: =H5+H17+(H25+H27-H30-H31-H32) -> 625.18088 | I42: =I5+I17+(I25+I27-I30-I31-I32)+H42 -> 1279.1176 | J42: =J5+J17+(J25+J27-J30-J31-J32)+I42 -> 1959.4098 | K42: =K5+K17+(K25+K27-K30-K31-K32)+J42 -> 2627.3282 | L42: =L5+L17+(L25+L27-L30-L31-L32)+K42 -> 3315.3467 | M42: =M5+M17+(M25+M27-M30-M31-M32)+L42 -> 3955.0477 | N42: =N5+N17+(N25+N27-N30-N31-N32)+M42 -> 4412.5221 | O42: =O5+O17+(O25+O27-O30-O31-O32)+N42 -> 4777.3538 | P42: =P5+P17+(P25+P27-P30-P31-P32)+O42 -> 5152.4303 | ... AA42: =AA5+AA17+(AA25+AA27-AA30-AA31-AA32)+Z42 -> 11912.077
C43: 借款合计 | H43: =0 -> 0 | I43: =0 -> 0 | J43: =0 -> 0 | K43: =0 -> 0 | L43: =0 -> 0 | M43: =0 -> 0 | N43: =0 -> 0 | O43: =0 -> 0 | ... AA43: =0 -> 0

Sheet 表10-资产负债表
B3: 序号 | C3: 项目 | D3: 单位 | E3: 建设期 | G3: 运营期
E4: 1 | F4: 2 | G4: 1 | H4: 2 | I4: 3 | J4: 4 | K4: 5 | L4: 6 | M4: 7 | N4: 8 | O4: 9 | P4: 10 | Q4: 11 | R4: 12 | S4: 13 | T4: 14 | U4: 15 | V4: 16 | W4: 17 | X4: 18 | Y4: 19 | Z4: 20
B5: 1 | C5: 资产合计 | D5: 万元 | E5: =E6+E31 -> 24752.494 | F5: =F6+F31 -> 0 | G5: =G6+G31 -> 21789.09 | H5: =H6+H31 -> 21022.157 | I5: =I6+I31 -> 20281.58 | J5: =J6+J31 -> 19528.629 | K5: =K6+K31 -> 18795.778 | L5: =L6+L31 -> 18014.61 | ... Z5: =Z6+Z31 -> 13205.055
B6: 1.1 | C6: 流动资产 | D6: 万元 | E6: =SUM(E7:E21)+E23+E24+SUM(E27:E30) -> 0 | F6: =SUM(F7:F21)+F23+F24+SUM(F27:F30) -> 0 | G6: =SUM(G7:G21)+G23+G24+SUM(G27:G30) -> 775.18088 | H6: =SUM(H7:H21)+H23+H24+SUM(H27:H30) -> 1429.1176 | I6: =SUM(I7:I21)+I23+I24+SUM(I27:I30) -> 2109.4098 | J6: =SUM(J7:J21)+J23+J24+SUM(J27:J30) -> 2777.3282 | K6: =SUM(K7:K21)+K23+K24+SUM(K27:K30) -> 3465.3467 | L6: =SUM(L7:L21)+L23+L24+SUM(L27:L30) -> 4105.0477 | ... Z6: =SUM(Z7:Z21)+Z23+Z24+SUM(Z27:Z30) -> 12062.077
C7: 货币资金 | D7: 万元 | E7: ='表9-现金流量表-财务计划'!F34 -> 0 | F7: ='表9-现金流量表-财务计划'!G34 -> 0 | G7: ='表9-现金流量表-财务计划'!H34+'表1-资金筹措及还本付息表'!$H$6 -> 775.18088 | H7: ='表9-现金流量表-财务计划'!I34+'表1-资金筹措及还本付息表'!$H$6 -> 1429.1176 | I7: ='表9-现金流量表-财务计划'!J34+'表1-资金筹措及还本付息表'!$H$6 -> 2109.4098 | J7: ='表9-现金流量表-财务计划'!K34+'表1-资金筹措及还本付息表'!$H$6 -> 2777.3282 | K7: ='表9-现金流量表-财务计划'!L34+'表1-资金筹措及还本付息表'!$H$6 -> 3465.3467 | L7: ='表9-现金流量表-财务计划'!M34+'表1-资金筹措及还本付息表'!$H$6 -> 4105.0477 | M7: ='表9-现金流量表-财务计划'!N34+'表1-资金筹措及还本付息表'!$H$6 -> 4562.5221 | N7: ='表9-现金流量表-财务计划'!O34+'表1-资金筹措及还本付息表'!$H$6 -> 4927.3538 | ... Z7: ='表9-现金流量表-财务计划'!AA34+'表1-资金筹措及还本付息表'!$H$6 -> 12062.077
C8: △结算备付金 | D8: 万元
C9: △拆出资金 | D9: 万元
C10: 交易性金融资产 | D10: 万元
C11: ☆以公允价值计量且其变动计入当期损益的金融资产 | D11: 万元
C12: 衍生金融资产 | D12: 万元
C13: 应收票据 | D13: 万元
C14: 应收账款 | D14: 万元 | G14: ='表4-收入税金表'!H60 -> 0 | H14: ='表4-收入税金表'!I60 -> 0 | I14: ='表4-收入税金表'!J60 -> 0 | J14: ='表4-收入税金表'!K60 -> 0 | K14: ='表4-收入税金表'!L60 -> 0 | L14: ='表4-收入税金表'!M60 -> 0 | M14: ='表4-收入税金表'!N60 -> 0 | N14: ='表4-收入税金表'!O60 -> 0 | ... Z14: ='表4-收入税金表'!AA60 -> 0
C15: 应收款项融资 | D15: 万元
C16: 预付款项 | D16: 万元
C17: △应收保费 | D17: 万元
C18: △应收分保账款 | D18: 万元
C19: △应收分保合同准备金 | D19: 万元
C20: 应收资金集中管理款 | D20: 万元
C21: 其他应收款 | D21: 万元 | E21: 0 | F21: =IF('表1-资金筹措及还本付息表'!G5=0,0,'表4-收入税金表'!G45) -> 0 | G21: =0 -> 0 | H21: =0 -> 0 | I21: =0 -> 0 | J21: =0 -> 0 | K21: =0 -> 0 | L21: =0 -> 0 | M21: =0 -> 0 | N21: =0 -> 0 | ... Z21: =0 -> 0
C22: 其中：应收股利 | D22: 万元
C23: △买入返售金融资产 | D23: 万元
C24: 存货 | D24: 万元 | E24: =SUM(E25:E26) -> 0 | F24: =SUM(F25:F26) -> 0 | G24: =SUM(G25:G26) -> 0 | H24: =SUM(H25:H26) -> 0 | I24: =SUM(I25:I26) -> 0 | J24: =SUM(J25:J26) -> 0 | K24: =SUM(K25:K26) -> 0 | L24: =SUM(L25:L26) -> 0 | ... Z24: =SUM(Z25:Z26) -> 0
C25: 其中：原材料 | D25: 万元
C26: 库存商品（产成品） | D26: 万元
C27: 合同资产 | D27: 万元
C28: 持有待售资产 | D28: 万元
C29: 一年内到期的非流动资产 | D29: 万元
C30: 其他流动资产 | D30: 万元 | H30: =G30 -> 0 | I30: =H30 -> 0 | J30: =I30 -> 0 | K30: =J30 -> 0 | L30: =K30 -> 0 | M30: =L30 -> 0 | N30: =M30 -> 0 | O30: =N30 -> 0 | ... Z30: =Y30 -> 0
B31: 1.2 | C31: 非流动资产 | D31: 万元 | E31: =SUM(E32:E42)+SUM(E46:E55) -> 24752.494 | F31: =SUM(F32:F42)+SUM(F46:F55) -> 0 | G31: =SUM(G32:G42)+SUM(G46:G55) -> 21013.909 | H31: =SUM(H32:H42)+SUM(H46:H55) -> 19593.04 | I31: =SUM(I32:I42)+SUM(I46:I55) -> 18172.17 | J31: =SUM(J32:J42)+SUM(J46:J55) -> 16751.301 | K31: =SUM(K32:K42)+SUM(K46:K55) -> 15330.432 | L31: =SUM(L32:L42)+SUM(L46:L55) -> 13909.562 | ... Z31: =SUM(Z32:Z42)+SUM(Z46:Z55) -> 1142.9778
C32: △发放贷款和垫款 | D32: 万元
C33: 债权投资 | D33: 万元
C34: ☆可供出售金融资产 | D34: 万元
C35: 其他债权投资 | D35: 万元
C36: ☆持有至到期投资 | D36: 万元
C37: 长期应收款 | D37: 万元
C38: 长期股权投资 | D38: 万元
C39: 其他权益工具投资 | D39: 万元
C40: 其他非流动金融资产 | D40: 万元
C41: 投资性房地产 | D41: 万元
C42: 固定资产 | D42: 万元 | F42: =F43-F44 -> 0 | G42: =G43-G44 -> 21013.909 | H42: =H43-H44 -> 19593.04 | I42: =I43-I44 -> 18172.17 | J42: =J43-J44 -> 16751.301 | K42: =K43-K44 -> 15330.432 | L42: =L43-L44 -> 13909.562 | M42: =M43-M44 -> 12488.693 | ... Z42: =Z43-Z44 -> 1142.9778
C43: 其中：固定资产原价 | D43: 万元 | F43: =IF('表1-资金筹措及还本付息表'!G5=0,0,'表2-折旧摊销表'!D4) -> 0 | G43: =F43+'表2-折旧摊销表'!D4 -> 22434.778 | H43: =G43+'表2-折旧摊销表'!I35 -> 22434.778 | I43: =H43+'表2-折旧摊销表'!J35 -> 22434.778 | J43: =I43+'表2-折旧摊销表'!K35 -> 22434.778 | K43: =J43+'表2-折旧摊销表'!L35 -> 22434.778 | L43: =K43+'表2-折旧摊销表'!M35 -> 22434.778 | M43: =L43+'表2-折旧摊销表'!N35 -> 22434.778 | N43: =M43+'表2-折旧摊销表'!O35 -> 22434.778 | O43: =N43+'表2-折旧摊销表'!P35 -> 22434.778 | ... Z43: =Y43+'表2-折旧摊销表'!AA35 -> 22859.557
C44: 累计折旧 | D44: 万元 | G44: ='表2-折旧摊销表'!H27+'表2-折旧摊销表'!H36 -> 1420.8693 | H44: =G44+'表2-折旧摊销表'!I27+'表2-折旧摊销表'!I36 -> 2841.7386 | I44: =H44+'表2-折旧摊销表'!J27+'表2-折旧摊销表'!J36 -> 4262.6079 | J44: =I44+'表2-折旧摊销表'!K27+'表2-折旧摊销表'!K36 -> 5683.4771 | K44: =J44+'表2-折旧摊销表'!L27+'表2-折旧摊销表'!L36 -> 7104.3464 | L44: =K44+'表2-折旧摊销表'!M27+'表2-折旧摊销表'!M36 -> 8525.2157 | M44: =L44+'表2-折旧摊销表'!N27+'表2-折旧摊销表'!N36 -> 9946.085 | N44: =M44+'表2-折旧摊销表'!O27+'表2-折旧摊销表'!O36 -> 11366.954 | O44: =N44+'表2-折旧摊销表'!P27+'表2-折旧摊销表'!P36 -> 12787.824 | ... Z44: =Y44+'表2-折旧摊销表'!AA27+'表2-折旧摊销表'!AA36 -> 21716.579
C45: 固定资产减值准备 | D45: 万元
C46: 在建工程 | D46: 万元 | E46: ='表1-资金筹措及还本付息表'!F6 -> 24752.494
C47: 生产性生物资产 | D47: 万元
C48: 油气资产 | D48: 万元
C49: 使用权资产 | D49: 万元
C50: 无形资产 | D50: 万元 | E50: ='表2-折旧摊销表'!F32 -> 0 | F50: ='表2-折旧摊销表'!G32 -> 0 | G50: ='表2-折旧摊销表'!H32 -> 0 | H50: ='表2-折旧摊销表'!I32 -> 0 | I50: ='表2-折旧摊销表'!J32 -> 0 | J50: ='表2-折旧摊销表'!K32 -> 0 | K50: ='表2-折旧摊销表'!L32 -> 0 | L50: ='表2-折旧摊销表'!M32 -> 0 | ... Z50: ='表2-折旧摊销表'!AA32 -> 0
C51: 开发支出 | D51: 万元
C52: 商誉 | D52: 万元
C53: 长期待摊费用 | D53: 万元 | G53: ='表2-折旧摊销表'!H31 -> 0 | H53: ='表2-折旧摊销表'!I31 -> 0 | I53: ='表2-折旧摊销表'!J31 -> 0 | J53: ='表2-折旧摊销表'!K31 -> 0 | K53: ='表2-折旧摊销表'!L31 -> 0 | L53: ='表2-折旧摊销表'!M31 -> 0 | M53: ='表2-折旧摊销表'!N31 -> 0 | N53: ='表2-折旧摊销表'!O31 -> 0 | ... Z53: ='表2-折旧摊销表'!AA31 -> 0
C54: 递延所得税资产 | D54: 万元
C55: 其他非流动资产 | D55: 万元
C56: 其中：特准储备物资 | D56: 万元
B57: 2 | C57: 负债合计 | D57: 万元 | E57: =E58+E86 -> 19801.995 | F57: =F58+F86 -> 0 | G57: =G58+G86 -> 16630.783 | H57: =H58+H86 -> 15672.286 | I57: =I58+I86 -> 14713.789 | J57: =J58+J86 -> 13755.292 | K57: =K58+K86 -> 12796.795 | L57: =L58+L86 -> 11841.26 | ... Z57: =Z58+Z86 -> 0
B58: 2.1 | C58: 流动负债 | D58: 万元 | E58: =SUM(E59:E73)+E77+E79+SUM(E81:E85) -> 0 | F58: =SUM(F59:F73)+F77+F79+SUM(F81:F85) -> 0 | G58: =SUM(G59:G73)+G77+G79+SUM(G81:G85) -> 105 | H58: =SUM(H59:H73)+H77+H79+SUM(H81:H85) -> 105 | I58: =SUM(I59:I73)+I77+I79+SUM(I81:I85) -> 105 | J58: =SUM(J59:J73)+J77+J79+SUM(J81:J85) -> 105 | K58: =SUM(K59:K73)+K77+K79+SUM(K81:K85) -> 105 | L58: =SUM(L59:L73)+L77+L79+SUM(L81:L85) -> 105 | ... Z58: =SUM(Z59:Z73)+Z77+Z79+SUM(Z81:Z85) -> 0
C59: 短期借款 | D59: 万元 | E59: ='表1-资金筹措及还本付息表'!F74+'表1-资金筹措及还本付息表'!F64 -> 0 | F59: ='表1-资金筹措及还本付息表'!G74+'表1-资金筹措及还本付息表'!G64 -> 0 | G59: ='表1-资金筹措及还本付息表'!H74+'表1-资金筹措及还本付息表'!H64 -> 105 | H59: ='表1-资金筹措及还本付息表'!I74+'表1-资金筹措及还本付息表'!I64 -> 105 | I59: ='表1-资金筹措及还本付息表'!J74+'表1-资金筹措及还本付息表'!J64 -> 105 | J59: ='表1-资金筹措及还本付息表'!K74+'表1-资金筹措及还本付息表'!K64 -> 105 | K59: ='表1-资金筹措及还本付息表'!L74+'表1-资金筹措及还本付息表'!L64 -> 105 | L59: ='表1-资金筹措及还本付息表'!M74+'表1-资金筹措及还本付息表'!M64 -> 105 | ... Z59: ='表1-资金筹措及还本付息表'!AA74+'表1-资金筹措及还本付息表'!AA64 -> 0
C60: △向中央银行借款 | D60: 万元
C61: △拆入资金 | D61: 万元
C62: 交易性金融负债 | D62: 万元
C63: ☆以公允价值计量且其变动计入当期损益的金融负债 | D63: 万元
C64: 衍生金融负债 | D64: 万元
C65: 应付票据 | D65: 万元
C66: 应付账款 | D66: 万元
C67: 预收款项 | D67: 万元
C68: 合同负债 | D68: 万元
C69: △卖出回购金融资产款 | D69: 万元
C70: △吸收存款及同业存放 | D70: 万元
C71: △代理买卖证券款 | D71: 万元
... C85: 其他流动负债 | D85: 万元
B86: 2.2 | C86: 非流动负债 | D86: 万元 | E86: =SUM(E87:E89)+SUM(E92:E98) -> 19801.995 | F86: =SUM(F87:F89)+SUM(F92:F98) -> 0 | G86: =SUM(G87:G89)+SUM(G92:G98) -> 16525.783 | H86: =SUM(H87:H89)+SUM(H92:H98) -> 15567.286 | I86: =SUM(I87:I89)+SUM(I92:I98) -> 14608.789 | J86: =SUM(J87:J89)+SUM(J92:J98) -> 13650.292 | K86: =SUM(K87:K89)+SUM(K92:K98) -> 12691.795 | L86: =SUM(L87:L89)+SUM(L92:L98) -> 11736.26 | ... Z86: =SUM(Z87:Z89)+SUM(Z92:Z98) -> 0
C87: △保险合同准备金 | D87: 万元
C88: 长期借款 | D88: 万元 | E88: ='表1-资金筹措及还本付息表'!F44 -> 19801.995 | F88: =IF('表1-资金筹措及还本付息表'!G5=0,0,'表1-资金筹措及还本付息表'!G44) -> 0 | G88: ='表1-资金筹措及还本付息表'!H54 -> 18481.862 | H88: ='表1-资金筹措及还本付息表'!I54 -> 17161.729 | I88: ='表1-资金筹措及还本付息表'!J54 -> 15841.596 | J88: ='表1-资金筹措及还本付息表'!K54 -> 14521.463 | K88: ='表1-资金筹措及还本付息表'!L54 -> 13201.33 | L88: ='表1-资金筹措及还本付息表'!M54 -> 11881.197 | M88: ='表1-资金筹措及还本付息表'!N54 -> 10561.064 | N88: ='表1-资金筹措及还本付息表'!O54 -> 9240.9309 | ... Z88: ='表1-资金筹措及还本付息表'!AA54 -> 0
C89: 应付债券 | D89: 万元
C90: 其中：优先股 | D90: 万元
C91: 永续债 | D91: 万元
C92: 租赁负债 | D92: 万元
C93: 长期应付款 | D93: 万元
C94: 长期应付职工薪酬 | D94: 万元
C95: 预计负债 | D95: 万元
C96: 递延收益 | D96: 万元 | G96: =-'表4-收入税金表'!H45 -> -1956.0791 | H96: =-'表4-收入税金表'!I45 -> -1594.443 | I96: =-'表4-收入税金表'!J45 -> -1232.8068 | J96: =-'表4-收入税金表'!K45 -> -871.17065 | K96: =-'表4-收入税金表'!L45 -> -509.53449 | L96: =-'表4-收入税金表'!M45 -> -144.93675 | M96: =-'表4-收入税金表'!N45 -> 0 | N96: =-'表4-收入税金表'!O45 -> 0 | ... Z96: =-'表4-收入税金表'!AA45 -> 0
C97: 递延所得税负债 | D97: 万元
C98: 其他非流动负债 | D98: 万元
C99: 其中：特准储备基金 | D99: 万元
B100: 3 | C100: 所有者权益（或股东权益） | D100: 万元 | E100: =E108+E109+E112-E113+E114+E116+E117+E123+E124+E125+E126 -> 4950.4987 | F100: =F108+F109+F112-F113+F114+F116+F117+F123+F124+F125+F126 -> 0 | G100: =G108+G109+G112-G113+G114+G116+G117+G123+G124+G125+G126 -> 5158.3071 | H100: =H108+H109+H112-H113+H114+H116+H117+H123+H124+H125+H126 -> 5349.8714 | I100: =I108+I109+I112-I113+I114+I116+I117+I123+I124+I125+I126 -> 5567.7911 | J100: =J108+J109+J112-J113+J114+J116+J117+J123+J124+J125+J126 -> 5773.3371 | K100: =K108+K109+K112-K113+K114+K116+K117+K123+K124+K125+K126 -> 5998.9831 | L100: =L108+L109+L112-L113+L114+L116+L117+L123+L124+L125+L126 -> 6173.3501 | ... Z100: =Z108+Z109+Z112-Z113+Z114+Z116+Z117+Z123+Z124+Z125+Z126 -> 13205.055
C101: 实收资本（或股本） | D101: 万元 | E101: ='表1-资金筹措及还本付息表'!F11 -> 4950.4987 | F101: =IF('表1-资金筹措及还本付息表'!G5=0,0,E101+'表1-资金筹措及还本付息表'!G11) -> 0 | G101: =E101+'表1-资金筹措及还本付息表'!H11 -> 4995.4987 | H101: =G101+'表1-资金筹措及还本付息表'!I11 -> 4995.4987 | I101: =H101+'表1-资金筹措及还本付息表'!J11 -> 4995.4987 | J101: =I101+'表1-资金筹措及还本付息表'!K11 -> 4995.4987 | K101: =J101+'表1-资金筹措及还本付息表'!L11 -> 4995.4987 | L101: =K101+'表1-资金筹措及还本付息表'!M11 -> 4995.4987 | M101: =L101+'表1-资金筹措及还本付息表'!N11 -> 4995.4987 | N101: =M101+'表1-资金筹措及还本付息表'!O11 -> 4995.4987 | O101: =N101+'表1-资金筹措及还本付息表'!P11 -> 4995.4987 | ... Z101: =Y101+'表1-资金筹措及还本付息表'!AA11 -> 4995.4987
C102: 国家资本 | D102: 万元
C103: 国有法人资本 | D103: 万元
C104: 集体资本 | D104: 万元
C105: 民营资本 | D105: 万元
C106: 外商资本 | D106: 万元
C107: #减：已归还投资 | D107: 万元
C108: 实收资本（或股本）净额 | D108: 万元 | E108: =E101-E107 -> 4950.4987 | F108: =IF('表1-资金筹措及还本付息表'!G5=0,0,F101-F107) -> 0 | G108: =G101-G107 -> 4995.4987 | H108: =H101-H107 -> 4995.4987 | I108: =I101-I107 -> 4995.4987 | J108: =J101-J107 -> 4995.4987 | K108: =K101-K107 -> 4995.4987 | L108: =L101-L107 -> 4995.4987 | M108: =M101-M107 -> 4995.4987 | N108: =N101-N107 -> 4995.4987 | ... Z108: =Z101-Z107 -> 4995.4987
C109: 其他权益工具 | D109: 万元
C110: 其中：优先股 | D110: 万元
C111: 永续债 | D111: 万元
C112: 资本公积 | D112: 万元
C113: 减：库存股 | D113: 万元
C114: 其他综合收益 | D114: 万元
C115: 其中：外币报表折算差额 | D115: 万元
...

Sheet 财务指标表
A1: 序号 | B1: 项目 | C1: 单位 | D1: 数值
A2: 1 | B2: 系统容量
A3: 1.1 | B3: 风电系统容量 | C3: MW | D3: =参数输入表!H13 -> 50
A4: 1.2 | B4: 储能系统容量 | C4: MW/MWh | D4: 参数输入表!H14/参数输入表!H15
A5: 2 | B5: 年售电量
A6: 2.1 | B6: 风电系统年上网电量 | C6: MWh | D6: ='表4-收入税金表'!D9/20*10 -> 35403.53
A7: 2.2 | B7: 数能融合年消纳电量 | C7: MWh | D7: ='表4-收入税金表'!D14/20*10 -> 69502.55
A8: 3 | B8: 年均电价
A9: 3.1 | B9: 风电系统经营期年均电价（含增值税） | C9: 元/kWh | D9: ='表4-收入税金表'!D8/'表4-收入税金表'!D9 -> 0.26938053
A10: 3.2 | B10: 数能融合经营期机制电价（含增值税） | C10: 元/kWh | D10: ='表4-收入税金表'!D13/'表4-收入税金表'!D14 -> 0.26548673
A11: 4 | B11: 项目总投资 | C11: 万元 | D11: ='表1-资金筹措及还本付息表'!D6 -> 24902.494
A12: 5 | B12: 建设投资 | C12: 万元 | D12: =参数输入表!H77 -> 24402.36 | F12: 表三成本表C6项生产成本运营期平均值做敏感性分析、蒙特卡洛
A13: 6 | B13: 建设期利息 | C13: 万元 | D13: =参数输入表!H78 -> 350.1335
A14: 7 | B14: 流动资金 | C14: 万元 | D14: =参数输入表!H81 -> 150
A15: 8 | B15: 销售收入总额（不含增值税） | C15: 万元 | D15: ='表4-收入税金表'!D5 -> 55978.052
A16: 9 | B16: 总成本费用 | C16: 万元 | D16: ='表3-成本费用表'!D5 -> 40115.554
A17: 10 | B17: 销售税金附加总额 | C17: 万元 | D17: ='表4-收入税金表'!D46 -> 588.50523
A18: 11 | B18: 利润总额 | C18: 万元 | D18: ='表5-利润表-资本金'!D14 -> 17726.098
A19: 12 | B19: 项目投资回收期（所得税前） | C19: 年 | D19: ='表8-现金流量表-全投资'!D29 -> 10.583692
A20: 13 | B20: 项目投资回收期（所得税后） | C20: 年 | D20: ='表8-现金流量表-全投资'!D28 -> 11.167916
A21: 14 | B21: 项目投资财务内部收益率（所得税前） | C21: % | D21: ='表8-现金流量表-全投资'!D26 -> 0.078490818 | E21: 反算依据指标，数值由操作者自动输入
A22: 15 | B22: 项目投资财务内部收益率（所得税后） | C22: % | D22: ='表8-现金流量表-全投资'!D27 -> 0.067843501
A23: 16 | B23: 资本金财务内部收益率 | C23: % | D23: ='表6-现金流量表-资本金'!D34 -> 0.13622615
A24: 17 | B24: 资产负债率（最大值） | C24: % | D24: ='表10-资产负债表'!C129 -> 0.8
A25: 18 | B25: 盈亏平衡点（生产能力利用率） | C25: % | D25: ='表3-成本费用表'!D5/('表4-收入税金表'!D5-'表4-收入税金表'!D46) -> 0.72424412
