Workbook
Name ____________PH1: '[1]SW-TEO'!#REF!

Sheet 说明
B2: 参数输入表中：
C3: 标黄项为相对固定模块
C4: 标绿项为对成本类、收入类数据进行分类，成本参数按照：“生产成本/销售费用/管理费用/研发费用”划分；收入参数按照：“营业收入/其他收入/营业外收入”划分
C5: 标橙项为固定的分类原则
C6: 标紫项为在参数表中不需要手动输入、勾选的内容，根据其他输入参数自动计算得出，可不在参数输入界面呈现。
C7: 标红项为引用同样红色sheet中相关数据
C8: 标蓝项为可不展示内容，大部分为中间过程计算表/中间计算过程
C10: 【成本费用表】、【收入税金表】、【利润表】体现的是会计报表相关数据，涉及到的收入及成本数据均为不含增值税金额，不含税金额计算公式为： 【含税金额/（1+增值税税率）】；增值税计算公式为：【不含税金额*增值税税率】或【含税金额/（1+增值税税率）*增值税税率】
C12: 【成本费用表】中各项成本按照：一、营业总成本：（1）生产成本；（2）销售费用；（3）管理费用；（4）研发费用；（5）财务费用；二、营业外支出，进行划分，其中需重点关注长期待摊费用成本项，在成本费用表中以逐年摊销的形式出现。
C14: 【成本费用表】中标蓝的内容为不展示内容，为中间计算表，其中数据均还原成含税金额，用于后续的【现金流量表】引用
C16: 【收入表】中各项收入按照：一、营业收入；二、其他收入；三、营业外收入，营业收入及营业外收入需展示二级目录（具体的收入项）
C18: 【现金流量表】体现的是公司账上实际收到或支付的现金流，因此涉及到的收入及成本数据均为含增值税金额，数据需引用成本费用表中还原后的含税金额或参数输入表中的含税金额。同时，收入数据需关注付款比例及回款期限的应用。原理为当年的部分比例收入的滞后支付，第一年的某项收入现金流为预测现金流*首年支付比例，第二年的某项收入现金流为：当年预测现金流*当年支付比例+上一年预测现金流*（1-上一年支付比例）
C20: 【现金流量表-财务计划】增加IF判定条件，当某年的累计盈余资金<“流动资金（本项目为960万元）”+次年的“生产经营现金支出合计（成本费用表标蓝表第一行）”，给出明显提示（允许用户在参数输入界面填写各年度短期借款当期借款金额及还本金额，再重新生成新的结果）

Sheet 可抵扣进项税
B2: 投资概算 | C2: 序号 | D2: 科目 | E2: 计取基数 | F2: 进项税率 | G2: 进项税
C3: 1 | D3: 设备购置费 | F3: =参数输入表!H709 -> 0.13 | G3: =E3/(1+F3)*F3 -> 0
C4: 2 | D4: 建安工程费 | F4: =参数输入表!H710 -> 0.09 | G4: =E4/(1+F4)*F4 -> 0
C5: 3 | D5: 其他费用 | F5: =参数输入表!H711 -> 0.06 | G5: =E5/(1+F5)*F5 -> 0
C6: 4 | D6: 预备费 | F6: =参数输入表!H712 -> 0 | G6: =E6/(1+F6)*F6 -> 0
C7: 5 | D7: 送出线路投资 | F7: =参数输入表!H714 -> 0.09 | G7: =E7/(1+F7)*F7 -> 0
C8: 6 | D8: 配套支持资金 | F8: =参数输入表!H715 -> 0 | G8: =E8/(1+F8)*F8 -> 0
C9: 7 | D9: 静态总投资
C10: 8 | D10: 建设期利息
C11: 9 | D11: 动态总投资
C12: 10 | D12: 流动资金
C13: 11 | D13: 可抵扣进项税 | E13: =SUM(G3:G8) -> 0
C17: 可抵扣进项税为后台计算，不需要作为成果展示

Sheet 参数输入表
G1: 【风储】财务评价计算模型边界条件输入参数表
B3: 类别 | C3: 序号 | D3: 参数 | E3: 操作类型 | F3: 收入/成本归类 | G3: 参数释义/计算公式 | H3: 数值 | I3: 单位 | J3: 取值说明 | K3: 备注
C4: 1 | D4: 项目规模 | E4: 手动输入 | G4: 按照算力规模 | H4: 1000 | I4: p
C5: 2 | D5: 项目变电容量 | E5: 手动输入 | H5: 5 | I5: MVa
C6: 3 | D6: 机柜总功率 | E6: 手动输入 | H6: 4000 | I6: kW
C7: 4 | D7: 全年用电量 | J7: 全年用电量大于风（光）储全年发电量，风（光）储上网电量为0，如果全年用电量小于风（光）储全年发电量，上网电量=风（光）储全年发电量-全年用电量；
D8: 运营期第1年 | E8: 手动输入 | H8: 120000 | I8: MWh
D9: 运营期第2年 | E9: 手动输入 | H9: 120000 | I9: MWh
D10: 运营期第3年 | E10: 手动输入 | H10: 120000 | I10: MWh
D11: 运营期第4年 | E11: 手动输入 | H11: 120000 | I11: MWh
D12: 运营期第5年 | E12: 手动输入 | H12: 120000 | I12: MWh
D13: 运营期第6年 | E13: 手动输入 | H13: 120000 | I13: MWh
D14: 运营期第7年 | E14: 手动输入 | H14: 120000 | I14: MWh
D15: 运营期第8年 | E15: 手动输入 | H15: 120000 | I15: MWh
D16: 运营期第9年 | E16: 手动输入 | H16: 120000 | I16: MWh
D17: 运营期第10年 | E17: 手动输入 | H17: 120000 | I17: MWh
D18: 运营期第11年 | E18: 手动输入 | H18: 120000 | I18: MWh
D19: 运营期第12年 | E19: 手动输入 | H19: 120000 | I19: MWh
... D27: 运营期第20年 | E27: 手动输入 | H27: 120000 | I27: MWh
C28: 5 | D28: PUE | E28: 手动输入 | H28: 1.25
C29: 5 | D29: 是否有新能源接入 | E29: 手动输入 | G29: 直连式新能源 源网核储一体化 | H29: 否
C30: 6 | D30: 新能源类型 | E30: 下拉菜单选择 | G30: 风储、光储、风光储
D31: 风电接入比例 | E31: 手动输入 | H31: 0.5
D32: 光伏接入比例 | E32: 手动输入 | H32: 0.4
C33: 7 | D33: 新能源接入电量 | J33: 还未设置链接
D34: 光伏接入电量
D35: 运营期第1年 | G35: 取值于风光储发电量 | H35: =[2]参数输入表!$H21*[2]参数输入表!$H77 -> 47520 | I35: MWh
D36: 运营期第2年 | G36: 取值于风光储发电量 | H36: =[2]参数输入表!$H22*[2]参数输入表!$H78 -> 47306.16 | I36: MWh
D37: 运营期第3年 | G37: 取值于风光储发电量 | H37: =[2]参数输入表!$H23*[2]参数输入表!$H79 -> 47093.282 | I37: MWh
D38: 运营期第4年 | G38: 取值于风光储发电量 | H38: =[2]参数输入表!$H24*[2]参数输入表!$H80 -> 46881.363 | I38: MWh
D39: 运营期第5年 | G39: 取值于风光储发电量 | H39: =[2]参数输入表!$H25*[2]参数输入表!$H81 -> 46670.396 | I39: MWh
D40: 运营期第6年 | G40: 取值于风光储发电量 | H40: =[2]参数输入表!$H26*[2]参数输入表!$H82 -> 65044.531 | I40: MWh
D41: 运营期第7年 | G41: 取值于风光储发电量 | H41: =[2]参数输入表!$H27*[2]参数输入表!$H83 -> 64751.831 | I41: MWh
D42: 运营期第8年 | G42: 取值于风光储发电量 | H42: =[2]参数输入表!$H28*[2]参数输入表!$H84 -> 64460.448 | I42: MWh
D43: 运营期第9年 | G43: 取值于风光储发电量 | H43: =[2]参数输入表!$H29*[2]参数输入表!$H85 -> 64170.376 | I43: MWh
D44: 运营期第10年 | G44: 取值于风光储发电量 | H44: =[2]参数输入表!$H30*[2]参数输入表!$H86 -> 63881.609 | I44: MWh
D45: 运营期第11年 | G45: 取值于风光储发电量 | H45: =[2]参数输入表!$H31*[2]参数输入表!$H87 -> 63594.142 | I45: MWh
D46: 运营期第12年 | G46: 取值于风光储发电量 | H46: =[2]参数输入表!$H32*[2]参数输入表!$H88 -> 63307.968 | I46: MWh
... D54: 运营期第20年 | G54: 取值于风光储发电量 | H54: =[2]参数输入表!$H40*[2]参数输入表!$H96 -> 61064.456 | I54: MWh
D55: 风电接入电量
D56: 运营期第1年 | G56: 取值于风光储发电量 | H56: =[3]参数输入表!$H$17*[3]参数输入表!$H45 -> 53463.5 | I56: MWh
D57: 运营期第2年 | G57: 取值于风光储发电量 | H57: =[3]参数输入表!$H$17*[3]参数输入表!$H46 -> 53463.5 | I57: MWh
D58: 运营期第3年 | G58: 取值于风光储发电量 | H58: =[3]参数输入表!$H$17*[3]参数输入表!$H47 -> 53463.5 | I58: MWh
D59: 运营期第4年 | G59: 取值于风光储发电量 | H59: =[3]参数输入表!$H$17*[3]参数输入表!$H48 -> 53463.5 | I59: MWh
D60: 运营期第5年 | G60: 取值于风光储发电量 | H60: =[3]参数输入表!$H$17*[3]参数输入表!$H49 -> 53463.5 | I60: MWh
D61: 运营期第6年 | G61: 取值于风光储发电量 | H61: =[3]参数输入表!$H$17*[3]参数输入表!$H50 -> 74848.9 | I61: MWh
D62: 运营期第7年 | G62: 取值于风光储发电量 | H62: =[3]参数输入表!$H$17*[3]参数输入表!$H51 -> 74848.9 | I62: MWh
D63: 运营期第8年 | G63: 取值于风光储发电量 | H63: =[3]参数输入表!$H$17*[3]参数输入表!$H52 -> 74848.9 | I63: MWh
D64: 运营期第9年 | G64: 取值于风光储发电量 | H64: =[3]参数输入表!$H$17*[3]参数输入表!$H53 -> 74848.9 | I64: MWh
D65: 运营期第10年 | G65: 取值于风光储发电量 | H65: =[3]参数输入表!$H$17*[3]参数输入表!$H54 -> 74848.9 | I65: MWh
D66: 运营期第11年 | G66: 取值于风光储发电量 | H66: =[3]参数输入表!$H$17*[3]参数输入表!$H55 -> 74848.9 | I66: MWh
D67: 运营期第12年 | G67: 取值于风光储发电量 | H67: =[3]参数输入表!$H$17*[3]参数输入表!$H56 -> 74848.9 | I67: MWh
... D75: 运营期第20年 | G75: 取值于风光储发电量 | H75: =[3]参数输入表!$H$17*[3]参数输入表!$H64 -> 74848.9 | I75: MWh
D76: 储能接入电量
D77: 运营期第1年 | G77: 取值于风光储发电量 | H77: =[4]参数输入表!$H295*[4]参数输入表!$H382 -> 2295 | I77: MWh
D78: 运营期第2年 | G78: 取值于风光储发电量 | H78: =[4]参数输入表!$H296*[4]参数输入表!$H383 -> 2249.1 | I78: MWh
D79: 运营期第3年 | G79: 取值于风光储发电量 | H79: =[4]参数输入表!$H297*[4]参数输入表!$H384 -> 2203.2 | I79: MWh
D80: 运营期第4年 | G80: 取值于风光储发电量 | H80: =[4]参数输入表!$H298*[4]参数输入表!$H385 -> 2157.3 | I80: MWh
D81: 运营期第5年 | G81: 取值于风光储发电量 | H81: =[4]参数输入表!$H299*[4]参数输入表!$H386 -> 2111.4 | I81: MWh
D82: 运营期第6年 | G82: 取值于风光储发电量 | H82: =[4]参数输入表!$H300*[4]参数输入表!$H387 -> 2065.5 | I82: MWh
D83: 运营期第7年 | G83: 取值于风光储发电量 | H83: =[4]参数输入表!$H301*[4]参数输入表!$H388 -> 2019.6 | I83: MWh
D84: 运营期第8年 | G84: 取值于风光储发电量 | H84: =[4]参数输入表!$H302*[4]参数输入表!$H389 -> 1973.7 | I84: MWh
D85: 运营期第9年 | G85: 取值于风光储发电量 | H85: =[4]参数输入表!$H303*[4]参数输入表!$H390 -> 1927.8 | I85: MWh
D86: 运营期第10年 | G86: 取值于风光储发电量 | H86: =[4]参数输入表!$H304*[4]参数输入表!$H391 -> 1881.9 | I86: MWh
D87: 运营期第11年 | G87: 取值于风光储发电量 | H87: =[4]参数输入表!$H305*[4]参数输入表!$H392 -> 2295 | I87: MWh
D88: 运营期第12年 | G88: 取值于风光储发电量 | H88: =[4]参数输入表!$H306*[4]参数输入表!$H393 -> 2249.1 | I88: MWh
... D96: 运营期第20年 | G96: 取值于风光储发电量 | H96: =[4]参数输入表!$H314*[4]参数输入表!$H401 -> 1881.9 | I96: MWh
C97: 8 | D97: 新能源装机比例 | E97: 手动输入 | G97: 新能源装机容量/数据中心总负荷 | I97: %
C98: 9 | D98: 电网过网费 | E98: 手动输入 | G98: 0 | H98: 元/千瓦时 | I98: 根据消纳的风光储电量，根据项目实际情况
B99: 基础信息 | C99: 10 | D99: 建设期 | E99: 手动输入 | H99: 2 | I99: 年
C100: 11 | D100: 动工年月 | E100: 手动输入/下拉菜单选择【日历】 | I100: 年/月
C101: 12 | D101: 施工进度安排 | I101: %
D102: 建设期第1年 | E102: 手动输入 | H102: 0.6
D103: 建设期第2年 | E103: 手动输入 | H103: 0.4
D104: 建设期第3年 | E104: 手动输入 | H104: 0
D105: 建设期第4年 | E105: 手动输入 | H105: 0
C106: 13 | D106: 运营期 | E106: 手动输入 | H106: 20 | I106: 年 | J106: 原则上按照20年考虑
C107: 14 | D107: 项目所在地 | E107: 下拉菜单选择 | J107: 判定是否属于西部地区
C108: 15 | D108: 所在省份 | E108: 下拉菜单选择
C109: 16 | D109: 所在市、县 | E109: 下拉菜单选择
B110: 收入 | C110: 1 | D110: 裸机柜出租 | E110: 手动输入 | F110: 收入
D111: 运营期第1年 | E111: 手动输入
D112: 机柜类型24kw
D113: 租赁数量 | E113: 手动输入 | H113: 292 | I113: 台
D114: 租赁单价 | E114: 手动输入 | H114: 41.328 | I114: 万元/台
D115: 机柜类型12kw（可预留自动补充）
D116: 租赁数量 | E116: 手动输入 | H116: 136 | I116: 台
D117: 租赁单价 | E117: 手动输入 | H117: 41.328 | I117: 万元/台
D118: 运营期第2年
D119: 机柜类型24kw
D120: 租赁数量 | E120: 手动输入 | H120: 292 | I120: 台
D121: 租赁单价 | E121: 手动输入 | H121: 41.328 | I121: 万元/台
D122: 机柜类型12kw（可预留自动补充）
D123: 租赁数量 | E123: 手动输入 | H123: 136 | I123: 台
D124: 租赁单价 | E124: 手动输入 | H124: 41.328 | I124: 万元/台
D125: 运营期第3年
D126: 机柜类型24kw
D127: 租赁数量 | E127: 手动输入 | H127: 292 | I127: 台
D128: 租赁单价 | E128: 手动输入 | H128: 41.328 | I128: 万元/台
D129: 机柜类型12kw（可预留自动补充）
...

Sheet 表1-资金筹措及还本付息表
B2: 资金筹措表
B3: 序号 | C3: 建设期 | D3: 合计 | E3: 单位 | F3: 建设期 | H3: 运营期
F4: 1 | G4: 2 | H4: 1 | I4: 2 | J4: 3 | K4: 4 | L4: 5 | M4: 6 | N4: 7 | O4: 8 | P4: 9 | Q4: 10 | R4: 11 | S4: 12 | T4: 13 | U4: 14 | V4: 15 | W4: 16 | X4: 17 | Y4: 18 | Z4: 19 | AA4: 20
C5: 施工进度安排 | D5: =SUM(F5:M5) -> 1 | F5: =参数输入表!H102 -> 0.6 | G5: =参数输入表!H103 -> 0.4
B6: 1 | C6: 动态总投资（自主投资） | D6: =D7+D8+D9 -> 67671.182 | E6: 万元 | F6: =SUM(F7:F9) -> 39711.143 | G6: =SUM(G7:G9) -> 27579.04 | H6: =SUM(H7:H9) -> 381
B7: 1.1 | C7: 静态总投资（自主投资） | D7: =SUM(F7:AA7) -> 65278.39 | E7: 万元 | F7: =参数输入表!H348*F5 -> 39167.034 | G7: =参数输入表!$H$348*G5 -> 26111.356 | H7: 0
B8: 1.2 | C8: 建设期利息 | D8: =SUM(F8:AA8) -> 2011.7923 | E8: 万元 | F8: =F17 -> 544.10881 | G8: =G17 -> 1467.6835 | H8: =H17 -> 0
B9: 1.3 | C9: 流动资金 | D9: =SUM(F9:AA9) -> 381 | E9: 万元 | F9: 0 | G9: 0 | H9: =参数输入表!H351 -> 381
B10: 2 | C10: 资金来源
B11: 2.1 | C11: 资本金 | D11: =SUM(F11:AA11) -> 13705.21 | E11: 万元 | F11: =F6*(参数输入表!$H$355+0.3346%) -> 8075.102 | G11: =G6*参数输入表!$H$355 -> 5515.8079 | H11: =H6*参数输入表!$H$363 -> 114.3
B12: 2.1.1 | C12: 用于建设投资 | D12: =SUM(F12:AA12) -> 13590.91 | E12: 万元 | F12: =F11-F13-F14 -> 8075.102 | G12: =G11-G13-G14 -> 5515.8079 | H12: 0
B13: 2.1.2 | C13: 用于建设期利息 | D13: =SUM(F13:AA13) -> 0 | E13: 万元 | F13: 0 | G13: 0 | H13: 0
B14: 2.1.3 | C14: 用于流动资金 | D14: =SUM(F14:AA14) -> 114.3 | F14: 0 | G14: 0 | H14: =H9*参数输入表!H363 -> 114.3
B15: 2.2 | C15: 债务资金 | D15: =SUM(F15:M15) -> 53965.972 | E15: 万元 | F15: =SUM(F16:F18) -> 31636.041 | G15: =SUM(G16:G18) -> 22063.232 | H15: =SUM(H16:H18) -> 266.7
B16: 2.2.1 | C16: 用于建设投资 | D16: =SUM(F16:AA16) -> 51687.48 | E16: 万元 | F16: =F7-F12 -> 31091.932 | G16: =G7-G12 -> 20595.548 | H16: =H7-H12 -> 0
B17: 2.1.2 | C17: 用于建设期利息 | D17: =SUM(F17:AA17) -> 2011.7923 | E17: 万元 | F17: =F16/2*参数输入表!$H$358*(12/12) -> 544.10881 | G17: =IF(G5>0,((G16/2+F15)*参数输入表!$H$358)*(12/12),0) -> 1467.6835 | H17: 0
B18: 2.1.3 | C18: 用于流动资金 | D18: =SUM(F18:AA18) -> 266.7 | E18: 万元 | F18: 0 | G18: 0 | H18: =H9-H14 -> 266.7
B20: 营运资本变动
B21: 序号 | C21: 项目 | D21: 合计 | E21: 单位 | F21: 建设期 | H21: 运营期
F22: 1 | G22: 2 | H22: 1 | I22: 2 | J22: 3 | K22: 4 | L22: 5 | M22: 6 | N22: 7 | O22: 8 | P22: 9 | Q22: 10 | R22: 11 | S22: 12 | T22: 13 | U22: 14 | V22: 15 | W22: 16 | X22: 17 | Y22: 18 | Z22: 19 | AA22: 20
B23: 1 | C23: 流动资产 | D23: =SUM(F23:AA23) -> 217051.74 | E23: 万元 | F23: =SUM(F24:F27) -> 2674.206 | G23: =SUM(G24:G27) -> 4457.01 | H23: =SUM(H24:H27) -> 9309.1267 | I23: =SUM(I24:I27) -> 8550.2024 | J23: =SUM(J24:J27) -> 7998.4677 | K23: =SUM(K24:K27) -> 7634.4897 | L23: =SUM(L24:L27) -> 7440.7785 | M23: =SUM(M24:M27) -> 6648.9004 | ... AA23: =SUM(AA24:AA27) -> 22623.45
C24: 货币资金 | D24: =SUM(F24:AA24) -> 198161.49 | E24: 万元 | F24: ='表9-现金流量表-财务计划'!F34 -> 0 | G24: ='表9-现金流量表-财务计划'!G34 -> 0 | H24: ='表9-现金流量表-财务计划'!H34 -> 5894.3293 | I24: ='表9-现金流量表-财务计划'!I34 -> 5725.3675 | J24: ='表9-现金流量表-财务计划'!J34 -> 5764.1741 | K24: ='表9-现金流量表-财务计划'!K34 -> 5991.3142 | L24: ='表9-现金流量表-财务计划'!L34 -> 6389.2964 | M24: ='表9-现金流量表-财务计划'!M34 -> 6082.1577 | ... AA24: ='表9-现金流量表-财务计划'!AA34 -> 22623.45
C25: 应收账款 | D25: =SUM(F25:AA25) -> 0 | E25: 万元 | H25: ='表4-收入税金表'!H54 -> 0 | I25: ='表4-收入税金表'!I54 -> 0 | J25: ='表4-收入税金表'!J54 -> 0 | K25: ='表4-收入税金表'!K54 -> 0 | L25: ='表4-收入税金表'!L54 -> 0 | M25: ='表4-收入税金表'!M54 -> 0 | N25: ='表4-收入税金表'!N54 -> 0 | O25: ='表4-收入税金表'!O54 -> 0 | ... AA25: ='表4-收入税金表'!AA54 -> 0
C26: 存货 | D26: =SUM(F26:AA26) -> 0 | E26: 万元
C27: 其他流动资产（留抵税额） | D27: =SUM(F27:AA27) -> 18890.252 | E27: 万元 | F27: ='表4-收入税金表'!F39 -> 2674.206 | G27: ='表4-收入税金表'!G39 -> 4457.01 | H27: ='表4-收入税金表'!H39 -> 3414.7974 | I27: ='表4-收入税金表'!I39 -> 2824.8348 | J27: ='表4-收入税金表'!J39 -> 2234.2936 | K27: ='表4-收入税金表'!K39 -> 1643.1755 | L27: ='表4-收入税金表'!L39 -> 1051.4822 | M27: ='表4-收入税金表'!M39 -> 566.74268 | ... AA27: ='表4-收入税金表'!AA39 -> 0
B28: 2 | C28: 流动负债 | D28: =SUM(F28:AA28) -> 43563.636 | E28: 万元 | F28: =SUM(F29:F34) -> 0 | G28: =SUM(G29:G34) -> 0 | H28: =SUM(H29:H34) -> 3203.0305 | I28: =SUM(I29:I34) -> 1129.9634 | J28: =SUM(J29:J34) -> 1052.5226 | K28: =SUM(K29:K34) -> 994.50217 | L28: =SUM(L29:L34) -> 953.95887 | M28: =SUM(M29:M34) -> 854.70173 | ... AA28: =SUM(AA29:AA34) -> 4148.7008
C29: 短期借款 | D29: =SUM(F29:AA29) -> 266.7 | E29: 万元 | F29: =F64+F74 -> 0 | G29: =G60+G70 -> 0 | H29: =H60+H70 -> 266.7 | I29: =I60+I70 -> 0 | J29: =J60+J70 -> 0 | K29: =K60+K70 -> 0 | L29: =L60+L70 -> 0 | M29: =M60+M70 -> 0 | N29: =N60+N70 -> 0 | ... AA29: =AA60+AA70 -> 0
C30: 预收款项 | D30: =SUM(F30:AA30) -> 0 | E30: 万元
C31: 应付职工薪酬 | D31: =SUM(F31:AA31) -> 15360 | E31: 万元 | H31: ='表3-成本费用表'!H52 -> 768 | I31: ='表3-成本费用表'!I52 -> 768 | J31: ='表3-成本费用表'!J52 -> 768 | K31: ='表3-成本费用表'!K52 -> 768 | L31: ='表3-成本费用表'!L52 -> 768 | M31: ='表3-成本费用表'!M52 -> 768 | N31: ='表3-成本费用表'!N52 -> 768 | O31: ='表3-成本费用表'!O52 -> 768 | ... AA31: ='表3-成本费用表'!AA52 -> 768
C32: 应交税费 | D32: =SUM(F32:AA32) -> 17278.058 | E32: 万元 | H32: ='表6-现金流量表-资本金'!H24+'表6-现金流量表-资本金'!H25+'表6-现金流量表-资本金'!H29 -> 1707.3469 | I32: ='表6-现金流量表-资本金'!I24+'表6-现金流量表-资本金'!I25+'表6-现金流量表-资本金'!I29 -> 0 | J32: ='表6-现金流量表-资本金'!J24+'表6-现金流量表-资本金'!J25+'表6-现金流量表-资本金'!J29 -> 0 | K32: ='表6-现金流量表-资本金'!K24+'表6-现金流量表-资本金'!K25+'表6-现金流量表-资本金'!K29 -> 0 | L32: ='表6-现金流量表-资本金'!L24+'表6-现金流量表-资本金'!L25+'表6-现金流量表-资本金'!L29 -> 0 | M32: ='表6-现金流量表-资本金'!M24+'表6-现金流量表-资本金'!M25+'表6-现金流量表-资本金'!M29 -> 0 | N32: ='表6-现金流量表-资本金'!N24+'表6-现金流量表-资本金'!N25+'表6-现金流量表-资本金'!N29 -> 0 | O32: ='表6-现金流量表-资本金'!O24+'表6-现金流量表-资本金'!O25+'表6-现金流量表-资本金'!O29 -> 573.1091 | ... AA32: ='表6-现金流量表-资本金'!AA24+'表6-现金流量表-资本金'!AA25+'表6-现金流量表-资本金'!AA29 -> 1760.9675
C33: 应付股利 | D33: =SUM(F33:AA33) -> 10658.879 | E33: 万元 | H33: ='表5-利润表-资本金'!H31 -> 460.98366 | I33: ='表5-利润表-资本金'!I31 -> 361.96344 | J33: ='表5-利润表-资本金'!J31 -> 284.52264 | K33: ='表5-利润表-资本金'!K31 -> 226.50217 | L33: ='表5-利润表-资本金'!L31 -> 185.95887 | M33: ='表5-利润表-资本金'!M31 -> 86.701732 | N33: ='表5-利润表-资本金'!N31 -> 96.577532 | O33: ='表5-利润表-资本金'!O31 -> 114.08097 | ... AA33: ='表5-利润表-资本金'!AA31 -> 1619.7333
C34: 其他流动负债 | D34: =SUM(F34:AA34) -> 0 | E34: 万元
B36: 借款还本付息表（长期借款）
B37: 序号 | C37: 项目 | D37: 合计 | E37: 单位 | F37: 建设期 | H37: 运营期
F38: 1 | G38: 2 | H38: 1 | I38: 2 | J38: 3 | K38: 4 | L38: 5 | M38: 6 | N38: 7 | O38: 8 | P38: 9 | Q38: 10 | R38: 11 | S38: 12 | T38: 13 | U38: 14 | V38: 15 | W38: 16 | X38: 17 | Y38: 18 | Z38: 19 | AA38: 20
B39: 1 | C39: 期初借款累计 | E39: 万元 | F39: 0 | G39: =F44 -> 31636.041 | H39: =G44 -> 53699.272 | I39: =H44 -> 50916.304 | J39: =I44 -> 48035.931 | K39: =J44 -> 45054.746 | L39: =K44 -> 41969.219 | M39: =L44 -> 38775.699 | N39: =M44 -> 35470.405 | ... AA39: =Z44 -> 0
B40: 2 | C40: 当期借款 | D40: =SUM(F40:AA40) -> 53699.272 | E40: 万元 | F40: =F15 -> 31636.041 | G40: =G15 -> 22063.232
B41: 3 | C41: 当期还本付息 | D41: =SUM(F41:AA41) -> 69936.646 | E41: 万元 | H41: =-PMT(参数输入表!$H$359,参数输入表!$H$362,'表1-资金筹措及还本付息表'!$D$40) -> 4662.443 | I41: =-PMT(参数输入表!$H$359,参数输入表!$H$362,'表1-资金筹措及还本付息表'!$D$40) -> 4662.443 | J41: =-PMT(参数输入表!$H$359,参数输入表!$H$362,'表1-资金筹措及还本付息表'!$D$40) -> 4662.443 | K41: =-PMT(参数输入表!$H$359,参数输入表!$H$362,'表1-资金筹措及还本付息表'!$D$40) -> 4662.443 | L41: =-PMT(参数输入表!$H$359,参数输入表!$H$362,'表1-资金筹措及还本付息表'!$D$40) -> 4662.443 | M41: =-PMT(参数输入表!$H$359,参数输入表!$H$362,'表1-资金筹措及还本付息表'!$D$40) -> 4662.443 | N41: =-PMT(参数输入表!$H$359,参数输入表!$H$362,'表1-资金筹措及还本付息表'!$D$40) -> 4662.443 | O41: =-PMT(参数输入表!$H$359,参数输入表!$H$362,'表1-资金筹措及还本付息表'!$D$40) -> 4662.443 | ... V41: =-PMT(参数输入表!$H$359,参数输入表!$H$362,'表1-资金筹措及还本付息表'!$D$40) -> 4662.443
C42: 其中：还本（等额本息） | D42: =SUM(F42:AA42) -> 53699.272 | E42: 万元 | H42: =H41-H43 -> 2782.9685 | I42: =I41-I43 -> 2880.3724 | J42: =J41-J43 -> 2981.1854 | K42: =K41-K43 -> 3085.5269 | L42: =L41-L43 -> 3193.5204 | M42: =M41-M43 -> 3305.2936 | N42: =N41-N43 -> 3420.9789 | O42: =O41-O43 -> 3540.7131 | ... V42: =V41-V43 -> 4504.7759
C43: 付息 | D43: =SUM(F43:AA43) -> 16237.373 | E43: 万元 | H43: =(H39+H40/2)*参数输入表!$H$359 -> 1879.4745 | I43: =(I39+I40/2)*参数输入表!$H$359 -> 1782.0706 | J43: =(J39+J40/2)*参数输入表!$H$359 -> 1681.2576 | K43: =(K39+K40/2)*参数输入表!$H$359 -> 1576.9161 | L43: =(L39+L40/2)*参数输入表!$H$359 -> 1468.9227 | M43: =(M39+M40/2)*参数输入表!$H$359 -> 1357.1495 | N43: =(N39+N40/2)*参数输入表!$H$359 -> 1241.4642 | O43: =(O39+O40/2)*参数输入表!$H$359 -> 1121.7299 | ... V43: =(V39+V40/2)*参数输入表!$H$359 -> 157.66716
B44: 4 | C44: 期末借款余额 | D44: =V44 -> -3.0013325e-11 | E44: 万元 | F44: =F39+F40-F42 -> 31636.041 | G44: =G39+G40-G42 -> 53699.272 | H44: =H39+H40-H42 -> 50916.304 | I44: =I39+I40-I42 -> 48035.931 | J44: =J39+J40-J42 -> 45054.746 | K44: =K39+K40-K42 -> 41969.219 | L44: =L39+L40-L42 -> 38775.699 | M44: =M39+M40-M42 -> 35470.405 | ... V44: =V39+V40-V42 -> -3.0013325e-11
B46: 借款还本付息表（长期借款）
B47: 序号 | C47: 项目 | D47: 合计 | E47: 单位 | F47: 建设期 | H47: 运营期
F48: 1 | G48: 2 | H48: 1 | I48: 2 | J48: 3 | K48: 4 | L48: 5 | M48: 6 | N48: 7 | O48: 8 | P48: 9 | Q48: 10 | R48: 11 | S48: 12 | T48: 13 | U48: 14 | V48: 15 | W48: 16 | X48: 17 | Y48: 18 | Z48: 19 | AA48: 20
B49: 1 | C49: 期初借款累计 | E49: 万元 | F49: 0 | G49: =F54 -> 31636.041 | H49: =G54 -> 53699.272 | I49: =H54 -> 50119.321 | J49: =I54 -> 46539.369 | K49: =J54 -> 42959.418 | L49: =K54 -> 39379.466 | M49: =L54 -> 35799.515 | N49: =M54 -> 32219.563 | ... V49: =U54 -> 3579.9515
B50: 2 | C50: 当期借款 | D50: =SUM(F50:AA50) -> 53699.272 | E50: 万元 | F50: =F15 -> 31636.041 | G50: =G15 -> 22063.232
B51: 3 | C51: 当期还本付息 | D51: =SUM(F51:AA51) -> 68735.069 | E51: 万元 | H51: =SUM(H52:H53) -> 5459.426 | I51: =SUM(I52:I53) -> 5334.1277 | J51: =SUM(J52:J53) -> 5208.8294 | K51: =SUM(K52:K53) -> 5083.5311 | L51: =SUM(L52:L53) -> 4958.2328 | M51: =SUM(M52:M53) -> 4832.9345 | N51: =SUM(N52:N53) -> 4707.6362 | O51: =SUM(O52:O53) -> 4582.3379 | ... V51: =SUM(V52:V53) -> 3705.2498
C52: 其中：还本（等额本金） | D52: =SUM(F52:AA52) -> 53699.272 | E52: 万元 | H52: =$D$50/参数输入表!$H$362 -> 3579.9515 | I52: =$D$50/参数输入表!$H$362 -> 3579.9515 | J52: =$D$50/参数输入表!$H$362 -> 3579.9515 | K52: =$D$50/参数输入表!$H$362 -> 3579.9515 | L52: =$D$50/参数输入表!$H$362 -> 3579.9515 | M52: =$D$50/参数输入表!$H$362 -> 3579.9515 | N52: =$D$50/参数输入表!$H$362 -> 3579.9515 | O52: =$D$50/参数输入表!$H$362 -> 3579.9515 | ... V52: =$D$50/参数输入表!$H$362 -> 3579.9515
C53: 付息 | D53: =SUM(F53:AA53) -> 15035.796 | E53: 万元 | H53: =(H49+H50/2)*参数输入表!$H$359 -> 1879.4745 | I53: =(I49+I50/2)*参数输入表!$H$359 -> 1754.1762 | J53: =(J49+J50/2)*参数输入表!$H$359 -> 1628.8779 | K53: =(K49+K50/2)*参数输入表!$H$359 -> 1503.5796 | L53: =(L49+L50/2)*参数输入表!$H$359 -> 1378.2813 | M53: =(M49+M50/2)*参数输入表!$H$359 -> 1252.983 | N53: =(N49+N50/2)*参数输入表!$H$359 -> 1127.6847 | O53: =(O49+O50/2)*参数输入表!$H$359 -> 1002.3864 | ... V53: =(V49+V50/2)*参数输入表!$H$359 -> 125.2983
B54: 4 | C54: 期末借款余额 | D54: =V54 -> -1.0004442e-11 | E54: 万元 | F54: =F49+F50-F52 -> 31636.041 | G54: =G49+G50-G52 -> 53699.272 | H54: =H49+H50-H52 -> 50119.321 | I54: =I49+I50-I52 -> 46539.369 | J54: =J49+J50-J52 -> 42959.418 | K54: =K49+K50-K52 -> 39379.466 | L54: =L49+L50-L52 -> 35799.515 | M54: =M49+M50-M52 -> 32219.563 | ... V54: =V49+V50-V52 -> -1.0004442e-11
B56: 借款还本付息表（流动资金借款）
B57: 序号 | C57: 项目 | D57: 合计 | E57: 单位 | F57: 建设期 | H57: 运营期
F58: 1 | G58: 2 | H58: 1 | I58: 2 | J58: 3 | K58: 4 | L58: 5 | M58: 6 | N58: 7 | O58: 8 | P58: 9 | Q58: 10 | R58: 11 | S58: 12 | T58: 13 | U58: 14 | V58: 15 | W58: 16 | X58: 17 | Y58: 18 | Z58: 19 | AA58: 20
B59: 一 | C59: 期初借款累计 | E59: 万元 | F59: 0 | G59: =F64 -> 0 | H59: =G64 -> 0 | I59: =H64 -> 266.7 | J59: =I64 -> 266.7 | K59: =J64 -> 266.7 | L59: =K64 -> 266.7 | M59: =L64 -> 266.7 | N59: =M64 -> 266.7 | ... AA59: =Z64 -> 266.7
B60: 二 | C60: 当期借款 | D60: =SUM(F60:AA60) -> 266.7 | E60: 万元 | F60: 0 | G60: 0 | H60: =$H$15 -> 266.7
B61: 三 | C61: 当期还本付息 | D61: =SUM(F61:AA61) -> 418.719 | E61: 万元 | H61: 0 | I61: =SUM(I62:I63) -> 8.001 | J61: =SUM(J62:J63) -> 8.001 | K61: =SUM(K62:K63) -> 8.001 | L61: =SUM(L62:L63) -> 8.001 | M61: =SUM(M62:M63) -> 8.001 | N61: =SUM(N62:N63) -> 8.001 | O61: =SUM(O62:O63) -> 8.001 | P61: =SUM(P62:P63) -> 8.001 | ... AA61: =SUM(AA62:AA63) -> 274.701
C62: 其中：还本 | D62: =SUM(F62:AA62) -> 266.7 | E62: 万元 | H62: 0 | AA62: =H64 -> 266.7
C63: 付息 | D63: =SUM(F63:AA63) -> 160.02 | E63: 万元 | H63: =(H59+H60)*参数输入表!$H$360 -> 8.001 | I63: =(I59+I60)*参数输入表!$H$360 -> 8.001 | J63: =(J59+J60)*参数输入表!$H$360 -> 8.001 | K63: =(K59+K60)*参数输入表!$H$360 -> 8.001 | L63: =(L59+L60)*参数输入表!$H$360 -> 8.001 | M63: =(M59+M60)*参数输入表!$H$360 -> 8.001 | N63: =(N59+N60)*参数输入表!$H$360 -> 8.001 | O63: =(O59+O60)*参数输入表!$H$360 -> 8.001 | ... AA63: =(AA59+AA60)*参数输入表!$H$360 -> 8.001
B64: 四 | C64: 期末借款余额 | D64: =AA64 -> 0 | E64: 万元 | F64: =F59+F60-F62 -> 0 | G64: =G59+G60-G62 -> 0 | H64: =H59+H60-H62 -> 266.7 | I64: =I59+I60-I62 -> 266.7 | J64: =J59+J60-J62 -> 266.7 | K64: =K59+K60-K62 -> 266.7 | L64: =L59+L60-L62 -> 266.7 | M64: =M59+M60-M62 -> 266.7 | ... AA64: =AA59+AA60-AA62 -> 0
B66: 借款还本付息表（短期借款）
B67: 序号 | C67: 项目 | D67: 合计 | E67: 单位 | F67: 建设期 | H67: 运营期
F68: 1 | G68: 2 | H68: 1 | I68: 2 | J68: 3 | K68: 4 | L68: 5 | M68: 6 | N68: 7 | O68: 8 | P68: 9 | Q68: 10 | R68: 11 | S68: 12 | T68: 13 | U68: 14 | V68: 15 | W68: 16 | X68: 17 | Y68: 18 | Z68: 19 | AA68: 20
B69: 一 | C69: 期初借款累计 | E69: 万元 | F69: 0 | G69: =F74 -> 0 | H69: =G74 -> 0 | I69: =H74 -> 0 | J69: =I74 -> 0 | K69: =J74 -> 0 | L69: =K74 -> 0 | M69: =L74 -> 0 | N69: =M74 -> 0 | ... AA69: =Z74 -> 0
B70: 二 | C70: 当期借款 | D70: =SUM(F70:AA70) -> 0 | E70: 万元 | F70: 0 | G70: 0 | H70: ='表9-现金流量表-财务计划'!H28 -> 0 | I70: ='表9-现金流量表-财务计划'!I28 -> 0 | J70: ='表9-现金流量表-财务计划'!J28 -> 0 | K70: ='表9-现金流量表-财务计划'!K28 -> 0 | L70: ='表9-现金流量表-财务计划'!L28 -> 0 | M70: ='表9-现金流量表-财务计划'!M28 -> 0 | N70: ='表9-现金流量表-财务计划'!N28 -> 0 | O70: ='表9-现金流量表-财务计划'!O28 -> 0 | ... AA70: ='表9-现金流量表-财务计划'!AA28 -> 0
B71: 三 | C71: 当期还本付息 | D71: =SUM(F71:AA71) -> 0 | E71: 万元 | H71: =SUM(H72:H73) -> 0 | I71: =SUM(I72:I73) -> 0 | J71: =SUM(J72:J73) -> 0 | K71: =SUM(K72:K73) -> 0 | L71: =SUM(L72:L73) -> 0 | M71: =SUM(M72:M73) -> 0 | N71: =SUM(N72:N73) -> 0 | O71: =SUM(O72:O73) -> 0 | ... AA71: =SUM(AA72:AA73) -> 0
C72: 其中：还本 | D72: =SUM(F72:AA72) -> 0 | E72: 万元 | H72: =G74 -> 0 | I72: =H74 -> 0 | J72: =I74 -> 0 | K72: =J74 -> 0 | L72: =K74 -> 0 | M72: =L74 -> 0 | N72: =M74 -> 0 | O72: =N74 -> 0 | ... AA72: =Z74 -> 0
C73: 付息 | D73: =SUM(F73:AA73) -> 0 | E73: 万元 | H73: =(H70)*参数输入表!$H$360 -> 0 | I73: =(I70)*参数输入表!$H$360 -> 0 | J73: =(J70)*参数输入表!$H$360 -> 0 | K73: =(K70)*参数输入表!$H$360 -> 0 | L73: =(L70)*参数输入表!$H$360 -> 0 | M73: =(M70)*参数输入表!$H$360 -> 0 | N73: =(N70)*参数输入表!$H$360 -> 0 | O73: =(O70)*参数输入表!$H$360 -> 0 | ... AA73: =(AA70)*参数输入表!$H$360 -> 0
B74: 四 | C74: 期末借款余额 | D74: =AA74 -> 0 | E74: 万元 | F74: =F69+F70-F72 -> 0 | G74: =G69+G70-G72 -> 0 | H74: =H70+H69-H72 -> 0 | I74: =I70+I69-I72 -> 0 | J74: =J70+J69-J72 -> 0 | K74: =K70+K69-K72 -> 0 | L74: =L70+L69-L72 -> 0 | M74: =M70+M69-M72 -> 0 | N74: =N70+N69-N72 -> 0 | O74: =O70+O69-O72 -> 0 | ... AA74: =AA70+AA69-AA72 -> 0
B76: 借款还本付息表（汇总—等额本息）
B77: 序号 | C77: 项目 | D77: 合计 | E77: 单位 | F77: 建设期 | H77: 运营期
F78: 1 | G78: 2 | H78: 1 | I78: 2 | J78: 3 | K78: 4 | L78: 5 | M78: 6 | N78: 7 | O78: 8 | P78: 9 | Q78: 10 | R78: 11 | S78: 12 | T78: 13 | U78: 14 | V78: 15 | W78: 16 | X78: 17 | Y78: 18 | Z78: 19 | AA78: 20
B79: 一 | C79: 期初借款累计 | E79: 万元 | F79: =F39+F59+F69 -> 0 | G79: =G39+G59+G69 -> 31636.041 | H79: =H39+H59+H69 -> 53699.272 | I79: =I39+I59+I69 -> 51183.004 | J79: =J39+J59+J69 -> 48302.631 | K79: =K39+K59+K69 -> 45321.446 | L79: =L39+L59+L69 -> 42235.919 | M79: =M39+M59+M69 -> 39042.399 | ... AA79: =AA39+AA59+AA69 -> 266.7
B80: 二 | C80: 当期借款 | D80: =SUM(F80:AA80) -> 53965.972 | E80: 万元 | F80: =F40+F60+F70 -> 31636.041 | G80: =G40+G60+G70 -> 22063.232 | H80: =H40+H60+H70 -> 266.7 | I80: =I40+I60+I70 -> 0 | J80: =J40+J60+J70 -> 0 | K80: =K40+K60+K70 -> 0 | L80: =L40+L60+L70 -> 0 | M80: =M40+M60+M70 -> 0 | ... AA80: =AA40+AA60+AA70 -> 0
B81: 三 | C81: 当期还本付息 | D81: =SUM(F81:AA81) -> 70355.365 | E81: 万元 | H81: =H41+H61+H71 -> 4662.443 | I81: =I41+I61+I71 -> 4670.444 | J81: =J41+J61+J71 -> 4670.444 | K81: =K41+K61+K71 -> 4670.444 | L81: =L41+L61+L71 -> 4670.444 | M81: =M41+M61+M71 -> 4670.444 | N81: =N41+N61+N71 -> 4670.444 | O81: =O41+O61+O71 -> 4670.444 | ... AA81: =AA41+AA61+AA71 -> 274.701
C82: 其中：还本 | D82: =SUM(F82:AA82) -> 53965.972 | E82: 万元 | H82: =H42+H62+H72 -> 2782.9685 | I82: =I42+I62+I72 -> 2880.3724 | J82: =J42+J62+J72 -> 2981.1854 | K82: =K42+K62+K72 -> 3085.5269 | L82: =L42+L62+L72 -> 3193.5204 | M82: =M42+M62+M72 -> 3305.2936 | N82: =N42+N62+N72 -> 3420.9789 | O82: =O42+O62+O72 -> 3540.7131 | ... AA82: =AA42+AA62+AA72 -> 266.7
C83: 付息 | D83: =SUM(F83:AA83) -> 16397.393 | E83: 万元 | H83: =H43+H63+H73 -> 1887.4755 | I83: =I43+I63+I73 -> 1790.0716 | J83: =J43+J63+J73 -> 1689.2586 | K83: =K43+K63+K73 -> 1584.9171 | L83: =L43+L63+L73 -> 1476.9237 | M83: =M43+M63+M73 -> 1365.1505 | N83: =N43+N63+N73 -> 1249.4652 | O83: =O43+O63+O73 -> 1129.7309 | ... AA83: =AA43+AA63+AA73 -> 8.001
B84: 四 | C84: 期末借款余额 | D84: =AA84 -> 0 | E84: 万元 | F84: =F44+F64+F74 -> 31636.041 | G84: =G44+G64+G74 -> 53699.272 | H84: =H44+H64+H74 -> 51183.004 | I84: =I44+I64+I74 -> 48302.631 | J84: =J44+J64+J74 -> 45321.446 | K84: =K44+K64+K74 -> 42235.919 | L84: =L44+L64+L74 -> 39042.399 | M84: =M44+M64+M74 -> 35737.105 | ... AA84: =AA44+AA64+AA74 -> 0
B86: 借款还本付息表（汇总—等额本金）
B87: 序号 | C87: 项目 | D87: 合计 | E87: 单位 | F87: 建设期 | H87: 运营期
F88: 1 | G88: 2 | H88: 1 | I88: 2 | J88: 3 | K88: 4 | L88: 5 | M88: 6 | N88: 7 | O88: 8 | P88: 9 | Q88: 10 | R88: 11 | S88: 12 | T88: 13 | U88: 14 | V88: 15 | W88: 16 | X88: 17 | Y88: 18 | Z88: 19 | AA88: 20
B89: 一 | C89: 期初借款累计 | E89: 万元 | F89: =F49+F59+F69 -> 0 | G89: =G49+G59+G69 -> 31636.041 | H89: =H49+H59+H69 -> 53699.272 | I89: =I49+I59+I69 -> 50386.021 | J89: =J49+J59+J69 -> 46806.069 | K89: =K49+K59+K69 -> 43226.118 | L89: =L49+L59+L69 -> 39646.166 | M89: =M49+M59+M69 -> 36066.215 | ... AA89: =AA49+AA59+AA69 -> 266.7
B90: 二 | C90: 当期借款 | D90: =SUM(F90:AA90) -> 53965.972 | E90: 万元 | F90: =F50+F60+F70 -> 31636.041 | G90: =G50+G60+G70 -> 22063.232 | H90: =H50+H60+H70 -> 266.7 | I90: =I50+I60+I70 -> 0 | J90: =J50+J60+J70 -> 0 | K90: =K50+K60+K70 -> 0 | L90: =L50+L60+L70 -> 0 | M90: =M50+M60+M70 -> 0 | ... AA90: =AA50+AA60+AA70 -> 0
B91: 三 | C91: 当期还本付息 | D91: =SUM(F91:AA91) -> 69153.788 | E91: 万元 | H91: =H51+H61+H71 -> 5459.426 | I91: =I51+I61+I71 -> 5342.1287 | J91: =J51+J61+J71 -> 5216.8304 | K91: =K51+K61+K71 -> 5091.5321 | L91: =L51+L61+L71 -> 4966.2338 | M91: =M51+M61+M71 -> 4840.9355 | N91: =N51+N61+N71 -> 4715.6372 | O91: =O51+O61+O71 -> 4590.3389 | ... AA91: =AA51+AA61+AA71 -> 274.701
C92: 其中：还本 | D92: =SUM(F92:AA92) -> 53965.972 | E92: 万元 | H92: =H52+H62+H72 -> 3579.9515 | I92: =I52+I62+I72 -> 3579.9515 | J92: =J52+J62+J72 -> 3579.9515 | K92: =K52+K62+K72 -> 3579.9515 | L92: =L52+L62+L72 -> 3579.9515 | M92: =M52+M62+M72 -> 3579.9515 | N92: =N52+N62+N72 -> 3579.9515 | O92: =O52+O62+O72 -> 3579.9515 | ... AA92: =AA52+AA62+AA72 -> 266.7
C93: 付息 | D93: =SUM(F93:AA93) -> 15195.816 | E93: 万元 | H93: =H53+H63+H73 -> 1887.4755 | I93: =I53+I63+I73 -> 1762.1772 | J93: =J53+J63+J73 -> 1636.8789 | K93: =K53+K63+K73 -> 1511.5806 | L93: =L53+L63+L73 -> 1386.2823 | M93: =M53+M63+M73 -> 1260.984 | N93: =N53+N63+N73 -> 1135.6857 | O93: =O53+O63+O73 -> 1010.3874 | ... AA93: =AA53+AA63+AA73 -> 8.001
B94: 四 | C94: 期末借款余额 | D94: =AA94 -> 0 | E94: 万元 | F94: =F54+F64+F74 -> 31636.041 | G94: =G54+G64+G74 -> 53699.272 | H94: =H54+H64+H74 -> 50386.021 | I94: =I54+I64+I74 -> 46806.069 | J94: =J54+J64+J74 -> 43226.118 | K94: =K54+K64+K74 -> 39646.166 | L94: =L54+L64+L74 -> 36066.215 | M94: =M54+M64+M74 -> 32486.263 | ... AA94: =AA54+AA64+AA74 -> 0
C97: 当期借款引用“资金筹措表”对应年份债务资金数据
C98: 等额本金/等额本息/其他，作为参数输入表—投融资相关板块中的可选择情形，匹配如下不同的计算方法
C99: （1）等额本息情形下，还本付息采用年金公式先得出每年的 本金+利息 之和（固定值），再结合各年度期初及当期借款金额计算出各年度应付利息，进而推算出每年偿还的本金。
C100: （2）等额本金情形下，每年的本金偿还为固定值（建设期借款总额/还款年限），再结合各年度期初及当期借款金额计算出各年度应付利息。
C101: （3）其他情形下，运营期每年的本金偿还设置为手动输入项
C103: 短期借款每年的当期借款及还本直接引用参数表的数据（初始默认为0）

Sheet 表2-折旧摊销表
C1: 中间过程引用（隐藏）
C2: 动态总投资（自主投资_不含流动资金） | D2: =参数输入表!H350 -> 67290.182
C3: 可抵扣进项税 | D3: =参数输入表!H353 -> 4457.01
C4: 固定资产原值 | D4: =D2-D25-D3 -> 46359.172 | F4: 固定资产原值=项目动态总投资（自主投资_不含流动资金）-可抵扣进项税-无形资产原值=项目静态总投资-建设补贴+建设期利息-可抵扣进项税-无形资产原值
C5: 折旧方式 | D5: 直线法/其他
C6: 折旧年限 | D6: =参数输入表!H622 -> 15
C7: 残值率 | D7: =参数输入表!H623 -> 0.05
C8: 其中:
C9: 房屋建筑投资 | D9: =参数输入表!H342 -> 13170.58 | G9: =D14/D2 -> 0.19467922
C10: 可抵扣进项税
C11: 折算原值 | D11: =D4*(D9/D2) -> 9073.793 | G11: =G9-1 -> -0.80532078
C12: 折旧年限 | D12: 15
C13: 残值率 | D13: 0.05
C14: 算力设备投资 | D14: =参数输入表!H341 -> 13100
C15: 折算原值 | D15: =D4*(D14/D2) -> 9025.1674
C16: 折旧年限 | D16: 10
C17: 残值率 | D17: 0.05
C18: 长期待摊费用（第1年） | D18: =参数输入表!H631/(1+参数输入表!H653) -> 0 | F18: 长期待摊费用=计入长期待摊的成本项/（1+增值税税率）
C19: 长期待摊费用（第6年） | D19: =参数输入表!H636/(1+参数输入表!H653) -> 0
C20: 长期待摊费用（第11年） | D20: =参数输入表!H641/(1+参数输入表!H653) -> 0
C21: 长期待摊费用（第16年） | D21: =参数输入表!H646/(1+参数输入表!H653) -> 0
C23: 摊销方式 | D23: 直线法/其他
C24: 摊销年限 | D24: =参数输入表!H652 -> 5
C25: 无形资产原值 | D25: =参数输入表!H345 -> 16474
C26: 摊销方式 | D26: 直线法/其他
C27: 摊销年限 | D27: =参数输入表!H627 -> 30 | F27: 建设期 | H27: 运营期
C28: 残值率 | D28: =参数输入表!H628 -> 0 | F28: 1 | G28: 2 | H28: 1 | I28: 2 | J28: 3 | K28: 4 | L28: 5 | M28: 6 | N28: 7 | O28: 8 | P28: 9 | Q28: 10 | R28: 11 | S28: 12 | T28: 13 | U28: 14 | V28: 15 | W28: 16 | X28: 17 | Y28: 18 | Z28: 19 | AA28: 20
C29: 大修及更新重置资产原值
C30: 摊销方式 | D30: 直线法/其他 | H30: =参数输入表!H656 -> 0 | I30: =参数输入表!H657 -> 0 | J30: =参数输入表!H658 -> 0 | K30: =参数输入表!H659 -> 0 | L30: =参数输入表!H660 -> 0 | M30: =参数输入表!H661 -> 0 | N30: =参数输入表!H662 -> 0 | O30: =参数输入表!H663 -> 0 | P30: =参数输入表!H664 -> 0 | Q30: =参数输入表!H665 -> 0 | R30: =参数输入表!H666/(1+参数输入表!$H$679) -> 0 | S30: =参数输入表!H667 -> 500 | T30: =参数输入表!H668 -> 0 | U30: =参数输入表!H669 -> 0 | V30: =参数输入表!H670 -> 0 | W30: =参数输入表!H671 -> 0 | X30: =参数输入表!H672 -> 0 | Y30: =参数输入表!H673 -> 0 | Z30: =参数输入表!H674 -> 0 | AA30: =参数输入表!H675 -> 0
C31: 摊销年限 | D31: =参数输入表!H677 -> 10
C32: 残值率 | D32: =参数输入表!H678 -> 0.05
B33: 折旧摊销表-资本金
B34: 序号 | C34: 科目 | D34: 合计 | E34: 单位 | F34: 建设期 | H34: 运营期
F35: 1 | G35: 2 | H35: 1 | I35: 2 | J35: 3 | K35: 4 | L35: 5 | M35: 6 | N35: 7 | O35: 8 | P35: 9 | Q35: 10 | R35: 11 | S35: 12 | T35: 13 | U35: 14 | V35: 15 | W35: 16 | X35: 17 | Y35: 18 | Z35: 19 | AA35: 20
B36: 1 | C36: 固定资产净值 | E36: 万元 | F36: =(D4-D11-D15)*'表1-资金筹措及还本付息表'!F5 -> 16956.127 | G36: =(D4-D11-D15)*'表1-资金筹措及还本付息表'!G5 -> 11304.085 | H36: =G36-H37+F36 -> 26470.399 | I36: =H36-I37 -> 24680.585 | J36: =I36-J37 -> 22890.772 | K36: =J36-K37 -> 21100.958 | L36: =K36-L37 -> 19311.145 | M36: =L36-M37 -> 17521.331 | N36: =M36-N37 -> 15731.518 | O36: =N36-O37 -> 13941.705 | P36: =O36-P37 -> 12151.891 | ... AA36: =Z36-AA37 -> 1413.0106
C37: 当期固定资产折旧 | D37: =SUM(F37:AA37) -> 26847.201 | E37: 万元 | H37: =IF(H35<=$D$6,($D$4-$D$11-$D$15)*(1-$D$7)/($D$6),0) -> 1789.8134 | I37: =IF(I35<=$D$6,($D$4-$D$11-$D$15)*(1-$D$7)/($D$6),0) -> 1789.8134 | J37: =IF(J35<=$D$6,($D$4-$D$11-$D$15)*(1-$D$7)/($D$6),0) -> 1789.8134 | K37: =IF(K35<=$D$6,($D$4-$D$11-$D$15)*(1-$D$7)/($D$6),0) -> 1789.8134 | L37: =IF(L35<=$D$6,($D$4-$D$11-$D$15)*(1-$D$7)/($D$6),0) -> 1789.8134 | M37: =IF(M35<=$D$6,($D$4-$D$11-$D$15)*(1-$D$7)/($D$6),0) -> 1789.8134 | N37: =IF(N35<=$D$6,($D$4-$D$11-$D$15)*(1-$D$7)/($D$6),0) -> 1789.8134 | O37: =IF(O35<=$D$6,($D$4-$D$11-$D$15)*(1-$D$7)/($D$6),0) -> 1789.8134 | ... AA37: =IF(AA35<=$D$6,($D$4-$D$11-$D$15)*(1-$D$7)/($D$6),0) -> 0
B38: 2 | C38: 房屋建筑净值 | E38: 万元 | F38: =D11 -> 9073.793 | H38: =F38-H39 -> 8499.1195 | I38: =H38-I39 -> 7924.4459 | J38: =I38-J39 -> 7349.7724 | K38: =J38-K39 -> 6775.0988 | L38: =K38-L39 -> 6200.4252 | M38: =L38-M39 -> 5625.7517 | N38: =M38-N39 -> 5051.0781 | O38: =N38-O39 -> 4476.4046 | P38: =O38-P39 -> 3901.731 | ... AA38: =Z38-AA39 -> 453.68965
C39: 当期折旧 | D39: =SUM(F39:AA39) -> 8620.1034 | E39: 万元 | H39: =IF(H35<=$D$6,$D$11*(1-$D$13)/($D$12),0) -> 574.67356 | I39: =IF(I35<=$D$6,$D$11*(1-$D$13)/($D$12),0) -> 574.67356 | J39: =IF(J35<=$D$6,$D$11*(1-$D$13)/($D$12),0) -> 574.67356 | K39: =IF(K35<=$D$6,$D$11*(1-$D$13)/($D$12),0) -> 574.67356 | L39: =IF(L35<=$D$6,$D$11*(1-$D$13)/($D$12),0) -> 574.67356 | M39: =IF(M35<=$D$6,$D$11*(1-$D$13)/($D$12),0) -> 574.67356 | N39: =IF(N35<=$D$6,$D$11*(1-$D$13)/($D$12),0) -> 574.67356 | O39: =IF(O35<=$D$6,$D$11*(1-$D$13)/($D$12),0) -> 574.67356 | ... AA39: =IF(AA35<=$D$6,$D$11*(1-$D$13)/($D$12),0) -> 0
B40: 3 | C40: 算力设备净值 | E40: 万元 | F40: =D15*'表1-资金筹措及还本付息表'!F5 -> 5415.1004 | G40: =D15*'表1-资金筹措及还本付息表'!G5 -> 3610.0669 | H40: =F40+G40-H41 -> 8167.7765 | I40: =H40-I41 -> 7310.3856 | J40: =I40-J41 -> 6452.9947 | K40: =J40-K41 -> 5595.6038 | L40: =K40-L41 -> 4738.2129 | M40: =L40-M41 -> 3880.822 | N40: =M40-N41 -> 3023.4311 | O40: =N40-O41 -> 2166.0402 | P40: =O40-P41 -> 1308.6493 | ... AA40: =Z40-AA41 -> 451.25837
C41: 当期折旧 | D41: =SUM(F41:AA41) -> 8573.909 | E41: 万元 | H41: =IF(H35<=$D$16,$D$15*(1-$D$17)/($D$16),0) -> 857.3909 | I41: =IF(I35<=$D$16,$D$15*(1-$D$17)/($D$16),0) -> 857.3909 | J41: =IF(J35<=$D$16,$D$15*(1-$D$17)/($D$16),0) -> 857.3909 | K41: =IF(K35<=$D$16,$D$15*(1-$D$17)/($D$16),0) -> 857.3909 | L41: =IF(L35<=$D$16,$D$15*(1-$D$17)/($D$16),0) -> 857.3909 | M41: =IF(M35<=$D$16,$D$15*(1-$D$17)/($D$16),0) -> 857.3909 | N41: =IF(N35<=$D$16,$D$15*(1-$D$17)/($D$16),0) -> 857.3909 | O41: =IF(O35<=$D$16,$D$15*(1-$D$17)/($D$16),0) -> 857.3909 | ... R41: =IF(R35<=$D$16,$D$15*(1-$D$17)/($D$16),0) -> 0
B42: 2 | C42: 期初长期待摊费用 | E42: 万元 | H42: 0 | I42: =H45 -> 0 | J42: =I45 -> 0 | K42: =J45 -> 0 | L42: =K45 -> 0 | M42: =L45 -> 0 | N42: =M45 -> 0 | O42: =N45 -> 0 | P42: =O45 -> 0 | ... AA42: =Z45 -> 0
C43: 当期新增长期待摊费用 | H43: =参数输入表!H631/(1+参数输入表!H653) -> 0 | I43: =参数输入表!H632/(1+参数输入表!H653) -> 0 | J43: =参数输入表!H633/(1+参数输入表!H653) -> 0 | K43: =参数输入表!H634/(1+参数输入表!H653) -> 0 | L43: =参数输入表!H635/(1+参数输入表!H653) -> 0 | M43: =参数输入表!H636/(1+参数输入表!H653) -> 0 | N43: =参数输入表!H637/(1+参数输入表!H653) -> 0 | O43: =参数输入表!H638/(1+参数输入表!H653) -> 0 | P43: =参数输入表!H639/(1+参数输入表!H653) -> 0 | Q43: =参数输入表!H640/(1+参数输入表!H653) -> 0 | R43: =参数输入表!H641/(1+参数输入表!H653) -> 0 | S43: =参数输入表!H642/(1+参数输入表!H653) -> 0 | T43: =参数输入表!H643/(1+参数输入表!H653) -> 0 | U43: =参数输入表!H644/(1+参数输入表!H653) -> 0 | V43: =参数输入表!H645/(1+参数输入表!H653) -> 0 | W43: =参数输入表!H646/(1+参数输入表!H653) -> 0 | X43: =参数输入表!H647/(1+参数输入表!H653) -> 0 | Y43: =参数输入表!H648/(1+参数输入表!H653) -> 0 | Z43: =参数输入表!H649/(1+参数输入表!H653) -> 0 | AA43: =参数输入表!H650/(1+参数输入表!H653) -> 0
C44: 当期摊销 | D44: =SUM(F44:AA44) -> 0 | E44: 万元 | H44: =H43/$D$24 -> 0 | I44: =H44 -> 0 | J44: =I44 -> 0 | K44: =J44 -> 0 | L44: =K44 -> 0 | M44: =M43/$D$24 -> 0 | N44: =M44 -> 0 | O44: =N44 -> 0 | P44: =O44 -> 0 | Q44: =P44 -> 0 | R44: =R43/$D$24 -> 0 | S44: =R44 -> 0 | T44: =S44 -> 0 | U44: =T44 -> 0 | V44: =U44 -> 0 | W44: =W43/$D$24 -> 0 | X44: =W44 -> 0 | Y44: =X44 -> 0 | Z44: =Y44 -> 0 | AA44: =Z44 -> 0
C45: 期末期初长期待摊费用 | H45: =H42+H43-H44 -> 0 | I45: =I42+I43-I44 -> 0 | J45: =J42+J43-J44 -> 0 | K45: =K42+K43-K44 -> 0 | L45: =L42+L43-L44 -> 0 | M45: =M42+M43-M44 -> 0 | N45: =N42+N43-N44 -> 0 | O45: =O42+O43-O44 -> 0 | ... AA45: =AA42+AA43-AA44 -> 0
B46: 3 | C46: 无形资产净值 | E46: 万元 | F46: =参数输入表!$H$625*参数输入表!$H$102 -> 9884.4 | G46: =参数输入表!$H$625*参数输入表!$H$103 -> 6589.6 | H46: =G46-H47+F46 -> 15924.867 | I46: =H46-I47 -> 15375.733 | J46: =I46-J47 -> 14826.6 | K46: =J46-K47 -> 14277.467 | L46: =K46-L47 -> 13728.333 | M46: =L46-M47 -> 13179.2 | N46: =M46-N47 -> 12630.067 | O46: =N46-O47 -> 12080.933 | P46: =O46-P47 -> 11531.8 | ... AA46: =Z46-AA47 -> 5491.3333
C47: 当期无形资产摊销 | D47: =SUM(F47:AA47) -> 10982.667 | E47: 万元 | H47: =IF(H35<=$D$27,D25*(1-$D$28)/($D$27-H35+1),0) -> 549.13333 | I47: =IF(I35<=$D$27,H46*(1-$D$28)/($D$27-I35+1),0) -> 549.13333 | J47: =IF(J35<=$D$27,I46*(1-$D$28)/($D$27-J35+1),0) -> 549.13333 | K47: =IF(K35<=$D$27,J46*(1-$D$28)/($D$27-K35+1),0) -> 549.13333 | L47: =IF(L35<=$D$27,K46*(1-$D$28)/($D$27-L35+1),0) -> 549.13333 | M47: =IF(M35<=$D$27,L46*(1-$D$28)/($D$27-M35+1),0) -> 549.13333 | N47: =IF(N35<=$D$27,M46*(1-$D$28)/($D$27-N35+1),0) -> 549.13333 | O47: =IF(O35<=$D$27,N46*(1-$D$28)/($D$27-O35+1),0) -> 549.13333 | P47: =IF(P35<=$D$27,O46*(1-$D$28)/($D$27-P35+1),0) -> 549.13333 | ... AA47: =IF(AA35<=$D$27,Z46*(1-$D$28)/($D$27-AA35+1),0) -> 549.13333
B48: 4 | C48: 期初大修及更新重置资产净值 | E48: 万元 | H48: 0 | I48: =H51 -> 0 | J48: =I51 -> 0 | K48: =J51 -> 0 | L48: =K51 -> 0 | M48: =L51 -> 0 | N48: =M51 -> 0 | O48: =N51 -> 0 | P48: =O51 -> 0 | ... AA48: =Z51 -> 106.19469
C49: 当期新增大修及更新重置资产 | H49: =参数输入表!H656/(1+参数输入表!$H$679) -> 0 | I49: =参数输入表!H657/(1+参数输入表!$H$679) -> 0 | J49: =参数输入表!H658/(1+参数输入表!$H$679) -> 0 | K49: =参数输入表!H659/(1+参数输入表!$H$679) -> 0 | L49: =参数输入表!H660/(1+参数输入表!$H$679) -> 0 | M49: =参数输入表!H661/(1+参数输入表!$H$679) -> 0 | N49: =参数输入表!H662/(1+参数输入表!$H$679) -> 0 | O49: =参数输入表!H663/(1+参数输入表!$H$679) -> 0 | P49: =参数输入表!H664/(1+参数输入表!$H$679) -> 0 | Q49: =参数输入表!H665/(1+参数输入表!$H$679) -> 0 | R49: =R30 -> 0 | S49: =参数输入表!H667/(1+参数输入表!$H$679) -> 442.47788 | T49: =参数输入表!H668/(1+参数输入表!$H$679) -> 0 | U49: =参数输入表!H669/(1+参数输入表!$H$679) -> 0 | V49: =参数输入表!H670/(1+参数输入表!$H$679) -> 0 | W49: =参数输入表!H671/(1+参数输入表!$H$679) -> 0 | X49: =参数输入表!H672/(1+参数输入表!$H$679) -> 0 | Y49: =参数输入表!H673/(1+参数输入表!$H$679) -> 0 | Z49: =参数输入表!H674/(1+参数输入表!$H$679) -> 0 | AA49: =参数输入表!H675/(1+参数输入表!$H$679) -> 0
C50: 当期大修及更新重置资产折旧摊销 | D50: =SUM(F50:AA50) -> 378.31858 | E50: 万元 | H50: 0 | I50: 0 | J50: 0 | K50: 0 | L50: 0 | M50: 0 | N50: 0 | O50: 0 | P50: 0 | Q50: =Q49/D31 -> 0 | R50: =R30*(1-$D$32)/$D$31 -> 0 | S50: =S49*(1-$D$32)/$D$31+R50 -> 42.035398 | T50: =S50 -> 42.035398 | U50: =T50 -> 42.035398 | V50: =U50 -> 42.035398 | W50: =V50 -> 42.035398 | X50: =W50 -> 42.035398 | Y50: =X50 -> 42.035398 | Z50: =Y50 -> 42.035398 | AA50: =Z50 -> 42.035398
C51: 期末大修及更新重置资产净值 | H51: =H48+H49-H50 -> 0 | I51: =I48+I49-I50 -> 0 | J51: =J48+J49-J50 -> 0 | K51: =K48+K49-K50 -> 0 | L51: =L48+L49-L50 -> 0 | M51: =M48+M49-M50 -> 0 | N51: =N48+N49-N50 -> 0 | O51: =O48+O49-O50 -> 0 | ... AA51: =AA48+AA49-AA50 -> 64.159292
B52: 5 | C52: 当期折旧摊销 | D52: =SUM(F52:AA52) -> 55402.199 | E52: 万元 | F52: =F37+F44+F47+F50 -> 0 | G52: =G37+G44+G47+G50 -> 0 | H52: =H37+H44+H47+H50+H39+H41 -> 3771.0112 | I52: =I37+I44+I47+I50+I39+I41 -> 3771.0112 | J52: =J37+J44+J47+J50+J39+J41 -> 3771.0112 | K52: =K37+K44+K47+K50+K39+K41 -> 3771.0112 | L52: =L37+L44+L47+L50+L39+L41 -> 3771.0112 | M52: =M37+M44+M47+M50+M39+M41 -> 3771.0112 | N52: =N37+N44+N47+N50+N39+N41 -> 3771.0112 | O52: =O37+O44+O47+O50+O39+O41 -> 3771.0112 | ... AA52: =AA37+AA44+AA47+AA50+AA39+AA41 -> 591.16873
C53: 累计固定资产净值 | AA53: =AA36+AA51+AA38+AA40+AA46 -> 7873.4512
C55: 上述为“直线法”下折旧摊销计算，若在参数输入表中下拉菜单选择为“其他”，设置为手动输入各年份折旧额/摊销额
C57: 中间过程引用（隐藏）
C58: 静态总投资（自主投资）
C59: 可抵扣进项税
C60: 固定资产原值 | F60: 全投资情形下的固定资产原值=静态总投资（自主投资）-可抵扣进项税-无形资产原值；资本金情形下的固定资产原值采用的是“项目动态总投资（自主投资_不含流动资金）”
C61: 折旧方式 | F61: 折旧方式、残值率及折旧年限与资本金情形保持一致
C62: 折旧年限
C63: 残值率
B65: 折旧摊销表-全投资
B66: 序号 | C66: 科目 | D66: 合计 | E66: 单位 | F66: 建设期 | H66: 运营期
F67: 1 | G67: 2 | H67: 1 | I67: 2 | J67: 3 | K67: 4 | L67: 5 | M67: 6 | N67: 7 | O67: 8 | P67: 9 | Q67: 10 | R67: 11 | S67: 12 | T67: 13 | U67: 14 | V67: 15 | W67: 16 | X67: 17 | Y67: 18 | Z67: 19 | AA67: 20
B68: 1 | C68: 固定资产净值（全投资） | E68: 万元 | F68: =F36 -> 16956.127 | G68: =G36 -> 11304.085 | H68: =F68+G68-H69 -> 26470.399 | I68: =H68-I69 -> 24680.585 | J68: =I68-J69 -> 22890.772 | K68: =J68-K69 -> 21100.958 | L68: =K68-L69 -> 19311.145 | M68: =L68-M69 -> 17521.331 | N68: =M68-N69 -> 15731.518 | O68: =N68-O69 -> 13941.705 | P68: =O68-P69 -> 12151.891 | ... AA68: =Z68-AA69 -> 1413.0106
C69: 当期固定资产折旧 | D69: =SUM(F69:AA69) -> 26847.201 | E69: 万元 | H69: =H37 -> 1789.8134 | I69: =I37 -> 1789.8134 | J69: =J37 -> 1789.8134 | K69: =K37 -> 1789.8134 | L69: =L37 -> 1789.8134 | M69: =M37 -> 1789.8134 | N69: =N37 -> 1789.8134 | O69: =O37 -> 1789.8134 | ... AA69: =AA37 -> 0
B70: 2 | C70: 房屋建筑净值 | E70: 万元 | F70: =F38 -> 9073.793 | H70: =H38 -> 8499.1195 | I70: =I38 -> 7924.4459 | J70: =J38 -> 7349.7724 | K70: =K38 -> 6775.0988 | L70: =L38 -> 6200.4252 | M70: =M38 -> 5625.7517 | N70: =N38 -> 5051.0781 | O70: =O38 -> 4476.4046 | ... AA70: =AA38 -> 453.68965
C71: 当期折旧 | D71: =SUM(F71:AA71) -> 8620.1034 | E71: 万元 | H71: =H39 -> 574.67356 | I71: =I39 -> 574.67356 | J71: =J39 -> 574.67356 | K71: =K39 -> 574.67356 | L71: =L39 -> 574.67356 | M71: =M39 -> 574.67356 | N71: =N39 -> 574.67356 | O71: =O39 -> 574.67356 | ... AA71: =AA39 -> 0
B72: 3 | C72: 算力设备净值 | E72: 万元 | F72: =F40 -> 5415.1004 | G72: =G40 -> 3610.0669 | H72: =H40 -> 8167.7765 | I72: =I40 -> 7310.3856 | J72: =J40 -> 6452.9947 | K72: =K40 -> 5595.6038 | L72: =L40 -> 4738.2129 | M72: =M40 -> 3880.822 | ... AA72: =AA40 -> 451.25837
C73: 当期折旧 | D73: =SUM(F73:AA73) -> 8573.909 | E73: 万元 | H73: =H41 -> 857.3909 | I73: =I41 -> 857.3909 | J73: =J41 -> 857.3909 | K73: =K41 -> 857.3909 | L73: =L41 -> 857.3909 | M73: =M41 -> 857.3909 | N73: =N41 -> 857.3909 | O73: =O41 -> 857.3909 | ... AA73: =AA41 -> 0
B74: 4 | C74: 期初长期待摊费用 | E74: 万元 | H74: 0 | I74: =H77 -> 0 | J74: =I77 -> 0 | K74: =J77 -> 0 | L74: =K77 -> 0 | M74: =L77 -> 0 | N74: =M77 -> 0 | O74: =N77 -> 0 | P74: =O77 -> 0 | ... AA74: =Z77 -> 0
C75: 当期新增长期待摊费用 | H75: =H43 -> 0 | I75: =I43 -> 0 | J75: =J43 -> 0 | K75: =K43 -> 0 | L75: =L43 -> 0 | M75: =M43 -> 0 | N75: =N43 -> 0 | O75: =O43 -> 0 | ... AA75: =AA43 -> 0
C76: 当期摊销 | D76: =SUM(F76:AA76) -> 0 | E76: 万元 | H76: =H75/$D$24 -> 0 | I76: =H76 -> 0 | J76: =I76 -> 0 | K76: =J76 -> 0 | L76: =K76 -> 0 | M76: =M75/$D$24 -> 0 | N76: =M76 -> 0 | O76: =N76 -> 0 | P76: =O76 -> 0 | Q76: =P76 -> 0 | R76: =R75/$D$24 -> 0 | S76: =R76 -> 0 | T76: =S76 -> 0 | U76: =T76 -> 0 | V76: =U76 -> 0 | W76: =W75/$D$24 -> 0 | X76: =W76 -> 0 | Y76: =X76 -> 0 | Z76: =Y76 -> 0 | AA76: =Z76 -> 0
C77: 期末期初长期待摊费用 | H77: =H74+H75-H76 -> 0 | I77: =I74+I75-I76 -> 0 | J77: =J74+J75-J76 -> 0 | K77: =K74+K75-K76 -> 0 | L77: =L74+L75-L76 -> 0 | M77: =M74+M75-M76 -> 0 | N77: =N74+N75-N76 -> 0 | O77: =O74+O75-O76 -> 0 | ... AA77: =AA74+AA75-AA76 -> 0
B78: 5 | C78: 无形资产净值 | E78: 万元 | F78: =参数输入表!$H$625*参数输入表!$H$102 -> 9884.4 | G78: =参数输入表!$H$625*参数输入表!$H$102+参数输入表!$H$625*参数输入表!$H$103 -> 16474 | H78: =G78-H79 -> 15924.867 | I78: =H78-I79 -> 15375.733 | J78: =I78-J79 -> 14826.6 | K78: =J78-K79 -> 14277.467 | L78: =K78-L79 -> 13728.333 | M78: =L78-M79 -> 13179.2 | N78: =M78-N79 -> 12630.067 | O78: =N78-O79 -> 12080.933 | ... AA78: =Z78-AA79 -> 5491.3333
C79: 当期无形资产摊销 | D79: =SUM(F79:AA79) -> 10982.667 | E79: 万元 | H79: =IF(H67<=$D$27,G78*(1-$D$28)/($D$27-H35+1),0) -> 549.13333 | I79: =IF(I67<=$D$27,H78*(1-$D$28)/($D$27-I35+1),0) -> 549.13333 | J79: =IF(J67<=$D$27,I78*(1-$D$28)/($D$27-J35+1),0) -> 549.13333 | K79: =IF(K67<=$D$27,J78*(1-$D$28)/($D$27-K35+1),0) -> 549.13333 | L79: =IF(L67<=$D$27,K78*(1-$D$28)/($D$27-L35+1),0) -> 549.13333 | M79: =IF(M67<=$D$27,L78*(1-$D$28)/($D$27-M35+1),0) -> 549.13333 | N79: =IF(N67<=$D$27,M78*(1-$D$28)/($D$27-N35+1),0) -> 549.13333 | O79: =IF(O67<=$D$27,N78*(1-$D$28)/($D$27-O35+1),0) -> 549.13333 | ... AA79: =IF(AA67<=$D$27,Z78*(1-$D$28)/($D$27-AA35+1),0) -> 549.13333
B80: 6 | C80: 期初大修及更新重置资产净值 | E80: 万元 | H80: =H48 -> 0 | I80: =I48 -> 0 | J80: =J48 -> 0 | K80: =K48 -> 0 | L80: =L48 -> 0 | M80: =M48 -> 0 | N80: =N48 -> 0 | O80: =O48 -> 0 | ... AA80: =AA48 -> 106.19469
C81: 当期新增大修及更新重置资产 | H81: =H49 -> 0 | I81: =I49 -> 0 | J81: =J49 -> 0 | K81: =K49 -> 0 | L81: =L49 -> 0 | M81: =M49 -> 0 | N81: =N49 -> 0 | O81: =O49 -> 0 | ... AA81: =AA49 -> 0
C82: 当期大修及更新重置资产折旧摊销 | D82: =SUM(F82:AA82) -> 378.31858 | E82: 万元 | H82: =H50 -> 0 | I82: =I50 -> 0 | J82: =J50 -> 0 | K82: =K50 -> 0 | L82: =L50 -> 0 | M82: =M50 -> 0 | N82: =N50 -> 0 | O82: =O50 -> 0 | ... AA82: =AA50 -> 42.035398
C83: 期末大修及更新重置资产净值 | H83: =H51 -> 0 | I83: =I51 -> 0 | J83: =J51 -> 0 | K83: =K51 -> 0 | L83: =L51 -> 0 | M83: =M51 -> 0 | N83: =N51 -> 0 | O83: =O51 -> 0 | ... AA83: =AA51 -> 64.159292
B84: 5 | C84: 当期折旧摊销 | D84: =SUM(F84:AA84) -> 55402.199 | E84: 万元 | F84: =F69+F76+F79+F82 -> 0 | G84: =G69+G76+G79+G82 -> 0 | H84: =H69+H76+H79+H82+H71+H73 -> 3771.0112 | I84: =I69+I76+I79+I82+I71+I73 -> 3771.0112 | J84: =J69+J76+J79+J82+J71+J73 -> 3771.0112 | K84: =K69+K76+K79+K82+K71+K73 -> 3771.0112 | L84: =L69+L76+L79+L82+L71+L73 -> 3771.0112 | M84: =M69+M76+M79+M82+M71+M73 -> 3771.0112 | N84: =N69+N76+N79+N82+N71+N73 -> 3771.0112 | O84: =O69+O76+O79+O82+O71+O73 -> 3771.0112 | ... AA84: =AA69+AA76+AA79+AA82+AA71+AA73 -> 591.16873

Sheet 表3-成本费用表
B2: 成本费用表-资本金
B3: 序号 | C3: 项目 | D3: 合计 | E3: 单位 | F3: 建设期 | H3: 运营期
F4: 1 | G4: 2 | H4: 1 | I4: 2 | J4: 3 | K4: 4 | L4: 5 | M4: 6 | N4: 7 | O4: 8 | P4: 9 | Q4: 10 | R4: 11 | S4: 12 | T4: 13 | U4: 14 | V4: 15 | W4: 16 | X4: 17 | Y4: 18 | Z4: 19 | AA4: 20
B5: 一 | C5: 营业总成本 | D5: =SUM(F5:AA5) -> 335351.07 | E5: 万元 | H5: =H6+H15+H16+H19+H20 -> 18348.333 | I5: =I6+I15+I16+I19+I20 -> 18218.572 | J5: =J6+J15+J16+J19+J20 -> 18088.823 | K5: =K6+K15+K16+K19+K20 -> 17959.087 | L5: =L6+L15+L16+L19+L20 -> 17829.363 | M5: =M6+M15+M16+M19+M20 -> 18526.787 | N5: =N6+N15+N16+N19+N20 -> 18388.487 | O5: =O6+O15+O16+O19+O20 -> 18250.234 | ... AA5: =AA6+AA15+AA16+AA19+AA20 -> 13942.513
B6: 1 | C6: 生产成本 | D6: =SUM(F6:AA6) -> 319691.66 | H6: =SUM(H7:H14) -> 16437.678 | I6: =SUM(I7:I14) -> 16433.215 | J6: =SUM(J7:J14) -> 16428.764 | K6: =SUM(K7:K14) -> 16424.326 | L6: =SUM(L7:L14) -> 16419.901 | M6: =SUM(M7:M14) -> 17242.623 | N6: =SUM(N7:N14) -> 17229.622 | O6: =SUM(O7:O14) -> 17216.667 | ... AA6: =SUM(AA7:AA14) -> 13911.332
B7: 1.1 | C7: 水费、油费 | D7: =SUM(F7:AA7) -> 104000 | E7: 万元 | H7: =参数输入表!$H$374/(1+参数输入表!$H$378) -> 5200 | I7: =参数输入表!$H$374/(1+参数输入表!$H$378) -> 5200 | J7: =参数输入表!$H$374/(1+参数输入表!$H$378) -> 5200 | K7: =参数输入表!$H$374/(1+参数输入表!$H$378) -> 5200 | L7: =参数输入表!$H$374/(1+参数输入表!$H$378) -> 5200 | M7: =参数输入表!$H$375/(1+参数输入表!$H$378) -> 5200 | N7: =参数输入表!$H$375/(1+参数输入表!$H$378) -> 5200 | O7: =参数输入表!$H$375/(1+参数输入表!$H$378) -> 5200 | P7: =参数输入表!$H$375/(1+参数输入表!$H$378) -> 5200 | Q7: =参数输入表!$H$375/(1+参数输入表!$H$378) -> 5200 | R7: =参数输入表!$H$376/(1+参数输入表!$H$378) -> 5200 | S7: =参数输入表!$H$376/(1+参数输入表!$H$378) -> 5200 | T7: =参数输入表!$H$376/(1+参数输入表!$H$378) -> 5200 | U7: =参数输入表!$H$376/(1+参数输入表!$H$378) -> 5200 | V7: =参数输入表!$H$376/(1+参数输入表!$H$378) -> 5200 | W7: =参数输入表!$H$377/(1+参数输入表!$H$378) -> 5200 | X7: =参数输入表!$H$377/(1+参数输入表!$H$378) -> 5200 | Y7: =参数输入表!$H$377/(1+参数输入表!$H$378) -> 5200 | Z7: =参数输入表!$H$377/(1+参数输入表!$H$378) -> 5200 | AA7: =参数输入表!$H$377/(1+参数输入表!$H$378) -> 5200
B8: 1.2 | C8: 维修费 | D8: =SUM(F8:AA8) -> 13910.639 | E8: 万元 | H8: =(参数输入表!$H$350-参数输入表!$H$353-参数输入表!$H$345-参数输入表!$H$346)*参数输入表!$H$382/(1+参数输入表!$H$386) -> 695.20008 | I8: =(参数输入表!$H$350-参数输入表!$H$353-参数输入表!$H$345-参数输入表!$H$346)*参数输入表!$H$382/(1+参数输入表!$H$386) -> 695.20008 | J8: =(参数输入表!$H$350-参数输入表!$H$353-参数输入表!$H$345-参数输入表!$H$346)*参数输入表!$H$382/(1+参数输入表!$H$386) -> 695.20008 | K8: =(参数输入表!$H$350-参数输入表!$H$353-参数输入表!$H$345-参数输入表!$H$346)*参数输入表!$H$382/(1+参数输入表!$H$386) -> 695.20008 | L8: =(参数输入表!$H$350-参数输入表!$H$353-参数输入表!$H$345-参数输入表!$H$346)*参数输入表!$H$382/(1+参数输入表!$H$386) -> 695.20008 | M8: =(参数输入表!$H$350-参数输入表!$H$353-参数输入表!$H$345-参数输入表!$H$346)*参数输入表!$H$382/(1+参数输入表!$H$386) -> 695.20008 | N8: =(参数输入表!$H$350-参数输入表!$H$353-参数输入表!$H$345-参数输入表!$H$346)*参数输入表!$H$382/(1+参数输入表!$H$386) -> 695.20008 | O8: =(参数输入表!$H$350-参数输入表!$H$353-参数输入表!$H$345-参数输入表!$H$346)*参数输入表!$H$382/(1+参数输入表!$H$386) -> 695.20008 | ... Q8: =(参数输入表!$H$350-参数输入表!$H$353-参数输入表!$H$345-参数输入表!$H$346)*参数输入表!$H$382/(1+参数输入表!$H$386) -> 695.20008 | R8: =(参数输入表!$H$350-参数输入表!$H$353-参数输入表!$H$345-参数输入表!$H$346)*参数输入表!$H$382/(1+参数输入表!$H$386)+参数输入表!$H$667*参数输入表!$H$384/(1+参数输入表!$H$679) -> 701.83725 | S8: =(参数输入表!$H$350-参数输入表!$H$353-参数输入表!$H$345-参数输入表!$H$346)*参数输入表!$H$382/(1+参数输入表!$H$386) -> 695.20008 | T8: =(参数输入表!$H$350-参数输入表!$H$353-参数输入表!$H$345-参数输入表!$H$346)*参数输入表!$H$382/(1+参数输入表!$H$386) -> 695.20008 | U8: =(参数输入表!$H$350-参数输入表!$H$353-参数输入表!$H$345-参数输入表!$H$346)*参数输入表!$H$382/(1+参数输入表!$H$386) -> 695.20008 | V8: =(参数输入表!$H$350-参数输入表!$H$353-参数输入表!$H$345-参数输入表!$H$346)*参数输入表!$H$382/(1+参数输入表!$H$386) -> 695.20008 | W8: =(参数输入表!$H$350-参数输入表!$H$353-参数输入表!$H$345-参数输入表!$H$346)*参数输入表!$H$382/(1+参数输入表!$H$386) -> 695.20008 | X8: =(参数输入表!$H$350-参数输入表!$H$353-参数输入表!$H$345-参数输入表!$H$346)*参数输入表!$H$382/(1+参数输入表!$H$386) -> 695.20008 | Y8: =(参数输入表!$H$350-参数输入表!$H$353-参数输入表!$H$345-参数输入表!$H$346)*参数输入表!$H$382/(1+参数输入表!$H$386) -> 695.20008 | Z8: =(参数输入表!$H$350-参数输入表!$H$353-参数输入表!$H$345-参数输入表!$H$346)*参数输入表!$H$382/(1+参数输入表!$H$386) -> 695.20008 | AA8: =(参数输入表!$H$350-参数输入表!$H$353-参数输入表!$H$345-参数输入表!$H$346)*参数输入表!$H$382/(1+参数输入表!$H$386) -> 695.20008
B9: 1.3 | C9: 生产人员薪酬及福利 | D9: =SUM(F9:AA9) -> 15360 | E9: 万元 | H9: =(参数输入表!$H$397*参数输入表!$H$400+参数输入表!$H$398*参数输入表!$H$401)*(1+参数输入表!$H$402)*(1+参数输入表!$H$403*(H4-1))/(1+参数输入表!$H$404) -> 768 | I9: =(参数输入表!$H$397*参数输入表!$H$400+参数输入表!$H$398*参数输入表!$H$401)*(1+参数输入表!$H$402)*(1+参数输入表!$H$403*(I4-1))/(1+参数输入表!$H$404) -> 768 | J9: =(参数输入表!$H$397*参数输入表!$H$400+参数输入表!$H$398*参数输入表!$H$401)*(1+参数输入表!$H$402)*(1+参数输入表!$H$403*(J4-1))/(1+参数输入表!$H$404) -> 768 | K9: =(参数输入表!$H$397*参数输入表!$H$400+参数输入表!$H$398*参数输入表!$H$401)*(1+参数输入表!$H$402)*(1+参数输入表!$H$403*(K4-1))/(1+参数输入表!$H$404) -> 768 | L9: =(参数输入表!$H$397*参数输入表!$H$400+参数输入表!$H$398*参数输入表!$H$401)*(1+参数输入表!$H$402)*(1+参数输入表!$H$403*(L4-1))/(1+参数输入表!$H$404) -> 768 | M9: =(参数输入表!$H$397*参数输入表!$H$400+参数输入表!$H$398*参数输入表!$H$401)*(1+参数输入表!$H$402)*(1+参数输入表!$H$403*(M4-1))/(1+参数输入表!$H$404) -> 768 | N9: =(参数输入表!$H$397*参数输入表!$H$400+参数输入表!$H$398*参数输入表!$H$401)*(1+参数输入表!$H$402)*(1+参数输入表!$H$403*(N4-1))/(1+参数输入表!$H$404) -> 768 | O9: =(参数输入表!$H$397*参数输入表!$H$400+参数输入表!$H$398*参数输入表!$H$401)*(1+参数输入表!$H$402)*(1+参数输入表!$H$403*(O4-1))/(1+参数输入表!$H$404) -> 768 | ... AA9: =(参数输入表!$H$397*参数输入表!$H$400+参数输入表!$H$398*参数输入表!$H$401)*(1+参数输入表!$H$402)*(1+参数输入表!$H$403*(AA4-1))/(1+参数输入表!$H$404) -> 768
B10: 1.4 | C10: 长期待摊费用当期摊销 | D10: =SUM(F10:AA10) -> 0 | E10: 万元 | H10: ='表2-折旧摊销表'!H44 -> 0 | I10: ='表2-折旧摊销表'!I44 -> 0 | J10: ='表2-折旧摊销表'!J44 -> 0 | K10: ='表2-折旧摊销表'!K44 -> 0 | L10: ='表2-折旧摊销表'!L44 -> 0 | M10: ='表2-折旧摊销表'!M44 -> 0 | N10: ='表2-折旧摊销表'!N44 -> 0 | O10: ='表2-折旧摊销表'!O44 -> 0 | ... AA10: ='表2-折旧摊销表'!AA44 -> 0
B11: 1.5 | C11: 营业相关资产折旧及摊销 | D11: =SUM(F11:AA11) -> 55402.199 | E11: 万元 | H11: ='表2-折旧摊销表'!H37+'表2-折旧摊销表'!H47+'表2-折旧摊销表'!H50+'表2-折旧摊销表'!H39+'表2-折旧摊销表'!H41 -> 3771.0112 | I11: ='表2-折旧摊销表'!I37+'表2-折旧摊销表'!I47+'表2-折旧摊销表'!I50+'表2-折旧摊销表'!I39+'表2-折旧摊销表'!I41 -> 3771.0112 | J11: ='表2-折旧摊销表'!J37+'表2-折旧摊销表'!J47+'表2-折旧摊销表'!J50+'表2-折旧摊销表'!J39+'表2-折旧摊销表'!J41 -> 3771.0112 | K11: ='表2-折旧摊销表'!K37+'表2-折旧摊销表'!K47+'表2-折旧摊销表'!K50+'表2-折旧摊销表'!K39+'表2-折旧摊销表'!K41 -> 3771.0112 | L11: ='表2-折旧摊销表'!L37+'表2-折旧摊销表'!L47+'表2-折旧摊销表'!L50+'表2-折旧摊销表'!L39+'表2-折旧摊销表'!L41 -> 3771.0112 | M11: ='表2-折旧摊销表'!M37+'表2-折旧摊销表'!M47+'表2-折旧摊销表'!M50+'表2-折旧摊销表'!M39+'表2-折旧摊销表'!M41 -> 3771.0112 | N11: ='表2-折旧摊销表'!N37+'表2-折旧摊销表'!N47+'表2-折旧摊销表'!N50+'表2-折旧摊销表'!N39+'表2-折旧摊销表'!N41 -> 3771.0112 | O11: ='表2-折旧摊销表'!O37+'表2-折旧摊销表'!O47+'表2-折旧摊销表'!O50+'表2-折旧摊销表'!O39+'表2-折旧摊销表'!O41 -> 3771.0112 | ... AA11: ='表2-折旧摊销表'!AA37+'表2-折旧摊销表'!AA47+'表2-折旧摊销表'!AA50+'表2-折旧摊销表'!AA39+'表2-折旧摊销表'!AA41 -> 591.16873
B12: 1.6 | C12: 其他费用 | D12: =SUM(F12:AA12) -> 44000 | E12: 万元 | H12: =参数输入表!$H$405/(1+参数输入表!$H$406) -> 2200 | I12: =参数输入表!$H$405/(1+参数输入表!$H$406) -> 2200 | J12: =参数输入表!$H$405/(1+参数输入表!$H$406) -> 2200 | K12: =参数输入表!$H$405/(1+参数输入表!$H$406) -> 2200 | L12: =参数输入表!$H$405/(1+参数输入表!$H$406) -> 2200 | M12: =参数输入表!$H$405/(1+参数输入表!$H$406) -> 2200 | N12: =参数输入表!$H$405/(1+参数输入表!$H$406) -> 2200 | O12: =参数输入表!$H$405/(1+参数输入表!$H$406) -> 2200 | ... AA12: =参数输入表!$H$405/(1+参数输入表!$H$406) -> 2200
B13: 1.7 | C13: 电费(每年不同）注意调整 | D13: =SUM(F13:AA13) -> 83018.827 | E13: 万元 | H13: =参数输入表!H417*参数输入表!H418/10/(1+参数输入表!$H$617)+参数输入表!H597/(1+参数输入表!$H$617) -> 3603.4668 | I13: =参数输入表!H426*参数输入表!H427/10/(1+参数输入表!$H$617)+参数输入表!H598/(1+参数输入表!$H$617) -> 3599.0035 | J13: =参数输入表!H435*参数输入表!H436/10/(1+参数输入表!$H$617)+参数输入表!H599/(1+参数输入表!$H$617) -> 3594.5529 | K13: =参数输入表!H444*参数输入表!H445/10/(1+参数输入表!$H$617)+参数输入表!H600/(1+参数输入表!$H$617) -> 3590.115 | L13: =参数输入表!H453*参数输入表!H454/10/(1+参数输入表!$H$617)+参数输入表!H601/(1+参数输入表!$H$617) -> 3585.6898 | M13: =参数输入表!H462*参数输入表!H463/10/(1+参数输入表!$H$617)+参数输入表!H602/(1+参数输入表!$H$617) -> 4408.4122 | N13: =参数输入表!H471*参数输入表!H472/10/(1+参数输入表!$H$617)+参数输入表!H603/(1+参数输入表!$H$617) -> 4395.4108 | O13: =参数输入表!H480*参数输入表!H481/10/(1+参数输入表!$H$617)+参数输入表!H604/(1+参数输入表!$H$617) -> 4382.4561 | P13: =参数输入表!H489*参数输入表!H490/10/(1+参数输入表!$H$617)+参数输入表!H605/(1+参数输入表!$H$617) -> 4369.5478 | Q13: =参数输入表!H498*参数输入表!H499/10/(1+参数输入表!$H$617)+参数输入表!H606/(1+参数输入表!$H$617) -> 4356.6857 | R13: =参数输入表!H507*参数输入表!H508/10/(1+参数输入表!$H$617)+参数输入表!H607/(1+参数输入表!$H$617) -> 4370.2723 | S13: =参数输入表!H516*参数输入表!H517/10/(1+参数输入表!$H$617)+参数输入表!H608/(1+参数输入表!$H$617) -> 4357.502 | T13: =参数输入表!H525*参数输入表!H526/10/(1+参数输入表!$H$617)+参数输入表!H609/(1+参数输入表!$H$617) -> 4344.7773 | U13: =参数输入表!H534*参数输入表!H535/10/(1+参数输入表!$H$617)+参数输入表!H610/(1+参数输入表!$H$617) -> 4332.0979 | V13: =参数输入表!H543*参数输入表!H544/10/(1+参数输入表!$H$617)+参数输入表!H611/(1+参数输入表!$H$617) -> 4319.4637 | W13: =参数输入表!H552*参数输入表!H553/10/(1+参数输入表!$H$617)+参数输入表!H612/(1+参数输入表!$H$617) -> 4306.8746 | X13: =参数输入表!H561*参数输入表!H562/10/(1+参数输入表!$H$617)+参数输入表!H613/(1+参数输入表!$H$617) -> 4294.3301 | Y13: =参数输入表!H570*参数输入表!H571/10/(1+参数输入表!$H$617)+参数输入表!H614/(1+参数输入表!$H$617) -> 4281.8303 | Z13: =参数输入表!H579*参数输入表!H580/10/(1+参数输入表!$H$617)+参数输入表!H615/(1+参数输入表!$H$617) -> 4269.3748 | AA13: =参数输入表!H588*参数输入表!H589/10/(1+参数输入表!$H$617)+参数输入表!H616/(1+参数输入表!$H$617) -> 4256.9635
B14: 1.8 | C14: 宽带费用 | D14: =SUM(F14:AA14) -> 4000 | E14: 万元 | H14: =参数输入表!$H$408/(1+参数输入表!$H$409) -> 200 | I14: =参数输入表!$H$408/(1+参数输入表!$H$409) -> 200 | J14: =参数输入表!$H$408/(1+参数输入表!$H$409) -> 200 | K14: =参数输入表!$H$408/(1+参数输入表!$H$409) -> 200 | L14: =参数输入表!$H$408/(1+参数输入表!$H$409) -> 200 | M14: =参数输入表!$H$408/(1+参数输入表!$H$409) -> 200 | N14: =参数输入表!$H$408/(1+参数输入表!$H$409) -> 200 | O14: =参数输入表!$H$408/(1+参数输入表!$H$409) -> 200 | ... AA14: =参数输入表!$H$408/(1+参数输入表!$H$409) -> 200
B15: 2 | C15: 销售费用 | D15: =SUM(F15:AA15) -> 0 | E15: 万元 | H15: 0 | I15: 0 | J15: 0 | K15: 0 | L15: 0 | M15: 0 | N15: 0 | O15: 0 | P15: 0 | Q15: 0 | R15: 0 | S15: 0 | T15: 0 | U15: 0 | V15: 0 | W15: 0 | X15: 0 | Y15: 0 | Z15: 0 | AA15: 0
B16: 3 | C16: 管理费用 | D16: =SUM(F16:AA16) -> 463.59172 | E16: 万元 | H16: =SUM(H17:H18) -> 23.179586 | I16: =SUM(I17:I18) -> 23.179586 | J16: =SUM(J17:J18) -> 23.179586 | K16: =SUM(K17:K18) -> 23.179586 | L16: =SUM(L17:L18) -> 23.179586 | M16: =SUM(M17:M18) -> 23.179586 | N16: =SUM(N17:N18) -> 23.179586 | O16: =SUM(O17:O18) -> 23.179586 | ... AA16: =SUM(AA17:AA18) -> 23.179586
B17: 3.1 | C17: 保险费 | D17: =SUM(F17:AA17) -> 463.59172 | E17: 万元 | H17: =('表2-折旧摊销表'!$D$4)*参数输入表!$H$390/(1+参数输入表!$H$394) -> 23.179586 | I17: =('表2-折旧摊销表'!$D$4)*参数输入表!$H$390/(1+参数输入表!$H$394) -> 23.179586 | J17: =('表2-折旧摊销表'!$D$4)*参数输入表!$H$390/(1+参数输入表!$H$394) -> 23.179586 | K17: =('表2-折旧摊销表'!$D$4)*参数输入表!$H$390/(1+参数输入表!$H$394) -> 23.179586 | L17: =('表2-折旧摊销表'!$D$4)*参数输入表!$H$390/(1+参数输入表!$H$394) -> 23.179586 | M17: =('表2-折旧摊销表'!$D$4)*参数输入表!$H$390/(1+参数输入表!$H$394) -> 23.179586 | N17: =('表2-折旧摊销表'!$D$4)*参数输入表!$H$390/(1+参数输入表!$H$394) -> 23.179586 | O17: =('表2-折旧摊销表'!$D$4)*参数输入表!$H$390/(1+参数输入表!$H$394) -> 23.179586 | ... AA17: =('表2-折旧摊销表'!$D$4)*参数输入表!$H$390/(1+参数输入表!$H$394) -> 23.179586
B18: 3.2 | C18: 期末拆除费用 | D18: =SUM(F18:AA18) -> 0 | E18: 万元 | H18: 0 | I18: 0 | J18: 0 | K18: 0 | L18: 0 | M18: 0 | N18: 0 | O18: 0 | P18: 0 | Q18: 0 | R18: 0 | S18: 0 | T18: 0 | U18: 0 | V18: 0 | W18: 0 | X18: 0 | Y18: 0 | Z18: 0 | AA18: =参数输入表!H412*参数输入表!H411/(1+参数输入表!$H$413) -> 0
B19: 4 | C19: 研发费用 | D19: =SUM(F19:AA19) -> 0 | E19: 万元 | H19: 0 | I19: 0 | J19: 0 | K19: 0 | L19: 0 | M19: 0 | N19: 0 | O19: 0 | P19: 0 | Q19: 0 | R19: 0 | S19: 0 | T19: 0 | U19: 0 | V19: 0 | W19: 0 | X19: 0 | Y19: 0 | Z19: 0 | AA19: 0
B20: 5 | C20: 财务费用 | D20: =SUM(F20:AA20) -> 15195.816 | E20: 万元 | H20: =SUM(H21:H23) -> 1887.4755 | I20: =SUM(I21:I23) -> 1762.1772 | J20: =SUM(J21:J23) -> 1636.8789 | K20: =SUM(K21:K23) -> 1511.5806 | L20: =SUM(L21:L23) -> 1386.2823 | M20: =SUM(M21:M23) -> 1260.984 | N20: =SUM(N21:N23) -> 1135.6857 | O20: =SUM(O21:O23) -> 1010.3874 | ... AA20: =SUM(AA21:AA23) -> 8.001
B21: 5.1 | C21: 长期借款利息 | D21: =SUM(F21:AA21) -> 15035.796 | E21: 万元 | H21: ='表1-资金筹措及还本付息表'!H43 -> 1879.4745 | I21: ='表1-资金筹措及还本付息表'!I53 -> 1754.1762 | J21: ='表1-资金筹措及还本付息表'!J53 -> 1628.8779 | K21: ='表1-资金筹措及还本付息表'!K53 -> 1503.5796 | L21: ='表1-资金筹措及还本付息表'!L53 -> 1378.2813 | M21: ='表1-资金筹措及还本付息表'!M53 -> 1252.983 | N21: ='表1-资金筹措及还本付息表'!N53 -> 1127.6847 | O21: ='表1-资金筹措及还本付息表'!O53 -> 1002.3864 | P21: ='表1-资金筹措及还本付息表'!P53 -> 877.08812 | ... V21: ='表1-资金筹措及还本付息表'!V53 -> 125.2983 | W21: ='表1-资金筹措及还本付息表'!W43 -> 0 | X21: ='表1-资金筹措及还本付息表'!X43 -> 0 | Y21: ='表1-资金筹措及还本付息表'!Y43 -> 0 | Z21: ='表1-资金筹措及还本付息表'!Z43 -> 0 | AA21: ='表1-资金筹措及还本付息表'!AA43 -> 0
B22: 5.2 | C22: 流动资金利息 | D22: =SUM(F22:AA22) -> 160.02 | E22: 万元 | H22: ='表1-资金筹措及还本付息表'!H63 -> 8.001 | I22: ='表1-资金筹措及还本付息表'!I63 -> 8.001 | J22: ='表1-资金筹措及还本付息表'!J63 -> 8.001 | K22: ='表1-资金筹措及还本付息表'!K63 -> 8.001 | L22: ='表1-资金筹措及还本付息表'!L63 -> 8.001 | M22: ='表1-资金筹措及还本付息表'!M63 -> 8.001 | N22: ='表1-资金筹措及还本付息表'!N63 -> 8.001 | O22: ='表1-资金筹措及还本付息表'!O63 -> 8.001 | ... AA22: ='表1-资金筹措及还本付息表'!AA63 -> 8.001
B23: 5.3 | C23: 短期借款利息 | D23: =SUM(F23:AA23) -> 0 | E23: 万元 | H23: ='表1-资金筹措及还本付息表'!H73 -> 0 | I23: ='表1-资金筹措及还本付息表'!I73 -> 0 | J23: ='表1-资金筹措及还本付息表'!J73 -> 0 | K23: ='表1-资金筹措及还本付息表'!K73 -> 0 | L23: ='表1-资金筹措及还本付息表'!L73 -> 0 | M23: ='表1-资金筹措及还本付息表'!M73 -> 0 | N23: ='表1-资金筹措及还本付息表'!N73 -> 0 | O23: ='表1-资金筹措及还本付息表'!O73 -> 0 | ... AA23: ='表1-资金筹措及还本付息表'!AA73 -> 0
B24: 二 | C24: 营业外支出 | D24: =SUM(F24:AA24) -> 0 | E24: 万元 | H24: =参数输入表!$H$682/(1+参数输入表!$H$686) -> 0 | I24: =参数输入表!$H$682/(1+参数输入表!$H$686) -> 0 | J24: =参数输入表!$H$682/(1+参数输入表!$H$686) -> 0 | K24: =参数输入表!$H$682/(1+参数输入表!$H$686) -> 0 | L24: =参数输入表!$H$682/(1+参数输入表!$H$686) -> 0 | M24: =参数输入表!$H$682/(1+参数输入表!$H$686) -> 0 | N24: =参数输入表!$H$682/(1+参数输入表!$H$686) -> 0 | O24: =参数输入表!$H$682/(1+参数输入表!$H$686) -> 0 | ... AA24: =参数输入表!$H$682/(1+参数输入表!$H$686) -> 0
B26: 成本费用表-全投资
B27: 序号 | C27: 项目 | D27: 合计 | E27: 单位 | F27: 建设期 | H27: 运营期
F28: 1 | G28: 2 | H28: 1 | I28: 2 | J28: 3 | K28: 4 | L28: 5 | M28: 6 | N28: 7 | O28: 8 | P28: 9 | Q28: 10 | R28: 11 | S28: 12 | T28: 13 | U28: 14 | V28: 15 | W28: 16 | X28: 17 | Y28: 18 | Z28: 19 | AA28: 20
B29: 一 | C29: 营业总成本 | D29: =SUM(F29:AA29) -> 320155.26 | E29: 万元 | H29: =H30+H39+H40+H43 -> 16460.858 | I29: =I30+I39+I40+I43 -> 16456.394 | J29: =J30+J39+J40+J43 -> 16451.944 | K29: =K30+K39+K40+K43 -> 16447.506 | L29: =L30+L39+L40+L43 -> 16443.081 | M29: =M30+M39+M40+M43 -> 17265.803 | N29: =N30+N39+N40+N43 -> 17252.802 | O29: =O30+O39+O40+O43 -> 17239.847 | ... AA29: =AA30+AA39+AA40+AA43 -> 13934.512
B30: 1 | C30: 生产成本 | D30: =SUM(F30:AA30) -> 319691.66 | H30: =SUM(H31:H38) -> 16437.678 | I30: =SUM(I31:I38) -> 16433.215 | J30: =SUM(J31:J38) -> 16428.764 | K30: =SUM(K31:K38) -> 16424.326 | L30: =SUM(L31:L38) -> 16419.901 | M30: =SUM(M31:M38) -> 17242.623 | N30: =SUM(N31:N38) -> 17229.622 | O30: =SUM(O31:O38) -> 17216.667 | ... AA30: =SUM(AA31:AA38) -> 13911.332
B31: 1.1 | C31: 材料费 | D31: =SUM(F31:AA31) -> 104000 | E31: 万元 | H31: =H7 -> 5200 | I31: =I7 -> 5200 | J31: =J7 -> 5200 | K31: =K7 -> 5200 | L31: =L7 -> 5200 | M31: =M7 -> 5200 | N31: =N7 -> 5200 | O31: =O7 -> 5200 | ... AA31: =AA7 -> 5200
B32: 1.2 | C32: 维修费 | D32: =SUM(F32:AA32) -> 13910.639 | E32: 万元 | H32: =H8 -> 695.20008 | I32: =I8 -> 695.20008 | J32: =J8 -> 695.20008 | K32: =K8 -> 695.20008 | L32: =L8 -> 695.20008 | M32: =M8 -> 695.20008 | N32: =N8 -> 695.20008 | O32: =O8 -> 695.20008 | ... AA32: =AA8 -> 695.20008
B33: 1.3 | C33: 生产人员薪酬及福利 | D33: =SUM(F33:AA33) -> 15360 | E33: 万元 | H33: =(参数输入表!$H$397*参数输入表!$H$400+参数输入表!$H$398*参数输入表!$H$401)*(1+参数输入表!$H$402)*(1+参数输入表!$H$403*(H28-1))/(1+参数输入表!$H$404) -> 768 | I33: =(参数输入表!$H$397*参数输入表!$H$400+参数输入表!$H$398*参数输入表!$H$401)*(1+参数输入表!$H$402)*(1+参数输入表!$H$403*(I28-1))/(1+参数输入表!$H$404) -> 768 | J33: =(参数输入表!$H$397*参数输入表!$H$400+参数输入表!$H$398*参数输入表!$H$401)*(1+参数输入表!$H$402)*(1+参数输入表!$H$403*(J28-1))/(1+参数输入表!$H$404) -> 768 | K33: =(参数输入表!$H$397*参数输入表!$H$400+参数输入表!$H$398*参数输入表!$H$401)*(1+参数输入表!$H$402)*(1+参数输入表!$H$403*(K28-1))/(1+参数输入表!$H$404) -> 768 | L33: =(参数输入表!$H$397*参数输入表!$H$400+参数输入表!$H$398*参数输入表!$H$401)*(1+参数输入表!$H$402)*(1+参数输入表!$H$403*(L28-1))/(1+参数输入表!$H$404) -> 768 | M33: =(参数输入表!$H$397*参数输入表!$H$400+参数输入表!$H$398*参数输入表!$H$401)*(1+参数输入表!$H$402)*(1+参数输入表!$H$403*(M28-1))/(1+参数输入表!$H$404) -> 768 | N33: =(参数输入表!$H$397*参数输入表!$H$400+参数输入表!$H$398*参数输入表!$H$401)*(1+参数输入表!$H$402)*(1+参数输入表!$H$403*(N28-1))/(1+参数输入表!$H$404) -> 768 | O33: =(参数输入表!$H$397*参数输入表!$H$400+参数输入表!$H$398*参数输入表!$H$401)*(1+参数输入表!$H$402)*(1+参数输入表!$H$403*(O28-1))/(1+参数输入表!$H$404) -> 768 | ... AA33: =(参数输入表!$H$397*参数输入表!$H$400+参数输入表!$H$398*参数输入表!$H$401)*(1+参数输入表!$H$402)*(1+参数输入表!$H$403*(AA28-1))/(1+参数输入表!$H$404) -> 768
B34: 1.4 | C34: 长期待摊费用当期摊销 | D34: =SUM(F34:AA34) -> 0 | E34: 万元 | H34: ='表2-折旧摊销表'!H76 -> 0 | I34: ='表2-折旧摊销表'!I76 -> 0 | J34: ='表2-折旧摊销表'!J76 -> 0 | K34: ='表2-折旧摊销表'!K76 -> 0 | L34: ='表2-折旧摊销表'!L76 -> 0 | M34: ='表2-折旧摊销表'!M76 -> 0 | N34: ='表2-折旧摊销表'!N76 -> 0 | O34: ='表2-折旧摊销表'!O76 -> 0 | ... AA34: ='表2-折旧摊销表'!AA76 -> 0
B35: 1.5 | C35: 营业相关资产折旧及摊销 | D35: =SUM(F35:AA35) -> 55402.199 | E35: 万元 | H35: ='表2-折旧摊销表'!H69+'表2-折旧摊销表'!H79+'表2-折旧摊销表'!H82+'表2-折旧摊销表'!H39+'表2-折旧摊销表'!H41 -> 3771.0112 | I35: ='表2-折旧摊销表'!I69+'表2-折旧摊销表'!I79+'表2-折旧摊销表'!I82+'表2-折旧摊销表'!I39+'表2-折旧摊销表'!I41 -> 3771.0112 | J35: ='表2-折旧摊销表'!J69+'表2-折旧摊销表'!J79+'表2-折旧摊销表'!J82+'表2-折旧摊销表'!J39+'表2-折旧摊销表'!J41 -> 3771.0112 | K35: ='表2-折旧摊销表'!K69+'表2-折旧摊销表'!K79+'表2-折旧摊销表'!K82+'表2-折旧摊销表'!K39+'表2-折旧摊销表'!K41 -> 3771.0112 | L35: ='表2-折旧摊销表'!L69+'表2-折旧摊销表'!L79+'表2-折旧摊销表'!L82+'表2-折旧摊销表'!L39+'表2-折旧摊销表'!L41 -> 3771.0112 | M35: ='表2-折旧摊销表'!M69+'表2-折旧摊销表'!M79+'表2-折旧摊销表'!M82+'表2-折旧摊销表'!M39+'表2-折旧摊销表'!M41 -> 3771.0112 | N35: ='表2-折旧摊销表'!N69+'表2-折旧摊销表'!N79+'表2-折旧摊销表'!N82+'表2-折旧摊销表'!N39+'表2-折旧摊销表'!N41 -> 3771.0112 | O35: ='表2-折旧摊销表'!O69+'表2-折旧摊销表'!O79+'表2-折旧摊销表'!O82+'表2-折旧摊销表'!O39+'表2-折旧摊销表'!O41 -> 3771.0112 | ... AA35: ='表2-折旧摊销表'!AA69+'表2-折旧摊销表'!AA79+'表2-折旧摊销表'!AA82+'表2-折旧摊销表'!AA39+'表2-折旧摊销表'!AA41 -> 591.16873
B36: 1.6 | C36: 其他费用 | D36: =SUM(F36:AA36) -> 44000 | E36: 万元 | H36: =H12 -> 2200 | I36: =I12 -> 2200 | J36: =J12 -> 2200 | K36: =K12 -> 2200 | L36: =L12 -> 2200 | M36: =M12 -> 2200 | N36: =N12 -> 2200 | O36: =O12 -> 2200 | ... AA36: =AA12 -> 2200
B37: 1.7 | C37: 电费(每年不同）注意调整 | D37: =SUM(F37:AA37) -> 83018.827 | E37: 万元 | H37: =H13 -> 3603.4668 | I37: =I13 -> 3599.0035 | J37: =J13 -> 3594.5529 | K37: =K13 -> 3590.115 | L37: =L13 -> 3585.6898 | M37: =M13 -> 4408.4122 | N37: =N13 -> 4395.4108 | O37: =O13 -> 4382.4561 | ... AA37: =AA13 -> 4256.9635
B38: 1.8 | C38: 宽带费用 | D38: =SUM(F38:AA38) -> 4000 | E38: 万元 | H38: =H14 -> 200 | I38: =I14 -> 200 | J38: =J14 -> 200 | K38: =K14 -> 200 | L38: =L14 -> 200 | M38: =M14 -> 200 | N38: =N14 -> 200 | O38: =O14 -> 200 | ... AA38: =AA14 -> 200
B39: 2 | C39: 销售费用 | D39: =SUM(F39:AA39) -> 0 | E39: 万元 | H39: 0 | I39: 0 | J39: 0 | K39: 0 | L39: 0 | M39: 0 | N39: 0 | O39: 0 | P39: 0 | Q39: 0 | R39: 0 | S39: 0 | T39: 0 | U39: 0 | V39: 0 | W39: 0 | X39: 0 | Y39: 0 | Z39: 0 | AA39: 0
B40: 3 | C40: 管理费用 | D40: =SUM(F40:AA40) -> 463.59172 | E40: 万元 | H40: =SUM(H41:H42) -> 23.179586 | I40: =SUM(I41:I42) -> 23.179586 | J40: =SUM(J41:J42) -> 23.179586 | K40: =SUM(K41:K42) -> 23.179586 | L40: =SUM(L41:L42) -> 23.179586 | M40: =SUM(M41:M42) -> 23.179586 | N40: =SUM(N41:N42) -> 23.179586 | O40: =SUM(O41:O42) -> 23.179586 | ... AA40: =SUM(AA41:AA42) -> 23.179586
B41: 3.1 | C41: 保险费 | D41: =SUM(F41:AA41) -> 463.59172 | E41: 万元 | H41: =H17 -> 23.179586 | I41: =I17 -> 23.179586 | J41: =J17 -> 23.179586 | K41: =K17 -> 23.179586 | L41: =L17 -> 23.179586 | M41: =M17 -> 23.179586 | N41: =N17 -> 23.179586 | O41: =O17 -> 23.179586 | ... AA41: =AA17 -> 23.179586
B42: 3.2 | C42: 期末拆除费用 | D42: =SUM(F42:AA42) -> 0 | E42: 万元 | H42: 0 | I42: 0 | J42: 0 | K42: 0 | L42: 0 | M42: 0 | N42: 0 | O42: 0 | P42: 0 | Q42: 0 | R42: 0 | S42: 0 | T42: 0 | U42: 0 | V42: 0 | W42: 0 | X42: 0 | Y42: 0 | Z42: 0 | AA42: =参数输入表!H412*参数输入表!H411/(1+参数输入表!$H$413) -> 0
B43: 4 | C43: 研发费用 | D43: =SUM(F43:AA43) -> 0 | E43: 万元 | H43: 0 | I43: 0 | J43: 0 | K43: 0 | L43: 0 | M43: 0 | N43: 0 | O43: 0 | P43: 0 | Q43: 0 | R43: 0 | S43: 0 | T43: 0 | U43: 0 | V43: 0 | W43: 0 | X43: 0 | Y43: 0 | Z43: 0 | AA43: 0
B44: 二 | C44: 营业外支出 | D44: =SUM(F44:AA44) -> 0 | E44: 万元 | H44: =参数输入表!$H$682/(1+参数输入表!$H$686) -> 0 | I44: =参数输入表!$H$682/(1+参数输入表!$H$686) -> 0 | J44: =参数输入表!$H$682/(1+参数输入表!$H$686) -> 0 | K44: =参数输入表!$H$682/(1+参数输入表!$H$686) -> 0 | L44: =参数输入表!$H$682/(1+参数输入表!$H$686) -> 0 | M44: =参数输入表!$H$682/(1+参数输入表!$H$686) -> 0 | N44: =参数输入表!$H$682/(1+参数输入表!$H$686) -> 0 | O44: =参数输入表!$H$682/(1+参数输入表!$H$686) -> 0 | ... AA44: =参数输入表!$H$682/(1+参数输入表!$H$686) -> 0
B47: 成本现金支出表（隐藏）
B48: 一 | C48: 生产经营现金支出合计 | D48: =SUM(F48:AA48) -> 264753.06 | E48: 万元 | H48: =H49+H57+H58+H61 -> 12689.846 | I48: =I49+I57+I58+I61 -> 12685.383 | J48: =J49+J57+J58+J61 -> 12680.933 | K48: =K49+K57+K58+K61 -> 12676.495 | L48: =L49+L57+L58+L61 -> 12672.069 | M48: =M49+M57+M58+M61 -> 13494.792 | N48: =N49+N57+N58+N61 -> 13481.791 | O48: =O49+O57+O58+O61 -> 13468.836 | ... AA48: =AA49+AA57+AA58+AA61 -> 13343.343
B49: 1 | C49: 生产相关现金支出 | D49: =SUM(F49:AA49) -> 264289.47 | E49: 万元 | H49: =SUM(H50:H56) -> 12666.667 | I49: =SUM(I50:I56) -> 12662.204 | J49: =SUM(J50:J56) -> 12657.753 | K49: =SUM(K50:K56) -> 12653.315 | L49: =SUM(L50:L56) -> 12648.89 | M49: =SUM(M50:M56) -> 13471.612 | N49: =SUM(N50:N56) -> 13458.611 | O49: =SUM(O50:O56) -> 13445.656 | ... AA49: =SUM(AA50:AA56) -> 13320.164
B50: 1.1 | C50: 材料费 | D50: =SUM(F50:AA50) -> 104000 | E50: 万元 | H50: =H7 -> 5200 | I50: =I7 -> 5200 | J50: =J7 -> 5200 | K50: =K7 -> 5200 | L50: =L7 -> 5200 | M50: =M7 -> 5200 | N50: =N7 -> 5200 | O50: =O7 -> 5200 | ... AA50: =AA7 -> 5200
B51: 1.2 | C51: 维修费 | D51: =SUM(F51:AA51) -> 13910.639 | E51: 万元 | H51: =H8 -> 695.20008 | I51: =I8 -> 695.20008 | J51: =J8 -> 695.20008 | K51: =K8 -> 695.20008 | L51: =L8 -> 695.20008 | M51: =M8 -> 695.20008 | N51: =N8 -> 695.20008 | O51: =O8 -> 695.20008 | ... AA51: =AA8 -> 695.20008
B52: 1.3 | C52: 生产人员薪酬及福利 | D52: =SUM(F52:AA52) -> 15360 | E52: 万元 | H52: =(参数输入表!$H$397*参数输入表!$H$400+参数输入表!$H$398*参数输入表!$H$401)*(1+参数输入表!$H$402)*(1+参数输入表!$H$403*(H4-1)) -> 768 | I52: =(参数输入表!$H$397*参数输入表!$H$400+参数输入表!$H$398*参数输入表!$H$401)*(1+参数输入表!$H$402)*(1+参数输入表!$H$403*(I4-1)) -> 768 | J52: =(参数输入表!$H$397*参数输入表!$H$400+参数输入表!$H$398*参数输入表!$H$401)*(1+参数输入表!$H$402)*(1+参数输入表!$H$403*(J4-1)) -> 768 | K52: =(参数输入表!$H$397*参数输入表!$H$400+参数输入表!$H$398*参数输入表!$H$401)*(1+参数输入表!$H$402)*(1+参数输入表!$H$403*(K4-1)) -> 768 | L52: =(参数输入表!$H$397*参数输入表!$H$400+参数输入表!$H$398*参数输入表!$H$401)*(1+参数输入表!$H$402)*(1+参数输入表!$H$403*(L4-1)) -> 768 | M52: =(参数输入表!$H$397*参数输入表!$H$400+参数输入表!$H$398*参数输入表!$H$401)*(1+参数输入表!$H$402)*(1+参数输入表!$H$403*(M4-1)) -> 768 | N52: =(参数输入表!$H$397*参数输入表!$H$400+参数输入表!$H$398*参数输入表!$H$401)*(1+参数输入表!$H$402)*(1+参数输入表!$H$403*(N4-1)) -> 768 | O52: =(参数输入表!$H$397*参数输入表!$H$400+参数输入表!$H$398*参数输入表!$H$401)*(1+参数输入表!$H$402)*(1+参数输入表!$H$403*(O4-1)) -> 768 | ... AA52: =(参数输入表!$H$397*参数输入表!$H$400+参数输入表!$H$398*参数输入表!$H$401)*(1+参数输入表!$H$402)*(1+参数输入表!$H$403*(AA4-1)) -> 768
B53: 1.4 | C53: 长期待摊实际支出 | D53: =SUM(F53:AA53) -> 0 | E53: 万元 | H53: =参数输入表!H631 -> 0 | I53: =参数输入表!H632 -> 0 | J53: =参数输入表!H633 -> 0 | K53: =参数输入表!H634 -> 0 | L53: =参数输入表!H635 -> 0 | M53: =参数输入表!H636 -> 0 | N53: =参数输入表!H637 -> 0 | O53: =参数输入表!H638 -> 0 | P53: =参数输入表!H639 -> 0 | Q53: =参数输入表!H640 -> 0 | R53: =参数输入表!H641 -> 0 | S53: =参数输入表!H642 -> 0 | T53: =参数输入表!H643 -> 0 | U53: =参数输入表!H644 -> 0 | V53: =参数输入表!H645 -> 0 | W53: =参数输入表!H646 -> 0 | X53: =参数输入表!H647 -> 0 | Y53: =参数输入表!H648 -> 0 | Z53: =参数输入表!H649 -> 0 | AA53: =参数输入表!H650 -> 0
B54: 1.5 | C54: 其他费用 | D54: =SUM(F54:AA54) -> 44000 | E54: 万元 | H54: =H12 -> 2200 | I54: =I12 -> 2200 | J54: =J12 -> 2200 | K54: =K12 -> 2200 | L54: =L12 -> 2200 | M54: =M12 -> 2200 | N54: =N12 -> 2200 | O54: =O12 -> 2200 | ... AA54: =AA12 -> 2200
B55: 1.7 | C55: 充电电费(每年不同）注意调整 | D55: =SUM(F55:AA55) -> 83018.827 | E55: 万元 | H55: =H37 -> 3603.4668 | I55: =I37 -> 3599.0035 | J55: =J37 -> 3594.5529 | K55: =K37 -> 3590.115 | L55: =L37 -> 3585.6898 | M55: =M37 -> 4408.4122 | N55: =N37 -> 4395.4108 | O55: =O37 -> 4382.4561 | ... AA55: =AA37 -> 4256.9635
B56: 1.7 | C56: 宽带费用 | D56: =SUM(F56:AA56) -> 4000 | E56: 万元 | H56: =H38 -> 200 | I56: =I38 -> 200 | J56: =J38 -> 200 | K56: =K38 -> 200 | L56: =L38 -> 200 | M56: =M38 -> 200 | N56: =N38 -> 200 | O56: =O38 -> 200 | ... AA56: =AA38 -> 200
B57: 2 | C57: 销售费用现金支出 | D57: =SUM(F57:AA57) -> 0 | E57: 万元 | H57: 0 | I57: 0 | J57: 0 | K57: 0 | L57: 0 | M57: 0 | N57: 0 | O57: 0 | P57: 0 | Q57: 0 | R57: 0 | S57: 0 | T57: 0 | U57: 0 | V57: 0 | W57: 0 | X57: 0 | Y57: 0 | Z57: 0 | AA57: 0
B58: 3 | C58: 管理费用现金支出 | D58: =SUM(F58:AA58) -> 463.59172 | E58: 万元 | H58: =SUM(H59:H60) -> 23.179586 | I58: =SUM(I59:I60) -> 23.179586 | J58: =SUM(J59:J60) -> 23.179586 | K58: =SUM(K59:K60) -> 23.179586 | L58: =SUM(L59:L60) -> 23.179586 | M58: =SUM(M59:M60) -> 23.179586 | N58: =SUM(N59:N60) -> 23.179586 | O58: =SUM(O59:O60) -> 23.179586 | ... AA58: =SUM(AA59:AA60) -> 23.179586
B59: 3.1 | C59: 保险费 | D59: =SUM(F59:AA59) -> 463.59172 | E59: 万元 | H59: =H41 -> 23.179586 | I59: =I41 -> 23.179586 | J59: =J41 -> 23.179586 | K59: =K41 -> 23.179586 | L59: =L41 -> 23.179586 | M59: =M41 -> 23.179586 | N59: =N41 -> 23.179586 | O59: =O41 -> 23.179586 | ... AA59: =AA41 -> 23.179586
B60: 3.2 | C60: 期末拆除费用 | D60: =SUM(F60:AA60) -> 0 | E60: 万元 | H60: 0 | I60: 0 | J60: 0 | K60: 0 | L60: 0 | M60: 0 | N60: 0 | O60: 0 | P60: 0 | Q60: 0 | R60: 0 | S60: 0 | T60: 0 | U60: 0 | V60: 0 | W60: 0 | X60: 0 | Y60: 0 | Z60: 0 | AA60: =参数输入表!H412*参数输入表!H411 -> 0
B61: 4 | C61: 研发费用现金支出 | D61: =SUM(F61:AA61) -> 0 | E61: 万元 | H61: 0 | I61: 0 | J61: 0 | K61: 0 | L61: 0 | M61: 0 | N61: 0 | O61: 0 | P61: 0 | Q61: 0 | R61: 0 | S61: 0 | T61: 0 | U61: 0 | V61: 0 | W61: 0 | X61: 0 | Y61: 0 | Z61: 0 | AA61: 0
B62: 二 | C62: 营业外现金支出 | D62: =SUM(F62:AA62) -> 0 | E62: 万元 | H62: =参数输入表!$H$682 -> 0 | I62: =参数输入表!$H$682 -> 0 | J62: =参数输入表!$H$682 -> 0 | K62: =参数输入表!$H$682 -> 0 | L62: =参数输入表!$H$682 -> 0 | M62: =参数输入表!$H$682 -> 0 | N62: =参数输入表!$H$682 -> 0 | O62: =参数输入表!$H$682 -> 0 | ... AA62: =参数输入表!$H$682 -> 0
C65: 成本表中（1）财务费用引用自“表2-还本付息表”；（2）折旧费、无形资产摊销、长期待摊费用摊销 引用自“表3-折旧摊销表”；其余数据通过参数输入表中成本费用板块相关参数计算而得。
C66: 经营成本为运营期各年不含税值
C68: 标黄部分为相对固定模块，适用于所有项目

Sheet 表4-收入税金表
B2: 收入表
B3: 序号 | C3: 项目 | D3: 合计 | E3: 单位 | F3: 建设期 | H3: 运营期
F4: 1 | G4: 2 | H4: 1 | I4: 2 | J4: 3 | K4: 4 | L4: 5 | M4: 6 | N4: 7 | O4: 8 | P4: 9 | Q4: 10 | R4: 11 | S4: 12 | T4: 13 | U4: 14 | V4: 15 | W4: 16 | X4: 17 | Y4: 18 | Z4: 19 | AA4: 20
B5: 1 | C5: 营业收入 | D5: =SUM(F5:AA5) -> 373365.74 | E5: 万元 | H5: =H6+H10 -> 25177.721 | I5: =I6+I10 -> 17630.551 | J5: =J6+J10 -> 17630.551 | K5: =K6+K10 -> 17630.551 | L5: =L6+L10 -> 17630.551 | M5: =M6+M10 -> 17630.551 | N5: =N6+N10 -> 18573.947 | O5: =O6+O10 -> 18573.947 | ... AA5: =AA6+AA10 -> 18573.947
B6: 1.1 | C6: 销售收入 | D6: =SUM(F6:AA6) -> 373365.74 | E6: 万元 | H6: =H7 -> 25177.721 | I6: =I7 -> 17630.551 | J6: =J7 -> 17630.551 | K6: =K7 -> 17630.551 | L6: =L7 -> 17630.551 | M6: =M7 -> 17630.551 | N6: =N7 -> 18573.947 | O6: =O7 -> 18573.947 | ... AA6: =AA7 -> 18573.947
B7: 1.1.1 | C7: 租赁收入 | D7: =SUM(H7:AA7) -> 373365.74 | E7: 万元 | G7: =H7*1.06 -> 26688.384 | H7: =H8+H9 -> 25177.721 | I7: =I8+I9 -> 17630.551 | J7: =J8+J9 -> 17630.551 | K7: =K8+K9 -> 17630.551 | L7: =L8+L9 -> 17630.551 | M7: =M8+M9 -> 17630.551 | N7: =N8+N9 -> 18573.947 | O7: =O8+O9 -> 18573.947 | ... AA7: =AA8+AA9 -> 18573.947
C8: 机柜租赁收入 | D8: =SUM(H8:AA8) -> 333743.09 | E8: 万元 | H8: =(参数输入表!H113*参数输入表!H114+参数输入表!H116*参数输入表!H117)/(1+参数输入表!$H$251) -> 16687.155 | I8: =(参数输入表!H120*参数输入表!H121+参数输入表!H123*参数输入表!H124)/(1+参数输入表!$H$251) -> 16687.155 | J8: =(参数输入表!H127*参数输入表!H128+参数输入表!H130*参数输入表!H131)/(1+参数输入表!$H$251) -> 16687.155 | K8: =(参数输入表!H134*参数输入表!H135+参数输入表!H137*参数输入表!H138)/(1+参数输入表!$H$251) -> 16687.155 | L8: =(参数输入表!H141*参数输入表!H142+参数输入表!H144*参数输入表!H145)/(1+参数输入表!$H$251) -> 16687.155 | M8: =(参数输入表!H148*参数输入表!H149+参数输入表!H151*参数输入表!H152)/(1+参数输入表!$H$251) -> 16687.155 | N8: =(参数输入表!H155*参数输入表!H156+参数输入表!H158*参数输入表!H159)/(1+参数输入表!$H$251) -> 16687.155 | O8: =(参数输入表!H162*参数输入表!H163+参数输入表!H165*参数输入表!H166)/(1+参数输入表!$H$251) -> 16687.155 | P8: =(参数输入表!H169*参数输入表!H170+参数输入表!H172*参数输入表!H173)/(1+参数输入表!$H$251) -> 16687.155 | Q8: =(参数输入表!H176*参数输入表!H177+参数输入表!H179*参数输入表!H180)/(1+参数输入表!$H$251) -> 16687.155 | R8: =(参数输入表!H183*参数输入表!H184+参数输入表!H186*参数输入表!H187)/(1+参数输入表!$H$251) -> 16687.155 | S8: =(参数输入表!H190*参数输入表!H191+参数输入表!H193*参数输入表!H194)/(1+参数输入表!$H$251) -> 16687.155 | T8: =(参数输入表!H197*参数输入表!H198+参数输入表!H200*参数输入表!H201)/(1+参数输入表!$H$251) -> 16687.155 | U8: =(参数输入表!H204*参数输入表!H205+参数输入表!H207*参数输入表!H208)/(1+参数输入表!$H$251) -> 16687.155 | V8: =(参数输入表!H211*参数输入表!H212+参数输入表!H214*参数输入表!H215)/(1+参数输入表!$H$251) -> 16687.155 | W8: =(参数输入表!H218*参数输入表!H219+参数输入表!H221*参数输入表!H222)/(1+参数输入表!$H$251) -> 16687.155 | X8: =(参数输入表!H225*参数输入表!H226+参数输入表!H228*参数输入表!H229)/(1+参数输入表!$H$251) -> 16687.155 | Y8: =(参数输入表!H232*参数输入表!H233+参数输入表!H235*参数输入表!H236)/(1+参数输入表!$H$251) -> 16687.155 | Z8: =(参数输入表!H239*参数输入表!H240+参数输入表!H242*参数输入表!H243)/(1+参数输入表!$H$251) -> 16687.155 | AA8: =(参数输入表!H246*参数输入表!H247+参数输入表!H249*参数输入表!H250)/(1+参数输入表!$H$251) -> 16687.155
C9: 算力租赁收入 | D9: =SUM(F9:AA9) -> 39622.642 | E9: 万元 | H9: =参数输入表!H254/(1+参数输入表!$H$293) -> 8490.566 | I9: =参数输入表!H256/(1+参数输入表!$H$293) -> 943.39623 | J9: =参数输入表!H258/(1+参数输入表!$H$293) -> 943.39623 | K9: =参数输入表!H260/(1+参数输入表!$H$293) -> 943.39623 | L9: =参数输入表!H262/(1+参数输入表!$H$293) -> 943.39623 | M9: =参数输入表!H264/(1+参数输入表!$H$293) -> 943.39623 | N9: =参数输入表!H266/(1+参数输入表!$H$293) -> 1886.7925 | O9: =参数输入表!H268/(1+参数输入表!$H$293) -> 1886.7925 | P9: =参数输入表!H270/(1+参数输入表!$H$293) -> 1886.7925 | Q9: =参数输入表!H272/(1+参数输入表!$H$293) -> 1886.7925 | R9: =参数输入表!H274/(1+参数输入表!$H$293) -> 1886.7925 | S9: =参数输入表!H276/(1+参数输入表!$H$293) -> 1886.7925 | T9: =参数输入表!H278/(1+参数输入表!$H$293) -> 1886.7925 | U9: =参数输入表!H280/(1+参数输入表!$H$293) -> 1886.7925 | V9: =参数输入表!H282/(1+参数输入表!$H$293) -> 1886.7925 | W9: =参数输入表!H284/(1+参数输入表!$H$293) -> 1886.7925 | X9: =参数输入表!H286/(1+参数输入表!$H$293) -> 1886.7925 | Y9: =参数输入表!H288/(1+参数输入表!$H$293) -> 1886.7925 | Z9: =参数输入表!H290/(1+参数输入表!$H$293) -> 1886.7925 | AA9: =参数输入表!H290/(1+参数输入表!$H$293) -> 1886.7925
B10: 2 | C10: 其他收入 | D10: =SUM(F10:AA10) -> 0 | E10: 万元 | H10: =(参数输入表!H295)/(1+参数输入表!$H$315) -> 0 | I10: =(参数输入表!H296)/(1+参数输入表!$H$315) -> 0 | J10: =(参数输入表!H297)/(1+参数输入表!$H$315) -> 0 | K10: =(参数输入表!H298)/(1+参数输入表!$H$315) -> 0 | L10: =(参数输入表!H299)/(1+参数输入表!$H$315) -> 0 | M10: =(参数输入表!H300)/(1+参数输入表!$H$315) -> 0 | N10: =(参数输入表!H301)/(1+参数输入表!$H$315) -> 0 | O10: =(参数输入表!H302)/(1+参数输入表!$H$315) -> 0 | P10: =(参数输入表!H303)/(1+参数输入表!$H$315) -> 0 | Q10: =(参数输入表!H304)/(1+参数输入表!$H$315) -> 0 | R10: =(参数输入表!H305)/(1+参数输入表!$H$315) -> 0 | S10: =(参数输入表!H306)/(1+参数输入表!$H$315) -> 0 | T10: =(参数输入表!H307)/(1+参数输入表!$H$315) -> 0 | U10: =(参数输入表!H308)/(1+参数输入表!$H$315) -> 0 | V10: =(参数输入表!H309)/(1+参数输入表!$H$315) -> 0 | W10: =(参数输入表!H310)/(1+参数输入表!$H$315) -> 0 | X10: =(参数输入表!H311)/(1+参数输入表!$H$315) -> 0 | Y10: =(参数输入表!H312)/(1+参数输入表!$H$315) -> 0 | Z10: =(参数输入表!H313)/(1+参数输入表!$H$315) -> 0 | AA10: =(参数输入表!H314)/(1+参数输入表!$H$315) -> 0
B11: 3 | C11: 营业外收入 | D11: =SUM(F11:AA11) -> 0 | E11: 万元 | H11: =SUM(H12:H13) -> 0 | I11: =SUM(I12:I13) -> 0 | J11: =SUM(J12:J13) -> 0 | K11: =SUM(K12:K13) -> 0 | L11: =SUM(L12:L13) -> 0 | M11: =SUM(M12:M13) -> 0 | N11: =SUM(N12:N13) -> 0 | O11: =SUM(O12:O13) -> 0 | ... AA11: =SUM(AA12:AA13) -> 0
B12: 3.1 | C12: 政府一次性运营补贴收入 | D12: =SUM(F12:AA12) -> 0 | E12: 万元 | H12: =参数输入表!H318 -> 0
B13: 3.2 | C13: 增值税即征即退 | D13: =SUM(F13:AA13) -> 0 | E13: 万元 | H13: =H16*参数输入表!$H$688 -> 0 | I13: =I16*参数输入表!$H$688 -> 0 | J13: =J16*参数输入表!$H$688 -> 0 | K13: =K16*参数输入表!$H$688 -> 0 | L13: =L16*参数输入表!$H$688 -> 0 | M13: =M16*参数输入表!$H$688 -> 0 | N13: =N16*参数输入表!$H$688 -> 0 | O13: =O16*参数输入表!$H$688 -> 0 | ... AA13: =AA16*参数输入表!$H$688 -> 0
B15: 税金表
B16: 1 | C16: 当期实缴增值税 | D16: =SUM(F16:AA16) -> 7094.9645 | E16: 万元 | F16: 0 | G16: =IF(G39>0,0,G38-F39) -> 0 | H16: =IF(H39>0,0,H38-G39) -> 0 | I16: =IF(I39>0,0,I38-H39) -> 0 | J16: =IF(J39>0,0,J38-I39) -> 0 | K16: =IF(K39>0,0,K38-J39) -> 0 | L16: =IF(L39>0,0,L38-K39) -> 0 | M16: =IF(M39>0,0,M38-L39) -> 0 | N16: =IF(N39>0,0,N38-M39) -> 0 | ... AA16: =IF(AA39>0,0,AA38-Z39) -> 561.03158
B17: 2 | C17: 增值税销项税 | D17: =SUM(F17:AA17) -> 22401.944 | E17: 万元 | F17: =SUM(F18:F19) -> 0 | G17: =SUM(G18:G19) -> 0 | H17: =SUM(H18:H19) -> 1510.6632 | I17: =SUM(I18:I19) -> 1057.8331 | J17: =SUM(J18:J19) -> 1057.8331 | K17: =SUM(K18:K19) -> 1057.8331 | L17: =SUM(L18:L19) -> 1057.8331 | M17: =SUM(M18:M19) -> 1057.8331 | ... AA17: =SUM(AA18:AA19) -> 1114.4368
C18: 发电收入销项税 | D18: =SUM(F18:AA18) -> 22401.944 | E18: 万元 | H18: =H6*参数输入表!$H$251 -> 1510.6632 | I18: =I6*参数输入表!$H$251 -> 1057.8331 | J18: =J6*参数输入表!$H$251 -> 1057.8331 | K18: =K6*参数输入表!$H$251 -> 1057.8331 | L18: =L6*参数输入表!$H$251 -> 1057.8331 | M18: =M6*参数输入表!$H$251 -> 1057.8331 | N18: =N6*参数输入表!$H$251 -> 1114.4368 | O18: =O6*参数输入表!$H$251 -> 1114.4368 | ... AA18: =AA6*参数输入表!$H$251 -> 1114.4368
C19: 其他收入销项税 | D19: =SUM(F19:AA19) -> 0 | E19: 万元 | H19: =H10*参数输入表!$H$315 -> 0 | I19: =I10*参数输入表!$H$315 -> 0 | J19: =J10*参数输入表!$H$315 -> 0 | K19: =K10*参数输入表!$H$315 -> 0 | L19: =L10*参数输入表!$H$315 -> 0 | M19: =M10*参数输入表!$H$315 -> 0 | N19: =N10*参数输入表!$H$315 -> 0 | O19: =O10*参数输入表!$H$315 -> 0 | ... AA19: =AA10*参数输入表!$H$315 -> 0
B20: 3 | C20: 增值税进项税 | D20: =SUM(F20:AA20) -> 15306.98 | E20: 万元 | F20: =F21+F22+F36+F37 -> 2674.206 | G20: =G21+G22+G36+G37 -> 1782.804 | H20: =H21+H22+H36+H37 -> 468.45069 | I20: =I21+I22+I36+I37 -> 467.87045 | J20: =J21+J22+J36+J37 -> 467.29187 | K20: =K21+K22+K36+K37 -> 466.71495 | L20: =L21+L22+L36+L37 -> 466.13967 | M20: =M21+M22+M36+M37 -> 573.09358 | ... AA20: =AA21+AA22+AA36+AA37 -> 553.40525
B21: 3.1 | C21: 建设投资进项税 | D21: =SUM(F21:AA21) -> 4457.01 | E21: 万元 | F21: =参数输入表!H353*参数输入表!H102 -> 2674.206 | G21: =参数输入表!H353*参数输入表!H103 -> 1782.804
B22: 3.2 | C22: 营业成本进项税 | D22: =SUM(F22:AA22) -> 10792.448 | E22: 万元 | F22: =F23+F31+F32+F35 -> 0 | G22: =G23+G31+G32+G35 -> 0 | H22: =H23+H31+H32+H35 -> 468.45069 | I22: =I23+I31+I32+I35 -> 467.87045 | J22: =J23+J31+J32+J35 -> 467.29187 | K22: =K23+K31+K32+K35 -> 466.71495 | L22: =L23+L31+L32+L35 -> 466.13967 | M22: =M23+M31+M32+M35 -> 573.09358 | ... AA22: =AA23+AA31+AA32+AA35 -> 553.40525
B23: 3.2.1 | C23: 生产成本进项税 | D23: =SUM(F23:AA23) -> 10792.448 | E23: 万元 | H23: =SUM(H24:H30) -> 468.45069 | I23: =SUM(I24:I30) -> 467.87045 | J23: =SUM(J24:J30) -> 467.29187 | K23: =SUM(K24:K30) -> 466.71495 | L23: =SUM(L24:L30) -> 466.13967 | M23: =SUM(M24:M30) -> 573.09358 | N23: =SUM(N24:N30) -> 571.40341 | O23: =SUM(O24:O30) -> 569.7193 | ... AA23: =SUM(AA24:AA30) -> 553.40525
C24: 材料费 | D24: =SUM(F24:AA24) -> 0 | E24: 万元 | H24: ='表3-成本费用表'!H50*参数输入表!$H$378 -> 0 | I24: ='表3-成本费用表'!I50*参数输入表!$H$378 -> 0 | J24: ='表3-成本费用表'!J50*参数输入表!$H$378 -> 0 | K24: ='表3-成本费用表'!K50*参数输入表!$H$378 -> 0 | L24: ='表3-成本费用表'!L50*参数输入表!$H$378 -> 0 | M24: ='表3-成本费用表'!M50*参数输入表!$H$378 -> 0 | N24: ='表3-成本费用表'!N50*参数输入表!$H$378 -> 0 | O24: ='表3-成本费用表'!O50*参数输入表!$H$378 -> 0 | ... AA24: ='表3-成本费用表'!AA50*参数输入表!$H$378 -> 0
C25: 维修费 | D25: =SUM(F25:AA25) -> 0 | E25: 万元 | H25: ='表3-成本费用表'!H51*参数输入表!$H$386 -> 0 | I25: ='表3-成本费用表'!I51/(1+参数输入表!$H$386)*参数输入表!$H$386 -> 0 | J25: ='表3-成本费用表'!J51/(1+参数输入表!$H$386)*参数输入表!$H$386 -> 0 | K25: ='表3-成本费用表'!K51/(1+参数输入表!$H$386)*参数输入表!$H$386 -> 0 | L25: ='表3-成本费用表'!L51/(1+参数输入表!$H$386)*参数输入表!$H$386 -> 0 | M25: ='表3-成本费用表'!M51/(1+参数输入表!$H$386)*参数输入表!$H$386 -> 0 | N25: ='表3-成本费用表'!N51/(1+参数输入表!$H$386)*参数输入表!$H$386 -> 0 | O25: ='表3-成本费用表'!O51/(1+参数输入表!$H$386)*参数输入表!$H$386 -> 0 | P25: ='表3-成本费用表'!P51/(1+参数输入表!$H$386)*参数输入表!$H$386 -> 0 | ... AA25: ='表3-成本费用表'!AA51/(1+参数输入表!$H$386)*参数输入表!$H$386 -> 0
C26: 生产人员薪酬及福利 | D26: =SUM(F26:AA26) -> 0 | E26: 万元 | H26: ='表3-成本费用表'!H52*参数输入表!$H$404 -> 0 | I26: ='表3-成本费用表'!I52/(1+参数输入表!$H$404)*参数输入表!$H$404 -> 0 | J26: ='表3-成本费用表'!J52/(1+参数输入表!$H$404)*参数输入表!$H$404 -> 0 | K26: ='表3-成本费用表'!K52/(1+参数输入表!$H$404)*参数输入表!$H$404 -> 0 | L26: ='表3-成本费用表'!L52/(1+参数输入表!$H$404)*参数输入表!$H$404 -> 0 | M26: ='表3-成本费用表'!M52/(1+参数输入表!$H$404)*参数输入表!$H$404 -> 0 | N26: ='表3-成本费用表'!N52/(1+参数输入表!$H$404)*参数输入表!$H$404 -> 0 | O26: ='表3-成本费用表'!O52/(1+参数输入表!$H$404)*参数输入表!$H$404 -> 0 | P26: ='表3-成本费用表'!P52/(1+参数输入表!$H$404)*参数输入表!$H$404 -> 0 | ... AA26: ='表3-成本费用表'!AA52/(1+参数输入表!$H$404)*参数输入表!$H$404 -> 0
C27: 其他费用 | D27: =SUM(F27:AA27) -> 0 | E27: 万元 | H27: ='表3-成本费用表'!H54*参数输入表!$H$406 -> 0 | I27: ='表3-成本费用表'!I54/(1+参数输入表!$H$406)*参数输入表!$H$406 -> 0 | J27: ='表3-成本费用表'!J54/(1+参数输入表!$H$406)*参数输入表!$H$406 -> 0 | K27: ='表3-成本费用表'!K54/(1+参数输入表!$H$406)*参数输入表!$H$406 -> 0 | L27: ='表3-成本费用表'!L54/(1+参数输入表!$H$406)*参数输入表!$H$406 -> 0 | M27: ='表3-成本费用表'!M54/(1+参数输入表!$H$406)*参数输入表!$H$406 -> 0 | N27: ='表3-成本费用表'!N54/(1+参数输入表!$H$406)*参数输入表!$H$406 -> 0 | O27: ='表3-成本费用表'!O54/(1+参数输入表!$H$406)*参数输入表!$H$406 -> 0 | P27: ='表3-成本费用表'!P54/(1+参数输入表!$H$406)*参数输入表!$H$406 -> 0 | ... AA27: ='表3-成本费用表'!AA54/(1+参数输入表!$H$406)*参数输入表!$H$406 -> 0
C28: 下网电费 | D28: =SUM(F28:AA28) -> 10792.448 | E28: 万元 | H28: ='表3-成本费用表'!H13*参数输入表!$H$617 -> 468.45069 | I28: ='表3-成本费用表'!I13*参数输入表!$H$617 -> 467.87045 | J28: ='表3-成本费用表'!J13*参数输入表!$H$617 -> 467.29187 | K28: ='表3-成本费用表'!K13*参数输入表!$H$617 -> 466.71495 | L28: ='表3-成本费用表'!L13*参数输入表!$H$617 -> 466.13967 | M28: ='表3-成本费用表'!M13*参数输入表!$H$617 -> 573.09358 | N28: ='表3-成本费用表'!N13*参数输入表!$H$617 -> 571.40341 | O28: ='表3-成本费用表'!O13*参数输入表!$H$617 -> 569.7193 | ... AA28: ='表3-成本费用表'!AA13*参数输入表!$H$617 -> 553.40525
C29: 场地租金费用 | D29: =SUM(F29:AA29) -> 0 | E29: 万元 | H29: ='表3-成本费用表'!H56/(1+参数输入表!$H$409)*参数输入表!$H$409 -> 0 | I29: ='表3-成本费用表'!I56/(1+参数输入表!$H$409)*参数输入表!$H$409 -> 0 | J29: ='表3-成本费用表'!J56/(1+参数输入表!$H$409)*参数输入表!$H$409 -> 0 | K29: ='表3-成本费用表'!K56/(1+参数输入表!$H$409)*参数输入表!$H$409 -> 0 | L29: ='表3-成本费用表'!L56/(1+参数输入表!$H$409)*参数输入表!$H$409 -> 0 | M29: ='表3-成本费用表'!M56/(1+参数输入表!$H$409)*参数输入表!$H$409 -> 0 | N29: ='表3-成本费用表'!N56/(1+参数输入表!$H$409)*参数输入表!$H$409 -> 0 | O29: ='表3-成本费用表'!O56/(1+参数输入表!$H$409)*参数输入表!$H$409 -> 0 | ... AA29: ='表3-成本费用表'!AA56/(1+参数输入表!$H$409)*参数输入表!$H$409 -> 0
C30: 计入长期待摊成本项 | D30: =SUM(F30:AA30) -> 0 | E30: 万元 | H30: ='表3-成本费用表'!H53/(1+参数输入表!$H$653)*参数输入表!$H$653 -> 0 | I30: ='表3-成本费用表'!I53/(1+参数输入表!$H$653)*参数输入表!$H$653 -> 0 | J30: ='表3-成本费用表'!J53/(1+参数输入表!$H$653)*参数输入表!$H$653 -> 0 | K30: ='表3-成本费用表'!K53/(1+参数输入表!$H$653)*参数输入表!$H$653 -> 0 | L30: ='表3-成本费用表'!L53/(1+参数输入表!$H$653)*参数输入表!$H$653 -> 0 | M30: ='表3-成本费用表'!M53/(1+参数输入表!$H$653)*参数输入表!$H$653 -> 0 | N30: ='表3-成本费用表'!N53/(1+参数输入表!$H$653)*参数输入表!$H$653 -> 0 | O30: ='表3-成本费用表'!O53/(1+参数输入表!$H$653)*参数输入表!$H$653 -> 0 | ... AA30: ='表3-成本费用表'!AA53/(1+参数输入表!$H$653)*参数输入表!$H$653 -> 0
B31: 3.2.2 | C31: 销售费用进项税 | D31: =SUM(F31:AA31) -> 0 | E31: 万元 | H31: 0 | I31: 0 | J31: 0 | K31: 0 | L31: 0 | M31: 0 | N31: 0 | O31: 0 | P31: 0 | Q31: 0 | R31: 0 | S31: 0 | T31: 0 | U31: 0 | V31: 0 | W31: 0 | X31: 0 | Y31: 0 | Z31: 0 | AA31: 0
B32: 3.2.3 | C32: 管理费用进项税 | D32: =SUM(F32:AA32) -> 0 | E32: 万元 | H32: =SUM(H33:H34) -> 0 | I32: =SUM(I33:I34) -> 0 | J32: =SUM(J33:J34) -> 0 | K32: =SUM(K33:K34) -> 0 | L32: =SUM(L33:L34) -> 0 | M32: =SUM(M33:M34) -> 0 | N32: =SUM(N33:N34) -> 0 | O32: =SUM(O33:O34) -> 0 | ... AA32: =SUM(AA33:AA34) -> 0
C33: 保险费 | D33: =SUM(F33:AA33) -> 0 | E33: 万元 | H33: ='表3-成本费用表'!H17*参数输入表!$H$394 -> 0 | I33: ='表3-成本费用表'!I17*参数输入表!$H$394 -> 0 | J33: ='表3-成本费用表'!J17*参数输入表!$H$394 -> 0 | K33: ='表3-成本费用表'!K17*参数输入表!$H$394 -> 0 | L33: ='表3-成本费用表'!L17*参数输入表!$H$394 -> 0 | M33: ='表3-成本费用表'!M17*参数输入表!$H$394 -> 0 | N33: ='表3-成本费用表'!N17*参数输入表!$H$394 -> 0 | O33: ='表3-成本费用表'!O17*参数输入表!$H$394 -> 0 | ... AA33: ='表3-成本费用表'!AA17*参数输入表!$H$394 -> 0
C34: 期末拆除费用 | D34: =SUM(F34:AA34) -> 0 | E34: 万元 | H34: ='表3-成本费用表'!H18*参数输入表!$H$413 -> 0 | I34: ='表3-成本费用表'!I18*参数输入表!$H$413 -> 0 | J34: ='表3-成本费用表'!J18*参数输入表!$H$413 -> 0 | K34: ='表3-成本费用表'!K18*参数输入表!$H$413 -> 0 | L34: ='表3-成本费用表'!L18*参数输入表!$H$413 -> 0 | M34: ='表3-成本费用表'!M18*参数输入表!$H$413 -> 0 | N34: ='表3-成本费用表'!N18*参数输入表!$H$413 -> 0 | O34: ='表3-成本费用表'!O18*参数输入表!$H$413 -> 0 | ... AA34: ='表3-成本费用表'!AA18*参数输入表!$H$413 -> 0
B35: 3.2.4 | C35: 研发费用进项税 | D35: =SUM(F35:AA35) -> 0 | E35: 万元 | H35: 0 | I35: 0 | J35: 0 | K35: 0 | L35: 0 | M35: 0 | N35: 0 | O35: 0 | P35: 0 | Q35: 0 | R35: 0 | S35: 0 | T35: 0 | U35: 0 | V35: 0 | W35: 0 | X35: 0 | Y35: 0 | Z35: 0 | AA35: 0
B36: 3.3 | C36: 营业外支出进项税 | D36: =SUM(F36:AA36) -> 0 | E36: 万元 | H36: ='表3-成本费用表'!H62*参数输入表!$H$686 -> 0 | I36: ='表3-成本费用表'!I62*参数输入表!$H$686 -> 0 | J36: ='表3-成本费用表'!J62*参数输入表!$H$686 -> 0 | K36: ='表3-成本费用表'!K62*参数输入表!$H$686 -> 0 | L36: ='表3-成本费用表'!L62*参数输入表!$H$686 -> 0 | M36: ='表3-成本费用表'!M62*参数输入表!$H$686 -> 0 | N36: ='表3-成本费用表'!N62*参数输入表!$H$686 -> 0 | O36: ='表3-成本费用表'!O62*参数输入表!$H$686 -> 0 | ... AA36: ='表3-成本费用表'!AA62*参数输入表!$H$686 -> 0
B37: 3.4 | C37: 大修及更新重置进项税 | D37: =SUM(F37:AA37) -> 57.522124 | E37: 万元 | H37: =参数输入表!H656/(1+参数输入表!$H$679)*参数输入表!$H$679 -> 0 | I37: =参数输入表!H657/(1+参数输入表!$H$679)*参数输入表!$H$679 -> 0 | J37: =参数输入表!H658/(1+参数输入表!$H$679)*参数输入表!$H$679 -> 0 | K37: =参数输入表!H659/(1+参数输入表!$H$679)*参数输入表!$H$679 -> 0 | L37: =参数输入表!H660/(1+参数输入表!$H$679)*参数输入表!$H$679 -> 0 | M37: =参数输入表!H661/(1+参数输入表!$H$679)*参数输入表!$H$679 -> 0 | N37: =参数输入表!H662/(1+参数输入表!$H$679)*参数输入表!$H$679 -> 0 | O37: =参数输入表!H663/(1+参数输入表!$H$679)*参数输入表!$H$679 -> 0 | P37: =参数输入表!H664/(1+参数输入表!$H$679)*参数输入表!$H$679 -> 0 | Q37: =参数输入表!H665/(1+参数输入表!$H$679)*参数输入表!$H$679 -> 0 | R37: =参数输入表!H666/(1+参数输入表!$H$679)*参数输入表!$H$679 -> 0 | S37: =参数输入表!H667/(1+参数输入表!$H$679)*参数输入表!$H$679 -> 57.522124 | T37: =参数输入表!H668/(1+参数输入表!$H$679)*参数输入表!$H$679 -> 0 | U37: =参数输入表!H669/(1+参数输入表!$H$679)*参数输入表!$H$679 -> 0 | V37: =参数输入表!H670/(1+参数输入表!$H$679)*参数输入表!$H$679 -> 0 | W37: =参数输入表!H671/(1+参数输入表!$H$679)*参数输入表!$H$679 -> 0 | X37: =参数输入表!H672/(1+参数输入表!$H$679)*参数输入表!$H$679 -> 0 | Y37: =参数输入表!H673/(1+参数输入表!$H$679)*参数输入表!$H$679 -> 0 | Z37: =参数输入表!H674/(1+参数输入表!$H$679)*参数输入表!$H$679 -> 0 | AA37: =参数输入表!H675/(1+参数输入表!$H$679)*参数输入表!$H$679 -> 0
B38: 4 | C38: 销项税-进项税 | D38: =SUM(F38:AA38) -> 7094.9645 | E38: 万元 | F38: =F17-F20 -> -2674.206 | G38: =G17-G20 -> -1782.804 | H38: =H17-H20 -> 1042.2126 | I38: =I17-I20 -> 589.96261 | J38: =J17-J20 -> 590.54118 | K38: =K17-K20 -> 591.11811 | L38: =L17-L20 -> 591.69339 | M38: =M17-M20 -> 484.73947 | ... AA38: =AA17-AA20 -> 561.03158
B39: 5 | C39: 期末可抵扣进项税余额 | E39: 万元 | F39: =IF(F38<0,-F38,0) -> 2674.206 | G39: =IF(F39-G38>0,F39-G38,0) -> 4457.01 | H39: =IF(F39-H38>0,G39-H38,0) -> 3414.7974 | I39: =IF(H39-I38>0,H39-I38,0) -> 2824.8348 | J39: =IF(I39-J38>0,I39-J38,0) -> 2234.2936 | K39: =IF(J39-K38>0,J39-K38,0) -> 1643.1755 | L39: =IF(K39-L38>0,K39-L38,0) -> 1051.4822 | M39: =IF(L39-M38>0,L39-M38,0) -> 566.74268 | N39: =IF(M39-N38>0,M39-N38,0) -> 23.709258 | O39: =IF(N39-O38>0,N39-O38,0) -> 0 | P39: =IF(O39-P38>0,O39-P38,0) -> 0 | ... AA39: =IF(Z39-AA38>0,Z39-AA38,0) -> 0
B40: 6 | C40: 增值税附加税 | D40: =SUM(F40:AA40) -> 709.49645 | E40: 万元 | H40: =SUM(H41:H43) -> 0 | I40: =SUM(I41:I43) -> 0 | J40: =SUM(J41:J43) -> 0 | K40: =SUM(K41:K43) -> 0 | L40: =SUM(L41:L43) -> 0 | M40: =SUM(M41:M43) -> 0 | N40: =SUM(N41:N43) -> 0 | O40: =SUM(O41:O43) -> 52.100828 | ... AA40: =SUM(AA41:AA43) -> 56.103158
B41: 6.1 | C41: 城市维护建设税 | D41: =SUM(F41:AA41) -> 354.74823 | E41: 万元 | H41: =H16*参数输入表!$H$695 -> 0 | I41: =I16*参数输入表!$H$695 -> 0 | J41: =J16*参数输入表!$H$695 -> 0 | K41: =K16*参数输入表!$H$695 -> 0 | L41: =L16*参数输入表!$H$695 -> 0 | M41: =M16*参数输入表!$H$695 -> 0 | N41: =N16*参数输入表!$H$695 -> 0 | O41: =O16*参数输入表!$H$695 -> 26.050414 | ... AA41: =AA16*参数输入表!$H$695 -> 28.051579
B42: 6.2 | C42: 教育附加 | D42: =SUM(F42:AA42) -> 212.84894 | E42: 万元 | H42: =H16*参数输入表!$H$698 -> 0 | I42: =I16*参数输入表!$H$698 -> 0 | J42: =J16*参数输入表!$H$698 -> 0 | K42: =K16*参数输入表!$H$698 -> 0 | L42: =L16*参数输入表!$H$698 -> 0 | M42: =M16*参数输入表!$H$698 -> 0 | N42: =N16*参数输入表!$H$698 -> 0 | O42: =O16*参数输入表!$H$698 -> 15.630248 | ... AA42: =AA16*参数输入表!$H$698 -> 16.830947
B43: 6.3 | C43: 地方教育附加 | D43: =SUM(F43:AA43) -> 141.89929 | E43: 万元 | H43: =H16*参数输入表!$H$699 -> 0 | I43: =I16*参数输入表!$H$699 -> 0 | J43: =J16*参数输入表!$H$699 -> 0 | K43: =K16*参数输入表!$H$699 -> 0 | L43: =L16*参数输入表!$H$699 -> 0 | M43: =M16*参数输入表!$H$699 -> 0 | N43: =N16*参数输入表!$H$699 -> 0 | O43: =O16*参数输入表!$H$699 -> 10.420166 | ... AA43: =AA16*参数输入表!$H$699 -> 11.220632
B44: 7 | C44: 城镇土地使用税 | D44: =SUM(F44:AA44) -> 0 | E44: 万元 | H44: =参数输入表!$H$701*参数输入表!$H$702/10000 -> 0 | I44: =参数输入表!$H$701*参数输入表!$H$702/10000 -> 0 | J44: =参数输入表!$H$701*参数输入表!$H$702/10000 -> 0 | K44: =参数输入表!$H$701*参数输入表!$H$702/10000 -> 0 | L44: =参数输入表!$H$701*参数输入表!$H$702/10000 -> 0 | M44: =参数输入表!$H$701*参数输入表!$H$702/10000 -> 0 | N44: =参数输入表!$H$701*参数输入表!$H$702/10000 -> 0 | O44: =参数输入表!$H$701*参数输入表!$H$702/10000 -> 0 | ... AA44: =参数输入表!$H$701*参数输入表!$H$702/10000 -> 0
C47: 增值税即征即退为参数输入表，税金板块可选条件参数，若选择为常规，即没有增值税即征即退优惠，退税比例为0%；若选择即征即退，同步输入即征即退的比例，第n年增值税即征即退金额=第n年当期实缴增值税*退税比例
C48: 标黄部分为相对固定模块，适用于所有项目
C49: 标蓝部分为计算中间过程，可不展示
B50: 流动资金估算表
B51: 序号 | C51: 项目 | D51: 合计 | E51: 单位 | F51: 建设期 | H51: 运营期
F52: 1 | G52: 2 | H52: 1 | I52: 2 | J52: 3 | K52: 4 | L52: 5 | M52: 6 | N52: 7 | O52: 8 | P52: 9 | Q52: 10 | R52: 11 | S52: 12 | T52: 13 | U52: 14 | V52: 15 | W52: 16 | X52: 17 | Y52: 18 | Z52: 19 | AA52: 20
B53: 一 | C53: 流动资产 | E53: 万元 | F53: =SUM(F54:F57) -> 0 | G53: =SUM(G54:G57) -> 0 | H53: =SUM(H54:H57) -> 0 | I53: =SUM(I54:I57) -> 0 | J53: =SUM(J54:J57) -> 0 | K53: =SUM(K54:K57) -> 0 | L53: =SUM(L54:L57) -> 0 | M53: =SUM(M54:M57) -> 0 | ... AA53: =SUM(AA54:AA57) -> 0
B54: 1.1 | C54: 应收账款 | E54: 万元 | H54: =('表4-收入税金表'!H6+'表4-收入税金表'!H18)*(1-100%)+('表4-收入税金表'!H10+'表4-收入税金表'!H19)*(1-100%) -> 0 | I54: =('表4-收入税金表'!I6+'表4-收入税金表'!I18)*(1-100%)+('表4-收入税金表'!I10+'表4-收入税金表'!I19)*(1-100%) -> 0 | J54: =('表4-收入税金表'!J6+'表4-收入税金表'!J18)*(1-100%)+('表4-收入税金表'!J10+'表4-收入税金表'!J19)*(1-100%) -> 0 | K54: =('表4-收入税金表'!K6+'表4-收入税金表'!K18)*(1-100%)+('表4-收入税金表'!K10+'表4-收入税金表'!K19)*(1-100%) -> 0 | L54: =('表4-收入税金表'!L6+'表4-收入税金表'!L18)*(1-100%)+('表4-收入税金表'!L10+'表4-收入税金表'!L19)*(1-100%) -> 0 | M54: =('表4-收入税金表'!M6+'表4-收入税金表'!M18)*(1-100%)+('表4-收入税金表'!M10+'表4-收入税金表'!M19)*(1-100%) -> 0 | N54: =('表4-收入税金表'!N6+'表4-收入税金表'!N18)*(1-100%)+('表4-收入税金表'!N10+'表4-收入税金表'!N19)*(1-100%) -> 0 | O54: =('表4-收入税金表'!O6+'表4-收入税金表'!O18)*(1-100%)+('表4-收入税金表'!O10+'表4-收入税金表'!O19)*(1-100%) -> 0 | ... AA54: =('表4-收入税金表'!AA6+'表4-收入税金表'!AA18)*(1-100%)+('表4-收入税金表'!AA10+'表4-收入税金表'!AA19)*(1-100%) -> 0
B55: 1.2 | C55: 存货 | E55: 万元
B56: 1.3 | C56: 现金 | E56: 万元
B57: 1.4 | C57: 预付账款 | E57: 万元
B58: 二 | C58: 流动负债 | E58: 万元 | F58: =SUM(F59:F60) -> 0 | G58: =SUM(G59:G60) -> 0 | H58: =SUM(H59:H60) -> 0 | I58: =SUM(I59:I60) -> 0 | J58: =SUM(J59:J60) -> 0 | K58: =SUM(K59:K60) -> 0 | L58: =SUM(L59:L60) -> 0 | M58: =SUM(M59:M60) -> 0 | ... AA58: =SUM(AA59:AA60) -> 0
B59: 2.1 | C59: 应付账款 | E59: 万元
B60: 2.2 | C60: 预收账款 | E60: 万元
B61: 三 | C61: 流动资金 | E61: 万元 | F61: =F53-F58 -> 0 | G61: =G53-G58 -> 0 | H61: =H53-H58 -> 0 | I61: =I53-I58 -> 0 | J61: =J53-J58 -> 0 | K61: =K53-K58 -> 0 | L61: =L53-L58 -> 0 | M61: =M53-M58 -> 0 | ... AA61: =AA53-AA58 -> 0
B62: 四 | C62: 流动资金当期增加额 | E62: 万元 | F62: =F61 -> 0 | G62: =G61-F61 -> 0 | H62: =H61-G61 -> 0 | I62: =I61-H61 -> 0 | J62: =J61-I61 -> 0 | K62: =K61-J61 -> 0 | L62: =L61-K61 -> 0 | M62: =M61-L61 -> 0 | N62: =N61-M61 -> 0 | ... AA62: =AA61-Z61 -> 0
C64: 流动资金估算表用于计算某一项收入当年利润表确认收入与现金流量表中实际到账收入有差额时，差额计入应收账款中。
C65: 关联至参数表中应发收入与实发收入不完全相等的收入项，本模型中为“发电补贴”

Sheet 表5-利润表-资本金
B2: 利润表-资本金
B3: 序号 | C3: 项目 | D3: 合计 | E3: 单位 | F3: 建设期 | H3: 运营期
F4: 1 | G4: 2 | H4: 1 | I4: 2 | J4: 3 | K4: 4 | L4: 5 | M4: 6 | N4: 7 | O4: 8 | P4: 9 | Q4: 10 | R4: 11 | S4: 12 | T4: 13 | U4: 14 | V4: 15 | W4: 16 | X4: 17 | Y4: 18 | Z4: 19 | AA4: 20
B5: 1 | C5: 营业总收入 | D5: =SUM(F5:AA5) -> 373365.74 | E5: 万元 | H5: =H6+H7 -> 25177.721 | I5: =I6+I7 -> 17630.551 | J5: =J6+J7 -> 17630.551 | K5: =K6+K7 -> 17630.551 | L5: =L6+L7 -> 17630.551 | M5: =M6+M7 -> 17630.551 | N5: =N6+N7 -> 18573.947 | O5: =O6+O7 -> 18573.947 | ... AA5: =AA6+AA7 -> 18573.947
B6: 1.1 | C6: 营业收入 | D6: =SUM(F6:AA6) -> 373365.74 | E6: 万元 | H6: ='表4-收入税金表'!H6 -> 25177.721 | I6: ='表4-收入税金表'!I6 -> 17630.551 | J6: ='表4-收入税金表'!J6 -> 17630.551 | K6: ='表4-收入税金表'!K6 -> 17630.551 | L6: ='表4-收入税金表'!L6 -> 17630.551 | M6: ='表4-收入税金表'!M6 -> 17630.551 | N6: ='表4-收入税金表'!N6 -> 18573.947 | O6: ='表4-收入税金表'!O6 -> 18573.947 | ... AA6: ='表4-收入税金表'!AA6 -> 18573.947
B7: 1.2 | C7: 其他收入 | D7: =SUM(F7:AA7) -> 0 | E7: 万元 | H7: ='表4-收入税金表'!H10 -> 0 | I7: ='表4-收入税金表'!I10 -> 0 | J7: ='表4-收入税金表'!J10 -> 0 | K7: ='表4-收入税金表'!K10 -> 0 | L7: ='表4-收入税金表'!L10 -> 0 | M7: ='表4-收入税金表'!M10 -> 0 | N7: ='表4-收入税金表'!N10 -> 0 | O7: ='表4-收入税金表'!O10 -> 0 | ... AA7: ='表4-收入税金表'!AA10 -> 0
B8: 2 | C8: 营业总成本 | D8: =SUM(F8:AA8) -> 335351.07 | E8: 万元 | H8: ='表3-成本费用表'!H5 -> 18348.333 | I8: ='表3-成本费用表'!I49-'表3-成本费用表'!I53+'表3-成本费用表'!I15+'表3-成本费用表'!I16+'表3-成本费用表'!I19+'表3-成本费用表'!I20+'表2-折旧摊销表'!I52 -> 18218.572 | J8: ='表3-成本费用表'!J49-'表3-成本费用表'!J53+'表3-成本费用表'!J15+'表3-成本费用表'!J16+'表3-成本费用表'!J19+'表3-成本费用表'!J20+'表2-折旧摊销表'!J52 -> 18088.823 | K8: ='表3-成本费用表'!K49-'表3-成本费用表'!K53+'表3-成本费用表'!K15+'表3-成本费用表'!K16+'表3-成本费用表'!K19+'表3-成本费用表'!K20+'表2-折旧摊销表'!K52 -> 17959.087 | L8: ='表3-成本费用表'!L49-'表3-成本费用表'!L53+'表3-成本费用表'!L15+'表3-成本费用表'!L16+'表3-成本费用表'!L19+'表3-成本费用表'!L20+'表2-折旧摊销表'!L52 -> 17829.363 | M8: ='表3-成本费用表'!M49-'表3-成本费用表'!M53+'表3-成本费用表'!M15+'表3-成本费用表'!M16+'表3-成本费用表'!M19+'表3-成本费用表'!M20+'表2-折旧摊销表'!M52 -> 18526.787 | N8: ='表3-成本费用表'!N49-'表3-成本费用表'!N53+'表3-成本费用表'!N15+'表3-成本费用表'!N16+'表3-成本费用表'!N19+'表3-成本费用表'!N20+'表2-折旧摊销表'!N52 -> 18388.487 | O8: ='表3-成本费用表'!O49-'表3-成本费用表'!O53+'表3-成本费用表'!O15+'表3-成本费用表'!O16+'表3-成本费用表'!O19+'表3-成本费用表'!O20+'表2-折旧摊销表'!O52 -> 18250.234 | P8: ='表3-成本费用表'!P49-'表3-成本费用表'!P53+'表3-成本费用表'!P15+'表3-成本费用表'!P16+'表3-成本费用表'!P19+'表3-成本费用表'!P20+'表2-折旧摊销表'!P52 -> 18112.028 | ... AA8: ='表3-成本费用表'!AA49-'表3-成本费用表'!AA53+'表3-成本费用表'!AA15+'表3-成本费用表'!AA16+'表3-成本费用表'!AA19+'表3-成本费用表'!AA20+'表2-折旧摊销表'!AA52 -> 13942.513
B9: 3 | C9: 营业税金及附加 | D9: =SUM(F9:AA9) -> 709.49645 | E9: 万元 | H9: ='表4-收入税金表'!H40+'表4-收入税金表'!H44 -> 0 | I9: ='表4-收入税金表'!I40+'表4-收入税金表'!I44 -> 0 | J9: ='表4-收入税金表'!J40+'表4-收入税金表'!J44 -> 0 | K9: ='表4-收入税金表'!K40+'表4-收入税金表'!K44 -> 0 | L9: ='表4-收入税金表'!L40+'表4-收入税金表'!L44 -> 0 | M9: ='表4-收入税金表'!M40+'表4-收入税金表'!M44 -> 0 | N9: ='表4-收入税金表'!N40+'表4-收入税金表'!N44 -> 0 | O9: ='表4-收入税金表'!O40+'表4-收入税金表'!O44 -> 52.100828 | ... AA9: ='表4-收入税金表'!AA40+'表4-收入税金表'!AA44 -> 56.103158
B10: 4 | C10: 营业外收入 | D10: =SUM(F10:AA10) -> 0 | E10: 万元 | H10: =SUM(H11:H12) -> 0 | I10: =SUM(I11:I12) -> 0 | J10: =SUM(J11:J12) -> 0 | K10: =SUM(K11:K12) -> 0 | L10: =SUM(L11:L12) -> 0 | M10: =SUM(M11:M12) -> 0 | N10: =SUM(N11:N12) -> 0 | O10: =SUM(O11:O12) -> 0 | ... AA10: =SUM(AA11:AA12) -> 0
B11: 4.1 | C11: 政府一次性运营补贴收入—递延收益 | D11: =SUM(F11:AA11) -> 0 | E11: 万元 | H11: =参数输入表!H320 -> 0 | I11: =参数输入表!H321 -> 0 | J11: =参数输入表!H322 -> 0 | K11: =参数输入表!H323 -> 0 | L11: =参数输入表!H324 -> 0 | M11: =参数输入表!H325 -> 0 | N11: =参数输入表!H326 -> 0 | O11: =参数输入表!H327 -> 0 | P11: =参数输入表!H328 -> 0 | Q11: =参数输入表!H329 -> 0 | R11: =参数输入表!H330 -> 0 | S11: =参数输入表!H331 -> 0 | T11: =参数输入表!H332 -> 0 | U11: =参数输入表!H333 -> 0 | V11: =参数输入表!H334 -> 0 | W11: =参数输入表!H335 -> 0 | X11: =参数输入表!H336 -> 0 | Y11: =参数输入表!H337 -> 0 | Z11: =参数输入表!H338 -> 0 | AA11: =参数输入表!H339 -> 0
B12: 4.2 | C12: 增值税即征即退收入 | D12: =SUM(F12:AA12) -> 0 | E12: 万元 | H12: ='表4-收入税金表'!H13 -> 0 | I12: ='表4-收入税金表'!I13 -> 0 | J12: ='表4-收入税金表'!J13 -> 0 | K12: ='表4-收入税金表'!K13 -> 0 | L12: ='表4-收入税金表'!L13 -> 0 | M12: ='表4-收入税金表'!M13 -> 0 | N12: ='表4-收入税金表'!N13 -> 0 | O12: ='表4-收入税金表'!O13 -> 0 | ... AA12: ='表4-收入税金表'!AA13 -> 0
B13: 5 | C13: 营业外支出 | D13: =SUM(F13:AA13) -> 0 | E13: 万元 | H13: ='表3-成本费用表'!H24 -> 0 | I13: ='表3-成本费用表'!I24 -> 0 | J13: ='表3-成本费用表'!J24 -> 0 | K13: ='表3-成本费用表'!K24 -> 0 | L13: ='表3-成本费用表'!L24 -> 0 | M13: ='表3-成本费用表'!M24 -> 0 | N13: ='表3-成本费用表'!N24 -> 0 | O13: ='表3-成本费用表'!O24 -> 0 | ... AA13: ='表3-成本费用表'!AA24 -> 0
B14: 6 | C14: 利润总额（1+4-2-3-5） | D14: =SUM(F14:AA14) -> 37305.167 | E14: 万元 | H14: =H5+H10-H8-H9-H13 -> 6829.3875 | I14: =I5+I10-I8-I9-I13 -> -588.02062 | J14: =J5+J10-J8-J9-J13 -> -458.27173 | K14: =K5+K10-K8-K9-K13 -> -328.53556 | L14: =L5+L10-L8-L9-L13 -> -198.81204 | M14: =M5+M10-M8-M9-M13 -> -896.23614 | N14: =N5+N10-N8-N9-N13 -> 185.45973 | O14: =O5+O10-O8-O9-O13 -> 271.61192 | ... AA14: =AA5+AA10-AA8-AA9-AA13 -> 4575.3311
B15: 7 | C15: 弥补以前年度亏损 | D15: =SUM(F15:AA15) -> 1880.6554 | E15: 万元 | H15: =SUM(H16:H20) -> 0 | I15: =SUM(I16:I20) -> 0 | J15: =SUM(J16:J20) -> 0 | K15: =SUM(K16:K20) -> 0 | L15: =SUM(L16:L20) -> 0 | M15: =SUM(M16:M20) -> 0 | N15: =SUM(N16:N20) -> 185.45973 | O15: =SUM(O16:O20) -> 271.61192 | ... AA15: =SUM(AA16:AA20) -> 0
C16: 弥补前序第一年亏损 | E16: 万元 | I16: =IF(H14>0,0,IF(I14<0,0,MIN(I14-SUM(I17:I20),-H14))) -> 0 | J16: =IF(I14>0,0,IF(J14<0,0,MIN(J14-SUM(J17:J20),-I14))) -> 0 | K16: =IF(J14>0,0,IF(K14<0,0,MIN(K14-SUM(K17:K20),-J14))) -> 0 | L16: =IF(K14>0,0,IF(L14<0,0,MIN(L14-SUM(L17:L20),-K14))) -> 0 | M16: =IF(L14>0,0,IF(M14<0,0,MIN(M14-SUM(M17:M20),-L14))) -> 0 | N16: =IF(M14>0,0,IF(N14<0,0,MIN(N14-SUM(N17:N20),-M14))) -> 0 | O16: =IF(N14>0,0,IF(O14<0,0,MIN(O14-SUM(O17:O20),-N14))) -> 0 | P16: =IF(O14>0,0,IF(P14<0,0,MIN(P14-SUM(P17:P20),-O14))) -> 0 | ... AA16: =IF(Z14>0,0,IF(AA14<0,0,MIN(AA14-SUM(AA17:AA20),-Z14))) -> 0
C17: 弥补前序第二年亏损 | E17: 万元 | J17: =IF(H14>0,0,IF(J14<0,0,MIN(J14-SUM(J18:J20),-H14-I16))) -> 0 | K17: =IF(I14>0,0,IF(K14<0,0,MIN(K14-SUM(K18:K20),-I14-J16))) -> 0 | L17: =IF(J14>0,0,IF(L14<0,0,MIN(L14-SUM(L18:L20),-J14-K16))) -> 0 | M17: =IF(K14>0,0,IF(M14<0,0,MIN(M14-SUM(M18:M20),-K14-L16))) -> 0 | N17: =IF(L14>0,0,IF(N14<0,0,MIN(N14-SUM(N18:N20),-L14-M16))) -> 0 | O17: =IF(M14>0,0,IF(O14<0,0,MIN(O14-SUM(O18:O20),-M14-N16))) -> 0 | P17: =IF(N14>0,0,IF(P14<0,0,MIN(P14-SUM(P18:P20),-N14-O16))) -> 0 | Q17: =IF(O14>0,0,IF(Q14<0,0,MIN(Q14-SUM(Q18:Q20),-O14-P16))) -> 0 | ... AA17: =IF(Y14>0,0,IF(AA14<0,0,MIN(AA14-SUM(AA18:AA20),-Y14-Z16))) -> 0
C18: 弥补前序第三年亏损 | E18: 万元 | K18: =IF(H14>0,0,IF(K14<0,0,MIN(K14-SUM(K19:K20),-H14-I16-J17))) -> 0 | L18: =IF(I14>0,0,IF(L14<0,0,MIN(L14-SUM(L19:L20),-I14-J16-K17))) -> 0 | M18: =IF(J14>0,0,IF(M14<0,0,MIN(M14-SUM(M19:M20),-J14-K16-L17))) -> 0 | N18: =IF(K14>0,0,IF(N14<0,0,MIN(N14-SUM(N19:N20),-K14-L16-M17))) -> 0 | O18: =IF(L14>0,0,IF(O14<0,0,MIN(O14-SUM(O19:O20),-L14-M16-N17))) -> 0 | P18: =IF(M14>0,0,IF(P14<0,0,MIN(P14-SUM(P19:P20),-M14-N16-O17))) -> 0 | Q18: =IF(N14>0,0,IF(Q14<0,0,MIN(Q14-SUM(Q19:Q20),-N14-O16-P17))) -> 0 | R18: =IF(O14>0,0,IF(R14<0,0,MIN(R14-SUM(R19:R20),-O14-P16-Q17))) -> 0 | ... AA18: =IF(X14>0,0,IF(AA14<0,0,MIN(AA14-SUM(AA19:AA20),-X14-Y16-Z17))) -> 0
C19: 弥补前序第四年亏损 | E19: 万元 | L19: =IF(H14>0,0,IF(L14<0,0,MIN(L14-L20,-H14-I16-J17-K18))) -> 0 | M19: =IF(I14>0,0,IF(M14<0,0,MIN(M14-M20,-I14-J16-K17-L18))) -> 0 | N19: =IF(J14>0,0,IF(N14<0,0,MIN(N14-N20,-J14-K16-L17-M18))) -> 0 | O19: =IF(K14>0,0,IF(O14<0,0,MIN(O14-O20,-K14-L16-M17-N18))) -> 0 | P19: =IF(L14>0,0,IF(P14<0,0,MIN(P14-P20,-L14-M16-N17-O18))) -> 78.744235 | Q19: =IF(M14>0,0,IF(Q14<0,0,MIN(Q14-Q20,-M14-N16-O17-P18))) -> 425.20518 | R19: =IF(N14>0,0,IF(R14<0,0,MIN(R14-R20,-N14-O16-P17-Q18))) -> 0 | S19: =IF(O14>0,0,IF(S14<0,0,MIN(S14-S20,-O14-P16-Q17-R18))) -> 0 | ... AA19: =IF(W14>0,0,IF(AA14<0,0,MIN(AA14-AA20,-W14-X16-Y17-Z18))) -> 0
C20: 弥补前序第五年亏损 | E20: 万元 | M20: =IF(H14>0,0,IF(M14<0,0,MIN(M14,-H14-I16-J17-K18-L19))) -> 0 | N20: =IF(I14>0,0,IF(N14<0,0,MIN(N14,-I14-J16-K17-L18-M19))) -> 185.45973 | O20: =IF(J14>0,0,IF(O14<0,0,MIN(O14,-J14-K16-L17-M18-N19))) -> 271.61192 | P20: =IF(K14>0,0,IF(P14<0,0,MIN(P14,-K14-L16-M17-N18-O19))) -> 328.53556 | Q20: =IF(L14>0,0,IF(Q14<0,0,MIN(Q14,-L14-M16-N17-O18-P19))) -> 120.06781 | R20: =IF(M14>0,0,IF(R14<0,0,MIN(R14,-M14-N16-O17-P18-Q19))) -> 471.03096 | S20: =IF(N14>0,0,IF(S14<0,0,MIN(S14,-N14-O16-P17-Q18-R19))) -> 0 | T20: =IF(O14>0,0,IF(T14<0,0,MIN(T14,-O14-P16-Q17-R18-S19))) -> 0 | ... AA20: =IF(V14>0,0,IF(AA14<0,0,MIN(AA14,-V14-W16-X17-Y18-Z19))) -> 0
B21: 8 | C21: 应税所得额 | D21: =SUM(F21:AA21) -> 37894.387 | E21: 万元 | H21: =IF(H14-H15>0,H14-H15,0) -> 6829.3875 | I21: =IF(I14-I15>0,I14-I15,0) -> 0 | J21: =IF(J14-J15>0,J14-J15,0) -> 0 | K21: =IF(K14-K15>0,K14-K15,0) -> 0 | L21: =IF(L14-L15>0,L14-L15,0) -> 0 | M21: =IF(M14-M15>0,M14-M15,0) -> 0 | N21: =IF(N14-N15>0,N14-N15,0) -> 0 | O21: =IF(O14-O15>0,O14-O15,0) -> 0 | ... AA21: =IF(AA14-AA15>0,AA14-AA15,0) -> 4575.3311
B22: 9 | C22: 企业所得税 | D22: =SUM(F22:AA22) -> 9473.5968 | E22: 万元 | H22: =IF(参数输入表!$H$689="三免三减半",0,'表5-利润表-资本金'!H21*参数输入表!$H$690) -> 1707.3469 | I22: =IF(参数输入表!$H$689="三免三减半",0,'表5-利润表-资本金'!I21*参数输入表!$H$690) -> 0 | J22: =IF(参数输入表!$H$689="三免三减半",0,'表5-利润表-资本金'!J21*参数输入表!$H$690) -> 0 | K22: =IF(参数输入表!$H$689="三免三减半",'表5-利润表-资本金'!K21*参数输入表!$H$690/2,'表5-利润表-资本金'!K21*参数输入表!$H$690) -> 0 | L22: =IF(参数输入表!$H$689="三免三减半",'表5-利润表-资本金'!L21*参数输入表!$H$690/2,'表5-利润表-资本金'!L21*参数输入表!$H$690) -> 0 | M22: =IF(参数输入表!$H$689="三免三减半",'表5-利润表-资本金'!M21*参数输入表!$H$690/2,'表5-利润表-资本金'!M21*参数输入表!$H$690) -> 0 | N22: =N21*参数输入表!$H$690 -> 0 | O22: =O21*参数输入表!$H$690 -> 0 | P22: =P21*参数输入表!$H$690 -> 0 | Q22: =Q21*参数输入表!$H$690 -> 0 | R22: =R21*参数输入表!$H$690 -> 259.22103 | S22: =S21*参数输入表!$H$690 -> 404.04292 | T22: =T21*参数输入表!$H$690 -> 437.06926 | U22: =U21*参数输入表!$H$690 -> 471.52247 | ... AA22: =AA21*参数输入表!$H$690 -> 1143.8328
B23: 10 | C23: 净利润（6-9） | D23: =SUM(F23:AA23) -> 27831.57 | E23: 万元 | H23: =H14-H22 -> 5122.0406 | I23: =I14-I22 -> -588.02062 | J23: =J14-J22 -> -458.27173 | K23: =K14-K22 -> -328.53556 | L23: =L14-L22 -> -198.81204 | M23: =M14-M22 -> -896.23614 | N23: =N14-N22 -> 185.45973 | O23: =O14-O22 -> 271.61192 | ... AA23: =AA14-AA22 -> 3431.4983
B24: 11 | C24: 期初未分配的利润 | E24: 万元 | F24: 0 | G24: 0 | H24: =G32 -> 0 | I24: =H32 -> 4148.8529 | J24: =I32 -> 3257.6709 | K24: =J32 -> 2560.7037 | L24: =K32 -> 2038.5196 | M24: =L32 -> 1673.6298 | N24: =M32 -> 780.31559 | O24: =N32 -> 869.19779 | ... AA24: =Z32 -> 13108.985
B25: 12 | C25: 可供分配的利润（10+11） | D25: =SUM(F25:AA25) -> 109183.88 | E25: 万元 | H25: =H23+H24 -> 5122.0406 | I25: =I23+I24 -> 3560.8323 | J25: =J23+J24 -> 2799.3992 | K25: =K23+K24 -> 2232.1682 | L25: =L23+L24 -> 1839.7075 | M25: =M23+M24 -> 777.39371 | N25: =N23+N24 -> 965.77532 | O25: =O23+O24 -> 1140.8097 | ... AA25: =AA23+AA24 -> 16540.483
B26: 13 | C26: 提取法定盈余公积金 | D26: =SUM(F26:AA26) -> 2595.0914 | E26: 万元 | H26: =IF(G28>=参数输入表!$H$366,0,IF(H25<0,0,IF(H25*参数输入表!$H$367>=H27,H27,(-H24-H15+H25)*参数输入表!$H$367))) -> 512.20406 | I26: =IF(H28>=参数输入表!$H$366,0,IF(I25<0,0,IF(I25*参数输入表!$H$367>=I27,I27,(-I24-I15+I25)*参数输入表!$H$367))) -> -58.802062 | J26: =IF(I28>=参数输入表!$H$366,0,IF(J25<0,0,IF(J25*参数输入表!$H$367>=J27,J27,(-J24-J15+J25)*参数输入表!$H$367))) -> -45.827173 | K26: =IF(J28>=参数输入表!$H$366,0,IF(K25<0,0,IF(K25*参数输入表!$H$367>=K27,K27,(-K24-K15+K25)*参数输入表!$H$367))) -> -32.853556 | L26: =IF(K28>=参数输入表!$H$366,0,IF(L25<0,0,IF(L25*参数输入表!$H$367>=L27,L27,(-L24-L15+L25)*参数输入表!$H$367))) -> -19.881204 | M26: =IF(L28>=参数输入表!$H$366,0,IF(M25<0,0,IF(M25*参数输入表!$H$367>=M27,M27,(-M24-M15+M25)*参数输入表!$H$367))) -> -89.623614 | N26: =IF(M28>=参数输入表!$H$366,0,IF(N25<0,0,IF(N25*参数输入表!$H$367>=N27,N27,(-N24-N15+N25)*参数输入表!$H$367))) -> 0 | O26: =IF(N28>=参数输入表!$H$366,0,IF(O25<0,0,IF(O25*参数输入表!$H$367>=O27,O27,(-O24-O15+O25)*参数输入表!$H$367))) -> 0 | ... AA26: =IF(Z28>=参数输入表!$H$366,0,IF(AA25<0,0,IF(AA25*参数输入表!$H$367>=AA27,AA27,(-AA24-AA15+AA25)*参数输入表!$H$367))) -> 343.14983
C27: 期初法定盈余公积金上限缺口 | E27: 万元 | H27: =参数输入表!$H$366 -> 4037.551 | I27: =参数输入表!$H$366-H28 -> 3525.347 | J27: =参数输入表!$H$366-I28 -> 3584.149 | K27: =参数输入表!$H$366-J28 -> 3629.9762 | L27: =参数输入表!$H$366-K28 -> 3662.8298 | M27: =参数输入表!$H$366-L28 -> 3682.711 | N27: =参数输入表!$H$366-M28 -> 3772.3346 | O27: =参数输入表!$H$366-N28 -> 3772.3346 | P27: =参数输入表!$H$366-O28 -> 3772.3346 | ... AA27: =参数输入表!$H$366-Z28 -> 1785.6094
C28: 期末法定盈余公积金累计 | E28: 万元 | H28: =H26 -> 512.20406 | I28: =I26+H28 -> 453.402 | J28: =J26+I28 -> 407.57483 | K28: =K26+J28 -> 374.72127 | L28: =L26+K28 -> 354.84007 | M28: =M26+L28 -> 265.21645 | N28: =N26+M28 -> 265.21645 | O28: =O26+N28 -> 265.21645 | P28: =P26+O28 -> 265.21645 | ... AA28: =AA26+Z28 -> 2595.0914
B29: 14 | C29: 可供投资者分配的利润（12-13） | D29: =SUM(F29:AA29) -> 106588.79 | E29: 万元 | H29: =H25-H26 -> 4609.8366 | I29: =I25-I26 -> 3619.6344 | J29: =J25-J26 -> 2845.2264 | K29: =K25-K26 -> 2265.0217 | L29: =L25-L26 -> 1859.5887 | M29: =M25-M26 -> 867.01732 | N29: =N25-N26 -> 965.77532 | O29: =O25-O26 -> 1140.8097 | ... AA29: =AA25-AA26 -> 16197.333
B30: 15 | C30: 提取任意盈余公积金 | D30: =SUM(F30:AA30) -> 0 | E30: 万元 | H30: =H29*参数输入表!$H$368 -> 0 | I30: =I29*参数输入表!$H$368 -> 0 | J30: =J29*参数输入表!$H$368 -> 0 | K30: =K29*参数输入表!$H$368 -> 0 | L30: =L29*参数输入表!$H$368 -> 0 | M30: =M29*参数输入表!$H$368 -> 0 | N30: =N29*参数输入表!$H$368 -> 0 | O30: =O29*参数输入表!$H$368 -> 0 | ... AA30: =AA29*参数输入表!$H$368 -> 0
B31: 16 | C31: 各投资方利润分配 | D31: =SUM(F31:AA31) -> 10658.879 | E31: 万元 | H31: =IF(H29<0,0,(H29)*0.1) -> 460.98366 | I31: =IF(I29<0,0,(I29)*0.1) -> 361.96344 | J31: =IF(J29<0,0,(J29)*0.1) -> 284.52264 | K31: =IF(K29<0,0,(K29)*0.1) -> 226.50217 | L31: =IF(L29<0,0,(L29)*0.1) -> 185.95887 | M31: =IF(M29<0,0,(M29)*0.1) -> 86.701732 | N31: =IF(N29<0,0,(N29)*0.1) -> 96.577532 | O31: =IF(O29<0,0,(O29)*0.1) -> 114.08097 | ... AA31: =IF(AA29<0,0,(AA29)*0.1) -> 1619.7333
B32: 17 | C32: 未分配利润（14-15-16） | D32: =SUM(F32:AA32) -> 95929.907 | E32: 万元 | H32: =H29-H30-H31 -> 4148.8529 | I32: =I29-I30-I31 -> 3257.6709 | J32: =J29-J30-J31 -> 2560.7037 | K32: =K29-K30-K31 -> 2038.5196 | L32: =L29-L30-L31 -> 1673.6298 | M32: =M29-M30-M31 -> 780.31559 | N32: =N29-N30-N31 -> 869.19779 | O32: =O29-O30-O31 -> 1026.7287 | ... AA32: =AA29-AA30-AA31 -> 14577.6
B33: 18 | C33: 息税前利润（利润总额+利息支出） | D33: =SUM(F33:AA33) -> 52500.983 | E33: 万元 | H33: =H14+'表1-资金筹措及还本付息表'!H93 -> 8716.8631 | I33: =I14+'表1-资金筹措及还本付息表'!I93 -> 1174.1566 | J33: =J14+'表1-资金筹措及还本付息表'!J93 -> 1178.6072 | K33: =K14+'表1-资金筹措及还本付息表'!K93 -> 1183.0451 | L33: =L14+'表1-资金筹措及还本付息表'!L93 -> 1187.4703 | M33: =M14+'表1-资金筹措及还本付息表'!M93 -> 364.74788 | N33: =N14+'表1-资金筹措及还本付息表'!N93 -> 1321.1455 | O33: =O14+'表1-资金筹措及还本付息表'!O93 -> 1281.9993 | ... AA33: =AA14+'表1-资金筹措及还本付息表'!AA93 -> 4583.3321
B34: 19 | C34: 息税折旧摊销前利润 | D34: =SUM(F34:AA34) -> 107903.18 | E34: 万元 | H34: =H33+'表2-折旧摊销表'!H52 -> 12487.874 | I34: =I33+'表2-折旧摊销表'!I52 -> 4945.1678 | J34: =J33+'表2-折旧摊销表'!J52 -> 4949.6184 | K34: =K33+'表2-折旧摊销表'!K52 -> 4954.0563 | L34: =L33+'表2-折旧摊销表'!L52 -> 4958.4815 | M34: =M33+'表2-折旧摊销表'!M52 -> 4135.7591 | N34: =N33+'表2-折旧摊销表'!N52 -> 5092.1567 | O34: =O33+'表2-折旧摊销表'!O52 -> 5053.0106 | ... AA34: =AA33+'表2-折旧摊销表'!AA52 -> 5174.5009
C36: 利润表里的收入、成本均为不含税价
C37: 政府一次性运营补贴收入—递延收益，引用自参数输入表“政府一次性补贴收入—递延收益确认”
C38: 弥补以前年度亏损，按照5年为期限，滚动计算。
C40: 标黄部分为相对固定模块，适用于所有项目
C41: 标蓝部分为计算中间过程，可不展示

Sheet 表6-现金流量表-资本金
B2: 现金流量表-资本金
B3: 序号 | C3: 项目 | D3: 合计 | E3: 单位 | F3: 建设期 | H3: 运营期
F4: 1 | G4: 2 | H4: 1 | I4: 2 | J4: 3 | K4: 4 | L4: 5 | M4: 6 | N4: 7 | O4: 8 | P4: 9 | Q4: 10 | R4: 11 | S4: 12 | T4: 13 | U4: 14 | V4: 15 | W4: 16 | X4: 17 | Y4: 18 | Z4: 19 | AA4: 20
B5: 1 | C5: 现金流入 | D5: =SUM(F5:AA5) -> 457721.4 | E5: 万元 | F5: =SUM(F6:F12) -> 31636.041 | G5: =SUM(G6:G12) -> 22063.232 | H5: =H6+H7+H8+H9+H10+H11+H12 -> 26688.384 | I5: =SUM(I6:I12) -> 18688.384 | J5: =SUM(J6:J12) -> 18688.384 | K5: =SUM(K6:K12) -> 18688.384 | L5: =SUM(L6:L12) -> 18688.384 | M5: =SUM(M6:M12) -> 18688.384 | N5: =SUM(N6:N12) -> 19688.384 | O5: =SUM(O6:O12) -> 19688.384 | P5: =SUM(P6:P12) -> 19688.384 | ... AA5: =SUM(AA6:AA12) -> 27942.835
B6: 1.1 | C6: 债务资金 | D6: =SUM(F6:AA6) -> 53699.272 | E6: 万元 | F6: ='表1-资金筹措及还本付息表'!F80 -> 31636.041 | G6: ='表1-资金筹措及还本付息表'!G80 -> 22063.232 | H6: 0 | I6: 0 | J6: 0 | K6: 0 | L6: 0 | M6: 0 | N6: 0 | O6: 0 | P6: 0 | Q6: 0 | R6: 0 | S6: 0 | T6: 0 | U6: 0 | V6: 0 | W6: 0 | X6: 0 | Y6: 0 | Z6: 0 | AA6: 0
B7: 1.2 | C7: 发电销售收入（含税） | D7: =SUM(F7:AA7) -> 395767.68 | E7: 万元 | H7: ='表4-收入税金表'!H6+'表4-收入税金表'!H18 -> 26688.384 | I7: ='表4-收入税金表'!I6+'表4-收入税金表'!I18 -> 18688.384 | J7: ='表4-收入税金表'!J6+'表4-收入税金表'!J18 -> 18688.384 | K7: ='表4-收入税金表'!K6+'表4-收入税金表'!K18 -> 18688.384 | L7: ='表4-收入税金表'!L6+'表4-收入税金表'!L18 -> 18688.384 | M7: ='表4-收入税金表'!M6+'表4-收入税金表'!M18 -> 18688.384 | N7: ='表4-收入税金表'!N6+'表4-收入税金表'!N18 -> 19688.384 | O7: ='表4-收入税金表'!O6+'表4-收入税金表'!O18 -> 19688.384 | ... AA7: ='表4-收入税金表'!AA6+'表4-收入税金表'!AA18 -> 19688.384
B8: 1.3 | C8: 其他收入 | D8: =SUM(F8:AA8) -> 0 | E8: 万元 | H8: =('表4-收入税金表'!H10+'表4-收入税金表'!H19) -> 0 | I8: =('表4-收入税金表'!I10+'表4-收入税金表'!I19) -> 0 | J8: =('表4-收入税金表'!J10+'表4-收入税金表'!J19) -> 0 | K8: =('表4-收入税金表'!K10+'表4-收入税金表'!K19) -> 0 | L8: =('表4-收入税金表'!L10+'表4-收入税金表'!L19) -> 0 | M8: =('表4-收入税金表'!M10+'表4-收入税金表'!M19) -> 0 | N8: =('表4-收入税金表'!N10+'表4-收入税金表'!N19) -> 0 | O8: =('表4-收入税金表'!O10+'表4-收入税金表'!O19) -> 0 | ... AA8: =('表4-收入税金表'!AA10+'表4-收入税金表'!AA19) -> 0
B9: 1.4 | C9: 政府一次性运营补贴收入 | D9: =SUM(F9:AA9) -> 0 | E9: 万元 | H9: =参数输入表!H318 -> 0
B10: 1.5 | C10: 回收固定资产余值 | D10: =SUM(F10:AA10) -> 7873.4512 | E10: 万元 | H10: 0 | I10: 0 | J10: 0 | K10: 0 | L10: 0 | M10: 0 | N10: 0 | O10: 0 | P10: 0 | Q10: 0 | R10: 0 | S10: 0 | T10: 0 | U10: 0 | V10: 0 | W10: 0 | X10: 0 | Y10: 0 | Z10: 0 | AA10: ='表2-折旧摊销表'!AA53 -> 7873.4512
B11: 1.6 | C11: 回收流动资金 | D11: =SUM(F11:AA11) -> 381 | E11: 万元 | AA11: ='表1-资金筹措及还本付息表'!H6 -> 381
B12: 1.7 | C12: 增值税即征即退 | D12: =SUM(F12:AA12) -> 0 | E12: 万元 | H12: ='表4-收入税金表'!H13 -> 0 | I12: ='表4-收入税金表'!I13 -> 0 | J12: ='表4-收入税金表'!J13 -> 0 | K12: ='表4-收入税金表'!K13 -> 0 | L12: ='表4-收入税金表'!L13 -> 0 | M12: ='表4-收入税金表'!M13 -> 0 | N12: ='表4-收入税金表'!N13 -> 0 | O12: ='表4-收入税金表'!O13 -> 0 | ... AA12: ='表4-收入税金表'!AA13 -> 0
B13: 2 | C13: 现金流出 | D13: =SUM(F13:AA13) -> 420416.24 | E13: 万元 | F13: =F14+F17+F18+F22+F23+F24+F25+F26 -> 39711.143 | G13: =G14+G17+G18+G22+G23+G24+G25+G26 -> 27579.04 | H13: =H14+H17+H18+H22+H23+H24+H25+H26 -> 18740.024 | I13: =I14+I17+I18+I22+I23+I24+I25+I26 -> 18495.382 | J13: =J14+J17+J18+J22+J23+J24+J25+J26 -> 18365.055 | K13: =K14+K17+K18+K22+K23+K24+K25+K26 -> 18234.742 | L13: =L14+L17+L18+L22+L23+L24+L25+L26 -> 18104.443 | M13: =M14+M17+M18+M22+M23+M24+M25+M26 -> 18908.821 | ... AA13: =AA14+AA17+AA18+AA22+AA23+AA24+AA25+AA26 -> 14788.584
B14: 2.1 | C14: 工程建设投资 | D14: =SUM(F14:AA14) -> 67290.182 | F14: =SUM(F15:F16) -> 39711.143 | G14: =SUM(G15:G16) -> 27579.04
C15: 项目资本金 | D15: =SUM(F15:AA15) -> 13590.91 | E15: 万元 | F15: ='表1-资金筹措及还本付息表'!F11 -> 8075.102 | G15: ='表1-资金筹措及还本付息表'!G11 -> 5515.8079
C16: 长期借款 | D16: =SUM(F16:AA16) -> 53699.272 | E16: 万元 | F16: ='表1-资金筹措及还本付息表'!F15 -> 31636.041 | G16: ='表1-资金筹措及还本付息表'!G15 -> 22063.232
B17: 2.2 | C17: 支付流动资金 | D17: =SUM(F17:AA17) -> 114.3 | E17: 万元 | H17: ='表1-资金筹措及还本付息表'!H11 -> 114.3
B18: 2.3 | C18: 债务性支出 | D18: =SUM(F18:AA18) -> 69161.789 | E18: 万元 | H18: =SUM(H19:H21) -> 5467.427 | I18: =SUM(I19:I21) -> 5342.1287 | J18: =SUM(J19:J21) -> 5216.8304 | K18: =SUM(K19:K21) -> 5091.5321 | L18: =SUM(L19:L21) -> 4966.2338 | M18: =SUM(M19:M21) -> 4840.9355 | N18: =SUM(N19:N21) -> 4715.6372 | O18: =SUM(O19:O21) -> 4590.3389 | ... AA18: =SUM(AA19:AA21) -> 274.701
C19: 长期借款本金偿还 | D19: =SUM(F19:AA19) -> 53699.272 | E19: 万元 | H19: ='表1-资金筹措及还本付息表'!H52 -> 3579.9515 | I19: ='表1-资金筹措及还本付息表'!I52 -> 3579.9515 | J19: ='表1-资金筹措及还本付息表'!J52 -> 3579.9515 | K19: ='表1-资金筹措及还本付息表'!K52 -> 3579.9515 | L19: ='表1-资金筹措及还本付息表'!L52 -> 3579.9515 | M19: ='表1-资金筹措及还本付息表'!M52 -> 3579.9515 | N19: ='表1-资金筹措及还本付息表'!N52 -> 3579.9515 | O19: ='表1-资金筹措及还本付息表'!O52 -> 3579.9515 | ... AA19: ='表1-资金筹措及还本付息表'!AA52 -> 0
C20: 流动资金借款本金偿还 | E20: 万元 | H20: ='表1-资金筹措及还本付息表'!H62 -> 0 | I20: ='表1-资金筹措及还本付息表'!I62 -> 0 | J20: ='表1-资金筹措及还本付息表'!J62 -> 0 | K20: ='表1-资金筹措及还本付息表'!K62 -> 0 | L20: ='表1-资金筹措及还本付息表'!L62 -> 0 | M20: ='表1-资金筹措及还本付息表'!M62 -> 0 | N20: ='表1-资金筹措及还本付息表'!N62 -> 0 | O20: ='表1-资金筹措及还本付息表'!O62 -> 0 | ... AA20: ='表1-资金筹措及还本付息表'!AA62 -> 266.7
C21: 借款利息支付（含短贷利息） | D21: =SUM(F21:AA21) -> 15195.816 | E21: 万元 | H21: ='表1-资金筹措及还本付息表'!H53+'表1-资金筹措及还本付息表'!H63+'表1-资金筹措及还本付息表'!H73 -> 1887.4755 | I21: ='表1-资金筹措及还本付息表'!I53+'表1-资金筹措及还本付息表'!I63+'表1-资金筹措及还本付息表'!I73 -> 1762.1772 | J21: ='表1-资金筹措及还本付息表'!J53+'表1-资金筹措及还本付息表'!J63+'表1-资金筹措及还本付息表'!J73 -> 1636.8789 | K21: ='表1-资金筹措及还本付息表'!K53+'表1-资金筹措及还本付息表'!K63+'表1-资金筹措及还本付息表'!K73 -> 1511.5806 | L21: ='表1-资金筹措及还本付息表'!L53+'表1-资金筹措及还本付息表'!L63+'表1-资金筹措及还本付息表'!L73 -> 1386.2823 | M21: ='表1-资金筹措及还本付息表'!M53+'表1-资金筹措及还本付息表'!M63+'表1-资金筹措及还本付息表'!M73 -> 1260.984 | N21: ='表1-资金筹措及还本付息表'!N53+'表1-资金筹措及还本付息表'!N63+'表1-资金筹措及还本付息表'!N73 -> 1135.6857 | O21: ='表1-资金筹措及还本付息表'!O53+'表1-资金筹措及还本付息表'!O63+'表1-资金筹措及还本付息表'!O73 -> 1010.3874 | ... AA21: ='表1-资金筹措及还本付息表'!AA53+'表1-资金筹措及还本付息表'!AA63+'表1-资金筹措及还本付息表'!AA73 -> 8.001
B22: 2.4 | C22: 生产经营支出（含税） | D22: =SUM(F22:AA22) -> 275545.51 | E22: 万元 | H22: ='表3-成本费用表'!H48+'表4-收入税金表'!H22 -> 13158.297 | I22: ='表3-成本费用表'!I48+'表4-收入税金表'!I22 -> 13153.254 | J22: ='表3-成本费用表'!J48+'表4-收入税金表'!J22 -> 13148.224 | K22: ='表3-成本费用表'!K48+'表4-收入税金表'!K22 -> 13143.21 | L22: ='表3-成本费用表'!L48+'表4-收入税金表'!L22 -> 13138.209 | M22: ='表3-成本费用表'!M48+'表4-收入税金表'!M22 -> 14067.885 | N22: ='表3-成本费用表'!N48+'表4-收入税金表'!N22 -> 14053.194 | O22: ='表3-成本费用表'!O48+'表4-收入税金表'!O22 -> 14038.555 | ... AA22: ='表3-成本费用表'!AA48+'表4-收入税金表'!AA22 -> 13896.748
B23: 2.5 | C23: 营业外支出 | D23: =SUM(F23:AA23) -> 0 | E23: 万元 | H23: ='表3-成本费用表'!H62 -> 0 | I23: ='表3-成本费用表'!I62 -> 0 | J23: ='表3-成本费用表'!J62 -> 0 | K23: ='表3-成本费用表'!K62 -> 0 | L23: ='表3-成本费用表'!L62 -> 0 | M23: ='表3-成本费用表'!M62 -> 0 | N23: ='表3-成本费用表'!N62 -> 0 | O23: ='表3-成本费用表'!O62 -> 0 | ... AA23: ='表3-成本费用表'!AA62 -> 0
B24: 2.6 | C24: 增值税缴纳 | D24: =SUM(F24:AA24) -> 7094.9645 | E24: 万元 | H24: ='表4-收入税金表'!H16 -> 0 | I24: ='表4-收入税金表'!I16 -> 0 | J24: ='表4-收入税金表'!J16 -> 0 | K24: ='表4-收入税金表'!K16 -> 0 | L24: ='表4-收入税金表'!L16 -> 0 | M24: ='表4-收入税金表'!M16 -> 0 | N24: ='表4-收入税金表'!N16 -> 0 | O24: ='表4-收入税金表'!O16 -> 521.00828 | ... AA24: ='表4-收入税金表'!AA16 -> 561.03158
B25: 2.7 | C25: 营业税金及附加 | D25: =SUM(F25:AA25) -> 709.49645 | E25: 万元 | H25: ='表5-利润表-资本金'!H9 -> 0 | I25: ='表5-利润表-资本金'!I9 -> 0 | J25: ='表5-利润表-资本金'!J9 -> 0 | K25: ='表5-利润表-资本金'!K9 -> 0 | L25: ='表5-利润表-资本金'!L9 -> 0 | M25: ='表5-利润表-资本金'!M9 -> 0 | N25: ='表5-利润表-资本金'!N9 -> 0 | O25: ='表5-利润表-资本金'!O9 -> 52.100828 | ... AA25: ='表5-利润表-资本金'!AA9 -> 56.103158
B26: 2.8 | C26: 运营期资本性支出 | D26: =SUM(F26:AA26) -> 500 | E26: 万元 | H26: =参数输入表!H656 -> 0 | I26: =参数输入表!H657 -> 0 | J26: =参数输入表!H658 -> 0 | K26: =参数输入表!H659 -> 0 | L26: =参数输入表!H660 -> 0 | M26: =参数输入表!H661 -> 0 | N26: =参数输入表!H662 -> 0 | O26: =参数输入表!H663 -> 0 | P26: =参数输入表!H664 -> 0 | Q26: =参数输入表!H665 -> 0 | R26: =参数输入表!H666 -> 0 | S26: =参数输入表!H667 -> 500 | T26: =参数输入表!H668 -> 0 | U26: =参数输入表!H669 -> 0 | V26: =参数输入表!H670 -> 0 | W26: =参数输入表!H671 -> 0 | X26: =参数输入表!H672 -> 0 | Y26: =参数输入表!H673 -> 0 | Z26: =参数输入表!H674 -> 0 | AA26: =参数输入表!H675 -> 0
B27: 3 | C27: 税前净现金流量（1-2） | D27: =SUM(F27:AA27) -> 37305.167 | E27: 万元 | F27: =F5-F13 -> -8075.102 | G27: =G5-G13 -> -5515.8079 | H27: =H5-H13 -> 7948.3598 | I27: =I5-I13 -> 193.00171 | J27: =J5-J13 -> 323.32917 | K27: =K5-K13 -> 453.64227 | L27: =L5-L13 -> 583.94107 | M27: =M5-M13 -> -220.43694 | ... AA27: =AA5-AA13 -> 13154.251
B28: 4 | C28: 累计税前净现金流量 | E28: 万元 | F28: =F27 -> -8075.102 | G28: =IF('表1-资金筹措及还本付息表'!G5>0,F28+G27,0) -> -13590.91 | H28: =G28+H27 -> -5642.5501 | I28: =H28+I27 -> -5449.5484 | J28: =I28+J27 -> -5126.2193 | K28: =J28+K27 -> -4672.577 | L28: =K28+L27 -> -4088.6359 | M28: =L28+M27 -> -4309.0729 | N28: =M28+N27 -> -3389.52 | O28: =N28+O27 -> -2903.1391 | ... AA28: =Z28+AA27 -> 37305.167
B29: 5 | C29: 企业所得税 | D29: =SUM(F29:AA29) -> 9473.5968 | E29: 万元 | H29: ='表5-利润表-资本金'!H22 -> 1707.3469 | I29: ='表5-利润表-资本金'!I22 -> 0 | J29: ='表5-利润表-资本金'!J22 -> 0 | K29: ='表5-利润表-资本金'!K22 -> 0 | L29: ='表5-利润表-资本金'!L22 -> 0 | M29: ='表5-利润表-资本金'!M22 -> 0 | N29: ='表5-利润表-资本金'!N22 -> 0 | O29: ='表5-利润表-资本金'!O22 -> 0 | ... AA29: ='表5-利润表-资本金'!AA22 -> 1143.8328
B30: 6 | C30: 税后净现金流量（3-5） | D30: =SUM(F30:AA30) -> 27831.57 | E30: 万元 | F30: =F27-F29 -> -8075.102 | G30: =G27-G29 -> -5515.8079 | H30: =H27-H29 -> 6241.0129 | I30: =I27-I29 -> 193.00171 | J30: =J27-J29 -> 323.32917 | K30: =K27-K29 -> 453.64227 | L30: =L27-L29 -> 583.94107 | M30: =M27-M29 -> -220.43694 | ... AA30: =AA27-AA29 -> 12010.418
B31: 7 | C31: 累计税后净现金流量 | E31: 万元 | F31: =F30 -> -8075.102 | G31: =IF('表1-资金筹措及还本付息表'!G5>0,F31+G30,0) -> -13590.91 | H31: =G31+H30 -> -7349.897 | I31: =H31+I30 -> -7156.8953 | J31: =I31+J30 -> -6833.5661 | K31: =J31+K30 -> -6379.9239 | L31: =K31+L30 -> -5795.9828 | M31: =L31+M30 -> -6016.4197 | N31: =M31+N30 -> -5096.8669 | O31: =N31+O30 -> -4610.486 | ... AA31: =Z31+AA30 -> 27831.57
C33: 资本金内部收益率（税前） | D33: =IF('表1-资金筹措及还本付息表'!G5=0,IRR(E52:Y52),IRR(F27:AA27)) -> 0.11871397
C34: 资本金内部收益率（税后） | D34: =IF('表1-资金筹措及还本付息表'!G5=0,IRR(E55:Y55),IRR(F30:AA30)) -> 0.093083589
C35: 投资回收期（税后） | D35: =MAX(F35:AA35)+2 -> 17.044487 | E35: 年 | F35: 0 | G35: 0 | H35: 0 | I35: =IF(I31/H31<0,H4+ABS(H31/I30),0) -> 0 | J35: =IF(J31/I31<0,I4+ABS(I31/J30),0) -> 0 | K35: =IF(K31/J31<0,J4+ABS(J31/K30),0) -> 0 | L35: =IF(L31/K31<0,K4+ABS(K31/L30),0) -> 0 | M35: =IF(M31/L31<0,L4+ABS(L31/M30),0) -> 0 | N35: =IF(N31/M31<0,M4+ABS(M31/N30),0) -> 0 | O35: =IF(O31/N31<0,N4+ABS(N31/O30),0) -> 0 | P35: =IF(P31/O31<0,O4+ABS(O31/P30),0) -> 0 | ... AA35: =IF(AA31/Z31<0,Z4+ABS(Z31/AA30),0) -> 0
C37: 标黄部分为相对固定模块，适用于所有项目
C38: 现金流量表中各年的发电补贴收入数据引用参数表中输入的实发数据（含税且考虑滞后支付情形，即本年度实际支付比例＋上年度剩余支付比例）
C39: 政府一次性运营补贴收入，在运营期第1年引用参数表中政府一次性补贴总额
C40: 标蓝色部分为可隐藏内容
C41: 现金流出中借款本金偿还，关联还本付息表中长期贷款本金偿还
C44: Check | D44: =D30-'表5-利润表-资本金'!D23 -> 0
B46: 建设期为1年时，IRR计算要利用下面的公式计算
B50: 序号 | C50: 项目 | D50: 单位 | E50: 建设期 | F50: 建设 | G50: 运营期
E51: 1 | F51: 1 | G51: 2 | H51: 3 | I51: 4 | J51: 5 | K51: 6 | L51: 7 | M51: 8 | N51: 9 | O51: 10 | P51: 11 | Q51: 12 | R51: 13 | S51: 14 | T51: 15 | U51: 16 | V51: 17 | W51: 18 | X51: 19 | Y51: 20
B52: 3 | C52: 税前净现金流量（1-2） | D52: 万元 | E52: =F27 -> -8075.102 | F52: =H27 -> 7948.3598 | G52: =I27 -> 193.00171 | H52: =J27 -> 323.32917 | I52: =K27 -> 453.64227 | J52: =L27 -> 583.94107 | K52: =M27 -> -220.43694 | L52: =N27 -> 919.55288 | M52: =O27 -> 486.3809 | ... Y52: =AA27 -> 13154.251
B53: 4 | C53: 累计税前净现金流量 | D53: 万元 | E53: =E52 -> -8075.102 | F53: =H28 -> -5642.5501 | G53: =I28 -> -5449.5484 | H53: =J28 -> -5126.2193 | I53: =K28 -> -4672.577 | J53: =L28 -> -4088.6359 | K53: =M28 -> -4309.0729 | L53: =N28 -> -3389.52 | M53: =O28 -> -2903.1391 | ... Y53: =AA28 -> 37305.167
B54: 5 | C54: 企业所得税 | D54: 万元 | F54: =H29 -> 1707.3469 | G54: =I29 -> 0 | H54: =J29 -> 0 | I54: =K29 -> 0 | J54: =L29 -> 0 | K54: =M29 -> 0 | L54: =N29 -> 0 | M54: =O29 -> 0 | ... Y54: =AA29 -> 1143.8328
B55: 6 | C55: 税后净现金流量（3-5） | D55: 万元 | E55: =E52-E54 -> -8075.102 | F55: =H30 -> 6241.0129 | G55: =G52-G54 -> 193.00171 | H55: =H52-H54 -> 323.32917 | I55: =I52-I54 -> 453.64227 | J55: =J52-J54 -> 583.94107 | K55: =K52-K54 -> -220.43694 | L55: =L52-L54 -> 919.55288 | M55: =M52-M54 -> 486.3809 | N55: =N52-N54 -> 598.33951 | ... Y55: =Y52-Y54 -> 12010.418
B56: 7 | C56: 累计税后净现金流量 | D56: 万元 | E56: =E55 -> -8075.102 | F56: =H31 -> -7349.897 | G56: =F56+G55 -> -7156.8953 | H56: =G56+H55 -> -6833.5661 | I56: =H56+I55 -> -6379.9239 | J56: =I56+J55 -> -5795.9828 | K56: =J56+K55 -> -6016.4197 | L56: =K56+L55 -> -5096.8669 | M56: =L56+M55 -> -4610.486 | N56: =M56+N55 -> -4012.1465 | ... Y56: =X56+Y55 -> 27831.57

Sheet 表7-利润表-全投资
B2: 利润表-全投资
B3: 序号 | C3: 项目 | D3: 合计 | E3: 单位 | F3: 建设期 | H3: 运营期
F4: 1 | G4: 2 | H4: 1 | I4: 2 | J4: 3 | K4: 4 | L4: 5 | M4: 6 | N4: 7 | O4: 8 | P4: 9 | Q4: 10 | R4: 11 | S4: 12 | T4: 13 | U4: 14 | V4: 15 | W4: 16 | X4: 17 | Y4: 18 | Z4: 19 | AA4: 20
B5: 1 | C5: 营业总收入 | D5: =SUM(F5:AA5) -> 373365.74 | E5: 万元 | H5: =SUM(H6:H7) -> 25177.721 | I5: =SUM(I6:I7) -> 17630.551 | J5: =SUM(J6:J7) -> 17630.551 | K5: =SUM(K6:K7) -> 17630.551 | L5: =SUM(L6:L7) -> 17630.551 | M5: =SUM(M6:M7) -> 17630.551 | N5: =SUM(N6:N7) -> 18573.947 | O5: =SUM(O6:O7) -> 18573.947 | ... AA5: =SUM(AA6:AA7) -> 18573.947
B6: 1.1 | C6: 营业收入 | D6: =SUM(F6:AA6) -> 373365.74 | E6: 万元 | H6: ='表4-收入税金表'!H5 -> 25177.721 | I6: ='表4-收入税金表'!I5 -> 17630.551 | J6: ='表4-收入税金表'!J5 -> 17630.551 | K6: ='表4-收入税金表'!K5 -> 17630.551 | L6: ='表4-收入税金表'!L5 -> 17630.551 | M6: ='表4-收入税金表'!M5 -> 17630.551 | N6: ='表4-收入税金表'!N5 -> 18573.947 | O6: ='表4-收入税金表'!O5 -> 18573.947 | ... AA6: ='表4-收入税金表'!AA5 -> 18573.947
B7: 1.2 | C7: 其他收入 | D7: =SUM(F7:AA7) -> 0 | E7: 万元 | H7: ='表4-收入税金表'!H10 -> 0 | I7: ='表4-收入税金表'!I10 -> 0 | J7: ='表4-收入税金表'!J10 -> 0 | K7: ='表4-收入税金表'!K10 -> 0 | L7: ='表4-收入税金表'!L10 -> 0 | M7: ='表4-收入税金表'!M10 -> 0 | N7: ='表4-收入税金表'!N10 -> 0 | O7: ='表4-收入税金表'!O10 -> 0 | ... AA7: ='表4-收入税金表'!AA10 -> 0
B8: 2 | C8: 营业总成本（全投资） | D8: =SUM(F8:AA8) -> 320155.26 | E8: 万元 | H8: ='表3-成本费用表'!H29 -> 16460.858 | I8: ='表3-成本费用表'!I29 -> 16456.394 | J8: ='表3-成本费用表'!J29 -> 16451.944 | K8: ='表3-成本费用表'!K29 -> 16447.506 | L8: ='表3-成本费用表'!L29 -> 16443.081 | M8: ='表3-成本费用表'!M29 -> 17265.803 | N8: ='表3-成本费用表'!N29 -> 17252.802 | O8: ='表3-成本费用表'!O29 -> 17239.847 | ... AA8: ='表3-成本费用表'!AA29 -> 13934.512
B9: 3 | C9: 营业税金及附加 | D9: =SUM(F9:AA9) -> 709.49645 | E9: 万元 | H9: ='表4-收入税金表'!H40+'表4-收入税金表'!H44 -> 0 | I9: ='表4-收入税金表'!I40+'表4-收入税金表'!I44 -> 0 | J9: ='表4-收入税金表'!J40+'表4-收入税金表'!J44 -> 0 | K9: ='表4-收入税金表'!K40+'表4-收入税金表'!K44 -> 0 | L9: ='表4-收入税金表'!L40+'表4-收入税金表'!L44 -> 0 | M9: ='表4-收入税金表'!M40+'表4-收入税金表'!M44 -> 0 | N9: ='表4-收入税金表'!N40+'表4-收入税金表'!N44 -> 0 | O9: ='表4-收入税金表'!O40+'表4-收入税金表'!O44 -> 52.100828 | ... AA9: ='表4-收入税金表'!AA40+'表4-收入税金表'!AA44 -> 56.103158
B10: 4 | C10: 营业外收入 | D10: =SUM(F10:AA10) -> 0 | E10: 万元 | H10: =SUM(H11:H12) -> 0 | I10: =SUM(I11:I12) -> 0 | J10: =SUM(J11:J12) -> 0 | K10: =SUM(K11:K12) -> 0 | L10: =SUM(L11:L12) -> 0 | M10: =SUM(M11:M12) -> 0 | N10: =SUM(N11:N12) -> 0 | O10: =SUM(O11:O12) -> 0 | ... AA10: =SUM(AA11:AA12) -> 0
B11: 4.1 | C11: 政府一次性运营补贴收入—递延收益 | D11: =SUM(F11:AA11) -> 0 | E11: 万元 | H11: ='表5-利润表-资本金'!H11 -> 0 | I11: ='表5-利润表-资本金'!I11 -> 0 | J11: ='表5-利润表-资本金'!J11 -> 0 | K11: ='表5-利润表-资本金'!K11 -> 0 | L11: ='表5-利润表-资本金'!L11 -> 0 | M11: ='表5-利润表-资本金'!M11 -> 0 | N11: ='表5-利润表-资本金'!N11 -> 0 | O11: ='表5-利润表-资本金'!O11 -> 0 | ... AA11: ='表5-利润表-资本金'!AA11 -> 0
B12: 4.2 | C12: 增值税即征即退收入 | D12: =SUM(F12:AA12) -> 0 | E12: 万元 | H12: ='表4-收入税金表'!H13 -> 0 | I12: ='表4-收入税金表'!I13 -> 0 | J12: ='表4-收入税金表'!J13 -> 0 | K12: ='表4-收入税金表'!K13 -> 0 | L12: ='表4-收入税金表'!L13 -> 0 | M12: ='表4-收入税金表'!M13 -> 0 | N12: ='表4-收入税金表'!N13 -> 0 | O12: ='表4-收入税金表'!O13 -> 0 | ... AA12: ='表4-收入税金表'!AA13 -> 0
B13: 5 | C13: 营业外支出 | D13: =SUM(F13:AA13) -> 0 | E13: 万元 | H13: ='表3-成本费用表'!H24 -> 0 | I13: ='表3-成本费用表'!I24 -> 0 | J13: ='表3-成本费用表'!J24 -> 0 | K13: ='表3-成本费用表'!K24 -> 0 | L13: ='表3-成本费用表'!L24 -> 0 | M13: ='表3-成本费用表'!M24 -> 0 | N13: ='表3-成本费用表'!N24 -> 0 | O13: ='表3-成本费用表'!O24 -> 0 | ... AA13: ='表3-成本费用表'!AA24 -> 0
B14: 6 | C14: 利润总额（1+4-2-3-5） | D14: =SUM(F14:AA14) -> 52500.983 | E14: 万元 | H14: =H5+H10-H8-H9-H13 -> 8716.8631 | I14: =I5+I10-I8-I9-I13 -> 1174.1566 | J14: =J5+J10-J8-J9-J13 -> 1178.6072 | K14: =K5+K10-K8-K9-K13 -> 1183.0451 | L14: =L5+L10-L8-L9-L13 -> 1187.4703 | M14: =M5+M10-M8-M9-M13 -> 364.74788 | N14: =N5+N10-N8-N9-N13 -> 1321.1455 | O14: =O5+O10-O8-O9-O13 -> 1281.9993 | ... AA14: =AA5+AA10-AA8-AA9-AA13 -> 4583.3321
B15: 7 | C15: 弥补以前年度亏损 | D15: =SUM(F15:AA15) -> 0 | E15: 万元 | H15: =SUM(H16:H20) -> 0 | I15: =SUM(I16:I20) -> 0 | J15: =SUM(J16:J20) -> 0 | K15: =SUM(K16:K20) -> 0 | L15: =SUM(L16:L20) -> 0 | M15: =SUM(M16:M20) -> 0 | N15: =SUM(N16:N20) -> 0 | O15: =SUM(O16:O20) -> 0 | ... AA15: =SUM(AA16:AA20) -> 0
C16: 弥补前序第一年亏损 | E16: 万元 | I16: =IF(H14>0,0,IF(I14<0,0,MIN(I14-SUM(I17:I20),-H14))) -> 0 | J16: =IF(I14>0,0,IF(J14<0,0,MIN(J14-SUM(J17:J20),-I14))) -> 0 | K16: =IF(J14>0,0,IF(K14<0,0,MIN(K14-SUM(K17:K20),-J14))) -> 0 | L16: =IF(K14>0,0,IF(L14<0,0,MIN(L14-SUM(L17:L20),-K14))) -> 0 | M16: =IF(L14>0,0,IF(M14<0,0,MIN(M14-SUM(M17:M20),-L14))) -> 0 | N16: =IF(M14>0,0,IF(N14<0,0,MIN(N14-SUM(N17:N20),-M14))) -> 0 | O16: =IF(N14>0,0,IF(O14<0,0,MIN(O14-SUM(O17:O20),-N14))) -> 0 | P16: =IF(O14>0,0,IF(P14<0,0,MIN(P14-SUM(P17:P20),-O14))) -> 0 | ... AA16: =IF(Z14>0,0,IF(AA14<0,0,MIN(AA14-SUM(AA17:AA20),-Z14))) -> 0
C17: 弥补前序第二年亏损 | E17: 万元 | J17: =IF(H14>0,0,IF(J14<0,0,MIN(J14-SUM(J18:J20),-H14-I16))) -> 0 | K17: =IF(I14>0,0,IF(K14<0,0,MIN(K14-SUM(K18:K20),-I14-J16))) -> 0 | L17: =IF(J14>0,0,IF(L14<0,0,MIN(L14-SUM(L18:L20),-J14-K16))) -> 0 | M17: =IF(K14>0,0,IF(M14<0,0,MIN(M14-SUM(M18:M20),-K14-L16))) -> 0 | N17: =IF(L14>0,0,IF(N14<0,0,MIN(N14-SUM(N18:N20),-L14-M16))) -> 0 | O17: =IF(M14>0,0,IF(O14<0,0,MIN(O14-SUM(O18:O20),-M14-N16))) -> 0 | P17: =IF(N14>0,0,IF(P14<0,0,MIN(P14-SUM(P18:P20),-N14-O16))) -> 0 | Q17: =IF(O14>0,0,IF(Q14<0,0,MIN(Q14-SUM(Q18:Q20),-O14-P16))) -> 0 | ... AA17: =IF(Y14>0,0,IF(AA14<0,0,MIN(AA14-SUM(AA18:AA20),-Y14-Z16))) -> 0
C18: 弥补前序第三年亏损 | E18: 万元 | K18: =IF(H14>0,0,IF(K14<0,0,MIN(K14-SUM(K19:K20),-H14-I16-J17))) -> 0 | L18: =IF(I14>0,0,IF(L14<0,0,MIN(L14-SUM(L19:L20),-I14-J16-K17))) -> 0 | M18: =IF(J14>0,0,IF(M14<0,0,MIN(M14-SUM(M19:M20),-J14-K16-L17))) -> 0 | N18: =IF(K14>0,0,IF(N14<0,0,MIN(N14-SUM(N19:N20),-K14-L16-M17))) -> 0 | O18: =IF(L14>0,0,IF(O14<0,0,MIN(O14-SUM(O19:O20),-L14-M16-N17))) -> 0 | P18: =IF(M14>0,0,IF(P14<0,0,MIN(P14-SUM(P19:P20),-M14-N16-O17))) -> 0 | Q18: =IF(N14>0,0,IF(Q14<0,0,MIN(Q14-SUM(Q19:Q20),-N14-O16-P17))) -> 0 | R18: =IF(O14>0,0,IF(R14<0,0,MIN(R14-SUM(R19:R20),-O14-P16-Q17))) -> 0 | ... AA18: =IF(X14>0,0,IF(AA14<0,0,MIN(AA14-SUM(AA19:AA20),-X14-Y16-Z17))) -> 0
C19: 弥补前序第四年亏损 | E19: 万元 | L19: =IF(H14>0,0,IF(L14<0,0,MIN(L14-L20,-H14-I16-J17-K18))) -> 0 | M19: =IF(I14>0,0,IF(M14<0,0,MIN(M14-M20,-I14-J16-K17-L18))) -> 0 | N19: =IF(J14>0,0,IF(N14<0,0,MIN(N14-N20,-J14-K16-L17-M18))) -> 0 | O19: =IF(K14>0,0,IF(O14<0,0,MIN(O14-O20,-K14-L16-M17-N18))) -> 0 | P19: =IF(L14>0,0,IF(P14<0,0,MIN(P14-P20,-L14-M16-N17-O18))) -> 0 | Q19: =IF(M14>0,0,IF(Q14<0,0,MIN(Q14-Q20,-M14-N16-O17-P18))) -> 0 | R19: =IF(N14>0,0,IF(R14<0,0,MIN(R14-R20,-N14-O16-P17-Q18))) -> 0 | S19: =IF(O14>0,0,IF(S14<0,0,MIN(S14-S20,-O14-P16-Q17-R18))) -> 0 | ... AA19: =IF(W14>0,0,IF(AA14<0,0,MIN(AA14-AA20,-W14-X16-Y17-Z18))) -> 0
C20: 弥补前序第五年亏损 | E20: 万元 | M20: =IF(H14>0,0,IF(M14<0,0,MIN(M14,-H14-I16-J17-K18-L19))) -> 0 | N20: =IF(I14>0,0,IF(N14<0,0,MIN(N14,-I14-J16-K17-L18-M19))) -> 0 | O20: =IF(J14>0,0,IF(O14<0,0,MIN(O14,-J14-K16-L17-M18-N19))) -> 0 | P20: =IF(K14>0,0,IF(P14<0,0,MIN(P14,-K14-L16-M17-N18-O19))) -> 0 | Q20: =IF(L14>0,0,IF(Q14<0,0,MIN(Q14,-L14-M16-N17-O18-P19))) -> 0 | R20: =IF(M14>0,0,IF(R14<0,0,MIN(R14,-M14-N16-O17-P18-Q19))) -> 0 | S20: =IF(N14>0,0,IF(S14<0,0,MIN(S14,-N14-O16-P17-Q18-R19))) -> 0 | T20: =IF(O14>0,0,IF(T14<0,0,MIN(T14,-O14-P16-Q17-R18-S19))) -> 0 | ... AA20: =IF(V14>0,0,IF(AA14<0,0,MIN(AA14,-V14-W16-X17-Y18-Z19))) -> 0
B21: 8 | C21: 应税所得额 | D21: =SUM(F21:AA21) -> 52500.983 | E21: 万元 | H21: =IF(H14-H15>0,H14-H15,0) -> 8716.8631 | I21: =IF(I14-I15>0,I14-I15,0) -> 1174.1566 | J21: =IF(J14-J15>0,J14-J15,0) -> 1178.6072 | K21: =IF(K14-K15>0,K14-K15,0) -> 1183.0451 | L21: =IF(L14-L15>0,L14-L15,0) -> 1187.4703 | M21: =IF(M14-M15>0,M14-M15,0) -> 364.74788 | N21: =IF(N14-N15>0,N14-N15,0) -> 1321.1455 | O21: =IF(O14-O15>0,O14-O15,0) -> 1281.9993 | ... AA21: =IF(AA14-AA15>0,AA14-AA15,0) -> 4583.3321
B22: 9 | C22: 调整所得税 | D22: =SUM(F22:AA22) -> 13125.246 | E22: 万元 | H22: =IF(参数输入表!$H$689="三免三减半",0,H21*参数输入表!$H$690) -> 2179.2158 | I22: =IF(参数输入表!$H$689="三免三减半",0,I21*参数输入表!$H$690) -> 293.53915 | J22: =IF(参数输入表!$H$689="三免三减半",0,J21*参数输入表!$H$690) -> 294.6518 | K22: =IF(参数输入表!$H$689="三免三减半",K21*参数输入表!$H$690/2,K21*参数输入表!$H$690) -> 295.76127 | L22: =IF(参数输入表!$H$689="三免三减半",L21*参数输入表!$H$690/2,L21*参数输入表!$H$690) -> 296.86757 | M22: =IF(参数输入表!$H$689="三免三减半",M21*参数输入表!$H$690/2,M21*参数输入表!$H$690) -> 91.186971 | N22: =N21*参数输入表!$H$690 -> 330.28636 | O22: =O21*参数输入表!$H$690 -> 320.49984 | P22: =P21*参数输入表!$H$690 -> 323.09223 | Q22: =Q21*参数输入表!$H$690 -> 326.26595 | R22: =R21*参数输入表!$H$690 -> 535.6019 | S22: =S21*参数输入表!$H$690 -> 531.34147 | T22: =T21*参数输入表!$H$690 -> 533.04324 | U22: =U21*参数输入表!$H$690 -> 536.17187 | ... AA22: =AA21*参数输入表!$H$690 -> 1145.833
B23: 10 | C23: 净利润（6-9） | D23: =SUM(F23:AA23) -> 39375.737 | E23: 万元 | H23: =H14-H22 -> 6537.6473 | I23: =I14-I22 -> 880.61746 | J23: =J14-J22 -> 883.9554 | K23: =K14-K22 -> 887.2838 | L23: =L14-L22 -> 890.60271 | M23: =M14-M22 -> 273.56091 | N23: =N14-N22 -> 990.85909 | O23: =O14-O22 -> 961.49951 | ... AA23: =AA14-AA22 -> 3437.4991
B24: 11 | C24: 期初未分配的利润 | D24: =SUM(F24:AA24) -> 0 | E24: 万元 | F24: 0 | G24: 0 | H24: =G32 -> 0 | I24: =H32 -> 0 | J24: =I32 -> 0 | K24: =J32 -> 0 | L24: =K32 -> 0 | M24: =L32 -> 0 | N24: =M32 -> 0 | O24: =N32 -> 0 | ... AA24: =Z32 -> 0
B25: 12 | C25: 可供分配的利润（10+11） | D25: =SUM(F25:AA25) -> 39375.737 | E25: 万元 | H25: =H23+H24 -> 6537.6473 | I25: =I23+I24 -> 880.61746 | J25: =J23+J24 -> 883.9554 | K25: =K23+K24 -> 887.2838 | L25: =L23+L24 -> 890.60271 | M25: =M23+M24 -> 273.56091 | N25: =N23+N24 -> 990.85909 | O25: =O23+O24 -> 961.49951 | ... AA25: =AA23+AA24 -> 3437.4991
B26: 13 | C26: 提取法定盈余公积金 | D26: =SUM(F26:AA26) -> 3937.5737 | E26: 万元 | H26: =IF(H25<=0,0,H25*参数输入表!$H$367) -> 653.76473 | I26: =IF(H28>=参数输入表!$H$366,0,IF(I25<0,0,IF(I25*参数输入表!$H$367>=I27,I27,I25*参数输入表!$H$367))) -> 88.061746 | J26: =IF(I28>=参数输入表!$H$366,0,IF(J25<0,0,IF(J25*参数输入表!$H$367>=J27,J27,J25*参数输入表!$H$367))) -> 88.39554 | K26: =IF(J28>=参数输入表!$H$366,0,IF(K25<0,0,IF(K25*参数输入表!$H$367>=K27,K27,K25*参数输入表!$H$367))) -> 88.72838 | L26: =IF(K28>=参数输入表!$H$366,0,IF(L25<0,0,IF(L25*参数输入表!$H$367>=L27,L27,L25*参数输入表!$H$367))) -> 89.060271 | M26: =IF(L28>=参数输入表!$H$366,0,IF(M25<0,0,IF(M25*参数输入表!$H$367>=M27,M27,M25*参数输入表!$H$367))) -> 27.356091 | N26: =IF(M28>=参数输入表!$H$366,0,IF(N25<0,0,IF(N25*参数输入表!$H$367>=N27,N27,N25*参数输入表!$H$367))) -> 99.085909 | O26: =IF(N28>=参数输入表!$H$366,0,IF(O25<0,0,IF(O25*参数输入表!$H$367>=O27,O27,O25*参数输入表!$H$367))) -> 96.149951 | P26: =IF(O28>=参数输入表!$H$366,0,IF(P25<0,0,IF(P25*参数输入表!$H$367>=P27,P27,P25*参数输入表!$H$367))) -> 96.927668 | ... AA26: =IF(Z28>=参数输入表!$H$366,0,IF(AA25<0,0,IF(AA25*参数输入表!$H$367>=AA27,AA27,AA25*参数输入表!$H$367))) -> 343.74991
C27: 期初法定盈余公积金上限缺口 | E27: 万元 | H27: =参数输入表!$H$366 -> 4037.551 | I27: =参数输入表!$H$366-H28 -> 3383.7863 | J27: =参数输入表!$H$366-I28 -> 3295.7245 | K27: =参数输入表!$H$366-J28 -> 3207.329 | L27: =参数输入表!$H$366-K28 -> 3118.6006 | M27: =参数输入表!$H$366-L28 -> 3029.5404 | N27: =参数输入表!$H$366-M28 -> 3002.1843 | O27: =参数输入表!$H$366-N28 -> 2903.0984 | P27: =参数输入表!$H$366-O28 -> 2806.9484 | ... AA27: =参数输入表!$H$366-Z28 -> 443.72722
C28: 期末法定盈余公积金累计 | E28: 万元 | H28: =H26 -> 653.76473 | I28: =I26+H28 -> 741.82647 | J28: =J26+I28 -> 830.22201 | K28: =K26+J28 -> 918.95039 | L28: =L26+K28 -> 1008.0107 | M28: =M26+L28 -> 1035.3668 | N28: =N26+M28 -> 1134.4527 | O28: =O26+N28 -> 1230.6026 | P28: =P26+O28 -> 1327.5303 | ... AA28: =AA26+Z28 -> 3937.5737
B29: 14 | C29: 可供投资者分配的利润（12-13） | D29: =SUM(F29:AA29) -> 35438.163 | E29: 万元 | H29: =H25-H26 -> 5883.8826 | I29: =I25-I26 -> 792.55571 | J29: =J25-J26 -> 795.55986 | K29: =K25-K26 -> 798.55542 | L29: =L25-L26 -> 801.54244 | M29: =M25-M26 -> 246.20482 | N29: =N25-N26 -> 891.77318 | O29: =O25-O26 -> 865.34955 | ... AA29: =AA25-AA26 -> 3093.7492
B30: 15 | C30: 提取任意盈余公积金 | D30: =SUM(F30:AA30) -> 0 | E30: 万元 | H30: =H29*参数输入表!$H$368 -> 0 | I30: =I29*参数输入表!$H$368 -> 0 | J30: =J29*参数输入表!$H$368 -> 0 | K30: =K29*参数输入表!$H$368 -> 0 | L30: =L29*参数输入表!$H$368 -> 0 | M30: =M29*参数输入表!$H$368 -> 0 | N30: =N29*参数输入表!$H$368 -> 0 | O30: =O29*参数输入表!$H$368 -> 0 | ... AA30: =AA29*参数输入表!$H$368 -> 0
B31: 16 | C31: 各投资方利润分配 | D31: =SUM(F31:AA31) -> 35438.163 | E31: 万元 | H31: =H29-H30 -> 5883.8826 | I31: =I29-I30 -> 792.55571 | J31: =J29-J30 -> 795.55986 | K31: =K29-K30 -> 798.55542 | L31: =L29-L30 -> 801.54244 | M31: =M29-M30 -> 246.20482 | N31: =N29-N30 -> 891.77318 | O31: =O29-O30 -> 865.34955 | ... AA31: =AA29-AA30 -> 3093.7492
B32: 17 | C32: 未分配利润（14-15-16） | D32: =SUM(F32:AA32) -> 0 | E32: 万元 | H32: =H29-H30-H31 -> 0 | I32: =I29-I30-I31 -> 0 | J32: =J29-J30-J31 -> 0 | K32: =K29-K30-K31 -> 0 | L32: =L29-L30-L31 -> 0 | M32: =M29-M30-M31 -> 0 | N32: =N29-N30-N31 -> 0 | O32: =O29-O30-O31 -> 0 | ... AA32: =AA29-AA30-AA31 -> 0
B33: 18 | C33: 息税前利润（利润总额+利息支出） | D33: =SUM(F33:AA33) -> 67696.799 | E33: 万元 | H33: =H14+'表1-资金筹措及还本付息表'!H93 -> 10604.339 | I33: =I14+'表1-资金筹措及还本付息表'!I93 -> 2936.3338 | J33: =J14+'表1-资金筹措及还本付息表'!J93 -> 2815.4861 | K33: =K14+'表1-资金筹措及还本付息表'!K93 -> 2694.6257 | L33: =L14+'表1-资金筹措及还本付息表'!L93 -> 2573.7526 | M33: =M14+'表1-资金筹措及还本付息表'!M93 -> 1625.7319 | N33: =N14+'表1-资金筹措及还本付息表'!N93 -> 2456.8312 | O33: =O14+'表1-资金筹措及还本付息表'!O93 -> 2292.3868 | ... AA33: =AA14+'表1-资金筹措及还本付息表'!AA93 -> 4591.3331
B34: 19 | C34: 息税折旧摊销前利润 | D34: =SUM(F34:AA34) -> 123099 | E34: 万元 | H34: =H33+'表2-折旧摊销表'!H52 -> 14375.35 | I34: =I33+'表2-折旧摊销表'!I52 -> 6707.3451 | J34: =J33+'表2-折旧摊销表'!J52 -> 6586.4973 | K34: =K33+'表2-折旧摊销表'!K52 -> 6465.6369 | L34: =L33+'表2-折旧摊销表'!L52 -> 6344.7638 | M34: =M33+'表2-折旧摊销表'!M52 -> 5396.7431 | N34: =N33+'表2-折旧摊销表'!N52 -> 6227.8424 | O34: =O33+'表2-折旧摊销表'!O52 -> 6063.398 | ... AA34: =AA33+'表2-折旧摊销表'!AA52 -> 5182.5019
C38: 标黄部分为相对固定模块，适用于所有项目
C39: 标蓝部分为计算中间过程，可不展示

Sheet 表8-现金流量表-全投资
B2: 现金流量表-全投资
B3: 序号 | C3: 项目 | D3: 合计 | E3: 单位 | F3: 建设期 | H3: 运营期
F4: 1 | G4: 2 | H4: 1 | I4: 2 | J4: 3 | K4: 4 | L4: 5 | M4: 6 | N4: 7 | O4: 8 | P4: 9 | Q4: 10 | R4: 11 | S4: 12 | T4: 13 | U4: 14 | V4: 15 | W4: 16 | X4: 17 | Y4: 18 | Z4: 19 | AA4: 20
B5: 1 | C5: 现金流入 | D5: =SUM(F5:AA5) -> 404022.13 | E5: 万元 | F5: =SUM(F6:F11) -> 0 | G5: =SUM(G6:G11) -> 0 | H5: =SUM(H6:H11) -> 26688.384 | I5: =SUM(I6:I11) -> 18688.384 | J5: =SUM(J6:J11) -> 18688.384 | K5: =SUM(K6:K11) -> 18688.384 | L5: =SUM(L6:L11) -> 18688.384 | M5: =SUM(M6:M11) -> 18688.384 | ... AA5: =SUM(AA6:AA11) -> 27942.835
B6: 1.1 | C6: 发电销售收入（含税） | D6: =SUM(F6:AA6) -> 395767.68 | E6: 万元 | H6: =('表4-收入税金表'!H6+'表4-收入税金表'!H18) -> 26688.384 | I6: =('表4-收入税金表'!I6+'表4-收入税金表'!I18) -> 18688.384 | J6: =('表4-收入税金表'!J6+'表4-收入税金表'!J18) -> 18688.384 | K6: =('表4-收入税金表'!K6+'表4-收入税金表'!K18) -> 18688.384 | L6: =('表4-收入税金表'!L6+'表4-收入税金表'!L18) -> 18688.384 | M6: =('表4-收入税金表'!M6+'表4-收入税金表'!M18) -> 18688.384 | N6: =('表4-收入税金表'!N6+'表4-收入税金表'!N18) -> 19688.384 | O6: =('表4-收入税金表'!O6+'表4-收入税金表'!O18) -> 19688.384 | ... AA6: =('表4-收入税金表'!AA6+'表4-收入税金表'!AA18) -> 19688.384
B7: 1.2 | C7: 其他收入 | D7: =SUM(F7:AA7) -> 0 | E7: 万元 | H7: =('表4-收入税金表'!H10+'表4-收入税金表'!H19) -> 0 | I7: =('表4-收入税金表'!I10+'表4-收入税金表'!I19) -> 0 | J7: =('表4-收入税金表'!J10+'表4-收入税金表'!J19) -> 0 | K7: =('表4-收入税金表'!K10+'表4-收入税金表'!K19) -> 0 | L7: =('表4-收入税金表'!L10+'表4-收入税金表'!L19) -> 0 | M7: =('表4-收入税金表'!M10+'表4-收入税金表'!M19) -> 0 | N7: =('表4-收入税金表'!N10+'表4-收入税金表'!N19) -> 0 | O7: =('表4-收入税金表'!O10+'表4-收入税金表'!O19) -> 0 | ... AA7: =('表4-收入税金表'!AA10+'表4-收入税金表'!AA19) -> 0
B8: 1.3 | C8: 政府一次性运营补贴收入 | D8: =SUM(F8:AA8) -> 0 | E8: 万元 | H8: =参数输入表!H318 -> 0
B9: 1.4 | C9: 回收固定资产余值 | D9: =SUM(F9:AA9) -> 7873.4512 | E9: 万元 | H9: 0 | I9: 0 | J9: 0 | K9: 0 | L9: 0 | M9: 0 | N9: 0 | O9: 0 | P9: 0 | Q9: 0 | R9: 0 | S9: 0 | T9: 0 | U9: 0 | V9: 0 | W9: 0 | X9: 0 | Y9: 0 | Z9: 0 | AA9: ='表6-现金流量表-资本金'!AA10 -> 7873.4512
B10: 1.5 | C10: 回收流动资金 | D10: =SUM(F10:AA10) -> 381 | E10: 万元 | AA10: =参数输入表!H351 -> 381
B11: 1.6 | C11: 增值税即征即退 | D11: =SUM(F11:AA11) -> 0 | E11: 万元 | H11: ='表4-收入税金表'!H13 -> 0 | I11: ='表4-收入税金表'!I13 -> 0 | J11: ='表4-收入税金表'!J13 -> 0 | K11: ='表4-收入税金表'!K13 -> 0 | L11: ='表4-收入税金表'!L13 -> 0 | M11: ='表4-收入税金表'!M13 -> 0 | N11: ='表4-收入税金表'!N13 -> 0 | O11: ='表4-收入税金表'!O13 -> 0 | ... AA11: ='表4-收入税金表'!AA13 -> 0
B12: 2 | C12: 现金流出 | D12: =SUM(F12:AA12) -> 349509.36 | E12: 万元 | F12: =SUM(F13:F19) -> 39167.034 | G12: =SUM(G13:G19) -> 26111.356 | H12: =SUM(H13:H19) -> 13539.297 | I12: =SUM(I13:I19) -> 13153.254 | J12: =SUM(J13:J19) -> 13148.224 | K12: =SUM(K13:K19) -> 13143.21 | L12: =SUM(L13:L19) -> 13138.209 | M12: =SUM(M13:M19) -> 14067.885 | ... AA12: =SUM(AA13:AA19) -> 14513.883
B13: 2.1 | C13: 建设投资 | D13: =SUM(F13:AA13) -> 65278.39 | E13: 万元 | F13: ='表1-资金筹措及还本付息表'!F7 -> 39167.034 | G13: ='表1-资金筹措及还本付息表'!G7 -> 26111.356
B14: 2.2 | C14: 流动资金 | D14: =SUM(F14:AA14) -> 381 | E14: 万元 | H14: =参数输入表!H351 -> 381
B15: 2.3 | C15: 生产经营支出（含税） | D15: =SUM(F15:AA15) -> 275545.51 | E15: 万元 | H15: ='表3-成本费用表'!H48+'表4-收入税金表'!H22 -> 13158.297 | I15: ='表3-成本费用表'!I48+'表4-收入税金表'!I22 -> 13153.254 | J15: ='表3-成本费用表'!J48+'表4-收入税金表'!J22 -> 13148.224 | K15: ='表3-成本费用表'!K48+'表4-收入税金表'!K22 -> 13143.21 | L15: ='表3-成本费用表'!L48+'表4-收入税金表'!L22 -> 13138.209 | M15: ='表3-成本费用表'!M48+'表4-收入税金表'!M22 -> 14067.885 | N15: ='表3-成本费用表'!N48+'表4-收入税金表'!N22 -> 14053.194 | O15: ='表3-成本费用表'!O48+'表4-收入税金表'!O22 -> 14038.555 | ... AA15: ='表3-成本费用表'!AA48+'表4-收入税金表'!AA22 -> 13896.748
B16: 2.4 | C16: 营业外支出 | D16: =SUM(F16:AA16) -> 0 | E16: 万元 | H16: ='表3-成本费用表'!H62 -> 0 | I16: ='表3-成本费用表'!I62 -> 0 | J16: ='表3-成本费用表'!J62 -> 0 | K16: ='表3-成本费用表'!K62 -> 0 | L16: ='表3-成本费用表'!L62 -> 0 | M16: ='表3-成本费用表'!M62 -> 0 | N16: ='表3-成本费用表'!N62 -> 0 | O16: ='表3-成本费用表'!O62 -> 0 | ... AA16: ='表3-成本费用表'!AA62 -> 0
B17: 2.5 | C17: 增值税缴纳 | D17: =SUM(F17:AA17) -> 7094.9645 | E17: 万元 | H17: ='表4-收入税金表'!H16 -> 0 | I17: ='表4-收入税金表'!I16 -> 0 | J17: ='表4-收入税金表'!J16 -> 0 | K17: ='表4-收入税金表'!K16 -> 0 | L17: ='表4-收入税金表'!L16 -> 0 | M17: ='表4-收入税金表'!M16 -> 0 | N17: ='表4-收入税金表'!N16 -> 0 | O17: ='表4-收入税金表'!O16 -> 521.00828 | ... AA17: ='表4-收入税金表'!AA16 -> 561.03158
B18: 2.6 | C18: 营业税金及附加 | D18: =SUM(F18:AA18) -> 709.49645 | E18: 万元 | H18: ='表4-收入税金表'!H40+'表4-收入税金表'!H44 -> 0 | I18: ='表4-收入税金表'!I40+'表4-收入税金表'!I44 -> 0 | J18: ='表4-收入税金表'!J40+'表4-收入税金表'!J44 -> 0 | K18: ='表4-收入税金表'!K40+'表4-收入税金表'!K44 -> 0 | L18: ='表4-收入税金表'!L40+'表4-收入税金表'!L44 -> 0 | M18: ='表4-收入税金表'!M40+'表4-收入税金表'!M44 -> 0 | N18: ='表4-收入税金表'!N40+'表4-收入税金表'!N44 -> 0 | O18: ='表4-收入税金表'!O40+'表4-收入税金表'!O44 -> 52.100828 | ... AA18: ='表4-收入税金表'!AA40+'表4-收入税金表'!AA44 -> 56.103158
B19: 2.7 | C19: 运营期资本性支出 | D19: =SUM(F19:AA19) -> 500 | E19: 万元 | H19: =参数输入表!H656 -> 0 | I19: =参数输入表!H657 -> 0 | J19: =参数输入表!H658 -> 0 | K19: =参数输入表!H659 -> 0 | L19: =参数输入表!H660 -> 0 | M19: =参数输入表!H661 -> 0 | N19: =参数输入表!H662 -> 0 | O19: =参数输入表!H663 -> 0 | P19: =参数输入表!H664 -> 0 | Q19: =参数输入表!H665 -> 0 | R19: =参数输入表!H666 -> 0 | S19: =参数输入表!H667 -> 500 | T19: =参数输入表!H668 -> 0 | U19: =参数输入表!H669 -> 0 | V19: =参数输入表!H670 -> 0 | W19: =参数输入表!H671 -> 0 | X19: =参数输入表!H672 -> 0 | Y19: =参数输入表!H673 -> 0 | Z19: =参数输入表!H674 -> 0 | AA19: =参数输入表!H675 -> 0
B20: 3 | C20: 税前净现金流量（1-2） | D20: =SUM(F20:AA20) -> 54512.775 | E20: 万元 | F20: =F5-F12 -> -39167.034 | G20: =G5-G12 -> -26111.356 | H20: =H5-H12 -> 13149.087 | I20: =I5-I12 -> 5535.1304 | J20: =J5-J12 -> 5540.1596 | K20: =K5-K12 -> 5545.1744 | L20: =L5-L12 -> 5550.1749 | M20: =M5-M12 -> 4620.4986 | ... AA20: =AA5-AA12 -> 13428.952
B21: 4 | C21: 累计税前净现金流量 | E21: 万元 | F21: =F20 -> -39167.034 | G21: =IF('表1-资金筹措及还本付息表'!G5>0,F21+G20,0) -> -65278.39 | H21: =IF('表1-资金筹措及还本付息表'!G5>0,G21+H20,H20+F21) -> -52129.303 | I21: =H21+I20 -> -46594.173 | J21: =I21+J20 -> -41054.013 | K21: =J21+K20 -> -35508.839 | L21: =K21+L20 -> -29958.664 | M21: =L21+M20 -> -25338.165 | N21: =M21+N20 -> -19702.975 | O21: =N21+O20 -> -14626.255 | P21: =O21+P20 -> -9562.8753 | ... AA21: =Z21+AA20 -> 54512.775
B22: 5 | C22: 调整所得税 | D22: =SUM(F22:AA22) -> 13125.246 | E22: 万元 | H22: ='表7-利润表-全投资'!H22 -> 2179.2158 | I22: ='表7-利润表-全投资'!I22 -> 293.53915 | J22: ='表7-利润表-全投资'!J22 -> 294.6518 | K22: ='表7-利润表-全投资'!K22 -> 295.76127 | L22: ='表7-利润表-全投资'!L22 -> 296.86757 | M22: ='表7-利润表-全投资'!M22 -> 91.186971 | N22: ='表7-利润表-全投资'!N22 -> 330.28636 | O22: ='表7-利润表-全投资'!O22 -> 320.49984 | ... AA22: ='表7-利润表-全投资'!AA22 -> 1145.833
B23: 6 | C23: 税后净现金流量（3-5） | D23: =SUM(F23:AA23) -> 41387.53 | E23: 万元 | F23: =F20-F22 -> -39167.034 | G23: =G20-G22 -> -26111.356 | H23: =H20-H22 -> 10969.871 | I23: =I20-I22 -> 5241.5913 | J23: =J20-J22 -> 5245.5078 | K23: =K20-K22 -> 5249.4131 | L23: =L20-L22 -> 5253.3073 | M23: =M20-M22 -> 4529.3116 | ... AA23: =AA20-AA22 -> 12283.119
B24: 7 | C24: 累计税后净现金流量 | E24: 万元 | F24: =F23 -> -39167.034 | G24: =IF('表1-资金筹措及还本付息表'!G5>0,F24+G23,0) -> -65278.39 | H24: =IF('表1-资金筹措及还本付息表'!G5>0,G24+H23,F24+H23) -> -54308.519 | I24: =H24+I23 -> -49066.928 | J24: =I24+J23 -> -43821.42 | K24: =J24+K23 -> -38572.007 | L24: =K24+L23 -> -33318.699 | M24: =L24+M23 -> -28789.388 | N24: =M24+N23 -> -23484.484 | O24: =N24+O23 -> -18728.264 | P24: =O24+P23 -> -13987.976 | ... AA24: =Z24+AA23 -> 41387.53
C26: 全投资内部收益率（税前） | D26: =IF('表1-资金筹措及还本付息表'!G5=0,IRR(E44:Y44),IRR(F20:AA20)) -> 0.064079986
C27: 全投资内部收益率（税后） | D27: =IF('表1-资金筹措及还本付息表'!G5=0,IRR(E47:Y47),IRR(F23:AA23)) -> 0.051015872
C28: 投资回收期(税后) | D28: =SUM(F28:AA28)+2 -> 14.134043 | E28: 年 | F28: 0 | G28: 0 | H28: 0 | I28: =IF(I24/H24<0,H4+ABS(H24/I23),0) -> 0 | J28: =IF(J24/I24<0,I4+ABS(I24/J23),0) -> 0 | K28: =IF(K24/J24<0,J4+ABS(J24/K23),0) -> 0 | L28: =IF(L24/K24<0,K4+ABS(K24/L23),0) -> 0 | M28: =IF(M24/L24<0,L4+ABS(L24/M23),0) -> 0 | N28: =IF(N24/M24<0,M4+ABS(M24/N23),0) -> 0 | O28: =IF(O24/N24<0,N4+ABS(N24/O23),0) -> 0 | P28: =IF(P24/O24<0,O4+ABS(O24/P23),0) -> 0 | ... AA28: =IF(AA24/Z24<0,Z4+ABS(Z24/AA23),0) -> 0
C29: 投资回收期(税前) | D29: =SUM(F29:AA29)+2 -> 12.887416 | E29: 年 | F29: 0 | G29: 0 | H29: 0 | I29: =IF(I21/H21<0,H4+ABS(H21/I20),0) -> 0 | J29: =IF(J21/I21<0,I4+ABS(I21/J20),0) -> 0 | K29: =IF(K21/J21<0,J4+ABS(J21/K20),0) -> 0 | L29: =IF(L21/K21<0,K4+ABS(K21/L20),0) -> 0 | M29: =IF(M21/L21<0,L4+ABS(L21/M20),0) -> 0 | N29: =IF(N21/M21<0,M4+ABS(M21/N20),0) -> 0 | O29: =IF(O21/N21<0,N4+ABS(N21/O20),0) -> 0 | P29: =IF(P21/O21<0,O4+ABS(O21/P20),0) -> 0 | ... AA29: =IF(AA21/Z21<0,Z4+ABS(Z21/AA20),0) -> 0
C30: 标黄部分为相对固定模块，适用于所有项目
C31: 现金流量表中各年的发电补贴收入数据引用参数表中输入的实发数据
C32: 政府一次性运营补贴收入，在运营期第1年引用参数表中政府一次性补贴总额
C35: Check | D35: =D23-'表7-利润表-全投资'!D23 -> 2011.7923
B38: 建设期为1年时，IRR计算要利用下面的公式计算
B42: 序号 | C42: 项目 | D42: 单位 | E42: 建设期 | F42: 运营期
E43: 1 | F43: 1 | G43: 2 | H43: 3 | I43: 4 | J43: 5 | K43: 6 | L43: 7 | M43: 8 | N43: 9 | O43: 10 | P43: 11 | Q43: 12 | R43: 13 | S43: 14 | T43: 15 | U43: 16 | V43: 17 | W43: 18 | X43: 19 | Y43: 20
B44: 3 | C44: 税前净现金流量（1-2） | D44: 万元 | E44: =F20 -> -39167.034 | F44: =H20 -> 13149.087 | G44: =I20 -> 5535.1304 | H44: =J20 -> 5540.1596 | I44: =K20 -> 5545.1744 | J44: =L20 -> 5550.1749 | K44: =M20 -> 4620.4986 | L44: =N20 -> 5635.1901 | M44: =O20 -> 5076.7198 | ... Y44: =AA20 -> 13428.952
B45: 4 | C45: 累计税前净现金流量 | D45: 万元 | E45: =F21 -> -39167.034 | F45: =H21 -> -52129.303 | G45: =F45+G44 -> -46594.173 | H45: =G45+H44 -> -41054.013 | I45: =H45+I44 -> -35508.839 | J45: =I45+J44 -> -29958.664 | K45: =J45+K44 -> -25338.165 | L45: =K45+L44 -> -19702.975 | M45: =L45+M44 -> -14626.255 | N45: =M45+N44 -> -9562.8753 | ... Y45: =X45+Y44 -> 54512.775
B46: 5 | C46: 调整所得税 | D46: 万元 | E46: =F22 -> 0 | F46: =H22 -> 2179.2158 | G46: =I22 -> 293.53915 | H46: =J22 -> 294.6518 | I46: =K22 -> 295.76127 | J46: =L22 -> 296.86757 | K46: =M22 -> 91.186971 | L46: =N22 -> 330.28636 | M46: =O22 -> 320.49984 | ... Y46: =AA22 -> 1145.833
B47: 6 | C47: 税后净现金流量（3-5） | D47: 万元 | E47: =F23 -> -39167.034 | F47: =H23 -> 10969.871 | G47: =I23 -> 5241.5913 | H47: =J23 -> 5245.5078 | I47: =K23 -> 5249.4131 | J47: =L23 -> 5253.3073 | K47: =M23 -> 4529.3116 | L47: =N23 -> 5304.9037 | M47: =O23 -> 4756.22 | ... Y47: =AA23 -> 12283.119
B48: 7 | C48: 累计税后净现金流量 | D48: 万元 | E48: =F24 -> -39167.034 | F48: =H24 -> -54308.519 | G48: =I24 -> -49066.928 | H48: =J24 -> -43821.42 | I48: =K24 -> -38572.007 | J48: =L24 -> -33318.699 | K48: =M24 -> -28789.388 | L48: =N24 -> -23484.484 | M48: =O24 -> -18728.264 | ... Y48: =AA24 -> 41387.53

Sheet 表9-现金流量表-财务计划
B2: 现金流量表-财务计划
B3: 序号 | C3: 项目 | D3: 合计 | E3: 单位 | F3: 建设期 | H3: 运营期
F4: 1 | G4: 2 | H4: 1 | I4: 2 | J4: 3 | K4: 4 | L4: 5 | M4: 6 | N4: 7 | O4: 8 | P4: 9 | Q4: 10 | R4: 11 | S4: 12 | T4: 13 | U4: 14 | V4: 15 | W4: 16 | X4: 17 | Y4: 18 | Z4: 19 | AA4: 20
B5: 1 | C5: 经营活动净现金流量（1.1-1.2） | D5: =SUM(F5:AA5) -> 102944.12 | E5: 万元 | F5: =F6-F12 -> 0 | G5: =G6-G12 -> 0 | H5: =H6-H12 -> 11822.74 | I5: =I6-I12 -> 5535.1304 | J5: =J6-J12 -> 5540.1596 | K5: =K6-K12 -> 5545.1744 | L5: =L6-L12 -> 5550.1749 | M5: =M6-M12 -> 4620.4986 | ... AA5: =AA6-AA12 -> 4030.6681
B6: 1.1 | C6: 现金流入 | D6: =SUM(F6:AA6) -> 395767.68 | E6: 万元 | F6: =SUM(F7:F11) -> 0 | G6: =SUM(G7:G11) -> 0 | H6: =SUM(H7:H11) -> 26688.384 | I6: =SUM(I7:I11) -> 18688.384 | J6: =SUM(J7:J11) -> 18688.384 | K6: =SUM(K7:K11) -> 18688.384 | L6: =SUM(L7:L11) -> 18688.384 | M6: =SUM(M7:M11) -> 18688.384 | ... AA6: =SUM(AA7:AA11) -> 19688.384
C7: 销售收入（含税） | D7: =SUM(F7:AA7) -> 395767.68 | E7: 万元 | H7: ='表6-现金流量表-资本金'!H7 -> 26688.384 | I7: ='表6-现金流量表-资本金'!I7 -> 18688.384 | J7: ='表6-现金流量表-资本金'!J7 -> 18688.384 | K7: ='表6-现金流量表-资本金'!K7 -> 18688.384 | L7: ='表6-现金流量表-资本金'!L7 -> 18688.384 | M7: ='表6-现金流量表-资本金'!M7 -> 18688.384 | N7: ='表6-现金流量表-资本金'!N7 -> 19688.384 | O7: ='表6-现金流量表-资本金'!O7 -> 19688.384 | ... AA7: ='表6-现金流量表-资本金'!AA7 -> 19688.384
C8: 其他收入 | D8: =SUM(F8:AA8) -> 0 | E8: 万元 | H8: ='表6-现金流量表-资本金'!H8 -> 0 | I8: ='表6-现金流量表-资本金'!I8 -> 0 | J8: ='表6-现金流量表-资本金'!J8 -> 0 | K8: ='表6-现金流量表-资本金'!K8 -> 0 | L8: ='表6-现金流量表-资本金'!L8 -> 0 | M8: ='表6-现金流量表-资本金'!M8 -> 0 | N8: ='表6-现金流量表-资本金'!N8 -> 0 | O8: ='表6-现金流量表-资本金'!O8 -> 0 | ... AA8: ='表6-现金流量表-资本金'!AA8 -> 0
C9: 回收流动资金 | D9: =SUM(F9:AA9) -> 0 | E9: 万元 | AB9: 删除
C10: 政府一次性运营补贴收入 | D10: =SUM(F10:AA10) -> 0 | E10: 万元 | H10: =参数输入表!H318 -> 0
C11: 增值税即征即退 | D11: =SUM(F11:AA11) -> 0 | E11: 万元 | H11: ='表4-收入税金表'!H13 -> 0 | I11: ='表4-收入税金表'!I13 -> 0 | J11: ='表4-收入税金表'!J13 -> 0 | K11: ='表4-收入税金表'!K13 -> 0 | L11: ='表4-收入税金表'!L13 -> 0 | M11: ='表4-收入税金表'!M13 -> 0 | N11: ='表4-收入税金表'!N13 -> 0 | O11: ='表4-收入税金表'!O13 -> 0 | ... AA11: ='表4-收入税金表'!AA13 -> 0
B12: 1.2 | C12: 现金流出 | D12: =SUM(F12:AA12) -> 292823.56 | E12: 万元 | F12: =SUM(F13:F16) -> 0 | G12: =SUM(G13:G16) -> 0 | H12: =SUM(H13:H16) -> 14865.644 | I12: =SUM(I13:I16) -> 13153.254 | J12: =SUM(J13:J16) -> 13148.224 | K12: =SUM(K13:K16) -> 13143.21 | L12: =SUM(L13:L16) -> 13138.209 | M12: =SUM(M13:M16) -> 14067.885 | ... AA12: =SUM(AA13:AA16) -> 15657.716
C13: 生产经营支出(含税) | D13: =SUM(F13:AA13) -> 275545.51 | E13: 万元 | H13: ='表3-成本费用表'!H48+'表4-收入税金表'!H28 -> 13158.297 | I13: ='表3-成本费用表'!I48+'表4-收入税金表'!I28 -> 13153.254 | J13: ='表3-成本费用表'!J48+'表4-收入税金表'!J28 -> 13148.224 | K13: ='表3-成本费用表'!K48+'表4-收入税金表'!K28 -> 13143.21 | L13: ='表3-成本费用表'!L48+'表4-收入税金表'!L28 -> 13138.209 | M13: ='表3-成本费用表'!M48+'表4-收入税金表'!M28 -> 14067.885 | N13: ='表3-成本费用表'!N48+'表4-收入税金表'!N28 -> 14053.194 | O13: ='表3-成本费用表'!O48+'表4-收入税金表'!O28 -> 14038.555 | ... AA13: ='表3-成本费用表'!AA48+'表4-收入税金表'!AA28 -> 13896.748
C14: 增值税实缴 | D14: =SUM(F14:AA14) -> 7094.9645 | E14: 万元 | H14: ='表4-收入税金表'!H16 -> 0 | I14: ='表4-收入税金表'!I16 -> 0 | J14: ='表4-收入税金表'!J16 -> 0 | K14: ='表4-收入税金表'!K16 -> 0 | L14: ='表4-收入税金表'!L16 -> 0 | M14: ='表4-收入税金表'!M16 -> 0 | N14: ='表4-收入税金表'!N16 -> 0 | O14: ='表4-收入税金表'!O16 -> 521.00828 | ... AA14: ='表4-收入税金表'!AA16 -> 561.03158
C15: 税金及附加税 | D15: =SUM(F15:AA15) -> 709.49645 | E15: 万元 | H15: ='表4-收入税金表'!H40+'表4-收入税金表'!H44 -> 0 | I15: ='表4-收入税金表'!I40+'表4-收入税金表'!I44 -> 0 | J15: ='表4-收入税金表'!J40+'表4-收入税金表'!J44 -> 0 | K15: ='表4-收入税金表'!K40+'表4-收入税金表'!K44 -> 0 | L15: ='表4-收入税金表'!L40+'表4-收入税金表'!L44 -> 0 | M15: ='表4-收入税金表'!M40+'表4-收入税金表'!M44 -> 0 | N15: ='表4-收入税金表'!N40+'表4-收入税金表'!N44 -> 0 | O15: ='表4-收入税金表'!O40+'表4-收入税金表'!O44 -> 52.100828 | ... AA15: ='表4-收入税金表'!AA40+'表4-收入税金表'!AA44 -> 56.103158
C16: 企业所得税 | D16: =SUM(F16:AA16) -> 9473.5968 | E16: 万元 | H16: ='表5-利润表-资本金'!H22 -> 1707.3469 | I16: ='表5-利润表-资本金'!I22 -> 0 | J16: ='表5-利润表-资本金'!J22 -> 0 | K16: ='表5-利润表-资本金'!K22 -> 0 | L16: ='表5-利润表-资本金'!L22 -> 0 | M16: ='表5-利润表-资本金'!M22 -> 0 | N16: ='表5-利润表-资本金'!N22 -> 0 | O16: ='表5-利润表-资本金'!O22 -> 0 | ... AA16: ='表5-利润表-资本金'!AA22 -> 1143.8328
B17: 2 | C17: 投资活动净现金流量（2.1-2.2） | D17: =SUM(F17:AA17) -> -66159.39 | E17: 万元 | F17: =F18-F19 -> -39167.034 | G17: =G18-G19 -> -26111.356 | H17: =H18-H19 -> -381 | I17: =I18-I19 -> 0 | J17: =J18-J19 -> 0 | K17: =K18-K19 -> 0 | L17: =L18-L19 -> 0 | M17: =M18-M19 -> 0 | ... AA17: =AA18-AA19 -> 0
B18: 2.1 | C18: 现金流入 | D18: =SUM(F18:AA18) -> 0 | E18: 万元 | F18: 0 | G18: 0 | H18: 0 | I18: 0 | J18: 0 | K18: 0 | L18: 0 | M18: 0 | N18: 0 | O18: 0 | P18: 0 | Q18: 0 | R18: 0 | S18: 0 | T18: 0 | U18: 0 | V18: 0 | W18: 0 | X18: 0 | Y18: 0 | Z18: 0 | AA18: 0
B19: 2.2 | C19: 现金流出 | D19: =SUM(F19:AA19) -> 66159.39 | E19: 万元 | F19: =SUM(F20:F22) -> 39167.034 | G19: =SUM(G20:G22) -> 26111.356 | H19: =SUM(H20:H22) -> 381 | I19: =SUM(I20:I22) -> 0 | J19: =SUM(J20:J22) -> 0 | K19: =SUM(K20:K22) -> 0 | L19: =SUM(L20:L22) -> 0 | M19: =SUM(M20:M22) -> 0 | ... AA19: =SUM(AA20:AA22) -> 0
C20: 建设投资 | D20: =SUM(F20:AA20) -> 65278.39 | E20: 万元 | F20: ='表1-资金筹措及还本付息表'!F7 -> 39167.034 | G20: ='表1-资金筹措及还本付息表'!G7 -> 26111.356
C21: 流动资金 | D21: =SUM(F21:AA21) -> 381 | E21: 万元 | H21: =参数输入表!H351 -> 381
C22: 运营期资本性支出 | D22: =SUM(F22:AA22) -> 500 | E22: 万元 | H22: =参数输入表!H656 -> 0 | I22: =参数输入表!H657 -> 0 | J22: =参数输入表!H658 -> 0 | K22: =参数输入表!H659 -> 0 | L22: =参数输入表!H660 -> 0 | M22: =参数输入表!H661 -> 0 | N22: =参数输入表!H662 -> 0 | O22: =参数输入表!H663 -> 0 | P22: =参数输入表!H664 -> 0 | Q22: =参数输入表!H665 -> 0 | R22: =参数输入表!H666 -> 0 | S22: =参数输入表!H667 -> 500 | T22: =参数输入表!H668 -> 0 | U22: =参数输入表!H669 -> 0 | V22: =参数输入表!H670 -> 0 | W22: =参数输入表!H671 -> 0 | X22: =参数输入表!H672 -> 0 | Y22: =参数输入表!H673 -> 0 | Z22: =参数输入表!H674 -> 0 | AA22: =参数输入表!H675 -> 0
B23: 3 | C23: 筹资活动净现金流量（3.1-3.2） | D23: =SUM(F23:AA23) -> -14161.277 | E23: 万元 | F23: =F24-F29 -> 39167.034 | G23: =G24-G29 -> 26111.356 | H23: =H24-H29 -> -5547.4107 | I23: =I24-I29 -> -5704.0922 | J23: =J24-J29 -> -5501.3531 | K23: =K24-K29 -> -5318.0343 | L23: =L24-L29 -> -5152.1927 | M23: =M24-M29 -> -4927.6372 | ... AA23: =AA24-AA29 -> -1894.4343
B24: 3.1 | C24: 现金流入 | D24: =SUM(F24:AA24) -> 67671.182 | E24: 万元 | F24: =SUM(F25:F28) -> 39711.143 | G24: =SUM(G25:G28) -> 27579.04 | H24: =SUM(H25:H28) -> 381 | I24: =SUM(I25:I28) -> 0 | J24: =SUM(J25:J28) -> 0 | K24: =SUM(K25:K28) -> 0 | L24: =SUM(L25:L28) -> 0 | M24: =SUM(M25:M28) -> 0 | ... AA24: =SUM(AA25:AA28) -> 0
C25: 项目资本金投入 | D25: =SUM(F25:AA25) -> 13705.21 | E25: 万元 | F25: ='表1-资金筹措及还本付息表'!F11 -> 8075.102 | G25: ='表1-资金筹措及还本付息表'!G11 -> 5515.8079 | H25: ='表1-资金筹措及还本付息表'!H11 -> 114.3
C26: 长期借款 | D26: =SUM(F26:AA26) -> 53699.272 | E26: 万元 | F26: ='表1-资金筹措及还本付息表'!F40 -> 31636.041 | G26: ='表1-资金筹措及还本付息表'!G40 -> 22063.232 | H26: ='表1-资金筹措及还本付息表'!H40 -> 0 | I26: ='表1-资金筹措及还本付息表'!I40 -> 0 | J26: ='表1-资金筹措及还本付息表'!J40 -> 0 | K26: ='表1-资金筹措及还本付息表'!K40 -> 0 | L26: ='表1-资金筹措及还本付息表'!L40 -> 0 | M26: ='表1-资金筹措及还本付息表'!M40 -> 0 | ... AA26: ='表1-资金筹措及还本付息表'!AA40 -> 0
C27: 流动资金借款 | D27: =SUM(F27:AA27) -> 266.7 | E27: 万元 | F27: ='表1-资金筹措及还本付息表'!F60 -> 0 | G27: ='表1-资金筹措及还本付息表'!G60 -> 0 | H27: ='表1-资金筹措及还本付息表'!H60 -> 266.7 | I27: ='表1-资金筹措及还本付息表'!I60 -> 0 | J27: ='表1-资金筹措及还本付息表'!J60 -> 0 | K27: ='表1-资金筹措及还本付息表'!K60 -> 0 | L27: ='表1-资金筹措及还本付息表'!L60 -> 0 | M27: ='表1-资金筹措及还本付息表'!M60 -> 0 | ... AA27: ='表1-资金筹措及还本付息表'!AA60 -> 0
C28: 短期借款 | D28: =SUM(F28:AA28) -> 0 | E28: 万元 | F28: ='表1-资金筹措及还本付息表'!F70 -> 0 | G28: ='表1-资金筹措及还本付息表'!G70 -> 0 | H28: =H42 -> 0 | I28: =I42 -> 0 | J28: =J42 -> 0 | K28: =K42 -> 0 | L28: =L42 -> 0 | M28: =M42 -> 0 | N28: =N42 -> 0 | O28: =O42 -> 0 | ... AA28: =AA42 -> 0
B29: 3.2 | C29: 现金流出 | D29: =SUM(F29:AA29) -> 81832.46 | E29: 万元 | F29: =SUM(F30:F32) -> 544.10881 | G29: =SUM(G30:G32) -> 1467.6835 | H29: =SUM(H30:H32) -> 5928.4107 | I29: =SUM(I30:I32) -> 5704.0922 | J29: =SUM(J30:J32) -> 5501.3531 | K29: =SUM(K30:K32) -> 5318.0343 | L29: =SUM(L30:L32) -> 5152.1927 | M29: =SUM(M30:M32) -> 4927.6372 | ... AA29: =SUM(AA30:AA32) -> 1894.4343
C30: 偿还债务本金 | D30: =SUM(F30:AA30) -> 53965.972 | E30: 万元 | H30: ='表1-资金筹措及还本付息表'!H92 -> 3579.9515 | I30: ='表1-资金筹措及还本付息表'!I92 -> 3579.9515 | J30: ='表1-资金筹措及还本付息表'!J92 -> 3579.9515 | K30: ='表1-资金筹措及还本付息表'!K92 -> 3579.9515 | L30: ='表1-资金筹措及还本付息表'!L92 -> 3579.9515 | M30: ='表1-资金筹措及还本付息表'!M92 -> 3579.9515 | N30: ='表1-资金筹措及还本付息表'!N92 -> 3579.9515 | O30: ='表1-资金筹措及还本付息表'!O92 -> 3579.9515 | ... AA30: ='表1-资金筹措及还本付息表'!AA92 -> 266.7
C31: 各种利息支出 | D31: =SUM(F31:AA31) -> 17207.609 | E31: 万元 | F31: ='表1-资金筹措及还本付息表'!F8 -> 544.10881 | G31: ='表1-资金筹措及还本付息表'!G17 -> 1467.6835 | H31: ='表1-资金筹措及还本付息表'!H93 -> 1887.4755 | I31: ='表1-资金筹措及还本付息表'!I93 -> 1762.1772 | J31: ='表1-资金筹措及还本付息表'!J93 -> 1636.8789 | K31: ='表1-资金筹措及还本付息表'!K93 -> 1511.5806 | L31: ='表1-资金筹措及还本付息表'!L93 -> 1386.2823 | M31: ='表1-资金筹措及还本付息表'!M93 -> 1260.984 | N31: ='表1-资金筹措及还本付息表'!N93 -> 1135.6857 | O31: ='表1-资金筹措及还本付息表'!O93 -> 1010.3874 | ... AA31: ='表1-资金筹措及还本付息表'!AA93 -> 8.001
C32: 应付利润（股利分配） | D32: =SUM(F32:AA32) -> 10658.879 | E32: 万元 | H32: ='表5-利润表-资本金'!H31 -> 460.98366 | I32: ='表5-利润表-资本金'!I31 -> 361.96344 | J32: ='表5-利润表-资本金'!J31 -> 284.52264 | K32: ='表5-利润表-资本金'!K31 -> 226.50217 | L32: ='表5-利润表-资本金'!L31 -> 185.95887 | M32: ='表5-利润表-资本金'!M31 -> 86.701732 | N32: ='表5-利润表-资本金'!N31 -> 96.577532 | O32: ='表5-利润表-资本金'!O31 -> 114.08097 | ... AA32: ='表5-利润表-资本金'!AA31 -> 1619.7333
B33: 四 | C33: 项目公司账面净现金流量（1+2+3） | D33: =SUM(F33:AA33) -> 22623.45 | E33: 万元 | F33: =F5+F17+F23 -> 0 | G33: =G5+G17+G23 -> 0 | H33: =H5+H17+H23 -> 5894.3293 | I33: =I5+I17+I23 -> -168.96173 | J33: =J5+J17+J23 -> 38.806538 | K33: =K5+K17+K23 -> 227.1401 | L33: =L5+L17+L23 -> 397.9822 | M33: =M5+M17+M23 -> -307.13867 | ... AA33: =AA5+AA17+AA23 -> 2136.2338
B34: 五 | C34: 累计盈余资金 | E34: 万元 | F34: =F33 -> 0 | G34: =F34+G33 -> 0 | H34: =G34+H33 -> 5894.3293 | I34: =H34+I33 -> 5725.3675 | J34: =I34+J33 -> 5764.1741 | K34: =J34+K33 -> 5991.3142 | L34: =K34+L33 -> 6389.2964 | M34: =L34+M33 -> 6082.1577 | N34: =M34+N33 -> 6905.133 | ... AA34: =Z34+AA33 -> 22623.45
C41: 不含短期借款的累计盈余资金 | H41: =H5+H17+(H25+H27-H30-H32-H31) -> 5894.3293 | I41: =I5+I17+(I25+I27-I30-I32-I31+'表3-成本费用表'!I23)+H34 -> 5725.3675 | J41: =J5+J17+(J25+J27-J30-J32-J31+'表3-成本费用表'!J23)+I34 -> 5764.1741 | K41: =K5+K17+(K25+K27-K30-K32-K31+'表3-成本费用表'!K23)+J34 -> 5991.3142 | L41: =L5+L17+(L25+L27-L30-L32-L31+'表3-成本费用表'!L23)+K34 -> 6389.2964 | M41: =M5+M17+(M25+M27-M30-M32-M31+'表3-成本费用表'!M23)+L34 -> 6082.1577 | N41: =N5+N17+(N25+N27-N30-N32-N31+'表3-成本费用表'!N23)+M34 -> 6905.133 | O41: =O5+O17+(O25+O27-O30-O32-O31+'表3-成本费用表'!O23)+N34 -> 7277.433 | P41: =P5+P17+(P25+P27-P30-P32-P31+'表3-成本费用表'!P23)+O34 -> 7732.3716 | ... AA41: =AA5+AA17+(AA25+AA27-AA30-AA32-AA31+'表3-成本费用表'!AA23)+Z34 -> 22623.45
C42: 借款合计 | H42: =0 -> 0 | I42: =0 -> 0 | J42: =0 -> 0 | K42: =0 -> 0 | L42: =0 -> 0 | M42: =0 -> 0 | N42: =0 -> 0 | O42: =0 -> 0 | ... AA42: =0 -> 0

Sheet 表10-资产负债表
B3: 序号 | C3: 项目 | D3: 单位 | E3: 建设期 | G3: 运营期
E4: 1 | F4: 2 | G4: 1 | H4: 2 | I4: 3 | J4: 4 | K4: 5 | L4: 6 | M4: 7 | N4: 8 | O4: 9 | P4: 10 | Q4: 11 | R4: 12 | S4: 13 | T4: 14 | U4: 15 | V4: 16 | W4: 17 | X4: 18 | Y4: 19 | Z4: 20
B5: 1 | C5: 资产合计 | D5: 万元 | E5: =E6+E31 -> 39711.143 | F5: =F6+F31 -> 67290.182 | G5: =G6+G31 -> 65337.49 | H5: =H6+H31 -> 61397.517 | I5: =I6+I31 -> 57665.313 | J5: =J6+J31 -> 54121.442 | K5: =K6+K31 -> 50748.413 | L5: =L6+L31 -> 46670.263 | ... Z5: =Z6+Z31 -> 30877.901
B6: 1.1 | C6: 流动资产 | D6: 万元 | E6: =SUM(E7:E21)+E23+E24+SUM(E27:E30) -> 0 | F6: =SUM(F7:F21)+F23+F24+SUM(F27:F30) -> 0 | G6: =SUM(G7:G21)+G23+G24+SUM(G27:G30) -> 6275.3293 | H6: =SUM(H7:H21)+H23+H24+SUM(H27:H30) -> 6106.3675 | I6: =SUM(I7:I21)+I23+I24+SUM(I27:I30) -> 6145.1741 | J6: =SUM(J7:J21)+J23+J24+SUM(J27:J30) -> 6372.3142 | K6: =SUM(K7:K21)+K23+K24+SUM(K27:K30) -> 6770.2964 | L6: =SUM(L7:L21)+L23+L24+SUM(L27:L30) -> 6463.1577 | ... Z6: =SUM(Z7:Z21)+Z23+Z24+SUM(Z27:Z30) -> 23004.45
C7: 货币资金 | D7: 万元 | E7: ='表9-现金流量表-财务计划'!F34 -> 0 | F7: ='表9-现金流量表-财务计划'!G34 -> 0 | G7: ='表9-现金流量表-财务计划'!H34+'表1-资金筹措及还本付息表'!$H$6 -> 6275.3293 | H7: ='表9-现金流量表-财务计划'!I34+'表1-资金筹措及还本付息表'!$H$6 -> 6106.3675 | I7: ='表9-现金流量表-财务计划'!J34+'表1-资金筹措及还本付息表'!$H$6 -> 6145.1741 | J7: ='表9-现金流量表-财务计划'!K34+'表1-资金筹措及还本付息表'!$H$6 -> 6372.3142 | K7: ='表9-现金流量表-财务计划'!L34+'表1-资金筹措及还本付息表'!$H$6 -> 6770.2964 | L7: ='表9-现金流量表-财务计划'!M34+'表1-资金筹措及还本付息表'!$H$6 -> 6463.1577 | M7: ='表9-现金流量表-财务计划'!N34+'表1-资金筹措及还本付息表'!$H$6 -> 7286.133 | N7: ='表9-现金流量表-财务计划'!O34+'表1-资金筹措及还本付息表'!$H$6 -> 7658.433 | ... Z7: ='表9-现金流量表-财务计划'!AA34+'表1-资金筹措及还本付息表'!$H$6 -> 23004.45
C8: △结算备付金 | D8: 万元
C9: △拆出资金 | D9: 万元
C10: 交易性金融资产 | D10: 万元
C11: ☆以公允价值计量且其变动计入当期损益的金融资产 | D11: 万元
C12: 衍生金融资产 | D12: 万元
C13: 应收票据 | D13: 万元
C14: 应收账款 | D14: 万元 | G14: ='表4-收入税金表'!H54 -> 0 | H14: ='表4-收入税金表'!I54 -> 0 | I14: ='表4-收入税金表'!J54 -> 0 | J14: ='表4-收入税金表'!K54 -> 0 | K14: ='表4-收入税金表'!L54 -> 0 | L14: ='表4-收入税金表'!M54 -> 0 | M14: ='表4-收入税金表'!N54 -> 0 | N14: ='表4-收入税金表'!O54 -> 0 | ... Z14: ='表4-收入税金表'!AA54 -> 0
C15: 应收款项融资 | D15: 万元
C16: 预付款项 | D16: 万元
C17: △应收保费 | D17: 万元
C18: △应收分保账款 | D18: 万元
C19: △应收分保合同准备金 | D19: 万元
C20: 应收资金集中管理款 | D20: 万元
C21: 其他应收款 | D21: 万元 | F21: =0 -> 0 | G21: =0 -> 0 | H21: =0 -> 0 | I21: =0 -> 0 | J21: =0 -> 0 | K21: =0 -> 0 | L21: =0 -> 0 | M21: =0 -> 0 | ... Z21: =0 -> 0
C22: 其中：应收股利 | D22: 万元
C23: △买入返售金融资产 | D23: 万元
C24: 存货 | D24: 万元 | E24: =SUM(E25:E26) -> 0 | F24: =SUM(F25:F26) -> 0 | G24: =SUM(G25:G26) -> 0 | H24: =SUM(H25:H26) -> 0 | I24: =SUM(I25:I26) -> 0 | J24: =SUM(J25:J26) -> 0 | K24: =SUM(K25:K26) -> 0 | L24: =SUM(L25:L26) -> 0 | ... Z24: =SUM(Z25:Z26) -> 0
C25: 其中：原材料 | D25: 万元
C26: 库存商品（产成品） | D26: 万元
C27: 合同资产 | D27: 万元
C28: 持有待售资产 | D28: 万元
C29: 一年内到期的非流动资产 | D29: 万元
C30: 其他流动资产 | D30: 万元 | H30: =G30 -> 0 | I30: =H30 -> 0 | J30: =I30 -> 0 | K30: =J30 -> 0 | L30: =K30 -> 0 | M30: =L30 -> 0 | N30: =M30 -> 0 | O30: =N30 -> 0 | ... Z30: =Y30 -> 0
B31: 1.2 | C31: 非流动资产 | D31: 万元 | E31: =SUM(E32:E42)+SUM(E46:E55) -> 39711.143 | F31: =SUM(F32:F42)+SUM(F46:F55) -> 67290.182 | G31: =SUM(G32:G42)+SUM(G46:G55) -> 59062.161 | H31: =SUM(H32:H42)+SUM(H46:H55) -> 55291.15 | I31: =SUM(I32:I42)+SUM(I46:I55) -> 51520.139 | J31: =SUM(J32:J42)+SUM(J46:J55) -> 47749.127 | K31: =SUM(K32:K42)+SUM(K46:K55) -> 43978.116 | L31: =SUM(L32:L42)+SUM(L46:L55) -> 40207.105 | ... Z31: =SUM(Z32:Z42)+SUM(Z46:Z55) -> 7873.4512
C32: △发放贷款和垫款 | D32: 万元
C33: 债权投资 | D33: 万元
C34: ☆可供出售金融资产 | D34: 万元
C35: 其他债权投资 | D35: 万元
C36: ☆持有至到期投资 | D36: 万元
C37: 长期应收款 | D37: 万元
C38: 长期股权投资 | D38: 万元
C39: 其他权益工具投资 | D39: 万元
C40: 其他非流动金融资产 | D40: 万元
C41: 投资性房地产 | D41: 万元
C42: 固定资产 | D42: 万元 | F42: =0 -> 0 | G42: =G43-G44 -> 43137.294 | H42: =H43-H44 -> 39915.417 | I42: =I43-I44 -> 36693.539 | J42: =J43-J44 -> 33471.661 | K42: =K43-K44 -> 30249.783 | L42: =L43-L44 -> 27027.905 | M42: =M43-M44 -> 23806.027 | N42: =N43-N44 -> 20584.149 | ... Z42: =Z43-Z44 -> 2382.1179
C43: 其中：固定资产原价 | D43: 万元 | F43: 0 | G43: =F43+'表2-折旧摊销表'!D4 -> 46359.172 | H43: =G43+'表2-折旧摊销表'!I49 -> 46359.172 | I43: =H43+'表2-折旧摊销表'!J49 -> 46359.172 | J43: =I43+'表2-折旧摊销表'!K49 -> 46359.172 | K43: =J43+'表2-折旧摊销表'!L49 -> 46359.172 | L43: =K43+'表2-折旧摊销表'!M49 -> 46359.172 | M43: =L43+'表2-折旧摊销表'!N49 -> 46359.172 | N43: =M43+'表2-折旧摊销表'!O49 -> 46359.172 | O43: =N43+'表2-折旧摊销表'!P49 -> 46359.172 | ... Z43: =Y43+'表2-折旧摊销表'!AA49 -> 46801.65
C44: 累计折旧 | D44: 万元 | G44: ='表2-折旧摊销表'!H37+'表2-折旧摊销表'!H39+'表2-折旧摊销表'!H41+'表2-折旧摊销表'!H50 -> 3221.8779 | H44: ='表2-折旧摊销表'!I37+'表2-折旧摊销表'!I39+'表2-折旧摊销表'!I41+G44 -> 6443.7558 | I44: ='表2-折旧摊销表'!J37+'表2-折旧摊销表'!J39+'表2-折旧摊销表'!J41+'表2-折旧摊销表'!J50+H44 -> 9665.6336 | J44: ='表2-折旧摊销表'!K37+'表2-折旧摊销表'!K39+'表2-折旧摊销表'!K41+'表2-折旧摊销表'!K50+I44 -> 12887.512 | K44: ='表2-折旧摊销表'!L37+'表2-折旧摊销表'!L39+'表2-折旧摊销表'!L41+'表2-折旧摊销表'!L50+J44 -> 16109.389 | L44: ='表2-折旧摊销表'!M37+'表2-折旧摊销表'!M39+'表2-折旧摊销表'!M41+'表2-折旧摊销表'!M50+K44 -> 19331.267 | M44: ='表2-折旧摊销表'!N37+'表2-折旧摊销表'!N39+'表2-折旧摊销表'!N41+'表2-折旧摊销表'!N50+L44 -> 22553.145 | N44: ='表2-折旧摊销表'!O37+'表2-折旧摊销表'!O39+'表2-折旧摊销表'!O41+'表2-折旧摊销表'!O50+M44 -> 25775.023 | O44: ='表2-折旧摊销表'!P37+'表2-折旧摊销表'!P39+'表2-折旧摊销表'!P41+'表2-折旧摊销表'!P50+N44 -> 28996.901 | P44: ='表2-折旧摊销表'!Q37+'表2-折旧摊销表'!Q39+'表2-折旧摊销表'!Q41+'表2-折旧摊销表'!Q50+O44 -> 32218.779 | ... Z44: ='表2-折旧摊销表'!AA37+'表2-折旧摊销表'!AA39+'表2-折旧摊销表'!AA41+'表2-折旧摊销表'!AA50+Y44 -> 44419.532
C45: 固定资产减值准备 | D45: 万元
C46: 在建工程 | D46: 万元 | E46: ='表1-资金筹措及还本付息表'!F6-E50 -> 29826.743 | F46: ='表1-资金筹措及还本付息表'!G6+'表1-资金筹措及还本付息表'!F6-F50 -> 60700.582
C47: 生产性生物资产 | D47: 万元
C48: 油气资产 | D48: 万元
C49: 使用权资产 | D49: 万元
C50: 无形资产 | D50: 万元 | E50: =参数输入表!H345*'表1-资金筹措及还本付息表'!F5 -> 9884.4 | F50: =参数输入表!H345*'表1-资金筹措及还本付息表'!G5 -> 6589.6 | G50: ='表2-折旧摊销表'!H46 -> 15924.867 | H50: ='表2-折旧摊销表'!I46 -> 15375.733 | I50: ='表2-折旧摊销表'!J46 -> 14826.6 | J50: ='表2-折旧摊销表'!K46 -> 14277.467 | K50: ='表2-折旧摊销表'!L46 -> 13728.333 | L50: ='表2-折旧摊销表'!M46 -> 13179.2 | M50: ='表2-折旧摊销表'!N46 -> 12630.067 | N50: ='表2-折旧摊销表'!O46 -> 12080.933 | ... Z50: ='表2-折旧摊销表'!AA46 -> 5491.3333
C51: 开发支出 | D51: 万元
C52: 商誉 | D52: 万元
C53: 长期待摊费用 | D53: 万元 | G53: ='表2-折旧摊销表'!H45 -> 0 | H53: ='表2-折旧摊销表'!I45 -> 0 | I53: ='表2-折旧摊销表'!J45 -> 0 | J53: ='表2-折旧摊销表'!K45 -> 0 | K53: ='表2-折旧摊销表'!L45 -> 0 | L53: ='表2-折旧摊销表'!M45 -> 0 | M53: ='表2-折旧摊销表'!N45 -> 0 | N53: ='表2-折旧摊销表'!O45 -> 0 | ... Z53: ='表2-折旧摊销表'!AA45 -> 0
C54: 递延所得税资产 | D54: 万元
C55: 其他非流动资产 | D55: 万元
C56: 其中：特准储备物资 | D56: 万元
B57: 2 | C57: 负债合计 | D57: 万元 | E57: =E58+E86 -> 31636.041 | F57: =F58+F86 -> 53699.272 | G57: =G58+G86 -> 46971.223 | H57: =H58+H86 -> 43981.235 | I57: =I58+I86 -> 40991.824 | J57: =J58+J86 -> 38002.991 | K57: =K58+K86 -> 35014.733 | L57: =L58+L86 -> 31919.521 | ... Z57: =Z58+Z86 -> 0
B58: 2.1 | C58: 流动负债 | D58: 万元 | E58: =SUM(E59:E73)+E77+E79+SUM(E81:E85) -> 0 | F58: =SUM(F59:F73)+F77+F79+SUM(F81:F85) -> 0 | G58: =SUM(G59:G73)+G77+G79+SUM(G81:G85) -> 266.7 | H58: =SUM(H59:H73)+H77+H79+SUM(H81:H85) -> 266.7 | I58: =SUM(I59:I73)+I77+I79+SUM(I81:I85) -> 266.7 | J58: =SUM(J59:J73)+J77+J79+SUM(J81:J85) -> 266.7 | K58: =SUM(K59:K73)+K77+K79+SUM(K81:K85) -> 266.7 | L58: =SUM(L59:L73)+L77+L79+SUM(L81:L85) -> 266.7 | ... Z58: =SUM(Z59:Z73)+Z77+Z79+SUM(Z81:Z85) -> 0
C59: 短期借款 | D59: 万元 | E59: ='表1-资金筹措及还本付息表'!F74+'表1-资金筹措及还本付息表'!F64 -> 0 | F59: ='表1-资金筹措及还本付息表'!G74+'表1-资金筹措及还本付息表'!G64 -> 0 | G59: ='表1-资金筹措及还本付息表'!H74+'表1-资金筹措及还本付息表'!H64 -> 266.7 | H59: ='表1-资金筹措及还本付息表'!I74+'表1-资金筹措及还本付息表'!I64 -> 266.7 | I59: ='表1-资金筹措及还本付息表'!J74+'表1-资金筹措及还本付息表'!J64 -> 266.7 | J59: ='表1-资金筹措及还本付息表'!K74+'表1-资金筹措及还本付息表'!K64 -> 266.7 | K59: ='表1-资金筹措及还本付息表'!L74+'表1-资金筹措及还本付息表'!L64 -> 266.7 | L59: ='表1-资金筹措及还本付息表'!M74+'表1-资金筹措及还本付息表'!M64 -> 266.7 | ... Z59: ='表1-资金筹措及还本付息表'!AA74+'表1-资金筹措及还本付息表'!AA64 -> 0
C60: △向中央银行借款 | D60: 万元
C61: △拆入资金 | D61: 万元
C62: 交易性金融负债 | D62: 万元
C63: ☆以公允价值计量且其变动计入当期损益的金融负债 | D63: 万元
C64: 衍生金融负债 | D64: 万元
C65: 应付票据 | D65: 万元
C66: 应付账款 | D66: 万元
C67: 预收款项 | D67: 万元
C68: 合同负债 | D68: 万元
C69: △卖出回购金融资产款 | D69: 万元
C70: △吸收存款及同业存放 | D70: 万元
C71: △代理买卖证券款 | D71: 万元
... C85: 其他流动负债 | D85: 万元
B86: 2.2 | C86: 非流动负债 | D86: 万元 | E86: =SUM(E87:E89)+SUM(E92:E98) -> 31636.041 | F86: =SUM(F87:F89)+SUM(F92:F98) -> 53699.272 | G86: =SUM(G87:G89)+SUM(G92:G98) -> 46704.523 | H86: =SUM(H87:H89)+SUM(H92:H98) -> 43714.535 | I86: =SUM(I87:I89)+SUM(I92:I98) -> 40725.124 | J86: =SUM(J87:J89)+SUM(J92:J98) -> 37736.291 | K86: =SUM(K87:K89)+SUM(K92:K98) -> 34748.033 | L86: =SUM(L87:L89)+SUM(L92:L98) -> 31652.821 | ... Z86: =SUM(Z87:Z89)+SUM(Z92:Z98) -> 0
C87: △保险合同准备金 | D87: 万元
C88: 长期借款 | D88: 万元 | E88: ='表1-资金筹措及还本付息表'!F44 -> 31636.041 | F88: =IF('表1-资金筹措及还本付息表'!G5=0,0,'表1-资金筹措及还本付息表'!G44) -> 53699.272 | G88: ='表1-资金筹措及还本付息表'!H54 -> 50119.321 | H88: ='表1-资金筹措及还本付息表'!I54 -> 46539.369 | I88: ='表1-资金筹措及还本付息表'!J54 -> 42959.418 | J88: ='表1-资金筹措及还本付息表'!K54 -> 39379.466 | K88: ='表1-资金筹措及还本付息表'!L54 -> 35799.515 | L88: ='表1-资金筹措及还本付息表'!M54 -> 32219.563 | M88: ='表1-资金筹措及还本付息表'!N54 -> 28639.612 | N88: ='表1-资金筹措及还本付息表'!O54 -> 25059.66 | ... Z88: ='表1-资金筹措及还本付息表'!AA54 -> 0
C89: 应付债券 | D89: 万元
C90: 其中：优先股 | D90: 万元
C91: 永续债 | D91: 万元
C92: 租赁负债 | D92: 万元
C93: 长期应付款 | D93: 万元
C94: 长期应付职工薪酬 | D94: 万元
C95: 预计负债 | D95: 万元
C96: 递延收益 | D96: 万元 | G96: =-'表4-收入税金表'!H39 -> -3414.7974 | H96: =-'表4-收入税金表'!I39 -> -2824.8348 | I96: =-'表4-收入税金表'!J39 -> -2234.2936 | J96: =-'表4-收入税金表'!K39 -> -1643.1755 | K96: =-'表4-收入税金表'!L39 -> -1051.4822 | L96: =-'表4-收入税金表'!M39 -> -566.74268 | M96: =-'表4-收入税金表'!N39 -> -23.709258 | N96: =-'表4-收入税金表'!O39 -> 0 | ... Z96: =-'表4-收入税金表'!AA39 -> 0
C97: 递延所得税负债 | D97: 万元
C98: 其他非流动负债 | D98: 万元
C99: 其中：特准储备基金 | D99: 万元
B100: 3 | C100: 所有者权益（或股东权益） | D100: 万元 | E100: =E108+E109+E112-E113+E114+E116+E117+E123+E124+E125+E126 -> 8075.102 | F100: =F108+F109+F112-F113+F114+F116+F117+F123+F124+F125+F126 -> 13590.91 | G100: =G108+G109+G112-G113+G114+G116+G117+G123+G124+G125+G126 -> 18366.267 | H100: =H108+H109+H112-H113+H114+H116+H117+H123+H124+H125+H126 -> 17416.283 | I100: =I108+I109+I112-I113+I114+I116+I117+I123+I124+I125+I126 -> 16673.489 | J100: =J108+J109+J112-J113+J114+J116+J117+J123+J124+J125+J126 -> 16118.451 | K100: =K108+K109+K112-K113+K114+K116+K117+K123+K124+K125+K126 -> 15733.68 | L100: =L108+L109+L112-L113+L114+L116+L117+L123+L124+L125+L126 -> 14750.742 | ... Z100: =Z108+Z109+Z112-Z113+Z114+Z116+Z117+Z123+Z124+Z125+Z126 -> 30877.901
C101: 实收资本（或股本） | D101: 万元 | E101: ='表1-资金筹措及还本付息表'!F11 -> 8075.102 | F101: =IF('表1-资金筹措及还本付息表'!G5=0,0,E101+'表1-资金筹措及还本付息表'!G11) -> 13590.91 | G101: =IF('表1-资金筹措及还本付息表'!G5>0,F101+'表1-资金筹措及还本付息表'!H11,E101+'表1-资金筹措及还本付息表'!H11) -> 13705.21 | H101: =G101+'表1-资金筹措及还本付息表'!I11 -> 13705.21 | I101: =H101+'表1-资金筹措及还本付息表'!J11 -> 13705.21 | J101: =I101+'表1-资金筹措及还本付息表'!K11 -> 13705.21 | K101: =J101+'表1-资金筹措及还本付息表'!L11 -> 13705.21 | L101: =K101+'表1-资金筹措及还本付息表'!M11 -> 13705.21 | M101: =L101+'表1-资金筹措及还本付息表'!N11 -> 13705.21 | N101: =M101+'表1-资金筹措及还本付息表'!O11 -> 13705.21 | O101: =N101+'表1-资金筹措及还本付息表'!P11 -> 13705.21 | ... Z101: =Y101+'表1-资金筹措及还本付息表'!AA11 -> 13705.21
C102: 国家资本 | D102: 万元
C103: 国有法人资本 | D103: 万元
C104: 集体资本 | D104: 万元
C105: 民营资本 | D105: 万元
C106: 外商资本 | D106: 万元
C107: #减：已归还投资 | D107: 万元
C108: 实收资本（或股本）净额 | D108: 万元 | E108: =E101-E107 -> 8075.102 | F108: =IF('表1-资金筹措及还本付息表'!G5=0,0,F101-F107) -> 13590.91 | G108: =G101-G107 -> 13705.21 | H108: =H101-H107 -> 13705.21 | I108: =I101-I107 -> 13705.21 | J108: =J101-J107 -> 13705.21 | K108: =K101-K107 -> 13705.21 | L108: =L101-L107 -> 13705.21 | M108: =M101-M107 -> 13705.21 | N108: =N101-N107 -> 13705.21 | ... Z108: =Z101-Z107 -> 13705.21
C109: 其他权益工具 | D109: 万元
C110: 其中：优先股 | D110: 万元
C111: 永续债 | D111: 万元
C112: 资本公积 | D112: 万元
C113: 减：库存股 | D113: 万元
C114: 其他综合收益 | D114: 万元
C115: 其中：外币报表折算差额 | D115: 万元
...

Sheet 财务指标表
A1: 序号 | B1: 项目 | C1: 单位 | D1: 数值
A2: 1 | B2: 项目容量
A3: 1.1 | B3: 项目规模 | C3: P | D3: =参数输入表!H4 -> 1000
A4: 1.2 | B4: PUE | C4: % | D4: =参数输入表!I28 -> 0
A5: 1.3 | B5: 机柜总功率 | C5: KW | D5: =参数输入表!H6 -> 4000
A6: 2 | B6: 项目总投资 | C6: 万元 | D6: ='表1-资金筹措及还本付息表'!D6 -> 67671.182
A7: 3 | B7: 建设投资 | C7: 万元 | D7: =参数输入表!H348 -> 65278.39
A8: 4 | B8: 建设期利息 | C8: 万元 | D8: =参数输入表!H349 -> 2011.7923
A9: 5 | B9: 流动资金 | C9: 万元 | D9: =参数输入表!H351 -> 381
A10: 6 | B10: 销售收入总额（不含增值税） | C10: 万元 | D10: ='表4-收入税金表'!D5 -> 373365.74
A11: 7 | B11: 总成本费用 | C11: 万元 | D11: ='表3-成本费用表'!D5 -> 335351.07 | F11: 表三成本表C6项生产成本运营期平均值做敏感性分析、蒙特卡洛
A12: 8 | B12: 销售税金附加总额 | C12: 万元 | D12: ='表4-收入税金表'!D40 -> 709.49645
A13: 9 | B13: 利润总额 | C13: 万元 | D13: ='表5-利润表-资本金'!D14 -> 37305.167
A14: 10 | B14: 项目投资回收期（所得税前） | C14: 年 | D14: ='表8-现金流量表-全投资'!D29 -> 12.887416
A15: 11 | B15: 项目投资回收期（所得税后） | C15: 年 | D15: ='表8-现金流量表-全投资'!D28 -> 14.134043
A16: 12 | B16: 项目投资财务内部收益率（所得税前） | C16: % | D16: ='表8-现金流量表-全投资'!D26 -> 0.064079986 | E16: 反算依据指标，数值由操作者自动输入
A17: 13 | B17: 项目投资财务内部收益率（所得税后） | C17: % | D17: ='表8-现金流量表-全投资'!D27 -> 0.051015872
A18: 14 | B18: 资本金财务内部收益率 | C18: % | D18: ='表6-现金流量表-资本金'!D34 -> 0.093083589
A19: 15 | B19: 资产负债率（最大值） | C19: % | D19: ='表10-资产负债表'!C129 -> 0.79802537
A20: 16 | B20: 盈亏平衡点（生产能力利用率） | C20: % | D20: ='表3-成本费用表'!D5/('表4-收入税金表'!D5-'表4-收入税金表'!D40) -> 0.89989389
