Workbook

Sheet 说明
B2: 参数输入表中：
C3: 标黄项为相对固定模块
C4: 标绿项为对成本类、收入类数据进行分类，成本参数按照：“生产成本/销售费用/管理费用/研发费用”划分；收入参数按照：“营业收入/其他收入/营业外收入”划分
C5: 标橙项为固定的分类原则
C6: 标紫项为在参数表中不需要手动输入、勾选的内容，根据其他输入参数自动计算得出，可不在参数输入界面呈现。
C7: 标红项为引用同样红色sheet中相关数据
C8: 标蓝项为可不展示内容，大部分为中间过程计算表/中间计算过程
C10: 【成本费用表】、【收入税金表】、【利润表】体现的是会计报表相关数据，涉及到的收入及成本数据均为不含增值税金额，不含税金额计算公式为： 【含税金额/（1+增值税税率）】；增值税计算公式为：【不含税金额*增值税税率】或【含税金额/（1+增值税税率）*增值税税率】
C12: 【成本费用表】中各项成本按照：一、营业总成本：（1）生产成本；（2）销售费用；（3）管理费用；（4）研发费用；（5）财务费用；二、营业外支出，进行划分，其中需重点关注长期待摊费用成本项，在成本费用表中以逐年摊销的形式出现。
C14: 【成本费用表】中标蓝的内容为不展示内容，为中间计算表，其中数据均还原成含税金额，用于后续的【现金流量表】引用
C16: 【收入表】中各项收入按照：一、营业收入；二、其他收入；三、营业外收入，营业收入及营业外收入需展示二级目录（具体的收入项）
C18: 【现金流量表】体现的是公司账上实际收到或支付的现金流，因此涉及到的收入及成本数据均为含增值税金额，数据需引用成本费用表中还原后的含税金额或参数输入表中的含税金额。同时，收入数据需关注付款比例及回款期限的应用。原理为当年的部分比例收入的滞后支付，第一年的某项收入现金流为预测现金流*首年支付比例，第二年的某项收入现金流为：当年预测现金流*当年支付比例+上一年预测现金流*（1-上一年支付比例）
C20: 【现金流量表-财务计划】增加IF判定条件，当某年的累计盈余资金<“流动资金（本项目为960万元）”+次年的“生产经营现金支出合计（成本费用表标蓝表第一行）”，给出明显提示（允许用户在参数输入界面填写各年度短期借款当期借款金额及还本金额，再重新生成新的结果）

Sheet 可抵扣进项税
B2: 投资概算 | C2: 序号 | D2: 科目 | E2: 计取基数 | F2: 进项税率 | G2: 进项税
C3: 1 | D3: 设备购置费 | E3: =参数输入表!H106 -> 15000 | F3: =参数输入表!H353 -> 0.13 | G3: =E3/(1+F3)*F3 -> 1725.6637
C4: 2 | D4: 建安工程费 | E4: =参数输入表!H107 -> 4000 | F4: =参数输入表!H354 -> 0.09 | G4: =E4/(1+F4)*F4 -> 330.27523
C5: 3 | D5: 其他费用 | E5: =参数输入表!H108 -> 4000 | F5: =参数输入表!H355 -> 0.06 | G5: =E5/(1+F5)*F5 -> 226.41509
C6: 4 | D6: 预备费 | E6: =参数输入表!H109 -> 400 | F6: =参数输入表!H356 -> 0 | G6: =E6/(1+F6)*F6 -> 0
C7: 5 | D7: 储能投资 | E7: =参数输入表!H110 -> 500 | F7: =参数输入表!H357 -> 0.13 | G7: =E7/(1+F7)*F7 -> 57.522124
C8: 6 | D8: 送出线路投资 | E8: =参数输入表!H111 -> 2800 | F8: =参数输入表!H358 -> 0.09 | G8: =E8/(1+F8)*F8 -> 231.19266
C9: 7 | D9: 配套支持资金 | E9: =参数输入表!H112 -> 0 | F9: =参数输入表!H359 -> 0 | G9: =E9/(1+F9)*F9 -> 0
C10: 8 | D10: 静态总投资 | E10: =参数输入表!H113 -> 26700
C11: 9 | D11: 建设期利息 | E11: =参数输入表!H115 -> 383.10084
C12: 10 | D12: 动态总投资 | E12: =参数输入表!H116 -> 27083.101
C13: 11 | D13: 流动资金 | E13: =参数输入表!H118 -> 240
C14: 12 | D14: 可抵扣进项税 | E14: =SUM(G3:G9) -> 2571.0688
C18: 可抵扣进项税为后台计算，不需要作为成果展示

Sheet 参数输入表
G1: 【光伏】财务评价计算模型边界条件输入参数表
B3: 类别 | C3: 序号 | D3: 参数 | E3: 操作类型 | F3: 收入/成本归类 | G3: 参数释义/计算公式 | H3: 数值 | I3: 单位 | J3: 取值说明 | K3: 备注
B4: 基础信息 | C4: 1 | D4: 建设期 | E4: 手动输入 | H4: 12 | I4: 月 | J4: 在初核阶段，不含升压站的集中式光伏项目建设期一般按5个月计算，含升压站的按7个月计算，屋顶分布式项目、大型基地项目根据实际情况调整。
C5: 2 | D5: 动工年月 | E5: 手动输入/下拉菜单选择【日历】 | I5: 年/月
C6: 3 | D6: 施工进度安排 | I6: %
D7: 建设期第1年 | E7: 手动输入 | H7: 1
D8: 建设期第2年 | E8: 手动输入 | H8: =1-H7 -> 0
C9: 4 | D9: 运营期 | E9: 手动输入 | H9: 25 | I9: 年 | J9: 原则上按照25年考虑
C10: 5 | D10: 项目所在地 | E10: 下拉菜单选择 | J10: 判定是否属于西部地区
D11: 所在省份 | E11: 下拉菜单选择
D12: 所在市、县 | E12: 下拉菜单选择
D13: 实际装机容量 | E13: 手动输入 | H13: 80 | I13: MW | J13: 1MW=1000kW
D14: 储能额定功率 | E14: 手动输入 | H14: 10 | I14: MW
D15: 储能容量 | E15: 手动输入 | H15: 20 | I15: MWh
D16: 首年年利用小时数 | E16: 手动输入 | H16: 1200 | I16: h
D17: 发电量 | E17: 自动计算 | G17: 各年上网电量=（（首年年利用小时数*实际装机容量*各年衰减系数） | I17: MWh | J17: 1MWh=0.1万度电
D18: 衰减率（首年） | E18: 手动输入 | H18: 0.01 | I18: %
D19: 衰减率（其他年） | E19: 手动输入 | H19: 0.0045 | I19: %
D20: 限电率 | E20: 手动输入 | H20: 0.054 | I20: %
D21: 运营期第1年 | E21: 自动计算 | H21: =$H$13*$H$16*(1-$H$18) -> 95040
D22: 运营期第2年 | E22: 自动计算 | H22: =H21*(1-$H$19) -> 94612.32
D23: 运营期第3年 | E23: 自动计算 | H23: =H22*(1-$H$19) -> 94186.565
D24: 运营期第4年 | E24: 自动计算 | H24: =H23*(1-$H$19) -> 93762.725
D25: 运营期第5年 | E25: 自动计算 | H25: =H24*(1-$H$19) -> 93340.793
D26: 运营期第6年 | E26: 自动计算 | H26: =H25*(1-$H$19) -> 92920.759
D27: 运营期第7年 | E27: 自动计算 | H27: =H26*(1-$H$19) -> 92502.616
D28: 运营期第8年 | E28: 自动计算 | H28: =H27*(1-$H$19) -> 92086.354
D29: 运营期第9年 | E29: 自动计算 | H29: =H28*(1-$H$19) -> 91671.965
D30: 运营期第10年 | E30: 自动计算 | H30: =H29*(1-$H$19) -> 91259.442
D31: 运营期第11年 | E31: 自动计算 | H31: =H30*(1-$H$19) -> 90848.774
D32: 运营期第12年 | E32: 自动计算 | H32: =H31*(1-$H$19) -> 90439.955
D33: 运营期第13年 | E33: 自动计算 | H33: =H32*(1-$H$19) -> 90032.975
... D45: 运营期第25年 | E45: 自动计算 | H45: =H44*(1-$H$19) -> 85289.736
D46: 上网电量 | G46: 各年上网电量=（（首年年利用小时数*实际装机容量*各年衰减系数）-数能融合消纳电量）*（1-限电率）
D47: 运营期第1年 | E47: 自动计算 | H47: =IF((H21*(1-H77)*(1-$H$20))>0,H21*(1-H77)*(1-$H$20),0) -> 44953.92
D48: 运营期第2年 | E48: 自动计算 | H48: =IF((H22*(1-H78)*(1-$H$20))>0,H22*(1-H78)*(1-$H$20),0) -> 44751.627
D49: 运营期第3年 | E49: 自动计算 | H49: =IF((H23*(1-H79)*(1-$H$20))>0,H23*(1-H79)*(1-$H$20),0) -> 44550.245
D50: 运营期第4年 | E50: 自动计算 | H50: =IF((H24*(1-H80)*(1-$H$20))>0,H24*(1-H80)*(1-$H$20),0) -> 44349.769
D51: 运营期第5年 | E51: 自动计算 | H51: =IF((H25*(1-H81)*(1-$H$20))>0,H25*(1-H81)*(1-$H$20),0) -> 44150.195
D52: 运营期第6年 | E52: 自动计算 | H52: =IF((H26*(1-H82)*(1-$H$20))>0,H26*(1-H82)*(1-$H$20),0) -> 26370.911
D53: 运营期第7年 | E53: 自动计算 | H53: =IF((H27*(1-H83)*(1-$H$20))>0,H27*(1-H83)*(1-$H$20),0) -> 26252.242
D54: 运营期第8年 | E54: 自动计算 | H54: =IF((H28*(1-H84)*(1-$H$20))>0,H28*(1-H84)*(1-$H$20),0) -> 26134.107
D55: 运营期第9年 | E55: 自动计算 | H55: =IF((H29*(1-H85)*(1-$H$20))>0,H29*(1-H85)*(1-$H$20),0) -> 26016.504
D56: 运营期第10年 | E56: 自动计算 | H56: =IF((H30*(1-H86)*(1-$H$20))>0,H30*(1-H86)*(1-$H$20),0) -> 25899.43
D57: 运营期第11年 | E57: 自动计算 | H57: =IF((H31*(1-H87)*(1-$H$20))>0,H31*(1-H87)*(1-$H$20),0) -> 25782.882
D58: 运营期第12年 | E58: 自动计算 | H58: =IF((H32*(1-H88)*(1-$H$20))>0,H32*(1-H88)*(1-$H$20),0) -> 25666.859
... D71: 运营期第25年 | E71: 自动计算 | H71: =IF((H45*(1-H101)*(1-$H$20))>0,H45*(1-H101)*(1-$H$20),0) -> 24205.227
D72: 上网电价
D73: 运营期第1年 | E73: 手动输入 | H73: 0.33 | I73: 元/kWh
D74: …… | E74: 手动输入 | I74: 元/kWh
D75: 运营期第25年 | E75: 手动输入 | H75: =H73 -> 0.33 | I75: 元/kWh
D76: 数能融合消纳光伏电量占比
D77: 运营期第1年 | E77: 手动输入 | H77: =50% -> 0.5 | I77: %
D78: 运营期第2年 | E78: 手动输入 | H78: =50% -> 0.5 | I78: %
D79: 运营期第3年 | E79: 手动输入 | H79: =50% -> 0.5 | I79: %
D80: 运营期第4年 | E80: 手动输入 | H80: =50% -> 0.5 | I80: %
D81: 运营期第5年 | E81: 手动输入 | H81: =50% -> 0.5 | I81: %
D82: 运营期第6年 | E82: 手动输入 | H82: =70% -> 0.7 | I82: %
D83: 运营期第7年 | E83: 手动输入 | H83: =70% -> 0.7 | I83: %
D84: 运营期第8年 | E84: 手动输入 | H84: =70% -> 0.7 | I84: %
D85: 运营期第9年 | E85: 手动输入 | H85: =70% -> 0.7 | I85: %
D86: 运营期第10年 | E86: 手动输入 | H86: =70% -> 0.7 | I86: %
D87: 运营期第11年 | E87: 手动输入 | H87: =70% -> 0.7 | I87: %
D88: 运营期第12年 | E88: 手动输入 | H88: =70% -> 0.7 | I88: %
D89: 运营期第13年 | E89: 手动输入 | H89: =70% -> 0.7 | I89: %
D90: 运营期第14年 | E90: 手动输入 | H90: =70% -> 0.7 | I90: %
D91: 运营期第15年 | E91: 手动输入 | H91: =70% -> 0.7 | I91: %
D92: 运营期第16年 | E92: 手动输入 | H92: =70% -> 0.7 | I92: %
D93: 运营期第17年 | E93: 手动输入 | H93: =70% -> 0.7 | I93: %
... D101: 运营期第25年 | E101: 手动输入 | H101: =70% -> 0.7 | I101: %
D102: 数能融合机制电价
D103: 运营期第1年 | E103: 手动输入 | H103: 0.4 | I103: 元/kWh
D104: …… | E104: 手动输入 | I104: 元/kWh
D105: 运营期第25年 | E105: 手动输入 | H105: =H103 -> 0.4 | I105: 元/kWh
B106: 投资概算 | C106: 1 | D106: 设备购置费 | E106: 手动输入/下拉菜单选择【增值税税率】 | G106: 增值税税率（自动生成含税和不含税价）：13%/9%/6%/0% | H106: 15000 | I106: 万元
C107: 2 | D107: 建安工程费 | E107: 手动输入/下拉菜单选择【增值税税率】 | G107: 增值税税率（自动生成含税和不含税价）：13%/9%/6%/0% | H107: 4000 | I107: 万元
C108: 3 | D108: 其他费用 | E108: 手动输入/下拉菜单选择【增值税税率】 | G108: 增值税税率（自动生成含税和不含税价）：13%/9%/6%/0% | H108: 4000 | I108: 万元
C109: 4 | D109: 预备费 | E109: 手动输入/下拉菜单选择【增值税税率】 | G109: 增值税税率（自动生成含税和不含税价）：13%/9%/6%/0% | H109: 400 | I109: 万元
C110: 5 | D110: 储能投资 | E110: 手动输入/下拉菜单选择【增值税税率】 | G110: 增值税税率（自动生成含税和不含税价）：13%/9%/6%/0% | H110: 500 | I110: 万元
C111: 6 | D111: 送出线路投资 | E111: 手动输入/下拉菜单选择【增值税税率】 | G111: 增值税税率（自动生成含税和不含税价）：13%/9%/6%/0% | H111: 2800 | I111: 万元
C112: 7 | D112: 配套支持资金 | E112: 手动输入/下拉菜单选择【增值税税率】 | G112: 增值税税率（自动生成含税和不含税价）：13%/9%/6%/0% | H112: 0 | I112: 万元
C113: 8 | D113: 项目静态总投资 | E113: 自动计算 | G113: 投资概算1-7合计 | H113: =SUM(H106:H112) -> 26700 | I113: 万元
C114: 9 | D114: 静态总投资（自主投资） | E114: 自动计算 | G114: 静态总投资（自主投资）=项目静态总投资-建设补贴 | H114: =H113-H121 -> 26700 | I114: 万元
C115: 10 | D115: 建设期利息 | E115: 自动计算 | G115: 计入总投资的资本化利息，直接引用资金筹措表数据 | H115: ='表1-资金筹措及还本付息表'!D17 -> 383.10084 | I115: 万元
C116: 11 | D116: 项目动态总投资 (不含流动资金) | E116: 自动计算 | G116: 项目动态总投资（不含流动资金）=项目静态总投资+建设期利息 | H116: =H113+H115 -> 27083.101 | I116: 万元
C117: 12 | D117: 动态总投资（自主投资_不含流动资金） | E117: 自动计算 | G117: 动态总投资（自主投资_不含流动资金）=静态总投资（自主投资）+建设期利息 | H117: =H114+H115 -> 27083.101 | I117: 万元
C118: 13 | D118: 流动资金 | E118: 手动输入后自动计算 | G118: 自定义计算规则 | H118: =H119*H13*1000/10000 -> 240 | I118: 万元 | J118: 建议按照30元/kW考虑
D119: 流动资金取费单价 | E119: 手动输入 | G119: 流动资金=实际装机容量*流动资金取费单价/10000 | H119: 30 | I119: 元/kW
C120: 14 | D120: 可抵扣进项税 | E120: 自动计算 | H120: =可抵扣进项税!E14 -> 2571.0688 | I120: 万元 | J120: 根据项目设计概算梳理出设备类、建安类、服务类投资，再分别按照对应适用税率（现行标准为13%、9%、6%）计算出可抵扣增值税额
C121: 15 | D121: 建设补贴 | E121: 手动输入 | H121: 0 | I121: 万元
B122: 投融资相关 | C122: 1 | D122: 资本金比例 | E122: 手动输入 | H122: 0.2 | I122: % | J122: 资本金比例原则上在20%-30%之间
D123: 资本金 | E123: 自动计算 | G123: 资本金=资金筹措动态总投资*资本金比例 | H123: ='表1-资金筹措及还本付息表'!D11 -> 5488.6202 | I123: 万元
C124: 2 | D124: 宽限期 | E124: 手动输入 | H124: 1 | I124: 年/月 | J124: 建设期仅付息，不还本
C125: 3 | D125: 建设期利息贷款利率 | E125: 手动输入 | H125: 0.036 | I125: % | J125: 用于计算建设期利息的贷款利率
C126: 4 | D126: 长期贷款利率 | E126: 手动输入 | H126: 0.036 | I126: % | J126: 原则上按照开发主体在项目所在地实际融资水平取值，不得高于同期限银行贷款基础利率（LPR）
C127: 5 | D127: 短期贷款利率 | E127: 手动输入 | H127: 0.031 | I127: % | J127: 原则上按照开发主体在项目所在地实际融资水平取值，不得高于同期限银行贷款基础利率（LPR）
C128: 6 | D128: 长期借款本金偿还方式 | E128: 下拉菜单选择 | G128: 等额本息/等额本金/其他
C129: 7 | D129: 长期借款本金还款期限 | E129: 手动输入 | H129: 15 | I129: 年 | J129: 还款期限建议取值15年，最终根据与银行沟通协商情况据实调整
C130: 8 | D130: 流动资金中资本金占比 | E130: 手动输入 | H130: 0.3 | I130: %
C131: 9 | D131: 项目公司注册资本 | E131: 手动输入 | H131: 10000 | I131: 万元
...

Sheet 表1-资金筹措及还本付息表
B2: 资金筹措表
B3: 序号 | C3: 建设期 | D3: 合计 | E3: 单位 | F3: 建设期 | H3: 运营期
F4: 1 | G4: 2 | H4: 1 | I4: 2 | J4: 3 | K4: 4 | L4: 5 | M4: 6 | N4: 7 | O4: 8 | P4: 9 | Q4: 10 | R4: 11 | S4: 12 | T4: 13 | U4: 14 | V4: 15 | W4: 16 | X4: 17 | Y4: 18 | Z4: 19 | AA4: 20 | AB4: 21 | AC4: 22 | AD4: 23 | AE4: 24 | AF4: 25
C5: 施工进度安排 | D5: =SUM(F5:M5) -> 1 | F5: =参数输入表!H7 -> 1 | G5: =参数输入表!H8 -> 0
B6: 1 | C6: 动态总投资（自主投资） | D6: =D7+D8+D9 -> 27323.101 | E6: 万元 | F6: =SUM(F7:F9) -> 27083.101 | G6: =SUM(G7:G9) -> 0 | H6: =SUM(H7:H9) -> 240
B7: 1.1 | C7: 静态总投资（自主投资） | D7: =SUM(F7:AF7) -> 26700 | E7: 万元 | F7: =参数输入表!$H$114*F5 -> 26700 | G7: =参数输入表!$H$114*G5 -> 0 | H7: 0
B8: 1.2 | C8: 建设期利息 | D8: =SUM(F8:AF8) -> 383.10084 | E8: 万元 | F8: =F17 -> 383.10084 | G8: =G17 -> 0 | H8: =H17 -> 0
B9: 1.3 | C9: 流动资金 | D9: =SUM(F9:AF9) -> 240 | E9: 万元 | F9: 0 | G9: 0 | H9: =参数输入表!H118 -> 240
B10: 2 | C10: 资金来源
B11: 2.1 | C11: 资本金 | D11: =SUM(F11:AF11) -> 5488.6202 | E11: 万元 | F11: =F6*参数输入表!$H$122 -> 5416.6202 | G11: =G6*参数输入表!$H$122 -> 0 | H11: =H6*参数输入表!$H$130 -> 72
B12: 2.1.1 | C12: 用于建设投资 | D12: =SUM(F12:AF12) -> 5416.6202 | E12: 万元 | F12: =F11-F13-F14 -> 5416.6202 | G12: =G11-G13-G14 -> 0 | H12: 0
B13: 2.1.2 | C13: 用于建设期利息 | D13: =SUM(F13:AF13) -> 0 | E13: 万元 | F13: 0 | G13: 0 | H13: 0
B14: 2.1.3 | C14: 用于流动资金 | D14: =SUM(F14:AF14) -> 72 | F14: 0 | G14: 0 | H14: =H9*参数输入表!H130 -> 72
B15: 2.2 | C15: 债务资金 | D15: =SUM(F15:M15) -> 21834.481 | E15: 万元 | F15: =SUM(F16:F18) -> 21666.481 | G15: =SUM(G16:G18) -> 0 | H15: =SUM(H16:H18) -> 168
B16: 2.2.1 | C16: 用于建设投资 | D16: =SUM(F16:AF16) -> 21283.38 | E16: 万元 | F16: =F7-F12 -> 21283.38 | G16: =G7-G12 -> 0 | H16: =H7-H12 -> 0
B17: 2.1.2 | C17: 用于建设期利息 | D17: =SUM(F17:AF17) -> 383.10084 | E17: 万元 | F17: =F16/2*参数输入表!$H$125 -> 383.10084 | G17: =IF(G5=0,0,(G16/2+F15)*参数输入表!$H$125) -> 0 | H17: 0
B18: 2.1.3 | C18: 用于流动资金 | D18: =SUM(F18:AF18) -> 168 | E18: 万元 | F18: 0 | G18: 0 | H18: =H9-H14 -> 168
B20: 营运资本变动
B21: 序号 | C21: 项目 | D21: 合计 | E21: 单位 | F21: 建设期 | H21: 运营期
F22: 1 | G22: 2 | H22: 1 | I22: 2 | J22: 3 | K22: 4 | L22: 5 | M22: 6 | N22: 7 | O22: 8 | P22: 9 | Q22: 10 | R22: 11 | S22: 12 | T22: 13 | U22: 14 | V22: 15 | W22: 16 | X22: 17 | Y22: 18 | Z22: 19 | AA22: 20 | AB22: 21 | AC22: 22 | AD22: 23 | AE22: 24 | AF22: 25
B23: 1 | C23: 流动资产 | D23: =SUM(F23:AF23) -> 177422.2 | E23: 万元 | F23: =SUM(F24:F27) -> 2571.0688 | G23: =SUM(G24:G27) -> 2571.0688 | H23: =SUM(H24:H27) -> 2725.4621 | I23: =SUM(I24:I27) -> 2880.1027 | J23: =SUM(J24:J27) -> 3038.851 | K23: =SUM(K24:K27) -> 3137.3603 | L23: =SUM(L24:L27) -> 3246.6568 | M23: =SUM(M24:M27) -> 3442.3133 | ... AF23: =SUM(AF24:AF27) -> 16347.897
C24: 货币资金 | D24: =SUM(F24:AF24) -> 164987.55 | E24: 万元 | F24: ='表9-现金流量表-财务计划'!F34 -> 0 | G24: ='表9-现金流量表-财务计划'!G34 -> 0 | H24: ='表9-现金流量表-财务计划'!H34 -> 543.73516 | I24: ='表9-现金流量表-财务计划'!I34 -> 1085.9656 | J24: ='表9-现金流量表-财务计划'!J34 -> 1630.5595 | K24: ='表9-现金流量表-财务计划'!K34 -> 2113.1783 | L24: ='表9-现金流量表-财务计划'!L34 -> 2604.8556 | M24: ='表9-现金流量表-财务计划'!M34 -> 3199.9482 | ... AF24: ='表9-现金流量表-财务计划'!AF34 -> 16347.897
C25: 应收账款 | D25: =SUM(F25:AF25) -> 0 | E25: 万元 | H25: ='表4-收入税金表'!H60 -> 0 | I25: ='表4-收入税金表'!I60 -> 0 | J25: ='表4-收入税金表'!J60 -> 0 | K25: ='表4-收入税金表'!K60 -> 0 | L25: ='表4-收入税金表'!L60 -> 0 | M25: ='表4-收入税金表'!M60 -> 0 | N25: ='表4-收入税金表'!N60 -> 0 | O25: ='表4-收入税金表'!O60 -> 0 | ... AF25: ='表4-收入税金表'!AF60 -> 0
C26: 存货 | D26: =SUM(F26:AF26) -> 0 | E26: 万元
C27: 其他流动资产（留抵税额） | D27: =SUM(F27:AF27) -> 12434.641 | E27: 万元 | F27: ='表4-收入税金表'!F45 -> 2571.0688 | G27: ='表4-收入税金表'!G45 -> 2571.0688 | H27: ='表4-收入税金表'!H45 -> 2181.727 | I27: ='表4-收入税金表'!I45 -> 1794.1371 | J27: ='表4-收入税金表'!J45 -> 1408.2914 | K27: ='表4-收入税金表'!K45 -> 1024.1821 | L27: ='表4-收入税金表'!L45 -> 641.80118 | M27: ='表4-收入税金表'!M45 -> 242.3651 | ... AF27: ='表4-收入税金表'!AF45 -> 0
B28: 2 | C28: 流动负债 | D28: =SUM(F28:AF28) -> 25054.411 | E28: 万元 | F28: =SUM(F29:F34) -> 0 | G28: =SUM(G29:G34) -> 0 | H28: =SUM(H29:H34) -> 345.3729 | I28: =SUM(I29:I34) -> 215.64797 | J28: =SUM(J29:J34) -> 250.12324 | K28: =SUM(K29:K34) -> 349.0055 | L28: =SUM(L29:L34) -> 376.92188 | M28: =SUM(M29:M34) -> 422.4973 | ... AF28: =SUM(AF29:AF34) -> 1860.7837
C29: 短期借款 | D29: =SUM(F29:AF29) -> 168 | E29: 万元 | F29: =F64+F74 -> 0 | G29: =G60+G70 -> 0 | H29: =H60+H70 -> 168 | I29: =I60+I70 -> 0 | J29: =J60+J70 -> 0 | K29: =K60+K70 -> 0 | L29: =L60+L70 -> 0 | M29: =M60+M70 -> 0 | N29: =N60+N70 -> 0 | ... AF29: =AF60+AF70 -> 0
C30: 预收款项 | D30: =SUM(F30:AF30) -> 0 | E30: 万元
C31: 应付职工薪酬 | D31: =SUM(F31:AF31) -> 3360 | E31: 万元 | H31: ='表3-成本费用表'!H52 -> 134.4 | I31: ='表3-成本费用表'!I52 -> 134.4 | J31: ='表3-成本费用表'!J52 -> 134.4 | K31: ='表3-成本费用表'!K52 -> 134.4 | L31: ='表3-成本费用表'!L52 -> 134.4 | M31: ='表3-成本费用表'!M52 -> 134.4 | N31: ='表3-成本费用表'!N52 -> 134.4 | O31: ='表3-成本费用表'!O52 -> 134.4 | ... AF31: ='表3-成本费用表'!AF52 -> 134.4
C32: 应交税费 | D32: =SUM(F32:AF32) -> 13678.242 | E32: 万元 | H32: ='表6-现金流量表-资本金'!H24+'表6-现金流量表-资本金'!H25+'表6-现金流量表-资本金'!H29 -> 0 | I32: ='表6-现金流量表-资本金'!I24+'表6-现金流量表-资本金'!I25+'表6-现金流量表-资本金'!I29 -> 0 | J32: ='表6-现金流量表-资本金'!J24+'表6-现金流量表-资本金'!J25+'表6-现金流量表-资本金'!J29 -> 0 | K32: ='表6-现金流量表-资本金'!K24+'表6-现金流量表-资本金'!K25+'表6-现金流量表-资本金'!K29 -> 74.153174 | L32: ='表6-现金流量表-资本金'!L24+'表6-现金流量表-资本金'!L25+'表6-现金流量表-资本金'!L29 -> 78.991107 | M32: ='表6-现金流量表-资本金'!M24+'表6-现金流量表-资本金'!M25+'表6-现金流量表-资本金'!M29 -> 95.483049 | N32: ='表6-现金流量表-资本金'!N24+'表6-现金流量表-资本金'!N25+'表6-现金流量表-资本金'!N29 -> 369.75747 | O32: ='表6-现金流量表-资本金'!O24+'表6-现金流量表-资本金'!O25+'表6-现金流量表-资本金'!O29 -> 641.54379 | ... AF32: ='表6-现金流量表-资本金'!AF24+'表6-现金流量表-资本金'!AF25+'表6-现金流量表-资本金'!AF29 -> 910.14848
C33: 应付股利 | D33: =SUM(F33:AF33) -> 7848.1691 | E33: 万元 | H33: ='表5-利润表-资本金'!H31 -> 42.972905 | I33: ='表5-利润表-资本金'!I31 -> 81.247968 | J33: ='表5-利润表-资本金'!J31 -> 115.72324 | K33: ='表5-利润表-资本金'!K31 -> 140.45232 | L33: ='表5-利润表-资本金'!L31 -> 163.53078 | M33: ='表5-利润表-资本金'!M31 -> 192.61425 | N33: ='表5-利润表-资本金'!N31 -> 208.89735 | O33: ='表5-利润表-资本金'!O31 -> 222.71886 | ... AF33: ='表5-利润表-资本金'!AF31 -> 816.23524
C34: 其他流动负债 | D34: =SUM(F34:AF34) -> 0 | E34: 万元
B36: 借款还本付息表（长期借款）
B37: 序号 | C37: 项目 | D37: 合计 | E37: 单位 | F37: 建设期 | H37: 运营期
F38: 1 | G38: 2 | H38: 1 | I38: 2 | J38: 3 | K38: 4 | L38: 5 | M38: 6 | N38: 7 | O38: 8 | P38: 9 | Q38: 10 | R38: 11 | S38: 12 | T38: 13 | U38: 14 | V38: 15 | W38: 16 | X38: 17 | Y38: 18 | Z38: 19 | AA38: 20 | AB38: 21 | AC38: 22 | AD38: 23 | AE38: 24 | AF38: 25
B39: 1 | C39: 期初借款累计 | E39: 万元 | F39: 0 | G39: =F44 -> 21666.481 | H39: =G44 -> 21666.481 | I39: =H44 -> 20551.877 | J39: =I44 -> 19397.147 | K39: =J44 -> 18200.847 | L39: =K44 -> 16961.48 | M39: =L44 -> 15677.497 | N39: =M44 -> 14347.289 | ... AF39: =AE44 -> 0
B40: 2 | C40: 当期借款 | D40: =SUM(F40:AF40) -> 21666.481 | E40: 万元 | F40: =F15 -> 21666.481 | G40: =G15 -> 0
B41: 3 | C41: 当期还本付息 | D41: =SUM(F41:AF41) -> 28418.958 | E41: 万元 | H41: =-PMT(参数输入表!$H$126,参数输入表!$H$129,'表1-资金筹措及还本付息表'!$D$40) -> 1894.5972 | I41: =-PMT(参数输入表!$H$126,参数输入表!$H$129,'表1-资金筹措及还本付息表'!$D$40) -> 1894.5972 | J41: =-PMT(参数输入表!$H$126,参数输入表!$H$129,'表1-资金筹措及还本付息表'!$D$40) -> 1894.5972 | K41: =-PMT(参数输入表!$H$126,参数输入表!$H$129,'表1-资金筹措及还本付息表'!$D$40) -> 1894.5972 | L41: =-PMT(参数输入表!$H$126,参数输入表!$H$129,'表1-资金筹措及还本付息表'!$D$40) -> 1894.5972 | M41: =-PMT(参数输入表!$H$126,参数输入表!$H$129,'表1-资金筹措及还本付息表'!$D$40) -> 1894.5972 | N41: =-PMT(参数输入表!$H$126,参数输入表!$H$129,'表1-资金筹措及还本付息表'!$D$40) -> 1894.5972 | O41: =-PMT(参数输入表!$H$126,参数输入表!$H$129,'表1-资金筹措及还本付息表'!$D$40) -> 1894.5972 | ... V41: =-PMT(参数输入表!$H$126,参数输入表!$H$129,'表1-资金筹措及还本付息表'!$D$40) -> 1894.5972
C42: 其中：还本（等额本息） | D42: =SUM(F42:AF42) -> 21666.481 | E42: 万元 | H42: =H41-H43 -> 1114.6039 | I42: =I41-I43 -> 1154.7297 | J42: =J41-J43 -> 1196.2999 | K42: =K41-K43 -> 1239.3667 | L42: =L41-L43 -> 1283.9839 | M42: =M41-M43 -> 1330.2073 | N42: =N41-N43 -> 1378.0948 | O42: =O41-O43 -> 1427.7062 | ... V42: =V41-V43 -> 1828.7618
C43: 付息 | D43: =SUM(F43:AF43) -> 6752.4776 | E43: 万元 | H43: =(H39+H40/2)*参数输入表!$H$126 -> 779.9933 | I43: =(I39+I40/2)*参数输入表!$H$126 -> 739.86756 | J43: =(J39+J40/2)*参数输入表!$H$126 -> 698.2973 | K43: =(K39+K40/2)*参数输入表!$H$126 -> 655.2305 | L43: =(L39+L40/2)*参数输入表!$H$126 -> 610.6133 | M43: =(M39+M40/2)*参数输入表!$H$126 -> 564.38987 | N43: =(N39+N40/2)*参数输入表!$H$126 -> 516.50241 | O43: =(O39+O40/2)*参数输入表!$H$126 -> 466.891 | ... V43: =(V39+V40/2)*参数输入表!$H$126 -> 65.835425
B44: 4 | C44: 期末借款余额 | D44: =AF44 -> 0 | E44: 万元 | F44: =F39+F40-F42 -> 21666.481 | G44: =G39+G40-G42 -> 21666.481 | H44: =H39+H40-H42 -> 20551.877 | I44: =I39+I40-I42 -> 19397.147 | J44: =J39+J40-J42 -> 18200.847 | K44: =K39+K40-K42 -> 16961.48 | L44: =L39+L40-L42 -> 15677.497 | M44: =M39+M40-M42 -> 14347.289 | ... V44: =V39+V40-V42 -> 0
B46: 借款还本付息表（长期借款）
B47: 序号 | C47: 项目 | D47: 合计 | E47: 单位 | F47: 建设期 | H47: 运营期
F48: 1 | G48: 2 | H48: 1 | I48: 2 | J48: 3 | K48: 4 | L48: 5 | M48: 6 | N48: 7 | O48: 8 | P48: 9 | Q48: 10 | R48: 11 | S48: 12 | T48: 13 | U48: 14 | V48: 15 | W48: 16 | X48: 17 | Y48: 18 | Z48: 19 | AA48: 20 | AB48: 21 | AC48: 22 | AD48: 23 | AE48: 24 | AF48: 25
B49: 1 | C49: 期初借款累计 | E49: 万元 | F49: 0 | G49: =F54 -> 21666.481 | H49: =G54 -> 21666.481 | I49: =H54 -> 20222.049 | J49: =I54 -> 18777.617 | K49: =J54 -> 17333.185 | L49: =K54 -> 15888.752 | M49: =L54 -> 14444.32 | N49: =M54 -> 12999.888 | ... V49: =U54 -> 1444.432
B50: 2 | C50: 当期借款 | D50: =SUM(F50:AF50) -> 21666.481 | E50: 万元 | F50: =F15 -> 21666.481 | G50: =G15 -> 0
B51: 3 | C51: 当期还本付息 | D51: =SUM(F51:AF51) -> 27906.427 | E51: 万元 | H51: =SUM(H52:H53) -> 2224.4253 | I51: =SUM(I52:I53) -> 2172.4258 | J51: =SUM(J52:J53) -> 2120.4262 | K51: =SUM(K52:K53) -> 2068.4267 | L51: =SUM(L52:L53) -> 2016.4271 | M51: =SUM(M52:M53) -> 1964.4276 | N51: =SUM(N52:N53) -> 1912.428 | O51: =SUM(O52:O53) -> 1860.4285 | ... V51: =SUM(V52:V53) -> 1496.4316
C52: 其中：还本（等额本金） | D52: =SUM(F52:AF52) -> 21666.481 | E52: 万元 | H52: =$D$50/参数输入表!$H$129 -> 1444.432 | I52: =$D$50/参数输入表!$H$129 -> 1444.432 | J52: =$D$50/参数输入表!$H$129 -> 1444.432 | K52: =$D$50/参数输入表!$H$129 -> 1444.432 | L52: =$D$50/参数输入表!$H$129 -> 1444.432 | M52: =$D$50/参数输入表!$H$129 -> 1444.432 | N52: =$D$50/参数输入表!$H$129 -> 1444.432 | O52: =$D$50/参数输入表!$H$129 -> 1444.432 | ... V52: =$D$50/参数输入表!$H$129 -> 1444.432
C53: 付息 | D53: =SUM(F53:AF53) -> 6239.9464 | E53: 万元 | H53: =(H49+H50/2)*参数输入表!$H$126 -> 779.9933 | I53: =(I49+I50/2)*参数输入表!$H$126 -> 727.99375 | J53: =(J49+J50/2)*参数输入表!$H$126 -> 675.9942 | K53: =(K49+K50/2)*参数输入表!$H$126 -> 623.99464 | L53: =(L49+L50/2)*参数输入表!$H$126 -> 571.99509 | M53: =(M49+M50/2)*参数输入表!$H$126 -> 519.99554 | N53: =(N49+N50/2)*参数输入表!$H$126 -> 467.99598 | O53: =(O49+O50/2)*参数输入表!$H$126 -> 415.99643 | ... V53: =(V49+V50/2)*参数输入表!$H$126 -> 51.999554
B54: 4 | C54: 期末借款余额 | D54: =AF54 -> 0 | E54: 万元 | F54: =F49+F50-F52 -> 21666.481 | G54: =G49+G50-G52 -> 21666.481 | H54: =H49+H50-H52 -> 20222.049 | I54: =I49+I50-I52 -> 18777.617 | J54: =J49+J50-J52 -> 17333.185 | K54: =K49+K50-K52 -> 15888.752 | L54: =L49+L50-L52 -> 14444.32 | M54: =M49+M50-M52 -> 12999.888 | ... V54: =V49+V50-V52 -> -9.094947e-12
B56: 借款还本付息表（流动资金借款）
B57: 序号 | C57: 项目 | D57: 合计 | E57: 单位 | F57: 建设期 | H57: 运营期
F58: 1 | G58: 2 | H58: 1 | I58: 2 | J58: 3 | K58: 4 | L58: 5 | M58: 6 | N58: 7 | O58: 8 | P58: 9 | Q58: 10 | R58: 11 | S58: 12 | T58: 13 | U58: 14 | V58: 15 | W58: 16 | X58: 17 | Y58: 18 | Z58: 19 | AA58: 20 | AB58: 21 | AC58: 22 | AD58: 23 | AE58: 24 | AF58: 25
B59: 一 | C59: 期初借款累计 | E59: 万元 | F59: 0 | G59: =F64 -> 0 | H59: =G64 -> 0 | I59: =H64 -> 168 | J59: =I64 -> 168 | K59: =J64 -> 168 | L59: =K64 -> 168 | M59: =L64 -> 168 | N59: =M64 -> 168 | ... AF59: =AE64 -> 168
B60: 二 | C60: 当期借款 | D60: =SUM(F60:AF60) -> 168 | E60: 万元 | F60: 0 | G60: 0 | H60: =H15 -> 168
B61: 三 | C61: 当期还本付息 | D61: =SUM(F61:AF61) -> 298.2 | E61: 万元 | H61: =SUM(H62:H63) -> 5.208 | I61: =SUM(I62:I63) -> 5.208 | J61: =SUM(J62:J63) -> 5.208 | K61: =SUM(K62:K63) -> 5.208 | L61: =SUM(L62:L63) -> 5.208 | M61: =SUM(M62:M63) -> 5.208 | N61: =SUM(N62:N63) -> 5.208 | O61: =SUM(O62:O63) -> 5.208 | ... AF61: =SUM(AF62:AF63) -> 173.208
C62: 其中：还本 | D62: =SUM(F62:AF62) -> 168 | E62: 万元 | H62: =0 -> 0 | AF62: =H15 -> 168
C63: 付息 | D63: =SUM(F63:AF63) -> 130.2 | E63: 万元 | H63: =(H59+H60)*参数输入表!$H$127 -> 5.208 | I63: =H63 -> 5.208 | J63: =I63 -> 5.208 | K63: =J63 -> 5.208 | L63: =K63 -> 5.208 | M63: =L63 -> 5.208 | N63: =M63 -> 5.208 | O63: =N63 -> 5.208 | P63: =O63 -> 5.208 | ... AF63: =AE63 -> 5.208
B64: 四 | C64: 期末借款余额 | D64: =AF64 -> 0 | E64: 万元 | F64: =F59+F60-F62 -> 0 | G64: =G59+G60-G62 -> 0 | H64: =H59+H60-H62 -> 168 | I64: =I59+I60-I62 -> 168 | J64: =J59+J60-J62 -> 168 | K64: =K59+K60-K62 -> 168 | L64: =L59+L60-L62 -> 168 | M64: =M59+M60-M62 -> 168 | ... AF64: =AF59+AF60-AF62 -> 0
B66: 借款还本付息表（短期借款）
B67: 序号 | C67: 项目 | D67: 合计 | E67: 单位 | F67: 建设期 | H67: 运营期
F68: 1 | G68: 2 | H68: 1 | I68: 2 | J68: 3 | K68: 4 | L68: 5 | M68: 6 | N68: 7 | O68: 8 | P68: 9 | Q68: 10 | R68: 11 | S68: 12 | T68: 13 | U68: 14 | V68: 15 | W68: 16 | X68: 17 | Y68: 18 | Z68: 19 | AA68: 20 | AB68: 21 | AC68: 22 | AD68: 23 | AE68: 24 | AF68: 25
B69: 一 | C69: 期初借款累计 | E69: 万元 | F69: 0 | G69: =F74 -> 0 | H69: =G74 -> 0 | I69: =H74 -> 0 | J69: =I74 -> 0 | K69: =J74 -> 0 | L69: =K74 -> 0 | M69: =L74 -> 0 | N69: =M74 -> 0 | ... AF69: =AE74 -> 0
B70: 二 | C70: 当期借款 | D70: =SUM(F70:AF70) -> 0 | E70: 万元 | F70: 0 | G70: 0 | H70: =IF('表9-现金流量表-财务计划'!H42<0,ABS('表9-现金流量表-财务计划'!H42)/(1-参数输入表!$H$127),0) -> 0 | I70: =IF('表9-现金流量表-财务计划'!I42<0,ABS('表9-现金流量表-财务计划'!I42)/(1-参数输入表!$H$127),0) -> 0 | J70: =IF('表9-现金流量表-财务计划'!J42<0,ABS('表9-现金流量表-财务计划'!J42)/(1-参数输入表!$H$127),0) -> 0 | K70: =IF('表9-现金流量表-财务计划'!K42<0,ABS('表9-现金流量表-财务计划'!K42)/(1-参数输入表!$H$127),0) -> 0 | L70: =IF('表9-现金流量表-财务计划'!L42<0,ABS('表9-现金流量表-财务计划'!L42)/(1-参数输入表!$H$127),0) -> 0 | M70: =IF('表9-现金流量表-财务计划'!M42<0,ABS('表9-现金流量表-财务计划'!M42)/(1-参数输入表!$H$127),0) -> 0 | N70: =IF('表9-现金流量表-财务计划'!N42<0,ABS('表9-现金流量表-财务计划'!N42)/(1-参数输入表!$H$127),0) -> 0 | O70: =IF('表9-现金流量表-财务计划'!O42<0,ABS('表9-现金流量表-财务计划'!O42)/(1-参数输入表!$H$127),0) -> 0 | ... AF70: =IF('表9-现金流量表-财务计划'!AF42<0,ABS('表9-现金流量表-财务计划'!AF42)/(1-参数输入表!$H$127),0) -> 0
B71: 三 | C71: 当期还本付息 | D71: =SUM(F71:AF71) -> 0 | E71: 万元 | H71: =SUM(H72:H73) -> 0 | I71: =SUM(I72:I73) -> 0 | J71: =SUM(J72:J73) -> 0 | K71: =SUM(K72:K73) -> 0 | L71: =SUM(L72:L73) -> 0 | M71: =SUM(M72:M73) -> 0 | N71: =SUM(N72:N73) -> 0 | O71: =SUM(O72:O73) -> 0 | ... AF71: =SUM(AF72:AF73) -> 0
C72: 其中：还本 | D72: =SUM(F72:AF72) -> 0 | E72: 万元 | H72: 0 | I72: =H74 -> 0 | J72: =I74 -> 0 | K72: =J74 -> 0 | L72: =K74 -> 0 | M72: =L74 -> 0 | N72: =M74 -> 0 | O72: =N74 -> 0 | P72: =O74 -> 0 | ... AF72: =AE74 -> 0
C73: 付息 | D73: =SUM(F73:AF73) -> 0 | E73: 万元 | H73: =(H70)*参数输入表!$H$127 -> 0 | I73: =(I70)*参数输入表!$H$127 -> 0 | J73: =(J70)*参数输入表!$H$127 -> 0 | K73: =(K70)*参数输入表!$H$127 -> 0 | L73: =(L70)*参数输入表!$H$127 -> 0 | M73: =(M70)*参数输入表!$H$127 -> 0 | N73: =(N70)*参数输入表!$H$127 -> 0 | O73: =(O70)*参数输入表!$H$127 -> 0 | ... AF73: =(AF70)*参数输入表!$H$127 -> 0
B74: 四 | C74: 期末借款余额 | D74: =AF74 -> 0 | E74: 万元 | F74: =F69+F70-F72 -> 0 | G74: =G69+G70-G72 -> 0 | H74: =H69+H70-H72 -> 0 | I74: =I69+I70-I72 -> 0 | J74: =J69+J70-J72 -> 0 | K74: =K69+K70-K72 -> 0 | L74: =L69+L70-L72 -> 0 | M74: =M69+M70-M72 -> 0 | ... AF74: =AF69+AF70-AF72 -> 0
B76: 借款还本付息表（汇总—等额本息）
B77: 序号 | C77: 项目 | D77: 合计 | E77: 单位 | F77: 建设期 | H77: 运营期
F78: 1 | G78: 2 | H78: 1 | I78: 2 | J78: 3 | K78: 4 | L78: 5 | M78: 6 | N78: 7 | O78: 8 | P78: 9 | Q78: 10 | R78: 11 | S78: 12 | T78: 13 | U78: 14 | V78: 15 | W78: 16 | X78: 17 | Y78: 18 | Z78: 19 | AA78: 20 | AB78: 21 | AC78: 22 | AD78: 23 | AE78: 24 | AF78: 25
B79: 一 | C79: 期初借款累计 | E79: 万元 | F79: =F39+F59+F69 -> 0 | G79: =G39+G59+G69 -> 21666.481 | H79: =H39+H59+H69 -> 21666.481 | I79: =I39+I59+I69 -> 20719.877 | J79: =J39+J59+J69 -> 19565.147 | K79: =K39+K59+K69 -> 18368.847 | L79: =L39+L59+L69 -> 17129.48 | M79: =M39+M59+M69 -> 15845.497 | ... AF79: =AF39+AF59+AF69 -> 168
B80: 二 | C80: 当期借款 | D80: =SUM(F80:AF80) -> 21834.481 | E80: 万元 | F80: =F40+F60+F70 -> 21666.481 | G80: =G40+G60+G70 -> 0 | H80: =H40+H60+H70 -> 168 | I80: =I40+I60+I70 -> 0 | J80: =J40+J60+J70 -> 0 | K80: =K40+K60+K70 -> 0 | L80: =L40+L60+L70 -> 0 | M80: =M40+M60+M70 -> 0 | ... AF80: =AF40+AF60+AF70 -> 0
B81: 三 | C81: 当期还本付息 | D81: =SUM(F81:AF81) -> 28717.158 | E81: 万元 | H81: =H41+H61+H71 -> 1899.8052 | I81: =I41+I61+I71 -> 1899.8052 | J81: =J41+J61+J71 -> 1899.8052 | K81: =K41+K61+K71 -> 1899.8052 | L81: =L41+L61+L71 -> 1899.8052 | M81: =M41+M61+M71 -> 1899.8052 | N81: =N41+N61+N71 -> 1899.8052 | O81: =O41+O61+O71 -> 1899.8052 | ... AF81: =AF41+AF61+AF71 -> 173.208
C82: 其中：还本 | D82: =SUM(F82:AF82) -> 21834.481 | E82: 万元 | H82: =H42+H62+H72 -> 1114.6039 | I82: =I42+I62+I72 -> 1154.7297 | J82: =J42+J62+J72 -> 1196.2999 | K82: =K42+K62+K72 -> 1239.3667 | L82: =L42+L62+L72 -> 1283.9839 | M82: =M42+M62+M72 -> 1330.2073 | N82: =N42+N62+N72 -> 1378.0948 | O82: =O42+O62+O72 -> 1427.7062 | ... AF82: =AF42+AF62+AF72 -> 168
C83: 付息 | D83: =SUM(F83:AF83) -> 6882.6776 | E83: 万元 | H83: =H43+H63+H73 -> 785.2013 | I83: =I43+I63+I73 -> 745.07556 | J83: =J43+J63+J73 -> 703.5053 | K83: =K43+K63+K73 -> 660.4385 | L83: =L43+L63+L73 -> 615.8213 | M83: =M43+M63+M73 -> 569.59787 | N83: =N43+N63+N73 -> 521.71041 | O83: =O43+O63+O73 -> 472.099 | ... AF83: =AF43+AF63+AF73 -> 5.208
B84: 四 | C84: 期末借款余额 | D84: =AF84 -> 0 | E84: 万元 | F84: =F44+F64+F74 -> 21666.481 | G84: =G44+G64+G74 -> 21666.481 | H84: =H44+H64+H74 -> 20719.877 | I84: =I44+I64+I74 -> 19565.147 | J84: =J44+J64+J74 -> 18368.847 | K84: =K44+K64+K74 -> 17129.48 | L84: =L44+L64+L74 -> 15845.497 | M84: =M44+M64+M74 -> 14515.289 | ... AF84: =AF44+AF64+AF74 -> 0
B86: 借款还本付息表（汇总—等额本金）
B87: 序号 | C87: 项目 | D87: 合计 | E87: 单位 | F87: 建设期 | H87: 运营期
F88: 1 | G88: 2 | H88: 1 | I88: 2 | J88: 3 | K88: 4 | L88: 5 | M88: 6 | N88: 7 | O88: 8 | P88: 9 | Q88: 10 | R88: 11 | S88: 12 | T88: 13 | U88: 14 | V88: 15 | W88: 16 | X88: 17 | Y88: 18 | Z88: 19 | AA88: 20 | AB88: 21 | AC88: 22 | AD88: 23 | AE88: 24 | AF88: 25
B89: 一 | C89: 期初借款累计 | E89: 万元 | F89: =F49+F59+F69 -> 0 | G89: =G49+G59+G69 -> 21666.481 | H89: =H49+H59+H69 -> 21666.481 | I89: =I49+I59+I69 -> 20390.049 | J89: =J49+J59+J69 -> 18945.617 | K89: =K49+K59+K69 -> 17501.185 | L89: =L49+L59+L69 -> 16056.752 | M89: =M49+M59+M69 -> 14612.32 | ... AF89: =AF49+AF59+AF69 -> 168
B90: 二 | C90: 当期借款 | D90: =SUM(F90:AF90) -> 21834.481 | E90: 万元 | F90: =F50+F60+F70 -> 21666.481 | G90: =G50+G60+G70 -> 0 | H90: =H50+H60+H70 -> 168 | I90: =I50+I60+I70 -> 0 | J90: =J50+J60+J70 -> 0 | K90: =K50+K60+K70 -> 0 | L90: =L50+L60+L70 -> 0 | M90: =M50+M60+M70 -> 0 | ... AF90: =AF50+AF60+AF70 -> 0
B91: 三 | C91: 当期还本付息 | D91: =SUM(F91:AF91) -> 28204.627 | E91: 万元 | H91: =H51+H61+H71 -> 2229.6333 | I91: =I51+I61+I71 -> 2177.6338 | J91: =J51+J61+J71 -> 2125.6342 | K91: =K51+K61+K71 -> 2073.6347 | L91: =L51+L61+L71 -> 2021.6351 | M91: =M51+M61+M71 -> 1969.6356 | N91: =N51+N61+N71 -> 1917.636 | O91: =O51+O61+O71 -> 1865.6365 | ... AF91: =AF51+AF61+AF71 -> 173.208
C92: 其中：还本 | D92: =SUM(F92:AF92) -> 21834.481 | E92: 万元 | H92: =H52+H62+H72 -> 1444.432 | I92: =I52+I62+I72 -> 1444.432 | J92: =J52+J62+J72 -> 1444.432 | K92: =K52+K62+K72 -> 1444.432 | L92: =L52+L62+L72 -> 1444.432 | M92: =M52+M62+M72 -> 1444.432 | N92: =N52+N62+N72 -> 1444.432 | O92: =O52+O62+O72 -> 1444.432 | ... AF92: =AF52+AF62+AF72 -> 168
C93: 付息 | D93: =SUM(F93:AF93) -> 6370.1464 | E93: 万元 | H93: =H53+H63+H73 -> 785.2013 | I93: =I53+I63+I73 -> 733.20175 | J93: =J53+J63+J73 -> 681.2022 | K93: =K53+K63+K73 -> 629.20264 | L93: =L53+L63+L73 -> 577.20309 | M93: =M53+M63+M73 -> 525.20354 | N93: =N53+N63+N73 -> 473.20398 | O93: =O53+O63+O73 -> 421.20443 | ... AF93: =AF53+AF63+AF73 -> 5.208
B94: 四 | C94: 期末借款余额 | D94: =AF94 -> 0 | E94: 万元 | F94: =F54+F64+F74 -> 21666.481 | G94: =G54+G64+G74 -> 21666.481 | H94: =H54+H64+H74 -> 20390.049 | I94: =I54+I64+I74 -> 18945.617 | J94: =J54+J64+J74 -> 17501.185 | K94: =K54+K64+K74 -> 16056.752 | L94: =L54+L64+L74 -> 14612.32 | M94: =M54+M64+M74 -> 13167.888 | ... AF94: =AF54+AF64+AF74 -> 0
C97: 当期借款引用“资金筹措表”对应年份债务资金数据
C98: 等额本金/等额本息/其他，作为参数输入表—投融资相关板块中的可选择情形，匹配如下不同的计算方法
C99: （1）等额本息情形下，还本付息采用年金公式先得出每年的 本金+利息 之和（固定值），再结合各年度期初及当期借款金额计算出各年度应付利息，进而推算出每年偿还的本金。
C100: （2）等额本金情形下，每年的本金偿还为固定值（建设期借款总额/还款年限），再结合各年度期初及当期借款金额计算出各年度应付利息。
C101: （3）其他情形下，运营期每年的本金偿还设置为手动输入项
C103: 短期借款每年的当期借款及还本直接引用参数表的数据（初始默认为0）

Sheet 表2-折旧摊销表
C1: 中间过程引用（隐藏）
C2: 动态总投资（自主投资_不含流动资金） | D2: =参数输入表!H117 -> 27083.101
C3: 可抵扣进项税 | D3: =参数输入表!H120 -> 2571.0688
C4: 固定资产原值 | D4: =D2-D15-D3 -> 24512.032 | F4: 固定资产原值=项目动态总投资（自主投资_不含流动资金）-可抵扣进项税-无形资产原值=项目静态总投资-建设补贴+建设期利息-可抵扣进项税-无形资产原值
C5: 折旧方式 | D5: 直线法/其他
C6: 折旧年限 | D6: =参数输入表!H197 -> 20
C7: 残值率 | D7: =参数输入表!H198 -> 0.05
C8: 长期待摊费用（第1年） | D8: =参数输入表!H206/(1+参数输入表!H233) -> 0 | F8: 长期待摊费用=计入长期待摊的成本项/（1+增值税税率）
C9: 长期待摊费用（第6年） | D9: =参数输入表!H211/(1+参数输入表!H233) -> 0
C10: 长期待摊费用（第11年） | D10: =参数输入表!H216/(1+参数输入表!H233) -> 0
C11: 长期待摊费用（第16年） | D11: =参数输入表!H221/(1+参数输入表!H233) -> 0
C12: 长期待摊费用（第21年） | D12: =参数输入表!H226/(1+参数输入表!H233) -> 0
C13: 摊销方式 | D13: 直线法/其他 | H13: =D4*0.95/20 -> 1164.3215
C14: 摊销年限 | D14: =参数输入表!H232 -> 5
C15: 无形资产原值 | D15: =参数输入表!H200 -> 0
C16: 摊销方式 | D16: 直线法/其他
C17: 摊销年限 | D17: =参数输入表!H202 -> 10
C18: 残值率 | D18: =参数输入表!H203 -> 0
C19: 大修及更新重置资产原值 | D19: =参数输入表!H245/(1+参数输入表!$H$264) -> 0
C20: 摊销方式 | D20: 直线法/其他
C21: 摊销年限 | D21: =参数输入表!H262 -> 10
C22: 残值率 | D22: =参数输入表!H263 -> 0.05
B24: 折旧摊销表-资本金
B25: 序号 | C25: 科目 | D25: 合计 | E25: 单位 | F25: 建设期 | H25: 运营期
F26: 1 | G26: 2 | H26: 1 | I26: 2 | J26: 3 | K26: 4 | L26: 5 | M26: 6 | N26: 7 | O26: 8 | P26: 9 | Q26: 10 | R26: 11 | S26: 12 | T26: 13 | U26: 14 | V26: 15 | W26: 16 | X26: 17 | Y26: 18 | Z26: 19 | AA26: 20 | AB26: 21 | AC26: 22 | AD26: 23 | AE26: 24 | AF26: 25
B27: 1 | C27: 固定资产净值 | E27: 万元 | F27: =D28 -> 23286.43 | G27: =IF('表1-资金筹措及还本付息表'!G5=0,0,'表1-资金筹措及还本付息表'!F6+'表1-资金筹措及还本付息表'!G6-参数输入表!H120-参数输入表!H200) -> 0 | H27: =IF('表1-资金筹措及还本付息表'!G5=0,F27-H28,G27-H28) -> 22122.109 | I27: =H27-I28 -> 20957.787 | J27: =I27-J28 -> 19793.466 | K27: =J27-K28 -> 18629.144 | L27: =K27-L28 -> 17464.823 | M27: =L27-M28 -> 16300.501 | N27: =M27-N28 -> 15136.18 | O27: =N27-O28 -> 13971.858 | P27: =O27-P28 -> 12807.537 | ... AF27: =AE27-AF28 -> -1.8189894e-12
C28: 当期固定资产折旧 | D28: =SUM(F28:AF28) -> 23286.43 | E28: 万元 | H28: =IF(H26<=$D$6,$D$4*(1-$D$7)/($D$6),0) -> 1164.3215 | I28: =IF(I26<=$D$6,$D$4*(1-$D$7)/($D$6),0) -> 1164.3215 | J28: =IF(J26<=$D$6,$D$4*(1-$D$7)/($D$6),0) -> 1164.3215 | K28: =IF(K26<=$D$6,$D$4*(1-$D$7)/($D$6),0) -> 1164.3215 | L28: =IF(L26<=$D$6,$D$4*(1-$D$7)/($D$6),0) -> 1164.3215 | M28: =IF(M26<=$D$6,$D$4*(1-$D$7)/($D$6),0) -> 1164.3215 | N28: =IF(N26<=$D$6,$D$4*(1-$D$7)/($D$6),0) -> 1164.3215 | O28: =IF(O26<=$D$6,$D$4*(1-$D$7)/($D$6),0) -> 1164.3215 | ... AF28: =IF(AF26<=$D$6,$D$4*(1-$D$7)/($D$6),0) -> 0
B29: 2 | C29: 期初长期待摊费用 | E29: 万元 | H29: 0 | I29: =H32 -> 0 | J29: =I32 -> 0 | K29: =J32 -> 0 | L29: =K32 -> 0 | M29: =L32 -> 0 | N29: =M32 -> 0 | O29: =N32 -> 0 | P29: =O32 -> 0 | ... AF29: =AE32 -> 0
C30: 当期新增长期待摊费用 | H30: =参数输入表!H206/(1+参数输入表!H233) -> 0 | I30: =参数输入表!H207/(1+参数输入表!H233) -> 0 | J30: =参数输入表!H208/(1+参数输入表!H233) -> 0 | K30: =参数输入表!H209/(1+参数输入表!H233) -> 0 | L30: =参数输入表!H210/(1+参数输入表!H233) -> 0 | M30: =参数输入表!H211/(1+参数输入表!H233) -> 0 | N30: =参数输入表!H212/(1+参数输入表!H233) -> 0 | O30: =参数输入表!H213/(1+参数输入表!H233) -> 0 | P30: =参数输入表!H214/(1+参数输入表!H233) -> 0 | Q30: =参数输入表!H215/(1+参数输入表!H233) -> 0 | R30: =参数输入表!H216/(1+参数输入表!H233) -> 0 | S30: =参数输入表!H217/(1+参数输入表!H233) -> 0 | T30: =参数输入表!H218/(1+参数输入表!H233) -> 0 | U30: =参数输入表!H219/(1+参数输入表!H233) -> 0 | V30: =参数输入表!H220/(1+参数输入表!H233) -> 0 | W30: =参数输入表!H221/(1+参数输入表!H233) -> 0 | X30: =参数输入表!H222/(1+参数输入表!H233) -> 0 | Y30: =参数输入表!H223/(1+参数输入表!H233) -> 0 | Z30: =参数输入表!H224/(1+参数输入表!H233) -> 0 | AA30: =参数输入表!H225/(1+参数输入表!H233) -> 0 | AB30: =参数输入表!H226/(1+参数输入表!H233) -> 0 | AC30: =参数输入表!H227/(1+参数输入表!H233) -> 0 | AD30: =参数输入表!H228/(1+参数输入表!H233) -> 0 | AE30: =参数输入表!H229/(1+参数输入表!H233) -> 0 | AF30: =参数输入表!H230/(1+参数输入表!H233) -> 0
C31: 当期摊销 | D31: =SUM(F31:AF31) -> 0 | E31: 万元 | H31: =H30/$D$14 -> 0 | I31: =H31 -> 0 | J31: =I31 -> 0 | K31: =J31 -> 0 | L31: =K31 -> 0 | M31: =M30/$D$14 -> 0 | N31: =M31 -> 0 | O31: =N31 -> 0 | P31: =O31 -> 0 | Q31: =P31 -> 0 | R31: =R30/$D$14 -> 0 | S31: =R31 -> 0 | T31: =S31 -> 0 | U31: =T31 -> 0 | V31: =U31 -> 0 | W31: =W30/$D$14 -> 0 | X31: =W31 -> 0 | Y31: =X31 -> 0 | Z31: =Y31 -> 0 | AA31: =Z31 -> 0 | AB31: =AB30/$D$14 -> 0 | AC31: =AB31 -> 0 | AD31: =AC31 -> 0 | AE31: =AD31 -> 0 | AF31: =AE31 -> 0
C32: 期末期初长期待摊费用 | H32: =H29+H30-H31 -> 0 | I32: =I29+I30-I31 -> 0 | J32: =J29+J30-J31 -> 0 | K32: =K29+K30-K31 -> 0 | L32: =L29+L30-L31 -> 0 | M32: =M29+M30-M31 -> 0 | N32: =N29+N30-N31 -> 0 | O32: =O29+O30-O31 -> 0 | ... AF32: =AF29+AF30-AF31 -> 0
B33: 3 | C33: 无形资产净值 | E33: 万元 | F33: =参数输入表!$H$200*参数输入表!$H$7 -> 0 | G33: =参数输入表!$H$200*参数输入表!$H$7+参数输入表!$H$200*参数输入表!$H$8 -> 0 | H33: =G33-H34 -> 0 | I33: =H33-I34 -> 0 | J33: =I33-J34 -> 0 | K33: =J33-K34 -> 0 | L33: =K33-L34 -> 0 | M33: =L33-M34 -> 0 | N33: =M33-N34 -> 0 | O33: =N33-O34 -> 0 | ... AF33: =AE33-AF34 -> 0
C34: 当期无形资产摊销 | D34: =SUM(F34:AF34) -> 0 | E34: 万元 | H34: =IF(H26<=$D$17,G33*(1-$D$18)/($D$17-H26+1),0) -> 0 | I34: =IF(I26<=$D$17,H33*(1-$D$18)/($D$17-I26+1),0) -> 0 | J34: =IF(J26<=$D$17,I33*(1-$D$18)/($D$17-J26+1),0) -> 0 | K34: =IF(K26<=$D$17,J33*(1-$D$18)/($D$17-K26+1),0) -> 0 | L34: =IF(L26<=$D$17,K33*(1-$D$18)/($D$17-L26+1),0) -> 0 | M34: =IF(M26<=$D$17,L33*(1-$D$18)/($D$17-M26+1),0) -> 0 | N34: =IF(N26<=$D$17,M33*(1-$D$18)/($D$17-N26+1),0) -> 0 | O34: =IF(O26<=$D$17,N33*(1-$D$18)/($D$17-O26+1),0) -> 0 | ... AF34: =IF(AF26<=$D$17,AE33*(1-$D$18)/($D$17-AF26+1),0) -> 0
B35: 4 | C35: 期初大修及更新重置资产净值 | E35: 万元 | H35: 0 | I35: =H38 -> 0 | J35: =I38 -> 0 | K35: =J38 -> 0 | L35: =K38 -> 0 | M35: =L38 -> 0 | N35: =M38 -> 0 | O35: =N38 -> 0 | P35: =O38 -> 0 | ... AF35: =AE38 -> 21.238938
C36: 当期新增大修及更新重置资产 | H36: =参数输入表!H236/(1+参数输入表!$H$264) -> 0 | I36: =参数输入表!H237/(1+参数输入表!$H$264) -> 0 | J36: =参数输入表!H238/(1+参数输入表!$H$264) -> 0 | K36: =参数输入表!H239/(1+参数输入表!$H$264) -> 0 | L36: =参数输入表!H240/(1+参数输入表!$H$264) -> 0 | M36: =参数输入表!H241/(1+参数输入表!$H$264) -> 0 | N36: =参数输入表!H242/(1+参数输入表!$H$264) -> 0 | O36: =参数输入表!H243/(1+参数输入表!$H$264) -> 0 | P36: =参数输入表!H244/(1+参数输入表!$H$264) -> 0 | Q36: =参数输入表!H245/(1+参数输入表!$H$264) -> 0 | R36: =参数输入表!H246/(1+参数输入表!$H$264) -> 424.77876 | S36: =参数输入表!H247/(1+参数输入表!$H$264) -> 0 | T36: =参数输入表!H248/(1+参数输入表!$H$264) -> 0 | U36: =参数输入表!H249/(1+参数输入表!$H$264) -> 0 | V36: =参数输入表!H250/(1+参数输入表!$H$264) -> 0 | W36: =参数输入表!H251/(1+参数输入表!$H$264) -> 0 | X36: =参数输入表!H252/(1+参数输入表!$H$264) -> 0 | Y36: =参数输入表!H253/(1+参数输入表!$H$264) -> 0 | Z36: =参数输入表!H254/(1+参数输入表!$H$264) -> 0 | AA36: =参数输入表!H255/(1+参数输入表!$H$264) -> 0 | AB36: =参数输入表!H256/(1+参数输入表!$H$264) -> 0 | AC36: =参数输入表!H257/(1+参数输入表!$H$264) -> 0 | AD36: =参数输入表!H258/(1+参数输入表!$H$264) -> 0 | AE36: =参数输入表!H259/(1+参数输入表!$H$264) -> 0 | AF36: =参数输入表!H260/(1+参数输入表!$H$264) -> 0
C37: 当期大修及更新重置资产折旧摊销 | D37: =SUM(F37:AF37) -> 403.53982 | E37: 万元 | H37: 0 | I37: 0 | J37: 0 | K37: 0 | L37: 0 | M37: 0 | N37: 0 | O37: 0 | P37: 0 | Q37: =Q36/D21 -> 0 | R37: =IF(参数输入表!$H$262>(R26-$R$26),$R$36*(1-参数输入表!$H$263)/参数输入表!$H$262,0) -> 40.353982 | S37: =IF(参数输入表!$H$262>(S26-$R$26),$R$36*(1-参数输入表!$H$263)/参数输入表!$H$262,0) -> 40.353982 | T37: =IF(参数输入表!$H$262>(T26-$R$26),$R$36*(1-参数输入表!$H$263)/参数输入表!$H$262,0) -> 40.353982 | U37: =IF(参数输入表!$H$262>(U26-$R$26),$R$36*(1-参数输入表!$H$263)/参数输入表!$H$262,0) -> 40.353982 | V37: =IF(参数输入表!$H$262>(V26-$R$26),$R$36*(1-参数输入表!$H$263)/参数输入表!$H$262,0) -> 40.353982 | W37: =IF(参数输入表!$H$262>(W26-$R$26),$R$36*(1-参数输入表!$H$263)/参数输入表!$H$262,0) -> 40.353982 | X37: =IF(参数输入表!$H$262>(X26-$R$26),$R$36*(1-参数输入表!$H$263)/参数输入表!$H$262,0) -> 40.353982 | Y37: =IF(参数输入表!$H$262>(Y26-$R$26),$R$36*(1-参数输入表!$H$263)/参数输入表!$H$262,0) -> 40.353982 | ... AB37: =IF(参数输入表!$H$262>(AB26-$R$26),$R$36*(1-参数输入表!$H$263)/参数输入表!$H$262,0) -> 0 | AC37: =IF(参数输入表!$H$262>=(AC26-$R$26),$R$36*(1-参数输入表!$H$263)/参数输入表!$H$262,0) -> 0 | AD37: =IF(参数输入表!$H$262>=(AD26-$R$26),$R$36*(1-参数输入表!$H$263)/参数输入表!$H$262,0) -> 0 | AE37: =IF(参数输入表!$H$262>=(AE26-$R$26),$R$36*(1-参数输入表!$H$263)/参数输入表!$H$262,0) -> 0 | AF37: =IF(参数输入表!$H$262>=(AF26-$R$26),$R$36*(1-参数输入表!$H$263)/参数输入表!$H$262,0) -> 0
C38: 期末大修及更新重置资产净值 | H38: =H35+H36-H37 -> 0 | I38: =I35+I36-I37 -> 0 | J38: =J35+J36-J37 -> 0 | K38: =K35+K36-K37 -> 0 | L38: =L35+L36-L37 -> 0 | M38: =M35+M36-M37 -> 0 | N38: =N35+N36-N37 -> 0 | O38: =O35+O36-O37 -> 0 | ... AF38: =AF35+AF36-AF37 -> 21.238938
B39: 5 | C39: 当期折旧摊销 | D39: =SUM(F39:AF39) -> 23689.97 | E39: 万元 | F39: =F28+F31+F34+F37 -> 0 | G39: =G28+G31+G34+G37 -> 0 | H39: =H28+H31+H34+H37 -> 1164.3215 | I39: =I28+I31+I34+I37 -> 1164.3215 | J39: =J28+J31+J34+J37 -> 1164.3215 | K39: =K28+K31+K34+K37 -> 1164.3215 | L39: =L28+L31+L34+L37 -> 1164.3215 | M39: =M28+M31+M34+M37 -> 1164.3215 | ... AF39: =AF28+AF31+AF34+AF37 -> 0
C42: 上述为“直线法”下折旧摊销计算，若在参数输入表中下拉菜单选择为“其他”，设置为手动输入各年份折旧额/摊销额
C44: 中间过程引用（隐藏）
C45: 静态总投资（自主投资） | D45: =D2 -> 27083.101
C46: 可抵扣进项税 | D46: =参数输入表!H120 -> 2571.0688
C47: 固定资产原值 | D47: =D45-D46-参数输入表!H200 -> 24512.032 | F47: 全投资情形下的固定资产原值=静态总投资（自主投资）-可抵扣进项税-无形资产原值；资本金情形下的固定资产原值采用的是“项目动态总投资（自主投资_不含流动资金）”
C48: 折旧方式 | D48: 直线法/其他 | F48: 折旧方式、残值率及折旧年限与资本金情形保持一致
C49: 折旧年限 | D49: =参数输入表!H197 -> 20
C50: 残值率 | D50: =参数输入表!H198 -> 0.05
B52: 折旧摊销表-全投资
B53: 序号 | C53: 科目 | D53: 合计 | E53: 单位 | F53: 建设期 | H53: 运营期
F54: 1 | G54: 2 | H54: 1 | I54: 2 | J54: 3 | K54: 4 | L54: 5 | M54: 6 | N54: 7 | O54: 8 | P54: 9 | Q54: 10 | R54: 11 | S54: 12 | T54: 13 | U54: 14 | V54: 15 | W54: 16 | X54: 17 | Y54: 18 | Z54: 19 | AA54: 20 | AB54: 21 | AC54: 22 | AD54: 23 | AE54: 24 | AF54: 25
B55: 1 | C55: 固定资产净值（全投资） | E55: 万元 | F55: =F27 -> 23286.43 | G55: =IF('表1-资金筹措及还本付息表'!G5=0,0,'表1-资金筹措及还本付息表'!F7+'表1-资金筹措及还本付息表'!G7-参数输入表!H120-参数输入表!H200) -> 0 | H55: =IF('表1-资金筹措及还本付息表'!G5=0,F55-H56,G55-H56) -> 22122.109 | I55: =H55-I56 -> 20957.787 | J55: =I55-J56 -> 19793.466 | K55: =J55-K56 -> 18629.144 | L55: =K55-L56 -> 17464.823 | M55: =L55-M56 -> 16300.501 | N55: =M55-N56 -> 15136.18 | O55: =N55-O56 -> 13971.858 | P55: =O55-P56 -> 12807.537 | ... AF55: =AE55-AF56 -> -1.8189894e-12
C56: 当期固定资产折旧 | D56: =SUM(F56:AF56) -> 23286.43 | E56: 万元 | H56: =IF(H54<=$D$49,$D$47*(1-$D$50)/($D$49-H54+1),0) -> 1164.3215 | I56: =I28 -> 1164.3215 | J56: =J28 -> 1164.3215 | K56: =K28 -> 1164.3215 | L56: =L28 -> 1164.3215 | M56: =M28 -> 1164.3215 | N56: =N28 -> 1164.3215 | O56: =O28 -> 1164.3215 | P56: =P28 -> 1164.3215 | ... AF56: =AF28 -> 0
B57: 2 | C57: 期初长期待摊费用 | E57: 万元 | H57: 0 | I57: =H60 -> 0 | J57: =I60 -> 0 | K57: =J60 -> 0 | L57: =K60 -> 0 | M57: =L60 -> 0 | N57: =M60 -> 0 | O57: =N60 -> 0 | P57: =O60 -> 0 | ... AF57: =AE60 -> 0
C58: 当期新增长期待摊费用 | H58: =H30 -> 0 | I58: =I30 -> 0 | J58: =J30 -> 0 | K58: =K30 -> 0 | L58: =L30 -> 0 | M58: =M30 -> 0 | N58: =N30 -> 0 | O58: =O30 -> 0 | ... AF58: =AF30 -> 0
C59: 当期摊销 | D59: =SUM(F59:AF59) -> 0 | E59: 万元 | H59: =H58/$D$14 -> 0 | I59: =H59 -> 0 | J59: =I59 -> 0 | K59: =J59 -> 0 | L59: =K59 -> 0 | M59: =M58/$D$14 -> 0 | N59: =M59 -> 0 | O59: =N59 -> 0 | P59: =O59 -> 0 | Q59: =P59 -> 0 | R59: =R58/$D$14 -> 0 | S59: =R59 -> 0 | T59: =S59 -> 0 | U59: =T59 -> 0 | V59: =U59 -> 0 | W59: =W58/$D$14 -> 0 | X59: =W59 -> 0 | Y59: =X59 -> 0 | Z59: =Y59 -> 0 | AA59: =Z59 -> 0 | AB59: =AB58/$D$14 -> 0 | AC59: =AB59 -> 0 | AD59: =AC59 -> 0 | AE59: =AD59 -> 0 | AF59: =AE59 -> 0
C60: 期末期初长期待摊费用 | H60: =H57+H58-H59 -> 0 | I60: =I57+I58-I59 -> 0 | J60: =J57+J58-J59 -> 0 | K60: =K57+K58-K59 -> 0 | L60: =L57+L58-L59 -> 0 | M60: =M57+M58-M59 -> 0 | N60: =N57+N58-N59 -> 0 | O60: =O57+O58-O59 -> 0 | ... AF60: =AF57+AF58-AF59 -> 0
B61: 3 | C61: 无形资产净值 | E61: 万元 | F61: =参数输入表!$H$200*参数输入表!$H$7 -> 0 | G61: =参数输入表!$H$200*参数输入表!$H$7+参数输入表!$H$200*参数输入表!$H$8 -> 0 | H61: =G61-H62 -> 0 | I61: =H61-I62 -> 0 | J61: =I61-J62 -> 0 | K61: =J61-K62 -> 0 | L61: =K61-L62 -> 0 | M61: =L61-M62 -> 0 | N61: =M61-N62 -> 0 | O61: =N61-O62 -> 0 | ... AF61: =AE61-AF62 -> 0
C62: 当期无形资产摊销 | D62: =SUM(F62:AF62) -> 0 | E62: 万元 | H62: =IF(H54<=$D$17,G61*(1-$D$18)/($D$17-H26+1),0) -> 0 | I62: =IF(I54<=$D$17,H61*(1-$D$18)/($D$17-I26+1),0) -> 0 | J62: =IF(J54<=$D$17,I61*(1-$D$18)/($D$17-J26+1),0) -> 0 | K62: =IF(K54<=$D$17,J61*(1-$D$18)/($D$17-K26+1),0) -> 0 | L62: =IF(L54<=$D$17,K61*(1-$D$18)/($D$17-L26+1),0) -> 0 | M62: =IF(M54<=$D$17,L61*(1-$D$18)/($D$17-M26+1),0) -> 0 | N62: =IF(N54<=$D$17,M61*(1-$D$18)/($D$17-N26+1),0) -> 0 | O62: =IF(O54<=$D$17,N61*(1-$D$18)/($D$17-O26+1),0) -> 0 | ... AF62: =IF(AF54<=$D$17,AE61*(1-$D$18)/($D$17-AF26+1),0) -> 0
B63: 4 | C63: 期初大修及更新重置资产净值 | E63: 万元 | H63: =H35 -> 0 | I63: =I35 -> 0 | J63: =J35 -> 0 | K63: =K35 -> 0 | L63: =L35 -> 0 | M63: =M35 -> 0 | N63: =N35 -> 0 | O63: =O35 -> 0 | ... AF63: =AF35 -> 21.238938
C64: 当期新增大修及更新重置资产 | H64: =H36 -> 0 | I64: =I36 -> 0 | J64: =J36 -> 0 | K64: =K36 -> 0 | L64: =L36 -> 0 | M64: =M36 -> 0 | N64: =N36 -> 0 | O64: =O36 -> 0 | ... AF64: =AF36 -> 0
C65: 当期大修及更新重置资产折旧摊销 | D65: =SUM(F65:AF65) -> 403.53982 | E65: 万元 | H65: =H37 -> 0 | I65: =I37 -> 0 | J65: =J37 -> 0 | K65: =K37 -> 0 | L65: =L37 -> 0 | M65: =M37 -> 0 | N65: =N37 -> 0 | O65: =O37 -> 0 | ... AF65: =AF37 -> 0
C66: 期末大修及更新重置资产净值 | H66: =H38 -> 0 | I66: =I38 -> 0 | J66: =J38 -> 0 | K66: =K38 -> 0 | L66: =L38 -> 0 | M66: =M38 -> 0 | N66: =N38 -> 0 | O66: =O38 -> 0 | ... AF66: =AF38 -> 21.238938
B67: 5 | C67: 当期折旧摊销 | D67: =SUM(F67:AF67) -> 23689.97 | E67: 万元 | F67: =F56+F59+F62+F65 -> 0 | G67: =G56+G59+G62+G65 -> 0 | H67: =H56+H59+H62+H65 -> 1164.3215 | I67: =I56+I59+I62+I65 -> 1164.3215 | J67: =J56+J59+J62+J65 -> 1164.3215 | K67: =K56+K59+K62+K65 -> 1164.3215 | L67: =L56+L59+L62+L65 -> 1164.3215 | M67: =M56+M59+M62+M65 -> 1164.3215 | ... AF67: =AF56+AF59+AF62+AF65 -> 0

Sheet 表3-成本费用表
B2: 成本费用表-资本金
B3: 序号 | C3: 项目 | D3: 合计 | E3: 单位 | F3: 建设期 | H3: 运营期
F4: 1 | G4: 2 | H4: 1 | I4: 2 | J4: 3 | K4: 4 | L4: 5 | M4: 6 | N4: 7 | O4: 8 | P4: 9 | Q4: 10 | R4: 11 | S4: 12 | T4: 13 | U4: 14 | V4: 15 | W4: 16 | X4: 17 | Y4: 18 | Z4: 19 | AA4: 20 | AB4: 21 | AC4: 22 | AD4: 23 | AE4: 24 | AF4: 25
B5: 一 | C5: 营业总成本 | D5: =SUM(F5:AF5) -> 46821.458 | E5: 万元 | H5: =H6+H15+H16+H19+H20 -> 2517.4608 | I5: =I6+I15+I16+I19+I20 -> 2465.4612 | J5: =J6+J15+J16+J19+J20 -> 2413.4617 | K5: =K6+K15+K16+K19+K20 -> 2361.4621 | L5: =L6+L15+L16+L19+L20 -> 2309.4626 | M5: =M6+M15+M16+M19+M20 -> 2308.7209 | N5: =N6+N15+N16+N19+N20 -> 2256.7213 | O5: =O6+O15+O16+O19+O20 -> 2204.7218 | ... AF5: =AF6+AF15+AF16+AF19+AF20 -> 778.17739
B6: 1 | C6: 生产成本 | D6: =SUM(F6:AF6) -> 38919.31 | H6: =SUM(H7:H14) -> 1670.9794 | I6: =SUM(I7:I14) -> 1670.9794 | J6: =SUM(J7:J14) -> 1670.9794 | K6: =SUM(K7:K14) -> 1670.9794 | L6: =SUM(L7:L14) -> 1670.9794 | M6: =SUM(M7:M14) -> 1722.2372 | N6: =SUM(N7:N14) -> 1722.2372 | O6: =SUM(O7:O14) -> 1722.2372 | ... AF6: =SUM(AF7:AF14) -> 711.68931
B7: 1.1 | C7: 材料费 | D7: =SUM(F7:AF7) -> 3600 | E7: 万元 | H7: =参数输入表!$H$141*参数输入表!$H$13/(1+参数输入表!$H$146) -> 144 | I7: =参数输入表!$H$141*参数输入表!$H$13/(1+参数输入表!$H$146) -> 144 | J7: =参数输入表!$H$141*参数输入表!$H$13/(1+参数输入表!$H$146) -> 144 | K7: =参数输入表!$H$141*参数输入表!$H$13/(1+参数输入表!$H$146) -> 144 | L7: =参数输入表!$H$141*参数输入表!$H$13/(1+参数输入表!$H$146) -> 144 | M7: =参数输入表!$H$142*参数输入表!$H$13/(1+参数输入表!$H$146) -> 144 | N7: =参数输入表!$H$142*参数输入表!$H$13/(1+参数输入表!$H$146) -> 144 | O7: =参数输入表!$H$142*参数输入表!$H$13/(1+参数输入表!$H$146) -> 144 | P7: =参数输入表!$H$142*参数输入表!$H$13/(1+参数输入表!$H$146) -> 144 | Q7: =参数输入表!$H$142*参数输入表!$H$13/(1+参数输入表!$H$146) -> 144 | R7: =参数输入表!$H$143*参数输入表!$H$13/(1+参数输入表!$H$146) -> 144 | S7: =参数输入表!$H$143*参数输入表!$H$13/(1+参数输入表!$H$146) -> 144 | T7: =参数输入表!$H$143*参数输入表!$H$13/(1+参数输入表!$H$146) -> 144 | U7: =参数输入表!$H$143*参数输入表!$H$13/(1+参数输入表!$H$146) -> 144 | V7: =参数输入表!$H$143*参数输入表!$H$13/(1+参数输入表!$H$146) -> 144 | W7: =参数输入表!$H$144*参数输入表!$H$13/(1+参数输入表!$H$146) -> 144 | X7: =参数输入表!$H$144*参数输入表!$H$13/(1+参数输入表!$H$146) -> 144 | Y7: =参数输入表!$H$144*参数输入表!$H$13/(1+参数输入表!$H$146) -> 144 | Z7: =参数输入表!$H$144*参数输入表!$H$13/(1+参数输入表!$H$146) -> 144 | AA7: =参数输入表!$H$144*参数输入表!$H$13/(1+参数输入表!$H$146) -> 144 | AB7: =参数输入表!$H$145*参数输入表!$H$13/(1+参数输入表!$H$146) -> 144 | AC7: =参数输入表!$H$145*参数输入表!$H$13/(1+参数输入表!$H$146) -> 144 | AD7: =参数输入表!$H$145*参数输入表!$H$13/(1+参数输入表!$H$146) -> 144 | AE7: =参数输入表!$H$145*参数输入表!$H$13/(1+参数输入表!$H$146) -> 144 | AF7: =参数输入表!$H$145*参数输入表!$H$13/(1+参数输入表!$H$146) -> 144
B8: 1.2 | C8: 维修费 | D8: =SUM(F8:AF8) -> 3619.3397 | E8: 万元 | H8: =(参数输入表!$H$113-参数输入表!$H$120)*参数输入表!$H$150/(1+参数输入表!$H$155) -> 48.257862 | I8: =(参数输入表!$H$113-参数输入表!$H$120)*参数输入表!$H$150/(1+参数输入表!$H$155) -> 48.257862 | J8: =(参数输入表!$H$113-参数输入表!$H$120)*参数输入表!$H$150/(1+参数输入表!$H$155) -> 48.257862 | K8: =(参数输入表!$H$113-参数输入表!$H$120)*参数输入表!$H$150/(1+参数输入表!$H$155) -> 48.257862 | L8: =(参数输入表!$H$113-参数输入表!$H$120)*参数输入表!$H$150/(1+参数输入表!$H$155) -> 48.257862 | M8: =(参数输入表!$H$113-参数输入表!$H$120)*参数输入表!$H$151/(1+参数输入表!$H$155) -> 96.515725 | N8: =(参数输入表!$H$113-参数输入表!$H$120)*参数输入表!$H$151/(1+参数输入表!$H$155) -> 96.515725 | O8: =(参数输入表!$H$113-参数输入表!$H$120)*参数输入表!$H$151/(1+参数输入表!$H$155) -> 96.515725 | P8: =(参数输入表!$H$113-参数输入表!$H$120)*参数输入表!$H$151/(1+参数输入表!$H$155) -> 96.515725 | Q8: =(参数输入表!$H$113-参数输入表!$H$120)*参数输入表!$H$151/(1+参数输入表!$H$155) -> 96.515725 | R8: =(参数输入表!$H$113-参数输入表!$H$120)*参数输入表!$H$152/(1+参数输入表!$H$155) -> 144.77359 | S8: =(参数输入表!$H$113-参数输入表!$H$120)*参数输入表!$H$152/(1+参数输入表!$H$155) -> 144.77359 | T8: =(参数输入表!$H$113-参数输入表!$H$120)*参数输入表!$H$152/(1+参数输入表!$H$155) -> 144.77359 | U8: =(参数输入表!$H$113-参数输入表!$H$120)*参数输入表!$H$152/(1+参数输入表!$H$155) -> 144.77359 | V8: =(参数输入表!$H$113-参数输入表!$H$120)*参数输入表!$H$152/(1+参数输入表!$H$155) -> 144.77359 | W8: =(参数输入表!$H$113-参数输入表!$H$120)*参数输入表!$H$153/(1+参数输入表!$H$155) -> 193.03145 | X8: =(参数输入表!$H$113-参数输入表!$H$120)*参数输入表!$H$153/(1+参数输入表!$H$155) -> 193.03145 | Y8: =(参数输入表!$H$113-参数输入表!$H$120)*参数输入表!$H$153/(1+参数输入表!$H$155) -> 193.03145 | Z8: =(参数输入表!$H$113-参数输入表!$H$120)*参数输入表!$H$153/(1+参数输入表!$H$155) -> 193.03145 | AA8: =(参数输入表!$H$113-参数输入表!$H$120)*参数输入表!$H$153/(1+参数输入表!$H$155) -> 193.03145 | AB8: =(参数输入表!$H$113-参数输入表!$H$120)*参数输入表!$H$154/(1+参数输入表!$H$155) -> 241.28931 | AC8: =(参数输入表!$H$113-参数输入表!$H$120)*参数输入表!$H$154/(1+参数输入表!$H$155) -> 241.28931 | AD8: =(参数输入表!$H$113-参数输入表!$H$120)*参数输入表!$H$154/(1+参数输入表!$H$155) -> 241.28931 | AE8: =(参数输入表!$H$113-参数输入表!$H$120)*参数输入表!$H$154/(1+参数输入表!$H$155) -> 241.28931 | AF8: =(参数输入表!$H$113-参数输入表!$H$120)*参数输入表!$H$154/(1+参数输入表!$H$155) -> 241.28931
B9: 1.3 | C9: 生产人员薪酬及福利 | D9: =SUM(F9:AF9) -> 3360 | E9: 万元 | H9: =(参数输入表!$H$167*参数输入表!$H$170+参数输入表!$H$168*参数输入表!$H$171)*(1+参数输入表!$H$172)*(1+参数输入表!$H$173*(H4-1))/(1+参数输入表!$H$174) -> 134.4 | I9: =(参数输入表!$H$167*参数输入表!$H$170+参数输入表!$H$168*参数输入表!$H$171)*(1+参数输入表!$H$172)*(1+参数输入表!$H$173*(I4-1))/(1+参数输入表!$H$174) -> 134.4 | J9: =(参数输入表!$H$167*参数输入表!$H$170+参数输入表!$H$168*参数输入表!$H$171)*(1+参数输入表!$H$172)*(1+参数输入表!$H$173*(J4-1))/(1+参数输入表!$H$174) -> 134.4 | K9: =(参数输入表!$H$167*参数输入表!$H$170+参数输入表!$H$168*参数输入表!$H$171)*(1+参数输入表!$H$172)*(1+参数输入表!$H$173*(K4-1))/(1+参数输入表!$H$174) -> 134.4 | L9: =(参数输入表!$H$167*参数输入表!$H$170+参数输入表!$H$168*参数输入表!$H$171)*(1+参数输入表!$H$172)*(1+参数输入表!$H$173*(L4-1))/(1+参数输入表!$H$174) -> 134.4 | M9: =(参数输入表!$H$167*参数输入表!$H$170+参数输入表!$H$168*参数输入表!$H$171)*(1+参数输入表!$H$172)*(1+参数输入表!$H$173*(M4-1))/(1+参数输入表!$H$174) -> 134.4 | N9: =(参数输入表!$H$167*参数输入表!$H$170+参数输入表!$H$168*参数输入表!$H$171)*(1+参数输入表!$H$172)*(1+参数输入表!$H$173*(N4-1))/(1+参数输入表!$H$174) -> 134.4 | O9: =(参数输入表!$H$167*参数输入表!$H$170+参数输入表!$H$168*参数输入表!$H$171)*(1+参数输入表!$H$172)*(1+参数输入表!$H$173*(O4-1))/(1+参数输入表!$H$174) -> 134.4 | ... AF9: =(参数输入表!$H$167*参数输入表!$H$170+参数输入表!$H$168*参数输入表!$H$171)*(1+参数输入表!$H$172)*(1+参数输入表!$H$173*(AF4-1))/(1+参数输入表!$H$174) -> 134.4
B10: 1.4 | C10: 长期待摊费用当期摊销 | D10: =SUM(F10:AF10) -> 0 | E10: 万元 | H10: ='表2-折旧摊销表'!H31 -> 0 | I10: ='表2-折旧摊销表'!I31 -> 0 | J10: ='表2-折旧摊销表'!J31 -> 0 | K10: ='表2-折旧摊销表'!K31 -> 0 | L10: ='表2-折旧摊销表'!L31 -> 0 | M10: ='表2-折旧摊销表'!M31 -> 0 | N10: ='表2-折旧摊销表'!N31 -> 0 | O10: ='表2-折旧摊销表'!O31 -> 0 | ... AF10: ='表2-折旧摊销表'!AF31 -> 0
B11: 1.5 | C11: 营业相关资产折旧及摊销 | D11: =SUM(F11:AF11) -> 23689.97 | E11: 万元 | H11: ='表2-折旧摊销表'!H28+'表2-折旧摊销表'!H34+'表2-折旧摊销表'!H37 -> 1164.3215 | I11: ='表2-折旧摊销表'!I28+'表2-折旧摊销表'!I34+'表2-折旧摊销表'!I37 -> 1164.3215 | J11: ='表2-折旧摊销表'!J28+'表2-折旧摊销表'!J34+'表2-折旧摊销表'!J37 -> 1164.3215 | K11: ='表2-折旧摊销表'!K28+'表2-折旧摊销表'!K34+'表2-折旧摊销表'!K37 -> 1164.3215 | L11: ='表2-折旧摊销表'!L28+'表2-折旧摊销表'!L34+'表2-折旧摊销表'!L37 -> 1164.3215 | M11: ='表2-折旧摊销表'!M28+'表2-折旧摊销表'!M34+'表2-折旧摊销表'!M37 -> 1164.3215 | N11: ='表2-折旧摊销表'!N28+'表2-折旧摊销表'!N34+'表2-折旧摊销表'!N37 -> 1164.3215 | O11: ='表2-折旧摊销表'!O28+'表2-折旧摊销表'!O34+'表2-折旧摊销表'!O37 -> 1164.3215 | ... AF11: ='表2-折旧摊销表'!AF28+'表2-折旧摊销表'!AF34+'表2-折旧摊销表'!AF37 -> 0
B12: 1.6 | C12: 其他费用 | D12: =SUM(F12:AF12) -> 3000 | E12: 万元 | H12: =参数输入表!$H$175*参数输入表!$H$13/(1+参数输入表!$H$176) -> 120 | I12: =参数输入表!$H$175*参数输入表!$H$13/(1+参数输入表!$H$176) -> 120 | J12: =参数输入表!$H$175*参数输入表!$H$13/(1+参数输入表!$H$176) -> 120 | K12: =参数输入表!$H$175*参数输入表!$H$13/(1+参数输入表!$H$176) -> 120 | L12: =参数输入表!$H$175*参数输入表!$H$13/(1+参数输入表!$H$176) -> 120 | M12: =参数输入表!$H$175*参数输入表!$H$13/(1+参数输入表!$H$176) -> 120 | N12: =参数输入表!$H$175*参数输入表!$H$13/(1+参数输入表!$H$176) -> 120 | O12: =参数输入表!$H$175*参数输入表!$H$13/(1+参数输入表!$H$176) -> 120 | ... AF12: =参数输入表!$H$175*参数输入表!$H$13/(1+参数输入表!$H$176) -> 120
B13: 1.7 | C13: 储能费用 | D13: =SUM(F13:AF13) -> 0 | E13: 万元 | H13: =参数输入表!$H$191*参数输入表!$H$13*1000/10000/(1+参数输入表!$H$192) -> 0 | I13: =参数输入表!$H$191*参数输入表!$H$13*1000/10000/(1+参数输入表!$H$192) -> 0 | J13: =参数输入表!$H$191*参数输入表!$H$13*1000/10000/(1+参数输入表!$H$192) -> 0 | K13: =参数输入表!$H$191*参数输入表!$H$13*1000/10000/(1+参数输入表!$H$192) -> 0 | L13: =参数输入表!$H$191*参数输入表!$H$13*1000/10000/(1+参数输入表!$H$192) -> 0 | M13: =参数输入表!$H$191*参数输入表!$H$13*1000/10000/(1+参数输入表!$H$192) -> 0 | N13: =参数输入表!$H$191*参数输入表!$H$13*1000/10000/(1+参数输入表!$H$192) -> 0 | O13: =参数输入表!$H$191*参数输入表!$H$13*1000/10000/(1+参数输入表!$H$192) -> 0 | ... AF13: =参数输入表!$H$191*参数输入表!$H$13*1000/10000/(1+参数输入表!$H$192) -> 0
B14: 1.8 | C14: 场地租金费用 | D14: =SUM(F14:AF14) -> 1650 | E14: 万元 | H14: =参数输入表!$H$178*参数输入表!$H$179/10000*(1+参数输入表!$H$181)/(1+参数输入表!$H$186) -> 60 | I14: =参数输入表!$H$178*参数输入表!$H$179/10000*(1+参数输入表!$H$181)/(1+参数输入表!$H$186) -> 60 | J14: =参数输入表!$H$178*参数输入表!$H$179/10000*(1+参数输入表!$H$181)/(1+参数输入表!$H$186) -> 60 | K14: =参数输入表!$H$178*参数输入表!$H$179/10000*(1+参数输入表!$H$181)/(1+参数输入表!$H$186) -> 60 | L14: =参数输入表!$H$178*参数输入表!$H$179/10000*(1+参数输入表!$H$181)/(1+参数输入表!$H$186) -> 60 | M14: =参数输入表!$H$178*参数输入表!$H$179/10000*(1+参数输入表!$H$182)/(1+参数输入表!$H$186) -> 63 | N14: =参数输入表!$H$178*参数输入表!$H$179/10000*(1+参数输入表!$H$182)/(1+参数输入表!$H$186) -> 63 | O14: =参数输入表!$H$178*参数输入表!$H$179/10000*(1+参数输入表!$H$182)/(1+参数输入表!$H$186) -> 63 | P14: =参数输入表!$H$178*参数输入表!$H$179/10000*(1+参数输入表!$H$182)/(1+参数输入表!$H$186) -> 63 | Q14: =参数输入表!$H$178*参数输入表!$H$179/10000*(1+参数输入表!$H$182)/(1+参数输入表!$H$186) -> 63 | R14: =参数输入表!$H$178*参数输入表!$H$179/10000*(1+参数输入表!$H$183)/(1+参数输入表!$H$186) -> 66 | S14: =参数输入表!$H$178*参数输入表!$H$179/10000*(1+参数输入表!$H$183)/(1+参数输入表!$H$186) -> 66 | T14: =参数输入表!$H$178*参数输入表!$H$179/10000*(1+参数输入表!$H$183)/(1+参数输入表!$H$186) -> 66 | U14: =参数输入表!$H$178*参数输入表!$H$179/10000*(1+参数输入表!$H$183)/(1+参数输入表!$H$186) -> 66 | V14: =参数输入表!$H$178*参数输入表!$H$179/10000*(1+参数输入表!$H$183)/(1+参数输入表!$H$186) -> 66 | W14: =参数输入表!$H$178*参数输入表!$H$179/10000*(1+参数输入表!$H$184)/(1+参数输入表!$H$186) -> 69 | X14: =参数输入表!$H$178*参数输入表!$H$179/10000*(1+参数输入表!$H$184)/(1+参数输入表!$H$186) -> 69 | Y14: =参数输入表!$H$178*参数输入表!$H$179/10000*(1+参数输入表!$H$184)/(1+参数输入表!$H$186) -> 69 | Z14: =参数输入表!$H$178*参数输入表!$H$179/10000*(1+参数输入表!$H$184)/(1+参数输入表!$H$186) -> 69 | AA14: =参数输入表!$H$178*参数输入表!$H$179/10000*(1+参数输入表!$H$184)/(1+参数输入表!$H$186) -> 69 | AB14: =参数输入表!$H$178*参数输入表!$H$179/10000*(1+参数输入表!$H$185)/(1+参数输入表!$H$186) -> 72 | AC14: =参数输入表!$H$178*参数输入表!$H$179/10000*(1+参数输入表!$H$185)/(1+参数输入表!$H$186) -> 72 | AD14: =参数输入表!$H$178*参数输入表!$H$179/10000*(1+参数输入表!$H$185)/(1+参数输入表!$H$186) -> 72 | AE14: =参数输入表!$H$178*参数输入表!$H$179/10000*(1+参数输入表!$H$185)/(1+参数输入表!$H$186) -> 72 | AF14: =参数输入表!$H$178*参数输入表!$H$179/10000*(1+参数输入表!$H$185)/(1+参数输入表!$H$186) -> 72
B15: 2 | C15: 销售费用 | D15: =SUM(F15:AF15) -> 0 | E15: 万元 | H15: 0 | I15: 0 | J15: 0 | K15: 0 | L15: 0 | M15: 0 | N15: 0 | O15: 0 | P15: 0 | Q15: 0 | R15: 0 | S15: 0 | T15: 0 | U15: 0 | V15: 0 | W15: 0 | X15: 0 | Y15: 0 | Z15: 0 | AA15: 0 | AB15: 0 | AC15: 0 | AD15: 0 | AE15: 0 | AF15: 0
B16: 3 | C16: 管理费用 | D16: =SUM(F16:AF16) -> 1532.002 | E16: 万元 | H16: =SUM(H17:H18) -> 61.28008 | I16: =SUM(I17:I18) -> 61.28008 | J16: =SUM(J17:J18) -> 61.28008 | K16: =SUM(K17:K18) -> 61.28008 | L16: =SUM(L17:L18) -> 61.28008 | M16: =SUM(M17:M18) -> 61.28008 | N16: =SUM(N17:N18) -> 61.28008 | O16: =SUM(O17:O18) -> 61.28008 | ... AF16: =SUM(AF17:AF18) -> 61.28008
B17: 3.1 | C17: 保险费 | D17: =SUM(F17:AF17) -> 1532.002 | E17: 万元 | H17: ='表2-折旧摊销表'!$D$4*参数输入表!$H$159/(1+参数输入表!$H$164) -> 61.28008 | I17: ='表2-折旧摊销表'!$D$4*参数输入表!$H$159/(1+参数输入表!$H$164) -> 61.28008 | J17: ='表2-折旧摊销表'!$D$4*参数输入表!$H$159/(1+参数输入表!$H$164) -> 61.28008 | K17: ='表2-折旧摊销表'!$D$4*参数输入表!$H$159/(1+参数输入表!$H$164) -> 61.28008 | L17: ='表2-折旧摊销表'!$D$4*参数输入表!$H$159/(1+参数输入表!$H$164) -> 61.28008 | M17: ='表2-折旧摊销表'!$D$4*参数输入表!$H$160/(1+参数输入表!$H$164) -> 61.28008 | N17: ='表2-折旧摊销表'!$D$4*参数输入表!$H$160/(1+参数输入表!$H$164) -> 61.28008 | O17: ='表2-折旧摊销表'!$D$4*参数输入表!$H$160/(1+参数输入表!$H$164) -> 61.28008 | P17: ='表2-折旧摊销表'!$D$4*参数输入表!$H$160/(1+参数输入表!$H$164) -> 61.28008 | Q17: ='表2-折旧摊销表'!$D$4*参数输入表!$H$160/(1+参数输入表!$H$164) -> 61.28008 | R17: ='表2-折旧摊销表'!$D$4*参数输入表!$H$161/(1+参数输入表!$H$164) -> 61.28008 | S17: ='表2-折旧摊销表'!$D$4*参数输入表!$H$161/(1+参数输入表!$H$164) -> 61.28008 | T17: ='表2-折旧摊销表'!$D$4*参数输入表!$H$161/(1+参数输入表!$H$164) -> 61.28008 | U17: ='表2-折旧摊销表'!$D$4*参数输入表!$H$161/(1+参数输入表!$H$164) -> 61.28008 | V17: ='表2-折旧摊销表'!$D$4*参数输入表!$H$161/(1+参数输入表!$H$164) -> 61.28008 | W17: ='表2-折旧摊销表'!$D$4*参数输入表!$H$162/(1+参数输入表!$H$164) -> 61.28008 | X17: ='表2-折旧摊销表'!$D$4*参数输入表!$H$162/(1+参数输入表!$H$164) -> 61.28008 | Y17: ='表2-折旧摊销表'!$D$4*参数输入表!$H$162/(1+参数输入表!$H$164) -> 61.28008 | Z17: ='表2-折旧摊销表'!$D$4*参数输入表!$H$162/(1+参数输入表!$H$164) -> 61.28008 | AA17: ='表2-折旧摊销表'!$D$4*参数输入表!$H$162/(1+参数输入表!$H$164) -> 61.28008 | AB17: ='表2-折旧摊销表'!$D$4*参数输入表!$H$163/(1+参数输入表!$H$164) -> 61.28008 | AC17: ='表2-折旧摊销表'!$D$4*参数输入表!$H$163/(1+参数输入表!$H$164) -> 61.28008 | AD17: ='表2-折旧摊销表'!$D$4*参数输入表!$H$163/(1+参数输入表!$H$164) -> 61.28008 | AE17: ='表2-折旧摊销表'!$D$4*参数输入表!$H$163/(1+参数输入表!$H$164) -> 61.28008 | AF17: ='表2-折旧摊销表'!$D$4*参数输入表!$H$163/(1+参数输入表!$H$164) -> 61.28008
B18: 3.2 | C18: 期末拆除费用 | D18: =SUM(F18:AF18) -> 0 | E18: 万元 | H18: 0 | I18: 0 | J18: 0 | K18: 0 | L18: 0 | M18: 0 | N18: 0 | O18: 0 | P18: 0 | Q18: 0 | R18: 0 | S18: 0 | T18: 0 | U18: 0 | V18: 0 | W18: 0 | X18: 0 | Y18: 0 | Z18: 0 | AA18: 0 | AB18: 0 | AC18: 0 | AD18: 0 | AE18: 0 | AF18: =参数输入表!H189*参数输入表!H188/(1+参数输入表!$H$190) -> 0
B19: 4 | C19: 研发费用 | D19: =SUM(F19:AF19) -> 0 | E19: 万元 | H19: 0 | I19: 0 | J19: 0 | K19: 0 | L19: 0 | M19: 0 | N19: 0 | O19: 0 | P19: 0 | Q19: 0 | R19: 0 | S19: 0 | T19: 0 | U19: 0 | V19: 0 | W19: 0 | X19: 0 | Y19: 0 | Z19: 0 | AA19: 0 | AB19: 0 | AC19: 0 | AD19: 0 | AE19: 0 | AF19: 0
B20: 5 | C20: 财务费用 | D20: =SUM(F20:AF20) -> 6370.1464 | E20: 万元 | H20: =SUM(H21:H23) -> 785.2013 | I20: =SUM(I21:I23) -> 733.20175 | J20: =SUM(J21:J23) -> 681.2022 | K20: =SUM(K21:K23) -> 629.20264 | L20: =SUM(L21:L23) -> 577.20309 | M20: =SUM(M21:M23) -> 525.20354 | N20: =SUM(N21:N23) -> 473.20398 | O20: =SUM(O21:O23) -> 421.20443 | ... AF20: =SUM(AF21:AF23) -> 5.208
B21: 5.1 | C21: 长期借款利息 | D21: =SUM(F21:AF21) -> 6239.9464 | E21: 万元 | H21: ='表1-资金筹措及还本付息表'!H53 -> 779.9933 | I21: ='表1-资金筹措及还本付息表'!I53 -> 727.99375 | J21: ='表1-资金筹措及还本付息表'!J53 -> 675.9942 | K21: ='表1-资金筹措及还本付息表'!K53 -> 623.99464 | L21: ='表1-资金筹措及还本付息表'!L53 -> 571.99509 | M21: ='表1-资金筹措及还本付息表'!M53 -> 519.99554 | N21: ='表1-资金筹措及还本付息表'!N53 -> 467.99598 | O21: ='表1-资金筹措及还本付息表'!O53 -> 415.99643 | ... AF21: ='表1-资金筹措及还本付息表'!AF53 -> 0
B22: 5.2 | C22: 流动资金利息 | D22: =SUM(F22:AF22) -> 130.2 | E22: 万元 | H22: ='表1-资金筹措及还本付息表'!H63 -> 5.208 | I22: =H22 -> 5.208 | J22: =I22 -> 5.208 | K22: =J22 -> 5.208 | L22: =K22 -> 5.208 | M22: =L22 -> 5.208 | N22: =M22 -> 5.208 | O22: =N22 -> 5.208 | P22: =O22 -> 5.208 | ... AF22: =AE22 -> 5.208
B23: 5.3 | C23: 短期借款利息 | D23: =SUM(F23:AF23) -> 0 | E23: 万元 | H23: ='表1-资金筹措及还本付息表'!H73 -> 0 | I23: ='表1-资金筹措及还本付息表'!I73 -> 0 | J23: ='表1-资金筹措及还本付息表'!J73 -> 0 | K23: ='表1-资金筹措及还本付息表'!K73 -> 0 | L23: ='表1-资金筹措及还本付息表'!L73 -> 0 | M23: ='表1-资金筹措及还本付息表'!M73 -> 0 | N23: ='表1-资金筹措及还本付息表'!N73 -> 0 | O23: ='表1-资金筹措及还本付息表'!O73 -> 0 | ... AF23: ='表1-资金筹措及还本付息表'!AF73 -> 0
B24: 二 | C24: 营业外支出 | D24: =SUM(F24:AF24) -> 0 | E24: 万元 | H24: =参数输入表!$H$267/(1+参数输入表!$H$271) -> 0 | I24: =参数输入表!$H$267/(1+参数输入表!$H$271) -> 0 | J24: =参数输入表!$H$267/(1+参数输入表!$H$271) -> 0 | K24: =参数输入表!$H$267/(1+参数输入表!$H$271) -> 0 | L24: =参数输入表!$H$267/(1+参数输入表!$H$271) -> 0 | M24: =参数输入表!$H$267/(1+参数输入表!$H$271) -> 0 | N24: =参数输入表!$H$267/(1+参数输入表!$H$271) -> 0 | O24: =参数输入表!$H$267/(1+参数输入表!$H$271) -> 0 | ... AF24: =参数输入表!$H$267/(1+参数输入表!$H$271) -> 0
B26: 成本费用表-全投资
B27: 序号 | C27: 项目 | D27: 合计 | E27: 单位 | F27: 建设期 | H27: 运营期
F28: 1 | G28: 2 | H28: 1 | I28: 2 | J28: 3 | K28: 4 | L28: 5 | M28: 6 | N28: 7 | O28: 8 | P28: 9 | Q28: 10 | R28: 11 | S28: 12 | T28: 13 | U28: 14 | V28: 15 | W28: 16 | X28: 17 | Y28: 18 | Z28: 19 | AA28: 20 | AB28: 21 | AC28: 22 | AD28: 23 | AE28: 24 | AF28: 25
B29: 一 | C29: 营业总成本 | D29: =SUM(F29:AF29) -> 40451.312 | E29: 万元 | H29: =H30+H39+H40+H43 -> 1732.2595 | I29: =I30+I39+I40+I43 -> 1732.2595 | J29: =J30+J39+J40+J43 -> 1732.2595 | K29: =K30+K39+K40+K43 -> 1732.2595 | L29: =L30+L39+L40+L43 -> 1732.2595 | M29: =M30+M39+M40+M43 -> 1783.5173 | N29: =N30+N39+N40+N43 -> 1783.5173 | O29: =O30+O39+O40+O43 -> 1783.5173 | ... AF29: =AF30+AF39+AF40+AF43 -> 772.96939
B30: 1 | C30: 生产成本 | D30: =SUM(F30:AF30) -> 38919.31 | H30: =SUM(H31:H38) -> 1670.9794 | I30: =SUM(I31:I38) -> 1670.9794 | J30: =SUM(J31:J38) -> 1670.9794 | K30: =SUM(K31:K38) -> 1670.9794 | L30: =SUM(L31:L38) -> 1670.9794 | M30: =SUM(M31:M38) -> 1722.2372 | N30: =SUM(N31:N38) -> 1722.2372 | O30: =SUM(O31:O38) -> 1722.2372 | ... AF30: =SUM(AF31:AF38) -> 711.68931
B31: 1.1 | C31: 材料费 | D31: =SUM(F31:AF31) -> 3600 | E31: 万元 | H31: =参数输入表!$H$141*参数输入表!$H$13/(1+参数输入表!$H$146) -> 144 | I31: =参数输入表!$H$141*参数输入表!$H$13/(1+参数输入表!$H$146) -> 144 | J31: =参数输入表!$H$141*参数输入表!$H$13/(1+参数输入表!$H$146) -> 144 | K31: =参数输入表!$H$141*参数输入表!$H$13/(1+参数输入表!$H$146) -> 144 | L31: =参数输入表!$H$141*参数输入表!$H$13/(1+参数输入表!$H$146) -> 144 | M31: =参数输入表!$H$142*参数输入表!$H$13/(1+参数输入表!$H$146) -> 144 | N31: =参数输入表!$H$142*参数输入表!$H$13/(1+参数输入表!$H$146) -> 144 | O31: =参数输入表!$H$142*参数输入表!$H$13/(1+参数输入表!$H$146) -> 144 | P31: =参数输入表!$H$142*参数输入表!$H$13/(1+参数输入表!$H$146) -> 144 | Q31: =参数输入表!$H$142*参数输入表!$H$13/(1+参数输入表!$H$146) -> 144 | R31: =参数输入表!$H$143*参数输入表!$H$13/(1+参数输入表!$H$146) -> 144 | S31: =参数输入表!$H$143*参数输入表!$H$13/(1+参数输入表!$H$146) -> 144 | T31: =参数输入表!$H$143*参数输入表!$H$13/(1+参数输入表!$H$146) -> 144 | U31: =参数输入表!$H$143*参数输入表!$H$13/(1+参数输入表!$H$146) -> 144 | V31: =参数输入表!$H$143*参数输入表!$H$13/(1+参数输入表!$H$146) -> 144 | W31: =参数输入表!$H$144*参数输入表!$H$13/(1+参数输入表!$H$146) -> 144 | X31: =参数输入表!$H$144*参数输入表!$H$13/(1+参数输入表!$H$146) -> 144 | Y31: =参数输入表!$H$144*参数输入表!$H$13/(1+参数输入表!$H$146) -> 144 | Z31: =参数输入表!$H$144*参数输入表!$H$13/(1+参数输入表!$H$146) -> 144 | AA31: =参数输入表!$H$144*参数输入表!$H$13/(1+参数输入表!$H$146) -> 144 | AB31: =参数输入表!$H$145*参数输入表!$H$13/(1+参数输入表!$H$146) -> 144 | AC31: =参数输入表!$H$145*参数输入表!$H$13/(1+参数输入表!$H$146) -> 144 | AD31: =参数输入表!$H$145*参数输入表!$H$13/(1+参数输入表!$H$146) -> 144 | AE31: =参数输入表!$H$145*参数输入表!$H$13/(1+参数输入表!$H$146) -> 144 | AF31: =参数输入表!$H$145*参数输入表!$H$13/(1+参数输入表!$H$146) -> 144
B32: 1.2 | C32: 维修费 | D32: =SUM(F32:AF32) -> 3619.3397 | E32: 万元 | H32: =(参数输入表!$H$113-参数输入表!$H$120)*参数输入表!$H$150/(1+参数输入表!$H$155) -> 48.257862 | I32: =(参数输入表!$H$113-参数输入表!$H$120)*参数输入表!$H$150/(1+参数输入表!$H$155) -> 48.257862 | J32: =(参数输入表!$H$113-参数输入表!$H$120)*参数输入表!$H$150/(1+参数输入表!$H$155) -> 48.257862 | K32: =(参数输入表!$H$113-参数输入表!$H$120)*参数输入表!$H$150/(1+参数输入表!$H$155) -> 48.257862 | L32: =(参数输入表!$H$113-参数输入表!$H$120)*参数输入表!$H$150/(1+参数输入表!$H$155) -> 48.257862 | M32: =(参数输入表!$H$113-参数输入表!$H$120)*参数输入表!$H$151/(1+参数输入表!$H$155) -> 96.515725 | N32: =(参数输入表!$H$113-参数输入表!$H$120)*参数输入表!$H$151/(1+参数输入表!$H$155) -> 96.515725 | O32: =(参数输入表!$H$113-参数输入表!$H$120)*参数输入表!$H$151/(1+参数输入表!$H$155) -> 96.515725 | P32: =(参数输入表!$H$113-参数输入表!$H$120)*参数输入表!$H$151/(1+参数输入表!$H$155) -> 96.515725 | Q32: =(参数输入表!$H$113-参数输入表!$H$120)*参数输入表!$H$151/(1+参数输入表!$H$155) -> 96.515725 | R32: =(参数输入表!$H$113-参数输入表!$H$120)*参数输入表!$H$152/(1+参数输入表!$H$155) -> 144.77359 | S32: =(参数输入表!$H$113-参数输入表!$H$120)*参数输入表!$H$152/(1+参数输入表!$H$155) -> 144.77359 | T32: =(参数输入表!$H$113-参数输入表!$H$120)*参数输入表!$H$152/(1+参数输入表!$H$155) -> 144.77359 | U32: =(参数输入表!$H$113-参数输入表!$H$120)*参数输入表!$H$152/(1+参数输入表!$H$155) -> 144.77359 | V32: =(参数输入表!$H$113-参数输入表!$H$120)*参数输入表!$H$152/(1+参数输入表!$H$155) -> 144.77359 | W32: =(参数输入表!$H$113-参数输入表!$H$120)*参数输入表!$H$153/(1+参数输入表!$H$155) -> 193.03145 | X32: =(参数输入表!$H$113-参数输入表!$H$120)*参数输入表!$H$153/(1+参数输入表!$H$155) -> 193.03145 | Y32: =(参数输入表!$H$113-参数输入表!$H$120)*参数输入表!$H$153/(1+参数输入表!$H$155) -> 193.03145 | Z32: =(参数输入表!$H$113-参数输入表!$H$120)*参数输入表!$H$153/(1+参数输入表!$H$155) -> 193.03145 | AA32: =(参数输入表!$H$113-参数输入表!$H$120)*参数输入表!$H$153/(1+参数输入表!$H$155) -> 193.03145 | AB32: =(参数输入表!$H$113-参数输入表!$H$120)*参数输入表!$H$154/(1+参数输入表!$H$155) -> 241.28931 | AC32: =(参数输入表!$H$113-参数输入表!$H$120)*参数输入表!$H$154/(1+参数输入表!$H$155) -> 241.28931 | AD32: =(参数输入表!$H$113-参数输入表!$H$120)*参数输入表!$H$154/(1+参数输入表!$H$155) -> 241.28931 | AE32: =(参数输入表!$H$113-参数输入表!$H$120)*参数输入表!$H$154/(1+参数输入表!$H$155) -> 241.28931 | AF32: =(参数输入表!$H$113-参数输入表!$H$120)*参数输入表!$H$154/(1+参数输入表!$H$155) -> 241.28931
B33: 1.3 | C33: 生产人员薪酬及福利 | D33: =SUM(F33:AF33) -> 3360 | E33: 万元 | H33: =(参数输入表!$H$167*参数输入表!$H$170+参数输入表!$H$168*参数输入表!$H$171)*(1+参数输入表!$H$172)*(1+参数输入表!$H$173*(H28-1))/(1+参数输入表!$H$174) -> 134.4 | I33: =(参数输入表!$H$167*参数输入表!$H$170+参数输入表!$H$168*参数输入表!$H$171)*(1+参数输入表!$H$172)*(1+参数输入表!$H$173*(I28-1))/(1+参数输入表!$H$174) -> 134.4 | J33: =(参数输入表!$H$167*参数输入表!$H$170+参数输入表!$H$168*参数输入表!$H$171)*(1+参数输入表!$H$172)*(1+参数输入表!$H$173*(J28-1))/(1+参数输入表!$H$174) -> 134.4 | K33: =(参数输入表!$H$167*参数输入表!$H$170+参数输入表!$H$168*参数输入表!$H$171)*(1+参数输入表!$H$172)*(1+参数输入表!$H$173*(K28-1))/(1+参数输入表!$H$174) -> 134.4 | L33: =(参数输入表!$H$167*参数输入表!$H$170+参数输入表!$H$168*参数输入表!$H$171)*(1+参数输入表!$H$172)*(1+参数输入表!$H$173*(L28-1))/(1+参数输入表!$H$174) -> 134.4 | M33: =(参数输入表!$H$167*参数输入表!$H$170+参数输入表!$H$168*参数输入表!$H$171)*(1+参数输入表!$H$172)*(1+参数输入表!$H$173*(M28-1))/(1+参数输入表!$H$174) -> 134.4 | N33: =(参数输入表!$H$167*参数输入表!$H$170+参数输入表!$H$168*参数输入表!$H$171)*(1+参数输入表!$H$172)*(1+参数输入表!$H$173*(N28-1))/(1+参数输入表!$H$174) -> 134.4 | O33: =(参数输入表!$H$167*参数输入表!$H$170+参数输入表!$H$168*参数输入表!$H$171)*(1+参数输入表!$H$172)*(1+参数输入表!$H$173*(O28-1))/(1+参数输入表!$H$174) -> 134.4 | ... AF33: =(参数输入表!$H$167*参数输入表!$H$170+参数输入表!$H$168*参数输入表!$H$171)*(1+参数输入表!$H$172)*(1+参数输入表!$H$173*(AF28-1))/(1+参数输入表!$H$174) -> 134.4
B34: 1.4 | C34: 长期待摊费用当期摊销 | D34: =SUM(F34:AF34) -> 0 | E34: 万元 | H34: ='表2-折旧摊销表'!H59 -> 0 | I34: ='表2-折旧摊销表'!I59 -> 0 | J34: ='表2-折旧摊销表'!J59 -> 0 | K34: ='表2-折旧摊销表'!K59 -> 0 | L34: ='表2-折旧摊销表'!L59 -> 0 | M34: ='表2-折旧摊销表'!M59 -> 0 | N34: ='表2-折旧摊销表'!N59 -> 0 | O34: ='表2-折旧摊销表'!O59 -> 0 | ... AF34: ='表2-折旧摊销表'!AF59 -> 0
B35: 1.5 | C35: 营业相关资产折旧及摊销 | D35: =SUM(F35:AF35) -> 23689.97 | E35: 万元 | H35: ='表2-折旧摊销表'!H56+'表2-折旧摊销表'!H62+'表2-折旧摊销表'!H65 -> 1164.3215 | I35: ='表2-折旧摊销表'!I56+'表2-折旧摊销表'!I62+'表2-折旧摊销表'!I65 -> 1164.3215 | J35: ='表2-折旧摊销表'!J56+'表2-折旧摊销表'!J62+'表2-折旧摊销表'!J65 -> 1164.3215 | K35: ='表2-折旧摊销表'!K56+'表2-折旧摊销表'!K62+'表2-折旧摊销表'!K65 -> 1164.3215 | L35: ='表2-折旧摊销表'!L56+'表2-折旧摊销表'!L62+'表2-折旧摊销表'!L65 -> 1164.3215 | M35: ='表2-折旧摊销表'!M56+'表2-折旧摊销表'!M62+'表2-折旧摊销表'!M65 -> 1164.3215 | N35: ='表2-折旧摊销表'!N56+'表2-折旧摊销表'!N62+'表2-折旧摊销表'!N65 -> 1164.3215 | O35: ='表2-折旧摊销表'!O56+'表2-折旧摊销表'!O62+'表2-折旧摊销表'!O65 -> 1164.3215 | ... AF35: ='表2-折旧摊销表'!AF56+'表2-折旧摊销表'!AF62+'表2-折旧摊销表'!AF65 -> 0
B36: 1.6 | C36: 其他费用 | D36: =SUM(F36:AF36) -> 3000 | E36: 万元 | H36: =参数输入表!$H$175*参数输入表!$H$13/(1+参数输入表!$H$176) -> 120 | I36: =参数输入表!$H$175*参数输入表!$H$13/(1+参数输入表!$H$176) -> 120 | J36: =参数输入表!$H$175*参数输入表!$H$13/(1+参数输入表!$H$176) -> 120 | K36: =参数输入表!$H$175*参数输入表!$H$13/(1+参数输入表!$H$176) -> 120 | L36: =参数输入表!$H$175*参数输入表!$H$13/(1+参数输入表!$H$176) -> 120 | M36: =参数输入表!$H$175*参数输入表!$H$13/(1+参数输入表!$H$176) -> 120 | N36: =参数输入表!$H$175*参数输入表!$H$13/(1+参数输入表!$H$176) -> 120 | O36: =参数输入表!$H$175*参数输入表!$H$13/(1+参数输入表!$H$176) -> 120 | ... AF36: =参数输入表!$H$175*参数输入表!$H$13/(1+参数输入表!$H$176) -> 120
B37: 1.7 | C37: 储能费用 | D37: =SUM(F37:AF37) -> 0 | E37: 万元 | H37: =参数输入表!$H$191*参数输入表!$H$13*1000/10000/(1+参数输入表!$H$192) -> 0 | I37: =参数输入表!$H$191*参数输入表!$H$13*1000/10000/(1+参数输入表!$H$192) -> 0 | J37: =参数输入表!$H$191*参数输入表!$H$13*1000/10000/(1+参数输入表!$H$192) -> 0 | K37: =参数输入表!$H$191*参数输入表!$H$13*1000/10000/(1+参数输入表!$H$192) -> 0 | L37: =参数输入表!$H$191*参数输入表!$H$13*1000/10000/(1+参数输入表!$H$192) -> 0 | M37: =参数输入表!$H$191*参数输入表!$H$13*1000/10000/(1+参数输入表!$H$192) -> 0 | N37: =参数输入表!$H$191*参数输入表!$H$13*1000/10000/(1+参数输入表!$H$192) -> 0 | O37: =参数输入表!$H$191*参数输入表!$H$13*1000/10000/(1+参数输入表!$H$192) -> 0 | ... AF37: =参数输入表!$H$191*参数输入表!$H$13*1000/10000/(1+参数输入表!$H$192) -> 0
B38: 1.8 | C38: 场地租金费用 | D38: =SUM(F38:AF38) -> 1650 | E38: 万元 | H38: =参数输入表!$H$178*参数输入表!$H$179/10000*(1+参数输入表!$H$181)/(1+参数输入表!$H$186) -> 60 | I38: =参数输入表!$H$178*参数输入表!$H$179/10000*(1+参数输入表!$H$181)/(1+参数输入表!$H$186) -> 60 | J38: =参数输入表!$H$178*参数输入表!$H$179/10000*(1+参数输入表!$H$181)/(1+参数输入表!$H$186) -> 60 | K38: =参数输入表!$H$178*参数输入表!$H$179/10000*(1+参数输入表!$H$181)/(1+参数输入表!$H$186) -> 60 | L38: =参数输入表!$H$178*参数输入表!$H$179/10000*(1+参数输入表!$H$181)/(1+参数输入表!$H$186) -> 60 | M38: =参数输入表!$H$178*参数输入表!$H$179/10000*(1+参数输入表!$H$182)/(1+参数输入表!$H$186) -> 63 | N38: =参数输入表!$H$178*参数输入表!$H$179/10000*(1+参数输入表!$H$182)/(1+参数输入表!$H$186) -> 63 | O38: =参数输入表!$H$178*参数输入表!$H$179/10000*(1+参数输入表!$H$182)/(1+参数输入表!$H$186) -> 63 | P38: =参数输入表!$H$178*参数输入表!$H$179/10000*(1+参数输入表!$H$182)/(1+参数输入表!$H$186) -> 63 | Q38: =参数输入表!$H$178*参数输入表!$H$179/10000*(1+参数输入表!$H$182)/(1+参数输入表!$H$186) -> 63 | R38: =参数输入表!$H$178*参数输入表!$H$179/10000*(1+参数输入表!$H$183)/(1+参数输入表!$H$186) -> 66 | S38: =参数输入表!$H$178*参数输入表!$H$179/10000*(1+参数输入表!$H$183)/(1+参数输入表!$H$186) -> 66 | T38: =参数输入表!$H$178*参数输入表!$H$179/10000*(1+参数输入表!$H$183)/(1+参数输入表!$H$186) -> 66 | U38: =参数输入表!$H$178*参数输入表!$H$179/10000*(1+参数输入表!$H$183)/(1+参数输入表!$H$186) -> 66 | V38: =参数输入表!$H$178*参数输入表!$H$179/10000*(1+参数输入表!$H$183)/(1+参数输入表!$H$186) -> 66 | W38: =参数输入表!$H$178*参数输入表!$H$179/10000*(1+参数输入表!$H$184)/(1+参数输入表!$H$186) -> 69 | X38: =参数输入表!$H$178*参数输入表!$H$179/10000*(1+参数输入表!$H$184)/(1+参数输入表!$H$186) -> 69 | Y38: =参数输入表!$H$178*参数输入表!$H$179/10000*(1+参数输入表!$H$184)/(1+参数输入表!$H$186) -> 69 | Z38: =参数输入表!$H$178*参数输入表!$H$179/10000*(1+参数输入表!$H$184)/(1+参数输入表!$H$186) -> 69 | AA38: =参数输入表!$H$178*参数输入表!$H$179/10000*(1+参数输入表!$H$184)/(1+参数输入表!$H$186) -> 69 | AB38: =参数输入表!$H$178*参数输入表!$H$179/10000*(1+参数输入表!$H$185)/(1+参数输入表!$H$186) -> 72 | AC38: =参数输入表!$H$178*参数输入表!$H$179/10000*(1+参数输入表!$H$185)/(1+参数输入表!$H$186) -> 72 | AD38: =参数输入表!$H$178*参数输入表!$H$179/10000*(1+参数输入表!$H$185)/(1+参数输入表!$H$186) -> 72 | AE38: =参数输入表!$H$178*参数输入表!$H$179/10000*(1+参数输入表!$H$185)/(1+参数输入表!$H$186) -> 72 | AF38: =参数输入表!$H$178*参数输入表!$H$179/10000*(1+参数输入表!$H$185)/(1+参数输入表!$H$186) -> 72
B39: 2 | C39: 销售费用 | D39: =SUM(F39:AF39) -> 0 | E39: 万元 | H39: 0 | I39: 0 | J39: 0 | K39: 0 | L39: 0 | M39: 0 | N39: 0 | O39: 0 | P39: 0 | Q39: 0 | R39: 0 | S39: 0 | T39: 0 | U39: 0 | V39: 0 | W39: 0 | X39: 0 | Y39: 0 | Z39: 0 | AA39: 0 | AB39: 0 | AC39: 0 | AD39: 0 | AE39: 0 | AF39: 0
B40: 3 | C40: 管理费用 | D40: =SUM(F40:AF40) -> 1532.002 | E40: 万元 | H40: =SUM(H41:H42) -> 61.28008 | I40: =SUM(I41:I42) -> 61.28008 | J40: =SUM(J41:J42) -> 61.28008 | K40: =SUM(K41:K42) -> 61.28008 | L40: =SUM(L41:L42) -> 61.28008 | M40: =SUM(M41:M42) -> 61.28008 | N40: =SUM(N41:N42) -> 61.28008 | O40: =SUM(O41:O42) -> 61.28008 | ... AF40: =SUM(AF41:AF42) -> 61.28008
B41: 3.1 | C41: 保险费 | D41: =SUM(F41:AF41) -> 1532.002 | E41: 万元 | H41: ='表2-折旧摊销表'!$D$4*参数输入表!$H$159/(1+参数输入表!$H$164) -> 61.28008 | I41: ='表2-折旧摊销表'!$D$4*参数输入表!$H$159/(1+参数输入表!$H$164) -> 61.28008 | J41: ='表2-折旧摊销表'!$D$4*参数输入表!$H$159/(1+参数输入表!$H$164) -> 61.28008 | K41: ='表2-折旧摊销表'!$D$4*参数输入表!$H$159/(1+参数输入表!$H$164) -> 61.28008 | L41: ='表2-折旧摊销表'!$D$4*参数输入表!$H$159/(1+参数输入表!$H$164) -> 61.28008 | M41: ='表2-折旧摊销表'!$D$4*参数输入表!$H$160/(1+参数输入表!$H$164) -> 61.28008 | N41: ='表2-折旧摊销表'!$D$4*参数输入表!$H$160/(1+参数输入表!$H$164) -> 61.28008 | O41: ='表2-折旧摊销表'!$D$4*参数输入表!$H$160/(1+参数输入表!$H$164) -> 61.28008 | P41: ='表2-折旧摊销表'!$D$4*参数输入表!$H$160/(1+参数输入表!$H$164) -> 61.28008 | Q41: ='表2-折旧摊销表'!$D$4*参数输入表!$H$160/(1+参数输入表!$H$164) -> 61.28008 | R41: ='表2-折旧摊销表'!$D$4*参数输入表!$H$161/(1+参数输入表!$H$164) -> 61.28008 | S41: ='表2-折旧摊销表'!$D$4*参数输入表!$H$161/(1+参数输入表!$H$164) -> 61.28008 | T41: ='表2-折旧摊销表'!$D$4*参数输入表!$H$161/(1+参数输入表!$H$164) -> 61.28008 | U41: ='表2-折旧摊销表'!$D$4*参数输入表!$H$161/(1+参数输入表!$H$164) -> 61.28008 | V41: ='表2-折旧摊销表'!$D$4*参数输入表!$H$161/(1+参数输入表!$H$164) -> 61.28008 | W41: ='表2-折旧摊销表'!$D$4*参数输入表!$H$162/(1+参数输入表!$H$164) -> 61.28008 | X41: ='表2-折旧摊销表'!$D$4*参数输入表!$H$162/(1+参数输入表!$H$164) -> 61.28008 | Y41: ='表2-折旧摊销表'!$D$4*参数输入表!$H$162/(1+参数输入表!$H$164) -> 61.28008 | Z41: ='表2-折旧摊销表'!$D$4*参数输入表!$H$162/(1+参数输入表!$H$164) -> 61.28008 | AA41: ='表2-折旧摊销表'!$D$4*参数输入表!$H$162/(1+参数输入表!$H$164) -> 61.28008 | AB41: ='表2-折旧摊销表'!$D$4*参数输入表!$H$163/(1+参数输入表!$H$164) -> 61.28008 | AC41: ='表2-折旧摊销表'!$D$4*参数输入表!$H$163/(1+参数输入表!$H$164) -> 61.28008 | AD41: ='表2-折旧摊销表'!$D$4*参数输入表!$H$163/(1+参数输入表!$H$164) -> 61.28008 | AE41: ='表2-折旧摊销表'!$D$4*参数输入表!$H$163/(1+参数输入表!$H$164) -> 61.28008 | AF41: ='表2-折旧摊销表'!$D$4*参数输入表!$H$163/(1+参数输入表!$H$164) -> 61.28008
B42: 3.2 | C42: 期末拆除费用 | D42: =SUM(F42:AF42) -> 0 | E42: 万元 | H42: 0 | I42: 0 | J42: 0 | K42: 0 | L42: 0 | M42: 0 | N42: 0 | O42: 0 | P42: 0 | Q42: 0 | R42: 0 | S42: 0 | T42: 0 | U42: 0 | V42: 0 | W42: 0 | X42: 0 | Y42: 0 | Z42: 0 | AA42: 0 | AB42: 0 | AC42: 0 | AD42: 0 | AE42: 0 | AF42: =参数输入表!H189*参数输入表!H188/(1+参数输入表!$H$190) -> 0
B43: 4 | C43: 研发费用 | D43: =SUM(F43:AF43) -> 0 | E43: 万元 | H43: 0 | I43: 0 | J43: 0 | K43: 0 | L43: 0 | M43: 0 | N43: 0 | O43: 0 | P43: 0 | Q43: 0 | R43: 0 | S43: 0 | T43: 0 | U43: 0 | V43: 0 | W43: 0 | X43: 0 | Y43: 0 | Z43: 0 | AA43: 0 | AB43: 0 | AC43: 0 | AD43: 0 | AE43: 0 | AF43: 0
B44: 二 | C44: 营业外支出 | D44: =SUM(F44:AF44) -> 0 | E44: 万元 | H44: =参数输入表!$H$267/(1+参数输入表!$H$271) -> 0 | I44: =参数输入表!$H$267/(1+参数输入表!$H$271) -> 0 | J44: =参数输入表!$H$267/(1+参数输入表!$H$271) -> 0 | K44: =参数输入表!$H$267/(1+参数输入表!$H$271) -> 0 | L44: =参数输入表!$H$267/(1+参数输入表!$H$271) -> 0 | M44: =参数输入表!$H$267/(1+参数输入表!$H$271) -> 0 | N44: =参数输入表!$H$267/(1+参数输入表!$H$271) -> 0 | O44: =参数输入表!$H$267/(1+参数输入表!$H$271) -> 0 | ... AF44: =参数输入表!$H$267/(1+参数输入表!$H$271) -> 0
B47: 成本现金支出表（隐藏）
B48: 一 | C48: 生产经营现金支出合计 | D48: =SUM(F48:AF48) -> 16761.342 | E48: 万元 | H48: =H49+H57+H58+H61 -> 567.93794 | I48: =I49+I57+I58+I61 -> 567.93794 | J48: =J49+J57+J58+J61 -> 567.93794 | K48: =K49+K57+K58+K61 -> 567.93794 | L48: =L49+L57+L58+L61 -> 567.93794 | M48: =M49+M57+M58+M61 -> 619.1958 | N48: =N49+N57+N58+N61 -> 619.1958 | O48: =O49+O57+O58+O61 -> 619.1958 | ... AF48: =AF49+AF57+AF58+AF61 -> 772.96939
B49: 1 | C49: 生产相关现金支出 | D49: =SUM(F49:AF49) -> 15229.34 | E49: 万元 | H49: =SUM(H50:H56) -> 506.65786 | I49: =SUM(I50:I56) -> 506.65786 | J49: =SUM(J50:J56) -> 506.65786 | K49: =SUM(K50:K56) -> 506.65786 | L49: =SUM(L50:L56) -> 506.65786 | M49: =SUM(M50:M56) -> 557.91572 | N49: =SUM(N50:N56) -> 557.91572 | O49: =SUM(O50:O56) -> 557.91572 | ... AF49: =SUM(AF50:AF56) -> 711.68931
B50: 1.1 | C50: 材料费 | D50: =SUM(F50:AF50) -> 3600 | E50: 万元 | H50: =参数输入表!$H$141*参数输入表!$H$13 -> 144 | I50: =参数输入表!$H$141*参数输入表!$H$13 -> 144 | J50: =参数输入表!$H$141*参数输入表!$H$13 -> 144 | K50: =参数输入表!$H$141*参数输入表!$H$13 -> 144 | L50: =参数输入表!$H$141*参数输入表!$H$13 -> 144 | M50: =参数输入表!$H$142*参数输入表!$H$13 -> 144 | N50: =参数输入表!$H$142*参数输入表!$H$13 -> 144 | O50: =参数输入表!$H$142*参数输入表!$H$13 -> 144 | P50: =参数输入表!$H$142*参数输入表!$H$13 -> 144 | Q50: =参数输入表!$H$142*参数输入表!$H$13 -> 144 | R50: =参数输入表!$H$143*参数输入表!$H$13 -> 144 | S50: =参数输入表!$H$143*参数输入表!$H$13 -> 144 | T50: =参数输入表!$H$143*参数输入表!$H$13 -> 144 | U50: =参数输入表!$H$143*参数输入表!$H$13 -> 144 | V50: =参数输入表!$H$143*参数输入表!$H$13 -> 144 | W50: =参数输入表!$H$144*参数输入表!$H$13 -> 144 | X50: =参数输入表!$H$144*参数输入表!$H$13 -> 144 | Y50: =参数输入表!$H$144*参数输入表!$H$13 -> 144 | Z50: =参数输入表!$H$144*参数输入表!$H$13 -> 144 | AA50: =参数输入表!$H$144*参数输入表!$H$13 -> 144 | AB50: =参数输入表!$H$145*参数输入表!$H$13 -> 144 | AC50: =参数输入表!$H$145*参数输入表!$H$13 -> 144 | AD50: =参数输入表!$H$145*参数输入表!$H$13 -> 144 | AE50: =参数输入表!$H$145*参数输入表!$H$13 -> 144 | AF50: =参数输入表!$H$145*参数输入表!$H$13 -> 144
B51: 1.2 | C51: 维修费 | D51: =SUM(F51:AF51) -> 3619.3397 | E51: 万元 | H51: =(参数输入表!$H$113-参数输入表!$H$120)*参数输入表!$H$150 -> 48.257862 | I51: =(参数输入表!$H$113-参数输入表!$H$120)*参数输入表!$H$150 -> 48.257862 | J51: =(参数输入表!$H$113-参数输入表!$H$120)*参数输入表!$H$150 -> 48.257862 | K51: =(参数输入表!$H$113-参数输入表!$H$120)*参数输入表!$H$150 -> 48.257862 | L51: =(参数输入表!$H$113-参数输入表!$H$120)*参数输入表!$H$150 -> 48.257862 | M51: =(参数输入表!$H$113-参数输入表!$H$120)*参数输入表!$H$151 -> 96.515725 | N51: =(参数输入表!$H$113-参数输入表!$H$120)*参数输入表!$H$151 -> 96.515725 | O51: =(参数输入表!$H$113-参数输入表!$H$120)*参数输入表!$H$151 -> 96.515725 | P51: =(参数输入表!$H$113-参数输入表!$H$120)*参数输入表!$H$151 -> 96.515725 | Q51: =(参数输入表!$H$113-参数输入表!$H$120)*参数输入表!$H$151 -> 96.515725 | R51: =(参数输入表!$H$113-参数输入表!$H$120)*参数输入表!$H$152 -> 144.77359 | S51: =(参数输入表!$H$113-参数输入表!$H$120)*参数输入表!$H$152 -> 144.77359 | T51: =(参数输入表!$H$113-参数输入表!$H$120)*参数输入表!$H$152 -> 144.77359 | U51: =(参数输入表!$H$113-参数输入表!$H$120)*参数输入表!$H$152 -> 144.77359 | V51: =(参数输入表!$H$113-参数输入表!$H$120)*参数输入表!$H$152 -> 144.77359 | W51: =(参数输入表!$H$113-参数输入表!$H$120)*参数输入表!$H$153 -> 193.03145 | X51: =(参数输入表!$H$113-参数输入表!$H$120)*参数输入表!$H$153 -> 193.03145 | Y51: =(参数输入表!$H$113-参数输入表!$H$120)*参数输入表!$H$153 -> 193.03145 | Z51: =(参数输入表!$H$113-参数输入表!$H$120)*参数输入表!$H$153 -> 193.03145 | AA51: =(参数输入表!$H$113-参数输入表!$H$120)*参数输入表!$H$153 -> 193.03145 | AB51: =(参数输入表!$H$113-参数输入表!$H$120)*参数输入表!$H$154 -> 241.28931 | AC51: =(参数输入表!$H$113-参数输入表!$H$120)*参数输入表!$H$154 -> 241.28931 | AD51: =(参数输入表!$H$113-参数输入表!$H$120)*参数输入表!$H$154 -> 241.28931 | AE51: =(参数输入表!$H$113-参数输入表!$H$120)*参数输入表!$H$154 -> 241.28931 | AF51: =(参数输入表!$H$113-参数输入表!$H$120)*参数输入表!$H$154 -> 241.28931
B52: 1.3 | C52: 生产人员薪酬及福利 | D52: =SUM(F52:AF52) -> 3360 | E52: 万元 | H52: =(参数输入表!$H$167*参数输入表!$H$170+参数输入表!$H$168*参数输入表!$H$171)*(1+参数输入表!$H$172)*(1+参数输入表!$H$173*(H4-1)) -> 134.4 | I52: =(参数输入表!$H$167*参数输入表!$H$170+参数输入表!$H$168*参数输入表!$H$171)*(1+参数输入表!$H$172)*(1+参数输入表!$H$173*(I4-1)) -> 134.4 | J52: =(参数输入表!$H$167*参数输入表!$H$170+参数输入表!$H$168*参数输入表!$H$171)*(1+参数输入表!$H$172)*(1+参数输入表!$H$173*(J4-1)) -> 134.4 | K52: =(参数输入表!$H$167*参数输入表!$H$170+参数输入表!$H$168*参数输入表!$H$171)*(1+参数输入表!$H$172)*(1+参数输入表!$H$173*(K4-1)) -> 134.4 | L52: =(参数输入表!$H$167*参数输入表!$H$170+参数输入表!$H$168*参数输入表!$H$171)*(1+参数输入表!$H$172)*(1+参数输入表!$H$173*(L4-1)) -> 134.4 | M52: =(参数输入表!$H$167*参数输入表!$H$170+参数输入表!$H$168*参数输入表!$H$171)*(1+参数输入表!$H$172)*(1+参数输入表!$H$173*(M4-1)) -> 134.4 | N52: =(参数输入表!$H$167*参数输入表!$H$170+参数输入表!$H$168*参数输入表!$H$171)*(1+参数输入表!$H$172)*(1+参数输入表!$H$173*(N4-1)) -> 134.4 | O52: =(参数输入表!$H$167*参数输入表!$H$170+参数输入表!$H$168*参数输入表!$H$171)*(1+参数输入表!$H$172)*(1+参数输入表!$H$173*(O4-1)) -> 134.4 | ... AF52: =(参数输入表!$H$167*参数输入表!$H$170+参数输入表!$H$168*参数输入表!$H$171)*(1+参数输入表!$H$172)*(1+参数输入表!$H$173*(AF4-1)) -> 134.4
B53: 1.4 | C53: 长期待摊实际支出 | D53: =SUM(F53:AF53) -> 0 | E53: 万元 | H53: =参数输入表!H206 -> 0 | I53: =参数输入表!H207 -> 0 | J53: =参数输入表!H208 -> 0 | K53: =参数输入表!H209 -> 0 | L53: =参数输入表!H210 -> 0 | M53: =参数输入表!H211 -> 0 | N53: =参数输入表!H212 -> 0 | O53: =参数输入表!H213 -> 0 | P53: =参数输入表!H214 -> 0 | Q53: =参数输入表!H215 -> 0 | R53: =参数输入表!H216 -> 0 | S53: =参数输入表!H217 -> 0 | T53: =参数输入表!H218 -> 0 | U53: =参数输入表!H219 -> 0 | V53: =参数输入表!H220 -> 0 | W53: =参数输入表!H221 -> 0 | X53: =参数输入表!H222 -> 0 | Y53: =参数输入表!H223 -> 0 | Z53: =参数输入表!H224 -> 0 | AA53: =参数输入表!H225 -> 0 | AB53: =参数输入表!H226 -> 0 | AC53: =参数输入表!H227 -> 0 | AD53: =参数输入表!H228 -> 0 | AE53: =参数输入表!H229 -> 0 | AF53: =参数输入表!H230 -> 0
B54: 1.5 | C54: 其他费用 | D54: =SUM(F54:AF54) -> 3000 | E54: 万元 | H54: =参数输入表!$H$175*参数输入表!$H$13 -> 120 | I54: =参数输入表!$H$175*参数输入表!$H$13 -> 120 | J54: =参数输入表!$H$175*参数输入表!$H$13 -> 120 | K54: =参数输入表!$H$175*参数输入表!$H$13 -> 120 | L54: =参数输入表!$H$175*参数输入表!$H$13 -> 120 | M54: =参数输入表!$H$175*参数输入表!$H$13 -> 120 | N54: =参数输入表!$H$175*参数输入表!$H$13 -> 120 | O54: =参数输入表!$H$175*参数输入表!$H$13 -> 120 | ... AF54: =参数输入表!$H$175*参数输入表!$H$13 -> 120
B55: 1.6 | C55: 储能费用 | D55: =SUM(F55:AF55) -> 0 | E55: 万元 | H55: =参数输入表!$H$191*参数输入表!$H$13*1000/10000 -> 0 | I55: =参数输入表!$H$191*参数输入表!$H$13*1000/10000 -> 0 | J55: =参数输入表!$H$191*参数输入表!$H$13*1000/10000 -> 0 | K55: =参数输入表!$H$191*参数输入表!$H$13*1000/10000 -> 0 | L55: =参数输入表!$H$191*参数输入表!$H$13*1000/10000 -> 0 | M55: =参数输入表!$H$191*参数输入表!$H$13*1000/10000 -> 0 | N55: =参数输入表!$H$191*参数输入表!$H$13*1000/10000 -> 0 | O55: =参数输入表!$H$191*参数输入表!$H$13*1000/10000 -> 0 | ... AF55: =参数输入表!$H$191*参数输入表!$H$13*1000/10000 -> 0
B56: 1.7 | C56: 场地租金费用 | D56: =SUM(F56:AF56) -> 1650 | E56: 万元 | H56: =参数输入表!$H$178*参数输入表!$H$179/10000*(1+参数输入表!$H$181) -> 60 | I56: =参数输入表!$H$178*参数输入表!$H$179/10000*(1+参数输入表!$H$181) -> 60 | J56: =参数输入表!$H$178*参数输入表!$H$179/10000*(1+参数输入表!$H$181) -> 60 | K56: =参数输入表!$H$178*参数输入表!$H$179/10000*(1+参数输入表!$H$181) -> 60 | L56: =参数输入表!$H$178*参数输入表!$H$179/10000*(1+参数输入表!$H$181) -> 60 | M56: =参数输入表!$H$178*参数输入表!$H$179/10000*(1+参数输入表!$H$182) -> 63 | N56: =参数输入表!$H$178*参数输入表!$H$179/10000*(1+参数输入表!$H$182) -> 63 | O56: =参数输入表!$H$178*参数输入表!$H$179/10000*(1+参数输入表!$H$182) -> 63 | P56: =参数输入表!$H$178*参数输入表!$H$179/10000*(1+参数输入表!$H$182) -> 63 | Q56: =参数输入表!$H$178*参数输入表!$H$179/10000*(1+参数输入表!$H$182) -> 63 | R56: =参数输入表!$H$178*参数输入表!$H$179/10000*(1+参数输入表!$H$183) -> 66 | S56: =参数输入表!$H$178*参数输入表!$H$179/10000*(1+参数输入表!$H$183) -> 66 | T56: =参数输入表!$H$178*参数输入表!$H$179/10000*(1+参数输入表!$H$183) -> 66 | U56: =参数输入表!$H$178*参数输入表!$H$179/10000*(1+参数输入表!$H$183) -> 66 | V56: =参数输入表!$H$178*参数输入表!$H$179/10000*(1+参数输入表!$H$183) -> 66 | W56: =参数输入表!$H$178*参数输入表!$H$179/10000*(1+参数输入表!$H$184) -> 69 | X56: =参数输入表!$H$178*参数输入表!$H$179/10000*(1+参数输入表!$H$184) -> 69 | Y56: =参数输入表!$H$178*参数输入表!$H$179/10000*(1+参数输入表!$H$184) -> 69 | Z56: =参数输入表!$H$178*参数输入表!$H$179/10000*(1+参数输入表!$H$184) -> 69 | AA56: =参数输入表!$H$178*参数输入表!$H$179/10000*(1+参数输入表!$H$184) -> 69 | AB56: =参数输入表!$H$178*参数输入表!$H$179/10000*(1+参数输入表!$H$185) -> 72 | AC56: =参数输入表!$H$178*参数输入表!$H$179/10000*(1+参数输入表!$H$185) -> 72 | AD56: =参数输入表!$H$178*参数输入表!$H$179/10000*(1+参数输入表!$H$185) -> 72 | AE56: =参数输入表!$H$178*参数输入表!$H$179/10000*(1+参数输入表!$H$185) -> 72 | AF56: =参数输入表!$H$178*参数输入表!$H$179/10000*(1+参数输入表!$H$185) -> 72
B57: 2 | C57: 销售费用现金支出 | D57: =SUM(F57:AF57) -> 0 | E57: 万元 | H57: 0 | I57: 0 | J57: 0 | K57: 0 | L57: 0 | M57: 0 | N57: 0 | O57: 0 | P57: 0 | Q57: 0 | R57: 0 | S57: 0 | T57: 0 | U57: 0 | V57: 0 | W57: 0 | X57: 0 | Y57: 0 | Z57: 0 | AA57: 0 | AB57: 0 | AC57: 0 | AD57: 0 | AE57: 0 | AF57: 0
B58: 3 | C58: 管理费用现金支出 | D58: =SUM(F58:AF58) -> 1532.002 | E58: 万元 | H58: =SUM(H59:H60) -> 61.28008 | I58: =SUM(I59:I60) -> 61.28008 | J58: =SUM(J59:J60) -> 61.28008 | K58: =SUM(K59:K60) -> 61.28008 | L58: =SUM(L59:L60) -> 61.28008 | M58: =SUM(M59:M60) -> 61.28008 | N58: =SUM(N59:N60) -> 61.28008 | O58: =SUM(O59:O60) -> 61.28008 | ... AF58: =SUM(AF59:AF60) -> 61.28008
B59: 3.1 | C59: 保险费 | D59: =SUM(F59:AF59) -> 1532.002 | E59: 万元 | H59: =H17 -> 61.28008 | I59: =I17 -> 61.28008 | J59: =J17 -> 61.28008 | K59: =K17 -> 61.28008 | L59: =L17 -> 61.28008 | M59: =M17 -> 61.28008 | N59: =N17 -> 61.28008 | O59: =O17 -> 61.28008 | ... AF59: =AF17 -> 61.28008
B60: 3.2 | C60: 期末拆除费用 | D60: =SUM(F60:AF60) -> 0 | E60: 万元 | H60: 0 | I60: 0 | J60: 0 | K60: 0 | L60: 0 | M60: 0 | N60: 0 | O60: 0 | P60: 0 | Q60: 0 | R60: 0 | S60: 0 | T60: 0 | U60: 0 | V60: 0 | W60: 0 | X60: 0 | Y60: 0 | Z60: 0 | AA60: 0 | AB60: 0 | AC60: 0 | AD60: 0 | AE60: 0 | AF60: =参数输入表!H189*参数输入表!H188 -> 0
B61: 4 | C61: 研发费用现金支出 | D61: =SUM(F61:AF61) -> 0 | E61: 万元 | H61: 0 | I61: 0 | J61: 0 | K61: 0 | L61: 0 | M61: 0 | N61: 0 | O61: 0 | P61: 0 | Q61: 0 | R61: 0 | S61: 0 | T61: 0 | U61: 0 | V61: 0 | W61: 0 | X61: 0 | Y61: 0 | Z61: 0 | AA61: 0 | AB61: 0 | AC61: 0 | AD61: 0 | AE61: 0 | AF61: 0
B62: 二 | C62: 营业外现金支出 | D62: =SUM(F62:AF62) -> 0 | E62: 万元 | H62: =参数输入表!$H$267 -> 0 | I62: =参数输入表!$H$267 -> 0 | J62: =参数输入表!$H$267 -> 0 | K62: =参数输入表!$H$267 -> 0 | L62: =参数输入表!$H$267 -> 0 | M62: =参数输入表!$H$267 -> 0 | N62: =参数输入表!$H$267 -> 0 | O62: =参数输入表!$H$267 -> 0 | ... AF62: =参数输入表!$H$267 -> 0
C65: 成本表中（1）财务费用引用自“表2-还本付息表”；（2）折旧费、无形资产摊销、长期待摊费用摊销 引用自“表3-折旧摊销表”；其余数据通过参数输入表中成本费用板块相关参数计算而得。
C66: 经营成本为运营期各年不含税值
C68: 标黄部分为相对固定模块，适用于所有项目

Sheet 表4-收入税金表
B2: 收入表
B3: 序号 | C3: 项目 | D3: 合计 | E3: 单位 | F3: 建设期 | H3: 运营期
F4: 1 | G4: 2 | H4: 1 | I4: 2 | J4: 3 | K4: 4 | L4: 5 | M4: 6 | N4: 7 | O4: 8 | P4: 9 | Q4: 10 | R4: 11 | S4: 12 | T4: 13 | U4: 14 | V4: 15 | W4: 16 | X4: 17 | Y4: 18 | Z4: 19 | AA4: 20 | AB4: 21 | AC4: 22 | AD4: 23 | AE4: 24 | AF4: 25
B5: 1 | C5: 营业收入 | D5: =SUM(F5:AF5) -> 73734.758 | E5: 万元 | H5: =H6 -> 2994.9375 | I5: =I6 -> 2981.4603 | J5: =J6 -> 2968.0437 | K5: =K6 -> 2954.6875 | L5: =L6 -> 2941.3914 | M5: =M6 -> 3072.5853 | N5: =N6 -> 3058.7586 | O5: =O6 -> 3044.9942 | ... AF5: =AF6 -> 2820.2523
B6: 1.1 | C6: 发电销售收入 | D6: =SUM(F6:AF6) -> 73734.758 | E6: 万元 | H6: =(H9*H10-H11-H12)/(1+参数输入表!$H$291)+(H14*H15)/(1+参数输入表!$H$296) -> 2994.9375 | I6: =(I9*I10-I11-I12)/(1+参数输入表!$H$291)+(I14*I15)/(1+参数输入表!$H$296) -> 2981.4603 | J6: =(J9*J10-J11-J12)/(1+参数输入表!$H$291)+(J14*J15)/(1+参数输入表!$H$296) -> 2968.0437 | K6: =(K9*K10-K11-K12)/(1+参数输入表!$H$291)+(K14*K15)/(1+参数输入表!$H$296) -> 2954.6875 | L6: =(L9*L10-L11-L12)/(1+参数输入表!$H$291)+(L14*L15)/(1+参数输入表!$H$296) -> 2941.3914 | M6: =(M9*M10-M11-M12)/(1+参数输入表!$H$291)+(M14*M15)/(1+参数输入表!$H$296) -> 3072.5853 | N6: =(N9*N10-N11-N12)/(1+参数输入表!$H$291)+(N14*N15)/(1+参数输入表!$H$296) -> 3058.7586 | O6: =(O9*O10-O11-O12)/(1+参数输入表!$H$291)+(O14*O15)/(1+参数输入表!$H$296) -> 3044.9942 | ... AF6: =(AF9*AF10-AF11-AF12)/(1+参数输入表!$H$291)+(AF14*AF15)/(1+参数输入表!$H$296) -> 2820.2523
C7: 发电量 | D7: =SUM(F7:AF7) -> 225201.5 | E7: 万度 | H7: =参数输入表!H13*参数输入表!H16*(1-参数输入表!H18)/10 -> 9504 | I7: =H7*(1-参数输入表!$H$19) -> 9461.232 | J7: =I7*(1-参数输入表!$H$19) -> 9418.6565 | K7: =J7*(1-参数输入表!$H$19) -> 9376.2725 | L7: =K7*(1-参数输入表!$H$19) -> 9334.0793 | M7: =L7*(1-参数输入表!$H$19) -> 9292.0759 | N7: =M7*(1-参数输入表!$H$19) -> 9250.2616 | O7: =N7*(1-参数输入表!$H$19) -> 9208.6354 | P7: =O7*(1-参数输入表!$H$19) -> 9167.1965 | ... AF7: =AE7*(1-参数输入表!$H$19) -> 8528.9736
C8: 上网售电收入 | D8: =SUM(F8:AF8) -> 21266.723 | E8: 万元 | H8: =H9*H10/1.13 -> 1312.8136 | I8: =I9*I10/1.13 -> 1306.9059 | J8: =J9*J10/1.13 -> 1301.0249 | K8: =K9*K10/1.13 -> 1295.1702 | L8: =L9*L10/1.13 -> 1289.342 | M8: =M9*M10/1.13 -> 770.12396 | N8: =N9*N10/1.13 -> 766.65841 | O8: =O9*O10/1.13 -> 763.20844 | ... AF8: =AF9*AF10/1.13 -> 706.87832
C9: 上网电量 | D9: =SUM(F9:AF9) -> 72822.415 | E9: 万度 | H9: =参数输入表!H47/10 -> 4495.392 | I9: =参数输入表!H48/10 -> 4475.1627 | J9: =参数输入表!H49/10 -> 4455.0245 | K9: =参数输入表!H50/10 -> 4434.9769 | L9: =参数输入表!H51/10 -> 4415.0195 | M9: =参数输入表!H52/10 -> 2637.0911 | N9: =参数输入表!H53/10 -> 2625.2242 | O9: =参数输入表!H54/10 -> 2613.4107 | P9: =参数输入表!H55/10 -> 2601.6504 | Q9: =参数输入表!H56/10 -> 2589.943 | R9: =参数输入表!H57/10 -> 2578.2882 | S9: =参数输入表!H58/10 -> 2566.6859 | T9: =参数输入表!H59/10 -> 2555.1358 | U9: =参数输入表!H60/10 -> 2543.6377 | V9: =参数输入表!H61/10 -> 2532.1913 | W9: =参数输入表!H62/10 -> 2520.7965 | X9: =参数输入表!H63/10 -> 2509.4529 | Y9: =参数输入表!H64/10 -> 2498.1604 | Z9: =参数输入表!H65/10 -> 2486.9186 | AA9: =参数输入表!H66/10 -> 2475.7275 | AB9: =参数输入表!H67/10 -> 2464.5867 | AC9: =参数输入表!H68/10 -> 2453.4961 | AD9: =参数输入表!H69/10 -> 2442.4554 | AE9: =参数输入表!H70/10 -> 2431.4643 | AF9: =参数输入表!H71/10 -> 2420.5227
C10: 上网电价（含税） | E10: 元/度 | H10: =参数输入表!H73 -> 0.33 | I10: =H10 -> 0.33 | J10: =I10 -> 0.33 | K10: =J10 -> 0.33 | L10: =K10 -> 0.33 | M10: =L10 -> 0.33 | N10: =M10 -> 0.33 | O10: =N10 -> 0.33 | P10: =O10 -> 0.33 | ... AF10: =AE10 -> 0.33
C11: 电网辅助服务分摊 | D11: =SUM(F11:AF11) -> 0 | E11: 万元 | H11: =H9*参数输入表!$H$284 -> 0 | I11: =I9*参数输入表!$H$284 -> 0 | J11: =J9*参数输入表!$H$284 -> 0 | K11: =K9*参数输入表!$H$284 -> 0 | L11: =L9*参数输入表!$H$284 -> 0 | M11: =M9*参数输入表!$H$284 -> 0 | N11: =N9*参数输入表!$H$284 -> 0 | O11: =O9*参数输入表!$H$284 -> 0 | ... AF11: =AF9*参数输入表!$H$284 -> 0
C12: 两个细则考核 | D12: =SUM(F12:AF12) -> 0 | E12: 万元 | H12: =H9*参数输入表!$H$288 -> 0 | I12: =I9*参数输入表!$H$288 -> 0 | J12: =J9*参数输入表!$H$288 -> 0 | K12: =K9*参数输入表!$H$288 -> 0 | L12: =L9*参数输入表!$H$288 -> 0 | M12: =M9*参数输入表!$H$288 -> 0 | N12: =N9*参数输入表!$H$288 -> 0 | O12: =O9*参数输入表!$H$288 -> 0 | ... AF12: =AF9*参数输入表!$H$288 -> 0
C13: 数能融合售电收入 | D13: =SUM(F13:AF13) -> 52468.035 | E13: 万元 | H13: =H14*H15/1.13 -> 1682.1239 | I13: =I14*I15/1.13 -> 1674.5543 | J13: =J14*J15/1.13 -> 1667.0188 | K13: =K14*K15/1.13 -> 1659.5173 | L13: =L14*L15/1.13 -> 1652.0494 | M13: =M14*M15/1.13 -> 2302.4613 | N13: =N14*N15/1.13 -> 2292.1002 | O13: =O14*O15/1.13 -> 2281.7858 | ... AF13: =AF14*AF15/1.13 -> 2113.374
C14: 数能融合消纳电量 | D14: =SUM(F14:AF14) -> 148222.2 | E14: 万度 | H14: =参数输入表!H77*参数输入表!H21/10 -> 4752 | I14: =参数输入表!H78*参数输入表!H22/10 -> 4730.616 | J14: =参数输入表!H79*参数输入表!H23/10 -> 4709.3282 | K14: =参数输入表!H80*参数输入表!H24/10 -> 4688.1363 | L14: =参数输入表!H81*参数输入表!H25/10 -> 4667.0396 | M14: =参数输入表!H82*参数输入表!H26/10 -> 6504.4531 | N14: =参数输入表!H83*参数输入表!H27/10 -> 6475.1831 | O14: =参数输入表!H84*参数输入表!H28/10 -> 6446.0448 | P14: =参数输入表!H85*参数输入表!H29/10 -> 6417.0376 | Q14: =参数输入表!H86*参数输入表!H30/10 -> 6388.1609 | R14: =参数输入表!H87*参数输入表!H31/10 -> 6359.4142 | S14: =参数输入表!H88*参数输入表!H32/10 -> 6330.7968 | T14: =参数输入表!H89*参数输入表!H33/10 -> 6302.3082 | U14: =参数输入表!H90*参数输入表!H34/10 -> 6273.9478 | V14: =参数输入表!H91*参数输入表!H35/10 -> 6245.7151 | W14: =参数输入表!H92*参数输入表!H36/10 -> 6217.6094 | X14: =参数输入表!H93*参数输入表!H37/10 -> 6189.6301 | Y14: =参数输入表!H94*参数输入表!H38/10 -> 6161.7768 | Z14: =参数输入表!H95*参数输入表!H39/10 -> 6134.0488 | AA14: =参数输入表!H96*参数输入表!H40/10 -> 6106.4456 | AB14: =参数输入表!H97/10*参数输入表!H41 -> 6078.9666 | AC14: =参数输入表!H98/10*参数输入表!H42 -> 6051.6112 | AD14: =参数输入表!H99/10*参数输入表!H43 -> 6024.379 | AE14: =参数输入表!H100/10*参数输入表!H44 -> 5997.2693 | AF14: =参数输入表!H101/10*参数输入表!H45 -> 5970.2816
C15: 数能融合机制电价（含税） | E15: 元/度 | H15: =参数输入表!H103 -> 0.4 | I15: =H15 -> 0.4 | J15: =I15 -> 0.4 | K15: =J15 -> 0.4 | L15: =K15 -> 0.4 | M15: =L15 -> 0.4 | N15: =M15 -> 0.4 | O15: =N15 -> 0.4 | P15: =O15 -> 0.4 | ... AF15: =AE15 -> 0.4
B16: 2 | C16: 其他收入 | D16: =SUM(F16:AF16) -> 0 | E16: 万元 | H16: =(参数输入表!$H$298*参数输入表!$H$299)/(1+参数输入表!$H$300) -> 0 | I16: =(参数输入表!$H$298*参数输入表!$H$299)/(1+参数输入表!$H$300) -> 0 | J16: =(参数输入表!$H$298*参数输入表!$H$299)/(1+参数输入表!$H$300) -> 0 | K16: =(参数输入表!$H$298*参数输入表!$H$299)/(1+参数输入表!$H$300) -> 0 | L16: =(参数输入表!$H$298*参数输入表!$H$299)/(1+参数输入表!$H$300) -> 0 | M16: =(参数输入表!$H$298*参数输入表!$H$299)/(1+参数输入表!$H$300) -> 0 | N16: =(参数输入表!$H$298*参数输入表!$H$299)/(1+参数输入表!$H$300) -> 0 | O16: =(参数输入表!$H$298*参数输入表!$H$299)/(1+参数输入表!$H$300) -> 0 | ... AF16: =(参数输入表!$H$298*参数输入表!$H$299)/(1+参数输入表!$H$300) -> 0
B17: 3 | C17: 营业外收入 | D17: =SUM(F17:AF17) -> 0 | E17: 万元 | H17: =SUM(H18:H19) -> 0 | I17: =SUM(I18:I19) -> 0 | J17: =SUM(J18:J19) -> 0 | K17: =SUM(K18:K19) -> 0 | L17: =SUM(L18:L19) -> 0 | M17: =SUM(M18:M19) -> 0 | N17: =SUM(N18:N19) -> 0 | O17: =SUM(O18:O19) -> 0 | ... AF17: =SUM(AF18:AF19) -> 0
B18: 3.1 | C18: 政府一次性运营补贴收入 | D18: =SUM(F18:AF18) -> 0 | E18: 万元 | H18: =参数输入表!H303 -> 0
B19: 3.2 | C19: 增值税即征即退 | D19: =SUM(F19:AF19) -> 0 | E19: 万元 | H19: =H22*参数输入表!$H$331 -> 0 | I19: =I22*参数输入表!$H$331 -> 0 | J19: =J22*参数输入表!$H$331 -> 0 | K19: =K22*参数输入表!$H$331 -> 0 | L19: =L22*参数输入表!$H$331 -> 0 | M19: =M22*参数输入表!$H$331 -> 0 | N19: =N22*参数输入表!$H$331 -> 0 | O19: =O22*参数输入表!$H$331 -> 0 | ... AF19: =AF22*参数输入表!$H$331 -> 0
B21: 税金表
B22: 1 | C22: 当期实缴增值税 | D22: =SUM(F22:AF22) -> 6959.2285 | E22: 万元 | F22: 0 | G22: =IF(G45>0,0,G44-F45) -> 0 | H22: =IF(H45>0,0,H44-G45) -> 0 | I22: =IF(I45>0,0,I44-H45) -> 0 | J22: =IF(J45>0,0,J44-I45) -> 0 | K22: =IF(K45>0,0,K44-J45) -> 0 | L22: =IF(L45>0,0,L44-K45) -> 0 | M22: =IF(M45>0,0,M44-L45) -> 0 | N22: =IF(N45>0,0,N44-M45) -> 155.27352 | ... AF22: =IF(AF45>0,0,AF44-AE45) -> 366.6328
B23: 2 | C23: 增值税销项税 | D23: =SUM(F23:AF23) -> 9585.5186 | E23: 万元 | F23: =SUM(F24:F25) -> 0 | G23: =SUM(G24:G25) -> 0 | H23: =SUM(H24:H25) -> 389.34187 | I23: =SUM(I24:I25) -> 387.58983 | J23: =SUM(J24:J25) -> 385.84568 | K23: =SUM(K24:K25) -> 384.10938 | L23: =SUM(L24:L25) -> 382.38088 | M23: =SUM(M24:M25) -> 399.43608 | ... AF23: =SUM(AF24:AF25) -> 366.6328
C24: 发电收入销项税 | D24: =SUM(F24:AF24) -> 9585.5186 | E24: 万元 | H24: =H6*参数输入表!$H$291 -> 389.34187 | I24: =I6*参数输入表!$H$291 -> 387.58983 | J24: =J6*参数输入表!$H$291 -> 385.84568 | K24: =K6*参数输入表!$H$291 -> 384.10938 | L24: =L6*参数输入表!$H$291 -> 382.38088 | M24: =M6*参数输入表!$H$291 -> 399.43608 | N24: =N6*参数输入表!$H$291 -> 397.63862 | O24: =O6*参数输入表!$H$291 -> 395.84925 | ... AF24: =AF6*参数输入表!$H$291 -> 366.6328
C25: 其他收入销项税 | D25: =SUM(F25:AF25) -> 0 | E25: 万元 | H25: =H16*参数输入表!$H$300 -> 0 | I25: =I16*参数输入表!$H$300 -> 0 | J25: =J16*参数输入表!$H$300 -> 0 | K25: =K16*参数输入表!$H$300 -> 0 | L25: =L16*参数输入表!$H$300 -> 0 | M25: =M16*参数输入表!$H$300 -> 0 | N25: =N16*参数输入表!$H$300 -> 0 | O25: =O16*参数输入表!$H$300 -> 0 | ... AF25: =AF16*参数输入表!$H$300 -> 0
B26: 3 | C26: 增值税进项税 | D26: =SUM(F26:AF26) -> 2626.2901 | E26: 万元 | F26: =F27+F28+F42+F43 -> 2571.0688 | G26: =G27+G28+G42+G43 -> 0 | H26: =H27+H28+H42+H43 -> 0 | I26: =I27+I28+I42+I43 -> 0 | J26: =J27+J28+J42+J43 -> 0 | K26: =K27+K28+K42+K43 -> 0 | L26: =L27+L28+L42+L43 -> 0 | M26: =M27+M28+M42+M43 -> 0 | ... AF26: =AF27+AF28+AF42+AF43 -> 0
B27: 3.1 | C27: 建设投资进项税 | D27: =SUM(F27:AF27) -> 2571.0688 | E27: 万元 | F27: =参数输入表!H120*参数输入表!H7 -> 2571.0688 | G27: =参数输入表!H120*参数输入表!H8 -> 0
B28: 3.2 | C28: 营业成本进项税 | D28: =SUM(F28:AF28) -> 0 | E28: 万元 | F28: =F29+F37+F38+F41 -> 0 | G28: =G29+G37+G38+G41 -> 0 | H28: =H29+H37+H38+H41 -> 0 | I28: =I29+I37+I38+I41 -> 0 | J28: =J29+J37+J38+J41 -> 0 | K28: =K29+K37+K38+K41 -> 0 | L28: =L29+L37+L38+L41 -> 0 | M28: =M29+M37+M38+M41 -> 0 | ... AF28: =AF29+AF37+AF38+AF41 -> 0
B29: 3.2.1 | C29: 生产成本进项税 | D29: =SUM(F29:AF29) -> 0 | E29: 万元 | H29: =SUM(H30:H36) -> 0 | I29: =SUM(I30:I36) -> 0 | J29: =SUM(J30:J36) -> 0 | K29: =SUM(K30:K36) -> 0 | L29: =SUM(L30:L36) -> 0 | M29: =SUM(M30:M36) -> 0 | N29: =SUM(N30:N36) -> 0 | O29: =SUM(O30:O36) -> 0 | ... AF29: =SUM(AF30:AF36) -> 0
C30: 材料费 | D30: =SUM(F30:AF30) -> 0 | E30: 万元 | H30: ='表3-成本费用表'!H50*参数输入表!$H$146 -> 0 | I30: ='表3-成本费用表'!I50*参数输入表!$H$146 -> 0 | J30: ='表3-成本费用表'!J50*参数输入表!$H$146 -> 0 | K30: ='表3-成本费用表'!K50*参数输入表!$H$146 -> 0 | L30: ='表3-成本费用表'!L50*参数输入表!$H$146 -> 0 | M30: ='表3-成本费用表'!M50*参数输入表!$H$146 -> 0 | N30: ='表3-成本费用表'!N50*参数输入表!$H$146 -> 0 | O30: ='表3-成本费用表'!O50*参数输入表!$H$146 -> 0 | ... AF30: ='表3-成本费用表'!AF50*参数输入表!$H$146 -> 0
C31: 维修费 | D31: =SUM(F31:AF31) -> 0 | E31: 万元 | H31: ='表3-成本费用表'!H51*参数输入表!$H$155 -> 0 | I31: ='表3-成本费用表'!I51*参数输入表!$H$155 -> 0 | J31: ='表3-成本费用表'!J51*参数输入表!$H$155 -> 0 | K31: ='表3-成本费用表'!K51*参数输入表!$H$155 -> 0 | L31: ='表3-成本费用表'!L51*参数输入表!$H$155 -> 0 | M31: ='表3-成本费用表'!M51*参数输入表!$H$155 -> 0 | N31: ='表3-成本费用表'!N51*参数输入表!$H$155 -> 0 | O31: ='表3-成本费用表'!O51*参数输入表!$H$155 -> 0 | ... AF31: ='表3-成本费用表'!AF51*参数输入表!$H$155 -> 0
C32: 生产人员薪酬及福利 | D32: =SUM(F32:AF32) -> 0 | E32: 万元 | H32: ='表3-成本费用表'!H52*参数输入表!$H$174 -> 0 | I32: ='表3-成本费用表'!I52*参数输入表!$H$174 -> 0 | J32: ='表3-成本费用表'!J52*参数输入表!$H$174 -> 0 | K32: ='表3-成本费用表'!K52*参数输入表!$H$174 -> 0 | L32: ='表3-成本费用表'!L52*参数输入表!$H$174 -> 0 | M32: ='表3-成本费用表'!M52*参数输入表!$H$174 -> 0 | N32: ='表3-成本费用表'!N52*参数输入表!$H$174 -> 0 | O32: ='表3-成本费用表'!O52*参数输入表!$H$174 -> 0 | ... AF32: ='表3-成本费用表'!AF52*参数输入表!$H$174 -> 0
C33: 其他费用 | D33: =SUM(F33:AF33) -> 0 | E33: 万元 | H33: ='表3-成本费用表'!H54*参数输入表!$H$176 -> 0 | I33: ='表3-成本费用表'!I54*参数输入表!$H$176 -> 0 | J33: ='表3-成本费用表'!J54*参数输入表!$H$176 -> 0 | K33: ='表3-成本费用表'!K54*参数输入表!$H$176 -> 0 | L33: ='表3-成本费用表'!L54*参数输入表!$H$176 -> 0 | M33: ='表3-成本费用表'!M54*参数输入表!$H$176 -> 0 | N33: ='表3-成本费用表'!N54*参数输入表!$H$176 -> 0 | O33: ='表3-成本费用表'!O54*参数输入表!$H$176 -> 0 | ... AF33: ='表3-成本费用表'!AF54*参数输入表!$H$176 -> 0
C34: 储能费用 | D34: =SUM(F34:AF34) -> 0 | E34: 万元 | H34: ='表3-成本费用表'!H55*参数输入表!$H$192 -> 0 | I34: ='表3-成本费用表'!I55*参数输入表!$H$192 -> 0 | J34: ='表3-成本费用表'!J55*参数输入表!$H$192 -> 0 | K34: ='表3-成本费用表'!K55*参数输入表!$H$192 -> 0 | L34: ='表3-成本费用表'!L55*参数输入表!$H$192 -> 0 | M34: ='表3-成本费用表'!M55*参数输入表!$H$192 -> 0 | N34: ='表3-成本费用表'!N55*参数输入表!$H$192 -> 0 | O34: ='表3-成本费用表'!O55*参数输入表!$H$192 -> 0 | ... AF34: ='表3-成本费用表'!AF55*参数输入表!$H$192 -> 0
C35: 场地租金费用 | D35: =SUM(F35:AF35) -> 0 | E35: 万元 | H35: ='表3-成本费用表'!H56*参数输入表!$H$186 -> 0 | I35: ='表3-成本费用表'!I56*参数输入表!$H$186 -> 0 | J35: ='表3-成本费用表'!J56*参数输入表!$H$186 -> 0 | K35: ='表3-成本费用表'!K56*参数输入表!$H$186 -> 0 | L35: ='表3-成本费用表'!L56*参数输入表!$H$186 -> 0 | M35: ='表3-成本费用表'!M56*参数输入表!$H$186 -> 0 | N35: ='表3-成本费用表'!N56*参数输入表!$H$186 -> 0 | O35: ='表3-成本费用表'!O56*参数输入表!$H$186 -> 0 | ... AF35: ='表3-成本费用表'!AF56*参数输入表!$H$186 -> 0
C36: 计入长期待摊成本项 | D36: =SUM(F36:AF36) -> 0 | E36: 万元 | H36: ='表3-成本费用表'!H53*参数输入表!$H$233 -> 0 | I36: ='表3-成本费用表'!I53*参数输入表!$H$233 -> 0 | J36: ='表3-成本费用表'!J53*参数输入表!$H$233 -> 0 | K36: ='表3-成本费用表'!K53*参数输入表!$H$233 -> 0 | L36: ='表3-成本费用表'!L53*参数输入表!$H$233 -> 0 | M36: ='表3-成本费用表'!M53*参数输入表!$H$233 -> 0 | N36: ='表3-成本费用表'!N53*参数输入表!$H$233 -> 0 | O36: ='表3-成本费用表'!O53*参数输入表!$H$233 -> 0 | ... AF36: ='表3-成本费用表'!AF53*参数输入表!$H$233 -> 0
B37: 3.2.2 | C37: 销售费用进项税 | D37: =SUM(F37:AF37) -> 0 | E37: 万元 | H37: 0 | I37: 0 | J37: 0 | K37: 0 | L37: 0 | M37: 0 | N37: 0 | O37: 0 | P37: 0 | Q37: 0 | R37: 0 | S37: 0 | T37: 0 | U37: 0 | V37: 0 | W37: 0 | X37: 0 | Y37: 0 | Z37: 0 | AA37: 0 | AB37: 0 | AC37: 0 | AD37: 0 | AE37: 0 | AF37: 0
B38: 3.2.3 | C38: 管理费用进项税 | D38: =SUM(F38:AF38) -> 0 | E38: 万元 | H38: =SUM(H39:H40) -> 0 | I38: =SUM(I39:I40) -> 0 | J38: =SUM(J39:J40) -> 0 | K38: =SUM(K39:K40) -> 0 | L38: =SUM(L39:L40) -> 0 | M38: =SUM(M39:M40) -> 0 | N38: =SUM(N39:N40) -> 0 | O38: =SUM(O39:O40) -> 0 | ... AF38: =SUM(AF39:AF40) -> 0
C39: 保险费 | D39: =SUM(F39:AF39) -> 0 | E39: 万元 | H39: ='表3-成本费用表'!H17*参数输入表!$H$164 -> 0 | I39: ='表3-成本费用表'!I17*参数输入表!$H$164 -> 0 | J39: ='表3-成本费用表'!J17*参数输入表!$H$164 -> 0 | K39: ='表3-成本费用表'!K17*参数输入表!$H$164 -> 0 | L39: ='表3-成本费用表'!L17*参数输入表!$H$164 -> 0 | M39: ='表3-成本费用表'!M17*参数输入表!$H$164 -> 0 | N39: ='表3-成本费用表'!N17*参数输入表!$H$164 -> 0 | O39: ='表3-成本费用表'!O17*参数输入表!$H$164 -> 0 | ... AF39: ='表3-成本费用表'!AF17*参数输入表!$H$164 -> 0
C40: 期末拆除费用 | D40: =SUM(F40:AF40) -> 0 | E40: 万元 | H40: ='表3-成本费用表'!H18*参数输入表!$H$190 -> 0 | I40: ='表3-成本费用表'!I18*参数输入表!$H$190 -> 0 | J40: ='表3-成本费用表'!J18*参数输入表!$H$190 -> 0 | K40: ='表3-成本费用表'!K18*参数输入表!$H$190 -> 0 | L40: ='表3-成本费用表'!L18*参数输入表!$H$190 -> 0 | M40: ='表3-成本费用表'!M18*参数输入表!$H$190 -> 0 | N40: ='表3-成本费用表'!N18*参数输入表!$H$190 -> 0 | O40: ='表3-成本费用表'!O18*参数输入表!$H$190 -> 0 | ... AF40: ='表3-成本费用表'!AF18*参数输入表!$H$190 -> 0
B41: 3.2.4 | C41: 研发费用进项税 | D41: =SUM(F41:AF41) -> 0 | E41: 万元 | H41: 0 | I41: 0 | J41: 0 | K41: 0 | L41: 0 | M41: 0 | N41: 0 | O41: 0 | P41: 0 | Q41: 0 | R41: 0 | S41: 0 | T41: 0 | U41: 0 | V41: 0 | W41: 0 | X41: 0 | Y41: 0 | Z41: 0 | AA41: 0 | AB41: 0 | AC41: 0 | AD41: 0 | AE41: 0 | AF41: 0
B42: 3.3 | C42: 营业外支出进项税 | D42: =SUM(F42:AF42) -> 0 | E42: 万元 | H42: ='表3-成本费用表'!H62*参数输入表!$H$271 -> 0 | I42: ='表3-成本费用表'!I62*参数输入表!$H$271 -> 0 | J42: ='表3-成本费用表'!J62*参数输入表!$H$271 -> 0 | K42: ='表3-成本费用表'!K62*参数输入表!$H$271 -> 0 | L42: ='表3-成本费用表'!L62*参数输入表!$H$271 -> 0 | M42: ='表3-成本费用表'!M62*参数输入表!$H$271 -> 0 | N42: ='表3-成本费用表'!N62*参数输入表!$H$271 -> 0 | O42: ='表3-成本费用表'!O62*参数输入表!$H$271 -> 0 | ... AF42: ='表3-成本费用表'!AF62*参数输入表!$H$271 -> 0
B43: 3.4 | C43: 大修及更新重置进项税 | D43: =SUM(F43:AF43) -> 55.221239 | E43: 万元 | H43: =参数输入表!H236/(1+参数输入表!$H$264)*参数输入表!$H$264 -> 0 | I43: =参数输入表!H237/(1+参数输入表!$H$264)*参数输入表!$H$264 -> 0 | J43: =参数输入表!H238/(1+参数输入表!$H$264)*参数输入表!$H$264 -> 0 | K43: =参数输入表!H239/(1+参数输入表!$H$264)*参数输入表!$H$264 -> 0 | L43: =参数输入表!H240/(1+参数输入表!$H$264)*参数输入表!$H$264 -> 0 | M43: =参数输入表!H241/(1+参数输入表!$H$264)*参数输入表!$H$264 -> 0 | N43: =参数输入表!H242/(1+参数输入表!$H$264)*参数输入表!$H$264 -> 0 | O43: =参数输入表!H243/(1+参数输入表!$H$264)*参数输入表!$H$264 -> 0 | P43: =参数输入表!H244/(1+参数输入表!$H$264)*参数输入表!$H$264 -> 0 | Q43: =参数输入表!H245/(1+参数输入表!$H$264)*参数输入表!$H$264 -> 0 | R43: =参数输入表!H246/(1+参数输入表!$H$264)*参数输入表!$H$264 -> 55.221239 | S43: =参数输入表!H247/(1+参数输入表!$H$264)*参数输入表!$H$264 -> 0 | T43: =参数输入表!H248/(1+参数输入表!$H$264)*参数输入表!$H$264 -> 0 | U43: =参数输入表!H249/(1+参数输入表!$H$264)*参数输入表!$H$264 -> 0 | V43: =参数输入表!H250/(1+参数输入表!$H$264)*参数输入表!$H$264 -> 0 | W43: =参数输入表!H251/(1+参数输入表!$H$264)*参数输入表!$H$264 -> 0 | X43: =参数输入表!H252/(1+参数输入表!$H$264)*参数输入表!$H$264 -> 0 | Y43: =参数输入表!H253/(1+参数输入表!$H$264)*参数输入表!$H$264 -> 0 | Z43: =参数输入表!H254/(1+参数输入表!$H$264)*参数输入表!$H$264 -> 0 | AA43: =参数输入表!H255/(1+参数输入表!$H$264)*参数输入表!$H$264 -> 0 | AB43: =参数输入表!H256/(1+参数输入表!$H$264)*参数输入表!$H$264 -> 0 | AC43: =参数输入表!H257/(1+参数输入表!$H$264)*参数输入表!$H$264 -> 0 | AD43: =参数输入表!H258/(1+参数输入表!$H$264)*参数输入表!$H$264 -> 0 | AE43: =参数输入表!H259/(1+参数输入表!$H$264)*参数输入表!$H$264 -> 0 | AF43: =参数输入表!H260/(1+参数输入表!$H$264)*参数输入表!$H$264 -> 0
B44: 4 | C44: 销项税-进项税 | D44: =SUM(F44:AF44) -> 6959.2285 | E44: 万元 | F44: =F23-F26 -> -2571.0688 | G44: =G23-G26 -> 0 | H44: =H23-H26 -> 389.34187 | I44: =I23-I26 -> 387.58983 | J44: =J23-J26 -> 385.84568 | K44: =K23-K26 -> 384.10938 | L44: =L23-L26 -> 382.38088 | M44: =M23-M26 -> 399.43608 | ... AF44: =AF23-AF26 -> 366.6328
B45: 5 | C45: 期末可抵扣进项税余额 | E45: 万元 | F45: =IF(F44<0,-F44,0) -> 2571.0688 | G45: =IF(F45-G44>0,F45-G44,0) -> 2571.0688 | H45: =IF(G45-H44>0,G45-H44,0) -> 2181.727 | I45: =IF(H45-I44>0,H45-I44,0) -> 1794.1371 | J45: =IF(I45-J44>0,I45-J44,0) -> 1408.2914 | K45: =IF(J45-K44>0,J45-K44,0) -> 1024.1821 | L45: =IF(K45-L44>0,K45-L44,0) -> 641.80118 | M45: =IF(L45-M44>0,L45-M44,0) -> 242.3651 | N45: =IF(M45-N44>0,M45-N44,0) -> 0 | ... AF45: =IF(AE45-AF44>0,AE45-AF44,0) -> 0
B46: 6 | C46: 增值税附加税 | D46: =SUM(F46:AF46) -> 835.10742 | E46: 万元 | H46: =SUM(H47:H49) -> 0 | I46: =SUM(I47:I49) -> 0 | J46: =SUM(J47:J49) -> 0 | K46: =SUM(K47:K49) -> 0 | L46: =SUM(L47:L49) -> 0 | M46: =SUM(M47:M49) -> 0 | N46: =SUM(N47:N49) -> 18.632823 | O46: =SUM(O47:O49) -> 47.50191 | ... AF46: =SUM(AF47:AF49) -> 43.995936
B47: 6.1 | C47: 城市维护建设税 | D47: =SUM(F47:AF47) -> 487.146 | E47: 万元 | H47: =H22*参数输入表!$H$338 -> 0 | I47: =I22*参数输入表!$H$338 -> 0 | J47: =J22*参数输入表!$H$338 -> 0 | K47: =K22*参数输入表!$H$338 -> 0 | L47: =L22*参数输入表!$H$338 -> 0 | M47: =M22*参数输入表!$H$338 -> 0 | N47: =N22*参数输入表!$H$338 -> 10.869147 | O47: =O22*参数输入表!$H$338 -> 27.709447 | ... AF47: =AF22*参数输入表!$H$338 -> 25.664296
B48: 6.2 | C48: 教育附加 | D48: =SUM(F48:AF48) -> 208.77686 | E48: 万元 | H48: =H22*参数输入表!$H$342 -> 0 | I48: =I22*参数输入表!$H$342 -> 0 | J48: =J22*参数输入表!$H$342 -> 0 | K48: =K22*参数输入表!$H$342 -> 0 | L48: =L22*参数输入表!$H$342 -> 0 | M48: =M22*参数输入表!$H$342 -> 0 | N48: =N22*参数输入表!$H$342 -> 4.6582057 | O48: =O22*参数输入表!$H$342 -> 11.875477 | ... AF48: =AF22*参数输入表!$H$342 -> 10.998984
B49: 6.3 | C49: 地方教育附加 | D49: =SUM(F49:AF49) -> 139.18457 | E49: 万元 | H49: =H22*参数输入表!$H$343 -> 0 | I49: =I22*参数输入表!$H$343 -> 0 | J49: =J22*参数输入表!$H$343 -> 0 | K49: =K22*参数输入表!$H$343 -> 0 | L49: =L22*参数输入表!$H$343 -> 0 | M49: =M22*参数输入表!$H$343 -> 0 | N49: =N22*参数输入表!$H$343 -> 3.1054705 | O49: =O22*参数输入表!$H$343 -> 7.9169849 | ... AF49: =AF22*参数输入表!$H$343 -> 7.332656
B50: 7 | C50: 城镇土地使用税 | D50: =SUM(F50:AF50) -> 0 | E50: 万元 | H50: =参数输入表!$H$345*参数输入表!$H$346/10000 -> 0 | I50: =参数输入表!$H$345*参数输入表!$H$346/10000 -> 0 | J50: =参数输入表!$H$345*参数输入表!$H$346/10000 -> 0 | K50: =参数输入表!$H$345*参数输入表!$H$346/10000 -> 0 | L50: =参数输入表!$H$345*参数输入表!$H$346/10000 -> 0 | M50: =参数输入表!$H$345*参数输入表!$H$346/10000 -> 0 | N50: =参数输入表!$H$345*参数输入表!$H$346/10000 -> 0 | O50: =参数输入表!$H$345*参数输入表!$H$346/10000 -> 0 | ... AF50: =参数输入表!$H$345*参数输入表!$H$346/10000 -> 0
C53: 增值税即征即退为参数输入表，税金板块可选条件参数，若选择为常规，即没有增值税即征即退优惠，退税比例为0%；若选择即征即退，同步输入即征即退的比例，第n年增值税即征即退金额=第n年当期实缴增值税*退税比例
C54: 标黄部分为相对固定模块，适用于所有项目
C55: 标蓝部分为计算中间过程，可不展示
B56: 流动资金估算表
B57: 序号 | C57: 项目 | D57: 合计 | E57: 单位 | F57: 建设期 | H57: 运营期
F58: 1 | G58: 2 | H58: 1 | I58: 2 | J58: 3 | K58: 4 | L58: 5 | M58: 6 | N58: 7 | O58: 8 | P58: 9 | Q58: 10 | R58: 11 | S58: 12 | T58: 13 | U58: 14 | V58: 15 | W58: 16 | X58: 17 | Y58: 18 | Z58: 19 | AA58: 20 | AB58: 21 | AC58: 22 | AD58: 23 | AE58: 24 | AF58: 25
B59: 一 | C59: 流动资产 | E59: 万元 | F59: =SUM(F60:F63) -> 0 | G59: =SUM(G60:G63) -> 0 | H59: =SUM(H60:H63) -> 0 | I59: =SUM(I60:I63) -> 0 | J59: =SUM(J60:J63) -> 0 | K59: =SUM(K60:K63) -> 0 | L59: =SUM(L60:L63) -> 0 | M59: =SUM(M60:M63) -> 0 | ... AF59: =SUM(AF60:AF63) -> 0
B60: 1.1 | C60: 应收账款 | E60: 万元 | H60: =('表4-收入税金表'!H6+'表4-收入税金表'!H24)*(1-100%)+('表4-收入税金表'!H16+'表4-收入税金表'!H25)*(1-100%) -> 0 | I60: =('表4-收入税金表'!I6+'表4-收入税金表'!I24)*(1-100%)+('表4-收入税金表'!I16+'表4-收入税金表'!I25)*(1-100%) -> 0 | J60: =('表4-收入税金表'!J6+'表4-收入税金表'!J24)*(1-100%)+('表4-收入税金表'!J16+'表4-收入税金表'!J25)*(1-100%) -> 0 | K60: =('表4-收入税金表'!K6+'表4-收入税金表'!K24)*(1-100%)+('表4-收入税金表'!K16+'表4-收入税金表'!K25)*(1-100%) -> 0 | L60: =('表4-收入税金表'!L6+'表4-收入税金表'!L24)*(1-100%)+('表4-收入税金表'!L16+'表4-收入税金表'!L25)*(1-100%) -> 0 | M60: =('表4-收入税金表'!M6+'表4-收入税金表'!M24)*(1-100%)+('表4-收入税金表'!M16+'表4-收入税金表'!M25)*(1-100%) -> 0 | N60: =('表4-收入税金表'!N6+'表4-收入税金表'!N24)*(1-100%)+('表4-收入税金表'!N16+'表4-收入税金表'!N25)*(1-100%) -> 0 | O60: =('表4-收入税金表'!O6+'表4-收入税金表'!O24)*(1-100%)+('表4-收入税金表'!O16+'表4-收入税金表'!O25)*(1-100%) -> 0 | ... AF60: =('表4-收入税金表'!AF6+'表4-收入税金表'!AF24)*(1-100%)+('表4-收入税金表'!AF16+'表4-收入税金表'!AF25)*(1-100%) -> 0
B61: 1.2 | C61: 存货 | E61: 万元
B62: 1.3 | C62: 现金 | E62: 万元
B63: 1.4 | C63: 预付账款 | E63: 万元
B64: 二 | C64: 流动负债 | E64: 万元 | F64: =SUM(F65:F66) -> 0 | G64: =SUM(G65:G66) -> 0 | H64: =SUM(H65:H66) -> 0 | I64: =SUM(I65:I66) -> 0 | J64: =SUM(J65:J66) -> 0 | K64: =SUM(K65:K66) -> 0 | L64: =SUM(L65:L66) -> 0 | M64: =SUM(M65:M66) -> 0 | ... AF64: =SUM(AF65:AF66) -> 0
B65: 2.1 | C65: 应付账款 | E65: 万元
B66: 2.2 | C66: 预收账款 | E66: 万元
B67: 三 | C67: 流动资金 | E67: 万元 | F67: =F59-F64 -> 0 | G67: =G59-G64 -> 0 | H67: =H59-H64 -> 0 | I67: =I59-I64 -> 0 | J67: =J59-J64 -> 0 | K67: =K59-K64 -> 0 | L67: =L59-L64 -> 0 | M67: =M59-M64 -> 0 | ... AF67: =AF59-AF64 -> 0
B68: 四 | C68: 流动资金当期增加额 | E68: 万元 | F68: =F67 -> 0 | G68: =G67-F67 -> 0 | H68: =H67-G67 -> 0 | I68: =I67-H67 -> 0 | J68: =J67-I67 -> 0 | K68: =K67-J67 -> 0 | L68: =L67-K67 -> 0 | M68: =M67-L67 -> 0 | N68: =N67-M67 -> 0 | ... AF68: =AF67-AE67 -> 0
C70: 流动资金估算表用于计算某一项收入当年利润表确认收入与现金流量表中实际到账收入有差额时，差额计入应收账款中。
C71: 关联至参数表中应发收入与实发收入不完全相等的收入项，本模型中为“发电补贴”

Sheet 表5-利润表-资本金
B2: 利润表-资本金
B3: 序号 | C3: 项目 | D3: 合计 | E3: 单位 | F3: 建设期 | H3: 运营期
F4: 1 | G4: 2 | H4: 1 | I4: 2 | J4: 3 | K4: 4 | L4: 5 | M4: 6 | N4: 7 | O4: 8 | P4: 9 | Q4: 10 | R4: 11 | S4: 12 | T4: 13 | U4: 14 | V4: 15 | W4: 16 | X4: 17 | Y4: 18 | Z4: 19 | AA4: 20 | AB4: 21 | AC4: 22 | AD4: 23 | AE4: 24 | AF4: 25
B5: 1 | C5: 营业总收入 | D5: =SUM(F5:AF5) -> 73734.758 | E5: 万元 | H5: =H6+H7 -> 2994.9375 | I5: =I6+I7 -> 2981.4603 | J5: =J6+J7 -> 2968.0437 | K5: =K6+K7 -> 2954.6875 | L5: =L6+L7 -> 2941.3914 | M5: =M6+M7 -> 3072.5853 | N5: =N6+N7 -> 3058.7586 | O5: =O6+O7 -> 3044.9942 | ... AF5: =AF6+AF7 -> 2820.2523
B6: 1.1 | C6: 营业收入 | D6: =SUM(F6:AF6) -> 73734.758 | E6: 万元 | H6: ='表4-收入税金表'!H5 -> 2994.9375 | I6: ='表4-收入税金表'!I5 -> 2981.4603 | J6: ='表4-收入税金表'!J5 -> 2968.0437 | K6: ='表4-收入税金表'!K5 -> 2954.6875 | L6: ='表4-收入税金表'!L5 -> 2941.3914 | M6: ='表4-收入税金表'!M5 -> 3072.5853 | N6: ='表4-收入税金表'!N5 -> 3058.7586 | O6: ='表4-收入税金表'!O5 -> 3044.9942 | ... AF6: ='表4-收入税金表'!AF5 -> 2820.2523
B7: 1.2 | C7: 其他收入 | D7: =SUM(F7:AF7) -> 0 | E7: 万元 | H7: ='表4-收入税金表'!H16 -> 0 | I7: ='表4-收入税金表'!I16 -> 0 | J7: ='表4-收入税金表'!J16 -> 0 | K7: ='表4-收入税金表'!K16 -> 0 | L7: ='表4-收入税金表'!L16 -> 0 | M7: ='表4-收入税金表'!M16 -> 0 | N7: ='表4-收入税金表'!N16 -> 0 | O7: ='表4-收入税金表'!O16 -> 0 | ... AF7: ='表4-收入税金表'!AF16 -> 0
B8: 2 | C8: 营业总成本 | D8: =SUM(F8:AF8) -> 46821.458 | E8: 万元 | H8: ='表3-成本费用表'!H5 -> 2517.4608 | I8: ='表3-成本费用表'!I49-'表3-成本费用表'!I53+'表3-成本费用表'!I15+'表3-成本费用表'!I16+'表3-成本费用表'!I19+'表3-成本费用表'!I20+'表2-折旧摊销表'!I39 -> 2465.4612 | J8: ='表3-成本费用表'!J49-'表3-成本费用表'!J53+'表3-成本费用表'!J15+'表3-成本费用表'!J16+'表3-成本费用表'!J19+'表3-成本费用表'!J20+'表2-折旧摊销表'!J39 -> 2413.4617 | K8: ='表3-成本费用表'!K49-'表3-成本费用表'!K53+'表3-成本费用表'!K15+'表3-成本费用表'!K16+'表3-成本费用表'!K19+'表3-成本费用表'!K20+'表2-折旧摊销表'!K39 -> 2361.4621 | L8: ='表3-成本费用表'!L49-'表3-成本费用表'!L53+'表3-成本费用表'!L15+'表3-成本费用表'!L16+'表3-成本费用表'!L19+'表3-成本费用表'!L20+'表2-折旧摊销表'!L39 -> 2309.4626 | M8: ='表3-成本费用表'!M49-'表3-成本费用表'!M53+'表3-成本费用表'!M15+'表3-成本费用表'!M16+'表3-成本费用表'!M19+'表3-成本费用表'!M20+'表2-折旧摊销表'!M39 -> 2308.7209 | N8: ='表3-成本费用表'!N49-'表3-成本费用表'!N53+'表3-成本费用表'!N15+'表3-成本费用表'!N16+'表3-成本费用表'!N19+'表3-成本费用表'!N20+'表2-折旧摊销表'!N39 -> 2256.7213 | O8: ='表3-成本费用表'!O49-'表3-成本费用表'!O53+'表3-成本费用表'!O15+'表3-成本费用表'!O16+'表3-成本费用表'!O19+'表3-成本费用表'!O20+'表2-折旧摊销表'!O39 -> 2204.7218 | P8: ='表3-成本费用表'!P49-'表3-成本费用表'!P53+'表3-成本费用表'!P15+'表3-成本费用表'!P16+'表3-成本费用表'!P19+'表3-成本费用表'!P20+'表2-折旧摊销表'!P39 -> 2152.7222 | ... AF8: ='表3-成本费用表'!AF49-'表3-成本费用表'!AF53+'表3-成本费用表'!AF15+'表3-成本费用表'!AF16+'表3-成本费用表'!AF19+'表3-成本费用表'!AF20+'表2-折旧摊销表'!AF39 -> 778.17739
B9: 3 | C9: 营业税金及附加 | D9: =SUM(F9:AF9) -> 835.10742 | E9: 万元 | H9: ='表4-收入税金表'!H46+'表4-收入税金表'!H50 -> 0 | I9: ='表4-收入税金表'!I46+'表4-收入税金表'!I50 -> 0 | J9: ='表4-收入税金表'!J46+'表4-收入税金表'!J50 -> 0 | K9: ='表4-收入税金表'!K46+'表4-收入税金表'!K50 -> 0 | L9: ='表4-收入税金表'!L46+'表4-收入税金表'!L50 -> 0 | M9: ='表4-收入税金表'!M46+'表4-收入税金表'!M50 -> 0 | N9: ='表4-收入税金表'!N46+'表4-收入税金表'!N50 -> 18.632823 | O9: ='表4-收入税金表'!O46+'表4-收入税金表'!O50 -> 47.50191 | ... AF9: ='表4-收入税金表'!AF46+'表4-收入税金表'!AF50 -> 43.995936
B10: 4 | C10: 营业外收入 | D10: =SUM(F10:AF10) -> 0 | E10: 万元 | H10: =SUM(H11:H12) -> 0 | I10: =SUM(I11:I12) -> 0 | J10: =SUM(J11:J12) -> 0 | K10: =SUM(K11:K12) -> 0 | L10: =SUM(L11:L12) -> 0 | M10: =SUM(M11:M12) -> 0 | N10: =SUM(N11:N12) -> 0 | O10: =SUM(O11:O12) -> 0 | ... AF10: =SUM(AF11:AF12) -> 0
B11: 4.1 | C11: 政府一次性运营补贴收入—递延收益 | D11: =SUM(F11:AF11) -> 0 | E11: 万元 | H11: =参数输入表!H305 -> 0 | I11: =参数输入表!H306 -> 0 | J11: =参数输入表!H307 -> 0 | K11: =参数输入表!H308 -> 0 | L11: =参数输入表!H309 -> 0 | M11: =参数输入表!H310 -> 0 | N11: =参数输入表!H311 -> 0 | O11: =参数输入表!H312 -> 0 | P11: =参数输入表!H313 -> 0 | Q11: =参数输入表!H314 -> 0 | R11: =参数输入表!H315 -> 0 | S11: =参数输入表!H316 -> 0 | T11: =参数输入表!H317 -> 0 | U11: =参数输入表!H318 -> 0 | V11: =参数输入表!H319 -> 0 | W11: =参数输入表!H320 -> 0 | X11: =参数输入表!H321 -> 0 | Y11: =参数输入表!H322 -> 0 | Z11: =参数输入表!H323 -> 0 | AA11: =参数输入表!H324 -> 0 | AB11: =参数输入表!H325 -> 0 | AC11: =参数输入表!H326 -> 0 | AD11: =参数输入表!H327 -> 0 | AE11: =参数输入表!H328 -> 0 | AF11: =参数输入表!H329 -> 0
B12: 4.2 | C12: 增值税即征即退收入 | D12: =SUM(F12:AF12) -> 0 | E12: 万元 | H12: ='表4-收入税金表'!H19 -> 0 | I12: ='表4-收入税金表'!I19 -> 0 | J12: ='表4-收入税金表'!J19 -> 0 | K12: ='表4-收入税金表'!K19 -> 0 | L12: ='表4-收入税金表'!L19 -> 0 | M12: ='表4-收入税金表'!M19 -> 0 | N12: ='表4-收入税金表'!N19 -> 0 | O12: ='表4-收入税金表'!O19 -> 0 | ... AF12: ='表4-收入税金表'!AF19 -> 0
B13: 5 | C13: 营业外支出 | D13: =SUM(F13:AF13) -> 0 | E13: 万元 | H13: ='表3-成本费用表'!H24 -> 0 | I13: ='表3-成本费用表'!I24 -> 0 | J13: ='表3-成本费用表'!J24 -> 0 | K13: ='表3-成本费用表'!K24 -> 0 | L13: ='表3-成本费用表'!L24 -> 0 | M13: ='表3-成本费用表'!M24 -> 0 | N13: ='表3-成本费用表'!N24 -> 0 | O13: ='表3-成本费用表'!O24 -> 0 | ... AF13: ='表3-成本费用表'!AF24 -> 0
B14: 6 | C14: 利润总额（1+4-2-3-5） | D14: =SUM(F14:AF14) -> 26078.193 | E14: 万元 | H14: =H5+H10-H8-H9-H13 -> 477.47672 | I14: =I5+I10-I8-I9-I13 -> 515.99905 | J14: =J5+J10-J8-J9-J13 -> 554.58204 | K14: =K5+K10-K8-K9-K13 -> 593.22539 | L14: =L5+L10-L8-L9-L13 -> 631.92885 | M14: =M5+M10-M8-M9-M13 -> 763.86439 | N14: =N5+N10-N8-N9-N13 -> 783.40449 | O14: =O5+O10-O8-O9-O13 -> 792.77054 | ... AF14: =AF5+AF10-AF8-AF9-AF13 -> 1998.079
B15: 7 | C15: 弥补以前年度亏损 | D15: =SUM(F15:AF15) -> 0 | E15: 万元 | H15: =SUM(H16:H20) -> 0 | I15: =SUM(I16:I20) -> 0 | J15: =SUM(J16:J20) -> 0 | K15: =SUM(K16:K20) -> 0 | L15: =SUM(L16:L20) -> 0 | M15: =SUM(M16:M20) -> 0 | N15: =SUM(N16:N20) -> 0 | O15: =SUM(O16:O20) -> 0 | ... AF15: =SUM(AF16:AF20) -> 0
C16: 弥补前序第一年亏损 | E16: 万元 | I16: =IF(H14>0,0,IF(I14<0,0,MIN(I14-SUM(I17:I20),-H14))) -> 0 | J16: =IF(I14>0,0,IF(J14<0,0,MIN(J14-SUM(J17:J20),-I14))) -> 0 | K16: =IF(J14>0,0,IF(K14<0,0,MIN(K14-SUM(K17:K20),-J14))) -> 0 | L16: =IF(K14>0,0,IF(L14<0,0,MIN(L14-SUM(L17:L20),-K14))) -> 0 | M16: =IF(L14>0,0,IF(M14<0,0,MIN(M14-SUM(M17:M20),-L14))) -> 0 | N16: =IF(M14>0,0,IF(N14<0,0,MIN(N14-SUM(N17:N20),-M14))) -> 0 | O16: =IF(N14>0,0,IF(O14<0,0,MIN(O14-SUM(O17:O20),-N14))) -> 0 | P16: =IF(O14>0,0,IF(P14<0,0,MIN(P14-SUM(P17:P20),-O14))) -> 0 | ... AF16: =IF(AE14>0,0,IF(AF14<0,0,MIN(AF14-SUM(AF17:AF20),-AE14))) -> 0
C17: 弥补前序第二年亏损 | E17: 万元 | J17: =IF(H14>0,0,IF(J14<0,0,MIN(J14-SUM(J18:J20),-H14-I16))) -> 0 | K17: =IF(I14>0,0,IF(K14<0,0,MIN(K14-SUM(K18:K20),-I14-J16))) -> 0 | L17: =IF(J14>0,0,IF(L14<0,0,MIN(L14-SUM(L18:L20),-J14-K16))) -> 0 | M17: =IF(K14>0,0,IF(M14<0,0,MIN(M14-SUM(M18:M20),-K14-L16))) -> 0 | N17: =IF(L14>0,0,IF(N14<0,0,MIN(N14-SUM(N18:N20),-L14-M16))) -> 0 | O17: =IF(M14>0,0,IF(O14<0,0,MIN(O14-SUM(O18:O20),-M14-N16))) -> 0 | P17: =IF(N14>0,0,IF(P14<0,0,MIN(P14-SUM(P18:P20),-N14-O16))) -> 0 | Q17: =IF(O14>0,0,IF(Q14<0,0,MIN(Q14-SUM(Q18:Q20),-O14-P16))) -> 0 | ... AF17: =IF(AD14>0,0,IF(AF14<0,0,MIN(AF14-SUM(AF18:AF20),-AD14-AE16))) -> 0
C18: 弥补前序第三年亏损 | E18: 万元 | K18: =IF(H14>0,0,IF(K14<0,0,MIN(K14-SUM(K19:K20),-H14-I16-J17))) -> 0 | L18: =IF(I14>0,0,IF(L14<0,0,MIN(L14-SUM(L19:L20),-I14-J16-K17))) -> 0 | M18: =IF(J14>0,0,IF(M14<0,0,MIN(M14-SUM(M19:M20),-J14-K16-L17))) -> 0 | N18: =IF(K14>0,0,IF(N14<0,0,MIN(N14-SUM(N19:N20),-K14-L16-M17))) -> 0 | O18: =IF(L14>0,0,IF(O14<0,0,MIN(O14-SUM(O19:O20),-L14-M16-N17))) -> 0 | P18: =IF(M14>0,0,IF(P14<0,0,MIN(P14-SUM(P19:P20),-M14-N16-O17))) -> 0 | Q18: =IF(N14>0,0,IF(Q14<0,0,MIN(Q14-SUM(Q19:Q20),-N14-O16-P17))) -> 0 | R18: =IF(O14>0,0,IF(R14<0,0,MIN(R14-SUM(R19:R20),-O14-P16-Q17))) -> 0 | ... AF18: =IF(AC14>0,0,IF(AF14<0,0,MIN(AF14-SUM(AF19:AF20),-AC14-AD16-AE17))) -> 0
C19: 弥补前序第四年亏损 | E19: 万元 | L19: =IF(H14>0,0,IF(L14<0,0,MIN(L14-L20,-H14-I16-J17-K18))) -> 0 | M19: =IF(I14>0,0,IF(M14<0,0,MIN(M14-M20,-I14-J16-K17-L18))) -> 0 | N19: =IF(J14>0,0,IF(N14<0,0,MIN(N14-N20,-J14-K16-L17-M18))) -> 0 | O19: =IF(K14>0,0,IF(O14<0,0,MIN(O14-O20,-K14-L16-M17-N18))) -> 0 | P19: =IF(L14>0,0,IF(P14<0,0,MIN(P14-P20,-L14-M16-N17-O18))) -> 0 | Q19: =IF(M14>0,0,IF(Q14<0,0,MIN(Q14-Q20,-M14-N16-O17-P18))) -> 0 | R19: =IF(N14>0,0,IF(R14<0,0,MIN(R14-R20,-N14-O16-P17-Q18))) -> 0 | S19: =IF(O14>0,0,IF(S14<0,0,MIN(S14-S20,-O14-P16-Q17-R18))) -> 0 | ... AF19: =IF(AB14>0,0,IF(AF14<0,0,MIN(AF14-AF20,-AB14-AC16-AD17-AE18))) -> 0
C20: 弥补前序第五年亏损 | E20: 万元 | M20: =IF(H14>0,0,IF(M14<0,0,MIN(M14,-H14-I16-J17-K18-L19))) -> 0 | N20: =IF(I14>0,0,IF(N14<0,0,MIN(N14,-I14-J16-K17-L18-M19))) -> 0 | O20: =IF(J14>0,0,IF(O14<0,0,MIN(O14,-J14-K16-L17-M18-N19))) -> 0 | P20: =IF(K14>0,0,IF(P14<0,0,MIN(P14,-K14-L16-M17-N18-O19))) -> 0 | Q20: =IF(L14>0,0,IF(Q14<0,0,MIN(Q14,-L14-M16-N17-O18-P19))) -> 0 | R20: =IF(M14>0,0,IF(R14<0,0,MIN(R14,-M14-N16-O17-P18-Q19))) -> 0 | S20: =IF(N14>0,0,IF(S14<0,0,MIN(S14,-N14-O16-P17-Q18-R19))) -> 0 | T20: =IF(O14>0,0,IF(T14<0,0,MIN(T14,-O14-P16-Q17-R18-S19))) -> 0 | ... AF20: =IF(AA14>0,0,IF(AF14<0,0,MIN(AF14,-AA14-AB16-AC17-AD18-AE19))) -> 0
B21: 8 | C21: 应税所得额 | D21: =SUM(F21:AF21) -> 26078.193 | E21: 万元 | H21: =IF(H14-H15>0,H14-H15,0) -> 477.47672 | I21: =IF(I14-I15>0,I14-I15,0) -> 515.99905 | J21: =IF(J14-J15>0,J14-J15,0) -> 554.58204 | K21: =IF(K14-K15>0,K14-K15,0) -> 593.22539 | L21: =IF(L14-L15>0,L14-L15,0) -> 631.92885 | M21: =IF(M14-M15>0,M14-M15,0) -> 763.86439 | N21: =IF(N14-N15>0,N14-N15,0) -> 783.40449 | O21: =IF(O14-O15>0,O14-O15,0) -> 792.77054 | ... AF21: =IF(AF14-AF15>0,AF14-AF15,0) -> 1998.079
B22: 9 | C22: 企业所得税 | D22: =SUM(F22:AF22) -> 5883.9064 | E22: 万元 | H22: =IF(参数输入表!$H$333="三免三减半",0,'表5-利润表-资本金'!H21*参数输入表!$H$334) -> 0 | I22: =IF(参数输入表!$H$333="三免三减半",0,'表5-利润表-资本金'!I21*参数输入表!$H$334) -> 0 | J22: =IF(参数输入表!$H$333="三免三减半",0,'表5-利润表-资本金'!J21*参数输入表!$H$334) -> 0 | K22: =IF(参数输入表!$H$333="三免三减半",'表5-利润表-资本金'!K21*参数输入表!$H$334/2,'表5-利润表-资本金'!K21*参数输入表!$H$334) -> 74.153174 | L22: =IF(参数输入表!$H$333="三免三减半",'表5-利润表-资本金'!L21*参数输入表!$H$334/2,'表5-利润表-资本金'!L21*参数输入表!$H$334) -> 78.991107 | M22: =IF(参数输入表!$H$333="三免三减半",'表5-利润表-资本金'!M21*参数输入表!$H$334/2,'表5-利润表-资本金'!M21*参数输入表!$H$334) -> 95.483049 | N22: =N21*参数输入表!$H$334 -> 195.85112 | O22: =O21*参数输入表!$H$334 -> 198.19264 | P22: =P21*参数输入表!$H$334 -> 207.82034 | Q22: =Q21*参数输入表!$H$334 -> 217.46323 | R22: =R21*参数输入表!$H$334 -> 205.8749 | S22: =S21*参数输入表!$H$334 -> 213.89129 | T22: =T21*参数输入表!$H$334 -> 223.57929 | U22: =U21*参数输入表!$H$334 -> 233.28219 | ... AF22: =AF21*参数输入表!$H$334 -> 499.51975
B23: 10 | C23: 净利润（6-9） | D23: =SUM(F23:AF23) -> 20194.286 | E23: 万元 | H23: =H14-H22 -> 477.47672 | I23: =I14-I22 -> 515.99905 | J23: =J14-J22 -> 554.58204 | K23: =K14-K22 -> 519.07222 | L23: =L14-L22 -> 552.93775 | M23: =M14-M22 -> 668.38134 | N23: =N14-N22 -> 587.55337 | O23: =O14-O22 -> 594.57791 | ... AF23: =AF14-AF22 -> 1498.5592
B24: 11 | C24: 期初未分配的利润 | D24: =SUM(F24:AF24) -> 63287.405 | E24: 万元 | F24: 0 | G24: 0 | H24: =G32 -> 0 | I24: =H32 -> 386.75614 | J24: =I32 -> 731.23171 | K24: =J32 -> 1041.5091 | L24: =K32 -> 1264.0709 | M24: =L32 -> 1471.777 | N24: =M32 -> 1733.5283 | O24: =N32 -> 1880.0761 | ... AF24: =AE32 -> 6663.7932
B25: 12 | C25: 可供分配的利润（10+11） | D25: =SUM(F25:AF25) -> 83481.691 | E25: 万元 | H25: =H23+H24 -> 477.47672 | I25: =I23+I24 -> 902.7552 | J25: =J23+J24 -> 1285.8137 | K25: =K23+K24 -> 1560.5814 | L25: =L23+L24 -> 1817.0086 | M25: =M23+M24 -> 2140.1583 | N25: =N23+N24 -> 2321.0816 | O25: =O23+O24 -> 2474.654 | ... AF25: =AF23+AF24 -> 8162.3524
B26: 13 | C26: 提取法定盈余公积金 | D26: =SUM(F26:AF26) -> 5000 | E26: 万元 | H26: =IF(H25<0,0,H25*参数输入表!$H$134) -> 47.747672 | I26: =IF(H28>=参数输入表!$H$133,0,IF(I25<0,0,IF(I25*参数输入表!$H$134>=I27,I27,I25*参数输入表!$H$134))) -> 90.27552 | J26: =IF(I28>=参数输入表!$H$133,0,IF(J25<0,0,IF(J25*参数输入表!$H$134>=J27,J27,J25*参数输入表!$H$134))) -> 128.58137 | K26: =IF(J28>=参数输入表!$H$133,0,IF(K25<0,0,IF(K25*参数输入表!$H$134>=K27,K27,K25*参数输入表!$H$134))) -> 156.05814 | L26: =IF(K28>=参数输入表!$H$133,0,IF(L25<0,0,IF(L25*参数输入表!$H$134>=L27,L27,L25*参数输入表!$H$134))) -> 181.70086 | M26: =IF(L28>=参数输入表!$H$133,0,IF(M25<0,0,IF(M25*参数输入表!$H$134>=M27,M27,M25*参数输入表!$H$134))) -> 214.01583 | N26: =IF(M28>=参数输入表!$H$133,0,IF(N25<0,0,IF(N25*参数输入表!$H$134>=N27,N27,N25*参数输入表!$H$134))) -> 232.10816 | O26: =IF(N28>=参数输入表!$H$133,0,IF(O25<0,0,IF(O25*参数输入表!$H$134>=O27,O27,O25*参数输入表!$H$134))) -> 247.4654 | P26: =IF(O28>=参数输入表!$H$133,0,IF(P25<0,0,IF(P25*参数输入表!$H$134>=P27,P27,P25*参数输入表!$H$134))) -> 262.79308 | ... AF26: =IF(AE28>=参数输入表!$H$133,0,IF(AF25<0,0,IF(AF25*参数输入表!$H$134>=AF27,AF27,AF25*参数输入表!$H$134))) -> 0
C27: 期初法定盈余公积金上限缺口 | E27: 万元 | H27: =参数输入表!$H$133 -> 5000 | I27: =参数输入表!$H$133-H28 -> 4952.2523 | J27: =参数输入表!$H$133-I28 -> 4861.9768 | K27: =参数输入表!$H$133-J28 -> 4733.3954 | L27: =参数输入表!$H$133-K28 -> 4577.3373 | M27: =参数输入表!$H$133-L28 -> 4395.6364 | N27: =参数输入表!$H$133-M28 -> 4181.6206 | O27: =参数输入表!$H$133-N28 -> 3949.5124 | P27: =参数输入表!$H$133-O28 -> 3702.047 | ... AF27: =参数输入表!$H$133-AE28 -> 0
C28: 期末法定盈余公积金累计 | E28: 万元 | H28: =H26 -> 47.747672 | I28: =I26+H28 -> 138.02319 | J28: =J26+I28 -> 266.60457 | K28: =K26+J28 -> 422.6627 | L28: =L26+K28 -> 604.36357 | M28: =M26+L28 -> 818.3794 | N28: =N26+M28 -> 1050.4876 | O28: =O26+N28 -> 1297.953 | P28: =P26+O28 -> 1560.746 | ... AF28: =AF26+AE28 -> 5000
B29: 14 | C29: 可供投资者分配的利润（12-13） | D29: =SUM(F29:AF29) -> 78481.691 | E29: 万元 | H29: =H25-H26 -> 429.72905 | I29: =I25-I26 -> 812.47968 | J29: =J25-J26 -> 1157.2324 | K29: =K25-K26 -> 1404.5232 | L29: =L25-L26 -> 1635.3078 | M29: =M25-M26 -> 1926.1425 | N29: =N25-N26 -> 2088.9735 | O29: =O25-O26 -> 2227.1886 | ... AF29: =AF25-AF26 -> 8162.3524
B30: 15 | C30: 提取任意盈余公积金 | D30: =SUM(F30:AF30) -> 0 | E30: 万元 | H30: =H29*参数输入表!$H$135 -> 0 | I30: =I29*参数输入表!$H$135 -> 0 | J30: =J29*参数输入表!$H$135 -> 0 | K30: =K29*参数输入表!$H$135 -> 0 | L30: =L29*参数输入表!$H$135 -> 0 | M30: =M29*参数输入表!$H$135 -> 0 | N30: =N29*参数输入表!$H$135 -> 0 | O30: =O29*参数输入表!$H$135 -> 0 | ... AF30: =AF29*参数输入表!$H$135 -> 0
B31: 16 | C31: 各投资方利润分配 | D31: =SUM(F31:AF31) -> 7848.1691 | E31: 万元 | H31: =IF(H29<0,0,H29*0.1) -> 42.972905 | I31: =IF(I29<0,0,I29*0.1) -> 81.247968 | J31: =IF(J29<0,0,J29*0.1) -> 115.72324 | K31: =IF(K29<0,0,K29*0.1) -> 140.45232 | L31: =IF(L29<0,0,L29*0.1) -> 163.53078 | M31: =IF(M29<0,0,M29*0.1) -> 192.61425 | N31: =IF(N29<0,0,N29*0.1) -> 208.89735 | O31: =IF(O29<0,0,O29*0.1) -> 222.71886 | ... AF31: =IF(AF29<0,0,AF29*0.1) -> 816.23524
B32: 17 | C32: 未分配利润（14-15-16） | D32: =SUM(F32:AF32) -> 70633.522 | E32: 万元 | H32: =H29-H30-H31 -> 386.75614 | I32: =I29-I30-I31 -> 731.23171 | J32: =J29-J30-J31 -> 1041.5091 | K32: =K29-K30-K31 -> 1264.0709 | L32: =L29-L30-L31 -> 1471.777 | M32: =M29-M30-M31 -> 1733.5283 | N32: =N29-N30-N31 -> 1880.0761 | O32: =O29-O30-O31 -> 2004.4698 | ... AF32: =AF29-AF30-AF31 -> 7346.1172
B33: 18 | C33: 息税前利润（利润总额+利息支出） | D33: =SUM(F33:AF33) -> 32960.87 | E33: 万元 | H33: =H14+'表1-资金筹措及还本付息表'!H83 -> 1262.678 | I33: =I14+'表1-资金筹措及还本付息表'!I83 -> 1261.0746 | J33: =J14+'表1-资金筹措及还本付息表'!J83 -> 1258.0873 | K33: =K14+'表1-资金筹措及还本付息表'!K83 -> 1253.6639 | L33: =L14+'表1-资金筹措及还本付息表'!L83 -> 1247.7501 | M33: =M14+'表1-资金筹措及还本付息表'!M83 -> 1333.4623 | N33: =N14+'表1-资金筹措及还本付息表'!N83 -> 1305.1149 | O33: =O14+'表1-资金筹措及还本付息表'!O83 -> 1264.8695 | ... AF33: =AF14+'表1-资金筹措及还本付息表'!AF83 -> 2003.287
B34: 19 | C34: 息税折旧摊销前利润 | D34: =SUM(F34:AF34) -> 56650.841 | E34: 万元 | H34: =H33+'表2-折旧摊销表'!H39 -> 2426.9995 | I34: =I33+'表2-折旧摊销表'!I39 -> 2425.3961 | J34: =J33+'表2-折旧摊销表'!J39 -> 2422.4089 | K34: =K33+'表2-折旧摊销表'!K39 -> 2417.9854 | L34: =L33+'表2-折旧摊销表'!L39 -> 2412.0717 | M34: =M33+'表2-折旧摊销表'!M39 -> 2497.7838 | N34: =N33+'表2-折旧摊销表'!N39 -> 2469.4364 | O34: =O33+'表2-折旧摊销表'!O39 -> 2429.1911 | ... AF34: =AF33+'表2-折旧摊销表'!AF39 -> 2003.287
C36: 利润表里的收入、成本均为不含税价
C37: 政府一次性运营补贴收入—递延收益，引用自参数输入表“政府一次性补贴收入—递延收益确认”
C38: 弥补以前年度亏损，按照5年为期限，滚动计算。
C40: 标黄部分为相对固定模块，适用于所有项目
C41: 标蓝部分为计算中间过程，可不展示

Sheet 表6-现金流量表-资本金
B2: 现金流量表-资本金
B3: 序号 | C3: 项目 | D3: 合计 | E3: 单位 | F3: 建设期 | H3: 运营期
F4: 1 | G4: 2 | H4: 1 | I4: 2 | J4: 3 | K4: 4 | L4: 5 | M4: 6 | N4: 7 | O4: 8 | P4: 9 | Q4: 10 | R4: 11 | S4: 12 | T4: 13 | U4: 14 | V4: 15 | W4: 16 | X4: 17 | Y4: 18 | Z4: 19 | AA4: 20 | AB4: 21 | AC4: 22 | AD4: 23 | AE4: 24 | AF4: 25
B5: 1 | C5: 现金流入 | D5: =SUM(F5:AF5) -> 106473.6 | E5: 万元 | F5: =SUM(F6:F12) -> 21666.481 | G5: =SUM(G6:G12) -> 0 | H5: =SUM(H6:H12) -> 3384.2794 | I5: =SUM(I6:I12) -> 3369.0501 | J5: =SUM(J6:J12) -> 3353.8894 | K5: =SUM(K6:K12) -> 3338.7969 | L5: =SUM(L6:L12) -> 3323.7723 | M5: =SUM(M6:M12) -> 3472.0213 | ... AF5: =SUM(AF6:AF12) -> 4673.7257
B6: 1.1 | C6: 债务资金 | D6: =SUM(F6:AF6) -> 21666.481 | E6: 万元 | F6: ='表1-资金筹措及还本付息表'!F80 -> 21666.481 | G6: ='表1-资金筹措及还本付息表'!G80 -> 0 | H6: 0 | I6: 0 | J6: 0 | K6: 0 | L6: 0 | M6: 0 | N6: 0 | O6: 0 | P6: 0 | Q6: 0 | R6: 0 | S6: 0 | T6: 0 | U6: 0 | V6: 0 | W6: 0 | X6: 0 | Y6: 0 | Z6: 0 | AA6: 0 | AB6: 0 | AC6: 0 | AD6: 0 | AE6: 0 | AF6: 0
B7: 1.2 | C7: 发电销售收入（含税） | D7: =SUM(F7:AF7) -> 83320.277 | E7: 万元 | H7: =('表4-收入税金表'!H6+'表4-收入税金表'!H24) -> 3384.2794 | I7: =('表4-收入税金表'!I6+'表4-收入税金表'!I24) -> 3369.0501 | J7: =('表4-收入税金表'!J6+'表4-收入税金表'!J24) -> 3353.8894 | K7: =('表4-收入税金表'!K6+'表4-收入税金表'!K24) -> 3338.7969 | L7: =('表4-收入税金表'!L6+'表4-收入税金表'!L24) -> 3323.7723 | M7: =('表4-收入税金表'!M6+'表4-收入税金表'!M24) -> 3472.0213 | N7: =('表4-收入税金表'!N6+'表4-收入税金表'!N24) -> 3456.3972 | O7: =('表4-收入税金表'!O6+'表4-收入税金表'!O24) -> 3440.8435 | ... AF7: =('表4-收入税金表'!AF6+'表4-收入税金表'!AF24) -> 3186.8851
B8: 1.3 | C8: 其他收入 | D8: =SUM(F8:AF8) -> 0 | E8: 万元 | H8: =('表4-收入税金表'!H16+'表4-收入税金表'!H25) -> 0 | I8: =('表4-收入税金表'!I16+'表4-收入税金表'!I25) -> 0 | J8: =('表4-收入税金表'!J16+'表4-收入税金表'!J25) -> 0 | K8: =('表4-收入税金表'!K16+'表4-收入税金表'!K25) -> 0 | L8: =('表4-收入税金表'!L16+'表4-收入税金表'!L25) -> 0 | M8: =('表4-收入税金表'!M16+'表4-收入税金表'!M25) -> 0 | N8: =('表4-收入税金表'!N16+'表4-收入税金表'!N25) -> 0 | O8: =('表4-收入税金表'!O16+'表4-收入税金表'!O25) -> 0 | ... AF8: =('表4-收入税金表'!AF16+'表4-收入税金表'!AF25) -> 0
B9: 1.4 | C9: 政府一次性运营补贴收入 | D9: =SUM(F9:AF9) -> 0 | E9: 万元 | H9: =参数输入表!H303 -> 0
B10: 1.5 | C10: 回收固定资产余值 | D10: =SUM(F10:AF10) -> 1246.8405 | E10: 万元 | H10: 0 | I10: 0 | J10: 0 | K10: 0 | L10: 0 | M10: 0 | N10: 0 | O10: 0 | P10: 0 | Q10: 0 | R10: 0 | S10: 0 | T10: 0 | U10: 0 | V10: 0 | W10: 0 | X10: 0 | Y10: 0 | Z10: 0 | AA10: 0 | AB10: 0 | AC10: 0 | AD10: 0 | AE10: 0 | AF10: =(参数输入表!H117-参数输入表!H120)*参数输入表!H198+'表2-折旧摊销表'!R36*'表2-折旧摊销表'!D22 -> 1246.8405
B11: 1.6 | C11: 回收流动资金 | D11: =SUM(F11:AF11) -> 240 | E11: 万元 | H11: 0 | AF11: ='表1-资金筹措及还本付息表'!H6 -> 240
B12: 1.7 | C12: 增值税即征即退 | D12: =SUM(F12:AF12) -> 0 | E12: 万元 | H12: ='表4-收入税金表'!H19 -> 0 | I12: ='表4-收入税金表'!I19 -> 0 | J12: ='表4-收入税金表'!J19 -> 0 | K12: ='表4-收入税金表'!K19 -> 0 | L12: ='表4-收入税金表'!L19 -> 0 | M12: ='表4-收入税金表'!M19 -> 0 | N12: ='表4-收入税金表'!N19 -> 0 | O12: ='表4-收入税金表'!O19 -> 0 | ... AF12: ='表4-收入税金表'!AF19 -> 0
B13: 2 | C13: 现金流出 | D13: =SUM(F13:AF13) -> 80395.406 | E13: 万元 | F13: =F14+F17+F18+F22+F23+F24+F25+F26 -> 27083.101 | G13: =G14+G17+G18+G22+G23+G24+G25+G26 -> 0 | H13: =H14+H17+H18+H22+H23+H24+H25+H26 -> 2869.5713 | I13: =I14+I17+I18+I22+I23+I24+I25+I26 -> 2745.5717 | J13: =J14+J17+J18+J22+J23+J24+J25+J26 -> 2693.5722 | K13: =K14+K17+K18+K22+K23+K24+K25+K26 -> 2641.5726 | L13: =L14+L17+L18+L22+L23+L24+L25+L26 -> 2589.5731 | M13: =M14+M17+M18+M22+M23+M24+M25+M26 -> 2588.8314 | ... AF13: =AF14+AF17+AF18+AF22+AF23+AF24+AF25+AF26 -> 1356.8061
B14: 2.1 | C14: 工程建设投资 | D14: =SUM(F14:AF14) -> 27083.101 | F14: =SUM(F15:F16) -> 27083.101 | G14: =SUM(G15:G16) -> 0
C15: 项目资本金 | D15: =SUM(F15:AF15) -> 5416.6202 | E15: 万元 | F15: ='表1-资金筹措及还本付息表'!D12 -> 5416.6202 | G15: ='表1-资金筹措及还本付息表'!G11 -> 0
C16: 长期借款 | D16: =SUM(F16:AF16) -> 21666.481 | E16: 万元 | F16: ='表1-资金筹措及还本付息表'!F15 -> 21666.481 | G16: ='表1-资金筹措及还本付息表'!G15 -> 0
B17: 2.2 | C17: 支付流动资金 | H17: ='表1-资金筹措及还本付息表'!H11 -> 72
B18: 2.3 | C18: 债务性支出 | D18: =SUM(F18:AF18) -> 28204.627 | E18: 万元 | H18: =SUM(H19:H21) -> 2229.6333 | I18: =SUM(I19:I21) -> 2177.6338 | J18: =SUM(J19:J21) -> 2125.6342 | K18: =SUM(K19:K21) -> 2073.6347 | L18: =SUM(L19:L21) -> 2021.6351 | M18: =SUM(M19:M21) -> 1969.6356 | N18: =SUM(N19:N21) -> 1917.636 | O18: =SUM(O19:O21) -> 1865.6365 | ... AF18: =SUM(AF19:AF21) -> 173.208
C19: 长期借款本金偿还 | D19: =SUM(F19:AF19) -> 21834.481 | E19: 万元 | H19: ='表1-资金筹措及还本付息表'!H52 -> 1444.432 | I19: ='表1-资金筹措及还本付息表'!I52 -> 1444.432 | J19: ='表1-资金筹措及还本付息表'!J52 -> 1444.432 | K19: ='表1-资金筹措及还本付息表'!K52 -> 1444.432 | L19: ='表1-资金筹措及还本付息表'!L52 -> 1444.432 | M19: ='表1-资金筹措及还本付息表'!M52 -> 1444.432 | N19: ='表1-资金筹措及还本付息表'!N52 -> 1444.432 | O19: ='表1-资金筹措及还本付息表'!O52 -> 1444.432 | ... AE19: ='表1-资金筹措及还本付息表'!AE52 -> 0 | AF19: ='表1-资金筹措及还本付息表'!H15 -> 168
C20: 流动资金借款本金偿还 | E20: 万元 | H20: 0 | I20: ='表1-资金筹措及还本付息表'!I62 -> 0 | J20: ='表1-资金筹措及还本付息表'!J62 -> 0 | K20: ='表1-资金筹措及还本付息表'!K62 -> 0 | L20: ='表1-资金筹措及还本付息表'!L62 -> 0 | M20: ='表1-资金筹措及还本付息表'!M62 -> 0 | N20: ='表1-资金筹措及还本付息表'!N62 -> 0 | O20: ='表1-资金筹措及还本付息表'!O62 -> 0 | P20: ='表1-资金筹措及还本付息表'!P62 -> 0 | ... AE20: ='表1-资金筹措及还本付息表'!AE62 -> 0 | AF20: 0
C21: 借款利息支付（含短贷利息） | D21: =SUM(F21:AF21) -> 6370.1464 | E21: 万元 | H21: ='表1-资金筹措及还本付息表'!H93 -> 785.2013 | I21: ='表1-资金筹措及还本付息表'!I93 -> 733.20175 | J21: ='表1-资金筹措及还本付息表'!J93 -> 681.2022 | K21: ='表1-资金筹措及还本付息表'!K93 -> 629.20264 | L21: ='表1-资金筹措及还本付息表'!L93 -> 577.20309 | M21: ='表1-资金筹措及还本付息表'!M93 -> 525.20354 | N21: ='表1-资金筹措及还本付息表'!N93 -> 473.20398 | O21: ='表1-资金筹措及还本付息表'!O93 -> 421.20443 | ... AF21: ='表1-资金筹措及还本付息表'!AF93 -> 5.208
B22: 2.4 | C22: 生产经营支出（含税） | D22: =SUM(F22:AF22) -> 16761.342 | E22: 万元 | H22: ='表3-成本费用表'!H48+'表4-收入税金表'!H28 -> 567.93794 | I22: ='表3-成本费用表'!I48+'表4-收入税金表'!I28 -> 567.93794 | J22: ='表3-成本费用表'!J48+'表4-收入税金表'!J28 -> 567.93794 | K22: ='表3-成本费用表'!K48+'表4-收入税金表'!K28 -> 567.93794 | L22: ='表3-成本费用表'!L48+'表4-收入税金表'!L28 -> 567.93794 | M22: ='表3-成本费用表'!M48+'表4-收入税金表'!M28 -> 619.1958 | N22: ='表3-成本费用表'!N48+'表4-收入税金表'!N28 -> 619.1958 | O22: ='表3-成本费用表'!O48+'表4-收入税金表'!O28 -> 619.1958 | ... AF22: ='表3-成本费用表'!AF48+'表4-收入税金表'!AF28 -> 772.96939
B23: 2.5 | C23: 营业外支出 | D23: =SUM(F23:AF23) -> 0 | E23: 万元 | H23: ='表3-成本费用表'!H62 -> 0 | I23: ='表3-成本费用表'!I62 -> 0 | J23: ='表3-成本费用表'!J62 -> 0 | K23: ='表3-成本费用表'!K62 -> 0 | L23: ='表3-成本费用表'!L62 -> 0 | M23: ='表3-成本费用表'!M62 -> 0 | N23: ='表3-成本费用表'!N62 -> 0 | O23: ='表3-成本费用表'!O62 -> 0 | ... AF23: ='表3-成本费用表'!AF62 -> 0
B24: 2.6 | C24: 增值税缴纳 | D24: =SUM(F24:AF24) -> 6959.2285 | E24: 万元 | H24: ='表4-收入税金表'!H22 -> 0 | I24: ='表4-收入税金表'!I22 -> 0 | J24: ='表4-收入税金表'!J22 -> 0 | K24: ='表4-收入税金表'!K22 -> 0 | L24: ='表4-收入税金表'!L22 -> 0 | M24: ='表4-收入税金表'!M22 -> 0 | N24: ='表4-收入税金表'!N22 -> 155.27352 | O24: ='表4-收入税金表'!O22 -> 395.84925 | ... AF24: ='表4-收入税金表'!AF22 -> 366.6328
B25: 2.7 | C25: 营业税金及附加 | D25: =SUM(F25:AF25) -> 835.10742 | E25: 万元 | H25: ='表5-利润表-资本金'!H9 -> 0 | I25: ='表5-利润表-资本金'!I9 -> 0 | J25: ='表5-利润表-资本金'!J9 -> 0 | K25: ='表5-利润表-资本金'!K9 -> 0 | L25: ='表5-利润表-资本金'!L9 -> 0 | M25: ='表5-利润表-资本金'!M9 -> 0 | N25: ='表5-利润表-资本金'!N9 -> 18.632823 | O25: ='表5-利润表-资本金'!O9 -> 47.50191 | ... AF25: ='表5-利润表-资本金'!AF9 -> 43.995936
B26: 2.8 | C26: 运营期资本性支出 | D26: =SUM(F26:AF26) -> 480 | E26: 万元 | H26: =参数输入表!H236 -> 0 | I26: =参数输入表!H237 -> 0 | J26: =参数输入表!H238 -> 0 | K26: =参数输入表!H239 -> 0 | L26: =参数输入表!H240 -> 0 | M26: =参数输入表!H241 -> 0 | N26: =参数输入表!H242 -> 0 | O26: =参数输入表!H243 -> 0 | P26: =参数输入表!H244 -> 0 | Q26: =参数输入表!H245 -> 0 | R26: =参数输入表!H246 -> 480 | S26: =参数输入表!H247 -> 0 | T26: =参数输入表!H248 -> 0 | U26: =参数输入表!H249 -> 0 | V26: =参数输入表!H250 -> 0 | W26: =参数输入表!H251 -> 0 | X26: =参数输入表!H252 -> 0 | Y26: =参数输入表!H253 -> 0 | Z26: =参数输入表!H254 -> 0 | AA26: =参数输入表!H255 -> 0 | AB26: =参数输入表!H256 -> 0 | AC26: =参数输入表!H257 -> 0 | AD26: =参数输入表!H258 -> 0 | AE26: =参数输入表!H259 -> 0 | AF26: =参数输入表!H260 -> 0
B27: 3 | C27: 税前净现金流量（1-2） | D27: =SUM(F27:AF27) -> 26078.193 | E27: 万元 | F27: =F5-F13 -> -5416.6202 | G27: =G5-G13 -> 0 | H27: =H5-H13 -> 514.70807 | I27: =I5-I13 -> 623.47837 | J27: =J5-J13 -> 660.31719 | K27: =K5-K13 -> 697.22424 | L27: =L5-L13 -> 734.19921 | M27: =M5-M13 -> 883.18995 | ... AF27: =AF5-AF13 -> 3316.9195
B28: 4 | C28: 累计税前净现金流量 | E28: 万元 | F28: =F27 -> -5416.6202 | G28: =F28+G27 -> -5416.6202 | H28: =G28+H27 -> -4901.9121 | I28: =H28+I27 -> -4278.4337 | J28: =I28+J27 -> -3618.1165 | K28: =J28+K27 -> -2920.8923 | L28: =K28+L27 -> -2186.6931 | M28: =L28+M27 -> -1303.5031 | N28: =M28+N27 -> -557.84407 | ... AF28: =AE28+AF27 -> 26078.193
B29: 5 | C29: 企业所得税 | D29: =SUM(F29:AF29) -> 5883.9064 | E29: 万元 | H29: ='表5-利润表-资本金'!H22 -> 0 | I29: ='表5-利润表-资本金'!I22 -> 0 | J29: ='表5-利润表-资本金'!J22 -> 0 | K29: ='表5-利润表-资本金'!K22 -> 74.153174 | L29: ='表5-利润表-资本金'!L22 -> 78.991107 | M29: ='表5-利润表-资本金'!M22 -> 95.483049 | N29: ='表5-利润表-资本金'!N22 -> 195.85112 | O29: ='表5-利润表-资本金'!O22 -> 198.19264 | ... AF29: ='表5-利润表-资本金'!AF22 -> 499.51975
B30: 6 | C30: 税后净现金流量（3-5） | D30: =SUM(F30:AF30) -> 20194.286 | E30: 万元 | F30: =F27-F29 -> -5416.6202 | G30: =G27-G29 -> 0 | H30: =H27-H29 -> 514.70807 | I30: =I27-I29 -> 623.47837 | J30: =J27-J29 -> 660.31719 | K30: =K27-K29 -> 623.07107 | L30: =L27-L29 -> 655.20811 | M30: =M27-M29 -> 787.7069 | ... AF30: =AF27-AF29 -> 2817.3998
B31: 7 | C31: 累计税后净现金流量 | E31: 万元 | F31: =F30 -> -5416.6202 | G31: =F31+G30 -> -5416.6202 | H31: =G31+H30 -> -4901.9121 | I31: =H31+I30 -> -4278.4337 | J31: =I31+J30 -> -3618.1165 | K31: =J31+K30 -> -2995.0455 | L31: =K31+L30 -> -2339.8374 | M31: =L31+M30 -> -1552.1305 | N31: =M31+N30 -> -1002.3225 | ... AF31: =AE31+AF30 -> 20194.286
C33: 资本金内部收益率（税前） | D33: =IF('表1-资金筹措及还本付息表'!G5=0,IRR(E53:AE53),IRR(F27:AF27)) -> 0.14102405
C34: 资本金内部收益率（税后） | D34: =IF('表1-资金筹措及还本付息表'!G5=0,IRR(E56:AE56),IRR(F30:AF30)) -> 0.12140837
C35: 投资回收期 | E35: 年 | F35: 0 | G35: 0 | H35: 0 | I35: =IF(I31/H31<0,H4+ABS(H31/I30),0) -> 0 | J35: =IF(J31/I31<0,I4+ABS(I31/J30),0) -> 0 | K35: =IF(K31/J31<0,J4+ABS(J31/K30),0) -> 0 | L35: =IF(L31/K31<0,K4+ABS(K31/L30),0) -> 0 | M35: =IF(M31/L31<0,L4+ABS(L31/M30),0) -> 0 | N35: =IF(N31/M31<0,M4+ABS(M31/N30),0) -> 0 | O35: =IF(O31/N31<0,N4+ABS(N31/O30),0) -> 0 | P35: =IF(P31/O31<0,O4+ABS(O31/P30),0) -> 0 | ... AF35: =IF(AF31/AE31<0,AE4+ABS(AE31/AF30),0) -> 0
C37: 标黄部分为相对固定模块，适用于所有项目
C38: 现金流量表中各年的发电补贴收入数据引用参数表中输入的实发数据（含税且考虑滞后支付情形，即本年度实际支付比例＋上年度剩余支付比例）
C39: 政府一次性运营补贴收入，在运营期第1年引用参数表中政府一次性补贴总额
C40: 标蓝色部分为可隐藏内容
C41: 现金流出中借款本金偿还，关联还本付息表中长期贷款本金偿还
C44: Check | D44: =D30-'表5-利润表-资本金'!D23 -> 0
C46: 建设期为1年时，IRR计算要利用下面的公式计算
B51: 序号 | C51: 项目 | D51: 单位 | E51: 建设期 | G51: 运营期
E52: 1 | G52: 1 | H52: 2 | I52: 3 | J52: 4 | K52: 5 | L52: 6 | M52: 7 | N52: 8 | O52: 9 | P52: 10 | Q52: 11 | R52: 12 | S52: 13 | T52: 14 | U52: 15 | V52: 16 | W52: 17 | X52: 18 | Y52: 19 | Z52: 20 | AA52: 21 | AB52: 22 | AC52: 23 | AD52: 24 | AE52: 25
B53: 3 | C53: 税前净现金流量（1-2） | D53: 万元 | E53: =F27 -> -5416.6202 | G53: =H27 -> 514.70807 | H53: =I27 -> 623.47837 | I53: =J27 -> 660.31719 | J53: =K27 -> 697.22424 | K53: =L27 -> 734.19921 | L53: =M27 -> 883.18995 | M53: =N27 -> 745.65906 | N53: =O27 -> 512.66002 | ... AE53: =AF27 -> 3316.9195
B54: 4 | C54: 累计税前净现金流量 | D54: 万元 | E54: =F28 -> -5416.6202 | G54: =H28 -> -4901.9121 | H54: =I28 -> -4278.4337 | I54: =J28 -> -3618.1165 | J54: =K28 -> -2920.8923 | K54: =L28 -> -2186.6931 | L54: =M28 -> -1303.5031 | M54: =N28 -> -557.84407 | N54: =O28 -> -45.184055 | ... AE54: =AF28 -> 26078.193
B55: 5 | C55: 企业所得税 | D55: 万元 | E55: =F29 -> 0 | G55: =H29 -> 0 | H55: =I29 -> 0 | I55: =J29 -> 0 | J55: =K29 -> 74.153174 | K55: =L29 -> 78.991107 | L55: =M29 -> 95.483049 | M55: =N29 -> 195.85112 | N55: =O29 -> 198.19264 | ... AE55: =AF29 -> 499.51975
B56: 6 | C56: 税后净现金流量（3-5） | D56: 万元 | E56: =F30 -> -5416.6202 | G56: =H30 -> 514.70807 | H56: =I30 -> 623.47837 | I56: =J30 -> 660.31719 | J56: =K30 -> 623.07107 | K56: =L30 -> 655.20811 | L56: =M30 -> 787.7069 | M56: =N30 -> 549.80794 | N56: =O30 -> 314.46738 | ... AE56: =AF30 -> 2817.3998
B57: 7 | C57: 累计税后净现金流量 | D57: 万元 | E57: =F31 -> -5416.6202 | G57: =H31 -> -4901.9121 | H57: =I31 -> -4278.4337 | I57: =J31 -> -3618.1165 | J57: =K31 -> -2995.0455 | K57: =L31 -> -2339.8374 | L57: =M31 -> -1552.1305 | M57: =N31 -> -1002.3225 | N57: =O31 -> -687.85514 | ... AE57: =AF31 -> 20194.286

Sheet 表7-利润表-全投资
B2: 利润表-全投资
B3: 序号 | C3: 项目 | D3: 合计 | E3: 单位 | F3: 建设期 | H3: 运营期
F4: 1 | G4: 2 | H4: 1 | I4: 2 | J4: 3 | K4: 4 | L4: 5 | M4: 6 | N4: 7 | O4: 8 | P4: 9 | Q4: 10 | R4: 11 | S4: 12 | T4: 13 | U4: 14 | V4: 15 | W4: 16 | X4: 17 | Y4: 18 | Z4: 19 | AA4: 20 | AB4: 21 | AC4: 22 | AD4: 23 | AE4: 24 | AF4: 25
B5: 1 | C5: 营业总收入 | D5: =SUM(F5:AF5) -> 73734.758 | E5: 万元 | H5: =SUM(H6:H7) -> 2994.9375 | I5: =SUM(I6:I7) -> 2981.4603 | J5: =SUM(J6:J7) -> 2968.0437 | K5: =SUM(K6:K7) -> 2954.6875 | L5: =SUM(L6:L7) -> 2941.3914 | M5: =SUM(M6:M7) -> 3072.5853 | N5: =SUM(N6:N7) -> 3058.7586 | O5: =SUM(O6:O7) -> 3044.9942 | ... AF5: =SUM(AF6:AF7) -> 2820.2523
B6: 1.1 | C6: 营业收入 | D6: =SUM(F6:AF6) -> 73734.758 | E6: 万元 | H6: ='表4-收入税金表'!H5 -> 2994.9375 | I6: ='表4-收入税金表'!I5 -> 2981.4603 | J6: ='表4-收入税金表'!J5 -> 2968.0437 | K6: ='表4-收入税金表'!K5 -> 2954.6875 | L6: ='表4-收入税金表'!L5 -> 2941.3914 | M6: ='表4-收入税金表'!M5 -> 3072.5853 | N6: ='表4-收入税金表'!N5 -> 3058.7586 | O6: ='表4-收入税金表'!O5 -> 3044.9942 | ... AF6: ='表4-收入税金表'!AF5 -> 2820.2523
B7: 1.2 | C7: 其他收入 | D7: =SUM(F7:AF7) -> 0 | E7: 万元 | H7: ='表4-收入税金表'!H16 -> 0 | I7: ='表4-收入税金表'!I16 -> 0 | J7: ='表4-收入税金表'!J16 -> 0 | K7: ='表4-收入税金表'!K16 -> 0 | L7: ='表4-收入税金表'!L16 -> 0 | M7: ='表4-收入税金表'!M16 -> 0 | N7: ='表4-收入税金表'!N16 -> 0 | O7: ='表4-收入税金表'!O16 -> 0 | ... AF7: ='表4-收入税金表'!AF16 -> 0
B8: 2 | C8: 营业总成本（全投资） | D8: =SUM(F8:AF8) -> 40451.312 | E8: 万元 | H8: ='表3-成本费用表'!H29 -> 1732.2595 | I8: ='表3-成本费用表'!I29 -> 1732.2595 | J8: ='表3-成本费用表'!J29 -> 1732.2595 | K8: ='表3-成本费用表'!K29 -> 1732.2595 | L8: ='表3-成本费用表'!L29 -> 1732.2595 | M8: ='表3-成本费用表'!M29 -> 1783.5173 | N8: ='表3-成本费用表'!N29 -> 1783.5173 | O8: ='表3-成本费用表'!O29 -> 1783.5173 | ... AF8: ='表3-成本费用表'!AF29 -> 772.96939
B9: 3 | C9: 营业税金及附加 | D9: =SUM(F9:AF9) -> 835.10742 | E9: 万元 | H9: ='表4-收入税金表'!H46+'表4-收入税金表'!H50 -> 0 | I9: ='表4-收入税金表'!I46+'表4-收入税金表'!I50 -> 0 | J9: ='表4-收入税金表'!J46+'表4-收入税金表'!J50 -> 0 | K9: ='表4-收入税金表'!K46+'表4-收入税金表'!K50 -> 0 | L9: ='表4-收入税金表'!L46+'表4-收入税金表'!L50 -> 0 | M9: ='表4-收入税金表'!M46+'表4-收入税金表'!M50 -> 0 | N9: ='表4-收入税金表'!N46+'表4-收入税金表'!N50 -> 18.632823 | O9: ='表4-收入税金表'!O46+'表4-收入税金表'!O50 -> 47.50191 | ... AF9: ='表4-收入税金表'!AF46+'表4-收入税金表'!AF50 -> 43.995936
B10: 4 | C10: 营业外收入 | D10: =SUM(F10:AF10) -> 0 | E10: 万元 | H10: =SUM(H11:H12) -> 0 | I10: =SUM(I11:I12) -> 0 | J10: =SUM(J11:J12) -> 0 | K10: =SUM(K11:K12) -> 0 | L10: =SUM(L11:L12) -> 0 | M10: =SUM(M11:M12) -> 0 | N10: =SUM(N11:N12) -> 0 | O10: =SUM(O11:O12) -> 0 | ... AF10: =SUM(AF11:AF12) -> 0
B11: 4.1 | C11: 政府一次性运营补贴收入—递延收益 | D11: =SUM(F11:AF11) -> 0 | E11: 万元 | H11: =参数输入表!H305 -> 0 | I11: =参数输入表!H306 -> 0 | J11: =参数输入表!H307 -> 0 | K11: =参数输入表!H308 -> 0 | L11: =参数输入表!H309 -> 0 | M11: =参数输入表!H310 -> 0 | N11: =参数输入表!H311 -> 0 | O11: =参数输入表!H312 -> 0 | P11: =参数输入表!H313 -> 0 | Q11: =参数输入表!H314 -> 0 | R11: =参数输入表!H315 -> 0 | S11: =参数输入表!H316 -> 0 | T11: =参数输入表!H317 -> 0 | U11: =参数输入表!H318 -> 0 | V11: =参数输入表!H319 -> 0 | W11: =参数输入表!H320 -> 0 | X11: =参数输入表!H321 -> 0 | Y11: =参数输入表!H322 -> 0 | Z11: =参数输入表!H323 -> 0 | AA11: =参数输入表!H324 -> 0 | AB11: =参数输入表!H325 -> 0 | AC11: =参数输入表!H326 -> 0 | AD11: =参数输入表!H327 -> 0 | AE11: =参数输入表!H328 -> 0 | AF11: =参数输入表!H329 -> 0
B12: 4.2 | C12: 增值税即征即退收入 | D12: =SUM(F12:AF12) -> 0 | E12: 万元 | H12: ='表4-收入税金表'!H19 -> 0 | I12: ='表4-收入税金表'!I19 -> 0 | J12: ='表4-收入税金表'!J19 -> 0 | K12: ='表4-收入税金表'!K19 -> 0 | L12: ='表4-收入税金表'!L19 -> 0 | M12: ='表4-收入税金表'!M19 -> 0 | N12: ='表4-收入税金表'!N19 -> 0 | O12: ='表4-收入税金表'!O19 -> 0 | ... AF12: ='表4-收入税金表'!AF19 -> 0
B13: 5 | C13: 营业外支出 | D13: =SUM(F13:AF13) -> 0 | E13: 万元 | H13: ='表3-成本费用表'!H24 -> 0 | I13: ='表3-成本费用表'!I24 -> 0 | J13: ='表3-成本费用表'!J24 -> 0 | K13: ='表3-成本费用表'!K24 -> 0 | L13: ='表3-成本费用表'!L24 -> 0 | M13: ='表3-成本费用表'!M24 -> 0 | N13: ='表3-成本费用表'!N24 -> 0 | O13: ='表3-成本费用表'!O24 -> 0 | ... AF13: ='表3-成本费用表'!AF24 -> 0
B14: 6 | C14: 利润总额（1+4-2-3-5） | D14: =SUM(F14:AF14) -> 32448.339 | E14: 万元 | H14: =H5+H10-H8-H9-H13 -> 1262.678 | I14: =I5+I10-I8-I9-I13 -> 1249.2008 | J14: =J5+J10-J8-J9-J13 -> 1235.7842 | K14: =K5+K10-K8-K9-K13 -> 1222.428 | L14: =L5+L10-L8-L9-L13 -> 1209.1319 | M14: =M5+M10-M8-M9-M13 -> 1289.0679 | N14: =N5+N10-N8-N9-N13 -> 1256.6085 | O14: =O5+O10-O8-O9-O13 -> 1213.975 | ... AF14: =AF5+AF10-AF8-AF9-AF13 -> 2003.287
B15: 7 | C15: 弥补以前年度亏损 | D15: =SUM(F15:AF15) -> 0 | E15: 万元 | H15: =SUM(H16:H20) -> 0 | I15: =SUM(I16:I20) -> 0 | J15: =SUM(J16:J20) -> 0 | K15: =SUM(K16:K20) -> 0 | L15: =SUM(L16:L20) -> 0 | M15: =SUM(M16:M20) -> 0 | N15: =SUM(N16:N20) -> 0 | O15: =SUM(O16:O20) -> 0 | ... AF15: =SUM(AF16:AF20) -> 0
C16: 弥补前序第一年亏损 | E16: 万元 | I16: =IF(H14>0,0,IF(I14<0,0,MIN(I14-SUM(I17:I20),-H14))) -> 0 | J16: =IF(I14>0,0,IF(J14<0,0,MIN(J14-SUM(J17:J20),-I14))) -> 0 | K16: =IF(J14>0,0,IF(K14<0,0,MIN(K14-SUM(K17:K20),-J14))) -> 0 | L16: =IF(K14>0,0,IF(L14<0,0,MIN(L14-SUM(L17:L20),-K14))) -> 0 | M16: =IF(L14>0,0,IF(M14<0,0,MIN(M14-SUM(M17:M20),-L14))) -> 0 | N16: =IF(M14>0,0,IF(N14<0,0,MIN(N14-SUM(N17:N20),-M14))) -> 0 | O16: =IF(N14>0,0,IF(O14<0,0,MIN(O14-SUM(O17:O20),-N14))) -> 0 | P16: =IF(O14>0,0,IF(P14<0,0,MIN(P14-SUM(P17:P20),-O14))) -> 0 | ... AF16: =IF(AE14>0,0,IF(AF14<0,0,MIN(AF14-SUM(AF17:AF20),-AE14))) -> 0
C17: 弥补前序第二年亏损 | E17: 万元 | J17: =IF(H14>0,0,IF(J14<0,0,MIN(J14-SUM(J18:J20),-H14-I16))) -> 0 | K17: =IF(I14>0,0,IF(K14<0,0,MIN(K14-SUM(K18:K20),-I14-J16))) -> 0 | L17: =IF(J14>0,0,IF(L14<0,0,MIN(L14-SUM(L18:L20),-J14-K16))) -> 0 | M17: =IF(K14>0,0,IF(M14<0,0,MIN(M14-SUM(M18:M20),-K14-L16))) -> 0 | N17: =IF(L14>0,0,IF(N14<0,0,MIN(N14-SUM(N18:N20),-L14-M16))) -> 0 | O17: =IF(M14>0,0,IF(O14<0,0,MIN(O14-SUM(O18:O20),-M14-N16))) -> 0 | P17: =IF(N14>0,0,IF(P14<0,0,MIN(P14-SUM(P18:P20),-N14-O16))) -> 0 | Q17: =IF(O14>0,0,IF(Q14<0,0,MIN(Q14-SUM(Q18:Q20),-O14-P16))) -> 0 | ... AF17: =IF(AD14>0,0,IF(AF14<0,0,MIN(AF14-SUM(AF18:AF20),-AD14-AE16))) -> 0
C18: 弥补前序第三年亏损 | E18: 万元 | K18: =IF(H14>0,0,IF(K14<0,0,MIN(K14-SUM(K19:K20),-H14-I16-J17))) -> 0 | L18: =IF(I14>0,0,IF(L14<0,0,MIN(L14-SUM(L19:L20),-I14-J16-K17))) -> 0 | M18: =IF(J14>0,0,IF(M14<0,0,MIN(M14-SUM(M19:M20),-J14-K16-L17))) -> 0 | N18: =IF(K14>0,0,IF(N14<0,0,MIN(N14-SUM(N19:N20),-K14-L16-M17))) -> 0 | O18: =IF(L14>0,0,IF(O14<0,0,MIN(O14-SUM(O19:O20),-L14-M16-N17))) -> 0 | P18: =IF(M14>0,0,IF(P14<0,0,MIN(P14-SUM(P19:P20),-M14-N16-O17))) -> 0 | Q18: =IF(N14>0,0,IF(Q14<0,0,MIN(Q14-SUM(Q19:Q20),-N14-O16-P17))) -> 0 | R18: =IF(O14>0,0,IF(R14<0,0,MIN(R14-SUM(R19:R20),-O14-P16-Q17))) -> 0 | ... AF18: =IF(AC14>0,0,IF(AF14<0,0,MIN(AF14-SUM(AF19:AF20),-AC14-AD16-AE17))) -> 0
C19: 弥补前序第四年亏损 | E19: 万元 | L19: =IF(H14>0,0,IF(L14<0,0,MIN(L14-L20,-H14-I16-J17-K18))) -> 0 | M19: =IF(I14>0,0,IF(M14<0,0,MIN(M14-M20,-I14-J16-K17-L18))) -> 0 | N19: =IF(J14>0,0,IF(N14<0,0,MIN(N14-N20,-J14-K16-L17-M18))) -> 0 | O19: =IF(K14>0,0,IF(O14<0,0,MIN(O14-O20,-K14-L16-M17-N18))) -> 0 | P19: =IF(L14>0,0,IF(P14<0,0,MIN(P14-P20,-L14-M16-N17-O18))) -> 0 | Q19: =IF(M14>0,0,IF(Q14<0,0,MIN(Q14-Q20,-M14-N16-O17-P18))) -> 0 | R19: =IF(N14>0,0,IF(R14<0,0,MIN(R14-R20,-N14-O16-P17-Q18))) -> 0 | S19: =IF(O14>0,0,IF(S14<0,0,MIN(S14-S20,-O14-P16-Q17-R18))) -> 0 | ... AF19: =IF(AB14>0,0,IF(AF14<0,0,MIN(AF14-AF20,-AB14-AC16-AD17-AE18))) -> 0
C20: 弥补前序第五年亏损 | E20: 万元 | M20: =IF(H14>0,0,IF(M14<0,0,MIN(M14,-H14-I16-J17-K18-L19))) -> 0 | N20: =IF(I14>0,0,IF(N14<0,0,MIN(N14,-I14-J16-K17-L18-M19))) -> 0 | O20: =IF(J14>0,0,IF(O14<0,0,MIN(O14,-J14-K16-L17-M18-N19))) -> 0 | P20: =IF(K14>0,0,IF(P14<0,0,MIN(P14,-K14-L16-M17-N18-O19))) -> 0 | Q20: =IF(L14>0,0,IF(Q14<0,0,MIN(Q14,-L14-M16-N17-O18-P19))) -> 0 | R20: =IF(M14>0,0,IF(R14<0,0,MIN(R14,-M14-N16-O17-P18-Q19))) -> 0 | S20: =IF(N14>0,0,IF(S14<0,0,MIN(S14,-N14-O16-P17-Q18-R19))) -> 0 | T20: =IF(O14>0,0,IF(T14<0,0,MIN(T14,-O14-P16-Q17-R18-S19))) -> 0 | ... AF20: =IF(AA14>0,0,IF(AF14<0,0,MIN(AF14,-AA14-AB16-AC17-AD18-AE19))) -> 0
B21: 8 | C21: 应税所得额 | D21: =SUM(F21:AF21) -> 32448.339 | E21: 万元 | H21: =IF(H14-H15>0,H14-H15,0) -> 1262.678 | I21: =IF(I14-I15>0,I14-I15,0) -> 1249.2008 | J21: =IF(J14-J15>0,J14-J15,0) -> 1235.7842 | K21: =IF(K14-K15>0,K14-K15,0) -> 1222.428 | L21: =IF(L14-L15>0,L14-L15,0) -> 1209.1319 | M21: =IF(M14-M15>0,M14-M15,0) -> 1289.0679 | N21: =IF(N14-N15>0,N14-N15,0) -> 1256.6085 | O21: =IF(O14-O15>0,O14-O15,0) -> 1213.975 | ... AF21: =IF(AF14-AF15>0,AF14-AF15,0) -> 2003.287
B22: 9 | C22: 调整所得税 | D22: =SUM(F22:AF22) -> 6710.0905 | E22: 万元 | H22: =IF(参数输入表!$H$333="三免三减半",0,H21*参数输入表!$H$334) -> 0 | I22: =IF(参数输入表!$H$333="三免三减半",0,I21*参数输入表!$H$334) -> 0 | J22: =IF(参数输入表!$H$333="三免三减半",0,J21*参数输入表!$H$334) -> 0 | K22: =IF(参数输入表!$H$333="三免三减半",K21*参数输入表!$H$334/2,K21*参数输入表!$H$334) -> 152.8035 | L22: =IF(参数输入表!$H$333="三免三减半",L21*参数输入表!$H$334/2,L21*参数输入表!$H$334) -> 151.14149 | M22: =IF(参数输入表!$H$333="三免三减半",M21*参数输入表!$H$334/2,M21*参数输入表!$H$334) -> 161.13349 | N22: =N21*参数输入表!$H$334 -> 314.15212 | O22: =O21*参数输入表!$H$334 -> 303.49374 | P22: =P21*参数输入表!$H$334 -> 300.12156 | Q22: =Q21*参数输入表!$H$334 -> 296.76456 | R22: =R21*参数输入表!$H$334 -> 272.17634 | S22: =S21*参数输入表!$H$334 -> 267.19284 | T22: =T21*参数输入表!$H$334 -> 263.88095 | U22: =U21*参数输入表!$H$334 -> 260.58397 | ... AF22: =AF21*参数输入表!$H$334 -> 500.82175
B23: 10 | C23: 净利润（6-9） | D23: =SUM(F23:AF23) -> 25738.249 | E23: 万元 | H23: =H14-H22 -> 1262.678 | I23: =I14-I22 -> 1249.2008 | J23: =J14-J22 -> 1235.7842 | K23: =K14-K22 -> 1069.6245 | L23: =L14-L22 -> 1057.9905 | M23: =M14-M22 -> 1127.9344 | N23: =N14-N22 -> 942.45635 | O23: =O14-O22 -> 910.48123 | ... AF23: =AF14-AF22 -> 1502.4652
B24: 11 | C24: 期初未分配的利润 | D24: =SUM(F24:AF24) -> 0 | E24: 万元 | F24: 0 | G24: 0 | H24: =G32 -> 0 | I24: =H32 -> 0 | J24: =I32 -> 0 | K24: =J32 -> 0 | L24: =K32 -> 0 | M24: =L32 -> 0 | N24: =M32 -> 0 | O24: =N32 -> 0 | ... AF24: =AE32 -> 0
B25: 12 | C25: 可供分配的利润（10+11） | D25: =SUM(F25:AF25) -> 25738.249 | E25: 万元 | H25: =H23+H24 -> 1262.678 | I25: =I23+I24 -> 1249.2008 | J25: =J23+J24 -> 1235.7842 | K25: =K23+K24 -> 1069.6245 | L25: =L23+L24 -> 1057.9905 | M25: =M23+M24 -> 1127.9344 | N25: =N23+N24 -> 942.45635 | O25: =O23+O24 -> 910.48123 | ... AF25: =AF23+AF24 -> 1502.4652
B26: 13 | C26: 提取法定盈余公积金 | D26: =SUM(F26:AF26) -> 2573.8249 | E26: 万元 | H26: =IF(H25<0,0,H25*参数输入表!$H$134) -> 126.2678 | I26: =IF(H28>=参数输入表!$H$133,0,IF(I25<0,0,IF(I25*参数输入表!$H$134>=I27,I27,I25*参数输入表!$H$134))) -> 124.92008 | J26: =IF(I28>=参数输入表!$H$133,0,IF(J25<0,0,IF(J25*参数输入表!$H$134>=J27,J27,J25*参数输入表!$H$134))) -> 123.57842 | K26: =IF(J28>=参数输入表!$H$133,0,IF(K25<0,0,IF(K25*参数输入表!$H$134>=K27,K27,K25*参数输入表!$H$134))) -> 106.96245 | L26: =IF(K28>=参数输入表!$H$133,0,IF(L25<0,0,IF(L25*参数输入表!$H$134>=L27,L27,L25*参数输入表!$H$134))) -> 105.79905 | M26: =IF(L28>=参数输入表!$H$133,0,IF(M25<0,0,IF(M25*参数输入表!$H$134>=M27,M27,M25*参数输入表!$H$134))) -> 112.79344 | N26: =IF(M28>=参数输入表!$H$133,0,IF(N25<0,0,IF(N25*参数输入表!$H$134>=N27,N27,N25*参数输入表!$H$134))) -> 94.245635 | O26: =IF(N28>=参数输入表!$H$133,0,IF(O25<0,0,IF(O25*参数输入表!$H$134>=O27,O27,O25*参数输入表!$H$134))) -> 91.048123 | P26: =IF(O28>=参数输入表!$H$133,0,IF(P25<0,0,IF(P25*参数输入表!$H$134>=P27,P27,P25*参数输入表!$H$134))) -> 90.036469 | ... AF26: =IF(AE28>=参数输入表!$H$133,0,IF(AF25<0,0,IF(AF25*参数输入表!$H$134>=AF27,AF27,AF25*参数输入表!$H$134))) -> 150.24652
C27: 期初法定盈余公积金上限缺口 | E27: 万元 | H27: =参数输入表!$H$133 -> 5000 | I27: =参数输入表!$H$133-H28 -> 4873.7322 | J27: =参数输入表!$H$133-I28 -> 4748.8121 | K27: =参数输入表!$H$133-J28 -> 4625.2337 | L27: =参数输入表!$H$133-K28 -> 4518.2712 | M27: =参数输入表!$H$133-L28 -> 4412.4722 | N27: =参数输入表!$H$133-M28 -> 4299.6788 | O27: =参数输入表!$H$133-N28 -> 4205.4331 | P27: =参数输入表!$H$133-O28 -> 4114.385 | ... AF27: =参数输入表!$H$133-AE28 -> 2576.4217
C28: 期末法定盈余公积金累计 | E28: 万元 | H28: =H26 -> 126.2678 | I28: =I26+H28 -> 251.18788 | J28: =J26+I28 -> 374.76631 | K28: =K26+J28 -> 481.72876 | L28: =L26+K28 -> 587.5278 | M28: =M26+L28 -> 700.32125 | N28: =N26+M28 -> 794.56688 | O28: =O26+N28 -> 885.61501 | P28: =P26+O28 -> 975.65148 | ... AF28: =AF26+AE28 -> 2573.8249
B29: 14 | C29: 可供投资者分配的利润（12-13） | D29: =SUM(F29:AF29) -> 23164.424 | E29: 万元 | H29: =H25-H26 -> 1136.4102 | I29: =I25-I26 -> 1124.2807 | J29: =J25-J26 -> 1112.2058 | K29: =K25-K26 -> 962.66208 | L29: =L25-L26 -> 952.19141 | M29: =M25-M26 -> 1015.141 | N29: =N25-N26 -> 848.21072 | O29: =O25-O26 -> 819.4331 | ... AF29: =AF25-AF26 -> 1352.2187
B30: 15 | C30: 提取任意盈余公积金 | D30: =SUM(F30:AF30) -> 0 | E30: 万元 | H30: =H29*参数输入表!$H$135 -> 0 | I30: =I29*参数输入表!$H$135 -> 0 | J30: =J29*参数输入表!$H$135 -> 0 | K30: =K29*参数输入表!$H$135 -> 0 | L30: =L29*参数输入表!$H$135 -> 0 | M30: =M29*参数输入表!$H$135 -> 0 | N30: =N29*参数输入表!$H$135 -> 0 | O30: =O29*参数输入表!$H$135 -> 0 | ... AF30: =AF29*参数输入表!$H$135 -> 0
B31: 16 | C31: 各投资方利润分配 | D31: =SUM(F31:AF31) -> 23164.424 | E31: 万元 | H31: =H29-H30 -> 1136.4102 | I31: =I29-I30 -> 1124.2807 | J31: =J29-J30 -> 1112.2058 | K31: =K29-K30 -> 962.66208 | L31: =L29-L30 -> 952.19141 | M31: =M29-M30 -> 1015.141 | N31: =N29-N30 -> 848.21072 | O31: =O29-O30 -> 819.4331 | ... AF31: =AF29-AF30 -> 1352.2187
B32: 17 | C32: 未分配利润（14-15-16） | D32: =SUM(F32:AF32) -> 0 | E32: 万元 | H32: =H29-H30-H31 -> 0 | I32: =I29-I30-I31 -> 0 | J32: =J29-J30-J31 -> 0 | K32: =K29-K30-K31 -> 0 | L32: =L29-L30-L31 -> 0 | M32: =M29-M30-M31 -> 0 | N32: =N29-N30-N31 -> 0 | O32: =O29-O30-O31 -> 0 | ... AF32: =AF29-AF30-AF31 -> 0
B33: 18 | C33: 息税前利润（利润总额+利息支出） | D33: =SUM(F33:AF33) -> 39331.017 | E33: 万元 | H33: =H14+'表1-资金筹措及还本付息表'!H83 -> 2047.8793 | I33: =I14+'表1-资金筹措及还本付息表'!I83 -> 1994.2764 | J33: =J14+'表1-资金筹措及还本付息表'!J83 -> 1939.2895 | K33: =K14+'表1-资金筹措及还本付息表'!K83 -> 1882.8665 | L33: =L14+'表1-资金筹措及还本付息表'!L83 -> 1824.9532 | M33: =M14+'表1-资金筹措及还本付息表'!M83 -> 1858.6658 | N33: =N14+'表1-资金筹措及还本付息表'!N83 -> 1778.3189 | O33: =O14+'表1-资金筹措及还本付息表'!O83 -> 1686.074 | ... AF33: =AF14+'表1-资金筹措及还本付息表'!AF83 -> 2008.495
B34: 19 | C34: 息税折旧摊销前利润 | D34: =SUM(F34:AF34) -> 63020.987 | E34: 万元 | H34: =H33+'表2-折旧摊销表'!H39 -> 3212.2008 | I34: =I33+'表2-折旧摊销表'!I39 -> 3158.5979 | J34: =J33+'表2-折旧摊销表'!J39 -> 3103.611 | K34: =K33+'表2-折旧摊销表'!K39 -> 3047.1881 | L34: =L33+'表2-折旧摊销表'!L39 -> 2989.2748 | M34: =M33+'表2-折旧摊销表'!M39 -> 3022.9873 | N34: =N33+'表2-折旧摊销表'!N39 -> 2942.6404 | O34: =O33+'表2-折旧摊销表'!O39 -> 2850.3955 | ... AF34: =AF33+'表2-折旧摊销表'!AF39 -> 2008.495
H36: =H33*0.25 -> 511.96983 | I36: =I33*0.25 -> 498.56909 | J36: =J33*0.25 -> 484.82238 | K36: =K33*0.15 -> 282.42998 | L36: =L33*0.15 -> 273.74299 | M36: =M33*0.15 -> 278.79987 | N36: =N33*0.25 -> 444.57972 | O36: =O33*0.25 -> 421.51849 | P36: =P33*0.25 -> 405.29696 | Q36: =Q33*0.25 -> 388.62802 | R36: =R33*0.25 -> 350.24864 | S36: =S33*0.25 -> 330.9775 | T36: =T33*0.25 -> 312.86361 | U36: =U33*0.25 -> 294.23175 | ... AF36: =AF33*0.25 -> 502.12375
C38: 标黄部分为相对固定模块，适用于所有项目 | H38: =H6-'表3-成本费用表'!H29-'表4-收入税金表'!H46-'表2-折旧摊销表'!H39 -> 98.356503
C39: 标蓝部分为计算中间过程，可不展示

Sheet 表8-现金流量表-全投资
B2: 现金流量表-全投资
B3: 序号 | C3: 项目 | D3: 合计 | E3: 单位 | F3: 建设期 | H3: 运营期
F4: 1 | G4: 2 | H4: 1 | I4: 2 | J4: 3 | K4: 4 | L4: 5 | M4: 6 | N4: 7 | O4: 8 | P4: 9 | Q4: 10 | R4: 11 | S4: 12 | T4: 13 | U4: 14 | V4: 15 | W4: 16 | X4: 17 | Y4: 18 | Z4: 19 | AA4: 20 | AB4: 21 | AC4: 22 | AD4: 23 | AE4: 24 | AF4: 25
B5: 1 | C5: 现金流入 | D5: =SUM(F5:AF5) -> 84807.118 | E5: 万元 | F5: =SUM(F6:F11) -> 0 | G5: =SUM(G6:G11) -> 0 | H5: =SUM(H6:H11) -> 3384.2794 | I5: =SUM(I6:I11) -> 3369.0501 | J5: =SUM(J6:J11) -> 3353.8894 | K5: =SUM(K6:K11) -> 3338.7969 | L5: =SUM(L6:L11) -> 3323.7723 | M5: =SUM(M6:M11) -> 3472.0213 | ... AF5: =SUM(AF6:AF11) -> 4673.7257
B6: 1.1 | C6: 发电销售收入（含税） | D6: =SUM(F6:AF6) -> 83320.277 | E6: 万元 | H6: =('表4-收入税金表'!H6+'表4-收入税金表'!H24) -> 3384.2794 | I6: =('表4-收入税金表'!I6+'表4-收入税金表'!I24) -> 3369.0501 | J6: =('表4-收入税金表'!J6+'表4-收入税金表'!J24) -> 3353.8894 | K6: =('表4-收入税金表'!K6+'表4-收入税金表'!K24) -> 3338.7969 | L6: =('表4-收入税金表'!L6+'表4-收入税金表'!L24) -> 3323.7723 | M6: =('表4-收入税金表'!M6+'表4-收入税金表'!M24) -> 3472.0213 | N6: =('表4-收入税金表'!N6+'表4-收入税金表'!N24) -> 3456.3972 | O6: =('表4-收入税金表'!O6+'表4-收入税金表'!O24) -> 3440.8435 | ... AF6: =('表4-收入税金表'!AF6+'表4-收入税金表'!AF24) -> 3186.8851
B7: 1.2 | C7: 其他收入 | D7: =SUM(F7:AF7) -> 0 | E7: 万元 | H7: =('表4-收入税金表'!H16+'表4-收入税金表'!H25) -> 0 | I7: =('表4-收入税金表'!I16+'表4-收入税金表'!I25) -> 0 | J7: =('表4-收入税金表'!J16+'表4-收入税金表'!J25) -> 0 | K7: =('表4-收入税金表'!K16+'表4-收入税金表'!K25) -> 0 | L7: =('表4-收入税金表'!L16+'表4-收入税金表'!L25) -> 0 | M7: =('表4-收入税金表'!M16+'表4-收入税金表'!M25) -> 0 | N7: =('表4-收入税金表'!N16+'表4-收入税金表'!N25) -> 0 | O7: =('表4-收入税金表'!O16+'表4-收入税金表'!O25) -> 0 | ... AF7: =('表4-收入税金表'!AF16+'表4-收入税金表'!AF25) -> 0
B8: 1.3 | C8: 政府一次性运营补贴收入 | D8: =SUM(F8:AF8) -> 0 | E8: 万元 | H8: =参数输入表!H303 -> 0
B9: 1.4 | C9: 回收固定资产余值 | D9: =SUM(F9:AF9) -> 1246.8405 | E9: 万元 | H9: 0 | I9: 0 | J9: 0 | K9: 0 | L9: 0 | M9: 0 | N9: 0 | O9: 0 | P9: 0 | Q9: 0 | R9: 0 | S9: 0 | T9: 0 | U9: 0 | V9: 0 | W9: 0 | X9: 0 | Y9: 0 | Z9: 0 | AA9: 0 | AB9: 0 | AC9: 0 | AD9: 0 | AE9: 0 | AF9: ='表6-现金流量表-资本金'!AF10 -> 1246.8405
B10: 1.5 | C10: 回收流动资金 | D10: =SUM(F10:AF10) -> 240 | E10: 万元 | H10: 0 | AF10: ='表1-资金筹措及还本付息表'!H6 -> 240
B11: 1.6 | C11: 增值税即征即退 | D11: =SUM(F11:AF11) -> 0 | E11: 万元 | H11: ='表4-收入税金表'!H19 -> 0 | I11: ='表4-收入税金表'!I19 -> 0 | J11: ='表4-收入税金表'!J19 -> 0 | K11: ='表4-收入税金表'!K19 -> 0 | L11: ='表4-收入税金表'!L19 -> 0 | M11: ='表4-收入税金表'!M19 -> 0 | N11: ='表4-收入税金表'!N19 -> 0 | O11: ='表4-收入税金表'!O19 -> 0 | ... AF11: ='表4-收入税金表'!AF19 -> 0
B12: 2 | C12: 现金流出 | D12: =SUM(F12:AF12) -> 51975.678 | E12: 万元 | F12: =SUM(F13:F19) -> 26700 | G12: =SUM(G13:G19) -> 0 | H12: =SUM(H13:H19) -> 807.93794 | I12: =SUM(I13:I19) -> 567.93794 | J12: =SUM(J13:J19) -> 567.93794 | K12: =SUM(K13:K19) -> 567.93794 | L12: =SUM(L13:L19) -> 567.93794 | M12: =SUM(M13:M19) -> 619.1958 | ... AF12: =SUM(AF13:AF19) -> 1183.5981
B13: 2.1 | C13: 建设投资 | D13: =SUM(F13:AF13) -> 26700 | E13: 万元 | F13: ='表1-资金筹措及还本付息表'!F7 -> 26700 | G13: ='表1-资金筹措及还本付息表'!G7 -> 0
B14: 2.2 | C14: 流动资金 | D14: =SUM(F14:AF14) -> 240 | E14: 万元 | H14: =参数输入表!H118 -> 240
B15: 2.3 | C15: 生产经营支出（含税） | D15: =SUM(F15:AF15) -> 16761.342 | E15: 万元 | H15: ='表3-成本费用表'!H48+'表4-收入税金表'!H28 -> 567.93794 | I15: ='表3-成本费用表'!I48+'表4-收入税金表'!I28 -> 567.93794 | J15: ='表3-成本费用表'!J48+'表4-收入税金表'!J28 -> 567.93794 | K15: ='表3-成本费用表'!K48+'表4-收入税金表'!K28 -> 567.93794 | L15: ='表3-成本费用表'!L48+'表4-收入税金表'!L28 -> 567.93794 | M15: ='表3-成本费用表'!M48+'表4-收入税金表'!M28 -> 619.1958 | N15: ='表3-成本费用表'!N48+'表4-收入税金表'!N28 -> 619.1958 | O15: ='表3-成本费用表'!O48+'表4-收入税金表'!O28 -> 619.1958 | ... AF15: ='表3-成本费用表'!AF48+'表4-收入税金表'!AF28 -> 772.96939
B16: 2.4 | C16: 营业外支出 | D16: =SUM(F16:AF16) -> 0 | E16: 万元 | H16: ='表3-成本费用表'!H62 -> 0 | I16: ='表3-成本费用表'!I62 -> 0 | J16: ='表3-成本费用表'!J62 -> 0 | K16: ='表3-成本费用表'!K62 -> 0 | L16: ='表3-成本费用表'!L62 -> 0 | M16: ='表3-成本费用表'!M62 -> 0 | N16: ='表3-成本费用表'!N62 -> 0 | O16: ='表3-成本费用表'!O62 -> 0 | ... AF16: ='表3-成本费用表'!AF62 -> 0
B17: 2.5 | C17: 增值税缴纳 | D17: =SUM(F17:AF17) -> 6959.2285 | E17: 万元 | H17: ='表4-收入税金表'!H22 -> 0 | I17: ='表4-收入税金表'!I22 -> 0 | J17: ='表4-收入税金表'!J22 -> 0 | K17: ='表4-收入税金表'!K22 -> 0 | L17: ='表4-收入税金表'!L22 -> 0 | M17: ='表4-收入税金表'!M22 -> 0 | N17: ='表4-收入税金表'!N22 -> 155.27352 | O17: ='表4-收入税金表'!O22 -> 395.84925 | ... AF17: ='表4-收入税金表'!AF22 -> 366.6328
B18: 2.6 | C18: 营业税金及附加 | D18: =SUM(F18:AF18) -> 835.10742 | E18: 万元 | H18: ='表4-收入税金表'!H46+'表4-收入税金表'!H50 -> 0 | I18: ='表4-收入税金表'!I46+'表4-收入税金表'!I50 -> 0 | J18: ='表4-收入税金表'!J46+'表4-收入税金表'!J50 -> 0 | K18: ='表4-收入税金表'!K46+'表4-收入税金表'!K50 -> 0 | L18: ='表4-收入税金表'!L46+'表4-收入税金表'!L50 -> 0 | M18: ='表4-收入税金表'!M46+'表4-收入税金表'!M50 -> 0 | N18: ='表4-收入税金表'!N46+'表4-收入税金表'!N50 -> 18.632823 | O18: ='表4-收入税金表'!O46+'表4-收入税金表'!O50 -> 47.50191 | ... AF18: ='表4-收入税金表'!AF46+'表4-收入税金表'!AF50 -> 43.995936
B19: 2.7 | C19: 运营期资本性支出 | D19: =SUM(F19:AF19) -> 480 | E19: 万元 | H19: ='表6-现金流量表-资本金'!H26 -> 0 | I19: ='表6-现金流量表-资本金'!I26 -> 0 | J19: ='表6-现金流量表-资本金'!J26 -> 0 | K19: ='表6-现金流量表-资本金'!K26 -> 0 | L19: ='表6-现金流量表-资本金'!L26 -> 0 | M19: ='表6-现金流量表-资本金'!M26 -> 0 | N19: ='表6-现金流量表-资本金'!N26 -> 0 | O19: ='表6-现金流量表-资本金'!O26 -> 0 | ... AF19: ='表6-现金流量表-资本金'!AF26 -> 0
B20: 3 | C20: 税前净现金流量（1-2） | D20: =SUM(F20:AF20) -> 32831.44 | E20: 万元 | F20: =F5-F12 -> -26700 | G20: =G5-G12 -> 0 | H20: =H5-H12 -> 2576.3414 | I20: =I5-I12 -> 2801.1122 | J20: =J5-J12 -> 2785.9514 | K20: =K5-K12 -> 2770.8589 | L20: =L5-L12 -> 2755.8343 | M20: =M5-M12 -> 2852.8255 | ... AF20: =AF5-AF12 -> 3490.1275
B21: 4 | C21: 累计税前净现金流量 | E21: 万元 | F21: =F20 -> -26700 | G21: =F21+G20 -> -26700 | H21: =G21+H20 -> -24123.659 | I21: =H21+I20 -> -21322.546 | J21: =I21+J20 -> -18536.595 | K21: =J21+K20 -> -15765.736 | L21: =K21+L20 -> -13009.902 | M21: =L21+M20 -> -10157.076 | N21: =M21+N20 -> -7493.7811 | ... AF21: =AE21+AF20 -> 32831.44
B22: 5 | C22: 调整所得税 | D22: =SUM(F22:AF22) -> 6710.0905 | E22: 万元 | H22: ='表7-利润表-全投资'!H22 -> 0 | I22: ='表7-利润表-全投资'!I22 -> 0 | J22: ='表7-利润表-全投资'!J22 -> 0 | K22: ='表7-利润表-全投资'!K22 -> 152.8035 | L22: ='表7-利润表-全投资'!L22 -> 151.14149 | M22: ='表7-利润表-全投资'!M22 -> 161.13349 | N22: ='表7-利润表-全投资'!N22 -> 314.15212 | O22: ='表7-利润表-全投资'!O22 -> 303.49374 | ... AF22: ='表7-利润表-全投资'!AF22 -> 500.82175
B23: 6 | C23: 税后净现金流量（3-5） | D23: =SUM(F23:AF23) -> 26121.349 | E23: 万元 | F23: =F20-F22 -> -26700 | G23: =G20-G22 -> 0 | H23: =H20-H22 -> 2576.3414 | I23: =I20-I22 -> 2801.1122 | J23: =J20-J22 -> 2785.9514 | K23: =K20-K22 -> 2618.0554 | L23: =L20-L22 -> 2604.6929 | M23: =M20-M22 -> 2691.692 | ... AF23: =AF20-AF22 -> 2989.3058
B24: 7 | C24: 累计税后净现金流量 | E24: 万元 | F24: =F23 -> -26700 | G24: =F24+G23 -> -26700 | H24: =G24+H23 -> -24123.659 | I24: =H24+I23 -> -21322.546 | J24: =I24+J23 -> -18536.595 | K24: =J24+K23 -> -15918.54 | L24: =K24+L23 -> -13313.847 | M24: =L24+M23 -> -10622.155 | N24: =M24+N23 -> -8273.0117 | ... AF24: =AE24+AF23 -> 26121.349
C26: 全投资内部收益率（税前） | D26: =IF('表1-资金筹措及还本付息表'!G5=0,IRR(E41:AE41),IRR(F20:AF20)) -> 0.07897936
C27: 全投资内部收益率（税后） | D27: =IF('表1-资金筹措及还本付息表'!G5=0,IRR(E44:AE44),IRR(F23:AF23)) -> 0.068172546
C28: 投资回收期(税后) | D28: =SUM(F28:AF28)+1 -> 12.240489 | E28: 年 | F28: 0 | G28: 0 | H28: 0 | I28: =IF(H24/I24<0,H4+ABS(H24/I23),0) -> 0 | J28: =IF(I24/J24<0,I4+ABS(I24/J23),0) -> 0 | K28: =IF(J24/K24<0,J4+ABS(J24/K23),0) -> 0 | L28: =IF(K24/L24<0,K4+ABS(K24/L23),0) -> 0 | M28: =IF(L24/M24<0,L4+ABS(L24/M23),0) -> 0 | N28: =IF(M24/N24<0,M4+ABS(M24/N23),0) -> 0 | O28: =IF(N24/O24<0,N4+ABS(N24/O23),0) -> 0 | P28: =IF(O24/P24<0,O4+ABS(O24/P23),0) -> 0 | ... AF28: =IF(AE24/AF24<0,AE4+ABS(AE24/AF23),0) -> 0
C29: 投资回收期(税前） | D29: =SUM(F29:AF29)+1 -> 11.213688 | E29: 年 | H29: 0 | I29: =IF(H21/I21<0,H4+ABS(H21/I20),0) -> 0 | J29: =IF(I21/J21<0,I4+ABS(I21/J20),0) -> 0 | K29: =IF(J21/K21<0,J4+ABS(J21/K20),0) -> 0 | L29: =IF(K21/L21<0,K4+ABS(K21/L20),0) -> 0 | M29: =IF(L21/M21<0,L4+ABS(L21/M20),0) -> 0 | N29: =IF(M21/N21<0,M4+ABS(M21/N20),0) -> 0 | O29: =IF(N21/O21<0,N4+ABS(N21/O20),0) -> 0 | P29: =IF(O21/P21<0,O4+ABS(O21/P20),0) -> 0 | ... AF29: =IF(AE21/AF21<0,AE4+ABS(AE21/AF20),0) -> 0
C30: 标黄部分为相对固定模块，适用于所有项目
C31: 现金流量表中各年的发电补贴收入数据引用参数表中输入的实发数据
C32: 政府一次性运营补贴收入，在运营期第1年引用参数表中政府一次性补贴总额
C35: Check | D35: =D23-'表7-利润表-全投资'!D23 -> 383.10084
B39: 序号 | C39: 项目 | D39: 单位 | E39: 建设期 | G39: 运营期
E40: 1 | G40: 1 | H40: 2 | I40: 3 | J40: 4 | K40: 5 | L40: 6 | M40: 7 | N40: 8 | O40: 9 | P40: 10 | Q40: 11 | R40: 12 | S40: 13 | T40: 14 | U40: 15 | V40: 16 | W40: 17 | X40: 18 | Y40: 19 | Z40: 20 | AA40: 21 | AB40: 22 | AC40: 23 | AD40: 24 | AE40: 25
B41: 3 | C41: 税前净现金流量（1-2） | D41: 万元 | E41: =F20 -> -26700 | G41: =H20 -> 2576.3414 | H41: =I20 -> 2801.1122 | I41: =J20 -> 2785.9514 | J41: =K20 -> 2770.8589 | K41: =L20 -> 2755.8343 | L41: =M20 -> 2852.8255 | M41: =N20 -> 2663.2951 | N41: =O20 -> 2378.2965 | ... AE41: =AF20 -> 3490.1275
B42: 4 | C42: 累计税前净现金流量 | D42: 万元 | E42: =F21 -> -26700 | G42: =H21 -> -24123.659 | H42: =I21 -> -21322.546 | I42: =J21 -> -18536.595 | J42: =K21 -> -15765.736 | K42: =L21 -> -13009.902 | L42: =M21 -> -10157.076 | M42: =N21 -> -7493.7811 | N42: =O21 -> -5115.4846 | ... AE42: =AF21 -> 32831.44
B43: 5 | C43: 调整所得税 | D43: 万元 | E43: =F22 -> 0 | G43: =H22 -> 0 | H43: =I22 -> 0 | I43: =J22 -> 0 | J43: =K22 -> 152.8035 | K43: =L22 -> 151.14149 | L43: =M22 -> 161.13349 | M43: =N22 -> 314.15212 | N43: =O22 -> 303.49374 | ... AE43: =AF22 -> 500.82175
B44: 6 | C44: 税后净现金流量（3-5） | D44: 万元 | E44: =F23 -> -26700 | G44: =H23 -> 2576.3414 | H44: =I23 -> 2801.1122 | I44: =J23 -> 2785.9514 | J44: =K23 -> 2618.0554 | K44: =L23 -> 2604.6929 | L44: =M23 -> 2691.692 | M44: =N23 -> 2349.143 | N44: =O23 -> 2074.8027 | ... AE44: =AF23 -> 2989.3058
B45: 7 | C45: 累计税后净现金流量 | D45: 万元 | E45: =F24 -> -26700 | G45: =H24 -> -24123.659 | H45: =I24 -> -21322.546 | I45: =J24 -> -18536.595 | J45: =K24 -> -15918.54 | K45: =L24 -> -13313.847 | L45: =M24 -> -10622.155 | M45: =N24 -> -8273.0117 | N45: =O24 -> -6198.2089 | ... AE45: =AF24 -> 26121.349

Sheet 表9-现金流量表-财务计划
B2: 现金流量表-财务计划
B3: 序号 | C3: 项目 | D3: 合计 | E3: 单位 | F3: 建设期 | H3: 运营期
F4: 1 | G4: 2 | H4: 1 | I4: 2 | J4: 3 | K4: 4 | L4: 5 | M4: 6 | N4: 7 | O4: 8 | P4: 9 | Q4: 10 | R4: 11 | S4: 12 | T4: 13 | U4: 14 | V4: 15 | W4: 16 | X4: 17 | Y4: 18 | Z4: 19 | AA4: 20 | AB4: 21 | AC4: 22 | AD4: 23 | AE4: 24 | AF4: 25
B5: 1 | C5: 经营活动净现金流量（1.1-1.2） | D5: =SUM(F5:AF5) -> 52880.693 | E5: 万元 | F5: =F6-F12 -> 0 | G5: =G6-G12 -> 0 | H5: =H6-H12 -> 2816.3414 | I5: =I6-I12 -> 2801.1122 | J5: =J6-J12 -> 2785.9514 | K5: =K6-K12 -> 2696.7058 | L5: =L6-L12 -> 2676.8432 | M5: =M6-M12 -> 2757.3425 | ... AF5: =AF6-AF12 -> 1503.7672
B6: 1.1 | C6: 现金流入 | D6: =SUM(F6:AF6) -> 83320.277 | E6: 万元 | F6: =SUM(F7:F11) -> 0 | G6: =SUM(G7:G11) -> 0 | H6: =SUM(H7:H11) -> 3384.2794 | I6: =SUM(I7:I11) -> 3369.0501 | J6: =SUM(J7:J11) -> 3353.8894 | K6: =SUM(K7:K11) -> 3338.7969 | L6: =SUM(L7:L11) -> 3323.7723 | M6: =SUM(M7:M11) -> 3472.0213 | ... AF6: =SUM(AF7:AF11) -> 3186.8851
C7: 销售收入 | D7: =SUM(F7:AF7) -> 83320.277 | E7: 万元 | H7: ='表6-现金流量表-资本金'!H7 -> 3384.2794 | I7: ='表6-现金流量表-资本金'!I7 -> 3369.0501 | J7: ='表6-现金流量表-资本金'!J7 -> 3353.8894 | K7: ='表6-现金流量表-资本金'!K7 -> 3338.7969 | L7: ='表6-现金流量表-资本金'!L7 -> 3323.7723 | M7: ='表6-现金流量表-资本金'!M7 -> 3472.0213 | N7: ='表6-现金流量表-资本金'!N7 -> 3456.3972 | O7: ='表6-现金流量表-资本金'!O7 -> 3440.8435 | ... AF7: ='表6-现金流量表-资本金'!AF7 -> 3186.8851
C8: 其他收入 | D8: =SUM(F8:AF8) -> 0 | E8: 万元 | H8: ='表6-现金流量表-资本金'!H8 -> 0 | I8: ='表6-现金流量表-资本金'!I8 -> 0 | J8: ='表6-现金流量表-资本金'!J8 -> 0 | K8: ='表6-现金流量表-资本金'!K8 -> 0 | L8: ='表6-现金流量表-资本金'!L8 -> 0 | M8: ='表6-现金流量表-资本金'!M8 -> 0 | N8: ='表6-现金流量表-资本金'!N8 -> 0 | O8: ='表6-现金流量表-资本金'!O8 -> 0 | ... AF8: ='表6-现金流量表-资本金'!AF8 -> 0
C9: 回收流动资金 | D9: =SUM(F9:AF9) -> 0 | E9: 万元 | AF9: 0 | AG9: 删除
C10: 政府一次性运营补贴收入 | D10: =SUM(F10:AF10) -> 0 | E10: 万元 | H10: =参数输入表!H303 -> 0
C11: 增值税即征即退 | D11: =SUM(F11:AF11) -> 0 | E11: 万元 | H11: ='表4-收入税金表'!H19 -> 0 | I11: ='表4-收入税金表'!I19 -> 0 | J11: ='表4-收入税金表'!J19 -> 0 | K11: ='表4-收入税金表'!K19 -> 0 | L11: ='表4-收入税金表'!L19 -> 0 | M11: ='表4-收入税金表'!M19 -> 0 | N11: ='表4-收入税金表'!N19 -> 0 | O11: ='表4-收入税金表'!O19 -> 0 | ... AF11: ='表4-收入税金表'!AF19 -> 0
B12: 1.2 | C12: 现金流出 | D12: =SUM(F12:AF12) -> 30439.584 | E12: 万元 | F12: =SUM(F13:F16) -> 0 | G12: =SUM(G13:G16) -> 0 | H12: =SUM(H13:H16) -> 567.93794 | I12: =SUM(I13:I16) -> 567.93794 | J12: =SUM(J13:J16) -> 567.93794 | K12: =SUM(K13:K16) -> 642.09112 | L12: =SUM(L13:L16) -> 646.92905 | M12: =SUM(M13:M16) -> 714.67885 | ... AF12: =SUM(AF13:AF16) -> 1683.1179
C13: 生产经营支出（含税） | D13: =SUM(F13:AF13) -> 16761.342 | E13: 万元 | H13: ='表3-成本费用表'!H48+'表4-收入税金表'!H28 -> 567.93794 | I13: ='表3-成本费用表'!I48+'表4-收入税金表'!I28 -> 567.93794 | J13: ='表3-成本费用表'!J48+'表4-收入税金表'!J28 -> 567.93794 | K13: ='表3-成本费用表'!K48+'表4-收入税金表'!K28 -> 567.93794 | L13: ='表3-成本费用表'!L48+'表4-收入税金表'!L28 -> 567.93794 | M13: ='表3-成本费用表'!M48+'表4-收入税金表'!M28 -> 619.1958 | N13: ='表3-成本费用表'!N48+'表4-收入税金表'!N28 -> 619.1958 | O13: ='表3-成本费用表'!O48+'表4-收入税金表'!O28 -> 619.1958 | ... AF13: ='表3-成本费用表'!AF48+'表4-收入税金表'!AF28 -> 772.96939
C14: 增值税实缴 | D14: =SUM(F14:AF14) -> 6959.2285 | E14: 万元 | H14: ='表4-收入税金表'!H22 -> 0 | I14: ='表4-收入税金表'!I22 -> 0 | J14: ='表4-收入税金表'!J22 -> 0 | K14: ='表4-收入税金表'!K22 -> 0 | L14: ='表4-收入税金表'!L22 -> 0 | M14: ='表4-收入税金表'!M22 -> 0 | N14: ='表4-收入税金表'!N22 -> 155.27352 | O14: ='表4-收入税金表'!O22 -> 395.84925 | ... AF14: ='表4-收入税金表'!AF22 -> 366.6328
C15: 税金及附加税 | D15: =SUM(F15:AF15) -> 835.10742 | E15: 万元 | H15: ='表4-收入税金表'!H46+'表4-收入税金表'!H50 -> 0 | I15: ='表4-收入税金表'!I46+'表4-收入税金表'!I50 -> 0 | J15: ='表4-收入税金表'!J46+'表4-收入税金表'!J50 -> 0 | K15: ='表4-收入税金表'!K46+'表4-收入税金表'!K50 -> 0 | L15: ='表4-收入税金表'!L46+'表4-收入税金表'!L50 -> 0 | M15: ='表4-收入税金表'!M46+'表4-收入税金表'!M50 -> 0 | N15: ='表4-收入税金表'!N46+'表4-收入税金表'!N50 -> 18.632823 | O15: ='表4-收入税金表'!O46+'表4-收入税金表'!O50 -> 47.50191 | ... AF15: ='表4-收入税金表'!AF46+'表4-收入税金表'!AF50 -> 43.995936
C16: 企业所得税 | D16: =SUM(F16:AF16) -> 5883.9064 | E16: 万元 | H16: ='表5-利润表-资本金'!H22 -> 0 | I16: ='表5-利润表-资本金'!I22 -> 0 | J16: ='表5-利润表-资本金'!J22 -> 0 | K16: ='表5-利润表-资本金'!K22 -> 74.153174 | L16: ='表5-利润表-资本金'!L22 -> 78.991107 | M16: ='表5-利润表-资本金'!M22 -> 95.483049 | N16: ='表5-利润表-资本金'!N22 -> 195.85112 | O16: ='表5-利润表-资本金'!O22 -> 198.19264 | ... AF16: ='表5-利润表-资本金'!AF22 -> 499.51975
B17: 2 | C17: 投资活动净现金流量（2.1-2.2） | D17: =SUM(F17:AF17) -> -27803.101 | E17: 万元 | F17: =F18-F19 -> -27083.101 | G17: =G18-G19 -> 0 | H17: =H18-H19 -> -240 | I17: =I18-I19 -> 0 | J17: =J18-J19 -> 0 | K17: =K18-K19 -> 0 | L17: =L18-L19 -> 0 | M17: =M18-M19 -> 0 | ... AF17: =AF18-AF19 -> 0
B18: 2.1 | C18: 现金流入 | D18: =SUM(F18:AF18) -> 0 | E18: 万元 | F18: 0 | G18: 0 | H18: 0 | I18: 0 | J18: 0 | K18: 0 | L18: 0 | M18: 0 | N18: 0 | O18: 0 | P18: 0 | Q18: 0 | R18: 0 | S18: 0 | T18: 0 | U18: 0 | V18: 0 | W18: 0 | X18: 0 | Y18: 0 | Z18: 0 | AA18: 0 | AB18: 0 | AC18: 0 | AD18: 0 | AE18: 0 | AF18: 0
B19: 2.2 | C19: 现金流出 | D19: =SUM(F19:AF19) -> 27803.101 | E19: 万元 | F19: =SUM(F20:F22) -> 27083.101 | G19: =SUM(G20:G22) -> 0 | H19: =SUM(H20:H22) -> 240 | I19: =SUM(I20:I22) -> 0 | J19: =SUM(J20:J22) -> 0 | K19: =SUM(K20:K22) -> 0 | L19: =SUM(L20:L22) -> 0 | M19: =SUM(M20:M22) -> 0 | ... AF19: =SUM(AF20:AF22) -> 0
C20: 建设投资 | D20: =SUM(F20:AF20) -> 27083.101 | E20: 万元 | F20: ='表1-资金筹措及还本付息表'!F6 -> 27083.101 | G20: ='表1-资金筹措及还本付息表'!G6 -> 0
C21: 流动资金 | D21: =SUM(F21:AF21) -> 240 | E21: 万元 | H21: =参数输入表!$H$118 -> 240
C22: 运营期资本性支出 | D22: =SUM(F22:AF22) -> 480 | E22: 万元 | H22: ='表6-现金流量表-资本金'!H26 -> 0 | I22: ='表6-现金流量表-资本金'!I26 -> 0 | J22: ='表6-现金流量表-资本金'!J26 -> 0 | K22: ='表6-现金流量表-资本金'!K26 -> 0 | L22: ='表6-现金流量表-资本金'!L26 -> 0 | M22: ='表6-现金流量表-资本金'!M26 -> 0 | N22: ='表6-现金流量表-资本金'!N26 -> 0 | O22: ='表6-现金流量表-资本金'!O26 -> 0 | ... AF22: ='表6-现金流量表-资本金'!AF26 -> 0
B23: 3 | C23: 筹资活动净现金流量（3.1-3.2） | D23: =SUM(F23:AF23) -> -8729.6953 | E23: 万元 | F23: =F24-F29 -> 27083.101 | G23: =G24-G29 -> 0 | H23: =H24-H29 -> -2032.6063 | I23: =I24-I29 -> -2258.8818 | J23: =J24-J29 -> -2241.3575 | K23: =K24-K29 -> -2214.087 | L23: =L24-L29 -> -2185.1659 | M23: =M24-M29 -> -2162.2498 | ... AF23: =AF24-AF29 -> -989.44324
B24: 3.1 | C24: 现金流入 | D24: =SUM(F24:AF24) -> 27323.101 | E24: 万元 | F24: =SUM(F25:F28) -> 27083.101 | G24: =SUM(G25:G28) -> 0 | H24: =SUM(H25:H28) -> 240 | I24: =SUM(I25:I28) -> 0 | J24: =SUM(J25:J28) -> 0 | K24: =SUM(K25:K28) -> 0 | L24: =SUM(L25:L28) -> 0 | M24: =SUM(M25:M28) -> 0 | ... AF24: =SUM(AF25:AF28) -> 0
C25: 项目资本金投入 | D25: =SUM(F25:AF25) -> 5488.6202 | E25: 万元 | F25: ='表1-资金筹措及还本付息表'!F11 -> 5416.6202 | G25: ='表1-资金筹措及还本付息表'!G11 -> 0 | H25: ='表1-资金筹措及还本付息表'!H11 -> 72
C26: 长期借款 | D26: =SUM(F26:AF26) -> 21666.481 | E26: 万元 | F26: ='表1-资金筹措及还本付息表'!F40 -> 21666.481 | G26: ='表1-资金筹措及还本付息表'!G40 -> 0 | H26: ='表1-资金筹措及还本付息表'!H40 -> 0 | I26: ='表1-资金筹措及还本付息表'!I40 -> 0 | J26: ='表1-资金筹措及还本付息表'!J40 -> 0 | K26: ='表1-资金筹措及还本付息表'!K40 -> 0 | L26: ='表1-资金筹措及还本付息表'!L40 -> 0 | M26: ='表1-资金筹措及还本付息表'!M40 -> 0 | ... AF26: ='表1-资金筹措及还本付息表'!AF40 -> 0
C27: 流动资金借款 | D27: =SUM(F27:AF27) -> 168 | E27: 万元 | F27: ='表1-资金筹措及还本付息表'!F60 -> 0 | G27: ='表1-资金筹措及还本付息表'!G60 -> 0 | H27: ='表1-资金筹措及还本付息表'!H60 -> 168 | I27: ='表1-资金筹措及还本付息表'!I60 -> 0 | J27: ='表1-资金筹措及还本付息表'!J60 -> 0 | K27: ='表1-资金筹措及还本付息表'!K60 -> 0 | L27: ='表1-资金筹措及还本付息表'!L60 -> 0 | M27: ='表1-资金筹措及还本付息表'!M60 -> 0 | ... AF27: ='表1-资金筹措及还本付息表'!AF60 -> 0
C28: 短期借款 | D28: =SUM(F28:AF28) -> 0 | E28: 万元 | F28: ='表1-资金筹措及还本付息表'!F70 -> 0 | G28: ='表1-资金筹措及还本付息表'!G70 -> 0 | H28: ='表1-资金筹措及还本付息表'!H70 -> 0 | I28: ='表1-资金筹措及还本付息表'!I70 -> 0 | J28: ='表1-资金筹措及还本付息表'!J70 -> 0 | K28: ='表1-资金筹措及还本付息表'!K70 -> 0 | L28: ='表1-资金筹措及还本付息表'!L70 -> 0 | M28: ='表1-资金筹措及还本付息表'!M70 -> 0 | ... AF28: ='表1-资金筹措及还本付息表'!AF70 -> 0
B29: 3.2 | C29: 现金流出 | D29: =SUM(F29:AF29) -> 36052.796 | E29: 万元 | F29: =SUM(F30:F32) -> 0 | G29: =SUM(G30:G32) -> 0 | H29: =SUM(H30:H32) -> 2272.6063 | I29: =SUM(I30:I32) -> 2258.8818 | J29: =SUM(J30:J32) -> 2241.3575 | K29: =SUM(K30:K32) -> 2214.087 | L29: =SUM(L30:L32) -> 2185.1659 | M29: =SUM(M30:M32) -> 2162.2498 | ... AF29: =SUM(AF30:AF32) -> 989.44324
C30: 偿还债务本金 | D30: =SUM(F30:AF30) -> 21834.481 | E30: 万元 | H30: ='表1-资金筹措及还本付息表'!H92 -> 1444.432 | I30: ='表1-资金筹措及还本付息表'!I92 -> 1444.432 | J30: ='表1-资金筹措及还本付息表'!J92 -> 1444.432 | K30: ='表1-资金筹措及还本付息表'!K92 -> 1444.432 | L30: ='表1-资金筹措及还本付息表'!L92 -> 1444.432 | M30: ='表1-资金筹措及还本付息表'!M92 -> 1444.432 | N30: ='表1-资金筹措及还本付息表'!N92 -> 1444.432 | O30: ='表1-资金筹措及还本付息表'!O92 -> 1444.432 | ... AF30: ='表1-资金筹措及还本付息表'!AF92 -> 168
C31: 各种利息支出 | D31: =SUM(F31:AF31) -> 6370.1464 | E31: 万元 | H31: ='表1-资金筹措及还本付息表'!H93 -> 785.2013 | I31: ='表1-资金筹措及还本付息表'!I93 -> 733.20175 | J31: ='表1-资金筹措及还本付息表'!J93 -> 681.2022 | K31: ='表1-资金筹措及还本付息表'!K93 -> 629.20264 | L31: ='表1-资金筹措及还本付息表'!L93 -> 577.20309 | M31: ='表1-资金筹措及还本付息表'!M93 -> 525.20354 | N31: ='表1-资金筹措及还本付息表'!N93 -> 473.20398 | O31: ='表1-资金筹措及还本付息表'!O93 -> 421.20443 | ... AF31: ='表1-资金筹措及还本付息表'!AF93 -> 5.208
C32: 应付利润（股利分配） | D32: =SUM(F32:AF32) -> 7848.1691 | E32: 万元 | H32: ='表5-利润表-资本金'!H31 -> 42.972905 | I32: ='表5-利润表-资本金'!I31 -> 81.247968 | J32: ='表5-利润表-资本金'!J31 -> 115.72324 | K32: ='表5-利润表-资本金'!K31 -> 140.45232 | L32: ='表5-利润表-资本金'!L31 -> 163.53078 | M32: ='表5-利润表-资本金'!M31 -> 192.61425 | N32: ='表5-利润表-资本金'!N31 -> 208.89735 | O32: ='表5-利润表-资本金'!O31 -> 222.71886 | ... AF32: ='表5-利润表-资本金'!AF31 -> 816.23524
B33: 四 | C33: 项目公司账面净现金流量（1+2+3） | D33: =SUM(F33:AF33) -> 16347.897 | E33: 万元 | F33: =F5+F17+F23 -> 0 | G33: =G5+G17+G23 -> 0 | H33: =H5+H17+H23 -> 543.73516 | I33: =I5+I17+I23 -> 542.2304 | J33: =J5+J17+J23 -> 544.59396 | K33: =K5+K17+K23 -> 482.61875 | L33: =L5+L17+L23 -> 491.67733 | M33: =M5+M17+M23 -> 595.09265 | ... AF33: =AF5+AF17+AF23 -> 514.324
B34: 五 | C34: 累计盈余资金 | E34: 万元 | F34: =F33 -> 0 | G34: =F34+G33 -> 0 | H34: =G34+H33 -> 543.73516 | I34: =H34+I33 -> 1085.9656 | J34: =I34+J33 -> 1630.5595 | K34: =J34+K33 -> 2113.1783 | L34: =K34+L33 -> 2604.8556 | M34: =L34+M33 -> 3199.9482 | N34: =M34+N33 -> 3540.8588 | ... AF34: =AE34+AF33 -> 16347.897
C37: 增加IF判定条件，当某年的累计盈余资金<“流动资金（本项目为960万元）”+次年的“生产经营现金支出合计（成本费用表标蓝表第一行）”，给出明显提示（允许用户在参数输入界面填写各年度短期借款当期借款金额及还本金额，再重新生成新的结果）
C42: 不含短期借款的累计盈余资金 | H42: =H5+H17+(H25+H27-H31-H32-H30) -> 543.73516 | I42: =I5+I17+(I25+I27-I31-I32-I30+'表3-成本费用表'!H23)+H34 -> 1085.9656 | J42: =J5+J17+(J25+J27-J31-J32-J30+'表3-成本费用表'!I23)+I34 -> 1630.5595 | K42: =K5+K17+(K25+K27-K31-K32-K30+'表3-成本费用表'!J23)+J34 -> 2113.1783 | L42: =L5+L17+(L25+L27-L31-L32-L30+'表3-成本费用表'!K23)+K34 -> 2604.8556 | M42: =M5+M17+(M25+M27-M31-M32-M30+'表3-成本费用表'!L23)+L34 -> 3199.9482 | N42: =N5+N17+(N25+N27-N31-N32-N30+'表3-成本费用表'!M23)+M34 -> 3540.8588 | O42: =O5+O17+(O25+O27-O31-O32-O30+'表3-成本费用表'!N23)+N34 -> 3632.6074 | P42: =P5+P17+(P25+P27-P31-P32-P30+'表3-成本费用表'!O23)+O34 -> 3739.4441 | ... AF42: =AF5+AF17+(AF25+AF27-AF31-AF32-AF30+'表3-成本费用表'!AE23)+AE34 -> 16347.897

Sheet 表10-资产负债表
B3: 序号 | C3: 项目 | D3: 单位 | E3: 建设期 | G3: 运营期
E4: 1 | F4: 2 | G4: 1 | H4: 2 | I4: 3 | J4: 4 | K4: 5 | L4: 6 | M4: 7 | N4: 8 | O4: 9 | P4: 10 | Q4: 11 | R4: 12 | S4: 13 | T4: 14 | U4: 15 | V4: 16 | W4: 17 | X4: 18 | Y4: 19 | Z4: 20 | AA4: 21 | AB4: 22 | AC4: 23 | AD4: 24 | AE4: 25
B5: 1 | C5: 资产合计 | D5: 万元 | E5: =E6+E31 -> 27083.101 | F5: =F6+F31 -> 0 | G5: =G6+G31 -> 24131.446 | H5: =H6+H31 -> 23509.355 | I5: =I6+I31 -> 22889.627 | J5: =J6+J31 -> 22207.924 | K5: =K6+K31 -> 21535.28 | L5: =L6+L31 -> 20966.051 | ... AE5: =AE6+AE31 -> 17834.737
B6: 1.1 | C6: 流动资产 | D6: 万元 | E6: =SUM(E7:E21)+E23+E24+SUM(E27:E30) -> 0 | F6: =SUM(F7:F21)+F23+F24+SUM(F27:F30) -> 0 | G6: =SUM(G7:G21)+G23+G24+SUM(G27:G30) -> 783.73516 | H6: =SUM(H7:H21)+H23+H24+SUM(H27:H30) -> 1325.9656 | I6: =SUM(I7:I21)+I23+I24+SUM(I27:I30) -> 1870.5595 | J6: =SUM(J7:J21)+J23+J24+SUM(J27:J30) -> 2353.1783 | K6: =SUM(K7:K21)+K23+K24+SUM(K27:K30) -> 2844.8556 | L6: =SUM(L7:L21)+L23+L24+SUM(L27:L30) -> 3439.9482 | ... AE6: =SUM(AE7:AE21)+AE23+AE24+SUM(AE27:AE30) -> 16587.897
C7: 货币资金 | D7: 万元 | E7: ='表9-现金流量表-财务计划'!F34 -> 0 | F7: ='表9-现金流量表-财务计划'!G34 -> 0 | G7: ='表9-现金流量表-财务计划'!H34+'表1-资金筹措及还本付息表'!$H$6 -> 783.73516 | H7: ='表9-现金流量表-财务计划'!I34+'表1-资金筹措及还本付息表'!$H$6 -> 1325.9656 | I7: ='表9-现金流量表-财务计划'!J34+'表1-资金筹措及还本付息表'!$H$6 -> 1870.5595 | J7: ='表9-现金流量表-财务计划'!K34+'表1-资金筹措及还本付息表'!$H$6 -> 2353.1783 | K7: ='表9-现金流量表-财务计划'!L34+'表1-资金筹措及还本付息表'!$H$6 -> 2844.8556 | L7: ='表9-现金流量表-财务计划'!M34+'表1-资金筹措及还本付息表'!$H$6 -> 3439.9482 | M7: ='表9-现金流量表-财务计划'!N34+'表1-资金筹措及还本付息表'!$H$6 -> 3780.8588 | N7: ='表9-现金流量表-财务计划'!O34+'表1-资金筹措及还本付息表'!$H$6 -> 3872.6074 | ... AE7: ='表9-现金流量表-财务计划'!AF34+'表1-资金筹措及还本付息表'!$H$6 -> 16587.897
C8: △结算备付金 | D8: 万元
C9: △拆出资金 | D9: 万元
C10: 交易性金融资产 | D10: 万元
C11: ☆以公允价值计量且其变动计入当期损益的金融资产 | D11: 万元
C12: 衍生金融资产 | D12: 万元
C13: 应收票据 | D13: 万元
C14: 应收账款 | D14: 万元 | G14: ='表4-收入税金表'!H60 -> 0 | H14: ='表4-收入税金表'!I60 -> 0 | I14: ='表4-收入税金表'!J60 -> 0 | J14: ='表4-收入税金表'!K60 -> 0 | K14: ='表4-收入税金表'!L60 -> 0 | L14: ='表4-收入税金表'!M60 -> 0 | M14: ='表4-收入税金表'!N60 -> 0 | N14: ='表4-收入税金表'!O60 -> 0 | ... AE14: ='表4-收入税金表'!AF60 -> 0
C15: 应收款项融资 | D15: 万元
C16: 预付款项 | D16: 万元
C17: △应收保费 | D17: 万元
C18: △应收分保账款 | D18: 万元
C19: △应收分保合同准备金 | D19: 万元
C20: 应收资金集中管理款 | D20: 万元
C21: 其他应收款 | D21: 万元 | E21: 0 | F21: =IF('表1-资金筹措及还本付息表'!G5=0,0,'表4-收入税金表'!G45) -> 0 | G21: =0 -> 0 | H21: =0 -> 0 | I21: =0 -> 0 | J21: =0 -> 0 | K21: =0 -> 0 | L21: =0 -> 0 | M21: =0 -> 0 | N21: =0 -> 0 | ... AE21: =0 -> 0
C22: 其中：应收股利 | D22: 万元
C23: △买入返售金融资产 | D23: 万元
C24: 存货 | D24: 万元 | E24: =SUM(E25:E26) -> 0 | F24: =SUM(F25:F26) -> 0 | G24: =SUM(G25:G26) -> 0 | H24: =SUM(H25:H26) -> 0 | I24: =SUM(I25:I26) -> 0 | J24: =SUM(J25:J26) -> 0 | K24: =SUM(K25:K26) -> 0 | L24: =SUM(L25:L26) -> 0 | ... AE24: =SUM(AE25:AE26) -> 0
C25: 其中：原材料 | D25: 万元
C26: 库存商品（产成品） | D26: 万元
C27: 合同资产 | D27: 万元
C28: 持有待售资产 | D28: 万元
C29: 一年内到期的非流动资产 | D29: 万元
C30: 其他流动资产 | D30: 万元
B31: 1.2 | C31: 非流动资产 | D31: 万元 | E31: =SUM(E32:E42)+SUM(E46:E55) -> 27083.101 | F31: =SUM(F32:F42)+SUM(F46:F55) -> 0 | G31: =SUM(G32:G42)+SUM(G46:G55) -> 23347.71 | H31: =SUM(H32:H42)+SUM(H46:H55) -> 22183.389 | I31: =SUM(I32:I42)+SUM(I46:I55) -> 21019.067 | J31: =SUM(J32:J42)+SUM(J46:J55) -> 19854.746 | K31: =SUM(K32:K42)+SUM(K46:K55) -> 18690.424 | L31: =SUM(L32:L42)+SUM(L46:L55) -> 17526.103 | ... AE31: =SUM(AE32:AE42)+SUM(AE46:AE55) -> 1246.8405
C32: △发放贷款和垫款 | D32: 万元
C33: 债权投资 | D33: 万元
C34: ☆可供出售金融资产 | D34: 万元
C35: 其他债权投资 | D35: 万元
C36: ☆持有至到期投资 | D36: 万元
C37: 长期应收款 | D37: 万元
C38: 长期股权投资 | D38: 万元
C39: 其他权益工具投资 | D39: 万元
C40: 其他非流动金融资产 | D40: 万元
C41: 投资性房地产 | D41: 万元
C42: 固定资产 | D42: 万元 | F42: =F43-F44 -> 0 | G42: =G43-G44 -> 23347.71 | H42: =H43-H44 -> 22183.389 | I42: =I43-I44 -> 21019.067 | J42: =J43-J44 -> 19854.746 | K42: =K43-K44 -> 18690.424 | L42: =L43-L44 -> 17526.103 | M42: =M43-M44 -> 16361.781 | ... AE42: =AE43-AE44 -> 1246.8405
C43: 其中：固定资产原价 | D43: 万元 | F43: =IF('表1-资金筹措及还本付息表'!G5=0,0,'表2-折旧摊销表'!D4) -> 0 | G43: =F43+'表2-折旧摊销表'!D4 -> 24512.032 | H43: =G43+'表2-折旧摊销表'!I36 -> 24512.032 | I43: =H43+'表2-折旧摊销表'!J36 -> 24512.032 | J43: =I43+'表2-折旧摊销表'!K36 -> 24512.032 | K43: =J43+'表2-折旧摊销表'!L36 -> 24512.032 | L43: =K43+'表2-折旧摊销表'!M36 -> 24512.032 | M43: =L43+'表2-折旧摊销表'!N36 -> 24512.032 | N43: =M43+'表2-折旧摊销表'!O36 -> 24512.032 | O43: =N43+'表2-折旧摊销表'!P36 -> 24512.032 | ... AE43: =AD43+'表2-折旧摊销表'!AF36 -> 24936.811
C44: 累计折旧 | D44: 万元 | G44: ='表2-折旧摊销表'!H28+'表2-折旧摊销表'!H37 -> 1164.3215 | H44: =G44+'表2-折旧摊销表'!I28+'表2-折旧摊销表'!I37 -> 2328.643 | I44: =H44+'表2-折旧摊销表'!J28+'表2-折旧摊销表'!J37 -> 3492.9646 | J44: =I44+'表2-折旧摊销表'!K28+'表2-折旧摊销表'!K37 -> 4657.2861 | K44: =J44+'表2-折旧摊销表'!L28+'表2-折旧摊销表'!L37 -> 5821.6076 | L44: =K44+'表2-折旧摊销表'!M28+'表2-折旧摊销表'!M37 -> 6985.9291 | M44: =L44+'表2-折旧摊销表'!N28+'表2-折旧摊销表'!N37 -> 8150.2506 | N44: =M44+'表2-折旧摊销表'!O28+'表2-折旧摊销表'!O37 -> 9314.5722 | O44: =N44+'表2-折旧摊销表'!P28+'表2-折旧摊销表'!P37 -> 10478.894 | ... AE44: =AD44+'表2-折旧摊销表'!AF28+'表2-折旧摊销表'!AF37 -> 23689.97
C45: 固定资产减值准备 | D45: 万元
C46: 在建工程 | D46: 万元 | E46: ='表1-资金筹措及还本付息表'!F6 -> 27083.101
C47: 生产性生物资产 | D47: 万元
C48: 油气资产 | D48: 万元
C49: 使用权资产 | D49: 万元
C50: 无形资产 | D50: 万元 | E50: ='表2-折旧摊销表'!F33 -> 0 | F50: ='表2-折旧摊销表'!G33 -> 0 | G50: ='表2-折旧摊销表'!H33 -> 0 | H50: ='表2-折旧摊销表'!I33 -> 0 | I50: ='表2-折旧摊销表'!J33 -> 0 | J50: ='表2-折旧摊销表'!K33 -> 0 | K50: ='表2-折旧摊销表'!L33 -> 0 | L50: ='表2-折旧摊销表'!M33 -> 0 | ... AE50: ='表2-折旧摊销表'!AF33 -> 0
C51: 开发支出 | D51: 万元
C52: 商誉 | D52: 万元
C53: 长期待摊费用 | D53: 万元 | G53: ='表2-折旧摊销表'!H32 -> 0 | H53: ='表2-折旧摊销表'!I32 -> 0 | I53: ='表2-折旧摊销表'!J32 -> 0 | J53: ='表2-折旧摊销表'!K32 -> 0 | K53: ='表2-折旧摊销表'!L32 -> 0 | L53: ='表2-折旧摊销表'!M32 -> 0 | M53: ='表2-折旧摊销表'!N32 -> 0 | N53: ='表2-折旧摊销表'!O32 -> 0 | ... AE53: ='表2-折旧摊销表'!AF32 -> 0
C54: 递延所得税资产 | D54: 万元
C55: 其他非流动资产 | D55: 万元
C56: 其中：特准储备物资 | D56: 万元
B57: 2 | C57: 负债合计 | D57: 万元 | E57: =E58+E86 -> 21666.481 | F57: =F58+F86 -> 0 | G57: =G58+G86 -> 18208.322 | H57: =H58+H86 -> 17151.479 | I57: =I58+I86 -> 16092.893 | J57: =J58+J86 -> 15032.57 | K57: =K58+K86 -> 13970.519 | L57: =L58+L86 -> 12925.523 | ... AE57: =AE58+AE86 -> 0
B58: 2.1 | C58: 流动负债 | D58: 万元 | E58: =SUM(E59:E73)+E77+E79+SUM(E81:E85) -> 0 | F58: =SUM(F59:F73)+F77+F79+SUM(F81:F85) -> 0 | G58: =SUM(G59:G73)+G77+G79+SUM(G81:G85) -> 168 | H58: =SUM(H59:H73)+H77+H79+SUM(H81:H85) -> 168 | I58: =SUM(I59:I73)+I77+I79+SUM(I81:I85) -> 168 | J58: =SUM(J59:J73)+J77+J79+SUM(J81:J85) -> 168 | K58: =SUM(K59:K73)+K77+K79+SUM(K81:K85) -> 168 | L58: =SUM(L59:L73)+L77+L79+SUM(L81:L85) -> 168 | ... AE58: =SUM(AE59:AE73)+AE77+AE79+SUM(AE81:AE85) -> 0
C59: 短期借款 | D59: 万元 | E59: ='表1-资金筹措及还本付息表'!F74+'表1-资金筹措及还本付息表'!F64 -> 0 | F59: ='表1-资金筹措及还本付息表'!G74+'表1-资金筹措及还本付息表'!G64 -> 0 | G59: ='表1-资金筹措及还本付息表'!H64+'表1-资金筹措及还本付息表'!H74 -> 168 | H59: ='表1-资金筹措及还本付息表'!I64+'表1-资金筹措及还本付息表'!I74 -> 168 | I59: ='表1-资金筹措及还本付息表'!J64+'表1-资金筹措及还本付息表'!J74 -> 168 | J59: ='表1-资金筹措及还本付息表'!K64+'表1-资金筹措及还本付息表'!K74 -> 168 | K59: ='表1-资金筹措及还本付息表'!L64+'表1-资金筹措及还本付息表'!L74 -> 168 | L59: ='表1-资金筹措及还本付息表'!M64+'表1-资金筹措及还本付息表'!M74 -> 168 | M59: ='表1-资金筹措及还本付息表'!N64+'表1-资金筹措及还本付息表'!N74 -> 168 | N59: ='表1-资金筹措及还本付息表'!O64+'表1-资金筹措及还本付息表'!O74 -> 168 | ... AE59: ='表1-资金筹措及还本付息表'!AF64+'表1-资金筹措及还本付息表'!AF74 -> 0
C60: △向中央银行借款 | D60: 万元
C61: △拆入资金 | D61: 万元
C62: 交易性金融负债 | D62: 万元
C63: ☆以公允价值计量且其变动计入当期损益的金融负债 | D63: 万元
C64: 衍生金融负债 | D64: 万元
C65: 应付票据 | D65: 万元
C66: 应付账款 | D66: 万元
C67: 预收款项 | D67: 万元
C68: 合同负债 | D68: 万元
C69: △卖出回购金融资产款 | D69: 万元
C70: △吸收存款及同业存放 | D70: 万元
C71: △代理买卖证券款 | D71: 万元
... C85: 其他流动负债 | D85: 万元
B86: 2.2 | C86: 非流动负债 | D86: 万元 | E86: =SUM(E87:E89)+SUM(E92:E98) -> 21666.481 | F86: =SUM(F87:F89)+SUM(F92:F98) -> 0 | G86: =SUM(G87:G89)+SUM(G92:G98) -> 18040.322 | H86: =SUM(H87:H89)+SUM(H92:H98) -> 16983.479 | I86: =SUM(I87:I89)+SUM(I92:I98) -> 15924.893 | J86: =SUM(J87:J89)+SUM(J92:J98) -> 14864.57 | K86: =SUM(K87:K89)+SUM(K92:K98) -> 13802.519 | L86: =SUM(L87:L89)+SUM(L92:L98) -> 12757.523 | ... AE86: =SUM(AE87:AE89)+SUM(AE92:AE98) -> 0
C87: △保险合同准备金 | D87: 万元
C88: 长期借款 | D88: 万元 | E88: ='表1-资金筹措及还本付息表'!F15 -> 21666.481 | F88: =IF('表1-资金筹措及还本付息表'!G5=0,0,'表1-资金筹措及还本付息表'!G44) -> 0 | G88: ='表1-资金筹措及还本付息表'!H54 -> 20222.049 | H88: ='表1-资金筹措及还本付息表'!I54 -> 18777.617 | I88: ='表1-资金筹措及还本付息表'!J54 -> 17333.185 | J88: ='表1-资金筹措及还本付息表'!K54 -> 15888.752 | K88: ='表1-资金筹措及还本付息表'!L54 -> 14444.32 | L88: ='表1-资金筹措及还本付息表'!M54 -> 12999.888 | M88: ='表1-资金筹措及还本付息表'!N54 -> 11555.456 | N88: ='表1-资金筹措及还本付息表'!O54 -> 10111.024 | ... AE88: ='表1-资金筹措及还本付息表'!AF54 -> 0
C89: 应付债券 | D89: 万元
C90: 其中：优先股 | D90: 万元
C91: 永续债 | D91: 万元
C92: 租赁负债 | D92: 万元
C93: 长期应付款 | D93: 万元
C94: 长期应付职工薪酬 | D94: 万元
C95: 预计负债 | D95: 万元
C96: 递延收益 | D96: 万元 | G96: =-'表4-收入税金表'!H45 -> -2181.727 | H96: =-'表4-收入税金表'!I45 -> -1794.1371 | I96: =-'表4-收入税金表'!J45 -> -1408.2914 | J96: =-'表4-收入税金表'!K45 -> -1024.1821 | K96: =-'表4-收入税金表'!L45 -> -641.80118 | L96: =-'表4-收入税金表'!M45 -> -242.3651 | M96: =-'表4-收入税金表'!N45 -> 0 | N96: =-'表4-收入税金表'!O45 -> 0 | ... AE96: =-'表4-收入税金表'!AF45 -> 0
C97: 递延所得税负债 | D97: 万元
C98: 其他非流动负债 | D98: 万元
C99: 其中：特准储备基金 | D99: 万元
B100: 3 | C100: 所有者权益（或股东权益） | D100: 万元 | E100: =E108+E109+E112-E113+E114+E116+E117+E123+E124+E125+E126 -> 5416.6202 | F100: =F108+F109+F112-F113+F114+F116+F117+F123+F124+F125+F126 -> 0 | G100: =G108+G109+G112-G113+G114+G116+G117+G123+G124+G125+G126 -> 5923.124 | H100: =H108+H109+H112-H113+H114+H116+H117+H123+H124+H125+H126 -> 6357.8751 | I100: =I108+I109+I112-I113+I114+I116+I117+I123+I124+I125+I126 -> 6796.7339 | J100: =J108+J109+J112-J113+J114+J116+J117+J123+J124+J125+J126 -> 7175.3538 | K100: =K108+K109+K112-K113+K114+K116+K117+K123+K124+K125+K126 -> 7564.7607 | L100: =L108+L109+L112-L113+L114+L116+L117+L123+L124+L125+L126 -> 8040.5278 | ... AE100: =AE108+AE109+AE112-AE113+AE114+AE116+AE117+AE123+AE124+AE125+AE126 -> 17834.737
C101: 实收资本（或股本） | D101: 万元 | E101: ='表1-资金筹措及还本付息表'!F11 -> 5416.6202 | F101: =IF('表1-资金筹措及还本付息表'!G5=0,0,E101+'表1-资金筹措及还本付息表'!G11) -> 0 | G101: =IF('表1-资金筹措及还本付息表'!G5=0,E101+'表1-资金筹措及还本付息表'!H11,F101+'表1-资金筹措及还本付息表'!H11) -> 5488.6202 | H101: =G101+'表1-资金筹措及还本付息表'!I11 -> 5488.6202 | I101: =H101+'表1-资金筹措及还本付息表'!J11 -> 5488.6202 | J101: =I101+'表1-资金筹措及还本付息表'!K11 -> 5488.6202 | K101: =J101+'表1-资金筹措及还本付息表'!L11 -> 5488.6202 | L101: =K101+'表1-资金筹措及还本付息表'!M11 -> 5488.6202 | M101: =L101+'表1-资金筹措及还本付息表'!N11 -> 5488.6202 | N101: =M101+'表1-资金筹措及还本付息表'!O11 -> 5488.6202 | O101: =N101+'表1-资金筹措及还本付息表'!P11 -> 5488.6202 | ... AE101: =AD101+'表1-资金筹措及还本付息表'!AF11 -> 5488.6202
C102: 国家资本 | D102: 万元
C103: 国有法人资本 | D103: 万元
C104: 集体资本 | D104: 万元
C105: 民营资本 | D105: 万元
C106: 外商资本 | D106: 万元
C107: #减：已归还投资 | D107: 万元
C108: 实收资本（或股本）净额 | D108: 万元 | E108: =E101-E107 -> 5416.6202 | F108: =F101-F107 -> 0 | G108: =G101-G107 -> 5488.6202 | H108: =H101-H107 -> 5488.6202 | I108: =I101-I107 -> 5488.6202 | J108: =J101-J107 -> 5488.6202 | K108: =K101-K107 -> 5488.6202 | L108: =L101-L107 -> 5488.6202 | ... AE108: =AE101-AE107 -> 5488.6202
C109: 其他权益工具 | D109: 万元
C110: 其中：优先股 | D110: 万元
C111: 永续债 | D111: 万元
C112: 资本公积 | D112: 万元
C113: 减：库存股 | D113: 万元
C114: 其他综合收益 | D114: 万元
C115: 其中：外币报表折算差额 | D115: 万元
...

Sheet 财务指标表
A1: 序号 | B1: 项目 | C1: 单位 | D1: 数值
A2: 1 | B2: 系统容量
A3: 1.1 | B3: 光伏系统容量 | C3: MW | D3: =参数输入表!H13 -> 80
A4: 1.2 | B4: 储能系统容量 | C4: MW/MWh | D4: 10/20
A5: 2 | B5: 年售电量
A6: 2.1 | B6: 光伏系统年上网电量 | C6: MWh | D6: ='表4-收入税金表'!D9/25*10 -> 29128.966
A7: 2.2 | B7: 数能融合年消纳电量 | C7: MWh | D7: ='表4-收入税金表'!D14/25*10 -> 59288.88
A8: 3 | B8: 年均电价
A9: 3.1 | B9: 光伏系统经营期年均电价（含增值税） | C9: 元/kWh | D9: ='表4-收入税金表'!D8/'表4-收入税金表'!D9 -> 0.2920354
A10: 3.2 | B10: 数能融合经营期机制电价（含增值税） | C10: 元/kWh | D10: ='表4-收入税金表'!D13/'表4-收入税金表'!D14 -> 0.3539823
A11: 4 | B11: 项目总投资 | C11: 万元 | D11: ='表1-资金筹措及还本付息表'!D6 -> 27323.101
A12: 5 | B12: 建设投资 | C12: 万元 | D12: ='表1-资金筹措及还本付息表'!D7 -> 26700
A13: 6 | B13: 建设期利息 | C13: 万元 | D13: ='表1-资金筹措及还本付息表'!D8 -> 383.10084
A14: 7 | B14: 流动资金 | C14: 万元 | D14: ='表1-资金筹措及还本付息表'!D9 -> 240
A15: 8 | B15: 销售收入总额（不含增值税） | C15: 万元 | D15: ='表4-收入税金表'!D5 -> 73734.758 | F15: 表三成本表C6项生产成本运营期平均值做敏感性分析、蒙特卡洛
A16: 9 | B16: 总成本费用 | C16: 万元 | D16: ='表3-成本费用表'!D5 -> 46821.458
A17: 10 | B17: 销售税金附加总额 | C17: 万元 | D17: ='表4-收入税金表'!D46 -> 835.10742
A18: 11 | B18: 利润总额 | C18: 万元 | D18: ='表5-利润表-资本金'!D14 -> 26078.193
A19: 12 | B19: 项目投资回收期（所得税前） | C19: 年 | D19: ='表8-现金流量表-全投资'!D29 -> 11.213688
A20: 13 | B20: 项目投资回收期（所得税后） | C20: 年 | D20: ='表8-现金流量表-全投资'!D28 -> 12.240489
A21: 14 | B21: 项目投资财务内部收益率（所得税前） | C21: % | D21: ='表8-现金流量表-全投资'!D26 -> 0.07897936 | E21: 反算依据指标，数值由操作者自动输入
A22: 15 | B22: 项目投资财务内部收益率（所得税后） | C22: % | D22: ='表8-现金流量表-全投资'!D27 -> 0.068172546
A23: 16 | B23: 资本金财务内部收益率 | C23: % | D23: ='表6-现金流量表-资本金'!D34 -> 0.12140837
A24: 17 | B24: 资产负债率（最大值） | C24: % | D24: ='表10-资产负债表'!C131 -> 0.8
A25: 18 | B25: 盈亏平衡点（生产能力利用率） | C25: % | D25: =D16/(D15-D17) -> 0.64227274
